Workbook

Sheet 1. General 2025
A1: General 2025 | F1: Number of Customers by Customer Class | J1: Retail Load by Customer Class
A2: Zip | B2: Class | C2: Number of Customers by Customer Class | D2: Retail Load by Customer Class | F2: Count - 1/2025 | G2: Count -2/2025 | H2: Count - 3/2025 | J2: Load - 1/2025 | K2: Load - 2/2025 | L2: Load - 3/2025
A3: 97031 | B3: Commercial | C3: =SUM(F3:H3) -> 0 | D3: =SUM(J3:L3) -> 0 | F3: 0 | G3: 0 | H3: 0 | J3: 0 | K3: 0 | L3: 0
A4: 97031 | B4: Industrial | C4: =SUM(F4:H4) -> 0 | D4: =SUM(J4:L4) -> 0 | F4: 0 | G4: 0 | H4: 0 | J4: 0 | K4: 0 | L4: 0
A5: 97031 | B5: Residential | C5: =SUM(F5:H5) -> 0 | D5: =SUM(J5:L5) -> 0 | F5: 0 | G5: 0 | H5: 0 | J5: 0 | K5: 0 | L5: 0
A6: 97301 | B6: Commercial | C6: =SUM(F6:H6) -> 0 | D6: =SUM(J6:L6) -> 0 | F6: 0 | G6: 0 | H6: 0 | J6: 0 | K6: 0 | L6: 0
A7: 97301 | B7: Industrial | C7: =SUM(F7:H7) -> 0 | D7: =SUM(J7:L7) -> 0 | F7: 0 | G7: 0 | H7: 0 | J7: 0 | K7: 0 | L7: 0
A8: 97301 | B8: Residential | C8: =SUM(F8:H8) -> 0 | D8: =SUM(J8:L8) -> 0 | F8: 0 | G8: 0 | H8: 0 | J8: 0 | K8: 0 | L8: 0
A9: 97388 | B9: Commercial | C9: =SUM(F9:H9) -> 0 | D9: =SUM(J9:L9) -> 0 | F9: 0 | G9: 0 | H9: 0 | J9: 0 | K9: 0 | L9: 0
A10: 97388 | B10: Industrial | C10: =SUM(F10:H10) -> 0 | D10: =SUM(J10:L10) -> 0 | F10: 0 | G10: 0 | H10: 0 | J10: 0 | K10: 0 | L10: 0
A11: 97388 | B11: Residential | C11: =SUM(F11:H11) -> 0 | D11: =SUM(J11:L11) -> 0 | F11: 0 | G11: 0 | H11: 0 | J11: 0 | K11: 0 | L11: 0
A12: 98026 | B12: Commercial | C12: =SUM(F12:H12) -> 0 | D12: =SUM(J12:L12) -> 0 | F12: 0 | G12: 0 | H12: 0 | J12: 0 | K12: 0 | L12: 0
A13: 98026 | B13: Industrial | C13: =SUM(F13:H13) -> 0 | D13: =SUM(J13:L13) -> 0 | F13: 0 | G13: 0 | H13: 0 | J13: 0 | K13: 0 | L13: 0
A14: 98026 | B14: Residential | C14: =SUM(F14:H14) -> 0 | D14: =SUM(J14:L14) -> 0 | F14: 0 | G14: 0 | H14: 0 | J14: 0 | K14: 0 | L14: 0
... A131: 98762 | B131: Residential | C131: =SUM(F131:H131) -> 0 | D131: =SUM(J131:L131) -> 0 | F131: 0 | G131: 0 | H131: 0 | J131: 0 | K131: 0 | L131: 0

Sheet 2. Disconnections 2025
A1: Disconnections 2025 | D1: Item a) Number of Disconnections by Customer Class per Month | H1: Item b) Avg. Duration of Disconnection by Customer Class (excludes accounts never reconnected) | U1: Item c) Number of Customers by Customer Class Receiving Disconnection Notices | Y1: Item d) Number of Customers by Customer Class Who Absent the Disconnection Moratorium Would Have Been Disconnected
H2: =+D4 -> COUNT_2501 | L2: =+E4 -> COUNT_2502 | P2: =+F4 -> COUNT_2503
H3: Reconnect | I3: Reconnect | J3: Reconnect | K3: Reconnect | L3: Reconnect | M3: Reconnect | N3: Reconnect | O3: Reconnect | P3: Reconnect | Q3: Reconnect | R3: Reconnect | S3: Reconnect
A4: Zip Code | B4: Customer Class | D4: COUNT_2501 | E4: COUNT_2502 | F4: COUNT_2503 | H4: w/in 24 hrs | I4: w/in 48 hrs | J4: w/in 7 days | K4: over 7 days | L4: w/in 24 hrs | M4: w/in 48 hrs | N4: w/in 7 days | O4: over 7 days | P4: w/in 24 hrs | Q4: w/in 48 hrs | R4: w/in 7 days | S4: over 7 days | U4: =+D4 -> COUNT_2501 | V4: =+E4 -> COUNT_2502 | W4: =+F4 -> COUNT_2503 | Y4: =+D4 -> COUNT_2501 | Z4: =+E4 -> COUNT_2502 | AA4: =+F4 -> COUNT_2503
A5: 97031 | B5: Commercial | D5: 0 | E5: 0 | F5: 0 | H5: 0 | I5: 0 | J5: 0 | K5: 0 | L5: 0 | M5: 0 | N5: 0 | O5: 0 | P5: 0 | Q5: 0 | R5: 0 | S5: 0 | U5: 0 | V5: 0 | W5: 0 | Y5: Not available - we have not attempted to predict who would have been
A6: 97031 | B6: Industrial | D6: 0 | E6: 0 | F6: 0 | H6: 0 | I6: 0 | J6: 0 | K6: 0 | L6: 0 | M6: 0 | N6: 0 | O6: 0 | P6: 0 | Q6: 0 | R6: 0 | S6: 0 | U6: 0 | V6: 0 | W6: 0 | Y6: disconnected given that customer disconnection for non-payment notices
A7: 97031 | B7: Residential | D7: 0 | E7: 0 | F7: 0 | H7: 0 | I7: 0 | J7: 0 | K7: 0 | L7: 0 | M7: 0 | N7: 0 | O7: 0 | P7: 0 | Q7: 0 | R7: 0 | S7: 0 | U7: 0 | V7: 0 | W7: 0 | Y7: have not been sent for the customer classes subject to the moratorium.
A8: 97301 | B8: Commercial | D8: 0 | E8: 0 | F8: 0 | H8: 0 | I8: 0 | J8: 0 | K8: 0 | L8: 0 | M8: 0 | N8: 0 | O8: 0 | P8: 0 | Q8: 0 | R8: 0 | S8: 0 | U8: 0 | V8: 0 | W8: 0
A9: 97301 | B9: Industrial | D9: 0 | E9: 0 | F9: 0 | H9: 0 | I9: 0 | J9: 0 | K9: 0 | L9: 0 | M9: 0 | N9: 0 | O9: 0 | P9: 0 | Q9: 0 | R9: 0 | S9: 0 | U9: 0 | V9: 0 | W9: 0
A10: 97301 | B10: Residential | D10: 0 | E10: 0 | F10: 0 | H10: 0 | I10: 0 | J10: 0 | K10: 0 | L10: 0 | M10: 0 | N10: 0 | O10: 0 | P10: 0 | Q10: 0 | R10: 0 | S10: 0 | U10: 0 | V10: 0 | W10: 0
A11: 97388 | B11: Commercial | D11: 0 | E11: 0 | F11: 0 | H11: 0 | I11: 0 | J11: 0 | K11: 0 | L11: 0 | M11: 0 | N11: 0 | O11: 0 | P11: 0 | Q11: 0 | R11: 0 | S11: 0 | U11: 0 | V11: 0 | W11: 0
A12: 97388 | B12: Industrial | D12: 0 | E12: 0 | F12: 0 | H12: 0 | I12: 0 | J12: 0 | K12: 0 | L12: 0 | M12: 0 | N12: 0 | O12: 0 | P12: 0 | Q12: 0 | R12: 0 | S12: 0 | U12: 0 | V12: 0 | W12: 0
A13: 97388 | B13: Residential | D13: 0 | E13: 0 | F13: 0 | H13: 0 | I13: 0 | J13: 0 | K13: 0 | L13: 0 | M13: 0 | N13: 0 | O13: 0 | P13: 0 | Q13: 0 | R13: 0 | S13: 0 | U13: 0 | V13: 0 | W13: 0
A14: 98026 | B14: Commercial | D14: 0 | E14: 0 | F14: 0 | H14: 0 | I14: 0 | J14: 0 | K14: 0 | L14: 0 | M14: 0 | N14: 0 | O14: 0 | P14: 0 | Q14: 0 | R14: 0 | S14: 0 | U14: 0 | V14: 0 | W14: 0
A15: 98026 | B15: Industrial | D15: 0 | E15: 0 | F15: 0 | H15: 0 | I15: 0 | J15: 0 | K15: 0 | L15: 0 | M15: 0 | N15: 0 | O15: 0 | P15: 0 | Q15: 0 | R15: 0 | S15: 0 | U15: 0 | V15: 0 | W15: 0
A16: 98026 | B16: Residential | D16: 0 | E16: 0 | F16: 0 | H16: 0 | I16: 0 | J16: 0 | K16: 0 | L16: 0 | M16: 0 | N16: 0 | O16: 0 | P16: 0 | Q16: 0 | R16: 0 | S16: 0 | U16: 0 | V16: 0 | W16: 0
A17: 98119 | B17: Commercial | D17: 0 | E17: 0 | F17: 0 | H17: 0 | I17: 0 | J17: 0 | K17: 0 | L17: 0 | M17: 0 | N17: 0 | O17: 0 | P17: 0 | Q17: 0 | R17: 0 | S17: 0 | U17: 0 | V17: 0 | W17: 0
A18: 98119 | B18: Industrial | D18: 0 | E18: 0 | F18: 0 | H18: 0 | I18: 0 | J18: 0 | K18: 0 | L18: 0 | M18: 0 | N18: 0 | O18: 0 | P18: 0 | Q18: 0 | R18: 0 | S18: 0 | U18: 0 | V18: 0 | W18: 0
A19: 98119 | B19: Residential | D19: 0 | E19: 0 | F19: 0 | H19: 0 | I19: 0 | J19: 0 | K19: 0 | L19: 0 | M19: 0 | N19: 0 | O19: 0 | P19: 0 | Q19: 0 | R19: 0 | S19: 0 | U19: 0 | V19: 0 | W19: 0
... A133: 98762 | B133: Residential | D133: 0 | E133: 0 | F133: 0 | H133: 0 | I133: 0 | J133: 0 | K133: 0 | L133: 0 | M133: 0 | N133: 0 | O133: 0 | P133: 0 | Q133: 0 | R133: 0 | S133: 0 | U133: 0 | V133: 0 | W133: 0

Sheet 3. Fees 2025
A1: Fees 2025 | D1: Item a) Number of Customers by Customer Class Assessed Late Payment Fees* | H1: Item b) Aggregate amount of Charged Late Payment Fees* | L1: Item c) Number of Customers by Customer Class Assessed Disconnection Fees | P1: Item d) Aggregate amount of Charged Disconnection Fees | T1: Item e) Number of Customers by Customer Class Assessed Reconnection Fees* | X1: Item f) Aggregate amount of Charged Reconnection Fees*
A2: Late Zip | B2: Late Class | D2: Jan | E2: Feb | F2: Mar | H2: =+D2 -> Jan | I2: =+E2 -> Feb | J2: =+F2 -> Mar | L2: =+H2 -> Jan | M2: =+I2 -> Feb | N2: =+J2 -> Mar | P2: =+L2 -> Jan | Q2: =+M2 -> Feb | R2: =+N2 -> Mar | T2: =+P2 -> Jan | U2: =+Q2 -> Feb | V2: =+R2 -> Mar | X2: =+T2 -> Jan | Y2: =+U2 -> Feb | Z2: =+V2 -> Mar
A3: 97031 | B3: Commercial | D3: 0 | E3: 0 | F3: 0 | H3: 0 | I3: 0 | J3: 0 | L3: N/A | M3: N/A | N3: N/A | P3: N/A | Q3: N/A | R3: N/A | T3: 0 | U3: 0 | V3: 0 | X3: 0 | Y3: 0 | Z3: 0
A4: 97031 | B4: Industrial | D4: 0 | E4: 0 | F4: 0 | H4: 0 | I4: 0 | J4: 0 | L4: N/A | M4: N/A | N4: N/A | P4: N/A | Q4: N/A | R4: N/A | T4: 0 | U4: 0 | V4: 0 | X4: 0 | Y4: 0 | Z4: 0
A5: 97031 | B5: Residential | D5: 0 | E5: 0 | F5: 0 | H5: 0 | I5: 0 | J5: 0 | L5: N/A | M5: N/A | N5: N/A | P5: N/A | Q5: N/A | R5: N/A | T5: 0 | U5: 0 | V5: 0 | X5: 0 | Y5: 0 | Z5: 0
A6: 97301 | B6: Commercial | D6: 0 | E6: 0 | F6: 0 | H6: 0 | I6: 0 | J6: 0 | L6: N/A | M6: N/A | N6: N/A | P6: N/A | Q6: N/A | R6: N/A | T6: 0 | U6: 0 | V6: 0 | X6: 0 | Y6: 0 | Z6: 0
A7: 97301 | B7: Industrial | D7: 0 | E7: 0 | F7: 0 | H7: 0 | I7: 0 | J7: 0 | L7: N/A | M7: N/A | N7: N/A | P7: N/A | Q7: N/A | R7: N/A | T7: 0 | U7: 0 | V7: 0 | X7: 0 | Y7: 0 | Z7: 0
A8: 97301 | B8: Residential | D8: 0 | E8: 0 | F8: 0 | H8: 0 | I8: 0 | J8: 0 | L8: N/A | M8: N/A | N8: N/A | P8: N/A | Q8: N/A | R8: N/A | T8: 0 | U8: 0 | V8: 0 | X8: 0 | Y8: 0 | Z8: 0
A9: 97388 | B9: Commercial | D9: 0 | E9: 0 | F9: 0 | H9: 0 | I9: 0 | J9: 0 | L9: N/A | M9: N/A | N9: N/A | P9: N/A | Q9: N/A | R9: N/A | T9: 0 | U9: 0 | V9: 0 | X9: 0 | Y9: 0 | Z9: 0
A10: 97388 | B10: Industrial | D10: 0 | E10: 0 | F10: 0 | H10: 0 | I10: 0 | J10: 0 | L10: N/A | M10: N/A | N10: N/A | P10: N/A | Q10: N/A | R10: N/A | T10: 0 | U10: 0 | V10: 0 | X10: 0 | Y10: 0 | Z10: 0
A11: 97388 | B11: Residential | D11: 0 | E11: 0 | F11: 0 | H11: 0 | I11: 0 | J11: 0 | L11: N/A | M11: N/A | N11: N/A | P11: N/A | Q11: N/A | R11: N/A | T11: 0 | U11: 0 | V11: 0 | X11: 0 | Y11: 0 | Z11: 0
A12: 98026 | B12: Commercial | D12: 0 | E12: 0 | F12: 0 | H12: 0 | I12: 0 | J12: 0 | L12: N/A | M12: N/A | N12: N/A | P12: N/A | Q12: N/A | R12: N/A | T12: 0 | U12: 0 | V12: 0 | X12: 0 | Y12: 0 | Z12: 0
A13: 98026 | B13: Industrial | D13: 0 | E13: 0 | F13: 0 | H13: 0 | I13: 0 | J13: 0 | L13: N/A | M13: N/A | N13: N/A | P13: N/A | Q13: N/A | R13: N/A | T13: 0 | U13: 0 | V13: 0 | X13: 0 | Y13: 0 | Z13: 0
A14: 98026 | B14: Residential | D14: 0 | E14: 0 | F14: 0 | H14: 0 | I14: 0 | J14: 0 | L14: N/A | M14: N/A | N14: N/A | P14: N/A | Q14: N/A | R14: N/A | T14: 0 | U14: 0 | V14: 0 | X14: 0 | Y14: 0 | Z14: 0
... A131: 98762 | B131: Residential | D131: 0 | E131: 0 | F131: 0 | H131: 0 | I131: 0 | J131: 0 | L131: N/A | M131: N/A | N131: N/A | P131: N/A | Q131: N/A | R131: N/A | T131: 0 | U131: 0 | V131: 0 | X131: 0 | Y131: 0 | Z131: 0
D133: =SUMIF($B3:$B131,$B$131,D3:D131) -> -1 | E133: =SUMIF($B3:$B131,$B$131,E3:E131) -> 0 | F133: =SUMIF($B3:$B131,$B$131,F3:F131) -> 0 | H133: =SUMIF($B3:$B131,$B$131,H3:H131) -> -15 | I133: =SUMIF($B3:$B131,$B$131,I3:I131) -> 0 | J133: =SUMIF($B3:$B131,$B$131,J3:J131) -> 0 | T133: =SUMIF($B3:$B131,$B$131,T3:T131) -> 113 | U133: =SUMIF($B3:$B131,$B$131,U3:U131) -> 0 | V133: =SUMIF($B3:$B131,$B$131,V3:V131) -> 0 | X133: =SUMIF($B3:$B131,$B$131,X3:X131) -> -3150 | Y133: =SUMIF($B3:$B131,$B$131,Y3:Y131) -> 0 | Z133: =SUMIF($B3:$B131,$B$131,Z3:Z131) -> 0
D134: *Please note that NW Natural will/has credit/credited back these fees charged to Residential customers in error | H134: *Please note that NW Natural will/has credit/credited back these fees charged to Residential customers in error | T134: *Please note that NW Natural will credit/has credited back these fees charged to Residential customers in error | X134: *Please note that NW Natural will credit/has credited back these fees charged to Residential customers in error

Sheet 4. Payment Arrangements 2025
A1: Pmt Arrangements 2025 | D1: Item a) Number of Customers by Customer Class Taking Service at the Beginning of Each Month with Existing Long Term Payment Agreements | H1: Item b) Number of Customers By Customer Class Completing Long-term Payment Agreements | L1: Item c) Number of Customers by Customer Class Enrolling in New Long-term Payment Agreements | P1: Item d) Number of Customers By Customer Class Renegotiating Long-term Payment Agreements
A2: Zip Code | B2: Customer Class | D2: Jan 2025 | E2: Feb 2025 | F2: Mar 2025 | H2: =+D2 -> Jan 2025 | I2: =+E2 -> Feb 2025 | J2: =+F2 -> Mar 2025 | L2: =+H2 -> Jan 2025 | M2: =+I2 -> Feb 2025 | N2: =+J2 -> Mar 2025 | P2: =+L2 -> Jan 2025 | Q2: =+M2 -> Feb 2025 | R2: =+N2 -> Mar 2025
A3: 97031 | B3: Commercial | D3: 0 | E3: 0 | F3: 0 | H3: 0 | I3: 0 | J3: 0 | L3: 0 | M3: 0 | N3: 0 | P3: 0 | Q3: 0 | R3: 0
A4: 97031 | B4: Industrial | D4: 0 | E4: 0 | F4: 0 | H4: 0 | I4: 0 | J4: 0 | L4: 0 | M4: 0 | N4: 0 | P4: 0 | Q4: 0 | R4: 0
A5: 97031 | B5: Residential | D5: 0 | E5: 0 | F5: 0 | H5: 0 | I5: 0 | J5: 0 | L5: 0 | M5: 0 | N5: 0 | P5: 0 | Q5: 0 | R5: 0
A6: 97301 | B6: Commercial | D6: 0 | E6: 0 | F6: 0 | H6: 0 | I6: 0 | J6: 0 | L6: 0 | M6: 0 | N6: 0 | P6: 0 | Q6: 0 | R6: 0
A7: 97301 | B7: Industrial | D7: 0 | E7: 0 | F7: 0 | H7: 0 | I7: 0 | J7: 0 | L7: 0 | M7: 0 | N7: 0 | P7: 0 | Q7: 0 | R7: 0
A8: 97301 | B8: Residential | D8: 0 | E8: 0 | F8: 0 | H8: 0 | I8: 0 | J8: 0 | L8: 0 | M8: 0 | N8: 0 | P8: 0 | Q8: 0 | R8: 0
A9: 97388 | B9: Commercial | D9: 0 | E9: 0 | F9: 0 | H9: 0 | I9: 0 | J9: 0 | L9: 0 | M9: 0 | N9: 0 | P9: 0 | Q9: 0 | R9: 0
A10: 97388 | B10: Industrial | D10: 0 | E10: 0 | F10: 0 | H10: 0 | I10: 0 | J10: 0 | L10: 0 | M10: 0 | N10: 0 | P10: 0 | Q10: 0 | R10: 0
A11: 97388 | B11: Residential | D11: 0 | E11: 0 | F11: 0 | H11: 0 | I11: 0 | J11: 0 | L11: 0 | M11: 0 | N11: 0 | P11: 0 | Q11: 0 | R11: 0
A12: 98026 | B12: Commercial | D12: 0 | E12: 0 | F12: 0 | H12: 0 | I12: 0 | J12: 0 | L12: 0 | M12: 0 | N12: 0 | P12: 0 | Q12: 0 | R12: 0
A13: 98026 | B13: Industrial | D13: 0 | E13: 0 | F13: 0 | H13: 0 | I13: 0 | J13: 0 | L13: 0 | M13: 0 | N13: 0 | P13: 0 | Q13: 0 | R13: 0
A14: 98026 | B14: Residential | D14: 0 | E14: 0 | F14: 0 | H14: 0 | I14: 0 | J14: 0 | L14: 0 | M14: 0 | N14: 0 | P14: 0 | Q14: 0 | R14: 0
... A131: 98762 | B131: Residential | D131: 0 | E131: 0 | F131: 0 | H131: 0 | I131: 0 | J131: 0 | L131: 0 | M131: 0 | N131: 0 | P131: 0 | Q131: 0 | R131: 0

Sheet 5. Medical Certificates 2025
A1: Med Certs 2025 | C1: Item a) Number of Customers Taking Service at the Beginning of Each Month Under Existing Medical Payment Arrangements | G1: Item b) Number of Customers Completing Medical Payment Arrangements Each Month | K1: Item c) Number of Customers Enrolling in New Medical Payment Arrangements Each Month | O1: Item d) Number of Customers Renegotiating Medical Payment Arrangements Each Month
A2: Zip Code | C2: =+'4. Payment Arrangements 2025'!D2 -> Jan 2025 | D2: =+'4. Payment Arrangements 2025'!E2 -> Feb 2025 | E2: =+'4. Payment Arrangements 2025'!F2 -> Mar 2025 | G2: =+C2 -> Jan 2025 | H2: =+D2 -> Feb 2025 | I2: =+E2 -> Mar 2025 | K2: =+G2 -> Jan 2025 | L2: =+H2 -> Feb 2025 | M2: =+I2 -> Mar 2025 | O2: =+K2 -> Jan 2025 | P2: =+L2 -> Feb 2025 | Q2: =+M2 -> Mar 2025
C4: Assmption: (the number of customers starting service at a new location,
C5: i.e. the number of orders for transfer of service from one premise address
C6: to another at any time during the reporting monthwhile on an active
C7: medical certificate, closing orders not included
C8: Response: | G8: Response: | K8: Response:
A9: all zips total | C9: =SUM(C10:C20) -> 2 | D9: =SUM(D10:D20) -> 0 | E9: =SUM(E10:E20) -> 0 | G9: =SUM(G10:G16) -> 0 | H9: =SUM(H10:H16) -> 0 | I9: =SUM(I10:I16) -> 0 | K9: =SUM(K11:K23) -> 4 | L9: =SUM(L11:L23) -> 0 | M9: =SUM(M11:M23) -> 0 | O9: =SUM(O11:O23) -> 0 | P9: =SUM(P11:P23) -> 2 | Q9: =SUM(Q11:Q23) -> 0
G10: No occurrences to report
A12: 98642 | K12: 1
A13: 98665
A14: 98671
A15: 98682 | P15: 1
A16: 98605
A17: 98684 | C17: 1 | K17: 1
A18: 98661 | K18: 2
A19: 98604
A20: 98607 | C20: 1 | P20: 1

Sheet 6. Deposits 2025
A1: Deposits 2025 | D1: Item a) Number of Customers by Customer Class with Required Deposits at the Beginning of Each Month* | H1: Item b) Number of Customers by Customer Class Required to Submit New or Increased Deposits Each Month* | L1: Item c) Number of Customers by Customer Class Whose Deposits Were Reduced In Part or Foregone Each Month | P1: Item d) Number of Customers by Customer Class whose Deposits were Returned in Full Each Month
A2: Zip Code | B2: Customer Class | D2: =+'4. Payment Arrangements 2025'!D2 -> Jan 2025 | E2: =+'4. Payment Arrangements 2025'!E2 -> Feb 2025 | F2: =+'4. Payment Arrangements 2025'!F2 -> Mar 2025 | H2: =+D2 -> Jan 2025 | I2: =+E2 -> Feb 2025 | J2: =+F2 -> Mar 2025 | L2: =+H2 -> Jan 2025 | M2: =+I2 -> Feb 2025 | N2: =+J2 -> Mar 2025 | P2: =+L2 -> Jan 2025 | Q2: =+M2 -> Feb 2025 | R2: =+N2 -> Mar 2025
A4: 97031 | B4: Commercial | D4: 0 | E4: 0 | F4: 0 | H4: 0 | I4: 0 | J4: 0 | P4: 0 | Q4: 0 | R4: 0
A5: 97031 | B5: Industrial | D5: 0 | E5: 0 | F5: 0 | H5: 0 | I5: 0 | J5: 0 | L5: This data is not available - NW Natural is unable to | P5: 0 | Q5: 0 | R5: 0
A6: 97031 | B6: Residential | D6: 0 | E6: 0 | F6: 0 | H6: 0 | I6: 0 | J6: 0 | L6: track this data. | P6: 0 | Q6: 0 | R6: 0
A7: 97301 | B7: Commercial | D7: 0 | E7: 0 | F7: 0 | H7: 0 | I7: 0 | J7: 0 | P7: 0 | Q7: 0 | R7: 0
A8: 97301 | B8: Industrial | D8: 0 | E8: 0 | F8: 0 | H8: 0 | I8: 0 | J8: 0 | P8: 0 | Q8: 0 | R8: 0
A9: 97301 | B9: Residential | D9: 0 | E9: 0 | F9: 0 | H9: 0 | I9: 0 | J9: 0 | P9: 0 | Q9: 0 | R9: 0
A10: 97388 | B10: Commercial | D10: 0 | E10: 0 | F10: 0 | H10: 0 | I10: 0 | J10: 0 | P10: 0 | Q10: 0 | R10: 0
A11: 97388 | B11: Industrial | D11: 0 | E11: 0 | F11: 0 | H11: 0 | I11: 0 | J11: 0 | P11: 0 | Q11: 0 | R11: 0
A12: 97388 | B12: Residential | D12: 0 | E12: 0 | F12: 0 | H12: 0 | I12: 0 | J12: 0 | P12: 0 | Q12: 0 | R12: 0
A13: 98026 | B13: Commercial | D13: 0 | E13: 0 | F13: 0 | H13: 0 | I13: 0 | J13: 0 | P13: 0 | Q13: 0 | R13: 0
A14: 98026 | B14: Industrial | D14: 0 | E14: 0 | F14: 0 | H14: 0 | I14: 0 | J14: 0 | P14: 0 | Q14: 0 | R14: 0
A15: 98026 | B15: Residential | D15: 0 | E15: 0 | F15: 0 | H15: 0 | I15: 0 | J15: 0 | P15: 0 | Q15: 0 | R15: 0
A16: 98119 | B16: Commercial | D16: 0 | E16: 0 | F16: 0 | H16: 0 | I16: 0 | J16: 0 | P16: 0 | Q16: 0 | R16: 0
A17: 98119 | B17: Industrial | D17: 0 | E17: 0 | F17: 0 | H17: 0 | I17: 0 | J17: 0 | P17: 0 | Q17: 0 | R17: 0
A18: 98119 | B18: Residential | D18: 0 | E18: 0 | F18: 0 | H18: 0 | I18: 0 | J18: 0 | P18: 0 | Q18: 0 | R18: 0
... A132: 98762 | B132: Residential | D132: 0 | E132: 0 | F132: 0 | H132: 0 | I132: 0 | J132: 0 | P132: 0 | Q132: 0 | R132: 0
D134: =SUMIF($B$4:$B$132,$B$132,D4:D132) -> 58 | E134: =SUMIF($B$4:$B$132,$B$132,E4:E132) -> 64 | F134: =SUMIF($B$4:$B$132,$B$132,F4:F132) -> 81 | H134: =SUMIF($B$4:$B$132,$B$132,H4:H132) -> 12 | I134: =SUMIF($B$4:$B$132,$B$132,I4:I132) -> 16 | J134: =SUMIF($B$4:$B$132,$B$132,J4:J132) -> 19 | P134: =SUMIF($B$4:$B$132,$B$132,P4:P132) -> 10 | Q134: =SUMIF($B$4:$B$132,$B$132,Q4:Q132) -> 2 | R134: =SUMIF($B$4:$B$132,$B$132,R4:R132) -> 10
D135: Please note that NW Natural will return any new deposits charged to Residential customers in error | H135: Please note that NW Natural will return these deposits charged to Residential customers in error

Sheet 7. Bill Assistance 2025
A1: Bill Assist 2025 | D1: Item a) Number of Premises Receiving Bill Assistance or Enrolled in Any Other Assistance Program
A2: Zip Code | B2: Customer Class | D2: =+'6. Deposits 2025'!D2 -> Jan 2025 | E2: =+'6. Deposits 2025'!E2 -> Feb 2025 | F2: =+'6. Deposits 2025'!F2 -> Mar 2025
A3: 97031 | B3: Commercial | D3: 0 | E3: 0 | F3: 0
A4: 97031 | B4: Industrial | D4: 0 | E4: 0 | F4: 0
A5: 97031 | B5: Residential | D5: 0 | E5: 0 | F5: 0
A6: 97301 | B6: Commercial | D6: 0 | E6: 0 | F6: 0
A7: 97301 | B7: Industrial | D7: 0 | E7: 0 | F7: 0
A8: 97301 | B8: Residential | D8: 0 | E8: 0 | F8: 0
A9: 97388 | B9: Commercial | D9: 0 | E9: 0 | F9: 0
A10: 97388 | B10: Industrial | D10: 0 | E10: 0 | F10: 0
A11: 97388 | B11: Residential | D11: 0 | E11: 0 | F11: 0
A12: 98026 | B12: Commercial | D12: 0 | E12: 0 | F12: 0
A13: 98026 | B13: Industrial | D13: 0 | E13: 0 | F13: 0
A14: 98026 | B14: Residential | D14: 0 | E14: 0 | F14: 0
... A131: 98762 | B131: Residential | D131: 0 | E131: 0 | F131: 0

Sheet 8. Past Due Balances 2025
A1: Past Due 2025 | D1: Item a) Number of Customers by Customer Class With Past-due balances (arrearages) | H1: Item b) Past-due Balances by Customer Class and Number of Days Past-due | AG1: Item c) Amount of Past-due Balances for Known Low-income Households and Number of Days Past-due | AU1: Item d) Amount of Past Due Balances Classified as Uncollectible | AY1: Item e) The Amount of Past-due Balances Written-off and Classified as Bad Debt, if different than item d | BD1: Item f) Number of Customer Accounts Referred to Collection Agencies | BH1: Item f) Total Amount of Bad Debt Referred for Collection | BM1: Item f) Total Revenue to the Company from the Collection Process
H2: =+D3 -> Jan 2025 | P2: =+E3 -> Feb 2025 | X2: =+F3 -> Mar 2025 | AG2: =+D3 -> Jan 2025 | AK2: =+E3 -> Feb 2025 | AO2: =+F3 -> Mar 2025
A3: Zip Code | B3: Customer Class | D3: Jan 2025 | E3: Feb 2025 | F3: Mar 2025 | H3: 30 Days Amt | I3: 30 Day Count | J3: 60 Days Amt | K3: 60 Days Count | L3: 90 Days + Amt | M3: 90 Days + Count | N3: Total Arrearages | O3: Total Count | P3: =+H3 -> 30 Days Amt | Q3: =+I3 -> 30 Day Count | R3: =+J3 -> 60 Days Amt | S3: =+K3 -> 60 Days Count | T3: =+L3 -> 90 Days + Amt | U3: =+M3 -> 90 Days + Count | V3: =+N3 -> Total Arrearages | W3: =+O3 -> Total Count | ... AE3: =+W3 -> Total Count | AG3: 30 Days | AH3: 60 Days | AI3: 90 Days + | AJ3: Total Arrearages | AK3: 30 Days | AL3: 60 Days | AM3: 90 Days + | AN3: Total Arrearages | AO3: 30 Days | AP3: 60 Days | AQ3: 90 Days + | AR3: Total Arrearages | AU3: =+'4. Payment Arrangements 2025'!D2 -> Jan 2025 | AV3: =+'4. Payment Arrangements 2025'!E2 -> Feb 2025 | AW3: =+'4. Payment Arrangements 2025'!F2 -> Mar 2025 | AY3: =+AU3 -> Jan 2025 | AZ3: =+AV3 -> Feb 2025 | BA3: =+AW3 -> Mar 2025 | BD3: =+AY3 -> Jan 2025 | BE3: =+AZ3 -> Feb 2025 | BF3: =+BA3 -> Mar 2025 | BH3: =+BD3 -> Jan 2025 | BI3: =+BE3 -> Feb 2025 | BJ3: =+BF3 -> Mar 2025 | BM3: =+BH3 -> Jan 2025 | BN3: =+BI3 -> Feb 2025 | BO3: =+BJ3 -> Mar 2025
A4: 97031 | B4: Commercial | D4: 0 | E4: 0 | F4: 0 | H4: 0 | I4: 0 | J4: 0 | K4: 0 | L4: 0 | M4: 0 | N4: 0 | O4: 0 | P4: 0 | Q4: 0 | R4: 0 | S4: 0 | T4: 0 | U4: 0 | V4: 0 | W4: 0 | X4: 0 | Y4: 0 | Z4: 0 | AA4: 0 | AB4: 0 | AC4: 0 | AD4: 0 | AE4: 0 | AG4: 0 | AH4: 0 | AI4: 0 | AJ4: 0 | AK4: 0 | AL4: 0 | AM4: 0 | AN4: 0 | AO4: 0 | AP4: 0 | AQ4: 0 | AR4: 0 | AU4: This data is not available by zip code | BD4: This data is not available by zip code | BM4: This data is not available by zip code
A5: 97031 | B5: Industrial | D5: 0 | E5: 0 | F5: 0 | H5: 0 | I5: 0 | J5: 0 | K5: 0 | L5: 0 | M5: 0 | N5: 0 | O5: 0 | P5: 0 | Q5: 0 | R5: 0 | S5: 0 | T5: 0 | U5: 0 | V5: 0 | W5: 0 | X5: 0 | Y5: 0 | Z5: 0 | AA5: 0 | AB5: 0 | AC5: 0 | AD5: 0 | AE5: 0 | AG5: 0 | AH5: 0 | AI5: 0 | AJ5: 0 | AK5: 0 | AL5: 0 | AM5: 0 | AN5: 0 | AO5: 0 | AP5: 0 | AQ5: 0 | AR5: 0
A6: 97031 | B6: Residential | D6: 0 | E6: 0 | F6: 0 | H6: 0 | I6: 0 | J6: 0 | K6: 0 | L6: 0 | M6: 0 | N6: 0 | O6: 0 | P6: 0 | Q6: 0 | R6: 0 | S6: 0 | T6: 0 | U6: 0 | V6: 0 | W6: 0 | X6: 0 | Y6: 0 | Z6: 0 | AA6: 0 | AB6: 0 | AC6: 0 | AD6: 0 | AE6: 0 | AG6: 0 | AH6: 0 | AI6: 0 | AJ6: 0 | AK6: 0 | AL6: 0 | AM6: 0 | AN6: 0 | AO6: 0 | AP6: 0 | AQ6: 0 | AR6: 0 | AT6: Commercial | AU6: 5418.23 | AV6: 26426.34 | AW6: 6607.2 | BC6: Commercial | BD6: 16 | BE6: 10 | BF6: 9 | BL6: Commercial | BM6: 1000.77 | BN6: 510.13 | BO6: 12932.58
A7: 97301 | B7: Commercial | D7: 0 | E7: 0 | F7: 0 | H7: 0 | I7: 0 | J7: 0 | K7: 0 | L7: 0 | M7: 0 | N7: 0 | O7: 0 | P7: 0 | Q7: 0 | R7: 0 | S7: 0 | T7: 0 | U7: 0 | V7: 0 | W7: 0 | X7: 0 | Y7: 0 | Z7: 0 | AA7: 0 | AB7: 0 | AC7: 0 | AD7: 0 | AE7: 0 | AG7: 0 | AH7: 0 | AI7: 0 | AJ7: 0 | AK7: 0 | AL7: 0 | AM7: 0 | AN7: 0 | AO7: 0 | AP7: 0 | AQ7: 0 | AR7: 0 | AT7: Industrial | AU7: 0 | AV7: 0 | AW7: 0 | BC7: Industrial | BD7: 0 | BE7: 0 | BF7: 0 | BL7: Industrial | BM7: 0 | BN7: 0 | BO7: 0
A8: 97301 | B8: Industrial | D8: 0 | E8: 0 | F8: 0 | H8: 0 | I8: 0 | J8: 0 | K8: 0 | L8: 0 | M8: 0 | N8: 0 | O8: 0 | P8: 0 | Q8: 0 | R8: 0 | S8: 0 | T8: 0 | U8: 0 | V8: 0 | W8: 0 | X8: 0 | Y8: 0 | Z8: 0 | AA8: 0 | AB8: 0 | AC8: 0 | AD8: 0 | AE8: 0 | AG8: 0 | AH8: 0 | AI8: 0 | AJ8: 0 | AK8: 0 | AL8: 0 | AM8: 0 | AN8: 0 | AO8: 0 | AP8: 0 | AQ8: 0 | AR8: 0 | AT8: Residential | AU8: 20703.34 | AV8: 23804.31 | AW8: 15960.24 | AY8: see item d | BC8: Residential | BD8: 101 | BE8: 111 | BF8: 83 | BH8: see item d | BL8: Residential | BM8: 12536.8 | BN8: 11846.47 | BO8: 17011.13
A9: 97301 | B9: Residential | D9: 0 | E9: 0 | F9: 0 | H9: 0 | I9: 0 | J9: 0 | K9: 0 | L9: 0 | M9: 0 | N9: 0 | O9: 0 | P9: 0 | Q9: 0 | R9: 0 | S9: 0 | T9: 0 | U9: 0 | V9: 0 | W9: 0 | X9: 0 | Y9: 0 | Z9: 0 | AA9: 0 | AB9: 0 | AC9: 0 | AD9: 0 | AE9: 0 | AG9: 0 | AH9: 0 | AI9: 0 | AJ9: 0 | AK9: 0 | AL9: 0 | AM9: 0 | AN9: 0 | AO9: 0 | AP9: 0 | AQ9: 0 | AR9: 0
A10: 97388 | B10: Commercial | D10: 0 | E10: 0 | F10: 0 | H10: 0 | I10: 0 | J10: 0 | K10: 0 | L10: 0 | M10: 0 | N10: 0 | O10: 0 | P10: 0 | Q10: 0 | R10: 0 | S10: 0 | T10: 0 | U10: 0 | V10: 0 | W10: 0 | X10: 0 | Y10: 0 | Z10: 0 | AA10: 0 | AB10: 0 | AC10: 0 | AD10: 0 | AE10: 0 | AG10: 0 | AH10: 0 | AI10: 0 | AJ10: 0 | AK10: 0 | AL10: 0 | AM10: 0 | AN10: 0 | AO10: 0 | AP10: 0 | AQ10: 0 | AR10: 0 | AT10: Totals | AU10: =SUM(AU6:AU8) -> 26121.57 | AV10: =SUM(AV6:AV8) -> 50230.65 | AW10: =SUM(AW6:AW8) -> 22567.44 | BC10: Totals | BD10: =SUM(BD6:BD8) -> 117 | BE10: =SUM(BE6:BE8) -> 121 | BF10: =SUM(BF6:BF8) -> 92 | BL10: Totals | BM10: =SUM(BM6:BM8) -> 13537.57 | BN10: =SUM(BN6:BN8) -> 12356.6 | BO10: =SUM(BO6:BO8) -> 29943.71
A11: 97388 | B11: Industrial | D11: 0 | E11: 0 | F11: 0 | H11: 0 | I11: 0 | J11: 0 | K11: 0 | L11: 0 | M11: 0 | N11: 0 | O11: 0 | P11: 0 | Q11: 0 | R11: 0 | S11: 0 | T11: 0 | U11: 0 | V11: 0 | W11: 0 | X11: 0 | Y11: 0 | Z11: 0 | AA11: 0 | AB11: 0 | AC11: 0 | AD11: 0 | AE11: 0 | AG11: 0 | AH11: 0 | AI11: 0 | AJ11: 0 | AK11: 0 | AL11: 0 | AM11: 0 | AN11: 0 | AO11: 0 | AP11: 0 | AQ11: 0 | AR11: 0
A12: 97388 | B12: Residential | D12: 0 | E12: 0 | F12: 0 | H12: 0 | I12: 0 | J12: 0 | K12: 0 | L12: 0 | M12: 0 | N12: 0 | O12: 0 | P12: 0 | Q12: 0 | R12: 0 | S12: 0 | T12: 0 | U12: 0 | V12: 0 | W12: 0 | X12: 0 | Y12: 0 | Z12: 0 | AA12: 0 | AB12: 0 | AC12: 0 | AD12: 0 | AE12: 0 | AG12: 0 | AH12: 0 | AI12: 0 | AJ12: 0 | AK12: 0 | AL12: 0 | AM12: 0 | AN12: 0 | AO12: 0 | AP12: 0 | AQ12: 0 | AR12: 0
A13: 98026 | B13: Commercial | D13: 0 | E13: 0 | F13: 0 | H13: 0 | I13: 0 | J13: 0 | K13: 0 | L13: 0 | M13: 0 | N13: 0 | O13: 0 | P13: 0 | Q13: 0 | R13: 0 | S13: 0 | T13: 0 | U13: 0 | V13: 0 | W13: 0 | X13: 0 | Y13: 0 | Z13: 0 | AA13: 0 | AB13: 0 | AC13: 0 | AD13: 0 | AE13: 0 | AG13: 0 | AH13: 0 | AI13: 0 | AJ13: 0 | AK13: 0 | AL13: 0 | AM13: 0 | AN13: 0 | AO13: 0 | AP13: 0 | AQ13: 0 | AR13: 0
A14: 98026 | B14: Industrial | D14: 0 | E14: 0 | F14: 0 | H14: 0 | I14: 0 | J14: 0 | K14: 0 | L14: 0 | M14: 0 | N14: 0 | O14: 0 | P14: 0 | Q14: 0 | R14: 0 | S14: 0 | T14: 0 | U14: 0 | V14: 0 | W14: 0 | X14: 0 | Y14: 0 | Z14: 0 | AA14: 0 | AB14: 0 | AC14: 0 | AD14: 0 | AE14: 0 | AG14: 0 | AH14: 0 | AI14: 0 | AJ14: 0 | AK14: 0 | AL14: 0 | AM14: 0 | AN14: 0 | AO14: 0 | AP14: 0 | AQ14: 0 | AR14: 0
A15: 98026 | B15: Residential | D15: 0 | E15: 0 | F15: 0 | H15: 0 | I15: 0 | J15: 0 | K15: 0 | L15: 0 | M15: 0 | N15: 0 | O15: 0 | P15: 0 | Q15: 0 | R15: 0 | S15: 0 | T15: 0 | U15: 0 | V15: 0 | W15: 0 | X15: 0 | Y15: 0 | Z15: 0 | AA15: 0 | AB15: 0 | AC15: 0 | AD15: 0 | AE15: 0 | AG15: 0 | AH15: 0 | AI15: 0 | AJ15: 0 | AK15: 0 | AL15: 0 | AM15: 0 | AN15: 0 | AO15: 0 | AP15: 0 | AQ15: 0 | AR15: 0
A16: 98119 | B16: Commercial | D16: 0 | E16: 0 | F16: 0 | H16: 0 | I16: 0 | J16: 0 | K16: 0 | L16: 0 | M16: 0 | N16: 0 | O16: 0 | P16: 0 | Q16: 0 | R16: 0 | S16: 0 | T16: 0 | U16: 0 | V16: 0 | W16: 0 | X16: 0 | Y16: 0 | Z16: 0 | AA16: 0 | AB16: 0 | AC16: 0 | AD16: 0 | AE16: 0 | AG16: 0 | AH16: 0 | AI16: 0 | AJ16: 0 | AK16: 0 | AL16: 0 | AM16: 0 | AN16: 0 | AO16: 0 | AP16: 0 | AQ16: 0 | AR16: 0
A17: 98119 | B17: Industrial | D17: 0 | E17: 0 | F17: 0 | H17: 0 | I17: 0 | J17: 0 | K17: 0 | L17: 0 | M17: 0 | N17: 0 | O17: 0 | P17: 0 | Q17: 0 | R17: 0 | S17: 0 | T17: 0 | U17: 0 | V17: 0 | W17: 0 | X17: 0 | Y17: 0 | Z17: 0 | AA17: 0 | AB17: 0 | AC17: 0 | AD17: 0 | AE17: 0 | AG17: 0 | AH17: 0 | AI17: 0 | AJ17: 0 | AK17: 0 | AL17: 0 | AM17: 0 | AN17: 0 | AO17: 0 | AP17: 0 | AQ17: 0 | AR17: 0
A18: 98119 | B18: Residential | D18: 0 | E18: 0 | F18: 0 | H18: 0 | I18: 0 | J18: 0 | K18: 0 | L18: 0 | M18: 0 | N18: 0 | O18: 0 | P18: 0 | Q18: 0 | R18: 0 | S18: 0 | T18: 0 | U18: 0 | V18: 0 | W18: 0 | X18: 0 | Y18: 0 | Z18: 0 | AA18: 0 | AB18: 0 | AC18: 0 | AD18: 0 | AE18: 0 | AG18: 0 | AH18: 0 | AI18: 0 | AJ18: 0 | AK18: 0 | AL18: 0 | AM18: 0 | AN18: 0 | AO18: 0 | AP18: 0 | AQ18: 0 | AR18: 0
A19: 98125 | B19: Commercial | D19: 0 | E19: 0 | F19: 0 | H19: 0 | I19: 0 | J19: 0 | K19: 0 | L19: 0 | M19: 0 | N19: 0 | O19: 0 | P19: 0 | Q19: 0 | R19: 0 | S19: 0 | T19: 0 | U19: 0 | V19: 0 | W19: 0 | X19: 0 | Y19: 0 | Z19: 0 | AA19: 0 | AB19: 0 | AC19: 0 | AD19: 0 | AE19: 0 | AG19: 0 | AH19: 0 | AI19: 0 | AJ19: 0 | AK19: 0 | AL19: 0 | AM19: 0 | AN19: 0 | AO19: 0 | AP19: 0 | AQ19: 0 | AR19: 0
A20: 98125 | B20: Industrial | D20: 0 | E20: 0 | F20: 0 | H20: 0 | I20: 0 | J20: 0 | K20: 0 | L20: 0 | M20: 0 | N20: 0 | O20: 0 | P20: 0 | Q20: 0 | R20: 0 | S20: 0 | T20: 0 | U20: 0 | V20: 0 | W20: 0 | X20: 0 | Y20: 0 | Z20: 0 | AA20: 0 | AB20: 0 | AC20: 0 | AD20: 0 | AE20: 0 | AG20: 0 | AH20: 0 | AI20: 0 | AJ20: 0 | AK20: 0 | AL20: 0 | AM20: 0 | AN20: 0 | AO20: 0 | AP20: 0 | AQ20: 0 | AR20: 0
A21: 98125 | B21: Residential | D21: 0 | E21: 0 | F21: 0 | H21: 0 | I21: 0 | J21: 0 | K21: 0 | L21: 0 | M21: 0 | N21: 0 | O21: 0 | P21: 0 | Q21: 0 | R21: 0 | S21: 0 | T21: 0 | U21: 0 | V21: 0 | W21: 0 | X21: 0 | Y21: 0 | Z21: 0 | AA21: 0 | AB21: 0 | AC21: 0 | AD21: 0 | AE21: 0 | AG21: 0 | AH21: 0 | AI21: 0 | AJ21: 0 | AK21: 0 | AL21: 0 | AM21: 0 | AN21: 0 | AO21: 0 | AP21: 0 | AQ21: 0 | AR21: 0
A22: 98127 | B22: Commercial | D22: 0 | E22: 0 | F22: 0 | H22: 0 | I22: 0 | J22: 0 | K22: 0 | L22: 0 | M22: 0 | N22: 0 | O22: 0 | P22: 0 | Q22: 0 | R22: 0 | S22: 0 | T22: 0 | U22: 0 | V22: 0 | W22: 0 | X22: 0 | Y22: 0 | Z22: 0 | AA22: 0 | AB22: 0 | AC22: 0 | AD22: 0 | AE22: 0 | AG22: 0 | AH22: 0 | AI22: 0 | AJ22: 0 | AK22: 0 | AL22: 0 | AM22: 0 | AN22: 0 | AO22: 0 | AP22: 0 | AQ22: 0 | AR22: 0
... A132: 98762 | B132: Residential | D132: 0 | E132: 0 | F132: 0 | H132: 0 | I132: 0 | J132: 0 | K132: 0 | L132: 0 | M132: 0 | N132: 0 | O132: 0 | P132: 99165.23 | Q132: 590 | R132: 21753.49 | S132: 158 | T132: 8489.9 | U132: 127 | V132: 129408.62 | W132: 875 | X132: 0 | Y132: 0 | Z132: 0 | AA132: 0 | AB132: 0 | AC132: 0 | AD132: 0 | AE132: 0 | AG132: 0 | AH132: 0 | AI132: 0 | AJ132: 0 | AK132: 0 | AL132: 0 | AM132: 0 | AN132: 0 | AO132: 0 | AP132: 0 | AQ132: 0 | AR132: 0
