Workbook

Sheet 1. General 2022_Q2
A1: Count of aggreements by ZIP and CLASS.
A2: WA_TERM_COVID_COUNTS
A3: General 2022
A4: 44652 | D4: 44682 | G4: 44713 | K4: Retail Sales (kWh) | L4: July | M4: August | N4: September | O4: 44652 | P4: 44682 | Q4: 44713 | R4: July | S4: August | T4: September | U4: October | V4: November | W4: December | X4: Totals Q2
A5: Zip | B5: Class | C5: Count | D5: Zip | E5: Class | F5: Count | G5: Zip | H5: Class | I5: Count | K5: Residential | L5: 149454803 | M5: 144341255 | N5: 106642496 | O5: 117639312 | P5: 105770932 | Q5: 92158912 | X5: =SUM(O5:Q5) -> 315569156
A6: 98901 | B6: COM | C6: 2121 | D6: 98901 | E6: COM | F6: 2118 | G6: 98901 | H6: COM | I6: 2132 | K6: Commercial | L6: 140404042 | M6: 148198213 | N6: 131511808 | O6: 110239574 | P6: 106749804 | Q6: 111946253 | X6: =SUM(O6:Q6) -> 328935631
A7: 98902 | B7: COM | C7: 2550 | D7: 98902 | E7: COM | F7: 2533 | G7: 98902 | H7: COM | I7: 2545 | K7: Industrial | L7: 72533895 | M7: 71622459 | N7: 72818621 | O7: 67776438 | P7: 110717833 | Q7: 24110397 | X7: =SUM(O7:Q7) -> 202604668
A8: 98903 | B8: COM | C8: 1615 | D8: 98903 | E8: COM | F8: 1618 | G8: 98903 | H8: COM | I8: 1613 | K8: Irrigation | L8: 36860793 | M8: 39164393 | N8: 25760901 | O8: 6980502 | P8: 12323026 | Q8: 17003255 | X8: =SUM(O8:Q8) -> 36306783
A9: 98904 | B9: COM | C9: 2 | D9: 98904 | E9: COM | F9: 2 | G9: 98904 | H9: COM | I9: 2 | K9: Totals | L9: =SUM(L5:L8) -> 399253533 | M9: =SUM(M5:M8) -> 403326320 | N9: =SUM(N5:N8) -> 336733826 | O9: =SUM(O5:O8) -> 302635826 | P9: =SUM(P5:P8) -> 335561595 | Q9: =SUM(Q5:Q8) -> 245218817 | R9: =SUM(R5:R8) -> 0 | S9: =SUM(S5:S8) -> 0 | ... X9: =SUM(X5:X8) -> 883416238
A10: 98907 | B10: COM | C10: 2 | D10: 98907 | E10: COM | F10: 2 | G10: 98907 | H10: COM | I10: 2
A11: 98908 | B11: COM | C11: 1526 | D11: 98908 | E11: COM | F11: 1527 | G11: 98908 | H11: COM | I11: 1535
A12: 98920 | B12: COM | C12: 4 | D12: 98920 | E12: COM | F12: 4 | G12: 98920 | H12: COM | I12: 4
A13: 98921 | B13: COM | C13: 26 | D13: 98921 | E13: COM | F13: 26 | G13: 98921 | H13: COM | I13: 26
A14: 98923 | B14: COM | C14: 107 | D14: 98923 | E14: COM | F14: 107 | G14: 98923 | H14: COM | I14: 107
A15: 98930 | B15: COM | C15: 619 | D15: 98930 | E15: COM | F15: 620 | G15: 98930 | H15: COM | I15: 624
A16: 98932 | B16: COM | C16: 226 | D16: 98932 | E16: COM | F16: 228 | G16: 98932 | H16: COM | I16: 227
A17: 98933 | B17: COM | C17: 73 | D17: 98933 | E17: COM | F17: 72 | G17: 98933 | H17: COM | I17: 74
A18: 98935 | B18: COM | C18: 135 | D18: 98935 | E18: COM | F18: 136 | G18: 98935 | H18: COM | I18: 138
A19: 98936 | B19: COM | C19: 349 | D19: 98936 | E19: COM | F19: 348 | G19: 98936 | H19: COM | I19: 348
A20: 98937 | B20: COM | C20: 389 | D20: 98937 | E20: COM | F20: 390 | G20: 98937 | H20: COM | I20: 388
A21: 98938 | B21: COM | C21: 154 | D21: 98938 | E21: COM | F21: 157 | G21: 98938 | H21: COM | I21: 157
... A40: 99363 | B40: COM | C40: 72 | D40: 99363 | E40: COM | F40: 74 | G40: 99363 | H40: COM | I40: 73
B41: COM | C41: 1 | E41: COM | F41: 1 | H41: COM | I41: 1
A42: 98901 | B42: IND | C42: 48 | D42: 98901 | E42: IND | F42: 48 | G42: 98901 | H42: IND | I42: 48
A43: 98902 | B43: IND | C43: 85 | D43: 98902 | E43: IND | F43: 85 | G43: 98902 | H43: IND | I43: 85
A44: 98903 | B44: IND | C44: 64 | D44: 98903 | E44: IND | F44: 64 | G44: 98903 | H44: IND | I44: 64
A45: 98908 | B45: IND | C45: 17 | D45: 98908 | E45: IND | F45: 17 | G45: 98908 | H45: IND | I45: 17
A46: 98921 | B46: IND | C46: 1 | D46: 98921 | E46: IND | F46: 1 | G46: 98921 | H46: IND | I46: 1
A47: 98923 | B47: IND | C47: 4 | D47: 98923 | E47: IND | F47: 4 | G47: 98923 | H47: IND | I47: 4
A48: 98930 | B48: IND | C48: 26 | D48: 98930 | E48: IND | F48: 26 | G48: 98930 | H48: IND | I48: 26
A49: 98932 | B49: IND | C49: 12 | D49: 98932 | E49: IND | F49: 12 | G49: 98932 | H49: IND | I49: 12
A50: 98933 | B50: IND | C50: 1 | D50: 98933 | E50: IND | F50: 1 | G50: 98933 | H50: IND | I50: 1
A51: 98935 | B51: IND | C51: 3 | D51: 98935 | E51: IND | F51: 3 | G51: 98935 | H51: IND | I51: 3
A52: 98936 | B52: IND | C52: 18 | D52: 98936 | E52: IND | F52: 18 | G52: 98936 | H52: IND | I52: 18
A53: 98937 | B53: IND | C53: 11 | D53: 98937 | E53: IND | F53: 11 | G53: 98937 | H53: IND | I53: 11
... A143: 99363 | B143: RES | C143: 75 | D143: 99363 | E143: RES | F143: 74 | G143: 99363 | H143: RES | I143: 74

Sheet 2. Disconnections 2022_Q2
A1: General 2022 | D1: Item a) Number of Disconnections by Customer Class per Month | H1: Item b) Avg. Duration of Disconnection by Customer Class (in Hours for recon 10 days or less) | L1: Item c) Number of Customers by Customer Class Receiving Disconnection Notices | P1: Item d) Number of Customers by Customer Class Who Absent the Disconnection Moratorium Would Have Been Disconnected
A2: Zip Code | B2: Customer Class | D2: 44652 | E2: 44682 | F2: 44713 | H2: 44652 | I2: 44682 | J2: 44713 | L2: 44652 | M2: 44682 | N2: 44713 | P2: 44652 | Q2: 44682 | R2: 44713
A3: none

Sheet 3. Fees 2022_Q2
A1: General 2022 | D1: Item a) Number of Customers by Customer Class Assessed Late Payment Fees | H1: Item a) Aggregate amount of Charged Late Payment Fees | L1: Item a) Number of Customers by Customer Class Assessed Disconnection Fees | P1: Item a) Aggregate amount of Charged Disconnection Fees | T1: Item a) Number of Customers by Customer Class Assessed Reconnection Fees | X1: Item a) Aggregate amount of Charged Reconnection Fees
A2: Zip Code | B2: Customer Class | D2: 44652 | E2: 44682 | F2: 44713 | H2: 44652 | I2: 44682 | J2: 44713 | L2: 44652 | M2: 44682 | N2: 44713 | P2: 44652 | Q2: 44682 | R2: 44713 | T2: 44652 | U2: 44682 | V2: 44713 | X2: 44652 | Y2: 44682 | Z2: 44713
A3: None

Sheet 4. Payment Arrangements 2022_Q2
A1: General 2022 | D1: Item a) Number of Customers by Customer Class Taking Service at the Beginning of Each Month with Existing Long Term Payment Agreements | H1: Item b) Number of Customers By Customer Class Completing Long-term Payment Agreements | L1: Item c) Number of Customers by Customer Class Enrolling in New Long-term Payment Agreements | P1: Item d) Number of Customers By Customer Class Renegotiating Long-term Payment Agreements
A2: Zip Code | B2: Customer Class | D2: 44652 | E2: 44682 | F2: 44713 | H2: 44652 | I2: 44682 | J2: 44713 | L2: 44652 | M2: 44682 | N2: 44713 | P2: 44652 | Q2: 44682 | R2: 44713
A3: NA | B3: COM | D3: 100 | E3: 96 | F3: 89 | H3: 5 | I3: 10 | J3: 7 | L3: 26 | M3: 27 | N3: 27 | P3: 0 | Q3: 1 | R3: 1
A4: NA | B4: RES | D4: 3535 | E4: 3340 | F4: 3246 | H4: 100 | I4: 84 | J4: 60 | L4: 882 | M4: 862 | N4: 809 | P4: 24 | Q4: 22 | R4: 45

Sheet 5. Medical Certificates 2022_Q2
A1: General 2022 | D1: Item a) Number of Customers Taking Service at the Beginning of Each Month Under Existing Medical Payment Arrangements | H1: Item b) Number of Customers Completing Medical Payment Arrangements Each Month | L1: Item c) Number of Customers Enrolling in New Medical Payment Arrangements Each Month | P1: Item d) Number of Customers Renegotiating Medical Payment Arrangements Each Month
A2: Zip Code | B2: Customer Class | D2: 44652 | E2: 44682 | F2: 44713 | H2: 44652 | I2: 44682 | J2: 44713 | L2: 44652 | M2: 44682 | N2: 44713 | P2: 44197 | Q2: 44228 | R2: 44256 | S2: 44287 | T2: 44317 | U2: 44348 | V2: 44378 | W2: 44409 | X2: 44440 | Y2: 44652 | Z2: 44682 | AA2: 44713
A3: NA | B3: RES | D3: 6 | E3: 4 | F3: 4 | H3: 0 | I3: 0 | J3: 0 | L3: 0 | M3: 2 | N3: 1 | P3: 0 | Q3: 0 | R3: 0 | S3: 0 | T3: 0 | U3: 0 | V3: 0 | W3: 0 | X3: 0 | Y3: 0 | Z3: 0 | AA3: 0

Sheet 6. Deposits 2022_Q2
A1: General 2022 | D1: Item a) Number of Customers by Customer Class with Required Deposits at the Beginning of Each Month | N1: Item b) Number of Customers by Customer Class Required to Submit New or Increased Deposits Each Month | AH1: Item c) Number of Customers by Customer Class Whose Deposits Were Reduced In Part or Foregone Each Month | AR1: Item d) Number of Customers by Customer Class whose Deposits were Returned in Full Each Month
D2: 44652 | G2: 44682 | J2: 44713 | N2: Zip Code | O2: Customer Class | P2: 44197 | Q2: 44228 | R2: 44256 | S2: Zip Code | T2: Customer Class | U2: 44287 | V2: 44317 | W2: 44348 | X2: 44652 | AA2: 44682 | AD2: 44713 | AH2: 44197 | AI2: 44228 | AJ2: 44256 | AK2: 44287 | AL2: 44317 | AM2: 44348 | AN2: 44652 | AO2: 44682 | AP2: 44713 | AR2: 44652 | AU2: 44682 | AX2: 44713
D3: ZIP | E3: CLASS | F3: Concat Agreement Number | G3: ZIP | H3: CLASS | I3: Concat Agreement Number | J3: ZIP | K3: CLASS | L3: Concat Agreement Number | N3: 98901 | O3: COM | P3: 4 | Q3: 1 | R3: 2 | S3: 98901 | T3: COM | U3: 1 | V3: 6 | X3: ZIP | Y3: CLASS | Z3: Concat Agreement Number | AA3: ZIP | AB3: CLASS | AC3: Concat Agreement Number | AD3: ZIP | AE3: CLASS | AF3: Concat Agreement Number | AR3: ZIP | AS3: CLASS | AT3: Concat Agreement Number | AU3: ZIP | AV3: CLASS | AW3: Concat Agreement Number | AX3: ZIP | AY3: CLASS | AZ3: Concat Agreement Number
D4: 98901 | E4: COM | F4: 16 | G4: 98901 | H4: COM | I4: 18 | J4: 98901 | K4: COM | L4: 18 | N4: 98901 | O4: RES | P4: 71 | Q4: 53 | R4: 58 | S4: 98901 | T4: RES | U4: 19 | V4: 17 | W4: 19 | X4: 98901 | Y4: COM | Z4: 2 | AA4: 98901 | AB4: RES | AC4: 10 | AD4: 98901 | AE4: COM | AF4: 5 | AR4: 98901 | AS4: RES | AT4: 29 | AU4: 98901 | AV4: RES | AW4: 8 | AX4: 98901 | AY4: RES | AZ4: 20
D5: 98901 | E5: RES | F5: 104 | G5: 98901 | H5: RES | I5: 93 | J5: 98901 | K5: RES | L5: 96 | N5: 98902 | O5: COM | Q5: 6 | R5: 3 | S5: 98902 | T5: COM | U5: 4 | V5: 12 | W5: 5 | X5: 98901 | Y5: RES | Z5: 19 | AA5: 98902 | AB5: COM | AC5: 1 | AD5: 98901 | AE5: RES | AF5: 13 | AR5: 98902 | AS5: COM | AT5: 1 | AU5: 98902 | AV5: COM | AW5: 2 | AX5: 98902 | AY5: RES | AZ5: 11
D6: 98902 | E6: COM | F6: 16 | G6: 98902 | H6: COM | I6: 18 | J6: 98902 | K6: COM | L6: 17 | N6: 98902 | O6: RES | P6: 103 | Q6: 75 | R6: 32 | S6: 98902 | T6: RES | U6: 48 | V6: 22 | W6: 19 | X6: 98902 | Y6: COM | Z6: 4 | AA6: 98902 | AB6: RES | AC6: 18 | AD6: 98902 | AE6: COM | AF6: 4 | AR6: 98902 | AS6: RES | AT6: 33 | AU6: 98902 | AV6: RES | AW6: 23 | AX6: 98903 | AY6: RES | AZ6: 8
D7: 98902 | E7: RES | F7: 119 | G7: 98902 | H7: RES | I7: 109 | J7: 98902 | K7: RES | L7: 105 | N7: 98903 | O7: COM | P7: 6 | R7: 1 | S7: 98903 | T7: COM | U7: 2 | V7: 3 | W7: 3 | X7: 98902 | Y7: RES | Z7: 26 | AA7: 98903 | AB7: COM | AC7: 2 | AD7: 98902 | AE7: RES | AF7: 7 | AR7: 98903 | AS7: COM | AT7: 4 | AU7: 98903 | AV7: RES | AW7: 3 | AX7: 98908 | AY7: RES | AZ7: 17
D8: 98903 | E8: COM | F8: 16 | G8: 98903 | H8: COM | I8: 15 | J8: 98903 | K8: COM | L8: 18 | N8: 98903 | O8: RES | P8: 17 | Q8: 16 | R8: 22 | S8: 98903 | T8: RES | U8: 5 | V8: 1 | W8: 6 | X8: 98903 | Y8: COM | Z8: 3 | AA8: 98903 | AB8: RES | AC8: 1 | AD8: 98903 | AE8: COM | AF8: 1 | AR8: 98903 | AS8: RES | AT8: 4 | AU8: 98908 | AV8: RES | AW8: 9 | AX8: 98930 | AY8: COM | AZ8: 1
D9: 98903 | E9: RES | F9: 35 | G9: 98903 | H9: RES | I9: 37 | J9: 98903 | K9: RES | L9: 35 | N9: 98908 | O9: COM | P9: 4 | Q9: 1 | R9: 2 | S9: 98908 | T9: COM | V9: 4 | W9: 2 | X9: 98903 | Y9: RES | Z9: 6 | AA9: 98908 | AB9: COM | AC9: 1 | AD9: 98903 | AE9: RES | AF9: 5 | AR9: 98908 | AS9: COM | AT9: 1 | AU9: 98930 | AV9: COM | AW9: 3 | AX9: 98930 | AY9: RES | AZ9: 3
D10: 98908 | E10: COM | F10: 10 | G10: 98908 | H10: COM | I10: 11 | J10: 98908 | K10: COM | L10: 12 | N10: 98908 | O10: RES | P10: 37 | Q10: 59 | R10: 47 | S10: 98908 | T10: RES | U10: 31 | V10: 18 | W10: 14 | X10: 98908 | Y10: COM | Z10: 2 | AA10: 98908 | AB10: RES | AC10: 14 | AD10: 98908 | AE10: COM | AF10: 2 | AR10: 98908 | AS10: RES | AT10: 17 | AU10: 98932 | AV10: RES | AW10: 1 | AX10: 98932 | AY10: RES | AZ10: 1
D11: 98908 | E11: RES | F11: 79 | G11: 98908 | H11: RES | I11: 72 | J11: 98908 | K11: RES | L11: 77 | N11: 98921 | O11: RES | P11: 2 | Q11: 1 | S11: 98921 | T11: RES | U11: 2 | X11: 98908 | Y11: RES | Z11: 11 | AA11: 98921 | AB11: RES | AC11: 2 | AD11: 98908 | AE11: RES | AF11: 14 | AR11: 98921 | AS11: RES | AT11: 2 | AU11: 98936 | AV11: RES | AW11: 2 | AX11: 98935 | AY11: RES | AZ11: 1
D12: 98921 | E12: RES | F12: 4 | G12: 98921 | H12: RES | I12: 2 | J12: 98921 | K12: RES | L12: 4 | N12: 98923 | O12: RES | P12: 3 | Q12: 1 | S12: 98923 | T12: RES | U12: 1 | X12: 98930 | Y12: RES | Z12: 5 | AA12: 98930 | AB12: COM | AC12: 3 | AD12: 98930 | AE12: RES | AF12: 2 | AR12: 98930 | AS12: RES | AT12: 6 | AU12: 98937 | AV12: COM | AW12: 1 | AX12: 98936 | AY12: RES | AZ12: 1
D13: 98923 | E13: RES | F13: 1 | G13: 98923 | H13: RES | I13: 1 | J13: 98923 | K13: RES | L13: 1 | N13: 98930 | O13: COM | P13: 2 | Q13: 2 | R13: 1 | S13: 98930 | T13: COM | V13: 2 | X13: 98933 | Y13: COM | Z13: 1 | AA13: 98932 | AB13: COM | AC13: 1 | AD13: 98936 | AE13: RES | AF13: 1 | AR13: 98935 | AS13: RES | AT13: 1 | AU13: 98942 | AV13: RES | AW13: 7 | AX13: 98942 | AY13: RES | AZ13: 6
D14: 98930 | E14: COM | F14: 7 | G14: 98930 | H14: COM | I14: 7 | J14: 98930 | K14: COM | L14: 10 | N14: 98930 | O14: RES | P14: 11 | Q14: 23 | R14: 21 | S14: 98930 | T14: RES | U14: 3 | V14: 2 | W14: 1 | X14: 98935 | Y14: RES | Z14: 1 | AA14: 98935 | AB14: RES | AC14: 1 | AD14: 98942 | AE14: COM | AF14: 3 | AR14: 98936 | AS14: RES | AT14: 2 | AU14: 98944 | AV14: COM | AW14: 1 | AX14: 98944 | AY14: COM | AZ14: 2
D15: 98930 | E15: RES | F15: 35 | G15: 98930 | H15: RES | I15: 34 | J15: 98930 | K15: RES | L15: 34 | N15: 98932 | O15: RES | P15: 5 | Q15: 4 | R15: 6 | S15: 98932 | T15: RES | V15: 3 | X15: 98936 | Y15: COM | Z15: 1 | AA15: 98936 | AB15: COM | AC15: 1 | AD15: 98942 | AE15: RES | AF15: 3 | AR15: 98937 | AS15: RES | AT15: 1 | AU15: 98944 | AV15: RES | AW15: 1 | AX15: 98944 | AY15: RES | AZ15: 4
D16: 98932 | E16: COM | F16: 3 | G16: 98932 | H16: COM | I16: 3 | J16: 98932 | K16: COM | L16: 4 | N16: 98933 | O16: RES | Q16: 1 | S16: 98933 | T16: RES | X16: 98936 | Y16: RES | Z16: 4 | AA16: 98942 | AB16: RES | AC16: 8 | AD16: 98944 | AE16: COM | AF16: 4 | AR16: 98938 | AS16: RES | AT16: 1 | AU16: 98948 | AV16: RES | AW16: 1 | AX16: 98947 | AY16: RES | AZ16: 1
D17: 98932 | E17: RES | F17: 8 | G17: 98932 | H17: RES | I17: 8 | J17: 98932 | K17: RES | L17: 7 | N17: 98935 | O17: COM | Q17: 4 | S17: 98935 | T17: COM | X17: 98938 | Y17: RES | Z17: 1 | AA17: 98944 | AB17: RES | AC17: 3 | AD17: 98944 | AE17: RES | AF17: 1 | AR17: 98942 | AS17: RES | AT17: 3 | AU17: 98951 | AV17: RES | AW17: 5 | AX17: 98948 | AY17: RES | AZ17: 4
D18: 98933 | E18: COM | F18: 1 | G18: 98933 | H18: COM | I18: 2 | J18: 98933 | K18: COM | L18: 2 | N18: 98935 | O18: RES | P18: 6 | Q18: 9 | R18: 1 | S18: 98935 | T18: RES | U18: 2 | V18: 1 | X18: 98942 | Y18: COM | Z18: 1 | AA18: 98951 | AB18: RES | AC18: 4 | AD18: 98947 | AE18: RES | AF18: 1 | AR18: 98944 | AS18: COM | AT18: 1 | AU18: 98953 | AV18: RES | AW18: 1 | AX18: 98951 | AY18: COM | AZ18: 2
D19: 98933 | E19: RES | F19: 1 | G19: 98933 | H19: RES | I19: 1 | J19: 98933 | K19: RES | L19: 1 | N19: 98936 | O19: RES | P19: 2 | Q19: 6 | R19: 5 | S19: 98936 | T19: RES | X19: 98942 | Y19: RES | Z19: 3 | AA19: 98953 | AB19: COM | AC19: 1 | AD19: 98948 | AE19: RES | AF19: 2 | AR19: 98944 | AS19: RES | AT19: 4 | AU19: 99328 | AV19: RES | AW19: 1 | AX19: 98951 | AY19: RES | AZ19: 2
D20: 98935 | E20: COM | F20: 1 | G20: 98935 | H20: COM | I20: 1 | J20: 98935 | K20: COM | L20: 1 | N20: 98937 | O20: RES | P20: 5 | Q20: 2 | R20: 2 | S20: 98937 | T20: COM | U20: 1 | W20: 2 | X20: 98944 | Y20: COM | Z20: 3 | AA20: 98953 | AB20: RES | AC20: 1 | AD20: 98951 | AE20: COM | AF20: 1 | AR20: 98948 | AS20: COM | AT20: 2 | AU20: 99360 | AV20: COM | AW20: 1 | AX20: 98953 | AY20: COM | AZ20: 1
D21: 98935 | E21: RES | F21: 7 | G21: 98935 | H21: RES | I21: 6 | J21: 98935 | K21: RES | L21: 7 | N21: 98938 | O21: COM | P21: 1 | S21: 98937 | T21: RES | V21: 2 | X21: 98944 | Y21: RES | Z21: 4 | AA21: 99324 | AB21: RES | AC21: 1 | AD21: 98953 | AE21: COM | AF21: 2 | AR21: 98951 | AS21: RES | AT21: 6 | AU21: 99360 | AV21: RES | AW21: 1 | AX21: 98953 | AY21: RES | AZ21: 2
D22: 98936 | E22: COM | F22: 7 | G22: 98936 | H22: COM | I22: 7 | J22: 98936 | K22: COM | L22: 8 | N22: 98938 | O22: RES | P22: 7 | Q22: 2 | R22: 1 | S22: 98938 | T22: COM | X22: 98948 | Y22: RES | Z22: 2 | AA22: 99328 | AB22: COM | AC22: 1 | AD22: 98953 | AE22: RES | AF22: 2 | AR22: 98953 | AS22: RES | AT22: 2 | AU22: 99361 | AV22: RES | AW22: 2 | AX22: 99324 | AY22: RES | AZ22: 2
D23: 98936 | E23: RES | F23: 9 | G23: 98936 | H23: RES | I23: 12 | J23: 98936 | K23: RES | L23: 11 | N23: 98939 | O23: RES | P23: 1 | S23: 98938 | T23: RES | X23: 98951 | Y23: COM | Z23: 1 | AA23: 99360 | AB23: RES | AC23: 1 | AD23: 99324 | AE23: RES | AF23: 2 | AR23: 99324 | AS23: RES | AT23: 3 | AU23: 99362 | AV23: COM | AW23: 1 | AX23: 99347 | AY23: RES | AZ23: 1
D24: 98937 | E24: COM | F24: 1 | G24: 98937 | H24: COM | I24: 1 | J24: 98937 | K24: RES | L24: 2 | N24: 98942 | O24: COM | P24: 2 | Q24: 2 | S24: 98939 | T24: RES | X24: 98951 | Y24: RES | Z24: 7 | AA24: 99361 | AB24: RES | AC24: 2 | AD24: 99328 | AE24: COM | AF24: 1 | AR24: 99328 | AS24: COM | AT24: 1 | AU24: 99362 | AV24: RES | AW24: 7 | AX24: 99362 | AY24: COM | AZ24: 4
D25: 98937 | E25: RES | F25: 3 | G25: 98937 | H25: RES | I25: 2 | J25: 98938 | K25: RES | L25: 6 | N25: 98942 | O25: RES | P25: 14 | Q25: 25 | R25: 25 | S25: 98942 | T25: COM | W25: 2 | X25: 98953 | Y25: COM | Z25: 1 | AA25: 99362 | AB25: RES | AC25: 13 | AD25: 99347 | AE25: RES | AF25: 2 | AR25: 99328 | AS25: RES | AT25: 1 | AX25: 99362 | AY25: RES | AZ25: 19
D26: 98938 | E26: RES | F26: 6 | G26: 98938 | H26: RES | I26: 6 | J26: 98939 | K26: RES | L26: 2 | N26: 98944 | O26: COM | P26: 4 | Q26: 1 | R26: 9 | S26: 98942 | T26: RES | U26: 7 | V26: 8 | W26: 6 | X26: 98953 | Y26: RES | Z26: 1 | AD26: 99362 | AE26: COM | AF26: 2 | AR26: 99362 | AS26: COM | AT26: 1
D27: 98939 | E27: RES | F27: 2 | G27: 98939 | H27: RES | I27: 2 | J27: 98942 | K27: COM | L27: 14 | N27: 98944 | O27: RES | P27: 36 | Q27: 21 | R27: 7 | S27: 98944 | T27: COM | U27: 2 | V27: 3 | W27: 1 | X27: 99323 | Y27: RES | Z27: 1 | AD27: 99362 | AE27: RES | AF27: 14 | AR27: 99362 | AS27: RES | AT27: 32
D28: 98942 | E28: COM | F28: 13 | G28: 98942 | H28: COM | I28: 14 | J28: 98942 | K28: RES | L28: 29 | N28: 98947 | O28: RES | P28: 3 | Q28: 5 | S28: 98944 | T28: RES | U28: 13 | V28: 7 | W28: 2 | X28: 99324 | Y28: RES | Z28: 4
D29: 98942 | E29: RES | F29: 27 | G29: 98942 | H29: RES | I29: 28 | J29: 98944 | K29: COM | L29: 20 | N29: 98948 | O29: RES | P29: 20 | Q29: 16 | R29: 20 | S29: 98947 | T29: RES | U29: 4 | V29: 2 | X29: 99360 | Y29: COM | Z29: 2
D30: 98944 | E30: COM | F30: 18 | G30: 98944 | H30: COM | I30: 19 | J30: 98944 | K30: RES | L30: 43 | N30: 98951 | O30: COM | R30: 1 | S30: 98948 | T30: COM | U30: 2 | V30: 5 | X30: 99362 | Y30: COM | Z30: 3
D31: 98944 | E31: RES | F31: 40 | G31: 98944 | H31: RES | I31: 40 | J31: 98947 | K31: RES | L31: 6 | N31: 98951 | O31: RES | P31: 18 | Q31: 24 | R31: 13 | S31: 98948 | T31: RES | U31: 4 | V31: 3 | W31: 1 | X31: 99362 | Y31: RES | Z31: 22
D32: 98947 | E32: RES | F32: 6 | G32: 98947 | H32: RES | I32: 6 | J32: 98948 | K32: COM | L32: 7 | N32: 98952 | O32: RES | Q32: 1 | R32: 2 | S32: 98951 | T32: COM | U32: 1 | V32: 8 | W32: 6
D33: 98948 | E33: COM | F33: 9 | G33: 98948 | H33: COM | I33: 7 | J33: 98948 | K33: RES | L33: 25 | N33: 98953 | O33: COM | R33: 1 | S33: 98951 | T33: RES | U33: 9 | V33: 2
D34: 98948 | E34: RES | F34: 23 | G34: 98948 | H34: RES | I34: 25 | J34: 98951 | K34: COM | L34: 18 | N34: 98953 | O34: RES | P34: 7 | Q34: 6 | R34: 9 | S34: 98952 | T34: RES | V34: 2
D35: 98951 | E35: COM | F35: 17 | G35: 98951 | H35: COM | I35: 18 | J35: 98951 | K35: RES | L35: 30 | N35: 99323 | O35: RES | Q35: 2 | R35: 3 | S35: 98953 | T35: COM | U35: 2
D36: 98951 | E36: RES | F36: 29 | G36: 98951 | H36: RES | I36: 30 | J36: 98952 | K36: RES | L36: 3 | N36: 99324 | O36: RES | P36: 14 | Q36: 8 | R36: 10 | S36: 98953 | T36: RES | U36: 5 | V36: 3
D37: 98952 | E37: RES | F37: 3 | G37: 98952 | H37: RES | I37: 3 | J37: 98953 | K37: COM | L37: 5 | N37: 99328 | O37: COM | R37: 1 | S37: 99323 | T37: COM | U37: 1
D38: 98953 | E38: COM | F38: 3 | G38: 98953 | H38: COM | I38: 4 | J38: 98953 | K38: RES | L38: 12 | N38: 99328 | O38: RES | P38: 7 | Q38: 9 | R38: 4 | S38: 99323 | T38: RES | U38: 2
D39: 98953 | E39: RES | F39: 13 | G39: 98953 | H39: RES | I39: 12 | J39: 99323 | K39: COM | L39: 2 | N39: 99347 | O39: RES | P39: 2 | Q39: 4 | R39: 4 | S39: 99324 | T39: RES | U39: 8 | W39: 7
D40: 99323 | E40: COM | F40: 2 | G40: 99323 | H40: COM | I40: 2 | J40: 99323 | K40: RES | L40: 3 | N40: 99360 | O40: COM | R40: 1 | S40: 99328 | T40: COM | U40: 1 | V40: 2
D41: 99323 | E41: RES | F41: 2 | G41: 99323 | H41: RES | I41: 3 | J41: 99324 | K41: RES | L41: 14 | N41: 99360 | O41: RES | P41: 1 | Q41: 2 | S41: 99328 | T41: RES | U41: 1 | V41: 7
D42: 99324 | E42: RES | F42: 12 | G42: 99324 | H42: RES | I42: 13 | J42: 99328 | K42: COM | L42: 2 | N42: 99361 | O42: RES | Q42: 4 | R42: 1 | S42: 99347 | T42: COM | U42: 2
D43: 99328 | E43: COM | F43: 2 | G43: 99328 | H43: COM | I43: 1 | J43: 99328 | K43: RES | L43: 8 | N43: 99362 | O43: COM | P43: 4 | Q43: 2 | R43: 1 | S43: 99347 | T43: RES | V43: 2
D44: 99328 | E44: RES | F44: 10 | G44: 99328 | H44: RES | I44: 9 | J44: 99347 | K44: COM | L44: 2 | N44: 99362 | O44: RES | P44: 69 | Q44: 47 | R44: 44 | S44: 99360 | T44: COM
D45: 99347 | E45: COM | F45: 2 | G45: 99347 | H45: COM | I45: 2 | J45: 99347 | K45: RES | L45: 5 | N45: 99363 | O45: RES | P45: 1 | S45: 99360 | T45: RES
D46: 99347 | E46: RES | F46: 5 | G46: 99347 | H46: RES | I46: 5 | J46: 99360 | K46: COM | L46: 5 | S46: 99361 | T46: RES | U46: 3
D47: 99360 | E47: COM | F47: 4 | G47: 99360 | H47: COM | I47: 6 | J47: 99361 | K47: COM | L47: 1 | S47: 99362 | T47: COM | U47: 3 | V47: 2 | W47: 8
D48: 99361 | E48: COM | F48: 1 | G48: 99361 | H48: COM | I48: 1 | J48: 99361 | K48: RES | L48: 3 | S48: 99362 | T48: RES | U48: 21 | V48: 14 | W48: 29
D49: 99361 | E49: RES | F49: 3 | G49: 99361 | H49: RES | I49: 3 | J49: 99362 | K49: COM | L49: 34 | S49: 99363 | T49: RES
D50: 99362 | E50: COM | F50: 32 | G50: 99362 | H50: COM | I50: 35 | J50: 99362 | K50: RES | L50: 69
D51: 99362 | E51: RES | F51: 70 | G51: 99362 | H51: RES | I51: 61

Sheet DEP_WKSHT
A1: Zip Code | B1: CLASS | C1: CountOfConcat Agreement Number | D1: MO | G1: Zip Code | H1: CLASS | I1: CountOfConcat Agreement Number | J1: YRMO | K1: Expr1 | Q1: Sum of CountOfConcat Agreement Number | S1: YRMO | X1: Zip Code | Y1: CLASS | Z1: CountOfConcat Agreement Number | AA1: SumOfAmount | AB1: YRMO | AD1: Sum of CountOfConcat Agreement Number | AF1: YRMO
A2: 98901 | B2: NDEP | C2: 78 | D2: 1 | E2: =VLOOKUP(A2,'6. Deposits 2022_Q2'!$A$3:$A$34,1,FALSE) -> #N/A | G2: 98901 | H2: NDEP | I2: 4 | J2: 202010 | K2: 0 | Q2: CLASS | R2: Zip Code | S2: 202010 | T2: 202011 | U2: 202012 | V2: 20209 | X2: 98901 | Y2: NDEP | Z2: 30 | AA2: 0 | AB2: 10 | AD2: CLASS | AE2: Zip Code | AF2: 10 | AG2: 11 | AH2: 12 | AI2: Grand Total
A3: 98902 | B3: NDEP | C3: 97 | D3: 1 | E3: =VLOOKUP(A3,'6. Deposits 2022_Q2'!$A$3:$A$34,1,FALSE) -> #N/A | G3: 98901 | H3: NDEP | I3: 9 | J3: 202011 | K3: 0 | Q3: NDEP | R3: 98901 | S3: 4 | T3: 9 | U3: 2 | V3: 6 | X3: 98901 | Y3: NDEP | Z3: 16 | AA3: 0 | AB3: 11 | AD3: NDEP | AE3: 98901 | AF3: 30 | AG3: 16 | AH3: 20 | AI3: 66
A4: 98903 | B4: NDEP | C4: 47 | D4: 1 | E4: =VLOOKUP(A4,'6. Deposits 2022_Q2'!$A$3:$A$34,1,FALSE) -> #N/A | G4: 98901 | H4: NDEP | I4: 2 | J4: 202012 | K4: 0 | Q4: NDEP | R4: 98902 | S4: 8 | T4: 2 | U4: 2 | V4: 5 | X4: 98901 | Y4: NDEP | Z4: 20 | AA4: 0 | AB4: 12 | AD4: NDEP | AE4: 98902 | AF4: 24 | AG4: 22 | AH4: 32 | AI4: 78
A5: 98908 | B5: NDEP | C5: 35 | D5: 1 | E5: =VLOOKUP(A5,'6. Deposits 2022_Q2'!$A$3:$A$34,1,FALSE) -> #N/A | G5: 98901 | H5: NDEP | I5: 6 | J5: 20209 | K5: 0 | Q5: NDEP | R5: 98903 | S5: 2 | T5: 2 | V5: 4 | X5: 98901 | Y5: RDEP | Z5: 344 | AA5: 0 | AB5: 10 | AD5: NDEP | AE5: 98903 | AF5: 12 | AG5: 6 | AH5: 8 | AI5: 26
A6: 98920 | B6: NDEP | C6: 2 | D6: 1 | E6: =VLOOKUP(A6,'6. Deposits 2022_Q2'!$A$3:$A$34,1,FALSE) -> #N/A | G6: 98901 | H6: RDEP | I6: 99 | J6: 202010 | K6: 0 | Q6: NDEP | R6: 98908 | T6: 5 | X6: 98901 | Y6: RDEP | Z6: 358 | AA6: 0 | AB6: 11 | AD6: NDEP | AE6: 98908 | AF6: 8 | AG6: 18 | AH6: 12 | AI6: 38
A7: 98921 | B7: NDEP | C7: 2 | D7: 1 | E7: =VLOOKUP(A7,'6. Deposits 2022_Q2'!$A$3:$A$34,1,FALSE) -> #N/A | G7: 98901 | H7: RDEP | I7: 70 | J7: 202011 | K7: 0 | Q7: NDEP | R7: 98930 | S7: 3 | X7: 98901 | Y7: RDEP | Z7: 398 | AA7: 0 | AB7: 12 | AD7: NDEP | AE7: 98920 | AH7: 2 | AI7: 2
A8: 98930 | B8: NDEP | C8: 24 | D8: 1 | E8: =VLOOKUP(A8,'6. Deposits 2022_Q2'!$A$3:$A$34,1,FALSE) -> #N/A | G8: 98901 | H8: RDEP | I8: 26 | J8: 202012 | K8: 0 | Q8: NDEP | R8: 98937 | T8: 3 | U8: 2 | X8: 98902 | Y8: NDEP | Z8: 24 | AA8: 0 | AB8: 10 | AD8: NDEP | AE8: 98930 | AF8: 8 | AG8: 8 | AH8: 4 | AI8: 20
A9: 98932 | B9: NDEP | C9: 7 | D9: 1 | E9: =VLOOKUP(A9,'6. Deposits 2022_Q2'!$A$3:$A$34,1,FALSE) -> #N/A | G9: 98901 | H9: RDEP | I9: 109 | J9: 20209 | K9: 0 | Q9: NDEP | R9: 98942 | S9: 2 | V9: 1 | X9: 98902 | Y9: NDEP | Z9: 22 | AA9: 0 | AB9: 11 | AD9: NDEP | AE9: 98932 | AF9: 2 | AI9: 2
A10: 98933 | B10: NDEP | C10: 3 | D10: 1 | E10: =VLOOKUP(A10,'6. Deposits 2022_Q2'!$A$3:$A$34,1,FALSE) -> #N/A | G10: 98902 | H10: NDEP | I10: 8 | J10: 202010 | K10: 0 | Q10: NDEP | R10: 98944 | S10: 17 | U10: 6 | V10: 2 | X10: 98902 | Y10: NDEP | Z10: 32 | AA10: 0 | AB10: 12 | AD10: NDEP | AE10: 98933 | AF10: 2 | AG10: 4 | AH10: 2 | AI10: 8
A11: 98935 | B11: NDEP | C11: 4 | D11: 1 | E11: =VLOOKUP(A11,'6. Deposits 2022_Q2'!$A$3:$A$34,1,FALSE) -> #N/A | G11: 98902 | H11: NDEP | I11: 2 | J11: 202011 | K11: 0 | Q11: NDEP | R11: 98948 | S11: 2 | X11: 98902 | Y11: RDEP | Z11: 502 | AA11: 0 | AB11: 10 | AD11: NDEP | AE11: 98935 | AF11: 4 | AI11: 4
A12: 98936 | B12: NDEP | C12: 21 | D12: 1 | E12: =VLOOKUP(A12,'6. Deposits 2022_Q2'!$A$3:$A$34,1,FALSE) -> #N/A | G12: 98902 | H12: NDEP | I12: 2 | J12: 202012 | K12: 0 | Q12: NDEP | R12: 98951 | S12: 2 | T12: 2 | U12: 2 | X12: 98902 | Y12: RDEP | Z12: 510 | AA12: 0 | AB12: 11 | AD12: NDEP | AE12: 98936 | AF12: 4 | AG12: 2 | AH12: 24 | AI12: 30
A13: 98937 | B13: NDEP | C13: 10 | D13: 1 | E13: =VLOOKUP(A13,'6. Deposits 2022_Q2'!$A$3:$A$34,1,FALSE) -> #N/A | G13: 98902 | H13: NDEP | I13: 5 | J13: 20209 | K13: 0 | Q13: NDEP | R13: 99324 | T13: 2 | X13: 98902 | Y13: RDEP | Z13: 784 | AA13: 0 | AB13: 12 | AD13: NDEP | AE13: 98937 | AG13: 6 | AH13: 2 | AI13: 8
A14: 98938 | B14: NDEP | C14: 1 | D14: 1 | E14: =VLOOKUP(A14,'6. Deposits 2022_Q2'!$A$3:$A$34,1,FALSE) -> #N/A | G14: 98902 | H14: RDEP | I14: 163 | J14: 202010 | K14: 0 | Q14: NDEP | R14: 99328 | V14: 1 | X14: 98903 | Y14: NDEP | Z14: 12 | AA14: 0 | AB14: 10 | AD14: NDEP | AE14: 98942 | AF14: 8 | AG14: 14 | AH14: 4 | AI14: 26
A15: 98942 | B15: NDEP | C15: 18 | D15: 1 | E15: =VLOOKUP(A15,'6. Deposits 2022_Q2'!$A$3:$A$34,1,FALSE) -> #N/A | G15: 98902 | H15: RDEP | I15: 98 | J15: 202011 | K15: 0 | Q15: NDEP | R15: 99347 | S15: 2 | T15: 2 | X15: 98903 | Y15: NDEP | Z15: 6 | AA15: 0 | AB15: 11 | AD15: NDEP | AE15: 98944 | AF15: 12 | AG15: 26 | AH15: 18 | AI15: 56
A16: 98944 | B16: NDEP | C16: 61 | D16: 1 | E16: =VLOOKUP(A16,'6. Deposits 2022_Q2'!$A$3:$A$34,1,FALSE) -> #N/A | G16: 98902 | H16: RDEP | I16: 53 | J16: 202012 | K16: 0 | Q16: NDEP | R16: 99360 | T16: 2 | X16: 98903 | Y16: NDEP | Z16: 8 | AA16: 0 | AB16: 12 | AD16: NDEP | AE16: 98948 | AF16: 6 | AG16: 2 | AH16: 10 | AI16: 18
A17: 98947 | B17: NDEP | C17: 1 | D17: 1 | E17: =VLOOKUP(A17,'6. Deposits 2022_Q2'!$A$3:$A$34,1,FALSE) -> #N/A | G17: 98902 | H17: RDEP | I17: 127 | J17: 20209 | K17: 0 | Q17: NDEP | R17: 99361 | S17: 2 | V17: 1 | X17: 98903 | Y17: RDEP | Z17: 130 | AA17: 0 | AB17: 10 | AD17: NDEP | AE17: 98951 | AF17: 2 | AG17: 4 | AH17: 16 | AI17: 22
A18: 98948 | B18: NDEP | C18: 29 | D18: 1 | E18: =VLOOKUP(A18,'6. Deposits 2022_Q2'!$A$3:$A$34,1,FALSE) -> #N/A | G18: 98903 | H18: NDEP | I18: 2 | J18: 202010 | K18: 0 | Q18: NDEP | R18: 99362 | S18: 4 | T18: 8 | U18: 3 | V18: 8 | X18: 98903 | Y18: RDEP | Z18: 84 | AA18: 0 | AB18: 11 | AD18: NDEP | AE18: 98952 | AH18: 4 | AI18: 4
A19: 98951 | B19: NDEP | C19: 36 | D19: 1 | E19: =VLOOKUP(A19,'6. Deposits 2022_Q2'!$A$3:$A$34,1,FALSE) -> #N/A | G19: 98903 | H19: NDEP | I19: 2 | J19: 202011 | K19: 0 | Q19: NDEP | R19: 99363 | S19: 1 | X19: 98903 | Y19: RDEP | Z19: 130 | AA19: 0 | AB19: 12 | AD19: NDEP | AE19: 98953 | AF19: 2 | AG19: 2 | AH19: 4 | AI19: 8
A20: 98952 | B20: NDEP | C20: 1 | D20: 1 | E20: =VLOOKUP(A20,'6. Deposits 2022_Q2'!$A$3:$A$34,1,FALSE) -> #N/A | G20: 98903 | H20: NDEP | I20: 4 | J20: 20209 | K20: 0 | Q20: RDEP | R20: 98901 | S20: 99 | T20: 70 | U20: 26 | V20: 109 | X20: 98908 | Y20: NDEP | Z20: 8 | AA20: 0 | AB20: 10 | AD20: NDEP | AE20: 99323 | AH20: 2 | AI20: 2
A21: 98953 | B21: NDEP | C21: 10 | D21: 1 | E21: =VLOOKUP(A21,'6. Deposits 2022_Q2'!$A$3:$A$34,1,FALSE) -> #N/A | G21: 98903 | H21: RDEP | I21: 27 | J21: 202010 | K21: 0 | Q21: RDEP | R21: 98902 | S21: 163 | T21: 98 | U21: 53 | V21: 127 | X21: 98908 | Y21: NDEP | Z21: 18 | AA21: 0 | AB21: 11 | AD21: NDEP | AE21: 99324 | AG21: 4 | AH21: 2 | AI21: 6
A22: 99323 | B22: NDEP | C22: 1 | D22: 1 | E22: =VLOOKUP(A22,'6. Deposits 2022_Q2'!$A$3:$A$34,1,FALSE) -> #N/A | G22: 98903 | H22: RDEP | I22: 5 | J22: 202011 | K22: 0 | Q22: RDEP | R22: 98903 | S22: 27 | T22: 5 | U22: 12 | V22: 26 | X22: 98908 | Y22: NDEP | Z22: 12 | AA22: 0 | AB22: 12 | AD22: NDEP | AE22: 99328 | AF22: 2 | AH22: 2 | AI22: 4
A23: 99324 | B23: NDEP | C23: 4 | D23: 1 | E23: =VLOOKUP(A23,'6. Deposits 2022_Q2'!$A$3:$A$34,1,FALSE) -> #N/A | G23: 98903 | H23: RDEP | I23: 12 | J23: 202012 | K23: 0 | Q23: RDEP | R23: 98908 | S23: 136 | T23: 107 | U23: 32 | V23: 123 | X23: 98908 | Y23: RDEP | Z23: 320 | AA23: 0 | AB23: 10 | AD23: NDEP | AE23: 99347 | AG23: 4 | AI23: 4
A24: 99328 | B24: NDEP | C24: 5 | D24: 1 | E24: =VLOOKUP(A24,'6. Deposits 2022_Q2'!$A$3:$A$34,1,FALSE) -> #N/A | G24: 98903 | H24: RDEP | I24: 26 | J24: 20209 | K24: 0 | Q24: RDEP | R24: 98921 | S24: 7 | T24: 4 | V24: 4 | X24: 98908 | Y24: RDEP | Z24: 450 | AA24: 0 | AB24: 11 | AD24: NDEP | AE24: 99360 | AG24: 4 | AH24: 2 | AI24: 6
A25: 99329 | B25: NDEP | C25: 1 | D25: 1 | E25: =VLOOKUP(A25,'6. Deposits 2022_Q2'!$A$3:$A$34,1,FALSE) -> #N/A | G25: 98908 | H25: NDEP | I25: 5 | J25: 202011 | K25: 0 | Q25: RDEP | R25: 98923 | S25: 3 | T25: 2 | U25: 1 | V25: 2 | X25: 98908 | Y25: RDEP | Z25: 350 | AA25: 0 | AB25: 12 | AD25: NDEP | AE25: 99361 | AH25: 6 | AI25: 6
A26: 99347 | B26: NDEP | C26: 3 | D26: 1 | E26: =VLOOKUP(A26,'6. Deposits 2022_Q2'!$A$3:$A$34,1,FALSE) -> #N/A | G26: 98908 | H26: RDEP | I26: 136 | J26: 202010 | K26: 0 | Q26: RDEP | R26: 98930 | S26: 29 | T26: 10 | U26: 18 | V26: 15 | X26: 98920 | Y26: NDEP | Z26: 2 | AA26: 0 | AB26: 12 | AD26: NDEP | AE26: 99362 | AF26: 18 | AG26: 20 | AH26: 16 | AI26: 54
A27: 99360 | B27: NDEP | C27: 3 | D27: 1 | E27: =VLOOKUP(A27,'6. Deposits 2022_Q2'!$A$3:$A$34,1,FALSE) -> #N/A | G27: 98908 | H27: RDEP | I27: 107 | J27: 202011 | K27: 0 | Q27: RDEP | R27: 98932 | S27: 7 | T27: 17 | U27: 8 | V27: 7 | X27: 98921 | Y27: RDEP | Z27: 6 | AA27: 0 | AB27: 10 | AD27: RDEP | AE27: 98901 | AF27: 344 | AG27: 358 | AH27: 398 | AI27: 1100
A28: 99361 | B28: NDEP | C28: 6 | D28: 1 | E28: =VLOOKUP(A28,'6. Deposits 2022_Q2'!$A$3:$A$34,1,FALSE) -> #N/A | G28: 98908 | H28: RDEP | I28: 32 | J28: 202012 | K28: 0 | Q28: RDEP | R28: 98933 | S28: 3 | T28: 3 | U28: 3 | V28: 1 | X28: 98921 | Y28: RDEP | Z28: 18 | AA28: 0 | AB28: 11 | AD28: RDEP | AE28: 98902 | AF28: 502 | AG28: 510 | AH28: 784 | AI28: 1796
A29: 99362 | B29: NDEP | C29: 62 | D29: 1 | E29: =VLOOKUP(A29,'6. Deposits 2022_Q2'!$A$3:$A$34,1,FALSE) -> #N/A | G29: 98908 | H29: RDEP | I29: 123 | J29: 20209 | K29: 0 | Q29: RDEP | R29: 98935 | S29: 5 | T29: 6 | U29: 2 | V29: 4 | X29: 98921 | Y29: RDEP | Z29: 14 | AA29: 0 | AB29: 12 | AD29: RDEP | AE29: 98903 | AF29: 130 | AG29: 84 | AH29: 130 | AI29: 344
A30: 99363 | B30: NDEP | C30: 1 | D30: 1 | E30: =VLOOKUP(A30,'6. Deposits 2022_Q2'!$A$3:$A$34,1,FALSE) -> #N/A | G30: 98921 | H30: RDEP | I30: 7 | J30: 202010 | K30: 0 | Q30: RDEP | R30: 98936 | S30: 6 | T30: 10 | U30: 6 | V30: 5 | X30: 98923 | Y30: RDEP | Z30: 4 | AA30: 0 | AB30: 10 | AD30: RDEP | AE30: 98908 | AF30: 320 | AG30: 450 | AH30: 350 | AI30: 1120
A31: 98901 | B31: RDEP | C31: 1427 | D31: 1 | E31: =VLOOKUP(A31,'6. Deposits 2022_Q2'!$A$35:$A$61,1,FALSE) -> #N/A | G31: 98921 | H31: RDEP | I31: 4 | J31: 202011 | K31: 0 | Q31: RDEP | R31: 98937 | S31: 9 | T31: 2 | U31: 3 | V31: 7 | X31: 98923 | Y31: RDEP | Z31: 4 | AA31: 0 | AB31: 11 | AD31: RDEP | AE31: 98921 | AF31: 6 | AG31: 18 | AH31: 14 | AI31: 38
A32: 98902 | B32: RDEP | C32: 1838 | D32: 1 | E32: =VLOOKUP(A32,'6. Deposits 2022_Q2'!$A$35:$A$61,1,FALSE) -> #N/A | G32: 98921 | H32: RDEP | I32: 4 | J32: 20209 | K32: 0 | Q32: RDEP | R32: 98938 | S32: 1 | U32: 4 | X32: 98923 | Y32: RDEP | Z32: 16 | AA32: 0 | AB32: 12 | AD32: RDEP | AE32: 98923 | AF32: 4 | AG32: 4 | AH32: 16 | AI32: 24
A33: 98903 | B33: RDEP | C33: 403 | D33: 1 | E33: =VLOOKUP(A33,'6. Deposits 2022_Q2'!$A$35:$A$61,1,FALSE) -> #N/A | G33: 98923 | H33: RDEP | I33: 3 | J33: 202010 | K33: 0 | Q33: RDEP | R33: 98939 | U33: 1 | X33: 98930 | Y33: NDEP | Z33: 8 | AA33: 0 | AB33: 10 | AD33: RDEP | AE33: 98930 | AF33: 90 | AG33: 74 | AH33: 120 | AI33: 284
A34: 98908 | B34: RDEP | C34: 1026 | D34: 1 | E34: =VLOOKUP(A34,'6. Deposits 2022_Q2'!$A$35:$A$61,1,FALSE) -> #N/A | G34: 98923 | H34: RDEP | I34: 2 | J34: 202011 | K34: 0 | Q34: RDEP | R34: 98942 | S34: 42 | T34: 27 | U34: 12 | V34: 36 | X34: 98930 | Y34: NDEP | Z34: 8 | AA34: 0 | AB34: 11 | AD34: RDEP | AE34: 98932 | AF34: 30 | AG34: 72 | AH34: 62 | AI34: 164
A35: 98921 | B35: RDEP | C35: 31 | D35: 1 | E35: =VLOOKUP(A35,'6. Deposits 2022_Q2'!$A$35:$A$61,1,FALSE) -> #N/A | G35: 98923 | H35: RDEP | I35: 1 | J35: 202012 | K35: 0 | Q35: RDEP | R35: 98944 | S35: 23 | T35: 30 | U35: 15 | V35: 31 | X35: 98930 | Y35: NDEP | Z35: 4 | AA35: 0 | AB35: 12 | AD35: RDEP | AE35: 98933 | AF35: 4 | AG35: 4 | AH35: 14 | AI35: 22
A36: 98923 | B36: RDEP | C36: 30 | D36: 1 | E36: =VLOOKUP(A36,'6. Deposits 2022_Q2'!$A$35:$A$61,1,FALSE) -> #N/A | G36: 98923 | H36: RDEP | I36: 2 | J36: 20209 | K36: 0 | Q36: RDEP | R36: 98947 | S36: 4 | T36: 2 | U36: 3 | V36: 1 | X36: 98930 | Y36: RDEP | Z36: 90 | AA36: 0 | AB36: 10 | AD36: RDEP | AE36: 98935 | AF36: 30 | AG36: 16 | AH36: 36 | AI36: 82
A37: 98930 | B37: RDEP | C37: 336 | D37: 1 | E37: =VLOOKUP(A37,'6. Deposits 2022_Q2'!$A$35:$A$61,1,FALSE) -> #N/A | G37: 98930 | H37: NDEP | I37: 3 | J37: 202010 | K37: 0 | Q37: RDEP | R37: 98948 | S37: 24 | T37: 4 | U37: 4 | V37: 10 | X37: 98930 | Y37: RDEP | Z37: 74 | AA37: 0 | AB37: 11 | AD37: RDEP | AE37: 98936 | AF37: 38 | AG37: 26 | AH37: 80 | AI37: 144
A38: 98932 | B38: RDEP | C38: 165 | D38: 1 | E38: =VLOOKUP(A38,'6. Deposits 2022_Q2'!$A$35:$A$61,1,FALSE) -> #N/A | G38: 98930 | H38: RDEP | I38: 29 | J38: 202010 | K38: 0 | Q38: RDEP | R38: 98951 | S38: 16 | T38: 12 | U38: 8 | V38: 10 | X38: 98930 | Y38: RDEP | Z38: 120 | AA38: 0 | AB38: 12 | AD38: RDEP | AE38: 98937 | AF38: 20 | AG38: 30 | AH38: 38 | AI38: 88
A39: 98933 | B39: RDEP | C39: 24 | D39: 1 | E39: =VLOOKUP(A39,'6. Deposits 2022_Q2'!$A$35:$A$61,1,FALSE) -> #N/A | G39: 98930 | H39: RDEP | I39: 10 | J39: 202011 | K39: 0 | Q39: RDEP | R39: 98952 | S39: 1 | U39: 1 | X39: 98932 | Y39: NDEP | Z39: 2 | AA39: 0 | AB39: 10 | AD39: RDEP | AE39: 98938 | AF39: 24 | AG39: 14 | AH39: 40 | AI39: 78
A40: 98935 | B40: RDEP | C40: 85 | D40: 1 | E40: =VLOOKUP(A40,'6. Deposits 2022_Q2'!$A$35:$A$61,1,FALSE) -> #N/A | G40: 98930 | H40: RDEP | I40: 18 | J40: 202012 | K40: 0 | Q40: RDEP | R40: 98953 | S40: 7 | T40: 9 | V40: 10 | X40: 98932 | Y40: RDEP | Z40: 30 | AA40: 0 | AB40: 10 | AD40: RDEP | AE40: 98939 | AF40: 4 | AG40: 4 | AH40: 2 | AI40: 10
A41: 98936 | B41: RDEP | C41: 130 | D41: 1 | E41: =VLOOKUP(A41,'6. Deposits 2022_Q2'!$A$35:$A$61,1,FALSE) -> #N/A | G41: 98930 | H41: RDEP | I41: 15 | J41: 20209 | K41: 0 | Q41: RDEP | R41: 99323 | U41: 2 | V41: 2 | X41: 98932 | Y41: RDEP | Z41: 72 | AA41: 0 | AB41: 11 | AD41: RDEP | AE41: 98942 | AF41: 114 | AG41: 190 | AH41: 106 | AI41: 410
A42: 98937 | B42: RDEP | C42: 85 | D42: 1 | E42: =VLOOKUP(A42,'6. Deposits 2022_Q2'!$A$35:$A$61,1,FALSE) -> #N/A | G42: 98932 | H42: RDEP | I42: 7 | J42: 202010 | K42: 0 | Q42: RDEP | R42: 99324 | S42: 29 | T42: 17 | U42: 4 | V42: 67 | X42: 98932 | Y42: RDEP | Z42: 62 | AA42: 0 | AB42: 12 | AD42: RDEP | AE42: 98944 | AF42: 100 | AG42: 182 | AH42: 230 | AI42: 512
A43: 98938 | B43: RDEP | C43: 51 | D43: 1 | E43: =VLOOKUP(A43,'6. Deposits 2022_Q2'!$A$35:$A$61,1,FALSE) -> #N/A | G43: 98932 | H43: RDEP | I43: 17 | J43: 202011 | K43: 0 | Q43: RDEP | R43: 99328 | S43: 11 | T43: 6 | U43: 7 | V43: 8 | X43: 98933 | Y43: NDEP | Z43: 2 | AA43: 0 | AB43: 10 | AD43: RDEP | AE43: 98947 | AF43: 22 | AG43: 26 | AH43: 28 | AI43: 76
A44: 98939 | B44: RDEP | C44: 8 | D44: 1 | E44: =VLOOKUP(A44,'6. Deposits 2022_Q2'!$A$35:$A$61,1,FALSE) -> #N/A | G44: 98932 | H44: RDEP | I44: 8 | J44: 202012 | K44: 0 | Q44: RDEP | R44: 99329 | U44: 1 | X44: 98933 | Y44: NDEP | Z44: 4 | AA44: 0 | AB44: 11 | AD44: RDEP | AE44: 98948 | AF44: 60 | AG44: 84 | AH44: 162 | AI44: 306
A45: 98942 | B45: RDEP | C45: 446 | D45: 1 | E45: =VLOOKUP(A45,'6. Deposits 2022_Q2'!$A$35:$A$61,1,FALSE) -> #N/A | G45: 98932 | H45: RDEP | I45: 7 | J45: 20209 | K45: 0 | Q45: RDEP | R45: 99347 | S45: 4 | V45: 6 | X45: 98933 | Y45: NDEP | Z45: 2 | AA45: 0 | AB45: 12 | AD45: RDEP | AE45: 98951 | AF45: 86 | AG45: 82 | AH45: 154 | AI45: 322
A46: 98944 | B46: RDEP | C46: 535 | D46: 1 | E46: =VLOOKUP(A46,'6. Deposits 2022_Q2'!$A$35:$A$61,1,FALSE) -> #N/A | G46: 98933 | H46: RDEP | I46: 3 | J46: 202010 | K46: 0 | Q46: RDEP | R46: 99348 | S46: 2 | V46: 1 | X46: 98933 | Y46: RDEP | Z46: 4 | AA46: 0 | AB46: 10 | AD46: RDEP | AE46: 98952 | AF46: 6 | AG46: 2 | AH46: 22 | AI46: 30
A47: 98947 | B47: RDEP | C47: 69 | D47: 1 | E47: =VLOOKUP(A47,'6. Deposits 2022_Q2'!$A$35:$A$61,1,FALSE) -> #N/A | G47: 98933 | H47: RDEP | I47: 3 | J47: 202011 | K47: 0 | Q47: RDEP | R47: 99360 | T47: 2 | X47: 98933 | Y47: RDEP | Z47: 4 | AA47: 0 | AB47: 11 | AD47: RDEP | AE47: 98953 | AF47: 62 | AG47: 58 | AH47: 62 | AI47: 182
A48: 98948 | B48: RDEP | C48: 308 | D48: 1 | E48: =VLOOKUP(A48,'6. Deposits 2022_Q2'!$A$35:$A$61,1,FALSE) -> #N/A | G48: 98933 | H48: RDEP | I48: 3 | J48: 202012 | K48: 0 | Q48: RDEP | R48: 99361 | S48: 3 | U48: 2 | V48: 1 | X48: 98933 | Y48: RDEP | Z48: 14 | AA48: 0 | AB48: 12 | AD48: RDEP | AE48: 99323 | AF48: 6 | AG48: 18 | AH48: 6 | AI48: 30
A49: 98951 | B49: RDEP | C49: 351 | D49: 1 | E49: =VLOOKUP(A49,'6. Deposits 2022_Q2'!$A$35:$A$61,1,FALSE) -> #N/A | G49: 98933 | H49: RDEP | I49: 1 | J49: 20209 | K49: 0 | Q49: RDEP | R49: 99362 | S49: 85 | T49: 56 | U49: 23 | V49: 112 | X49: 98935 | Y49: NDEP | Z49: 4 | AA49: 0 | AB49: 10 | AD49: RDEP | AE49: 99324 | AF49: 64 | AG49: 102 | AH49: 64 | AI49: 230
A50: 98952 | B50: RDEP | C50: 33 | D50: 1 | E50: =VLOOKUP(A50,'6. Deposits 2022_Q2'!$A$35:$A$61,1,FALSE) -> #N/A | G50: 98935 | H50: RDEP | I50: 5 | J50: 202010 | K50: 0 | Q50: Grand Total | S50: 795 | T50: 536 | U50: 268 | V50: 753 | X50: 98935 | Y50: RDEP | Z50: 30 | AA50: 0 | AB50: 10 | AD50: RDEP | AE50: 99328 | AF50: 20 | AG50: 36 | AH50: 34 | AI50: 90
A51: 98953 | B51: RDEP | C51: 127 | D51: 1 | E51: =VLOOKUP(A51,'6. Deposits 2022_Q2'!$A$35:$A$61,1,FALSE) -> #N/A | G51: 98935 | H51: RDEP | I51: 6 | J51: 202011 | K51: 0 | X51: 98935 | Y51: RDEP | Z51: 16 | AA51: 0 | AB51: 11 | AD51: RDEP | AE51: 99329 | AF51: 2 | AH51: 2 | AI51: 4
A52: 99323 | B52: RDEP | C52: 26 | D52: 1 | E52: =VLOOKUP(A52,'6. Deposits 2022_Q2'!$A$35:$A$61,1,FALSE) -> #N/A | G52: 98935 | H52: RDEP | I52: 2 | J52: 202012 | K52: 0 | X52: 98935 | Y52: RDEP | Z52: 36 | AA52: 0 | AB52: 12 | AD52: RDEP | AE52: 99347 | AF52: 6 | AG52: 10 | AH52: 6 | AI52: 22
A53: 99324 | B53: RDEP | C53: 336 | D53: 1 | E53: =VLOOKUP(A53,'6. Deposits 2022_Q2'!$A$35:$A$61,1,FALSE) -> #N/A | G53: 98935 | H53: RDEP | I53: 4 | J53: 20209 | K53: 0 | X53: 98936 | Y53: NDEP | Z53: 4 | AA53: 0 | AB53: 10 | AD53: RDEP | AE53: 99348 | AG53: 4 | AH53: 2 | AI53: 6
A54: 99328 | B54: RDEP | C54: 97 | D54: 1 | E54: =VLOOKUP(A54,'6. Deposits 2022_Q2'!$A$35:$A$61,1,FALSE) -> #N/A | G54: 98936 | H54: RDEP | I54: 6 | J54: 202010 | K54: 0 | X54: 98936 | Y54: NDEP | Z54: 2 | AA54: 0 | AB54: 11 | AD54: RDEP | AE54: 99360 | AF54: 2 | AG54: 2 | AH54: 6 | AI54: 10
A55: 99329 | B55: RDEP | C55: 2 | D55: 1 | E55: =VLOOKUP(A55,'6. Deposits 2022_Q2'!$A$35:$A$61,1,FALSE) -> #N/A | G55: 98936 | H55: RDEP | I55: 10 | J55: 202011 | K55: 0 | X55: 98936 | Y55: NDEP | Z55: 24 | AA55: 0 | AB55: 12 | AD55: RDEP | AE55: 99361 | AF55: 6 | AH55: 24 | AI55: 30
A56: 99347 | B56: RDEP | C56: 45 | D56: 1 | E56: =VLOOKUP(A56,'6. Deposits 2022_Q2'!$A$35:$A$61,1,FALSE) -> #N/A | G56: 98936 | H56: RDEP | I56: 6 | J56: 202012 | K56: 0 | X56: 98936 | Y56: RDEP | Z56: 38 | AA56: 0 | AB56: 10 | AD56: RDEP | AE56: 99362 | AF56: 394 | AG56: 308 | AH56: 342 | AI56: 1044
A57: 99348 | B57: RDEP | C57: 12 | D57: 1 | E57: =VLOOKUP(A57,'6. Deposits 2022_Q2'!$A$35:$A$61,1,FALSE) -> #N/A | G57: 98936 | H57: RDEP | I57: 5 | J57: 20209 | K57: 0 | X57: 98936 | Y57: RDEP | Z57: 26 | AA57: 0 | AB57: 11 | AD57: RDEP | AE57: 99363 | AF57: 4 | AH57: 2 | AI57: 6
A58: 99350 | B58: RDEP | C58: 3 | D58: 1 | E58: =VLOOKUP(A58,'6. Deposits 2022_Q2'!$A$35:$A$61,1,FALSE) -> #N/A | G58: 98937 | H58: NDEP | I58: 3 | J58: 202011 | K58: 0 | X58: 98936 | Y58: RDEP | Z58: 80 | AA58: 0 | AB58: 12 | AD58: Grand Total | AF58: 2644 | AG58: 2930 | AH58: 3528 | AI58: 9102
A59: 99360 | B59: RDEP | C59: 11 | D59: 1 | E59: =VLOOKUP(A59,'6. Deposits 2022_Q2'!$A$35:$A$61,1,FALSE) -> #N/A | G59: 98937 | H59: NDEP | I59: 2 | J59: 202012 | K59: 0 | X59: 98937 | Y59: NDEP | Z59: 6 | AA59: 0 | AB59: 11
A60: 99361 | B60: RDEP | C60: 31 | D60: 1 | E60: =VLOOKUP(A60,'6. Deposits 2022_Q2'!$A$35:$A$61,1,FALSE) -> #N/A | G60: 98937 | H60: RDEP | I60: 9 | J60: 202010 | K60: 0 | X60: 98937 | Y60: NDEP | Z60: 2 | AA60: 0 | AB60: 12
A61: 99362 | B61: RDEP | C61: 1179 | D61: 1 | E61: =VLOOKUP(A61,'6. Deposits 2022_Q2'!$A$35:$A$61,1,FALSE) -> #N/A | G61: 98937 | H61: RDEP | I61: 2 | J61: 202011 | K61: 0 | X61: 98937 | Y61: RDEP | Z61: 20 | AA61: 0 | AB61: 10
A62: 99363 | B62: RDEP | C62: 3 | D62: 1 | E62: =VLOOKUP(A62,'6. Deposits 2022_Q2'!$A$35:$A$61,1,FALSE) -> #N/A | G62: 98937 | H62: RDEP | I62: 3 | J62: 202012 | K62: 0 | X62: 98937 | Y62: RDEP | Z62: 30 | AA62: 0 | AB62: 11
G63: 98937 | H63: RDEP | I63: 7 | J63: 20209 | K63: 0 | X63: 98937 | Y63: RDEP | Z63: 38 | AA63: 0 | AB63: 12
G64: 98938 | H64: RDEP | I64: 1 | J64: 202010 | K64: 0 | X64: 98938 | Y64: RDEP | Z64: 24 | AA64: 0 | AB64: 10
G65: 98938 | H65: RDEP | I65: 4 | J65: 202012 | K65: 0 | X65: 98938 | Y65: RDEP | Z65: 14 | AA65: 0 | AB65: 11
G66: 98939 | H66: RDEP | I66: 1 | J66: 202012 | K66: 0 | X66: 98938 | Y66: RDEP | Z66: 40 | AA66: 0 | AB66: 12
G67: 98942 | H67: NDEP | I67: 2 | J67: 202010 | K67: 0 | X67: 98939 | Y67: RDEP | Z67: 4 | AA67: 0 | AB67: 10
G68: 98942 | H68: NDEP | I68: 1 | J68: 20209 | K68: 0 | X68: 98939 | Y68: RDEP | Z68: 4 | AA68: 0 | AB68: 11
G69: 98942 | H69: RDEP | I69: 42 | J69: 202010 | K69: 0 | X69: 98939 | Y69: RDEP | Z69: 2 | AA69: 0 | AB69: 12
G70: 98942 | H70: RDEP | I70: 27 | J70: 202011 | K70: 0 | X70: 98942 | Y70: NDEP | Z70: 8 | AA70: 0 | AB70: 10
G71: 98942 | H71: RDEP | I71: 12 | J71: 202012 | K71: 0 | X71: 98942 | Y71: NDEP | Z71: 14 | AA71: 0 | AB71: 11
G72: 98942 | H72: RDEP | I72: 36 | J72: 20209 | K72: 0 | X72: 98942 | Y72: NDEP | Z72: 4 | AA72: 0 | AB72: 12
G73: 98944 | H73: NDEP | I73: 17 | J73: 202010 | K73: 0 | X73: 98942 | Y73: RDEP | Z73: 114 | AA73: 0 | AB73: 10
G74: 98944 | H74: NDEP | I74: 6 | J74: 202012 | K74: 0 | X74: 98942 | Y74: RDEP | Z74: 190 | AA74: 0 | AB74: 11
... G135: 99363 | H135: NDEP | I135: 1 | J135: 202010 | K135: 0 | X135: 99361 | Y135: RDEP | Z135: 6 | AA135: 0 | AB135: 10
X136: 99361 | Y136: RDEP | Z136: 24 | AA136: 0 | AB136: 12
X137: 99362 | Y137: NDEP | Z137: 18 | AA137: 0 | AB137: 10
X138: 99362 | Y138: NDEP | Z138: 20 | AA138: 0 | AB138: 11
X139: 99362 | Y139: NDEP | Z139: 16 | AA139: 0 | AB139: 12
X140: 99362 | Y140: RDEP | Z140: 394 | AA140: 0 | AB140: 10
X141: 99362 | Y141: RDEP | Z141: 308 | AA141: 0 | AB141: 11
X142: 99362 | Y142: RDEP | Z142: 342 | AA142: 0 | AB142: 12
X143: 99363 | Y143: RDEP | Z143: 4 | AA143: 0 | AB143: 10
X144: 99363 | Y144: RDEP | Z144: 2 | AA144: 0 | AB144: 12

Sheet 7. Bill Assistance 2022_Q2
A1: Item a) Number of Premises Receiving Bill Assistance or Enrolled in Any Other Assistance Program
A2: 44197 | B2: 44228 | C2: 44256 | D2: ZIP ** | E2: 44287 | F2: 44317 | G2: 44348 | H2: 44378 | I2: 44409 | J2: 44440 | K2: 44470 | L2: 44501 | M2: 44531 | N2: Zip Code | O2: 44652 | P2: Zip Code | Q2: 44682 | R2: Zip Code | S2: 44713
A3: 44 | B3: 89 | C3: 87 | D3: 98901 | E3: 349 | F3: 108 | G3: 51 | N3: 98901 | O3: 1041 | P3: 98901 | Q3: 1032 | R3: 98901 | S3: 1010
A4: 70 | B4: 149 | C4: 107 | D4: 98902 | E4: 411 | F4: 123 | G4: 72 | N4: 98902 | O4: 1331 | P4: 98902 | Q4: 1316 | R4: 98902 | S4: 1305
A5: 24 | B5: 48 | C5: 38 | D5: 98903 | E5: 138 | F5: 31 | G5: 17 | N5: 98903 | O5: 436 | P5: 98903 | Q5: 430 | R5: 98903 | S5: 421
A6: 19 | B6: 33 | C6: 35 | D6: 98908 | E6: 111 | F6: 51 | G6: 23 | N6: 98908 | O6: 432 | P6: 98908 | Q6: 418 | R6: 98908 | S6: 406
A7: 6 | B7: 7 | C7: 7 | D7: 98921 | E7: 22 | F7: 7 | G7: 2 | N7: 98921 | O7: 38 | P7: 98921 | Q7: 39 | R7: 98921 | S7: 38
A8: 1 | B8: 1 | C8: 3 | D8: 98923 | E8: 6 | F8: 3 | G8: 4 | N8: 98923 | O8: 22 | P8: 98923 | Q8: 22 | R8: 98923 | S8: 22
A9: 43 | B9: 35 | C9: 40 | D9: 98930 | E9: 83 | F9: 29 | G9: 31 | N9: 98930 | O9: 343 | P9: 98930 | Q9: 340 | R9: 98930 | S9: 333
A10: 17 | B10: 10 | C10: 12 | D10: 98932 | E10: 38 | F10: 17 | G10: 13 | N10: 98932 | O10: 162 | P10: 98932 | Q10: 162 | R10: 98932 | S10: 158
A11: 2 | B11: 2 | D11: 98933 | E11: 6 | F11: 2 | G11: 1 | N11: 98933 | O11: 13 | P11: 98933 | Q11: 13 | R11: 98933 | S11: 13
A12: 13 | B12: 6 | C12: 5 | D12: 98935 | E12: 30 | F12: 16 | G12: 14 | N12: 98935 | O12: 120 | P12: 98935 | Q12: 121 | R12: 98935 | S12: 120
A13: 6 | B13: 1 | C13: 5 | D13: 98936 | E13: 20 | F13: 3 | G13: 2 | N13: 98936 | O13: 80 | P13: 98936 | Q13: 75 | R13: 98936 | S13: 74
A14: 3 | B14: 3 | C14: 2 | D14: 98937 | E14: 8 | F14: 3 | G14: 2 | N14: 98937 | O14: 42 | P14: 98937 | Q14: 43 | R14: 98937 | S14: 45
A15: 6 | B15: 3 | C15: 5 | D15: 98938 | E15: 12 | F15: 1 | G15: 8 | N15: 98938 | O15: 33 | P15: 98938 | Q15: 33 | R15: 98938 | S15: 33
B16: 1 | C16: 1 | D16: 98939 | E16: 1 | F16: 4 | G16: 1 | N16: 98939 | O16: 10 | P16: 98939 | Q16: 13 | R16: 98939 | S16: 10
A17: 10 | B17: 14 | C17: 8 | D17: 98942 | E17: 49 | F17: 7 | G17: 12 | N17: 98942 | O17: 164 | P17: 98942 | Q17: 161 | R17: 98942 | S17: 157
A18: 79 | B18: 51 | C18: 52 | D18: 98944 | E18: 169 | F18: 45 | G18: 55 | N18: 98944 | O18: 656 | P18: 98944 | Q18: 658 | R18: 98944 | S18: 652
A19: 6 | B19: 7 | C19: 6 | D19: 98947 | E19: 17 | F19: 5 | G19: 8 | N19: 98947 | O19: 75 | P19: 98947 | Q19: 72 | R19: 98947 | S19: 75
A20: 40 | B20: 42 | C20: 31 | D20: 98948 | E20: 178 | F20: 27 | G20: 41 | N20: 98948 | O20: 375 | P20: 98948 | Q20: 372 | R20: 98948 | S20: 353
A21: 34 | B21: 39 | C21: 40 | D21: 98951 | E21: 194 | F21: 27 | G21: 26 | N21: 98951 | O21: 298 | P21: 98951 | Q21: 286 | R21: 98951 | S21: 266
A22: 1 | B22: 3 | C22: 2 | D22: 98952 | E22: 20 | F22: 1 | G22: 2 | N22: 98952 | O22: 9 | P22: 98952 | Q22: 6 | R22: 98952 | S22: 2
A23: 11 | B23: 7 | C23: 6 | D23: 98953 | E23: 23 | F23: 6 | G23: 5 | N23: 98953 | O23: 83 | P23: 98953 | Q23: 83 | R23: 98953 | S23: 81
A24: 3 | B24: 2 | C24: 1 | D24: 99323 | E24: 4 | F24: 2 | G24: 3 | N24: 99323 | O24: 18 | P24: 99323 | Q24: 19 | R24: 99323 | S24: 18
A25: 13 | B25: 20 | C25: 23 | D25: 99324 | E25: 57 | F25: 4 | G25: 11 | N25: 99324 | O25: 126 | P25: 99324 | Q25: 129 | R25: 99324 | S25: 126
A26: 3 | C26: 2 | D26: 99328 | E26: 36 | F26: 2 | G26: 3 | N26: 99328 | O26: 87 | P26: 99328 | Q26: 87 | R26: 99328 | S26: 87
B27: 1 | C27: 1 | D27: 99347 | E27: 15 | F27: 0 | G27: 4 | N27: 99329 | O27: 3 | P27: 99329 | Q27: 3 | R27: 99329 | S27: 3
A28: 4 | B28: 3 | C28: 2 | D28: 99348 | E28: 4 | F28: 0 | G28: 2 | N28: 99347 | O28: 35 | P28: 99347 | Q28: 35 | R28: 99347 | S28: 35
A29: 1 | D29: 99360 | E29: 3 | F29: 0 | G29: 1 | N29: 99348 | O29: 12 | P29: 99348 | Q29: 10 | R29: 99348 | S29: 11
A30: 1 | B30: 1 | D30: 99361 | E30: 8 | F30: 2 | G30: 2 | N30: 99350 | O30: 2 | P30: 99350 | Q30: 2 | R30: 99350 | S30: 2
A31: 6 | B31: 6 | C31: 1 | D31: 99362 | E31: 311 | F31: 46 | G31: 96 | N31: 99360 | O31: 5 | P31: 99360 | Q31: 6 | R31: 99360 | S31: 5
A32: 69 | B32: 81 | C32: 92 | D32: 99363 | E32: 2 | F32: 1 | G32: 0 | N32: 99361 | O32: 20 | P32: 99361 | Q32: 19 | R32: 99361 | S32: 19
D33: 98907 | E33: 0 | F33: 1 | G33: 0 | N33: 99362 | O33: 737 | P33: 99362 | Q33: 725 | R33: 99362 | S33: 716
D34: 98909 | E34: 0 | F34: 1 | G34: 0 | N34: 99363 | O34: 3 | P34: 99363 | Q34: 3 | R34: 99363 | S34: 3
N35: TOTAL | O35: =SUM(O3:O34) -> 6811 | Q35: =SUM(Q3:Q34) -> 6733 | S35: =SUM(S3:S34) -> 6599

Sheet BA_WRKSHT
A1: FLAG | B1: SumOfJAN20 | C1: SumOfFEB20 | D1: SumOfMAR20 | E1: SumOfAPR20 | F1: SumOfMAY20 | G1: SumOfJUN20 | H1: SumOfJUL20 | I1: SumOfAUG20 | J1: SumOfSEP20 | K1: SumOfOCT20 | L1: SumOfNOV20 | M1: SumOfDEC20 | N1: SumOfJAN19 | O1: SumOfFEB19 | P1: SumOfMAR19 | Q1: SumOfAPR19 | R1: SumOfMAY19 | S1: SumOfJUN19 | T1: SumOfJUL19 | U1: SumOfAUG19 | V1: SumOfSEP19 | W1: SumOfOCT19 | X1: SumOfNOV19 | Y1: SumOfDEC19
A2: 98901RES | B2: 37 | C2: 35 | D2: 33 | E2: 31 | F2: 31 | G2: 31 | H2: 30 | I2: 27 | J2: 27 | K2: 27 | L2: 24 | M2: 24 | N2: 23 | O2: 28 | P2: 28 | Q2: 30 | R2: 32 | S2: 33 | T2: 33 | U2: 35 | V2: 36 | W2: 37 | X2: 38 | Y2: 39
A3: 98902RES | B3: 54 | C3: 51 | D3: 48 | E3: 46 | F3: 43 | G3: 41 | H3: 38 | I3: 34 | J3: 33 | K3: 29 | L3: 27 | M3: 24 | N3: 24 | O3: 31 | P3: 34 | Q3: 38 | R3: 39 | S3: 43 | T3: 45 | U3: 47 | V3: 48 | W3: 50 | X3: 51 | Y3: 53
A4: 98903RES | B4: 26 | C4: 26 | D4: 24 | E4: 24 | F4: 23 | G4: 21 | H4: 22 | I4: 23 | J4: 23 | K4: 22 | L4: 22 | M4: 21 | N4: 22 | O4: 23 | P4: 24 | Q4: 26 | R4: 26 | S4: 27 | T4: 26 | U4: 26 | V4: 25 | W4: 26 | X4: 26 | Y4: 26
A5: 98908RES | B5: 29 | C5: 29 | D5: 27 | E5: 27 | F5: 27 | G5: 26 | H5: 26 | I5: 25 | J5: 26 | K5: 26 | L5: 26 | M5: 23 | N5: 23 | O5: 26 | P5: 26 | Q5: 26 | R5: 25 | S5: 25 | T5: 25 | U5: 26 | V5: 27 | W5: 27 | X5: 26 | Y5: 28
A6: 98921RES | B6: 10 | C6: 10 | D6: 9 | E6: 9 | F6: 9 | G6: 10 | H6: 9 | I6: 9 | J6: 7 | K6: 7 | L6: 7 | M6: 7 | N6: 12 | O6: 13 | P6: 12 | Q6: 12 | R6: 12 | S6: 11 | T6: 11 | U6: 10 | V6: 10 | W6: 10 | X6: 10 | Y6: 10
A7: 98923RES | B7: 3 | C7: 4 | D7: 3 | E7: 4 | F7: 3 | G7: 3 | H7: 4 | I7: 3 | J7: 4 | K7: 3 | L7: 4 | M7: 4 | N7: 4 | O7: 4 | P7: 5 | Q7: 4 | R7: 4 | S7: 5 | T7: 4 | U7: 4 | V7: 5 | W7: 5 | X7: 4 | Y7: 4
A8: 98930RES | B8: 33 | C8: 32 | D8: 32 | E8: 32 | F8: 30 | G8: 29 | H8: 28 | I8: 28 | J8: 28 | K8: 24 | L8: 21 | M8: 20 | N8: 21 | O8: 22 | P8: 25 | Q8: 25 | R8: 26 | S8: 27 | T8: 28 | U8: 28 | V8: 32 | W8: 31 | X8: 32 | Y8: 32
A9: 98932RES | B9: 21 | C9: 20 | D9: 21 | E9: 22 | F9: 21 | G9: 18 | H9: 18 | I9: 18 | J9: 17 | K9: 16 | L9: 15 | M9: 14 | N9: 16 | O9: 17 | P9: 17 | Q9: 17 | R9: 17 | S9: 19 | T9: 19 | U9: 20 | V9: 19 | W9: 20 | X9: 21 | Y9: 21
A10: 98933RES | B10: 4 | C10: 4 | D10: 4 | E10: 4 | F10: 4 | G10: 4 | H10: 4 | I10: 3 | J10: 2 | K10: 2 | L10: 2 | M10: 3 | N10: 2 | O10: 3 | P10: 3 | Q10: 3 | R10: 2 | S10: 3 | T10: 1 | U10: 1 | V10: 1 | W10: 2 | X10: 3 | Y10: 3
A11: 98935RES | B11: 12 | C11: 12 | D11: 12 | E11: 12 | F11: 12 | G11: 11 | H11: 10 | I11: 10 | J11: 10 | K11: 10 | L11: 10 | M11: 8 | N11: 9 | O11: 10 | P11: 10 | Q11: 9 | R11: 10 | S11: 11 | T11: 11 | U11: 10 | V11: 10 | W11: 12 | X11: 12 | Y11: 12
A12: 98936RES | B12: 8 | C12: 8 | D12: 7 | E12: 8 | F12: 7 | G12: 8 | H12: 8 | I12: 8 | J12: 8 | K12: 10 | L12: 10 | M12: 9 | N12: 7 | O12: 7 | P12: 7 | Q12: 7 | R12: 6 | S12: 6 | T12: 6 | U12: 5 | V12: 5 | W12: 7 | X12: 6 | Y12: 8
A13: 98937RES | B13: 9 | C13: 10 | D13: 9 | E13: 9 | F13: 8 | G13: 10 | H13: 10 | I13: 9 | J13: 10 | K13: 9 | L13: 9 | M13: 9 | N13: 7 | O13: 7 | P13: 7 | Q13: 7 | R13: 8 | S13: 8 | T13: 7 | U13: 7 | V13: 7 | W13: 9 | X13: 8 | Y13: 9
... A33: 99363RES | B33: 3 | C33: 2 | D33: 2 | E33: 2 | F33: 2 | G33: 2 | H33: 2 | I33: 1 | J33: 2 | K33: 1 | L33: 1 | M33: 1 | N33: 2 | O33: 2 | P33: 2 | Q33: 3 | R33: 2 | S33: 2 | T33: 2 | U33: 2 | V33: 2 | W33: 2 | X33: 2 | Y33: 3

Sheet 8.ARREARS NEW 2022_Q2
A1: Item a) Number of Customers by Customer Class With Past-due balances (arrearages) | V1: Item c) Amount of Past-due Balances for Known Low-income Households and Number of Days Past-due | CH1: Section D. Bad Debt | CQ1: Item e) The Amount of Past-due Balances Written-off and Classified as Bad Debt, if different than item d | DD1: Item f) Number of Customer Accounts Referred to Collection Agencies | DM1: Item f) Total Amount of Bad Debt Referred for Collection | DS1: Item f) Total Revenue to the Company from the Collection Process
V2: EAP | CJ2: 0.32
A3: 202204 | H3: 202205 | O3: 202206 | X3: 202101 | AC3: 202102 | AH3: 202103 | AO3: 202104 | AT3: 202105 | AY3: 202106 | BD3: 202204 | BK3: 202205 | BR3: 202206 | CH3: 202204 | CK3: 202205 | CN3: 202206 | CQ3: Class | CR3: 202101 | CS3: 202102 | CT3: 202103 | CU3: 202104 | CV3: 202105 | CW3: 202106 | CX3: 202107 | CY3: 202108 | CZ3: 202109 | DA3: 202204 | DB3: 202205 | DC3: 202206 | DD3: 202204 | DG3: 202205 | DJ3: 202206 | DM3: 202204 | DO3: 202205 | DQ3: 202206 | DS3: 202204 | DU3: 202205 | DW3: 202206
A4: CLASS | B4: ZIP | C4: COUNT | D4: DAYS 31 60 | E4: DAYS 61 90 | F4: DAYS 91+ | G4: ARREARS | H4: CLASS | I4: ZIP | J4: COUNT | K4: DAYS 31 60 | L4: DAYS 61 90 | M4: DAYS 91+ | N4: ARREARS | O4: ZIP | P4: COUNT | Q4: COUNT | R4: DAYS 31 60 | S4: DAYS 61 90 | T4: DAYS 91+ | U4: ARREARS | V4: CLASS | W4: ZIP | X4: Count | Y4: Days 31 60 | Z4: Days 61 90 | AA4: Days 91+ | AB4: Arrears | AC4: Count | AD4: Days 31 60 | AE4: Days 61 90 | AF4: Days 91+ | AG4: Arrears | AH4: Count | AI4: Days 31 60 | AJ4: Days 61 90 | AK4: Days 91+ | AL4: Arrears | AM4: Agrmt Revenue Class Cd | AN4: Zip Code | AO4: Count | AP4: Days 31 60 | AQ4: Days 61 90 | AR4: Days 91+ | AS4: Arrears | AT4: Count | AU4: Days 31 60 | AV4: Days 61 90 | AW4: Days 91+ | AX4: Arrears | AY4: Count | AZ4: Days 31 60 | BA4: Days 61 90 | BB4: Days 91+ | BC4: Arrears | BD4: CLASS | BE4: ZIP | BF4: COUNT | BG4: DAYS 31 60 | BH4: DAYS 61 90 | BI4: DAYS 91+ | BJ4: ARREARS | BK4: CLASS | BL4: ZIP | BM4: COUNT | BN4: DAYS 31 60 | BO4: DAYS 61 90 | BP4: DAYS 91+ | BQ4: ARREARS | BR4: CLASS | BS4: ZIP | BT4: COUNT | BU4: DAYS 31 60 | BV4: DAYS 61 90 | BW4: DAYS 91+ | BX4: ARREARS | CH4: CLASS | CI4: ZIP | CJ4: BAD DEBT | CK4: CLASS | CL4: ZIP | CM4: BAD DEBT | CN4: CLASS | CO4: ZIP | CP4: BAD DEBT | CQ4: RES | CR4: 78547.88 | CS4: 83507.78 | CT4: 74673.15 | CU4: 63441.04 | CV4: 64476.9 | CW4: 57542.34 | CX4: 83815.89 | CY4: 81559.71 | CZ4: 121882.53 | DA4: 161527.14 | DB4: 197790.97 | DC4: 165796.26 | DD4: ZIP | DE4: CLASS | DF4: 202204 | DG4: ZIP | DH4: CLASS | DI4: 202205 | DJ4: Zip Code | DK4: Revenue Class Cd | DL4: 202206 | DM4: ZIP/CLASS | DN4: 202204 | DO4: ZIP/CLASS | DP4: 202205 | DQ4: ZIP/CLASS | DR4: 202206 | DS4: ZIP/CLASS | DT4: 202204 | DU4: ZIP/CLASS | DV4: 202205 | DW4: ZIP/CLASS | DX4: 202206
A5: COM | B5: 98901 | C5: 144 | D5: 61058.34 | E5: 26917.46 | F5: 149187.34 | G5: 237163.14 | H5: COM | I5: 98901 | J5: 150 | K5: 36240.65 | L5: 25142.84 | M5: 157378.33 | N5: 218761.82 | O5: COM | P5: 98901 | Q5: 137 | R5: 55526.69 | S5: 25500.16 | T5: 168042.41 | U5: 249069.26 | V5: COM | W5: 98901 | X5: 1 | Y5: 82.45 | Z5: 53.83 | AA5: 302.58 | AB5: 438.86 | AC5: 1 | AD5: 84.64 | AE5: 82.45 | AF5: 356.41 | AG5: 523.5 | AH5: 1 | AI5: 85.48 | AJ5: 84.64 | AK5: 438.86 | AL5: 608.98 | AM5: COM | AN5: 98901 | AO5: 2 | AP5: 281.67 | AQ5: 312.97 | AR5: 971.94 | AS5: 1566.58 | AT5: 1 | AU5: 59.27 | AV5: 84.24 | AW5: 608.98 | AX5: 752.49 | AY5: 1 | AZ5: 39.33 | BA5: 59.27 | BB5: 693.22 | BC5: 791.82 | BD5: COM | BE5: 98901 | BF5: 2 | BG5: 175.1 | BH5: 218.66 | BI5: 483.39 | BJ5: 877.15 | BK5: COM | BL5: 98901 | BM5: 4 | BN5: 208.5 | BO5: 175.1 | BP5: 702.05 | BQ5: 1085.65 | BR5: COM | BS5: 98901 | BT5: 3 | BU5: 57.09 | BV5: 58.25 | BW5: 68.07 | BX5: 183.41 | CH5: =A5 -> COM | CI5: =B5 -> 98901 | CJ5: =D5*1.6%+E5*6.3%+F5*28.9% -> 45787.875 | CK5: =H5 -> COM | CL5: =I5 -> 98901 | CM5: =K5*1.6%+L5*6.3%+M5*28.9% -> 47646.187 | CN5: =O5 -> COM | CO5: =P5 -> 98901 | CP5: =R5*1.6%+S5*6.3%+T5*28.9% -> 51059.194 | CQ5: COM | CR5: 35411.49 | CS5: 19861.99 | CT5: 1614.2 | CU5: 209.93 | CV5: 2347.21 | CW5: 3702.39 | CX5: 16587.84 | CY5: 21717.76 | CZ5: 41593.57 | DA5: 26622.79 | DB5: 22917.54 | DC5: 16743.23 | DD5: 98901 | DE5: COM | DF5: 7 | DG5: 98901 | DH5: COM | DI5: 3 | DJ5: 98901 | DK5: COM | DL5: 1 | DM5: 98901COM | DN5: 3846.37 | DO5: 98901COM | DP5: 520.66 | DQ5: 98901COM | DR5: 1526.8 | DS5: 98901RES | DT5: 1498.41 | DU5: 98901COM | DV5: 483.7 | DW5: 98901RES | DX5: 813.78
A6: COM | B6: 98902 | C6: 211 | D6: 77087.2 | E6: 28345.49 | F6: 125741.79 | G6: 231174.48 | H6: COM | I6: 98902 | J6: 217 | K6: 92293.42 | L6: 21740.24 | M6: 138675.7 | N6: 252709.36 | O6: COM | P6: 98902 | Q6: 182 | R6: 35377.08 | S6: 18130.43 | T6: 147129.49 | U6: 200637 | V6: COM | W6: 98902 | X6: 1 | Y6: 201.67 | Z6: 184.35 | AA6: 790.64 | AB6: 1176.66 | AC6: 1 | AD6: 199.22 | AE6: 201.67 | AF6: 974.99 | AG6: 1375.88 | AH6: 1 | AI6: 141.61 | AJ6: 199.22 | AK6: 1176.66 | AL6: 1517.49 | AM6: COM | AN6: 98902 | AO6: 3 | AP6: 220.21 | AQ6: 220.32 | AR6: 1375.88 | AS6: 1816.41 | AT6: 2 | AU6: 95.4 | AV6: 149.07 | AW6: 1017.49 | AX6: 1261.96 | AY6: 3 | AZ6: 96.28 | BA6: 87.4 | BB6: 1166.56 | BC6: 1350.24 | BD6: COM | BE6: 98902 | BF6: 3 | BG6: 253.64 | BH6: 125.48 | BI6: 307.49 | BJ6: 686.61 | BK6: COM | BL6: 98902 | BM6: 2 | BN6: 114.2 | BO6: 108.06 | BP6: 432.97 | BQ6: 655.23 | BR6: COM | BS6: 98902 | BT6: 2 | BU6: 88.44 | BV6: 106.2 | BW6: 541.03 | BX6: 735.67 | CH6: =A6 -> COM | CI6: =B6 -> 98902 | CJ6: =D6*1.6%+E6*6.3%+F6*28.9% -> 39358.538 | CK6: =H6 -> COM | CL6: =I6 -> 98902 | CM6: =K6*1.6%+L6*6.3%+M6*28.9% -> 42923.607 | CN6: =O6 -> COM | CO6: =P6 -> 98902 | CP6: =R6*1.6%+S6*6.3%+T6*28.9% -> 44228.673 | DD6: 98902 | DE6: COM | DF6: 2 | DG6: 98902 | DH6: COM | DI6: 5 | DJ6: 98902 | DK6: COM | DL6: 7 | DM6: 98901RES | DN6: 137166.95 | DO6: 98901RES | DP6: 22809.38 | DQ6: 98901RES | DR6: 26742.52 | DS6: 98902RES | DT6: 2372.83 | DU6: 98901RES | DV6: 298.23 | DW6: 98902RES | DX6: 251.74
A7: COM | B7: 98903 | C7: 130 | D7: 34608.06 | E7: 11749.03 | F7: 70588.16 | G7: 116945.25 | H7: COM | I7: 98903 | J7: 111 | K7: 16723.79 | L7: 17935.02 | M7: 79059.27 | N7: 113718.08 | O7: COM | P7: 98903 | Q7: 99 | R7: 20368.42 | S7: 10085.67 | T7: 76672.52 | U7: 107126.61 | V7: COM | W7: 98908 | X7: 2 | Y7: 158.37 | Z7: 111.77 | AA7: 460.42 | AB7: 730.56 | AC7: 2 | AD7: 150.01 | AE7: 158.37 | AF7: 572.19 | AG7: 880.57 | AH7: 2 | AI7: 110.55 | AJ7: 150.01 | AK7: 730.56 | AL7: 991.12 | AM7: COM | AN7: 98903 | AO7: 1 | AP7: 11.54 | AQ7: 0 | AR7: 0 | AS7: 11.54 | BD7: COM | BE7: 98903 | BF7: 3 | BG7: 138.84 | BH7: 40.46 | BI7: 68.31 | BJ7: 247.61 | BK7: COM | BL7: 98903 | BM7: 2 | BN7: 183.01 | BO7: 28.26 | BP7: 81.82 | BQ7: 293.09 | BR7: COM | BS7: 98903 | BT7: 2 | BU7: 183.23 | BV7: 104.83 | BW7: 106.26 | BX7: 394.32 | CH7: =A7 -> COM | CI7: =B7 -> 98903 | CJ7: =D7*1.6%+E7*6.3%+F7*28.9% -> 21693.896 | CK7: =H7 -> COM | CL7: =I7 -> 98903 | CM7: =K7*1.6%+L7*6.3%+M7*28.9% -> 24245.616 | CN7: =O7 -> COM | CO7: =P7 -> 98903 | CP7: =R7*1.6%+S7*6.3%+T7*28.9% -> 23119.65 | DD7: 98930 | DE7: COM | DF7: 1 | DG7: 98903 | DH7: COM | DI7: 1 | DJ7: 98908 | DK7: COM | DL7: 4 | DM7: 98902COM | DN7: 36862.79 | DO7: 98902COM | DP7: 3875.33 | DQ7: 98902COM | DR7: 5619.56 | DS7: 98908RES | DT7: 1146.97 | DU7: 98902COM | DV7: 25.41 | DW7: 98903RES | DX7: 324.35
A8: COM | B8: 98904 | D8: 0 | E8: 0 | F8: 0 | G8: 0 | H8: COM | I8: 98904 | K8: 0 | L8: 0 | M8: 0 | N8: 0 | O8: COM | P8: 98904 | R8: 0 | S8: 0 | T8: 0 | U8: 0 | V8: COM | W8: 98939 | AH8: 1 | AI8: 18.28 | AJ8: 0 | AK8: 0 | AL8: 18.28 | AM8: COM | AN8: 98908 | AO8: 2 | AP8: 110.6 | AQ8: 110.55 | AR8: 880.57 | AS8: 1101.72 | AT8: 2 | AU8: 83.91 | AV8: 110.6 | AW8: 888.12 | AX8: 1082.63 | AY8: 2 | AZ8: 63.03 | BA8: 83.91 | BB8: 996.87 | BC8: 1143.81 | BD8: COM | BE8: 98908 | BF8: 4 | BG8: 524.79 | BH8: 486.04 | BI8: 2728.77 | BJ8: 3739.6 | BK8: COM | BL8: 98908 | BM8: 4 | BN8: 508.28 | BO8: 524.79 | BP8: 2922.87 | BQ8: 3955.94 | BR8: COM | BS8: 98908 | BT8: 3 | BU8: 488.96 | BV8: 470.95 | BW8: 3373.23 | BX8: 4333.14 | CH8: =A8 -> COM | CI8: =B8 -> 98904 | CJ8: =D8*1.6%+E8*6.3%+F8*28.9% -> 0 | CK8: =H8 -> COM | CL8: =I8 -> 98904 | CM8: =K8*1.6%+L8*6.3%+M8*28.9% -> 0 | CN8: =O8 -> COM | CO8: =P8 -> 98904 | CP8: =R8*1.6%+S8*6.3%+T8*28.9% -> 0 | DD8: 98932 | DE8: COM | DF8: 1 | DG8: 98930 | DH8: COM | DI8: 2 | DJ8: 98932 | DK8: COM | DL8: 2 | DM8: 98902RES | DN8: 43475.35 | DO8: 98902RES | DP8: 77490.83 | DQ8: 98902RES | DR8: 56967.37 | DS8: 98921RES | DT8: 244.25 | DU8: 98902RES | DV8: 1566.43 | DW8: 98908COM | DX8: 634.85
A9: COM | B9: 98907 | D9: 0 | E9: 0 | F9: 0 | G9: 0 | H9: COM | I9: 98907 | K9: 0 | L9: 0 | M9: 0 | N9: 0 | O9: COM | P9: 98907 | R9: 0 | S9: 0 | T9: 0 | U9: 0 | V9: COM | W9: 98944 | X9: 1 | Y9: 693.32 | Z9: 625.8 | AA9: 8208.19 | AB9: 9527.31 | AC9: 1 | AD9: 651.21 | AE9: 693.32 | AF9: 8491.43 | AG9: 9835.96 | AH9: 1 | AI9: 746.89 | AJ9: 651.21 | AK9: 9184.75 | AL9: 10582.85 | AM9: COM | AN9: 98939 | AO9: 2 | AP9: 275.97 | AQ9: 333.69 | AR9: 0 | AS9: 609.66 | AT9: 2 | AU9: 275.97 | AV9: 0 | AW9: 0 | AX9: 275.97 | AY9: 2 | AZ9: 275.97 | BA9: 0 | BB9: 0 | BC9: 275.97 | BD9: COM | BE9: 98932 | BF9: 1 | BG9: 14.03 | BH9: 15.24 | BI9: 129.47 | BJ9: 158.74 | BK9: COM | BL9: 98932 | BM9: 1 | BN9: 13.91 | BO9: 14.03 | BP9: 49.92 | BQ9: 77.86 | BR9: COM | BS9: 98932 | BT9: 1 | BU9: 14.05 | BV9: 0 | BW9: 0 | BX9: 14.05 | CH9: =A9 -> COM | CI9: =B9 -> 98907 | CJ9: =D9*1.6%+E9*6.3%+F9*28.9% -> 0 | CK9: =H9 -> COM | CL9: =I9 -> 98907 | CM9: =K9*1.6%+L9*6.3%+M9*28.9% -> 0 | CN9: =O9 -> COM | CO9: =P9 -> 98907 | CP9: =R9*1.6%+S9*6.3%+T9*28.9% -> 0 | DD9: 98936 | DE9: COM | DF9: 2 | DG9: 98944 | DH9: COM | DI9: 1 | DJ9: 99362 | DK9: COM | DL9: 1 | DM9: 98903RES | DN9: 29938.64 | DO9: 98903COM | DP9: 312.62 | DQ9: 98903RES | DR9: 16394.39 | DS9: 98930RES | DT9: 376.46 | DU9: 98903RES | DV9: 280.29 | DW9: 98908RES | DX9: 186.02
A10: COM | B10: 98908 | C10: 119 | D10: 39004.73 | E10: 10177.83 | F10: 33853.78 | G10: 83036.34 | H10: COM | I10: 98908 | J10: 117 | K10: 27323.46 | L10: 9326.87 | M10: 35083.31 | N10: 71733.64 | O10: COM | P10: 98908 | Q10: 114 | R10: 22063.93 | S10: 7836.95 | T10: 33871.31 | U10: 63772.19 | V10: COM | W10: 98947 | X10: 1 | Y10: 133.37 | Z10: 100.97 | AA10: 523.95 | AB10: 758.29 | AH10: 1 | AI10: 28.62 | AJ10: 0 | AK10: 0 | AL10: 28.62 | AM10: COM | AN10: 98944 | AO10: 1 | AP10: 661.59 | AQ10: 746.89 | AR10: 9835.96 | AS10: 11244.44 | AT10: 1 | AU10: 524.18 | AV10: 661.59 | AW10: 9982.85 | AX10: 11168.62 | AY10: 1 | AZ10: 426.92 | BA10: 524.18 | BB10: 10244.44 | BC10: 11195.54 | BD10: COM | BE10: 98933 | BG10: 0 | BH10: 0 | BI10: 0 | BJ10: 0 | BK10: COM | BL10: 98933 | BN10: 0 | BO10: 0 | BP10: 0 | BQ10: 0 | BR10: COM | BS10: 98933 | BU10: 0 | BV10: 0 | BW10: 0 | BX10: 0 | CH10: =A10 -> COM | CI10: =B10 -> 98908 | CJ10: =D10*1.6%+E10*6.3%+F10*28.9% -> 11049.021 | CK10: =H10 -> COM | CL10: =I10 -> 98908 | CM10: =K10*1.6%+L10*6.3%+M10*28.9% -> 11163.845 | CN10: =O10 -> COM | CO10: =P10 -> 98908 | CP10: =R10*1.6%+S10*6.3%+T10*28.9% -> 10635.559 | DD10: 98951 | DE10: COM | DF10: 1 | DG10: 98948 | DH10: COM | DI10: 3 | DJ10: 98901 | DK10: RES | DL10: 43 | DM10: 98908RES | DN10: 13886.69 | DO10: 98903RES | DP10: 21393.79 | DQ10: 98908COM | DR10: 673.7 | DS10: 98938RES | DT10: 92.76 | DU10: 98908RES | DV10: 1131.82 | DW10: 98923RES | DX10: 44.32
A11: COM | B11: 98920 | D11: 0 | E11: 0 | F11: 0 | G11: 0 | H11: COM | I11: 98920 | K11: 0 | L11: 0 | M11: 0 | N11: 0 | O11: COM | P11: 98920 | R11: 0 | S11: 0 | T11: 0 | U11: 0 | V11: COM | W11: 98948 | X11: 13 | Y11: 2679.32 | Z11: 4508.48 | AA11: 8955.01 | AB11: 16142.81 | AC11: 13 | AD11: 4720.25 | AE11: 2679.3 | AF11: 12509.89 | AG11: 19909.44 | AH11: 7 | AI11: 2581.95 | AJ11: 1965.03 | AK11: 3186.9 | AL11: 7733.88 | AM11: COM | AN11: 98947 | AO11: 1 | AP11: 153.22 | AQ11: 28.62 | AR11: 0 | AS11: 181.84 | AT11: 1 | AU11: 53.68 | AV11: 153.22 | AW11: 28.62 | AX11: 235.52 | AY11: 1 | AZ11: 99.66 | BA11: 53.68 | BB11: 179.99 | BC11: 333.33 | BD11: COM | BE11: 98936 | BK11: COM | BL11: 98936 | BR11: COM | BS11: 98936 | BU11: 0 | BV11: 0 | BW11: 0 | BX11: 0 | CH11: =A11 -> COM | CI11: =B11 -> 98920 | CJ11: =D11*1.6%+E11*6.3%+F11*28.9% -> 0 | CK11: =H11 -> COM | CL11: =I11 -> 98920 | CM11: =K11*1.6%+L11*6.3%+M11*28.9% -> 0 | CN11: =O11 -> COM | CO11: =P11 -> 98920 | CP11: =R11*1.6%+S11*6.3%+T11*28.9% -> 0 | DD11: 99328 | DE11: COM | DF11: 3 | DG11: 98901 | DH11: RES | DI11: 52 | DJ11: 98902 | DK11: RES | DL11: 78 | DM11: 98921RES | DN11: 246 | DO11: 98908RES | DP11: 13682.06 | DQ11: 98908RES | DR11: 19280.31 | DS11: 98942RES | DT11: 2192.36 | DU11: 98923RES | DV11: 185.65 | DW11: 98936RES | DX11: 82.68
A12: COM | B12: 98921 | C12: 2 | D12: 124.99 | E12: 144.72 | F12: 148.98 | G12: 418.69 | H12: COM | I12: 98921 | J12: 4 | K12: 278.48 | L12: 121.77 | M12: 147.34 | N12: 547.59 | O12: COM | P12: 98921 | Q12: 3 | R12: 124.59 | S12: 125.29 | T12: 269.11 | U12: 518.99 | V12: COM | W12: 98951 | X12: 4 | Y12: 378.67 | Z12: 249.13 | AA12: 728.58 | AB12: 1356.38 | AC12: 4 | AD12: 357.8 | AE12: 209.84 | AF12: 977.71 | AG12: 1545.35 | AH12: 3 | AI12: 297.18 | AJ12: 174.7 | AK12: 1176.78 | AL12: 1648.66 | AM12: COM | AN12: 98948 | AO12: 6 | AP12: 6418.74 | AQ12: 11.34 | AR12: 650.48 | AS12: 7080.56 | AT12: 6 | AU12: 4152.47 | AV12: 1531.26 | AW12: 88.2 | AX12: 5771.93 | AY12: 4 | AZ12: 2645.64 | BA12: 79.99 | BB12: 22.92 | BC12: 2748.55 | BD12: COM | BE12: 98938 | BG12: 0 | BH12: 0 | BI12: 0 | BJ12: 0 | BK12: COM | BL12: 98938 | BN12: 0 | BO12: 0 | BP12: 0 | BQ12: 0 | BR12: COM | BS12: 98938 | BT12: 1 | BU12: 0.02 | BV12: 0 | BW12: 0 | BX12: 0.02 | CH12: =A12 -> COM | CI12: =B12 -> 98921 | CJ12: =D12*1.6%+E12*6.3%+F12*28.9% -> 54.17242 | CK12: =H12 -> COM | CL12: =I12 -> 98921 | CM12: =K12*1.6%+L12*6.3%+M12*28.9% -> 54.70845 | CN12: =O12 -> COM | CO12: =P12 -> 98921 | CP12: =R12*1.6%+S12*6.3%+T12*28.9% -> 87.6595 | DD12: 99347 | DE12: COM | DF12: 1 | DG12: 98902 | DH12: RES | DI12: 83 | DJ12: 98903 | DK12: RES | DL12: 20 | DM12: 98930COM | DN12: 884.12 | DO12: 98921RES | DP12: 1865.61 | DQ12: 98921RES | DR12: 1301.81 | DS12: 98944RES | DT12: 407.03 | DU12: 98930RES | DV12: 59.2 | DW12: 98942RES | DX12: 208.89
A13: COM | B13: 98923 | C13: 8 | D13: 12752.59 | E13: 88.99 | F13: 592.68 | G13: 13434.26 | H13: COM | I13: 98923 | J13: 10 | K13: 12113.39 | L13: 11846.26 | M13: 621.6 | N13: 24581.25 | O13: COM | P13: 98923 | Q13: 8 | R13: 12831.93 | S13: 5103.86 | T13: 6531.14 | U13: 24466.93 | V13: COM | W13: 98952 | X13: 1 | Y13: 191.52 | Z13: 111.91 | AA13: 298.69 | AB13: 602.12 | AC13: 1 | AD13: 139.04 | AE13: 191.52 | AF13: 110.6 | AG13: 441.16 | AH13: 1 | AI13: 86.41 | AJ13: 139.04 | AK13: 302.12 | AL13: 527.57 | AM13: COM | AN13: 98951 | AO13: 3 | AP13: 374.25 | AQ13: 107.31 | AR13: 1098.31 | AS13: 1579.87 | AT13: 3 | AU13: 385.42 | AV13: 374.25 | AW13: 1205.62 | AX13: 1965.29 | AY13: 2 | AZ13: 193.02 | BA13: 273.23 | BB13: 252.38 | BC13: 718.63 | BD13: COM | BE13: 98939 | BF13: 1 | BG13: 255.72 | BH13: 20.25 | BI13: 0 | BJ13: 275.97 | BK13: COM | BL13: 98939 | BM13: 1 | BN13: 275.97 | BO13: 0 | BP13: 0 | BQ13: 275.97 | BR13: COM | BS13: 98939 | BT13: 1 | BU13: 284.66 | BV13: 275.97 | BW13: 0 | BX13: 560.63 | CH13: =A13 -> COM | CI13: =B13 -> 98923 | CJ13: =D13*1.6%+E13*6.3%+F13*28.9% -> 380.93233 | CK13: =H13 -> COM | CL13: =I13 -> 98923 | CM13: =K13*1.6%+L13*6.3%+M13*28.9% -> 1119.771 | CN13: =O13 -> COM | CO13: =P13 -> 98923 | CP13: =R13*1.6%+S13*6.3%+T13*28.9% -> 2414.3535 | DD13: 98901 | DE13: RES | DF13: 42 | DG13: 98903 | DH13: RES | DI13: 17 | DJ13: 98908 | DK13: RES | DL13: 33 | DM13: 98930RES | DN13: 5556.71 | DO13: 98923RES | DP13: 322.29 | DQ13: 98923RES | DR13: 4010.65 | DS13: 98947RES | DT13: 288 | DU13: 98932RES | DV13: 743.66 | DW13: 98944RES | DX13: 96.21
A14: COM | B14: 98930 | C14: 35 | D14: 5841.59 | E14: 5030.47 | F14: 16375.5 | G14: 27247.56 | H14: COM | I14: 98930 | J14: 26 | K14: 3401.06 | L14: 4372.5 | M14: 20459.97 | N14: 28233.53 | O14: COM | P14: 98930 | Q14: 33 | R14: 4337.27 | S14: 3182.68 | T14: 22246.7 | U14: 29766.65 | V14: COM | W14: 99347 | X14: 2 | Y14: 522.01 | Z14: 305.81 | AA14: 46.45 | AB14: 874.27 | AC14: 2 | AD14: 338.57 | AE14: 522.01 | AF14: 352.26 | AG14: 1212.84 | AH14: 1 | AI14: 126.21 | AJ14: 188.49 | AK14: 716.19 | AL14: 1030.89 | AM14: COM | AN14: 98952 | AO14: 1 | AP14: 86.45 | AQ14: 86.41 | AR14: 441.16 | AS14: 614.02 | AT14: 1 | AU14: 74.27 | AV14: 86.45 | AW14: 527.57 | AX14: 688.29 | AY14: 1 | AZ14: 54.78 | BA14: 74.27 | BB14: 614.02 | BC14: 743.07 | BD14: COM | BE14: 98942 | BG14: 0 | BH14: 0 | BI14: 0 | BJ14: 0 | BK14: COM | BL14: 98942 | BN14: 0 | BO14: 0 | BP14: 0 | BQ14: 0 | BR14: COM | BS14: 98942 | BU14: 0 | BV14: 0 | BW14: 0 | BX14: 0 | CH14: =A14 -> COM | CI14: =B14 -> 98930 | CJ14: =D14*1.6%+E14*6.3%+F14*28.9% -> 5142.9045 | CK14: =H14 -> COM | CL14: =I14 -> 98930 | CM14: =K14*1.6%+L14*6.3%+M14*28.9% -> 6242.8158 | CN14: =O14 -> COM | CO14: =P14 -> 98930 | CP14: =R14*1.6%+S14*6.3%+T14*28.9% -> 6699.2015 | DD14: 98902 | DE14: RES | DF14: 70 | DG14: 98908 | DH14: RES | DI14: 24 | DJ14: 98921 | DK14: RES | DL14: 1 | DM14: 98932COM | DN14: 6460.72 | DO14: 98930COM | DP14: 2241.76 | DQ14: 98930RES | DR14: 13479.57 | DS14: 98948RES | DT14: 185.77 | DU14: 98935RES | DV14: 875.23 | DW14: 98948RES | DX14: 26.82
A15: COM | B15: 98932 | C15: 21 | D15: 6404.16 | E15: 2597.53 | F15: 9506.03 | G15: 18507.72 | H15: COM | I15: 98932 | J15: 22 | K15: 5317.66 | L15: 2353.51 | M15: 10989.1 | N15: 18660.27 | O15: COM | P15: 98932 | Q15: 22 | R15: 18746.49 | S15: 3335.86 | T15: 4863.81 | U15: 26946.16 | V15: COM | W15: 99362 | AC15: 2 | AD15: 27.21 | AE15: 0 | AF15: 0 | AG15: 27.21 | AM15: COM | AN15: 98953 | AO15: 2 | AP15: 128.22 | AQ15: 133.96 | AR15: 260.51 | AS15: 522.69 | AT15: 2 | AU15: 133.66 | AV15: 128.22 | AW15: 329.98 | AX15: 591.86 | AY15: 2 | AZ15: 132.91 | BA15: 133.66 | BB15: 422.5 | BC15: 689.07 | BD15: COM | BE15: 98944 | BF15: 4 | BG15: 1032.08 | BH15: 1150.34 | BI15: 15795.81 | BJ15: 17978.23 | BK15: COM | BL15: 98944 | BM15: 4 | BN15: 718.42 | BO15: 1032.08 | BP15: 16894.4 | BQ15: 18644.9 | BR15: COM | BS15: 98944 | BT15: 4 | BU15: 695.77 | BV15: 691.38 | BW15: 17382.02 | BX15: 18769.17 | CH15: =A15 -> COM | CI15: =B15 -> 98932 | CJ15: =D15*1.6%+E15*6.3%+F15*28.9% -> 3013.3536 | CK15: =H15 -> COM | CL15: =I15 -> 98932 | CM15: =K15*1.6%+L15*6.3%+M15*28.9% -> 3409.2036 | CN15: =O15 -> COM | CO15: =P15 -> 98932 | CP15: =R15*1.6%+S15*6.3%+T15*28.9% -> 1915.7441 | DD15: 98903 | DE15: RES | DF15: 12 | DG15: 98921 | DH15: RES | DI15: 2 | DJ15: 98923 | DK15: RES | DL15: 2 | DM15: 98932RES | DN15: 1754.52 | DO15: 98930RES | DP15: 6774.1 | DQ15: 98932COM | DR15: 13118.89 | DS15: 98951COM | DT15: 107.29 | DU15: 98937RES | DV15: 351.48 | DW15: 98953RES | DX15: 206.48
A16: COM | B16: 98933 | C16: 10 | D16: 4962.75 | E16: 4707.51 | F16: 9254.01 | G16: 18924.27 | H16: COM | I16: 98933 | J16: 15 | K16: 12472.63 | L16: 4343.49 | M16: 9700.11 | N16: 26516.23 | O16: COM | P16: 98933 | Q16: 9 | R16: 2245.06 | S16: 1212.82 | T16: 3237.76 | U16: 6695.64 | V16: RES | W16: 98901 | X16: 333 | Y16: 31436.93 | Z16: 13117.87 | AA16: 108321.59 | AB16: 152876.39 | AC16: 336 | AD16: 38705.4 | AE16: 26860.43 | AF16: 96853.61 | AG16: 162419.44 | AH16: 305 | AI16: 31631.39 | AJ16: 28430.36 | AK16: 100862.74 | AL16: 160924.49 | AM16: COM | AN16: 99347 | AO16: 1 | AP16: 144.96 | AQ16: 126.21 | AR16: 904.68 | AS16: 1175.85 | AT16: 1 | AU16: 118.02 | AV16: 144.96 | AW16: 1030.89 | AX16: 1293.87 | AY16: 1 | AZ16: 100.32 | BA16: 118.02 | BB16: 1175.85 | BC16: 1394.19 | BD16: COM | BE16: 98947 | BG16: 0 | BH16: 0 | BI16: 0 | BJ16: 0 | BK16: COM | BL16: 98947 | BN16: 0 | BO16: 0 | BP16: 0 | BQ16: 0 | BR16: COM | BS16: 98947 | BU16: 0 | BV16: 0 | BW16: 0 | BX16: 0 | CH16: =A16 -> COM | CI16: =B16 -> 98933 | CJ16: =D16*1.6%+E16*6.3%+F16*28.9% -> 3050.386 | CK16: =H16 -> COM | CL16: =I16 -> 98933 | CM16: =K16*1.6%+L16*6.3%+M16*28.9% -> 3276.5337 | CN16: =O16 -> COM | CO16: =P16 -> 98933 | CP16: =R16*1.6%+S16*6.3%+T16*28.9% -> 1048.0413 | DD16: 98908 | DE16: RES | DF16: 27 | DG16: 98923 | DH16: RES | DI16: 2 | DJ16: 98930 | DK16: RES | DL16: 11 | DM16: 98933RES | DN16: 812.97 | DO16: 98932RES | DP16: 4968.25 | DQ16: 98932RES | DR16: 3960.69 | DS16: 99324RES | DT16: 531.48 | DU16: 98942RES | DV16: 13.72 | DW16: 99324RES | DX16: 37.52
A17: COM | B17: 98935 | C17: 3 | D17: 894.92 | E17: 251.12 | F17: 3411 | G17: 4557.04 | H17: COM | I17: 98935 | J17: 5 | K17: 2304.45 | L17: 894.92 | M17: 3660.62 | N17: 6859.99 | O17: COM | P17: 98935 | Q17: 3 | R17: 248.54 | S17: 149.49 | T17: 4195.94 | U17: 4593.97 | V17: RES | W17: 98902 | X17: 499 | Y17: 58180.5 | Z17: 37954.75 | AA17: 129300.97 | AB17: 225436.22 | AC17: 435 | AD17: 49054.08 | AE17: 36710.58 | AF17: 125421.33 | AG17: 211185.99 | AH17: 404 | AI17: 48531.76 | AJ17: 30608.82 | AK17: 129772.16 | AL17: 208912.74 | AM17: RES | AN17: 98901 | AO17: 211 | AP17: 26722.79 | AQ17: 14655.06 | AR17: 64402.3 | AS17: 105780.15 | AT17: 273 | AU17: 23274.18 | AV17: 18765.14 | AW17: 59339.41 | AX17: 101378.73 | AY17: 288 | AZ17: 19098.05 | BA17: 18716.6 | BB17: 68141.53 | BC17: 105956.18 | BD17: COM | BE17: 98948 | BF17: 12 | BG17: 7009.14 | BH17: 6796.64 | BI17: 12804.87 | BJ17: 26610.65 | BK17: COM | BL17: 98948 | BM17: 10 | BN17: 1313.7 | BO17: 5363.27 | BP17: 8252.94 | BQ17: 14929.91 | BR17: COM | BS17: 98948 | BT17: 11 | BU17: 2391.38 | BV17: 3562.5 | BW17: 9960.16 | BX17: 15914.04 | CH17: =A17 -> COM | CI17: =B17 -> 98935 | CJ17: =D17*1.6%+E17*6.3%+F17*28.9% -> 1015.9183 | CK17: =H17 -> COM | CL17: =I17 -> 98935 | CM17: =K17*1.6%+L17*6.3%+M17*28.9% -> 1151.1703 | CN17: =O17 -> COM | CO17: =P17 -> 98935 | CP17: =R17*1.6%+S17*6.3%+T17*28.9% -> 1226.0212 | DD17: 98921 | DE17: RES | DF17: 1 | DG17: 98930 | DH17: RES | DI17: 10 | DJ17: 98932 | DK17: RES | DL17: 8 | DM17: 98935RES | DN17: 10833.52 | DO17: 98935RES | DP17: 4970.01 | DQ17: 98935RES | DR17: 987.61 | DS17: 99328COM | DT17: 55.27 | DU17: 98944RES | DV17: 57.73 | DW17: 99347RES | DX17: 38.24
A18: COM | B18: 98936 | C18: 22 | D18: 5597.76 | E18: 3459.05 | F18: 10766.45 | G18: 19823.26 | H18: COM | I18: 98936 | J18: 28 | K18: 2671.01 | L18: 4117.4 | M18: 13328.91 | N18: 20117.32 | O18: COM | P18: 98936 | Q18: 23 | R18: 1451.96 | S18: 1007.84 | T18: 12022.74 | U18: 14482.54 | V18: RES | W18: 98903 | X18: 154 | Y18: 12124.11 | Z18: 17322.79 | AA18: 46842.47 | AB18: 76289.37 | AC18: 135 | AD18: 23367.7 | AE18: 12528.06 | AF18: 42778.3 | AG18: 78674.06 | AH18: 128 | AI18: 19977.45 | AJ18: 15623.97 | AK18: 39963.99 | AL18: 75565.41 | AM18: RES | AN18: 98902 | AO18: 365 | AP18: 40123.88 | AQ18: 21211.61 | AR18: 81045.71 | AS18: 142381.2 | AT18: 462 | AU18: 36110.45 | AV18: 31734.28 | AW18: 76670.48 | AX18: 144515.21 | AY18: 450 | AZ18: 27560.96 | BA18: 27924.91 | BB18: 90407.96 | BC18: 145893.83 | BD18: COM | BE18: 98951 | BG18: 0 | BH18: 0 | BI18: 0 | BJ18: 0 | BK18: COM | BL18: 98951 | BM18: 1 | BN18: 13.93 | BO18: 0 | BP18: 0 | BQ18: 13.93 | BR18: COM | BS18: 98951 | BU18: 0 | BV18: 0 | BW18: 0 | BX18: 0 | CH18: =A18 -> COM | CI18: =B18 -> 98936 | CJ18: =D18*1.6%+E18*6.3%+F18*28.9% -> 3418.9884 | CK18: =H18 -> COM | CL18: =I18 -> 98936 | CM18: =K18*1.6%+L18*6.3%+M18*28.9% -> 4154.1873 | CN18: =O18 -> COM | CO18: =P18 -> 98936 | CP18: =R18*1.6%+S18*6.3%+T18*28.9% -> 3561.2971 | DD18: 98930 | DE18: RES | DF18: 10 | DG18: 98932 | DH18: RES | DI18: 10 | DJ18: 98935 | DK18: RES | DL18: 5 | DM18: 98936COM | DN18: 3408.66 | DO18: 98936RES | DP18: 1795.84 | DQ18: 98936RES | DR18: 8728.69 | DS18: 99328RES | DT18: 420.68 | DU18: 98947RES | DV18: 366.25 | DW18: 99361RES | DX18: 62.37
A19: COM | B19: 98937 | C19: 30 | D19: 7391.49 | E19: 4778.65 | F19: 8347.56 | G19: 20517.7 | H19: COM | I19: 98937 | J19: 23 | K19: 22048.7 | L19: 2871.67 | M19: 10115.21 | N19: 35035.58 | O19: COM | P19: 98937 | Q19: 24 | R19: 4627.24 | S19: 2140.11 | T19: 10508.45 | U19: 17275.8 | V19: RES | W19: 98908 | X19: 134 | Y19: 20642.35 | Z19: 10329.73 | AA19: 39272.14 | AB19: 70244.22 | AC19: 122 | AD19: 17080.96 | AE19: 14339.39 | AF19: 39897.89 | AG19: 71318.24 | AH19: 129 | AI19: 17412.43 | AJ19: 12146.71 | AK19: 40888.28 | AL19: 70447.42 | AM19: RES | AN19: 98903 | AO19: 80 | AP19: 16663.53 | AQ19: 5417.21 | AR19: 25254.27 | AS19: 47335.01 | AT19: 113 | AU19: 11637.79 | AV19: 10980.17 | AW19: 25342.27 | AX19: 47960.23 | AY19: 112 | AZ19: 6240.24 | BA19: 11103.55 | BB19: 28124.94 | BC19: 45468.73 | BD19: COM | BE19: 98952 | BF19: 1 | BG19: 9.94 | BH19: 0 | BI19: 0 | BJ19: 9.94 | BK19: COM | BL19: 98952 | BM19: 1 | BN19: 78.38 | BO19: 9.94 | BP19: 0 | BQ19: 88.32 | BR19: COM | BS19: 98952 | BT19: 1 | BU19: 93.93 | BV19: 78.38 | BW19: 9.94 | BX19: 182.25 | CH19: =A19 -> COM | CI19: =B19 -> 98937 | CJ19: =D19*1.6%+E19*6.3%+F19*28.9% -> 2831.7636 | CK19: =H19 -> COM | CL19: =I19 -> 98937 | CM19: =K19*1.6%+L19*6.3%+M19*28.9% -> 3456.9901 | CN19: =O19 -> COM | CO19: =P19 -> 98937 | CP19: =R19*1.6%+S19*6.3%+T19*28.9% -> 3245.8048 | DD19: 98932 | DE19: RES | DF19: 4 | DG19: 98935 | DH19: RES | DI19: 8 | DJ19: 98936 | DK19: RES | DL19: 5 | DM19: 98936RES | DN19: 4000.92 | DO19: 98937RES | DP19: 2345.36 | DQ19: 98937RES | DR19: 364.77 | DS19: 99347COM | DT19: 112.08 | DU19: 98948RES | DV19: 717.42 | DW19: 99362RES | DX19: 251.57
A20: COM | B20: 98938 | C20: 10 | D20: 1289.72 | E20: 689.5 | F20: 2782.83 | G20: 4762.05 | H20: COM | I20: 98938 | J20: 10 | K20: 1068.61 | L20: 661.54 | M20: 3129.92 | N20: 4860.07 | O20: COM | P20: 98938 | Q20: 13 | R20: 38937.92 | S20: 769.53 | T20: 3791.46 | U20: 43498.91 | V20: RES | W20: 98921 | X20: 30 | Y20: 3313.14 | Z20: 1536.66 | AA20: 4328.84 | AB20: 9178.64 | AC20: 28 | AD20: 3243.89 | AE20: 2346.98 | AF20: 4639.58 | AG20: 10230.45 | AH20: 30 | AI20: 3107.67 | AJ20: 2536.59 | AK20: 5123.18 | AL20: 10767.44 | AM20: RES | AN20: 98908 | AO20: 138 | AP20: 17828.72 | AQ20: 9196.4 | AR20: 41411.76 | AS20: 68436.88 | AT20: 127 | AU20: 11302.89 | AV20: 9409.55 | AW20: 28493.63 | AX20: 49206.07 | AY20: 141 | AZ20: 9534.85 | BA20: 9004.51 | BB20: 33980.02 | BC20: 52519.38 | BD20: COM | BE20: 98953 | BF20: 2 | BG20: 103.17 | BH20: 99.01 | BI20: 2132.19 | BJ20: 2334.37 | BK20: COM | BL20: 98953 | BM20: 2 | BN20: 103.58 | BO20: 103.17 | BP20: 2231.2 | BQ20: 2437.95 | BR20: COM | BS20: 98953 | BT20: 2 | BU20: 98.37 | BV20: 103.58 | BW20: 2334.37 | BX20: 2536.32 | CH20: =A20 -> COM | CI20: =B20 -> 98938 | CJ20: =D20*1.6%+E20*6.3%+F20*28.9% -> 868.31189 | CK20: =H20 -> COM | CL20: =I20 -> 98938 | CM20: =K20*1.6%+L20*6.3%+M20*28.9% -> 963.32166 | CN20: =O20 -> COM | CO20: =P20 -> 98938 | CP20: =R20*1.6%+S20*6.3%+T20*28.9% -> 1767.219 | DD20: 98933 | DE20: RES | DF20: 3 | DG20: 98936 | DH20: RES | DI20: 5 | DJ20: 98937 | DK20: RES | DL20: 1 | DM20: 98937RES | DN20: 1717.83 | DO20: 98938RES | DP20: 8805.58 | DQ20: 98938RES | DR20: 18833.21 | DS20: 99362RES | DT20: 676.85 | DU20: 98951RES | DV20: 4047.04
A21: COM | B21: 98939 | C21: 3 | D21: 581.22 | E21: 356.52 | F21: 0 | G21: 937.74 | H21: COM | I21: 98939 | J21: 2 | K21: 479.74 | L21: 294.99 | M21: 336.27 | N21: 1111 | O21: COM | P21: 98939 | Q21: 2 | R21: 514.52 | S21: 479.74 | T21: 631.26 | U21: 1625.52 | V21: RES | W21: 98923 | X21: 12 | Y21: 1420.98 | Z21: 313.94 | AA21: 413.26 | AB21: 2148.18 | AC21: 10 | AD21: 956.47 | AE21: 378.18 | AF21: 613.78 | AG21: 1948.43 | AH21: 7 | AI21: 902.12 | AJ21: 540.22 | AK21: 504.24 | AL21: 1946.58 | AM21: RES | AN21: 98921 | AO21: 23 | AP21: 2429.46 | AQ21: 1661.63 | AR21: 2633.09 | AS21: 6724.18 | AT21: 17 | AU21: 1035.63 | AV21: 1118.93 | AW21: 812.84 | AX21: 2967.4 | AY21: 18 | AZ21: 1039.66 | BA21: 965.9 | BB21: 1440.77 | BC21: 3446.33 | BD21: COM | BE21: 99323 | BF21: 1 | BG21: 66.91 | BH21: 0 | BI21: 0 | BJ21: 66.91 | BK21: COM | BL21: 99323 | BM21: 1 | BN21: 71.06 | BO21: 66.91 | BP21: 0 | BQ21: 137.97 | BR21: COM | BS21: 99323 | BT21: 1 | BU21: 45.1 | BV21: 36.22 | BW21: 0 | BX21: 81.32 | CH21: =A21 -> COM | CI21: =B21 -> 98939 | CJ21: =D21*1.6%+E21*6.3%+F21*28.9% -> 31.76028 | CK21: =H21 -> COM | CL21: =I21 -> 98939 | CM21: =K21*1.6%+L21*6.3%+M21*28.9% -> 123.44224 | CN21: =O21 -> COM | CO21: =P21 -> 98939 | CP21: =R21*1.6%+S21*6.3%+T21*28.9% -> 220.89008 | DD21: 98935 | DE21: RES | DF21: 1 | DG21: 98937 | DH21: RES | DI21: 4 | DJ21: 98938 | DK21: RES | DL21: 5 | DM21: 98938RES | DN21: 8217.83 | DO21: 98942RES | DP21: 3237.13 | DQ21: 98942RES | DR21: 13015.95 | DU21: 98953RES | DV21: 39.5
A22: COM | B22: 98942 | C22: 75 | D22: 97876.77 | E22: 6696.17 | F22: 26033.23 | G22: 130606.17 | H22: COM | I22: 98942 | J22: 61 | K22: 8271.08 | L22: 5996.71 | M22: 28986.47 | N22: 43254.26 | O22: COM | P22: 98942 | Q22: 58 | R22: 7333.03 | S22: 4775.02 | T22: 26280.99 | U22: 38389.04 | V22: RES | W22: 98930 | X22: 126 | Y22: 13777.86 | Z22: 2546.38 | AA22: 23293.82 | AB22: 39618.06 | AC22: 129 | AD22: 18660.63 | AE22: 9575.59 | AF22: 19541.33 | AG22: 47777.55 | AH22: 117 | AI22: 14596.07 | AJ22: 12011.65 | AK22: 22702.27 | AL22: 49309.99 | AM22: RES | AN22: 98923 | AO22: 7 | AP22: 972.86 | AQ22: 816.88 | AR22: 1136.38 | AS22: 2926.12 | AT22: 7 | AU22: 743.91 | AV22: 529.93 | AW22: 436.44 | AX22: 1710.28 | AY22: 6 | AZ22: 418.68 | BA22: 449 | BB22: 319.15 | BC22: 1186.83 | BD22: COM | BE22: 99324 | BF22: 1 | BG22: 14.14 | BH22: 14.02 | BI22: 803.96 | BJ22: 832.12 | BK22: COM | BL22: 99324 | BM22: 1 | BN22: 14.14 | BO22: 14.14 | BP22: 817.98 | BQ22: 846.26 | BR22: COM | BS22: 99324 | BT22: 1 | BU22: 14.05 | BV22: 14.14 | BW22: 832.12 | BX22: 860.31 | CH22: =A22 -> COM | CI22: =B22 -> 98942 | CJ22: =D22*1.6%+E22*6.3%+F22*28.9% -> 9511.4905 | CK22: =H22 -> COM | CL22: =I22 -> 98942 | CM22: =K22*1.6%+L22*6.3%+M22*28.9% -> 8887.2198 | CN22: =O22 -> COM | CO22: =P22 -> 98942 | CP22: =R22*1.6%+S22*6.3%+T22*28.9% -> 8013.3609 | DD22: 98936 | DE22: RES | DF22: 2 | DG22: 98938 | DH22: RES | DI22: 2 | DJ22: 98942 | DK22: RES | DL22: 15 | DM22: 98939RES | DN22: 323.75 | DO22: 98944COM | DP22: 26.13 | DQ22: 98944RES | DR22: 15281.88 | DU22: 99324RES | DV22: 557.77
A23: COM | B23: 98944 | C23: 120 | D23: 27287.89 | E23: 16270.63 | F23: 83869.22 | G23: 127427.74 | H23: COM | I23: 98944 | J23: 110 | K23: 21976.59 | L23: 14617.51 | M23: 93239.29 | N23: 129833.39 | O23: COM | P23: 98944 | Q23: 122 | R23: 43262.88 | S23: 12893.66 | T23: 92795.57 | U23: 148952.11 | V23: RES | W23: 98932 | X23: 65 | Y23: 9483.39 | Z23: 4037.57 | AA23: 9259.33 | AB23: 22780.29 | AC23: 60 | AD23: 8412.24 | AE23: 6164.99 | AF23: 11314.84 | AG23: 25892.07 | AH23: 52 | AI23: 8369.97 | AJ23: 5313.69 | AK23: 13230.82 | AL23: 26914.48 | AM23: RES | AN23: 98930 | AO23: 122 | AP23: 16865.72 | AQ23: 5815.58 | AR23: 16871.65 | AS23: 39552.95 | AT23: 106 | AU23: 9592.43 | AV23: 10715.22 | AW23: 17200.75 | AX23: 37508.4 | AY23: 94 | AZ23: 6676.54 | BA23: 6496.7 | BB23: 20503.23 | BC23: 33676.47 | BD23: COM | BE23: 99328 | BG23: 0 | BH23: 0 | BI23: 0 | BJ23: 0 | BK23: COM | BL23: 99328 | BN23: 0 | BO23: 0 | BP23: 0 | BQ23: 0 | BR23: COM | BS23: 99328 | BU23: 0 | BV23: 0 | BW23: 0 | BX23: 0 | CH23: =A23 -> COM | CI23: =B23 -> 98944 | CJ23: =D23*1.6%+E23*6.3%+F23*28.9% -> 25699.861 | CK23: =H23 -> COM | CL23: =I23 -> 98944 | CM23: =K23*1.6%+L23*6.3%+M23*28.9% -> 28218.683 | CN23: =O23 -> COM | CO23: =P23 -> 98944 | CP23: =R23*1.6%+S23*6.3%+T23*28.9% -> 28322.426 | DD23: 98937 | DE23: RES | DF23: 3 | DG23: 98942 | DH23: RES | DI23: 8 | DJ23: 98944 | DK23: RES | DL23: 24 | DM23: 98942RES | DN23: 6153.13 | DO23: 98944RES | DP23: 8601.64 | DQ23: 98948RES | DR23: 12896.43 | DU23: 99360RES | DV23: 100
A24: COM | B24: 98947 | C24: 13 | D24: 9338.7 | E24: 1724.67 | F24: 3152.09 | G24: 14215.46 | H24: COM | I24: 98947 | J24: 10 | K24: 6816.13 | L24: 7329.66 | M24: 3281.97 | N24: 17427.76 | O24: COM | P24: 98947 | Q24: 12 | R24: 7065.03 | S24: 6701.99 | T24: 5517.69 | U24: 19284.71 | V24: RES | W24: 98933 | X24: 13 | Y24: 2066.14 | Z24: 946.89 | AA24: 4403.78 | AB24: 7416.81 | AC24: 16 | AD24: 2809.68 | AE24: 1645.77 | AF24: 3636.87 | AG24: 8092.32 | AH24: 13 | AI24: 2769.96 | AJ24: 1606.1 | AK24: 4285.37 | AL24: 8661.43 | AM24: RES | AN24: 98932 | AO24: 70 | AP24: 8042.11 | AQ24: 5124.98 | AR24: 11746.42 | AS24: 24913.51 | AT24: 65 | AU24: 6887.6 | AV24: 5470.83 | AW24: 12364.87 | AX24: 24723.3 | AY24: 62 | AZ24: 4633.95 | BA24: 4489.86 | BB24: 13716.31 | BC24: 22840.12 | BD24: COM | BE24: 99347 | BF24: 2 | BG24: 264.07 | BH24: 315.29 | BI24: 122.47 | BJ24: 701.83 | BK24: COM | BL24: 99347 | BM24: 2 | BN24: 186.18 | BO24: 130.81 | BP24: 290.61 | BQ24: 607.6 | BR24: COM | BS24: 99347 | BT24: 2 | BU24: 204.17 | BV24: 186.18 | BW24: 421.42 | BX24: 811.77 | CH24: =A24 -> COM | CI24: =B24 -> 98947 | CJ24: =D24*1.6%+E24*6.3%+F24*28.9% -> 1169.0274 | CK24: =H24 -> COM | CL24: =I24 -> 98947 | CM24: =K24*1.6%+L24*6.3%+M24*28.9% -> 1519.316 | CN24: =O24 -> COM | CO24: =P24 -> 98947 | CP24: =R24*1.6%+S24*6.3%+T24*28.9% -> 2129.8783 | DD24: 98938 | DE24: RES | DF24: 4 | DG24: 98944 | DH24: RES | DI24: 14 | DJ24: 98948 | DK24: RES | DL24: 10 | DM24: 98944RES | DN24: 13567.78 | DO24: 98947RES | DP24: 1998.21 | DQ24: 98951RES | DR24: 10743.41 | DU24: 99362RES | DV24: 485.87
A25: COM | B25: 98948 | C25: 104 | D25: 56410.3 | E25: 32482.22 | F25: 96251.63 | G25: 185144.15 | H25: COM | I25: 98948 | J25: 80 | K25: 33468.89 | L25: 25782.12 | M25: 88742.21 | N25: 147993.22 | O25: COM | P25: 98948 | Q25: 64 | R25: 12229.41 | S25: 18023.5 | T25: 100905.83 | U25: 131158.74 | V25: RES | W25: 98935 | X25: 34 | Y25: 133.03 | Z25: 4183.79 | AA25: 11296.63 | AB25: 15613.45 | AC25: 36 | AD25: 5386.19 | AE25: 3199.79 | AF25: 9655.13 | AG25: 18241.11 | AH25: 35 | AI25: 4519.24 | AJ25: 3991.81 | AK25: 11393.04 | AL25: 19904.09 | AM25: RES | AN25: 98933 | AO25: 14 | AP25: 2979.36 | AQ25: 1537.01 | AR25: 3997.55 | AS25: 8513.92 | AT25: 13 | AU25: 1970.31 | AV25: 1584.28 | AW25: 2184.11 | AX25: 5738.7 | AY25: 14 | AZ25: 1288.82 | BA25: 1610.39 | BB25: 2290.59 | BC25: 5189.8 | BD25: COM | BE25: 99362 | BF25: 1 | BG25: 20.4 | BH25: 0.07 | BI25: 0 | BJ25: 20.47 | BK25: COM | BL25: 99362 | BM25: 1 | BN25: 16.15 | BO25: 0 | BP25: 0 | BQ25: 16.15 | BR25: COM | BS25: 99362 | BT25: 1 | BU25: 14.29 | BV25: 16.15 | BW25: 0 | BX25: 30.44 | CH25: =A25 -> COM | CI25: =B25 -> 98948 | CJ25: =D25*1.6%+E25*6.3%+F25*28.9% -> 30765.666 | CK25: =H25 -> COM | CL25: =I25 -> 98948 | CM25: =K25*1.6%+L25*6.3%+M25*28.9% -> 27806.274 | CN25: =O25 -> COM | CO25: =P25 -> 98948 | CP25: =R25*1.6%+S25*6.3%+T25*28.9% -> 30492.936 | DD25: 98939 | DE25: RES | DF25: 1 | DG25: 98947 | DH25: RES | DI25: 2 | DJ25: 98951 | DK25: RES | DL25: 11 | DM25: 98947RES | DN25: 14766.66 | DO25: 98948COM | DP25: 605.54 | DQ25: 98952RES | DR25: 151 | DU25: COM | DV25: 26.47
A26: COM | B26: 98951 | C26: 92 | D26: 42288.79 | E26: 17095.85 | F26: 34658.42 | G26: 94043.06 | H26: COM | I26: 98951 | J26: 87 | K26: 58290.71 | L26: 26554.43 | M26: 29750.82 | N26: 114595.96 | O26: COM | P26: 98951 | Q26: 86 | R26: 58934.66 | S26: 15981.27 | T26: 35653.75 | U26: 110569.68 | V26: RES | W26: 98936 | X26: 13 | Y26: 1614.18 | Z26: 0 | AA26: 3178.03 | AB26: 4792.21 | AC26: 18 | AD26: 2667.92 | AE26: 1196.54 | AF26: 2449.58 | AG26: 6314.04 | AH26: 18 | AI26: 2339.2 | AJ26: 1467.6 | AK26: 2548.02 | AL26: 6354.82 | AM26: RES | AN26: 98935 | AO26: 18 | AP26: 3649.1 | AQ26: 2854.53 | AR26: 7538.88 | AS26: 14042.51 | AT26: 27 | AU26: 2949.81 | AV26: 2544.98 | AW26: 8319.78 | AX26: 13814.57 | AY26: 23 | AZ26: 1887.09 | BA26: 1954.66 | BB26: 9184.82 | BC26: 13026.57 | BD26: RES | BE26: 98901 | BF26: 276 | BG26: 29701.45 | BH26: 27198.72 | BI26: 73685.27 | BJ26: 130585.44 | BK26: RES | BL26: 98901 | BM26: 297 | BN26: 27098.72 | BO26: 22853.77 | BP26: 82064.96 | BQ26: 132017.45 | BR26: RES | BS26: 98901 | BT26: 307 | BU26: 26939.04 | BV26: 20948.38 | BW26: 71511.89 | BX26: 119399.31 | CH26: =A26 -> COM | CI26: =B26 -> 98951 | CJ26: =D26*1.6%+E26*6.3%+F26*28.9% -> 11769.943 | CK26: =H26 -> COM | CL26: =I26 -> 98951 | CM26: =K26*1.6%+L26*6.3%+M26*28.9% -> 11203.567 | CN26: =O26 -> COM | CO26: =P26 -> 98951 | CP26: =R26*1.6%+S26*6.3%+T26*28.9% -> 12253.708 | DD26: 98942 | DE26: RES | DF26: 12 | DG26: 98948 | DH26: RES | DI26: 15 | DJ26: 98952 | DK26: RES | DL26: 1 | DM26: 98948RES | DN26: 1263.41 | DO26: 98948RES | DP26: 9730.01 | DQ26: 98953RES | DR26: 3068.56
A27: COM | B27: 98952 | C27: 6 | D27: 1422.5 | E27: 1367.54 | F27: 901.1 | G27: 3691.14 | H27: COM | I27: 98952 | J27: 16 | K27: 7450.23 | L27: 1422.5 | M27: 2268.64 | N27: 11141.37 | O27: COM | P27: 98952 | Q27: 7 | R27: 1688.1 | S27: 290.47 | T27: 1212.77 | U27: 3191.34 | V27: RES | W27: 98937 | X27: 14 | Y27: 2263.73 | Z27: 935.78 | AA27: 1307.76 | AB27: 4507.27 | AC27: 13 | AD27: 2250.49 | AE27: 1471.5 | AF27: 1928.42 | AG27: 5650.41 | AH27: 12 | AI27: 2113.25 | AJ27: 1943.68 | AK27: 2633.01 | AL27: 6689.94 | AM27: RES | AN27: 98936 | AO27: 20 | AP27: 3342.97 | AQ27: 1878.65 | AR27: 6397.6 | AS27: 11619.22 | AT27: 20 | AU27: 2370.23 | AV27: 2506.62 | AW27: 6613.55 | AX27: 11490.4 | AY27: 26 | AZ27: 2073.31 | BA27: 2324.03 | BB27: 8257.89 | BC27: 12655.23 | BD27: RES | BE27: 98902 | BF27: 458 | BG27: 58575.74 | BH27: 45271.31 | BI27: 110215.08 | BJ27: 214062.13 | BK27: RES | BL27: 98902 | BM27: 450 | BN27: 35252.86 | BO27: 43073.04 | BP27: 120299.23 | BQ27: 198625.13 | BR27: RES | BS27: 98902 | BT27: 455 | BU27: 33733.47 | BV27: 32351.43 | BW27: 127268.74 | BX27: 193353.64 | CH27: =A27 -> COM | CI27: =B27 -> 98952 | CJ27: =D27*1.6%+E27*6.3%+F27*28.9% -> 369.33292 | CK27: =H27 -> COM | CL27: =I27 -> 98952 | CM27: =K27*1.6%+L27*6.3%+M27*28.9% -> 864.45814 | CN27: =O27 -> COM | CO27: =P27 -> 98952 | CP27: =R27*1.6%+S27*6.3%+T27*28.9% -> 395.79974 | DD27: 98944 | DE27: RES | DF27: 18 | DG27: 98951 | DH27: RES | DI27: 8 | DJ27: 98953 | DK27: RES | DL27: 6 | DM27: 98951COM | DN27: 107.29 | DO27: 98951RES | DP27: 20134.91 | DQ27: 99324RES | DR27: 3258.04
A28: COM | B28: 98953 | C28: 53 | D28: 6883.12 | E28: 2767.15 | F28: 17351.46 | G28: 27001.73 | H28: COM | I28: 98953 | J28: 44 | K28: 10214.75 | L28: 2296.93 | M28: 18081.52 | N28: 30593.2 | O28: COM | P28: 98953 | Q28: 34 | R28: 4194.79 | S28: 2174.14 | T28: 18948.94 | U28: 25317.87 | V28: RES | W28: 98938 | X28: 21 | Y28: 3998.15 | Z28: 1858.46 | AA28: 3204.29 | AB28: 9060.9 | AC28: 25 | AD28: 4314.86 | AE28: 2949.12 | AF28: 4587.08 | AG28: 11851.06 | AH28: 18 | AI28: 3815.49 | AJ28: 2717.98 | AK28: 6047.83 | AL28: 12581.3 | AM28: RES | AN28: 98937 | AO28: 16 | AP28: 2550.34 | AQ28: 589.24 | AR28: 1533.27 | AS28: 4672.85 | AT28: 18 | AU28: 1813.83 | AV28: 1871.56 | AW28: 884.96 | AX28: 4570.35 | AY28: 17 | AZ28: 1282.14 | BA28: 1505.99 | BB28: 1558.97 | BC28: 4347.1 | BD28: RES | BE28: 98903 | BF28: 138 | BG28: 23488.42 | BH28: 14942.63 | BI28: 41139.63 | BJ28: 79570.68 | BK28: RES | BL28: 98903 | BM28: 131 | BN28: 11961.58 | BO28: 16621.48 | BP28: 46174.6 | BQ28: 74757.66 | BR28: RES | BS28: 98903 | BT28: 141 | BU28: 14534.39 | BV28: 12379.46 | BW28: 51631.19 | BX28: 78545.04 | CH28: =A28 -> COM | CI28: =B28 -> 98953 | CJ28: =D28*1.6%+E28*6.3%+F28*28.9% -> 5299.0323 | CK28: =H28 -> COM | CL28: =I28 -> 98953 | CM28: =K28*1.6%+L28*6.3%+M28*28.9% -> 5533.7019 | CN28: =O28 -> COM | CO28: =P28 -> 98953 | CP28: =R28*1.6%+S28*6.3%+T28*28.9% -> 5680.3311 | DD28: 98947 | DE28: RES | DF28: 4 | DG28: 98952 | DH28: RES | DI28: 1 | DJ28: 99324 | DK28: RES | DL28: 8 | DM28: 98951RES | DN28: 9061.77 | DO28: 98952RES | DP28: 184.94 | DQ28: 99328RES | DR28: 1257.81
A29: COM | B29: 99301 | D29: 0 | E29: 0 | F29: 0 | G29: 0 | H29: COM | I29: 99301 | K29: 0 | L29: 0 | M29: 0 | N29: 0 | O29: COM | P29: 99301 | R29: 0 | S29: 0 | T29: 0 | U29: 0 | V29: RES | W29: 98939 | X29: 2 | Y29: 297.96 | Z29: 166.29 | AA29: 464.19 | AB29: 928.44 | AC29: 2 | AD29: 302.51 | AE29: 297.96 | AF29: 326.63 | AG29: 927.1 | AH29: 3 | AI29: 430.87 | AJ29: 302.51 | AK29: 624.59 | AL29: 1357.97 | AM29: RES | AN29: 98938 | AO29: 20 | AP29: 2877.34 | AQ29: 2598.45 | AR29: 5369.68 | AS29: 10845.47 | AT29: 20 | AU29: 2185.41 | AV29: 2187.22 | AW29: 7354.56 | AX29: 11727.19 | AY29: 16 | AZ29: 1290.65 | BA29: 1464.5 | BB29: 7747.07 | BC29: 10502.22 | BD29: RES | BE29: 98908 | BF29: 147 | BG29: 16924.82 | BH29: 13056.85 | BI29: 26597.22 | BJ29: 56578.89 | BK29: RES | BL29: 98908 | BM29: 164 | BN29: 16093.68 | BO29: 13318.2 | BP29: 32940.1 | BQ29: 62351.98 | BR29: RES | BS29: 98908 | BT29: 169 | BU29: 14945.68 | BV29: 12526.55 | BW29: 35393.83 | BX29: 62866.06 | CH29: =A29 -> COM | CI29: =B29 -> 99301 | CJ29: =D29*1.6%+E29*6.3%+F29*28.9% -> 0 | CK29: =H29 -> COM | CL29: =I29 -> 99301 | CM29: =K29*1.6%+L29*6.3%+M29*28.9% -> 0 | CN29: =O29 -> COM | CO29: =P29 -> 99301 | CP29: =R29*1.6%+S29*6.3%+T29*28.9% -> 0 | DD29: 98948 | DE29: RES | DF29: 4 | DG29: 98953 | DH29: RES | DI29: 4 | DJ29: 99328 | DK29: RES | DL29: 4 | DM29: 98953RES | DN29: 815.67 | DO29: 98953RES | DP29: 1075.37 | DQ29: 99347RES | DR29: 5187.25
A30: COM | B30: 99323 | C30: 11 | D30: 4195.21 | E30: 3288.76 | F30: 6324.62 | G30: 13808.59 | H30: COM | I30: 99323 | J30: 11 | K30: 3753.46 | L30: 2908.48 | M30: 9229.96 | N30: 15891.9 | O30: COM | P30: 99323 | Q30: 9 | R30: 3323.06 | S30: 2145.01 | T30: 9124.04 | U30: 14592.11 | V30: RES | W30: 98942 | X30: 53 | Y30: 7811.31 | Z30: 3574.8 | AA30: 18230.71 | AB30: 29616.82 | AC30: 59 | AD30: 8228.74 | AE30: 5531.73 | AF30: 18668.09 | AG30: 32428.56 | AH30: 60 | AI30: 6539.57 | AJ30: 6276.52 | AK30: 20773.29 | AL30: 33589.38 | AM30: RES | AN30: 98939 | AO30: 4 | AP30: 607.5 | AQ30: 319.6 | AR30: 101.06 | AS30: 1028.16 | AT30: 2 | AU30: 240.44 | AV30: 246.99 | AW30: 0 | AX30: 487.43 | AY30: 2 | AZ30: 175.95 | BA30: 240.44 | BB30: 246.99 | BC30: 663.38 | BD30: RES | BE30: 98921 | BF30: 26 | BG30: 3470.79 | BH30: 3385.47 | BI30: 4225.81 | BJ30: 11082.07 | BK30: RES | BL30: 98921 | BM30: 28 | BN30: 2625.79 | BO30: 2144.58 | BP30: 4419.4 | BQ30: 9189.77 | BR30: RES | BS30: 98921 | BT30: 28 | BU30: 2408.62 | BV30: 1972.36 | BW30: 3953.08 | BX30: 8334.06 | CH30: =A30 -> COM | CI30: =B30 -> 99323 | CJ30: =D30*1.6%+E30*6.3%+F30*28.9% -> 2102.1304 | CK30: =H30 -> COM | CL30: =I30 -> 99323 | CM30: =K30*1.6%+L30*6.3%+M30*28.9% -> 2910.748 | CN30: =O30 -> COM | CO30: =P30 -> 99323 | CP30: =R30*1.6%+S30*6.3%+T30*28.9% -> 2825.1522 | DD30: 98951 | DE30: RES | DF30: 7 | DG30: 99323 | DH30: RES | DI30: 2 | DJ30: 99347 | DK30: RES | DL30: 2 | DM30: 99323RES | DN30: 355.49 | DO30: 99323RES | DP30: 491.72 | DQ30: 99348RES | DR30: 167.2
A31: COM | B31: 99324 | C31: 13 | D31: 2033.82 | E31: 755.55 | F31: 9053.09 | G31: 11842.46 | H31: COM | I31: 99324 | J31: 11 | K31: 2941.88 | L31: 1612.36 | M31: 9022.36 | N31: 13576.6 | O31: COM | P31: 99324 | Q31: 12 | R31: 2039.44 | S31: 2365.62 | T31: 4272.84 | U31: 8677.9 | V31: RES | W31: 98944 | X31: 250 | Y31: 32273.29 | Z31: 15041.32 | AA31: 50308.32 | AB31: 97622.93 | AC31: 256 | AD31: 32186.19 | AE31: 21950.77 | AF31: 53139.29 | AG31: 107276.25 | AH31: 239 | AI31: 29404.71 | AJ31: 22802.91 | AK31: 61586.48 | AL31: 113794.1 | AM31: RES | AN31: 98942 | AO31: 57 | AP31: 7351.4 | AQ31: 3222.22 | AR31: 13116.01 | AS31: 23689.63 | AT31: 49 | AU31: 4615.22 | AV31: 4596.08 | AW31: 11373 | AX31: 20584.3 | AY31: 48 | AZ31: 4097.29 | BA31: 3561.12 | BB31: 14283.54 | BC31: 21941.95 | BD31: RES | BE31: 98923 | BF31: 3 | BG31: 438.19 | BH31: 415.54 | BI31: 169.1 | BJ31: 1022.83 | BK31: RES | BL31: 98923 | BM31: 5 | BN31: 808.41 | BO31: 438.19 | BP31: 446.82 | BQ31: 1693.42 | BR31: RES | BS31: 98923 | BT31: 5 | BU31: 707.31 | BV31: 683.41 | BW31: 765.47 | BX31: 2156.19 | CH31: =A31 -> COM | CI31: =B31 -> 99324 | CJ31: =D31*1.6%+E31*6.3%+F31*28.9% -> 2696.4838 | CK31: =H31 -> COM | CL31: =I31 -> 99324 | CM31: =K31*1.6%+L31*6.3%+M31*28.9% -> 2756.1108 | CN31: =O31 -> COM | CO31: =P31 -> 99324 | CP31: =R31*1.6%+S31*6.3%+T31*28.9% -> 1416.5159 | DD31: 98953 | DE31: RES | DF31: 4 | DG31: 99324 | DH31: RES | DI31: 15 | DJ31: 99348 | DK31: RES | DL31: 1 | DM31: 99324RES | DN31: 7074.19 | DO31: 99324RES | DP31: 3092.06 | DQ31: 99361RES | DR31: 62.37
A32: COM | B32: 99328 | C32: 47 | D32: 17155.7 | E32: 8776.68 | F32: 10676.64 | G32: 36609.02 | H32: COM | I32: 99328 | J32: 44 | K32: 17276.74 | L32: 8206.16 | M32: 9901.91 | N32: 35384.81 | O32: COM | P32: 99328 | Q32: 42 | R32: 16807.84 | S32: 13392.25 | T32: 14769.18 | U32: 44969.27 | V32: RES | W32: 98947 | X32: 26 | Y32: 4191.39 | Z32: 1967.64 | AA32: 7375.23 | AB32: 13534.26 | AC32: 23 | AD32: 3436.23 | AE32: 2624.47 | AF32: 5988.99 | AG32: 12049.69 | AH32: 23 | AI32: 3459.11 | AJ32: 2530.22 | AK32: 6666.49 | AL32: 12655.82 | AM32: RES | AN32: 98944 | AO32: 242 | AP32: 28305.73 | AQ32: 16468.01 | AR32: 43441.82 | AS32: 88215.56 | AT32: 221 | AU32: 18700.34 | AV32: 19176.35 | AW32: 44690.96 | AX32: 82567.65 | AY32: 204 | AZ32: 13329.59 | BA32: 13164.57 | BB32: 43049.88 | BC32: 69544.04 | BD32: RES | BE32: 98930 | BF32: 136 | BG32: 17023.75 | BH32: 14024.46 | BI32: 27506.23 | BJ32: 58554.44 | BK32: RES | BL32: 98930 | BM32: 140 | BN32: 10931.53 | BO32: 12675.89 | BP32: 32747.46 | BQ32: 56354.88 | BR32: RES | BS32: 98930 | BT32: 145 | BU32: 11697.85 | BV32: 8490.69 | BW32: 34549.82 | BX32: 54738.36 | CH32: =A32 -> COM | CI32: =B32 -> 99328 | CJ32: =D32*1.6%+E32*6.3%+F32*28.9% -> 3912.971 | CK32: =H32 -> COM | CL32: =I32 -> 99328 | CM32: =K32*1.6%+L32*6.3%+M32*28.9% -> 3655.0679 | CN32: =O32 -> COM | CO32: =P32 -> 99328 | CP32: =R32*1.6%+S32*6.3%+T32*28.9% -> 5380.9302 | DD32: 99323 | DE32: RES | DF32: 1 | DG32: 99328 | DH32: RES | DI32: 4 | DJ32: 99361 | DK32: RES | DL32: 2 | DM32: 99328COM | DN32: 55.27 | DO32: 99328RES | DP32: 1690.17 | DQ32: 99362COM | DR32: 34.46
A33: COM | B33: 99329 | C33: 4 | D33: 270.64 | E33: 236.98 | F33: 1715.21 | G33: 2222.83 | H33: COM | I33: 99329 | J33: 5 | K33: 216.17 | L33: 128.36 | M33: 1952.19 | N33: 2296.72 | O33: COM | P33: 99329 | Q33: 4 | R33: 101.13 | S33: 74.41 | T33: 2080.55 | U33: 2256.09 | V33: RES | W33: 98948 | X33: 240 | Y33: 25609.34 | Z33: 26396.11 | AA33: 74329.72 | AB33: 126335.17 | AC33: 210 | AD33: 26696.69 | AE33: 18613.46 | AF33: 81173.07 | AG33: 126483.22 | AH33: 211 | AI33: 32558.65 | AJ33: 20629.85 | AK33: 81261.08 | AL33: 134449.58 | AM33: RES | AN33: 98947 | AO33: 25 | AP33: 4306.41 | AQ33: 2346.75 | AR33: 8891.81 | AS33: 15544.97 | AT33: 22 | AU33: 2490.4 | AV33: 2515.06 | AW33: 4244.97 | AX33: 9250.43 | AY33: 22 | AZ33: 1908.73 | BA33: 2246.75 | BB33: 6391.64 | BC33: 10547.12 | BD33: RES | BE33: 98932 | BF33: 78 | BG33: 9035.14 | BH33: 9600.19 | BI33: 21997.42 | BJ33: 40632.75 | BK33: RES | BL33: 98932 | BM33: 79 | BN33: 6930.86 | BO33: 7225.56 | BP33: 26751.99 | BQ33: 40908.41 | BR33: RES | BS33: 98932 | BT33: 77 | BU33: 5786.41 | BV33: 4715.35 | BW33: 24621.63 | BX33: 35123.39 | CH33: =A33 -> COM | CI33: =B33 -> 99329 | CJ33: =D33*1.6%+E33*6.3%+F33*28.9% -> 514.95567 | CK33: =H33 -> COM | CL33: =I33 -> 99329 | CM33: =K33*1.6%+L33*6.3%+M33*28.9% -> 575.72831 | CN33: =O33 -> COM | CO33: =P33 -> 99329 | CP33: =R33*1.6%+S33*6.3%+T33*28.9% -> 607.58486 | DD33: 99324 | DE33: RES | DF33: 12 | DG33: 99347 | DH33: RES | DI33: 2 | DJ33: 99362 | DK33: RES | DL33: 31 | DM33: 99328RES | DN33: 7634.17 | DO33: 99347RES | DP33: 1231.29 | DQ33: 99362RES | DR33: 16224.52
A34: COM | B34: 99347 | C34: 21 | D34: 3623.39 | E34: 2578.83 | F34: 4116.7 | G34: 10318.92 | H34: COM | I34: 99347 | J34: 16 | K34: 1568.6 | L34: 1246.28 | M34: 4219.03 | N34: 7033.91 | O34: COM | P34: 99347 | Q34: 16 | R34: 4206.63 | S34: 1136.84 | T34: 1445.38 | U34: 6788.85 | V34: RES | W34: 98951 | X34: 264 | Y34: 49352.19 | Z34: 17325.08 | AA34: 146351.57 | AB34: 213028.84 | AC34: 262 | AD34: 48161.08 | AE34: 37597.67 | AF34: 145433.37 | AG34: 231192.12 | AH34: 256 | AI34: 45703.32 | AJ34: 35284.24 | AK34: 161485.21 | AL34: 242472.77 | AM34: RES | AN34: 98948 | AO34: 145 | AP34: 27504.92 | AQ34: 10251.75 | AR34: 48155.64 | AS34: 85912.31 | AT34: 233 | AU34: 22377.93 | AV34: 24984.61 | AW34: 59147.38 | AX34: 106509.92 | AY34: 212 | AZ34: 10667.67 | BA34: 22508.82 | BB34: 65902.67 | BC34: 99079.16 | BD34: RES | BE34: 98933 | BF34: 14 | BG34: 2729.33 | BH34: 2602.45 | BI34: 6010.59 | BJ34: 11342.37 | BK34: RES | BL34: 98933 | BM34: 13 | BN34: 1797.56 | BO34: 2211.19 | BP34: 7207.61 | BQ34: 11216.36 | BR34: RES | BS34: 98933 | BT34: 13 | BU34: 2040.01 | BV34: 1602.04 | BW34: 7732.01 | BX34: 11374.06 | CH34: =A34 -> COM | CI34: =B34 -> 99347 | CJ34: =D34*1.6%+E34*6.3%+F34*28.9% -> 1410.1668 | CK34: =H34 -> COM | CL34: =I34 -> 99347 | CM34: =K34*1.6%+L34*6.3%+M34*28.9% -> 1322.9129 | CN34: =O34 -> COM | CO34: =P34 -> 99347 | CP34: =R34*1.6%+S34*6.3%+T34*28.9% -> 556.64182 | DD34: 99328 | DE34: RES | DF34: 9 | DG34: 99360 | DH34: RES | DI34: 1 | DM34: 99347COM | DN34: 112.08 | DO34: 99360RES | DP34: 100
A35: COM | B35: 99348 | C35: 3 | D35: 158.79 | E35: 47.09 | F35: 16.1 | G35: 221.98 | H35: COM | I35: 99348 | J35: 2 | K35: 39.56 | L35: 29.03 | M35: 27.62 | N35: 96.21 | O35: COM | P35: 99348 | Q35: 3 | R35: 46.85 | S35: 31.33 | T35: 21.08 | U35: 99.26 | V35: RES | W35: 98952 | X35: 27 | Y35: 5309.04 | Z35: 2258.25 | AA35: 12663.8 | AB35: 20231.09 | AC35: 30 | AD35: 5355.17 | AE35: 3752.72 | AF35: 12814.35 | AG35: 21922.24 | AH35: 33 | AI35: 6475.17 | AJ35: 3998.76 | AK35: 15403.26 | AL35: 25877.19 | AM35: RES | AN35: 98951 | AO35: 252 | AP35: 41246.12 | AQ35: 16362.47 | AR35: 86720.59 | AS35: 144329.18 | AT35: 234 | AU35: 28423.09 | AV35: 30398.35 | AW35: 93627.23 | AX35: 152448.67 | AY35: 223 | AZ35: 19430.86 | BA35: 22086.77 | BB35: 110484.16 | BC35: 152001.79 | BD35: RES | BE35: 98935 | BF35: 53 | BG35: 7597.51 | BH35: 5564.05 | BI35: 12792.13 | BJ35: 25953.69 | BK35: RES | BL35: 98935 | BM35: 51 | BN35: 5099.76 | BO35: 4440.36 | BP35: 13162.66 | BQ35: 22702.78 | BR35: RES | BS35: 98935 | BT35: 49 | BU35: 5034.02 | BV35: 3266.15 | BW35: 13198.12 | BX35: 21498.29 | CH35: =A35 -> COM | CI35: =B35 -> 99348 | CJ35: =D35*1.6%+E35*6.3%+F35*28.9% -> 10.16021 | CK35: =H35 -> COM | CL35: =I35 -> 99348 | CM35: =K35*1.6%+L35*6.3%+M35*28.9% -> 10.44403 | CN35: =O35 -> COM | CO35: =P35 -> 99348 | CP35: =R35*1.6%+S35*6.3%+T35*28.9% -> 8.81551 | DD35: 99347 | DE35: RES | DF35: 1 | DG35: 99362 | DH35: RES | DI35: 42 | DM35: 99347RES | DN35: 634.5 | DO35: 99362RES | DP35: 15885
A36: COM | B36: 99360 | C36: 15 | D36: 16069.49 | E36: 2736.43 | F36: 8571.25 | G36: 27377.17 | H36: COM | I36: 99360 | J36: 11 | K36: 10447.9 | L36: 2276.19 | M36: 10135.12 | N36: 22859.21 | O36: COM | P36: 99360 | Q36: 8 | R36: 178.17 | S36: 1582.98 | T36: 12178.69 | U36: 13939.84 | V36: RES | W36: 98953 | X36: 39 | Y36: 6824.37 | Z36: 3635.88 | AA36: 10392.44 | AB36: 20852.69 | AC36: 40 | AD36: 6386.5 | AE36: 4892.48 | AF36: 8369.79 | AG36: 19648.77 | AH36: 35 | AI36: 6014.63 | AJ36: 4120.69 | AK36: 9096.86 | AL36: 19232.18 | AM36: RES | AN36: 98952 | AO36: 29 | AP36: 6534.07 | AQ36: 1791.72 | AR36: 4413.65 | AS36: 12739.44 | AT36: 30 | AU36: 4794.08 | AV36: 5893.54 | AW36: 5250.82 | AX36: 15938.44 | AY36: 33 | AZ36: 3531.29 | BA36: 3933.37 | BB36: 9761.04 | BC36: 17225.7 | BD36: RES | BE36: 98936 | BF36: 19 | BG36: 2761.93 | BH36: 1997.47 | BI36: 3061.31 | BJ36: 7820.71 | BK36: RES | BL36: 98936 | BM36: 21 | BN36: 2242.65 | BO36: 2042.75 | BP36: 3385.78 | BQ36: 7671.18 | BR36: RES | BS36: 98936 | BT36: 23 | BU36: 2599.53 | BV36: 1591.85 | BW36: 4533.21 | BX36: 8724.59 | CH36: =A36 -> COM | CI36: =B36 -> 99360 | CJ36: =D36*1.6%+E36*6.3%+F36*28.9% -> 2906.5982 | CK36: =H36 -> COM | CL36: =I36 -> 99360 | CM36: =K36*1.6%+L36*6.3%+M36*28.9% -> 3239.6161 | CN36: =O36 -> COM | CO36: =P36 -> 99360 | CP36: =R36*1.6%+S36*6.3%+T36*28.9% -> 3622.2199 | DD36: 99360 | DE36: RES | DF36: 2 | DM36: 99360RES | DN36: 581.82 | DO36: COM | DP36: 26.47
A37: COM | B37: 99361 | C37: 12 | D37: 1604.79 | E37: 746.15 | F37: 386.61 | G37: 2737.55 | H37: COM | I37: 99361 | J37: 10 | K37: 953.42 | L37: 603.03 | M37: 147 | N37: 1703.45 | O37: COM | P37: 99361 | Q37: 16 | R37: 1062.37 | S37: 416.94 | T37: 328.44 | U37: 1807.75 | V37: RES | W37: 99323 | X37: 11 | Y37: 1565.88 | Z37: 719.21 | AA37: 5132.3 | AB37: 7417.39 | AC37: 10 | AD37: 1410.49 | AE37: 1028.88 | AF37: 5233.76 | AG37: 7673.13 | AH37: 10 | AI37: 1480.58 | AJ37: 1131.39 | AK37: 6063.95 | AL37: 8675.92 | AM37: RES | AN37: 98953 | AO37: 37 | AP37: 4803.77 | AQ37: 2421.62 | AR37: 5650.22 | AS37: 12875.61 | AT37: 35 | AU37: 3004.71 | AV37: 2677.02 | AW37: 3091.13 | AX37: 8772.86 | AY37: 34 | AZ37: 2191.93 | BA37: 2202.48 | BB37: 4859.49 | BC37: 9253.9 | BD37: RES | BE37: 98937 | BF37: 15 | BG37: 2500.89 | BH37: 2814.87 | BI37: 4645.09 | BJ37: 9960.85 | BK37: RES | BL37: 98937 | BM37: 17 | BN37: 1977.44 | BO37: 2303.54 | BP37: 6391.57 | BQ37: 10672.55 | BR37: RES | BS37: 98937 | BT37: 14 | BU37: 1610.21 | BV37: 1250.18 | BW37: 3075.18 | BX37: 5935.57 | CH37: =A37 -> COM | CI37: =B37 -> 99361 | CJ37: =D37*1.6%+E37*6.3%+F37*28.9% -> 184.41438 | CK37: =H37 -> COM | CL37: =I37 -> 99361 | CM37: =K37*1.6%+L37*6.3%+M37*28.9% -> 95.72861 | CN37: =O37 -> COM | CO37: =P37 -> 99361 | CP37: =R37*1.6%+S37*6.3%+T37*28.9% -> 138.1843 | DD37: 99361 | DE37: RES | DF37: 1 | DM37: 99361RES | DN37: 154.21
A38: COM | B38: 99362 | C38: 95 | D38: 17490.85 | E38: 9785.2 | F38: 72174.68 | G38: 99450.73 | H38: COM | I38: 99362 | J38: 99 | K38: 18700.42 | L38: 8986.02 | M38: 73070.09 | N38: 100756.53 | O38: COM | P38: 99362 | Q38: 93 | R38: 12765.74 | S38: 8478.73 | T38: 78619.18 | U38: 99863.65 | V38: RES | W38: 99324 | X38: 68 | Y38: 6397.77 | Z38: 2948.25 | AA38: 15197.05 | AB38: 24543.07 | AC38: 71 | AD38: 6984.8 | AE38: 4229.49 | AF38: 13820.63 | AG38: 25034.92 | AH38: 64 | AI38: 6170.84 | AJ38: 4888.67 | AK38: 13614.1 | AL38: 24673.61 | AM38: RES | AN38: 99323 | AO38: 9 | AP38: 1939.47 | AQ38: 0 | AR38: 655.96 | AS38: 2595.43 | AT38: 8 | AU38: 654.37 | AV38: 837.34 | AW38: 1002.16 | AX38: 2493.87 | AY38: 6 | AZ38: 390 | BA38: 346.55 | BB38: 1115.77 | BC38: 1852.32 | BD38: RES | BE38: 98938 | BF38: 27 | BG38: 4694.07 | BH38: 3938.13 | BI38: 9232.82 | BJ38: 17865.02 | BK38: RES | BL38: 98938 | BM38: 28 | BN38: 3930.64 | BO38: 3900.69 | BP38: 11000.99 | BQ38: 18832.32 | BR38: RES | BS38: 98938 | BT38: 25 | BU38: 2700.38 | BV38: 2922.27 | BW38: 13392.73 | BX38: 19015.38 | CH38: =A38 -> COM | CI38: =B38 -> 99362 | CJ38: =D38*1.6%+E38*6.3%+F38*28.9% -> 21754.804 | CK38: =H38 -> COM | CL38: =I38 -> 99362 | CM38: =K38*1.6%+L38*6.3%+M38*28.9% -> 21982.582 | CN38: =O38 -> COM | CO38: =P38 -> 99362 | CP38: =R38*1.6%+S38*6.3%+T38*28.9% -> 23459.355 | DD38: 99362 | DE38: RES | DF38: 40 | DM38: 99362RES | DN38: 14294.13
A39: COM | B39: 99363 | C39: 4 | D39: 493.21 | E39: 0 | F39: 0 | G39: 493.21 | H39: COM | I39: 99363 | J39: 4 | K39: 314.57 | L39: 89.97 | M39: 0 | N39: 404.54 | O39: COM | P39: 99363 | R39: 0 | S39: 0 | T39: 0 | U39: 0 | V39: RES | W39: 99328 | X39: 50 | Y39: 6368.51 | Z39: 4246.66 | AA39: 15225 | AB39: 25840.17 | AC39: 59 | AD39: 8016.57 | AE39: 4903.72 | AF39: 17493.31 | AG39: 30413.6 | AH39: 54 | AI39: 7886.23 | AJ39: 6264.87 | AK39: 19913.81 | AL39: 34064.91 | AM39: RES | AN39: 99324 | AO39: 56 | AP39: 5516.22 | AQ39: 2245.42 | AR39: 9455.1 | AS39: 17216.74 | AT39: 53 | AU39: 3297.4 | AV39: 3233.45 | AW39: 7681.99 | AX39: 14212.84 | AY39: 58 | AZ39: 2984.47 | BA39: 2550.74 | BB39: 8668.63 | BC39: 14203.84 | BD39: RES | BE39: 98939 | BF39: 2 | BG39: 266.53 | BH39: 281.84 | BI39: 373 | BJ39: 921.37 | BK39: RES | BL39: 98939 | BM39: 1 | BN39: 84.68 | BO39: 0 | BP39: 0 | BQ39: 84.68 | BR39: RES | BS39: 98939 | BT39: 2 | BU39: 86.14 | BV39: 84.68 | BW39: 0 | BX39: 170.82 | CH39: =A39 -> COM | CI39: =B39 -> 99363 | CJ39: =D39*1.6%+E39*6.3%+F39*28.9% -> 7.89136 | CK39: =H39 -> COM | CL39: =I39 -> 99363 | CM39: =K39*1.6%+L39*6.3%+M39*28.9% -> 10.70123 | CN39: =O39 -> COM | CO39: =P39 -> 99363 | CP39: =R39*1.6%+S39*6.3%+T39*28.9% -> 0 | DD39: 99363 | DE39: RES | DF39: 1 | DM39: 99363RES | DN39: 2505.26
A40: COM | B40: WA | D40: 0 | E40: 0 | F40: 0 | G40: 0 | H40: COM | I40: WA | K40: 0 | L40: 0 | M40: 0 | N40: 0 | O40: COM | P40: WA | R40: 0 | S40: 0 | T40: 0 | U40: 0 | V40: RES | W40: 99329 | AC40: 1 | AD40: 38.52 | AE40: 0 | AF40: 0 | AG40: 38.52 | AH40: 1 | AI40: 52.38 | AJ40: 38.52 | AK40: 0 | AL40: 90.9 | AM40: RES | AN40: 99328 | AO40: 50 | AP40: 5974.77 | AQ40: 3424.52 | AR40: 13299.74 | AS40: 22699.03 | AT40: 59 | AU40: 5981.35 | AV40: 4858.56 | AW40: 15873.75 | AX40: 26713.66 | AY40: 57 | AZ40: 3983.29 | BA40: 4252.11 | BB40: 17676.76 | BC40: 25912.16 | BD40: RES | BE40: 98942 | BF40: 56 | BG40: 7143.9 | BH40: 4984.44 | BI40: 13728.32 | BJ40: 25856.66 | BK40: RES | BL40: 98942 | BM40: 64 | BN40: 6302.8 | BO40: 5814.3 | BP40: 15742.36 | BQ40: 27859.46 | BR40: RES | BS40: 98942 | BT40: 66 | BU40: 7520.26 | BV40: 4103.56 | BW40: 14601.3 | BX40: 26225.12 | CH40: =A40 -> COM | CI40: =B40 -> WA | CJ40: =D40*1.6%+E40*6.3%+F40*28.9% -> 0 | CK40: =H40 -> COM | CL40: =I40 -> WA | CM40: =K40*1.6%+L40*6.3%+M40*28.9% -> 0 | CN40: =O40 -> COM | CO40: =P40 -> WA | CP40: =R40*1.6%+S40*6.3%+T40*28.9% -> 0 | DF40: =SUM(DF13:DF39) -> 296 | DI40: =SUM(DI11:DI35) -> 337 | DL40: =SUM(DL10:DL33) -> 327 | DN40: =SUM(DN6,DN8:DN11,DN13,DN15:DN17,DN19:DN26,DN28:DN31,DN33,DN35:DN39) -> 336793.87 | DP40: =SUM(DP6,DP8,DP10:DP13,DP15:DP21,DP23:DP24,DP26:DP35) -> 234675.55 | DR40: =SUM(DR6,DR8:DR9,DR11:DR14,DR16:DR31,DR33) -> 252366.01 | DT40: =SUM(DT5:DT14,DT16,DT18,DT20) -> 10433.85 | DV40: =SUM(DV6,DV8:DV24) -> 11877.29 | DX40: =SUM(DX5:DX7,DX9:DX19) -> 2630.99
A41: RES | B41: 98603 | D41: 0 | E41: 0 | F41: 0 | G41: 0 | H41: RES | I41: 98603 | K41: 0 | L41: 0 | M41: 0 | N41: 0 | O41: RES | P41: 98603 | Q41: 1 | R41: 73.89 | S41: 0 | T41: 0 | U41: 73.89 | V41: RES | W41: 99347 | X41: 15 | Y41: 2121.62 | Z41: 1138.19 | AA41: 2862.71 | AB41: 6122.52 | AC41: 18 | AD41: 2195.03 | AE41: 1111.44 | AF41: 3449.29 | AG41: 6755.76 | AH41: 14 | AI41: 1611.96 | AJ41: 1601.55 | AK41: 3981.02 | AL41: 7194.53 | AM41: RES | AN41: 99329 | AO41: 1 | AP41: 58.34 | AQ41: 0 | AR41: 0 | AS41: 58.34 | AT41: 1 | AU41: 55.22 | AV41: 58.34 | AW41: 0 | AX41: 113.56 | AY41: 1 | AZ41: 49.43 | BA41: 55.22 | BB41: 58.34 | BC41: 162.99 | BD41: RES | BE41: 98944 | BF41: 276 | BG41: 36002.71 | BH41: 31234.41 | BI41: 67473.05 | BJ41: 134710.17 | BK41: RES | BL41: 98944 | BM41: 274 | BN41: 25706.76 | BO41: 26729.01 | BP41: 74841.8 | BQ41: 127277.57 | BR41: RES | BS41: 98944 | BT41: 258 | BU41: 23064.22 | BV41: 18656.33 | BW41: 72640.25 | BX41: 114360.8 | CH41: =A41 -> RES | CI41: =B41 -> 98603 | CJ41: =D41*1.6%+E41*6.3%+F41*28.9% -> 0 | CK41: =H41 -> RES | CL41: =I41 -> 98603 | CM41: =K41*1.6%+L41*6.3%+M41*28.9% -> 0 | CN41: =O41 -> RES | CO41: =P41 -> 98603 | CP41: =R41*1.6%+S41*6.3%+T41*28.9% -> 1.18224
A42: RES | B42: 98901 | C42: 2561 | D42: 313893.83 | E42: 234976.32 | F42: 812932.59 | G42: 1361802.7 | H42: RES | I42: 98901 | J42: 2435 | K42: 228759.2 | L42: 203756.79 | M42: 892255.5 | N42: 1324771.5 | O42: RES | P42: 98901 | Q42: 2400 | R42: 224746.6 | S42: 152365.47 | T42: 930358.39 | U42: 1307470.5 | V42: RES | W42: 99348 | X42: 8 | Y42: 1267.9 | Z42: 642.25 | AA42: 1277.88 | AB42: 3188.03 | AC42: 8 | AD42: 1107.6 | AE42: 814.58 | AF42: 1538.93 | AG42: 3461.11 | AH42: 7 | AI42: 1023.41 | AJ42: 698.64 | AK42: 1790.37 | AL42: 3512.42 | AM42: RES | AN42: 99347 | AO42: 15 | AP42: 1918.59 | AQ42: 1209.14 | AR42: 7104.72 | AS42: 10232.45 | AT42: 18 | AU42: 1603.1 | AV42: 1396.46 | AW42: 7473.36 | AX42: 10472.92 | AY42: 18 | AZ42: 1322.72 | BA42: 1344.9 | BB42: 8676.97 | BC42: 11344.59 | BD42: RES | BE42: 98947 | BF42: 25 | BG42: 4233.52 | BH42: 4383.85 | BI42: 9003.42 | BJ42: 17620.79 | BK42: RES | BL42: 98947 | BM42: 27 | BN42: 3707.59 | BO42: 3629.83 | BP42: 10590.02 | BQ42: 17927.44 | BR42: RES | BS42: 98947 | BT42: 29 | BU42: 3699.99 | BV42: 3036.29 | BW42: 11893.6 | BX42: 18629.88 | CH42: =A42 -> RES | CI42: =B42 -> 98901 | CJ42: =D42*1.6%+E42*6.3%+F42*28.9% -> 254763.33 | CK42: =H42 -> RES | CL42: =I42 -> 98901 | CM42: =K42*1.6%+L42*6.3%+M42*28.9% -> 274358.66 | CN42: =O42 -> RES | CO42: =P42 -> 98901 | CP42: =R42*1.6%+S42*6.3%+T42*28.9% -> 282068.54
A43: RES | B43: 98902 | C43: 5058 | D43: 575040.72 | E43: 421765.74 | F43: 1162955.7 | G43: 2159762.2 | H43: RES | I43: 98902 | J43: 4651 | K43: 356148.23 | L43: 359777.67 | M43: 1294061.9 | N43: 2009987.8 | O43: RES | P43: 98902 | Q43: 4236 | R43: 280130.84 | S43: 259387.43 | T43: 1357250.8 | U43: 1896769.1 | V43: RES | W43: 99360 | X43: 2 | Y43: 299.18 | Z43: 449.61 | AA43: 143.67 | AB43: 892.46 | AC43: 3 | AD43: 261.91 | AE43: 0 | AF43: 0 | AG43: 261.91 | AH43: 3 | AI43: 635.48 | AJ43: 240.09 | AK43: 0 | AL43: 875.57 | AM43: RES | AN43: 99348 | AO43: 9 | AP43: 1377.72 | AQ43: 275.25 | AR43: 180.67 | AS43: 1833.64 | AT43: 10 | AU43: 1373.55 | AV43: 1269.96 | AW43: 401.67 | AX43: 3045.18 | AY43: 9 | AZ43: 719.06 | BA43: 742.97 | BB43: 868.15 | BC43: 2330.18 | BD43: RES | BE43: 98948 | BF43: 242 | BG43: 40480.8 | BH43: 36222.81 | BI43: 60161.53 | BJ43: 136865.14 | BK43: RES | BL43: 98948 | BM43: 217 | BN43: 15801.74 | BO43: 29553.63 | BP43: 73905.87 | BQ43: 119261.24 | BR43: RES | BS43: 98948 | BT43: 207 | BU43: 16793.81 | BV43: 18981.6 | BW43: 81774.54 | BX43: 117549.95 | CH43: =A43 -> RES | CI43: =B43 -> 98902 | CJ43: =D43*1.6%+E43*6.3%+F43*28.9% -> 371866.1 | CK43: =H43 -> RES | CL43: =I43 -> 98902 | CM43: =K43*1.6%+L43*6.3%+M43*28.9% -> 402348.25 | CN43: =O43 -> RES | CO43: =P43 -> 98902 | CP43: =R43*1.6%+S43*6.3%+T43*28.9% -> 413068.98
A44: RES | B44: 98903 | C44: 1966 | D44: 308601.89 | E44: 188226.01 | F44: 584700.59 | G44: 1081528.5 | H44: RES | I44: 98903 | J44: 1715 | K44: 170364.57 | L44: 187195.59 | M44: 643033.08 | N44: 1000593.2 | O44: RES | P44: 98903 | Q44: 1685 | R44: 171330.6 | S44: 123836.08 | T44: 665032.32 | U44: 960199 | V44: RES | W44: 99361 | X44: 7 | Y44: 1384.55 | Z44: 850.33 | AA44: 4534.6 | AB44: 6769.48 | AC44: 7 | AD44: 1234.47 | AE44: 1254.07 | AF44: 5197.8 | AG44: 7686.34 | AH44: 10 | AI44: 1087.42 | AJ44: 902.63 | AK44: 4391.05 | AL44: 6381.1 | AM44: RES | AN44: 99360 | AO44: 3 | AP44: 532.8 | AQ44: 171.06 | AR44: 0 | AS44: 703.86 | AT44: 4 | AU44: 457.57 | AV44: 423.2 | AW44: 340.78 | AX44: 1221.55 | AY44: 2 | AZ44: 171.57 | BA44: 112.02 | BB44: 36.99 | BC44: 320.58 | BD44: RES | BE44: 98951 | BF44: 254 | BG44: 39510.76 | BH44: 35538.52 | BI44: 85797.23 | BJ44: 160846.51 | BK44: RES | BL44: 98951 | BM44: 246 | BN44: 28800.1 | BO44: 30706.78 | BP44: 104129.6 | BQ44: 163636.48 | BR44: RES | BS44: 98951 | BT44: 253 | BU44: 28387.35 | BV44: 23858.37 | BW44: 123263.95 | BX44: 175509.67 | CH44: =A44 -> RES | CI44: =B44 -> 98903 | CJ44: =D44*1.6%+E44*6.3%+F44*28.9% -> 185774.34 | CK44: =H44 -> RES | CL44: =I44 -> 98903 | CM44: =K44*1.6%+L44*6.3%+M44*28.9% -> 200355.72 | CN44: =O44 -> RES | CO44: =P44 -> 98903 | CP44: =R44*1.6%+S44*6.3%+T44*28.9% -> 202737.3
A45: RES | B45: 98904 | D45: 0 | E45: 0 | F45: 0 | G45: 0 | H45: RES | I45: 98904 | K45: 0 | L45: 0 | M45: 0 | N45: 0 | O45: RES | P45: 98904 | R45: 0 | S45: 0 | T45: 0 | U45: 0 | V45: RES | W45: 99362 | X45: 330 | Y45: 18309.45 | Z45: 18427.64 | AA45: 90896.12 | AB45: 127633.21 | AC45: 352 | AD45: 36498.51 | AE45: 23884.84 | AF45: 82192.82 | AG45: 142576.17 | AH45: 322 | AI45: 29881.93 | AJ45: 25029.86 | AK45: 81492.03 | AL45: 136403.82 | AM45: RES | AN45: 99361 | AO45: 13 | AP45: 1850.91 | AQ45: 948.97 | AR45: 6510.21 | AS45: 9310.09 | AT45: 10 | AU45: 1188.46 | AV45: 1274.58 | AW45: 6963.33 | AX45: 9426.37 | AY45: 9 | AZ45: 716.63 | BA45: 713.28 | BB45: 4440.93 | BC45: 5870.84 | BD45: RES | BE45: 98952 | BF45: 23 | BG45: 4354.87 | BH45: 4334.28 | BI45: 21181.28 | BJ45: 29870.43 | BK45: RES | BL45: 98952 | BM45: 23 | BN45: 2972.2 | BO45: 3787.94 | BP45: 22537.73 | BQ45: 29297.87 | BR45: RES | BS45: 98952 | BT45: 27 | BU45: 3468.89 | BV45: 2686.12 | BW45: 24694.43 | BX45: 30849.44 | CH45: =A45 -> RES | CI45: =B45 -> 98904 | CJ45: =D45*1.6%+E45*6.3%+F45*28.9% -> 0 | CK45: =H45 -> RES | CL45: =I45 -> 98904 | CM45: =K45*1.6%+L45*6.3%+M45*28.9% -> 0 | CN45: =O45 -> RES | CO45: =P45 -> 98904 | CP45: =R45*1.6%+S45*6.3%+T45*28.9% -> 0
A46: RES | B46: 98908 | C46: 3781 | D46: 447775.08 | E46: 320424.38 | F46: 800777.29 | G46: 1568976.8 | H46: RES | I46: 98908 | J46: 3619 | K46: 357691.83 | L46: 255423.91 | M46: 877625.47 | N46: 1490741.2 | O46: RES | P46: 98908 | Q46: 3398 | R46: 287980.73 | S46: 208045.52 | T46: 892020.27 | U46: 1388046.5 | V46: RES | W46: 99363 | X46: 1 | Y46: 0 | Z46: 212.55 | AA46: 501.59 | AB46: 714.14 | AC46: 1 | AD46: 232.62 | AE46: 0 | AF46: 714.14 | AG46: 946.76 | AH46: 2 | AI46: 268.66 | AJ46: 232.62 | AK46: 714.14 | AL46: 1215.42 | AM46: RES | AN46: 99362 | AO46: 221 | AP46: 26398.85 | AQ46: 14125.53 | AR46: 60914.2 | AS46: 101438.58 | AT46: 303 | AU46: 23270.86 | AV46: 16987.06 | AW46: 50785.33 | AX46: 91043.25 | AY46: 286 | AZ46: 16749.61 | BA46: 14667.36 | BB46: 42328.31 | BC46: 73745.28 | BD46: RES | BE46: 98953 | BF46: 48 | BG46: 7437.1 | BH46: 7449.91 | BI46: 18216.33 | BJ46: 33103.34 | BK46: RES | BL46: 98953 | BM46: 52 | BN46: 5999.08 | BO46: 5412.22 | BP46: 16247.06 | BQ46: 27658.36 | BR46: RES | BS46: 98953 | BT46: 55 | BU46: 4846.97 | BV46: 4647.69 | BW46: 17556.55 | BX46: 27051.21 | CH46: =A46 -> RES | CI46: =B46 -> 98908 | CJ46: =D46*1.6%+E46*6.3%+F46*28.9% -> 258775.77 | CK46: =H46 -> RES | CL46: =I46 -> 98908 | CM46: =K46*1.6%+L46*6.3%+M46*28.9% -> 275448.54 | CN46: =O46 -> RES | CO46: =P46 -> 98908 | CP46: =R46*1.6%+S46*6.3%+T46*28.9% -> 275508.42
A47: RES | B47: 98920 | C47: 1 | D47: 178.37 | E47: 208.22 | F47: 597.02 | G47: 983.61 | H47: RES | I47: 98920 | J47: 1 | K47: 133.2 | L47: 178.37 | M47: 805.24 | N47: 1116.81 | O47: RES | P47: 98920 | Q47: 1 | R47: 112.07 | S47: 133.2 | T47: 703.86 | U47: 949.13 | AM47: RES | AN47: 99363 | AT47: 1 | AU47: 126.95 | AV47: 142.22 | AW47: 0 | AX47: 269.17 | AY47: 1 | AZ47: 72.27 | BA47: 126.95 | BB47: 142.22 | BC47: 341.44 | BD47: RES | BE47: 99323 | BF47: 16 | BG47: 1418.15 | BH47: 2018.25 | BI47: 5177.56 | BJ47: 8613.96 | BK47: RES | BL47: 99323 | BM47: 13 | BN47: 1132.52 | BO47: 839.03 | BP47: 3144.86 | BQ47: 5116.41 | BR47: RES | BS47: 99323 | BT47: 10 | BU47: 703.39 | BV47: 468.91 | BW47: 1568.7 | BX47: 2741 | CH47: =A47 -> RES | CI47: =B47 -> 98920 | CJ47: =D47*1.6%+E47*6.3%+F47*28.9% -> 188.51056 | CK47: =H47 -> RES | CL47: =I47 -> 98920 | CM47: =K47*1.6%+L47*6.3%+M47*28.9% -> 246.08287 | CN47: =O47 -> RES | CO47: =P47 -> 98920 | CP47: =R47*1.6%+S47*6.3%+T47*28.9% -> 213.60026
A48: RES | B48: 98921 | C48: 91 | D48: 11784.67 | E48: 9630.39 | F48: 30304.49 | G48: 51719.55 | H48: RES | I48: 98921 | J48: 89 | K48: 9663.76 | L48: 7979.38 | M48: 32661.23 | N48: 50304.37 | O48: RES | P48: 98921 | Q48: 90 | R48: 8254.59 | S48: 6707.19 | T48: 34089.48 | U48: 49051.26 | BD48: RES | BE48: 99324 | BF48: 87 | BG48: 7634.64 | BH48: 6943.7 | BI48: 15850.71 | BJ48: 30429.05 | BK48: RES | BL48: 99324 | BM48: 90 | BN48: 5464.54 | BO48: 5853.62 | BP48: 15510.14 | BQ48: 26828.3 | BR48: RES | BS48: 99324 | BT48: 89 | BU48: 5542.85 | BV48: 4061.66 | BW48: 14869 | BX48: 24473.51 | CH48: =A48 -> RES | CI48: =B48 -> 98921 | CJ48: =D48*1.6%+E48*6.3%+F48*28.9% -> 9553.2669 | CK48: =H48 -> RES | CL48: =I48 -> 98921 | CM48: =K48*1.6%+L48*6.3%+M48*28.9% -> 10096.417 | CN48: =O48 -> RES | CO48: =P48 -> 98921 | CP48: =R48*1.6%+S48*6.3%+T48*28.9% -> 10406.486
A49: RES | B49: 98923 | C49: 145 | D49: 23910.29 | E49: 14996.79 | F49: 34739.59 | G49: 73646.67 | H49: RES | I49: 98923 | J49: 132 | K49: 17787.88 | L49: 12972.32 | M49: 36795.35 | N49: 67555.55 | O49: RES | P49: 98923 | Q49: 124 | R49: 17017.81 | S49: 11590.51 | T49: 40975.1 | U49: 69583.42 | BD49: RES | BE49: 99328 | BF49: 60 | BG49: 8851.77 | BH49: 6887.88 | BI49: 9988.52 | BJ49: 25728.17 | BK49: RES | BL49: 99328 | BM49: 62 | BN49: 7856.42 | BO49: 7310.93 | BP49: 14585.44 | BQ49: 29752.79 | BR49: RES | BS49: 99328 | BT49: 58 | BU49: 5431.92 | BV49: 5914.78 | BW49: 17759.93 | BX49: 29106.63 | CH49: =A49 -> RES | CI49: =B49 -> 98923 | CJ49: =D49*1.6%+E49*6.3%+F49*28.9% -> 11367.104 | CK49: =H49 -> RES | CL49: =I49 -> 98923 | CM49: =K49*1.6%+L49*6.3%+M49*28.9% -> 11735.718 | CN49: =O49 -> RES | CO49: =P49 -> 98923 | CP49: =R49*1.6%+S49*6.3%+T49*28.9% -> 12844.291
A50: RES | B50: 98930 | C50: 1025 | D50: 133767.97 | E50: 82217.29 | F50: 213517.34 | G50: 429502.6 | H50: RES | I50: 98930 | J50: 983 | K50: 86445.73 | L50: 79612.63 | M50: 242226.59 | N50: 408284.95 | O50: RES | P50: 98930 | Q50: 972 | R50: 88318.91 | S50: 53315.44 | T50: 260898.78 | U50: 402533.13 | BD50: RES | BE50: 99329 | BF50: 2 | BG50: 142.04 | BH50: 58.02 | BI50: 690.58 | BJ50: 890.64 | BK50: RES | BL50: 99329 | BM50: 2 | BN50: 286.79 | BO50: 142.04 | BP50: 748.6 | BQ50: 1177.43 | BR50: RES | BS50: 99329 | BT50: 3 | BU50: 451.25 | BV50: 267.8 | BW50: 807.88 | BX50: 1526.93 | CH50: =A50 -> RES | CI50: =B50 -> 98930 | CJ50: =D50*1.6%+E50*6.3%+F50*28.9% -> 69026.488 | CK50: =H50 -> RES | CL50: =I50 -> 98930 | CM50: =K50*1.6%+L50*6.3%+M50*28.9% -> 76402.212 | CN50: =O50 -> RES | CO50: =P50 -> 98930 | CP50: =R50*1.6%+S50*6.3%+T50*28.9% -> 80171.723
A51: RES | B51: 98932 | C51: 551 | D51: 70517 | E51: 56571.41 | F51: 139616.76 | G51: 266705.17 | H51: RES | I51: 98932 | J51: 536 | K51: 55357.66 | L51: 46153.23 | M51: 154057.41 | N51: 255568.3 | O51: RES | P51: 98932 | Q51: 521 | R51: 42750.01 | S51: 34873.24 | T51: 159785.15 | U51: 237408.4 | BD51: RES | BE51: 99347 | BF51: 15 | BG51: 1790.28 | BH51: 1304.39 | BI51: 2901.42 | BJ51: 5996.09 | BK51: RES | BL51: 99347 | BM51: 15 | BN51: 1747.66 | BO51: 1603.95 | BP51: 3829.1 | BQ51: 7180.71 | BR51: RES | BS51: 99347 | BT51: 16 | BU51: 1877.47 | BV51: 1322.91 | BW51: 4555.76 | BX51: 7756.14 | CH51: =A51 -> RES | CI51: =B51 -> 98932 | CJ51: =D51*1.6%+E51*6.3%+F51*28.9% -> 45041.514 | CK51: =H51 -> RES | CL51: =I51 -> 98932 | CM51: =K51*1.6%+L51*6.3%+M51*28.9% -> 48315.968 | CN51: =O51 -> RES | CO51: =P51 -> 98932 | CP51: =R51*1.6%+S51*6.3%+T51*28.9% -> 49058.923
A52: RES | B52: 98933 | C52: 88 | D52: 15454.29 | E52: 11067.64 | F52: 31570.36 | G52: 58092.29 | H52: RES | I52: 98933 | J52: 82 | K52: 9981.06 | L52: 9799.7 | M52: 36169.13 | N52: 55949.89 | O52: RES | P52: 98933 | Q52: 85 | R52: 9992.66 | S52: 6233.26 | T52: 37710.14 | U52: 53936.06 | BD52: RES | BE52: 99348 | BF52: 8 | BG52: 1302.91 | BH52: 1356.28 | BI52: 3571.46 | BJ52: 6230.65 | BK52: RES | BL52: 99348 | BM52: 6 | BN52: 789.59 | BO52: 788.37 | BP52: 3808.68 | BQ52: 5386.64 | BR52: RES | BS52: 99348 | BT52: 6 | BU52: 647.29 | BV52: 502.48 | BW52: 4575.45 | BX52: 5725.22 | CH52: =A52 -> RES | CI52: =B52 -> 98933 | CJ52: =D52*1.6%+E52*6.3%+F52*28.9% -> 10068.364 | CK52: =H52 -> RES | CL52: =I52 -> 98933 | CM52: =K52*1.6%+L52*6.3%+M52*28.9% -> 11229.957 | CN52: =O52 -> RES | CO52: =P52 -> 98933 | CP52: =R52*1.6%+S52*6.3%+T52*28.9% -> 11450.808
A53: RES | B53: 98935 | C53: 245 | D53: 37966.05 | E53: 26030.3 | F53: 81292.86 | G53: 145289.21 | H53: RES | I53: 98935 | J53: 231 | K53: 25439.77 | L53: 24761.67 | M53: 94443.72 | N53: 144645.16 | O53: RES | P53: 98935 | Q53: 245 | R53: 28280.23 | S53: 17123.77 | T53: 103335.72 | U53: 148739.72 | BD53: RES | BE53: 99350 | BF53: 2 | BG53: 499.37 | BH53: 487.42 | BI53: 585.35 | BJ53: 1572.14 | BK53: RES | BL53: 99350 | BM53: 2 | BN53: 229.47 | BO53: 499.37 | BP53: 1072.77 | BQ53: 1801.61 | BR53: RES | BS53: 99350 | BT53: 2 | BU53: 314.22 | BV53: 229.47 | BW53: 1572.14 | BX53: 2115.83 | CH53: =A53 -> RES | CI53: =B53 -> 98935 | CJ53: =D53*1.6%+E53*6.3%+F53*28.9% -> 25741.002 | CK53: =H53 -> RES | CL53: =I53 -> 98935 | CM53: =K53*1.6%+L53*6.3%+M53*28.9% -> 29261.257 | CN53: =O53 -> RES | CO53: =P53 -> 98935 | CP53: =R53*1.6%+S53*6.3%+T53*28.9% -> 31395.304
A54: RES | B54: 98936 | C54: 470 | D54: 65290.3 | E54: 40172.04 | F54: 162308.03 | G54: 267770.37 | H54: RES | I54: 98936 | J54: 452 | K54: 47701.59 | L54: 41815.14 | M54: 171411.91 | N54: 260928.64 | O54: RES | P54: 98936 | Q54: 448 | R54: 48757.82 | S54: 31110.46 | T54: 189978.9 | U54: 269847.18 | BD54: RES | BE54: 99360 | BF54: 2 | BG54: 227.05 | BH54: 676.5 | BI54: 871.5 | BJ54: 1775.05 | BK54: RES | BL54: 99360 | BM54: 2 | BN54: 414.09 | BO54: 146.73 | BP54: 18.22 | BQ54: 579.04 | BR54: RES | BS54: 99360 | BT54: 1 | BU54: 0 | BV54: 280.91 | BW54: 164.95 | BX54: 445.86 | CH54: =A54 -> RES | CI54: =B54 -> 98936 | CJ54: =D54*1.6%+E54*6.3%+F54*28.9% -> 50482.504 | CK54: =H54 -> RES | CL54: =I54 -> 98936 | CM54: =K54*1.6%+L54*6.3%+M54*28.9% -> 52935.621 | CN54: =O54 -> RES | CO54: =P54 -> 98936 | CP54: =R54*1.6%+S54*6.3%+T54*28.9% -> 57643.986
A55: RES | B55: 98937 | C55: 408 | D55: 59156.29 | E55: 41179.22 | F55: 89829.96 | G55: 190165.47 | H55: RES | I55: 98937 | J55: 387 | K55: 43546.82 | L55: 35422.62 | M55: 101272.85 | N55: 180242.29 | O55: RES | P55: 98937 | Q55: 398 | R55: 43878.96 | S55: 27595.92 | T55: 102003.12 | U55: 173478 | BD55: RES | BE55: 99361 | BF55: 10 | BG55: 1496.88 | BH55: 531.14 | BI55: 293.55 | BJ55: 2321.57 | BK55: RES | BL55: 99361 | BM55: 10 | BN55: 970.63 | BO55: 939.32 | BP55: 566.24 | BQ55: 2476.19 | BR55: RES | BS55: 99361 | BT55: 11 | BU55: 1003.35 | BV55: 684.61 | BW55: 1338.04 | BX55: 3026 | CH55: =A55 -> RES | CI55: =B55 -> 98937 | CJ55: =D55*1.6%+E55*6.3%+F55*28.9% -> 29501.65 | CK55: =H55 -> RES | CL55: =I55 -> 98937 | CM55: =K55*1.6%+L55*6.3%+M55*28.9% -> 32196.228 | CN55: =O55 -> RES | CO55: =P55 -> 98937 | CP55: =R55*1.6%+S55*6.3%+T55*28.9% -> 31919.508
A56: RES | B56: 98938 | C56: 193 | D56: 35555.72 | E56: 21377.09 | F56: 75790.6 | G56: 132723.41 | H56: RES | I56: 98938 | J56: 187 | K56: 25450.17 | L56: 20518.41 | M56: 83367.22 | N56: 129335.8 | O56: RES | P56: 98938 | Q56: 174 | R56: 20571.84 | S56: 15381.16 | T56: 87851.82 | U56: 123804.82 | BD56: RES | BE56: 99362 | BF56: 402 | BG56: 39932.05 | BH56: 33193.4 | BI56: 56252.47 | BJ56: 129377.92 | BK56: RES | BL56: 99362 | BM56: 389 | BN56: 27572.31 | BO56: 28579.63 | BP56: 68925.03 | BQ56: 125076.97 | BR56: RES | BS56: 99362 | BT56: 381 | BU56: 28828.16 | BV56: 19745.25 | BW56: 70995.07 | BX56: 119568.48 | CH56: =A56 -> RES | CI56: =B56 -> 98938 | CJ56: =D56*1.6%+E56*6.3%+F56*28.9% -> 23819.132 | CK56: =H56 -> RES | CL56: =I56 -> 98938 | CM56: =K56*1.6%+L56*6.3%+M56*28.9% -> 25792.989 | CN56: =O56 -> RES | CO56: =P56 -> 98938 | CP56: =R56*1.6%+S56*6.3%+T56*28.9% -> 26687.338
A57: RES | B57: 98939 | C57: 26 | D57: 3637.38 | E57: 3826.28 | F57: 14876.06 | G57: 22339.72 | H57: RES | I57: 98939 | J57: 26 | K57: 2900.74 | L57: 2623.5 | M57: 17300.99 | N57: 22825.23 | O57: RES | P57: 98939 | Q57: 24 | R57: 2457.77 | S57: 2024.52 | T57: 18897.29 | U57: 23379.58 | BD57: RES | BE57: 99363 | BF57: 2 | BG57: 318.59 | BH57: 642.9 | BI57: 418.78 | BJ57: 1380.27 | BK57: RES | BL57: 99363 | BM57: 2 | BN57: 316.69 | BO57: 318.59 | BP57: 1061.68 | BQ57: 1696.96 | BR57: RES | BS57: 99363 | BT57: 2 | BU57: 0 | BV57: 316.69 | BW57: 1380.27 | BX57: 1696.96 | CH57: =A57 -> RES | CI57: =B57 -> 98939 | CJ57: =D57*1.6%+E57*6.3%+F57*28.9% -> 4598.4351 | CK57: =H57 -> RES | CL57: =I57 -> 98939 | CM57: =K57*1.6%+L57*6.3%+M57*28.9% -> 5211.6784 | CN57: =O57 -> RES | CO57: =P57 -> 98939 | CP57: =R57*1.6%+S57*6.3%+T57*28.9% -> 5628.1859
A58: RES | B58: 98942 | C58: 1745 | D58: 244738.32 | E58: 159116.05 | F58: 462671.63 | G58: 866526 | H58: RES | I58: 98942 | J58: 1612 | K58: 176159.72 | L58: 142040.22 | M58: 505749.82 | N58: 823949.76 | O58: RES | P58: 98942 | Q58: 1561 | R58: 169566.89 | S58: 105581.33 | T58: 534076.03 | U58: 809224.25 | BF58: =SUM(BF26:BF57) -> 2922 | BG58: =SUM(BG26:BG57) -> 381985.95 | BH58: =SUM(BH26:BH57) -> 323342.08 | BI58: =SUM(BI26:BI57) -> 713813.76 | BJ58: =SUM(BJ26:BJ57) -> 1419141.8 | BM58: =SUM(BM26:BM57) -> 2921 | BN58: =SUM(BN26:BN57) -> 262907.14 | BO58: =SUM(BO26:BO57) -> 285904.53 | BP58: =SUM(BP26:BP57) -> 818258.37 | BQ58: =SUM(BQ26:BQ57) -> 1367070 | BT58: =SUM(BT26:BT57) -> 2927 | BU58: =SUM(BU26:BU57) -> 257404.45 | BV58: =SUM(BV26:BV57) -> 214550.23 | BW58: =SUM(BW26:BW57) -> 857638.71 | BX58: =SUM(BX26:BX57) -> 1329593.4 | CH58: =A58 -> RES | CI58: =B58 -> 98942 | CJ58: =D58*1.6%+E58*6.3%+F58*28.9% -> 147652.23 | CK58: =H58 -> RES | CL58: =I58 -> 98942 | CM58: =K58*1.6%+L58*6.3%+M58*28.9% -> 157928.79 | CN58: =O58 -> RES | CO58: =P58 -> 98942 | CP58: =R58*1.6%+S58*6.3%+T58*28.9% -> 163712.67
A59: RES | B59: 98944 | C59: 1898 | D59: 237331.18 | E59: 167692.19 | F59: 455031.82 | G59: 860055.19 | H59: RES | I59: 98944 | J59: 1805 | K59: 165804.55 | L59: 147856.9 | M59: 503083.77 | N59: 816745.22 | O59: RES | P59: 98944 | Q59: 1778 | R59: 151971.85 | S59: 105706.65 | T59: 526016.02 | U59: 783694.52 | CH59: =A59 -> RES | CI59: =B59 -> 98944 | CJ59: =D59*1.6%+E59*6.3%+F59*28.9% -> 145866.1 | CK59: =H59 -> RES | CL59: =I59 -> 98944 | CM59: =K59*1.6%+L59*6.3%+M59*28.9% -> 157359.07 | CN59: =O59 -> RES | CO59: =P59 -> 98944 | CP59: =R59*1.6%+S59*6.3%+T59*28.9% -> 161109.7
A60: RES | B60: 98947 | C60: 329 | D60: 51202.53 | E60: 36437.52 | F60: 80380.48 | G60: 168020.53 | H60: RES | I60: 98947 | J60: 330 | K60: 39662.95 | L60: 33724.81 | M60: 94594.11 | N60: 167981.87 | O60: RES | P60: 98947 | Q60: 346 | R60: 40763.99 | S60: 26652.92 | T60: 103889.19 | U60: 171306.1 | CH60: =A60 -> RES | CI60: =B60 -> 98947 | CJ60: =D60*1.6%+E60*6.3%+F60*28.9% -> 26344.763 | CK60: =H60 -> RES | CL60: =I60 -> 98947 | CM60: =K60*1.6%+L60*6.3%+M60*28.9% -> 30096.968 | CN60: =O60 -> RES | CO60: =P60 -> 98947 | CP60: =R60*1.6%+S60*6.3%+T60*28.9% -> 32355.334
A61: RES | B61: 98948 | C61: 1146 | D61: 169984.02 | E61: 126316.81 | F61: 300741.33 | G61: 597042.16 | H61: RES | I61: 98948 | J61: 990 | K61: 74919.49 | L61: 104453.36 | M61: 356874.84 | N61: 536247.69 | O61: RES | P61: 98948 | Q61: 869 | R61: 60196.39 | S61: 66135.26 | T61: 370286.34 | U61: 496617.99 | CH61: =A61 -> RES | CI61: =B61 -> 98948 | CJ61: =D61*1.6%+E61*6.3%+F61*28.9% -> 97591.948 | CK61: =H61 -> RES | CL61: =I61 -> 98948 | CM61: =K61*1.6%+L61*6.3%+M61*28.9% -> 110916.1 | CN61: =O61 -> RES | CO61: =P61 -> 98948 | CP61: =R61*1.6%+S61*6.3%+T61*28.9% -> 112142.42
A62: RES | B62: 98951 | C62: 1104 | D62: 170058.6 | E62: 134725.81 | F62: 424585.03 | G62: 729369.44 | H62: RES | I62: 98951 | J62: 1061 | K62: 122867.54 | L62: 109647.85 | M62: 480572.06 | N62: 713087.45 | O62: RES | P62: 98951 | Q62: 1051 | R62: 106291.51 | S62: 80894.32 | T62: 523935.94 | U62: 711121.77 | CH62: =A62 -> RES | CI62: =B62 -> 98951 | CJ62: =D62*1.6%+E62*6.3%+F62*28.9% -> 133913.74 | CK62: =H62 -> RES | CL62: =I62 -> 98951 | CM62: =K62*1.6%+L62*6.3%+M62*28.9% -> 147759.02 | CN62: =O62 -> RES | CO62: =P62 -> 98951 | CP62: =R62*1.6%+S62*6.3%+T62*28.9% -> 158214.49
A63: RES | B63: 98952 | C63: 80 | D63: 14425.53 | E63: 12999.88 | F63: 59216.42 | G63: 86641.83 | H63: RES | I63: 98952 | J63: 81 | K63: 9677.08 | L63: 10901.43 | M63: 65114.21 | N63: 85692.72 | O63: RES | P63: 98952 | Q63: 86 | R63: 10513.36 | S63: 7446.92 | T63: 64065.48 | U63: 82025.76 | CH63: =A63 -> RES | CI63: =B63 -> 98952 | CJ63: =D63*1.6%+E63*6.3%+F63*28.9% -> 18163.346 | CK63: =H63 -> RES | CL63: =I63 -> 98952 | CM63: =K63*1.6%+L63*6.3%+M63*28.9% -> 19659.63 | CN63: =O63 -> RES | CO63: =P63 -> 98952 | CP63: =R63*1.6%+S63*6.3%+T63*28.9% -> 19152.293
A64: RES | B64: 98953 | C64: 687 | D64: 86933.78 | E64: 65946.4 | F64: 160782.99 | G64: 313663.17 | H64: RES | I64: 98953 | J64: 657 | K64: 70620.74 | L64: 51016.86 | M64: 169693.61 | N64: 291331.21 | O64: RES | P64: 98953 | Q64: 641 | R64: 56699.11 | S64: 41378.69 | T64: 172821.17 | U64: 270898.97 | CH64: =A64 -> RES | CI64: =B64 -> 98953 | CJ64: =D64*1.6%+E64*6.3%+F64*28.9% -> 52011.848 | CK64: =H64 -> RES | CL64: =I64 -> 98953 | CM64: =K64*1.6%+L64*6.3%+M64*28.9% -> 53385.447 | CN64: =O64 -> RES | CO64: =P64 -> 98953 | CP64: =R64*1.6%+S64*6.3%+T64*28.9% -> 53459.361
A65: RES | B65: 99301 | C65: 1 | D65: 89.64 | E65: 0 | F65: 0 | G65: 89.64 | H65: RES | I65: 99301 | J65: 1 | K65: 123.13 | L65: 89.64 | M65: 0 | N65: 212.77 | O65: RES | P65: 99301 | R65: 0 | S65: 0 | T65: 0 | U65: 0 | CH65: =A65 -> RES | CI65: =B65 -> 99301 | CJ65: =D65*1.6%+E65*6.3%+F65*28.9% -> 1.43424 | CK65: =H65 -> RES | CL65: =I65 -> 99301 | CM65: =K65*1.6%+L65*6.3%+M65*28.9% -> 7.6174 | CN65: =O65 -> RES | CO65: =P65 -> 99301 | CP65: =R65*1.6%+S65*6.3%+T65*28.9% -> 0
A66: RES | B66: 99323 | C66: 252 | D66: 29038.44 | E66: 25447.78 | F66: 48224.94 | G66: 102711.16 | H66: RES | I66: 99323 | J66: 236 | K66: 24337.84 | L66: 14785.93 | M66: 52316.03 | N66: 91439.8 | O66: RES | P66: 99323 | Q66: 206 | R66: 18508.34 | S66: 12506.67 | T66: 49098.15 | U66: 80113.16 | CH66: =A66 -> RES | CI66: =B66 -> 99323 | CJ66: =D66*1.6%+E66*6.3%+F66*28.9% -> 16004.833 | CK66: =H66 -> RES | CL66: =I66 -> 99323 | CM66: =K66*1.6%+L66*6.3%+M66*28.9% -> 16440.252 | CN66: =O66 -> RES | CO66: =P66 -> 99323 | CP66: =R66*1.6%+S66*6.3%+T66*28.9% -> 15273.419
A67: RES | B67: 99324 | C67: 604 | D67: 58171.13 | E67: 33236.98 | F67: 76778.1 | G67: 168186.21 | H67: RES | I67: 99324 | J67: 568 | K67: 39909.66 | L67: 31537.62 | M67: 82851.35 | N67: 154298.63 | O67: RES | P67: 99324 | Q67: 549 | R67: 36959.37 | S67: 22390.44 | T67: 83878.5 | U67: 143228.31 | CH67: =A67 -> RES | CI67: =B67 -> 99324 | CJ67: =D67*1.6%+E67*6.3%+F67*28.9% -> 25213.539 | CK67: =H67 -> RES | CL67: =I67 -> 99324 | CM67: =K67*1.6%+L67*6.3%+M67*28.9% -> 26569.465 | CN67: =O67 -> RES | CO67: =P67 -> 99324 | CP67: =R67*1.6%+S67*6.3%+T67*28.9% -> 26242.834
A68: RES | B68: 99328 | C68: 431 | D68: 59679.78 | E68: 38081.78 | F68: 92246.45 | G68: 190008.01 | H68: RES | I68: 99328 | J68: 425 | K68: 54392.92 | L68: 34960.34 | M68: 102265.22 | N68: 191618.48 | O68: RES | P68: 99328 | Q68: 402 | R68: 41257.99 | S68: 32161.92 | T68: 106947.96 | U68: 180367.87 | CH68: =A68 -> RES | CI68: =B68 -> 99328 | CJ68: =D68*1.6%+E68*6.3%+F68*28.9% -> 30013.253 | CK68: =H68 -> RES | CL68: =I68 -> 99328 | CM68: =K68*1.6%+L68*6.3%+M68*28.9% -> 32627.437 | CN68: =O68 -> RES | CO68: =P68 -> 99328 | CP68: =R68*1.6%+S68*6.3%+T68*28.9% -> 33594.289
A69: RES | B69: 99329 | C69: 28 | D69: 3632.88 | E69: 838.05 | F69: 1097.4 | G69: 5568.33 | H69: RES | I69: 99329 | J69: 25 | K69: 2879.52 | L69: 1534.3 | M69: 1527.82 | N69: 5941.64 | O69: RES | P69: 99329 | Q69: 25 | R69: 2976.32 | S69: 1135.07 | T69: 1944.51 | U69: 6055.9 | CH69: =A69 -> RES | CI69: =B69 -> 99329 | CJ69: =D69*1.6%+E69*6.3%+F69*28.9% -> 428.07183 | CK69: =H69 -> RES | CL69: =I69 -> 99329 | CM69: =K69*1.6%+L69*6.3%+M69*28.9% -> 584.2732 | CN69: =O69 -> RES | CO69: =P69 -> 99329 | CP69: =R69*1.6%+S69*6.3%+T69*28.9% -> 681.09392
A70: RES | B70: 99347 | C70: 208 | D70: 35942.28 | E70: 23330.41 | F70: 68928.26 | G70: 128200.95 | H70: RES | I70: 99347 | J70: 199 | K70: 24417.58 | L70: 23981.6 | M70: 76111.88 | N70: 124511.06 | O70: RES | P70: 99347 | Q70: 199 | R70: 28203.07 | S70: 16688.54 | T70: 85054.57 | U70: 129946.18 | CH70: =A70 -> RES | CI70: =B70 -> 99347 | CJ70: =D70*1.6%+E70*6.3%+F70*28.9% -> 21965.159 | CK70: =H70 -> RES | CL70: =I70 -> 99347 | CM70: =K70*1.6%+L70*6.3%+M70*28.9% -> 23897.855 | CN70: =O70 -> RES | CO70: =P70 -> 99347 | CP70: =R70*1.6%+S70*6.3%+T70*28.9% -> 26083.398
A71: RES | B71: 99348 | C71: 50 | D71: 7510.53 | E71: 4719.81 | F71: 13212.3 | G71: 25442.64 | H71: RES | I71: 99348 | J71: 54 | K71: 5598.4 | L71: 4409 | M71: 14648.07 | N71: 24655.47 | O71: RES | P71: 99348 | Q71: 53 | R71: 5212.53 | S71: 3123.2 | T71: 16878.38 | U71: 25214.11 | CH71: =A71 -> RES | CI71: =B71 -> 99348 | CJ71: =D71*1.6%+E71*6.3%+F71*28.9% -> 4235.8712 | CK71: =H71 -> RES | CL71: =I71 -> 99348 | CM71: =K71*1.6%+L71*6.3%+M71*28.9% -> 4600.6336 | CN71: =O71 -> RES | CO71: =P71 -> 99348 | CP71: =R71*1.6%+S71*6.3%+T71*28.9% -> 5158.0139
A72: RES | B72: 99350 | C72: 7 | D72: 1353.4 | E72: 773.44 | F72: 585.35 | G72: 2712.19 | H72: RES | I72: 99350 | J72: 6 | K72: 733.69 | L72: 901.35 | M72: 1072.77 | N72: 2707.81 | O72: RES | P72: 99350 | Q72: 6 | R72: 894.5 | S72: 409.63 | T72: 1725.59 | U72: 3029.72 | CH72: =A72 -> RES | CI72: =B72 -> 99350 | CJ72: =D72*1.6%+E72*6.3%+F72*28.9% -> 239.54727 | CK72: =H72 -> RES | CL72: =I72 -> 99350 | CM72: =K72*1.6%+L72*6.3%+M72*28.9% -> 378.55462 | CN72: =O72 -> RES | CO72: =P72 -> 99350 | CP72: =R72*1.6%+S72*6.3%+T72*28.9% -> 538.8142
A73: RES | B73: 99360 | C73: 106 | D73: 14429.52 | E73: 11505.32 | F73: 12383.46 | G73: 38318.3 | H73: RES | I73: 99360 | J73: 85 | K73: 9747.26 | L73: 7063.68 | M73: 14804.03 | N73: 31614.97 | O73: RES | P73: 99360 | Q73: 55 | R73: 941.86 | S73: 5610.7 | T73: 15473.3 | U73: 22025.86 | CH73: =A73 -> RES | CI73: =B73 -> 99360 | CJ73: =D73*1.6%+E73*6.3%+F73*28.9% -> 4534.5274 | CK73: =H73 -> RES | CL73: =I73 -> 99360 | CM73: =K73*1.6%+L73*6.3%+M73*28.9% -> 4879.3327 | CN73: =O73 -> RES | CO73: =P73 -> 99360 | CP73: =R73*1.6%+S73*6.3%+T73*28.9% -> 4840.3276
A74: RES | B74: 99361 | C74: 148 | D74: 25985.45 | E74: 13422.56 | F74: 37853.02 | G74: 77261.03 | H74: RES | I74: 99361 | J74: 138 | K74: 16158.75 | L74: 15020.35 | M74: 43397.74 | N74: 74576.84 | O74: RES | P74: 99361 | Q74: 137 | R74: 15760.73 | S74: 8880.78 | T74: 40638.59 | U74: 65280.1 | CH74: =A74 -> RES | CI74: =B74 -> 99361 | CJ74: =D74*1.6%+E74*6.3%+F74*28.9% -> 12200.911 | CK74: =H74 -> RES | CL74: =I74 -> 99361 | CM74: =K74*1.6%+L74*6.3%+M74*28.9% -> 13746.769 | CN74: =O74 -> RES | CO74: =P74 -> 99361 | CP74: =R74*1.6%+S74*6.3%+T74*28.9% -> 12556.213
A75: RES | B75: 99362 | C75: 2463 | D75: 249266.6 | E75: 147925.55 | F75: 411693.32 | G75: 808885.47 | H75: RES | I75: 99362 | J75: 2283 | K75: 173970.58 | L75: 142923.36 | M75: 441714.91 | N75: 758608.85 | O75: RES | P75: 99362 | Q75: 2203 | R75: 170927.14 | S75: 101565.66 | T75: 463900.44 | U75: 736393.24 | CH75: =A75 -> RES | CI75: =B75 -> 99362 | CJ75: =D75*1.6%+E75*6.3%+F75*28.9% -> 132286.94 | CK75: =H75 -> RES | CL75: =I75 -> 99362 | CM75: =K75*1.6%+L75*6.3%+M75*28.9% -> 139443.31 | CN75: =O75 -> RES | CO75: =P75 -> 99362 | CP75: =R75*1.6%+S75*6.3%+T75*28.9% -> 143200.7
A76: RES | B76: 99363 | C76: 20 | D76: 3275.11 | E76: 3925.98 | F76: 3322.03 | G76: 10523.12 | H76: RES | I76: 99363 | J76: 26 | K76: 3099.87 | L76: 2482.47 | M76: 3246.58 | N76: 8828.92 | O76: RES | P76: 99363 | Q76: 16 | R76: 0 | S76: 2526.06 | T76: 4113.46 | U76: 6639.52 | CH76: =A76 -> RES | CI76: =B76 -> 99363 | CJ76: =D76*1.6%+E76*6.3%+F76*28.9% -> 1259.8052 | CK76: =H76 -> RES | CL76: =I76 -> 99363 | CM76: =K76*1.6%+L76*6.3%+M76*28.9% -> 1144.2551 | CN76: =O76 -> RES | CO76: =P76 -> 99363 | CP76: =R76*1.6%+S76*6.3%+T76*28.9% -> 1347.9317
A77: TOTAL | C77: =SUM(C41:C76) -> 27916 | D77: =SUM(D41:D76) -> 3565578.6 | E77: =SUM(E41:E76) -> 2479111.4 | F77: =SUM(F41:F76) -> 6945543.6 | G77: =SUM(G41:G76) -> 12990234 | J77: =SUM(J41:J76) -> 26108 | K77: =SUM(K41:K76) -> 2452453.5 | L77: =SUM(L41:L76) -> 2167322 | M77: =SUM(M41:M76) -> 7687126.4 | N77: =SUM(N41:N76) -> 12306902 | Q77: =SUM(Q41:Q76) -> 24985 | R77: =SUM(R41:R76) -> 2192300.3 | S77: =SUM(S41:S76) -> 1590517.9 | T77: =SUM(T41:T76) -> 8045634.7 | U77: =SUM(U41:U76) -> 11828453 | CH77: =A77 -> TOTAL | CJ77: =SUM(CJ41:CJ76) -> 2220495.4 | CM77: =SUM(CM41:CM76) -> 2397360.1 | CP77: =SUM(CP41:CP76) -> 2460467.9

Sheet 8. Past Due Balances 2020 OLD
A1: General 2020 | E1: Item a) Number of Customers by Customer Class With Past-due balances (arrearages) | O1: Item b) Past-due Balances by Customer Class and Number of Days Past-due | AZ1: Item c) Amount of Past-due Balances for Known Low-income Households and Number of Days Past-due | CL1: Item d) Amount of Past Due Balances Classified as Uncollectible | CV1: Item e) The Amount of Past-due Balances Written-off and Classified as Bad Debt, if different than item d | DG1: Item f) Number of Customer Accounts Referred to Collection Agencies | DQ1: Item f) Total Amount of Bad Debt Referred for Collection | EA1: Item f) Total Revenue to the Company from the Collection Process
O2: 43831 | S2: 43862 | W2: 43891 | AA2: 43922 | AE2: 43952 | AI2: 43983 | AM2: 44013 | AQ2: 44044 | AU2: 44075 | AZ2: 43831 | BD2: 43862 | BH2: 43891 | BL2: 43922 | BP2: 43952 | BT2: 43983 | BX2: 44013 | CB2: 44044 | CF2: 44075
A3: Zip Code | B3: Customer Class | C3: x | D3: x | E3: 43831 | F3: 43862 | G3: 43891 | H3: 43922 | I3: 43952 | J3: 43983 | K3: 44013 | L3: 44044 | M3: 44075 | N3: x | O3: 30 Days | P3: 60 Days | Q3: 90 Days + | R3: Total Arrearages | S3: 30 Days | T3: 60 Days | U3: 90 Days + | V3: Total Arrearages | W3: 30 Days | X3: 60 Days | Y3: 90 Days + | Z3: Total Arrearages | AA3: 30 Days | AB3: 60 Days | AC3: 90 Days + | AD3: Total Arrearages | AE3: 30 Days | AF3: 60 Days | AG3: 90 Days + | AH3: Total Arrearages | AI3: 30 Days | AJ3: 60 Days | AK3: 90 Days + | AL3: Total Arrearages | AM3: 30 Days | AN3: 60 Days | AO3: 90 Days + | AP3: Total Arrearages | AQ3: 30 Days | AR3: 60 Days | AS3: 90 Days + | AT3: Total Arrearages | AU3: 30 Days | AV3: 60 Days | AW3: 90 Days + | AX3: Total Arrearages | AZ3: 30 Days | BA3: 60 Days | BB3: 90 Days + | BC3: Total Arrearages | BD3: 30 Days | BE3: 60 Days | BF3: 90 Days + | BG3: Total Arrearages | BH3: 30 Days | BI3: 60 Days | BJ3: 90 Days + | BK3: Total Arrearages | BL3: 30 Days | BM3: 60 Days | BN3: 90 Days + | BO3: Total Arrearages | BP3: 30 Days | BQ3: 60 Days | BR3: 90 Days + | BS3: Total Arrearages | BT3: 30 Days | BU3: 60 Days | BV3: 90 Days + | BW3: Total Arrearages | BX3: 30 Days | BY3: 60 Days | BZ3: 90 Days + | CA3: Total Arrearages | CB3: 30 Days | CC3: 60 Days | CD3: 90 Days + | CE3: Total Arrearages | CF3: 30 Days | CG3: 60 Days | CH3: 90 Days + | CI3: Total Arrearages | CL3: 43831 | CM3: 43862 | CN3: 43891 | CO3: 43922 | CP3: 43952 | CQ3: 43983 | CR3: 44013 | CS3: 44044 | CT3: 44075 | CV3: CLASS | CW3: 43831 | CX3: 43862 | CY3: 43891 | CZ3: 43922 | DA3: 43952 | DB3: 43983 | DC3: 44013 | DD3: 44044 | DE3: 44075 | DG3: 43831 | DH3: 43862 | DI3: 43891 | DJ3: 43922 | DK3: 43952 | DL3: 43983 | DM3: 44013 | DN3: 44044 | DO3: 44075 | DQ3: 43831 | DR3: 43862 | DS3: 43891 | DT3: 43922 | DU3: 43952 | DV3: 43983 | DW3: 44013 | DX3: 44044 | DY3: 44075 | EA3: 43831 | EB3: 43862 | EC3: 43891 | ED3: 43922 | EE3: 43952 | EF3: 43983 | EG3: 44013 | EH3: 44044 | EI3: 44075
A4: 98901 | B4: COM | C4: =A4&B4 -> 98901COM | E4: 131 | F4: 132 | G4: 145 | H4: 173 | I4: 221 | J4: 160 | K4: 137 | L4: 152 | M4: 156 | O4: 19871.38 | P4: 7897.63 | Q4: 24242.65 | R4: 52011.66 | S4: 53580.83 | T4: 9976.46 | U4: 27438.96 | V4: 90996.25 | W4: 48277.95 | X4: 17941.85 | Y4: 22854.02 | Z4: 89073.82 | AA4: 71009.6 | AB4: 29051.57 | AC4: 36760.09 | AD4: 136821.26 | AE4: 86883.42 | AF4: 34985.09 | AG4: 49645.24 | AH4: 171513.75 | AI4: 39740.66 | AJ4: 29311.53 | AK4: 66630.47 | AL4: 135682.66 | AM4: 38006.67 | AN4: 14078.08 | AO4: 65366.26 | AP4: 117451.01 | AQ4: 29853.1 | AR4: 15834.18 | AS4: 62985.51 | AT4: 108672.79 | AU4: 41939.18 | AV4: 15055.03 | AW4: 60553.4 | AX4: 117547.61 | AZ4: 42.71 | BA4: 41.08 | BC4: 83.79 | BD4: 48.96 | BE4: 42.71 | BF4: 41.08 | BG4: 132.75 | BH4: 56.74 | BI4: 48.96 | BJ4: 83.79 | BK4: 189.49 | BL4: 50.42 | BM4: 56.74 | BN4: 132.75 | BO4: 239.91 | BP4: 44.7 | BQ4: 50.42 | BR4: 189.49 | BS4: 284.61 | BT4: 24.09 | BU4: 44.7 | BV4: 189.91 | BW4: 258.7 | BX4: 23.42 | BY4: 24.09 | BZ4: 234.61 | CA4: 282.12 | CB4: 29.16 | CC4: 23.42 | CD4: 184.25 | CE4: 236.83 | CF4: 33.34 | CG4: 29.16 | CH4: 207.67 | CI4: 270.17 | CJ4: =VLOOKUP($C4,#REF!,#REF!,FALSE) -> #REF! | CL4: 6680.653 | CM4: 9123.4953 | CN4: 9211.7238 | CO4: 15409.934 | CP4: 18878.318 | CQ4: 22984.908 | CR4: 21490.276 | CS4: 22157.377 | CT4: 21296.568 | CV4: RES | CW4: 155378.03 | CX4: 91404.44 | CY4: 77084.33 | CZ4: 161847.29 | DA4: 69802.26 | DB4: 66491.04 | DC4: 72376.07 | DD4: 109624.03 | DE4: 76241.97 | DG4: 2 | DH4: 2 | DI4: 3 | DJ4: 3 | DK4: 1 | DQ4: 3400.92 | DR4: 1528.25 | DS4: 1009.25 | DT4: 25469.44 | DU4: 361.46 | EC4: 215.93 | EE4: 361.46
A5: 98902 | B5: COM | C5: =A5&B5 -> 98902COM | E5: 197 | F5: 198 | G5: 189 | H5: 218 | I5: 275 | J5: 206 | K5: 187 | L5: 219 | M5: 208 | O5: 56081.52 | P5: 11010.14 | Q5: 15451.95 | R5: 82543.61 | S5: 126371.49 | T5: 13179.05 | U5: 17580.15 | V5: 157130.69 | W5: 34416.43 | X5: 16097.77 | Y5: 20292.23 | Z5: 70806.43 | AA5: 67882.3 | AB5: 22425.07 | AC5: 28833.05 | AD5: 119140.42 | AE5: 82008.83 | AF5: 27881.35 | AG5: 44079.42 | AH5: 153969.6 | AI5: 39115.86 | AJ5: 22652.96 | AK5: 55917.07 | AL5: 117685.89 | AM5: 37473.1 | AN5: 19881.82 | AO5: 51286.11 | AP5: 108641.03 | AQ5: 60464.87 | AR5: 21310.31 | AS5: 56987.72 | AT5: 138762.9 | AU5: 44660.96 | AV5: 22729.12 | AW5: 61819.4 | AX5: 129209.48 | AZ5: 40.74 | BC5: 40.74 | BD5: 29.81 | BE5: 40.74 | BG5: 70.55 | BH5: 33.2 | BI5: 29.81 | BJ5: 40.74 | BK5: 103.75 | BL5: 122.34 | BM5: 33.2 | BN5: 70.55 | BO5: 226.09 | BP5: 110.62 | BQ5: 122.34 | BR5: 103.75 | BS5: 336.71 | BT5: 55.19 | BU5: 110.62 | BV5: 226.09 | BW5: 391.9 | BX5: 69.27 | BY5: 55.19 | BZ5: 336.71 | CA5: 461.17 | CB5: 87.53 | CC5: 69.27 | CD5: 391.9 | CE5: 548.7 | CF5: 80.19 | CG5: 87.53 | CH5: 461.17 | CI5: 628.89 | CJ5: 0.24399667 | CL5: 5618.0792 | CM5: 9221.8192 | CN5: 7917.4582 | CO5: 12496.834 | CP5: 16704.887 | CQ5: 19304.53 | CR5: 17758.213 | CS5: 21520.255 | CT5: 22300.768 | CV5: COM | CW5: 2753.02 | CX5: 9149.27 | CY5: 12487.38 | CZ5: 14610.42 | DA5: 12690.61 | DB5: 6158.09 | DC5: 7360.64 | DD5: 6977.57 | DE5: 14974.03 | DG5: 4 | DH5: 4 | DI5: 17 | DJ5: 5 | DK5: 1 | DL5: 4 | DQ5: 227.95 | DR5: 12847.79 | DS5: 12855.73 | DT5: 693.93 | DU5: 260.59 | DV5: 210.46 | EA5: 204.97 | EC5: 366.14 | ED5: 262.16 | EF5: 155.42 | EG5: 83.93
A6: 98903 | B6: COM | C6: =A6&B6 -> 98903COM | E6: 123 | F6: 109 | G6: 105 | H6: 119 | I6: 188 | J6: 112 | K6: 117 | L6: 134 | M6: 124 | O6: 22768.85 | P6: 7604.5 | Q6: 7617.7 | R6: 37991.05 | S6: 62967.03 | T6: 4976.34 | U6: 6658.94 | V6: 74602.31 | W6: 14427.86 | X6: 9455.36 | Y6: 6303.98 | Z6: 30187.2 | AA6: 34080.48 | AB6: 10589.12 | AC6: 11180.85 | AD6: 55850.45 | AE6: 57986.56 | AF6: 15693.43 | AG6: 19537.11 | AH6: 93217.1 | AI6: 18745.46 | AJ6: 12483.44 | AK6: 22869.82 | AL6: 54098.72 | AM6: 17601.8 | AN6: 3910.46 | AO6: 33199.92 | AP6: 54712.18 | AQ6: 19669.93 | AR6: 18272.7 | AS6: 34813.48 | AT6: 72756.11 | AU6: 23168.57 | AV6: 4663.56 | AW6: 42563.61 | AX6: 70395.74 | CJ6: 0.26286604 | CL6: 2767.5383 | CM6: 3960.1853 | CN6: 2984.8866 | CO6: 5282.1529 | CP6: 8223.6545 | CQ6: 8225.4179 | CR6: 10619.978 | CS6: 13059.721 | CT6: 14404.337 | DG6: 5 | DH6: 1 | DI6: 1 | DJ6: 4 | DK6: 1 | DL6: 2 | DQ6: 817.64 | DR6: 142.22 | DS6: 154.34 | DT6: 976.96 | DU6: 385.63 | DV6: 533.4 | EA6: 746.69 | EC6: 154.34 | ED6: 478.24 | EE6: 385.63 | EF6: 101.99
A7: 98908 | B7: COM | C7: =A7&B7 -> 98908COM | E7: 100 | F7: 117 | G7: 126 | H7: 144 | I7: 142 | J7: 104 | K7: 89 | L7: 123 | M7: 117 | O7: 24914.74 | P7: 1417.66 | Q7: 1482.68 | R7: 27815.08 | S7: 13416.06 | T7: 2358.05 | U7: 2511.35 | V7: 18285.46 | W7: 19122.52 | X7: 5305.24 | Y7: 2841.91 | Z7: 27269.67 | AA7: 21192.33 | AB7: 7382.52 | AC7: 5830.49 | AD7: 34405.34 | AE7: 42531.53 | AF7: 11285.05 | AG7: 9525.78 | AH7: 63342.36 | AI7: 16892.88 | AJ7: 5857.23 | AK7: 13310.88 | AL7: 36060.99 | AM7: 9242.42 | AN7: 4737.16 | AO7: 13686.29 | AP7: 27665.87 | AQ7: 22069.54 | AR7: 6286.33 | AS7: 16209.75 | AT7: 44565.62 | AU7: 17866.4 | AV7: 6732.99 | AW7: 15270.36 | AX7: 39869.75 | AZ7: 82.16 | BA7: 29.84 | BC7: 112 | BD7: 74.84 | BE7: 82.16 | BF7: 29.84 | BG7: 186.84 | BH7: 73.81 | BK7: 73.81 | BL7: 67.88 | BM7: 73.81 | BO7: 141.69 | BP7: 42.04 | BQ7: 67.88 | BR7: 73.81 | BS7: 183.73 | BT7: 24.13 | BU7: 42.04 | BV7: 141.69 | BW7: 207.86 | BX7: 45.72 | BY7: 24.13 | BZ7: 183.73 | CA7: 253.58 | CB7: 50.87 | CC7: 45.72 | CD7: 207.86 | CE7: 304.45 | CF7: 50.18 | CG7: 50.87 | CH7: 253.58 | CI7: 354.63 | CJ7: 0.2842874 | CL7: 1027.7791 | CM7: 1210.0733 | CN7: 1853.2718 | CO7: 3031.4297 | CP7: 4637.8175 | CQ7: 4850.8456 | CR7: 4673.1373 | CS7: 6275.5162 | CT7: 5750.6895 | DH7: 1 | DI7: 2 | DJ7: 3 | DL7: 2 | DR7: 258.25 | DS7: 584.7 | DT7: 866.82 | DV7: 740.9 | EB7: 258.25 | EC7: 209.33 | ED7: 240.28 | EF7: 740.9
A8: 98920 | B8: COM | C8: =A8&B8 -> 98920COM | E8: 1 | J8: 2 | O8: 35.7 | P8: 0 | Q8: 0 | R8: 35.7 | AI8: 53.06 | AJ8: 0 | AK8: 0 | AL8: 53.06 | CJ8: 0.28728463 | CL8: 0.85823928 | CQ8: 1.534743
A9: 98921 | B9: COM | C9: =A9&B9 -> 98921COM | E9: 1 | F9: 2 | G9: 2 | H9: 5 | I9: 4 | J9: 2 | K9: 4 | L9: 3 | M9: 3 | O9: 11.8 | P9: 11.68 | Q9: 13.15 | R9: 36.63 | S9: 161.8 | T9: 11.8 | U9: 24.83 | V9: 198.43 | W9: 146.79 | X9: 161.8 | Y9: 36.63 | Z9: 345.22 | AA9: 918.22 | AB9: 12.04 | AC9: 48.55 | AD9: 978.81 | AE9: 519.37 | AF9: 136.16 | AG9: 60.59 | AH9: 716.12 | AI9: 73.2 | AJ9: 113.5 | AK9: 196.75 | AL9: 383.45 | AM9: 292.13 | AN9: 29.87 | AO9: 83.69 | AP9: 405.69 | AQ9: 217.55 | AR9: 186.1 | AS9: 95.24 | AT9: 498.89 | AU9: 216.72 | AV9: 104.19 | AW9: 124.89 | AX9: 445.8 | CJ9: 0.29347129 | CL9: 4.0396567 | CM9: 11.983693 | CN9: 29.070748 | CO9: 47.934722 | CP9: 40.521968 | CQ9: 68.691376 | CR9: 35.864705 | CS9: 50.683103 | CT9: 52.160528 | DL9: 2 | DV9: 323.73 | EF9: 323.73
A10: 98923 | B10: COM | C10: =A10&B10 -> 98923COM | E10: 16 | F10: 9 | G10: 18 | H10: 6 | I10: 5 | J10: 18 | K10: 15 | L10: 16 | M10: 16 | O10: 17959.08 | P10: 31.33 | Q10: 255.2 | R10: 18245.61 | S10: 537.76 | T10: 47.2 | U10: 286.53 | V10: 871.49 | W10: 16599.05 | X10: 66.75 | Y10: 183.73 | Z10: 16849.53 | AA10: 91.78 | AB10: 110.2 | AC10: 250.48 | AD10: 452.46 | AE10: 70.62 | AF10: 77.75 | AG10: 318.49 | AH10: 466.86 | AI10: 7533.87 | AJ10: 70.62 | AK10: 396.24 | AL10: 8000.73 | AM10: 6002.33 | AN10: 42.71 | AO10: 377.8 | AP10: 6422.84 | AQ10: 7712.15 | AR10: 45.18 | AS10: 319.02 | AT10: 8076.35 | AU10: 8746.24 | AV10: 71.71 | AW10: 364.2 | AX10: 9182.15 | CJ10: 0.29479967 | CL10: 494.29869 | CM10: 90.21886 | CN10: 598.08661 | CO10: 83.612057 | CP10: 98.275407 | CQ10: 339.69606 | CR10: 298.54343 | CS10: 322.46673 | CT10: 330.36683 | DG10: 1 | DQ10: 106.87
A11: 98930 | B11: COM | C11: =A11&B11 -> 98930COM | E11: 27 | F11: 27 | G11: 37 | H11: 47 | I11: 41 | J11: 35 | K11: 40 | L11: 30 | M11: 44 | O11: 3937.2 | P11: 207.64 | Q11: 1005.96 | R11: 5150.8 | S11: 3368.57 | T11: 872.13 | U11: 845.24 | V11: 5085.94 | W11: 6174.01 | X11: 634.42 | Y11: 718.11 | Z11: 7526.54 | AA11: 10506.12 | AB11: 5266.98 | AC11: 1232.67 | AD11: 17005.77 | AE11: 18016.66 | AF11: 5883.63 | AG11: 5651.82 | AH11: 29552.11 | AI11: 6772.97 | AJ11: 4121.62 | AK11: 8529.95 | AL11: 19424.54 | AM11: 3828.79 | AN11: 3397.63 | AO11: 10724.7 | AP11: 17951.12 | AQ11: 4004.54 | AR11: 2298.98 | AS11: 11177.95 | AT11: 17481.47 | AU11: 7780.57 | AV11: 3529.16 | AW11: 13198.62 | AX11: 24508.35 | CJ11: 0.31933271 | CL11: 345.69247 | CM11: 377.73042 | CN11: 448.39332 | CO11: 1164.1248 | CP11: 2496.745 | CQ11: 3019.9837 | CR11: 3533.7121 | CS11: 3856.9734 | CT11: 4626.6464 | DI11: 1 | DK11: 1 | DL11: 1 | DS11: 128.23 | DU11: 116.78 | DV11: 87.06 | EC11: 128.23 | EE11: 116.78 | EF11: 87.06
A12: 98932 | B12: COM | C12: =A12&B12 -> 98932COM | E12: 29 | F12: 21 | G12: 22 | H12: 27 | I12: 20 | J12: 39 | K12: 19 | L12: 44 | M12: 26 | O12: 34084.29 | P12: 473.24 | Q12: 1162.68 | R12: 35720.21 | S12: 6747.19 | T12: 1739.15 | U12: 925.66 | V12: 9412 | W12: 4186.74 | X12: 950 | Y12: 1372.21 | Z12: 6508.95 | AA12: 7151.55 | AB12: 799.06 | AC12: 2041.27 | AD12: 9991.88 | AE12: 5209.73 | AF12: 2122.8 | AG12: 2780.96 | AH12: 10113.49 | AI12: 25617.11 | AJ12: 1969.69 | AK12: 4809.93 | AL12: 32396.73 | AM12: 11868.98 | AN12: 640.97 | AO12: 3789.83 | AP12: 16299.78 | AQ12: 28353.4 | AR12: 1284.5 | AS12: 4409.18 | AT12: 34047.08 | AU12: 23595.91 | AV12: 1355.28 | AW12: 5243.27 | AX12: 30194.46 | CJ12: 0.31770853 | CL12: 1121.8888 | CM12: 568.76641 | CN12: 583.77628 | CO12: 904.3337 | CP12: 1077.2483 | CQ12: 2305.8422 | CR12: 1529.0687 | CS12: 2303.9982 | CT12: 2326.2018 | DG12: 3 | DK12: 1 | DQ12: 4434.07 | DU12: 132.18 | EE12: 132.18
A13: 98933 | B13: COM | C13: =A13&B13 -> 98933COM | E13: 6 | F13: 6 | G13: 5 | H13: 6 | I13: 5 | J13: 4 | K13: 7 | L13: 8 | M13: 5 | O13: 3864.65 | P13: 273.81 | Q13: 49.14 | R13: 4187.6 | S13: 3224.29 | T13: 3476.65 | U13: 0 | V13: 6700.94 | W13: 696.79 | X13: 340.58 | Y13: 255.24 | Z13: 1292.61 | AA13: 1601.96 | AB13: 323.68 | AC13: 581.51 | AD13: 2507.15 | AE13: 2340.63 | AF13: 565.86 | AG13: 892.39 | AH13: 3798.88 | AI13: 898.59 | AJ13: 238.19 | AK13: 1203.87 | AL13: 2340.65 | AM13: 1433.43 | AN13: 862.59 | AO13: 1442.06 | AP13: 3738.08 | AQ13: 3542.54 | AR13: 421.55 | AS13: 1814.66 | AT13: 5778.75 | AU13: 2355.16 | AV13: 673.07 | AW13: 2195.97 | AX13: 5224.2 | CL13: 119.12037 | CM13: 367.14007 | CN13: 120.72194 | CO13: 249.83509 | CP13: 357.61206 | CQ13: 397.83084 | CR13: 533.72174 | CS13: 711.2703 | CT13: 801.20603
A14: 98935 | B14: COM | C14: =A14&B14 -> 98935COM | E14: 4 | F14: 6 | G14: 6 | H14: 5 | I14: 13 | J14: 5 | K14: 5 | L14: 5 | M14: 4 | O14: 149.96 | P14: 671.54 | Q14: 581.23 | R14: 1402.73 | S14: 754.6 | T14: 654.15 | U14: 311.23 | V14: 1719.98 | W14: 954.7 | X14: 546.48 | Y14: 365.42 | Z14: 1866.6 | AA14: 502.21 | AB14: 695.09 | AC14: 911.9 | AD14: 2109.2 | AE14: 1843.16 | AF14: 225.76 | AG14: 670.41 | AH14: 2739.33 | AI14: 253.45 | AJ14: 202.26 | AK14: 896.17 | AL14: 1351.88 | AM14: 289.37 | AN14: 0 | AO14: 1276.4 | AP14: 1565.77 | AQ14: 90.52 | AR14: 321.67 | AS14: 1192.57 | AT14: 1604.76 | AU14: 158.39 | AV14: 0 | AW14: 1513.61 | AX14: 1672 | CL14: 177.83509 | CM14: 149.60689 | CN14: 176.75503 | CO14: 334.71073 | CP14: 258.83263 | CQ14: 286.07286 | CR14: 385.15124 | CS14: 407.8232 | CT14: 484.68332
A15: 98936 | B15: COM | C15: =A15&B15 -> 98936COM | E15: 13 | F15: 17 | G15: 22 | H15: 21 | I15: 20 | J15: 21 | K15: 18 | L15: 21 | M15: 27 | O15: 1104.69 | P15: 78.91 | Q15: 1520.2 | R15: 2703.8 | S15: 3151.94 | T15: 633.25 | U15: 1433.68 | V15: 5218.87 | W15: 2444.51 | X15: 1857.26 | Y15: 1627.91 | Z15: 5929.68 | AA15: 3530.94 | AB15: 3133.97 | AC15: 2022.93 | AD15: 8687.84 | AE15: 1453.39 | AF15: 2537.97 | AG15: 5901.48 | AH15: 9892.84 | AI15: 2778.91 | AJ15: 1259.65 | AK15: 8299.19 | AL15: 12337.75 | AM15: 3827.82 | AN15: 2571.81 | AO15: 9163.91 | AP15: 15563.54 | AQ15: 2117.52 | AR15: 1482.42 | AS15: 6712.12 | AT15: 10312.06 | AU15: 12683.62 | AV15: 1442.45 | AW15: 8194.54 | AX15: 22320.61 | CL15: 393.50193 | CM15: 496.234 | CN15: 675.97277 | CO15: 961.0758 | CP15: 1892.4527 | CQ15: 2613.9906 | CR15: 3011.6491 | CS15: 2315.6924 | CT15: 3008.3816 | DJ15: 2 | DT15: 103.59 | ED15: 62.32
A16: 98937 | B16: COM | C16: =A16&B16 -> 98937COM | E16: 28 | F16: 22 | G16: 34 | H16: 35 | I16: 28 | J16: 37 | K16: 32 | L16: 36 | M16: 22 | O16: 2201.03 | P16: 805.92 | Q16: 721.38 | R16: 3728.33 | S16: 3729.78 | T16: 628.91 | U16: 315.98 | V16: 4674.67 | W16: 4471.17 | X16: 2079.24 | Y16: 157.9 | Z16: 6708.31 | AA16: 5410.5 | AB16: 2269.38 | AC16: 494.42 | AD16: 8174.3 | AE16: 4693.5 | AF16: 2128.39 | AG16: 1020.84 | AH16: 7842.73 | AI16: 3333.54 | AJ16: 2347.39 | AK16: 2460.92 | AL16: 8141.85 | AM16: 6046.68 | AN16: 1430.96 | AO16: 3620.15 | AP16: 11097.79 | AQ16: 5032.12 | AR16: 1881.12 | AS16: 3254.81 | AT16: 10168.05 | AU16: 2961.69 | AV16: 1481.18 | AW16: 2739.54 | AX16: 7182.41 | CL16: 267.69756 | CM16: 241.10847 | CN16: 376.02276 | CO16: 523.04709 | CP16: 557.26531 | CQ16: 1001.3264 | CR16: 1359.8255 | CS16: 1324.032 | CT16: 1044.9619 | DG16: 1 | DJ16: 2 | DQ16: 8.59 | DT16: 320.49 | EG16: 6.44
A17: 98938 | B17: COM | C17: =A17&B17 -> 98938COM | E17: 19 | F17: 9 | G17: 4 | H17: 10 | I17: 10 | J17: 31 | K17: 18 | L17: 21 | M17: 31 | O17: 28703.41 | P17: 7.92 | Q17: 0 | R17: 28711.33 | S17: 1460.29 | T17: 525.87 | U17: 7.92 | V17: 1994.08 | W17: 653.6 | X17: 28.9 | Y17: 0 | Z17: 682.5 | AA17: 2235.35 | AB17: 413.02 | AC17: 11.51 | AD17: 2659.88 | AE17: 8154.4 | AF17: 531.61 | AG17: 407.47 | AH17: 9093.48 | AI17: 44246.12 | AJ17: 389.25 | AK17: 904.91 | AL17: 45540.28 | AM17: 27696.04 | AN17: 189.79 | AO17: 914.92 | AP17: 28800.75 | AQ17: 27749.76 | AR17: 321.03 | AS17: 723.93 | AT17: 28794.72 | AU17: 28169.52 | AV17: 5734.07 | AW17: 53.25 | AX17: 33956.84 | CL17: 690.45807 | CM17: 87.632328 | CN17: 24.024445 | CO17: 118.02124 | CP17: 381.41988 | CQ17: 1575.6645 | CR17: 1132.806 | CS17: 1036.9539 | CT17: 1093.1765
A18: 98942 | B18: COM | C18: =A18&B18 -> 98942COM | E18: 61 | F18: 64 | G18: 61 | H18: 73 | I18: 70 | J18: 58 | K18: 46 | L18: 56 | M18: 63 | O18: 12032.12 | P18: 1888.13 | Q18: 1227.37 | R18: 15147.62 | S18: 50682.28 | T18: 3561.83 | U18: 2431.76 | V18: 56675.87 | W18: 9946.74 | X18: 2883.43 | Y18: 3116.66 | Z18: 15946.83 | AA18: 11559.45 | AB18: 5429.91 | AC18: 5479.66 | AD18: 22469.02 | AE18: 50847.74 | AF18: 6926.61 | AG18: 9794.77 | AH18: 67569.12 | AI18: 43936.06 | AJ18: 5152.35 | AK18: 14754.35 | AL18: 63842.76 | AM18: 7176.09 | AN18: 4418.02 | AO18: 12609.04 | AP18: 24203.15 | AQ18: 9350.26 | AR18: 5557.96 | AS18: 16123.68 | AT18: 31031.9 | AU18: 13554.32 | AV18: 5995.18 | AW18: 19525.29 | AX18: 39074.79 | CL18: 682.04274 | CM18: 2439.0431 | CN18: 1405.8815 | CO18: 2422.9475 | CP18: 4683.9702 | CQ18: 6001.8174 | CR18: 4268.3068 | CS18: 5834.5226 | CT18: 6947.5552 | DI18: 1 | DJ18: 3 | DS18: 83.67 | DT18: 189.48 | EC18: 83.67 | EG18: 118.91
A19: 98944 | B19: COM | C19: =A19&B19 -> 98944COM | E19: 102 | F19: 109 | G19: 116 | H19: 141 | I19: 139 | J19: 121 | K19: 115 | L19: 122 | M19: 148 | O19: 28613.88 | P19: 7264.59 | Q19: 16028.35 | R19: 51906.82 | S19: 29333.66 | T19: 8231.58 | U19: 15798.7 | V19: 53363.94 | W19: 28365.22 | X19: 13838.46 | Y19: 18015.38 | Z19: 60219.06 | AA19: 38176.02 | AB19: 14581.69 | AC19: 27376.56 | AD19: 80134.27 | AE19: 25168.18 | AF19: 15323.14 | AG19: 37689.21 | AH19: 78180.53 | AI19: 24913.62 | AJ19: 12061.23 | AK19: 45457.88 | AL19: 82432.73 | AM19: 29855.38 | AN19: 8886 | AO19: 48374.44 | AP19: 87115.82 | AQ19: 31184.6 | AR19: 9916.15 | AS19: 50435.11 | AT19: 91535.86 | AU19: 44021.59 | AV19: 13597.29 | AW19: 51075.36 | AX19: 108694.24 | CL19: 4897.1298 | CM19: 5397.1605 | CN19: 6916.3906 | CO19: 10363.582 | CP19: 12483.096 | CQ19: 14999.917 | CR19: 15842.006 | CS19: 17737.331 | CT19: 18233.27 | DG19: 1 | DH19: 3 | DI19: 1 | DJ19: 4 | DN19: 1 | DQ19: 74.38 | DR19: 412.46 | DS19: 198.41 | DT19: 2420.24 | DX19: 1155.9 | EB19: 224.58 | ED19: 16.75
A20: 98947 | B20: COM | C20: =A20&B20 -> 98947COM | E20: 24 | F20: 16 | G20: 12 | H20: 12 | I20: 14 | J20: 14 | K20: 18 | L20: 23 | M20: 21 | O20: 11460.87 | P20: 733.36 | Q20: 277.69 | R20: 12471.92 | S20: 4006.02 | T20: 1486.4 | U20: 154.83 | V20: 5647.25 | W20: 8745.89 | X20: 1847.37 | Y20: 663.19 | Z20: 11256.45 | AA20: 2453.94 | AB20: 2936.83 | AC20: 1541.56 | AD20: 6932.33 | AE20: 2095.96 | AF20: 2044.01 | AG20: 2638.66 | AH20: 6778.63 | AI20: 4199.68 | AJ20: 1991.46 | AK20: 3094.63 | AL20: 9285.77 | AM20: 3360.31 | AN20: 1627.78 | AO20: 4321.87 | AP20: 9309.96 | AQ20: 4113.45 | AR20: 1531.68 | AS20: 4242.07 | AT20: 9887.2 | AU20: 4822.47 | AV20: 1338.62 | AW20: 3321.27 | AX20: 9482.36 | CL20: 380.589 | CM20: 276.24261 | CN20: 627.9074 | CO20: 769.09484 | CP20: 943.04341 | CQ20: 1184.6531 | CR20: 1499.1133 | CS20: 1586.8701 | CT20: 1264.4133
A21: 98948 | B21: COM | C21: =A21&B21 -> 98948COM | E21: 82 | F21: 82 | G21: 61 | H21: 83 | I21: 115 | J21: 94 | K21: 123 | L21: 106 | M21: 95 | O21: 23670.59 | P21: 9817.95 | Q21: 9527.94 | R21: 43016.48 | S21: 45406.29 | T21: 10392.76 | U21: 15955.05 | V21: 71754.1 | W21: 11196.65 | X21: 4388.62 | Y21: 8562.34 | Z21: 24147.61 | AA21: 18721.49 | AB21: 8485.51 | AC21: 11791.56 | AD21: 38998.56 | AE21: 19917.3 | AF21: 18314.64 | AG21: 16273.44 | AH21: 54505.38 | AI21: 10461.57 | AJ21: 19008.72 | AK21: 22432.55 | AL21: 51902.84 | AM21: 29948.2 | AN21: 4265.13 | AO21: 34840.47 | AP21: 69053.8 | AQ21: 21391.13 | AR21: 7718.58 | AS21: 26566.07 | AT21: 55675.78 | AU21: 36008.3 | AV21: 11610.49 | AW21: 31064.86 | AX21: 78683.65 | AZ21: 4263.35 | BA21: 1046.4 | BC21: 5309.75 | BD21: 5183.12 | BE21: 3204.41 | BF21: 1046.4 | BG21: 9433.93 | BH21: 2706.94 | BI21: 3.75 | BK21: 2710.69 | BL21: 6015.17 | BM21: 2364.95 | BO21: 8380.12 | BP21: 5908.2 | BQ21: 5951.28 | BS21: 11859.48 | BT21: 2964.8 | BU21: 7647.2 | BV21: 3918.47 | BW21: 14530.47 | BX21: 7976.19 | BY21: 2914.57 | BZ21: 11044.5 | CA21: 21935.26 | CB21: 2300.29 | CC21: 1696.12 | CD21: 2847.77 | CE21: 6844.18 | CF21: 4100.83 | CG21: 2113.24 | CH21: 4316.18 | CI21: 10530.25 | CL21: 3362.1703 | CM21: 6099.8945 | CN21: 3014.4419 | CO21: 4727.9073 | CP21: 6365.0271 | CQ21: 8365.3402 | CR21: 11508.608 | CS21: 9672.3797 | CT21: 11544.729 | DG21: 1 | DH21: 1 | DI21: 7 | DJ21: 2 | DQ21: 0.32 | DR21: 244.27 | DS21: 2508.01 | DT21: 975.37 | EA21: 0.32
A22: 98951 | B22: COM | C22: =A22&B22 -> 98951COM | E22: 88 | F22: 114 | G22: 85 | H22: 88 | I22: 86 | J22: 109 | K22: 81 | L22: 75 | M22: 88 | O22: 64362.45 | P22: 1922.59 | Q22: 1690.43 | R22: 67975.47 | S22: 76535.55 | T22: 21184.04 | U22: 3957.03 | V22: 101676.62 | W22: 37253.46 | X22: 30018.66 | Y22: 20585.01 | Z22: 87857.13 | AA22: 43359.49 | AB22: 18643.46 | AC22: 8806.75 | AD22: 70809.7 | AE22: 38671.96 | AF22: 12576.05 | AG22: 9223.65 | AH22: 60471.66 | AI22: 26262.47 | AJ22: 8482.65 | AK22: 16803.69 | AL22: 51548.81 | AM22: 23891.44 | AN22: 17779.52 | AO22: 19019.06 | AP22: 60690.02 | AQ22: 30546.7 | AR22: 10574.39 | AS22: 22148.74 | AT22: 63269.83 | AU22: 25371.59 | AV22: 6949.61 | AW22: 23036.6 | AX22: 55357.8 | AZ22: 296.75 | BA22: 106.13 | BB22: 61.51 | BC22: 464.39 | BD22: 138.28 | BE22: 284.01 | BF22: 167.64 | BG22: 589.93 | BH22: 198.38 | BI22: 28.57 | BJ22: 207.35 | BK22: 434.3 | BL22: 187.22 | BM22: 198.38 | BN22: 235.92 | BO22: 621.52 | BP22: 170.1 | BQ22: 187.22 | BR22: 434.3 | BS22: 791.62 | BT22: 108.53 | BU22: 128.36 | BV22: 105.51 | BW22: 342.4 | BX22: 113.23 | BY22: 108.53 | BZ22: 233.87 | CA22: 455.63 | CB22: 116.95 | CC22: 113.23 | CD22: 342.4 | CE22: 572.58 | CF22: 30.46 | CG22: 116.95 | CH22: 455.63 | CI22: 603.04 | CL22: 2052.405 | CM22: 4967.1194 | CN22: 9346.3794 | CO22: 5606.5842 | CP22: 4520.5597 | CQ22: 6351.2317 | CR22: 7672.0194 | CS22: 8736.6338 | CT22: 8413.1357 | DG22: 3 | DJ22: 6 | DL22: 1 | DQ22: 455.93 | DT22: 14372.61 | DV22: 33.87 | EA22: 276.65 | ED22: 48.04 | EF22: 33.87 | EG22: 55.91
A23: 98952 | B23: COM | C23: =A23&B23 -> 98952COM | E23: 3 | F23: 1 | G23: 1 | H23: 4 | I23: 5 | J23: 5 | K23: 4 | L23: 2 | M23: 3 | O23: 1480.77 | P23: 245.28 | Q23: 0 | R23: 1726.05 | S23: 0.87 | T23: 0 | U23: 0 | V23: 0.87 | W23: 91.52 | X23: 0 | Y23: 0 | Z23: 91.52 | AA23: 1334.53 | AB23: 91.52 | AC23: 0 | AD23: 1426.05 | AE23: 1296.7 | AF23: 125.93 | AG23: 91.52 | AH23: 1514.15 | AI23: 177.28 | AJ23: 78.62 | AK23: 178.48 | AL23: 434.38 | AM23: 1433.71 | AN23: 55.32 | AO23: 257.1 | AP23: 1746.13 | AQ23: 65.25 | AR23: 38.34 | AS23: 312.42 | AT23: 416.01 | AU23: 175.81 | AV23: 36.48 | AW23: 350.76 | AX23: 563.05 | BH23: 91.52 | BK23: 91.52 | BL23: 86.96 | BM23: 91.52 | BO23: 178.48 | BP23: 78.62 | BQ23: 86.96 | BR23: 91.52 | BS23: 257.1 | BT23: 55.32 | BU23: 78.62 | BV23: 178.48 | BW23: 312.42 | BX23: 38.34 | BY23: 55.32 | BZ23: 257.1 | CA23: 350.76 | CB23: 36.48 | CC23: 38.34 | CD23: 312.42 | CE23: 387.24 | CF23: 16.34 | CG23: 36.48 | CH23: 350.76 | CI23: 403.58 | CL23: 48.575268 | CM23: 0.026985017 | CN23: 2.9980209 | CO23: 55.714509 | CP23: 70.870601 | CQ23: 63.625453 | CR23: 123.88235 | CS23: 104.51717 | CT23: 118.20499 | DJ23: 1 | DT23: 114.67 | ED23: 114.67
A24: 98953 | B24: COM | C24: =A24&B24 -> 98953COM | E24: 50 | F24: 45 | G24: 58 | H24: 66 | I24: 57 | J24: 46 | K24: 40 | L24: 59 | M24: 48 | O24: 10780.74 | P24: 3413.24 | Q24: 3220.65 | R24: 17414.63 | S24: 9165.6 | T24: 5173.53 | U24: 2982.85 | V24: 17321.98 | W24: 10821.9 | X24: 4981.04 | Y24: 4281.27 | Z24: 20084.21 | AA24: 10872.19 | AB24: 6630.19 | AC24: 6730.21 | AD24: 24232.59 | AE24: 7229.48 | AF24: 5613.28 | AG24: 9852.49 | AH24: 22695.25 | AI24: 4365.09 | AJ24: 4561.92 | AK24: 11590.42 | AL24: 20517.43 | AM24: 4784.8 | AN24: 3438.34 | AO24: 10939.72 | AP24: 19162.86 | AQ24: 94285.34 | AR24: 3716.02 | AS24: 13213.97 | AT24: 111215.33 | AU24: 7082.65 | AV24: 4838.43 | AW24: 12767.19 | AX24: 24688.27 | CL24: 1208.311 | CM24: 1409.6099 | CN24: 1930.3971 | CO24: 2852.6807 | CP24: 3380.3852 | CQ24: 3882.7649 | CR24: 3629.4529 | CS24: 7156.9747 | CT24: 4564.4218 | DI24: 3 | DL24: 1 | DS24: 3182.72 | DV24: 26.57 | EF24: 26.57
A25: 99323 | B25: COM | C25: =A25&B25 -> 99323COM | E25: 14 | F25: 9 | G25: 10 | H25: 10 | I25: 19 | J25: 13 | K25: 9 | L25: 14 | M25: 14 | O25: 4953.42 | P25: 355.81 | Q25: 493.61 | R25: 5802.84 | S25: 3706.74 | T25: 233.52 | U25: 167.96 | V25: 4108.22 | W25: 2421.11 | X25: 223.05 | Y25: 401.48 | Z25: 3045.64 | AA25: 1278.02 | AB25: 68.47 | AC25: 624.53 | AD25: 1971.02 | AE25: 3525.42 | AF25: 406.22 | AG25: 693 | AH25: 4624.64 | AI25: 2767.63 | AJ25: 414.25 | AK25: 1002.23 | AL25: 4184.11 | AM25: 2045.43 | AN25: 250.54 | AO25: 1331.02 | AP25: 3626.99 | AQ25: 4715.33 | AR25: 245.63 | AS25: 1581.56 | AT25: 6542.52 | AU25: 2192.39 | AV25: 1038.92 | AW25: 1827.19 | AX25: 5058.5 | CL25: 255.69836 | CM25: 173.89731 | CN25: 205.01934 | CO25: 229.31944 | CP25: 324.20409 | CQ25: 406.41926 | CR25: 473.85821 | CS25: 656.48702 | CT25: 705.72831 | DJ25: 1 | DT25: 94.92
A26: 99324 | B26: COM | C26: =A26&B26 -> 99324COM | E26: 7 | F26: 7 | G26: 10 | H26: 5 | I26: 4 | J26: 6 | K26: 2 | L26: 4 | M26: 9 | O26: 2004.59 | P26: 111.42 | Q26: 0 | R26: 2116.01 | S26: 673.98 | T26: 184.1 | U26: 0 | V26: 858.08 | W26: 1486.09 | X26: 253.59 | Y26: 110.43 | Z26: 1850.11 | AA26: 512.35 | AB26: 599.51 | AC26: 304.98 | AD26: 1416.84 | AE26: 341.18 | AF26: 127.73 | AG26: 572.43 | AH26: 1041.34 | AI26: 146.85 | AJ26: 140.32 | AK26: 700.16 | AL26: 987.33 | AM26: 107.79 | AN26: 56.42 | AO26: 776.37 | AP26: 940.58 | AQ26: 338.91 | AR26: 107.79 | AS26: 832.79 | AT26: 1279.49 | AU26: 1459.81 | AV26: 262.05 | AW26: 940.58 | AX26: 2662.44 | CL26: 54.085902 | CM26: 35.050497 | CN26: 100.64479 | CO26: 154.65177 | CP26: 181.98449 | CQ26: 220.64544 | CR26: 236.40718 | CS26: 283.67245 | CT26: 352.14934 | DG26: 1 | DQ26: 31.15
A27: 99328 | B27: COM | C27: =A27&B27 -> 99328COM | E27: 36 | F27: 24 | G27: 43 | H27: 39 | I27: 32 | J27: 31 | K27: 31 | L27: 30 | M27: 33 | O27: 12481.18 | P27: 2787.41 | Q27: 11033.61 | R27: 26302.2 | S27: 8186.04 | T27: 4960.69 | U27: 12322.69 | V27: 25469.42 | W27: 12221.81 | X27: 5905.06 | Y27: 11055.34 | Z27: 29182.21 | AA27: 20059.52 | AB27: 8336.8 | AC27: 13916.77 | AD27: 42313.09 | AE27: 6113.59 | AF27: 5915.32 | AG27: 16649.93 | AH27: 28678.84 | AI27: 5275.13 | AJ27: 3927.99 | AK27: 13776.41 | AL27: 22979.53 | AM27: 6285.47 | AN27: 3036.72 | AO27: 13367.7 | AP27: 22689.89 | AQ27: 5163.33 | AR27: 2461 | AS27: 8875.38 | AT27: 16499.71 | AU27: 5800.57 | AV27: 1885.46 | AW27: 9392.3 | AX27: 17078.33 | CL27: 3080.5094 | CM27: 3641.7627 | CN27: 3840.498 | CO27: 5368.0999 | CP27: 5320.0081 | CQ27: 4501.2745 | CR27: 4361.1048 | CS27: 3166.6308 | CT27: 3254.9229 | DI27: 1 | DS27: 81.48 | EC27: 81.48
A28: 99329 | B28: COM | C28: =A28&B28 -> 99329COM | E28: 2 | F28: 2 | G28: 4 | H28: 6 | I28: 3 | J28: 3 | K28: 3 | L28: 3 | M28: 1 | O28: 140.56 | P28: 103.03 | Q28: 183.18 | R28: 426.77 | S28: 171.79 | T28: 140.56 | U28: 286.21 | V28: 598.56 | W28: 476.32 | X28: 171.79 | Y28: 426.77 | Z28: 1074.88 | AA28: 677.03 | AB28: 476.32 | AC28: 598.56 | AD28: 1751.91 | AE28: 424.3 | AF28: 223.97 | AG28: 770.12 | AH28: 1418.39 | AI28: 295.82 | AJ28: 424.3 | AK28: 694.09 | AL28: 1414.21 | AM28: 287.89 | AN28: 89.64 | AO28: 824.57 | AP28: 1202.1 | AQ28: 239.25 | AR28: 63.39 | AS28: 906.46 | AT28: 1209.1 | AU28: 70.34 | AV28: 35.58 | AW28: 851.55 | AX28: 957.47 | CL28: 52.542938 | CM28: 85.962791 | CN28: 143.32359 | CO28: 233.89331 | CP28: 247.04581 | CQ28: 245.27491 | CR28: 258.62697 | CS28: 301.01695 | CT28: 274.71924
A29: 99347 | B29: COM | C29: =A29&B29 -> 99347COM | E29: 12 | F29: 12 | G29: 19 | H29: 18 | I29: 25 | J29: 18 | K29: 21 | L29: 13 | M29: 18 | O29: 3711.67 | P29: 476.78 | Q29: 508.46 | R29: 4696.91 | S29: 1522.3 | T29: 396.5 | U29: 943.61 | V29: 2862.41 | W29: 4951.82 | X29: 572.27 | Y29: 1320.82 | Z29: 6844.91 | AA29: 2597.36 | AB29: 2037.51 | AC29: 1650.41 | AD29: 6285.28 | AE29: 6447.62 | AF29: 2163.63 | AG29: 3241.57 | AH29: 11852.82 | AI29: 2051.87 | AJ29: 1284.68 | AK29: 2248.14 | AL29: 5584.69 | AM29: 2393.35 | AN29: 982.05 | AO29: 2756.99 | AP29: 6132.39 | AQ29: 2359.56 | AR29: 1365.18 | AS29: 3482.97 | AT29: 7207.71 | AU29: 3278.63 | AV29: 848.87 | AW29: 3962.5 | AX29: 8090 | AZ29: 266.65 | BA29: 25.71 | BC29: 292.36 | BD29: 226.98 | BG29: 226.98 | BH29: 252.84 | BI29: 226.98 | BK29: 479.82 | BL29: 360.09 | BM29: 189.36 | BO29: 549.45 | BP29: 227.36 | BQ29: 124.39 | BS29: 351.75 | BT29: 63.84 | BW29: 63.84 | BX29: 209.92 | BY29: 1.84 | CA29: 211.76 | CB29: 151.71 | CE29: 151.71 | CF29: 151.28 | CI29: 151.28 | CL29: 235.79018 | CM29: 307.92069 | CN29: 561.16776 | CO29: 731.02309 | CP29: 1247.2592 | CQ29: 819.09982 | CR29: 959.73946 | CS29: 1282.424 | CT29: 1396.8785 | DI29: 1 | DJ29: 1 | DK29: 2 | DS29: 277.4 | DT29: 3.48 | DU29: 79.25 | EE29: 26.79
A30: 99348 | B30: COM | C30: =A30&B30 -> 99348COM | E30: 1 | G30: 1 | H30: 2 | I30: 4 | J30: 5 | K30: 4 | L30: 4 | M30: 4 | O30: 135.07 | P30: 0 | Q30: 0 | R30: 135.07 | W30: 229.72 | X30: 0 | Y30: 0 | Z30: 229.72 | AA30: 6.78 | AB30: 0 | AC30: 0 | AD30: 6.78 | AE30: 242.24 | AF30: 6.68 | AG30: 0 | AH30: 248.92 | AI30: 976.08 | AJ30: 1.88 | AK30: 0 | AL30: 977.96 | AM30: 938.89 | AN30: 60.5 | AO30: 1.88 | AP30: 1001.27 | AQ30: 1025.57 | AR30: 30.41 | AS30: 0 | AT30: 1055.98 | AU30: 1046.51 | AV30: 22.74 | AW30: 0 | AX30: 1069.25 | CL30: 3.2471255 | CN30: 7.5251898 | CO30: 0.24469557 | CP30: 7.2940653 | CQ30: 28.37911 | CR30: 33.866137 | CS30: 31.189329 | CT30: 26.674665
A31: 99360 | B31: COM | C31: =A31&B31 -> 99360COM | E31: 13 | F31: 12 | G31: 3 | H31: 4 | I31: 16 | J31: 16 | K31: 7 | L31: 10 | M31: 12 | O31: 4475.98 | P31: 972.7 | Q31: 965.09 | R31: 6413.77 | S31: 3478.13 | T31: 182.5 | U31: 1313.8 | V31: 4974.43 | W31: 775.15 | X31: 505.96 | Y31: 1352.19 | Z31: 2633.3 | AA31: 1698.72 | AB31: 610.25 | AC31: 1357.05 | AD31: 3666.02 | AE31: 7703.62 | AF31: 1356.19 | AG31: 2378.24 | AH31: 11438.05 | AI31: 2562.11 | AJ31: 1430.59 | AK31: 3545.52 | AL31: 7538.22 | AM31: 2247.42 | AN31: 1626.44 | AO31: 4532.06 | AP31: 8405.92 | AQ31: 2062.93 | AR31: 2173.48 | AS31: 6125.79 | AT31: 10362.2 | AU31: 1786.31 | AV31: 1922.97 | AW31: 8299.27 | AX31: 12008.55 | CL31: 389.3692 | CM31: 442.46743 | CN31: 426.59695 | CO31: 497.44508 | CP31: 985.38234 | CQ31: 1225.9582 | CR31: 1526.8677 | CS31: 2179.4432 | CT31: 2814.0622
A32: 99361 | B32: COM | C32: =A32&B32 -> 99361COM | E32: 10 | F32: 11 | G32: 15 | H32: 17 | I32: 10 | J32: 11 | K32: 9 | L32: 28 | M32: 27 | O32: 938.62 | P32: 23.84 | Q32: 0 | R32: 962.46 | S32: 1151.25 | T32: 23.56 | U32: 11.55 | V32: 1186.36 | W32: 1905.07 | X32: 204.08 | Y32: 23.22 | Z32: 2132.37 | AA32: 1528.38 | AB32: 1303.22 | AC32: 50.12 | AD32: 2881.72 | AE32: 1134.76 | AF32: 488.89 | AG32: 761.04 | AH32: 2384.69 | AI32: 1292.8 | AJ32: 594.98 | AK32: 1198.9 | AL32: 3086.68 | AM32: 1079.26 | AN32: 731.53 | AO32: 1500.16 | AP32: 3310.95 | AQ32: 4574.44 | AR32: 628.32 | AS32: 2159.5 | AT32: 7362.26 | AU32: 2778.12 | AV32: 1214.25 | AW32: 2681.12 | AX32: 6673.49 | CL32: 23.82603 | CM32: 40.337036 | CN32: 86.967478 | CO32: 176.92265 | CP32: 280.88465 | CQ32: 435.54336 | CR32: 530.16886 | CS32: 866.16036 | CT32: 1003.3317 | DG32: 1 | DQ32: 389.95
A33: 99362 | B33: COM | C33: =A33&B33 -> 99362COM | E33: 70 | F33: 62 | G33: 98 | H33: 135 | I33: 150 | J33: 92 | K33: 97 | L33: 104 | M33: 126 | O33: 12678.68 | P33: 1557.65 | Q33: 3775.19 | R33: 18011.52 | S33: 9103.82 | T33: 1819.28 | U33: 3423.84 | V33: 14346.94 | W33: 19252.04 | X33: 2807.61 | Y33: 4184.42 | Z33: 26244.07 | AA33: 28713.23 | AB33: 14258.59 | AC33: 6223.88 | AD33: 49195.7 | AE33: 45283.34 | AF33: 14418.44 | AG33: 11726.35 | AH33: 71428.13 | AI33: 25210.76 | AJ33: 12626.28 | AK33: 17246.72 | AL33: 55083.76 | AM33: 17292.34 | AN33: 8965.93 | AO33: 27355.14 | AP33: 53613.41 | AQ33: 25047.3 | AR33: 14016.27 | AS33: 29128.22 | AT33: 68191.79 | AU33: 27589.99 | AV33: 10002.36 | AW33: 35529.39 | AX33: 73121.74 | CL33: 1288.0955 | CM33: 1257.5671 | CN33: 1984.526 | CO33: 3981.9664 | CP33: 5540.4935 | CQ33: 6773.3233 | CR33: 9266.4694 | CS33: 11072.149 | CT33: 12648.891 | DG33: 1 | DH33: 1 | DI33: 2 | DJ33: 11 | DK33: 1 | DL33: 1 | DQ33: 3.02 | DR33: 15.02 | DS33: 477.9 | DT33: 974.43 | DU33: 20.86 | DV33: 235.32 | EC33: 237.12 | ED33: 387.67 | EG33: 340.63
A34: 99363 | B34: COM | C34: =A34&B34 -> 99363COM | E34: 1 | F34: 1 | H34: 2 | I34: 5 | J34: 8 | K34: 3 | L34: 2 | M34: 5 | O34: 23.71 | P34: 21.48 | Q34: 0 | R34: 45.19 | S34: 294.05 | T34: 0 | U34: 0 | V34: 294.05 | AA34: 134.3 | AB34: 0 | AC34: 0 | AD34: 134.3 | AE34: 438.87 | AF34: 0 | AG34: 0 | AH34: 438.87 | AI34: 1768.02 | AJ34: 27.93 | AK34: 42.89 | AL34: 1838.84 | AM34: 189.73 | AN34: 50.31 | AO34: 70.82 | AP34: 310.86 | AQ34: 56.26 | AR34: 38.76 | AS34: 9.58 | AT34: 104.6 | AU34: 427.54 | AV34: 44.71 | AW34: 48.34 | AX34: 520.59 | CL34: 1.7064435 | CM34: 9.1206254 | CO34: 4.8469933 | CP34: 12.472106 | CQ34: 65.900147 | CR34: 30.464579 | CS34: 7.5892381 | CT34: 28.733005
A35: 98603 | B35: RES | C35: =A35&B35 -> 98603RES | E35: 2 | F35: 1 | G35: 2 | H35: 1 | J35: 2 | K35: 3 | L35: 3 | M35: 2 | O35: 193.12 | P35: 71.94 | Q35: 0 | R35: 265.06 | S35: 134.22 | T35: 0 | U35: 0 | V35: 134.22 | W35: 314.3 | X35: 134.22 | Y35: 0 | Z35: 448.52 | AA35: 73.95 | AB35: 99.78 | AC35: 0 | AD35: 173.73 | AI35: 137.09 | AJ35: 0 | AK35: 0 | AL35: 137.09 | AM35: 240.84 | AN35: 88.96 | AO35: 0 | AP35: 329.8 | AQ35: 230.75 | AR35: 147.87 | AS35: 0 | AT35: 378.62 | AU35: 227.73 | AV35: 86.75 | AW35: 87.56 | AX35: 402.04 | CL35: 8.4488131 | CM35: 4.1631367 | CN35: 22.434902 | CO35: 10.900616 | CQ35: 3.9652829 | CR35: 14.050987 | CS35: 17.735968 | CT35: 39.344581
A36: 98901 | B36: RES | C36: =A36&B36 -> 98901RES | E36: 1791 | F36: 2003 | G36: 2437 | H36: 2457 | I36: 2589 | J36: 2271 | K36: 2081 | L36: 2064 | M36: 2182 | O36: 211556.16 | P36: 49355.3 | Q36: 106478.27 | R36: 367389.73 | S36: 266940.28 | T36: 90735.95 | U36: 86472.57 | V36: 444148.8 | W36: 331306.28 | X36: 139007.9 | Y36: 118095.2 | Z36: 588409.38 | AA36: 285711.64 | AB36: 187431.68 | AC36: 192742.46 | AD36: 665885.78 | AE36: 283319.02 | AF36: 178061.7 | AG36: 295396.06 | AH36: 756776.78 | AI36: 157353.87 | AJ36: 172107.96 | AK36: 370224.93 | AL36: 699686.76 | AM36: 136305.7 | AN36: 91769.7 | AO36: 440880.57 | AP36: 668955.97 | AQ36: 126994.15 | AR36: 102469.1 | AS36: 443670.38 | AT36: 673133.63 | AU36: 188410.44 | AV36: 83261.09 | AW36: 462572.34 | AX36: 734243.87 | AZ36: 26441.46 | BA36: 8076.58 | BB36: 25567.34 | BC36: 60085.38 | BD36: 26927.63 | BE36: 14721.25 | BF36: 22024.94 | BG36: 63673.82 | BH36: 28524.05 | BI36: 17745.99 | BJ36: 27203 | BK36: 73473.04 | BL36: 26085.85 | BM36: 19410.97 | BN36: 36126.33 | BO36: 81623.15 | BP36: 27302.66 | BQ36: 19653.85 | BR36: 49293.7 | BS36: 96250.21 | BT36: 17354.58 | BU36: 19189.3 | BV36: 60975.14 | BW36: 97519.02 | BX36: 15339.28 | BY36: 10625.55 | BZ36: 67991.79 | CA36: 93956.62 | CB36: 13706.7 | CC36: 14767.51 | CD36: 71559.49 | CE36: 100033.7 | CF36: 19009.31 | CG36: 9828.92 | CH36: 70795.22 | CI36: 99633.45 | CL36: 33106.362 | CM36: 36350.551 | CN36: 54468.237 | CO36: 80568.647 | CP36: 103841.22 | CQ36: 126596.82 | CR36: 141029.2 | CS36: 153042.28 | CT36: 157302.71 | DG36: 79 | DH36: 35 | DI36: 60 | DJ36: 92 | DK36: 37 | DL36: 30 | DQ36: 24291.68 | DR36: 11494.23 | DS36: 16501.22 | DT36: 36800.86 | DU36: 10519.58 | DV36: 7519.44 | EA36: 3171.7 | EB36: 730.68 | EC36: 3314.41 | ED36: 2358.25 | EE36: 3086.46 | EF36: 1502.08 | EG36: 1931.95
A37: 98902 | B37: RES | C37: =A37&B37 -> 98902RES | E37: 4693 | F37: 4490 | G37: 4191 | H37: 4086 | I37: 4485 | J37: 4132 | K37: 4125 | L37: 4351 | M37: 4311 | O37: 635243.51 | P37: 142831.08 | Q37: 109970.09 | R37: 888044.68 | S37: 589300.06 | T37: 183914.74 | U37: 108026.7 | V37: 881241.5 | W37: 408410.38 | X37: 309914.48 | Y37: 150061.96 | Z37: 868386.82 | AA37: 426143.77 | AB37: 262940.95 | AC37: 269245.44 | AD37: 958330.16 | AE37: 354380.16 | AF37: 330641.52 | AG37: 407762.84 | AH37: 1092784.5 | AI37: 223156.79 | AJ37: 254252.39 | AK37: 503311.56 | AL37: 980720.74 | AM37: 289886.51 | AN37: 129102.32 | AO37: 555740.97 | AP37: 974729.8 | AQ37: 346119.51 | AR37: 156930.52 | AS37: 566480.19 | AT37: 1069530.2 | AU37: 344831.92 | AV37: 193881.03 | AW37: 581904.12 | AX37: 1120617.1 | AZ37: 53146.56 | BA37: 18696.43 | BB37: 25522.09 | BC37: 97365.08 | BD37: 46528.26 | BE37: 21774.33 | BF37: 23673.88 | BG37: 91976.47 | BH37: 36211.16 | BI37: 31191.41 | BJ37: 30909.39 | BK37: 98311.96 | BL37: 38995.5 | BM37: 26847.56 | BN37: 45527.91 | BO37: 111370.97 | BP37: 33424.16 | BQ37: 34721.6 | BR37: 65125.42 | BS37: 133271.18 | BT37: 24320.8 | BU37: 27325.06 | BV37: 77475.69 | BW37: 129121.55 | BX37: 27788.61 | BY37: 14155.25 | BZ37: 73453.91 | CA37: 115397.77 | CB37: 31822.6 | CC37: 17786.05 | CD37: 79590.6 | CE37: 129199.25 | CF37: 29417.13 | CG37: 20227.47 | CH37: 79114.34 | CI37: 128758.94 | CL37: 49070.749 | CM37: 58767.877 | CN37: 80854.011 | CO37: 113615.19 | CP37: 147505.13 | CQ37: 173950.49 | CR37: 182396 | CS37: 202568.83 | CT37: 206701.75 | DG37: 93 | DH37: 56 | DI37: 112 | DJ37: 125 | DK37: 43 | DL37: 46 | DQ37: 23031.17 | DR37: 11938.61 | DS37: 43588.68 | DT37: 46863.11 | DU37: 9870.55 | DV37: 14516.59 | EA37: 3102.07 | EB37: 2046.57 | EC37: 4601.78 | ED37: 6786.44 | EE37: 2660.06 | EF37: 1845.63 | EG37: 1727
A38: 98903 | B38: RES | C38: =A38&B38 -> 98903RES | E38: 1638 | F38: 1579 | G38: 1685 | H38: 1709 | I38: 1958 | J38: 1536 | K38: 1537 | L38: 1589 | M38: 1327 | O38: 275061.31 | P38: 87636.11 | Q38: 67222.86 | R38: 429920.28 | S38: 265584.44 | T38: 82201.84 | U38: 68401.98 | V38: 416188.26 | W38: 255838.06 | X38: 130359.84 | Y38: 93306.24 | Z38: 479504.14 | AA38: 236917.35 | AB38: 140904.84 | AC38: 152132.17 | AD38: 529954.36 | AE38: 226442.07 | AF38: 181354.85 | AG38: 211300.72 | AH38: 619097.64 | AI38: 103719.78 | AJ38: 139611.71 | AK38: 261811.37 | AL38: 505142.86 | AM38: 140825.51 | AN38: 43066.62 | AO38: 310614.76 | AP38: 494506.89 | AQ38: 138506.14 | AR38: 87443.69 | AS38: 296706.58 | AT38: 522656.41 | AU38: 109224.85 | AV38: 67052.49 | AW38: 306032.03 | AX38: 482309.37 | AZ38: 19086.36 | BA38: 11792.61 | BB38: 17447.02 | BC38: 48325.99 | BD38: 16634.29 | BE38: 8822.29 | BF38: 13278.41 | BG38: 38734.99 | BH38: 18786.04 | BI38: 12404.55 | BJ38: 14222.76 | BK38: 45413.35 | BL38: 16787.35 | BM38: 13027.91 | BN38: 20741.02 | BO38: 50556.28 | BP38: 18054.16 | BQ38: 16600.38 | BR38: 28705.41 | BS38: 63359.95 | BT38: 7659.03 | BU38: 14639.98 | BV38: 34249.49 | BW38: 56548.5 | BX38: 11094.65 | BY38: 3485.71 | BZ38: 39506.26 | CA38: 54086.62 | CB38: 8480.4 | CC38: 9379.93 | CD38: 37259.98 | CE38: 55120.31 | CF38: 6876.8 | CG38: 6487.43 | CH38: 34015.71 | CI38: 47379.94 | CL38: 27290.741 | CM38: 31243.607 | CN38: 44697.724 | CO38: 63424.234 | CP38: 78267.639 | CQ38: 90700.048 | CR38: 99114.071 | CS38: 105294.12 | CT38: 104536.83 | DG38: 20 | DH38: 29 | DI38: 18 | DJ38: 40 | DK38: 16 | DL38: 13 | DN38: 2 | DQ38: 5116.5 | DR38: 10964.56 | DS38: 13323.17 | DT38: 18140.77 | DU38: 3338.55 | DV38: 3231.23 | DX38: 2164.79 | EA38: 1413.53 | EB38: 1752.54 | EC38: 1180 | ED38: 3327.94 | EE38: 131.84 | EF38: 352.84 | EG38: 70.57
A39: 98908 | B39: RES | C39: =A39&B39 -> 98908RES | E39: 2982 | F39: 3347 | G39: 3428 | H39: 3270 | I39: 3083 | J39: 2920 | K39: 2619 | L39: 2887 | M39: 2982 | O39: 457284.55 | P39: 75247.62 | Q39: 60443.45 | R39: 592975.62 | S39: 519437.76 | T39: 147581.21 | U39: 70891.76 | V39: 737910.73 | W39: 436145.99 | X39: 240383.96 | Y39: 119362.6 | Z39: 795892.55 | AA39: 383361.37 | AB39: 236620.23 | AC39: 206209.41 | AD39: 826191.01 | AE39: 290907.9 | AF39: 221299.71 | AG39: 284366.9 | AH39: 796574.51 | AI39: 203244.25 | AJ39: 169197.36 | AK39: 341962.34 | AL39: 714403.95 | AM39: 200426.21 | AN39: 109483.88 | AO39: 360670.83 | AP39: 670580.92 | AQ39: 260112.03 | AR39: 105371.71 | AS39: 350429.68 | AT39: 715913.42 | AU39: 306548.73 | AV39: 128285.6 | AW39: 346275.4 | AX39: 781109.73 | AZ39: 20194.44 | BA39: 5809.53 | BB39: 6529.74 | BC39: 32533.71 | BD39: 19676.18 | BE39: 10778.62 | BF39: 7320.91 | BG39: 37775.71 | BH39: 15722.93 | BI39: 12723.1 | BJ39: 12522.72 | BK39: 40968.75 | BL39: 14343.46 | BM39: 11498.54 | BN39: 19195.09 | BO39: 45037.09 | BP39: 10731.94 | BQ39: 11055.81 | BR39: 23572.11 | BS39: 45359.86 | BT39: 7904.69 | BU39: 8699.06 | BV39: 28912.6 | BW39: 45516.35 | BX39: 7405.3 | BY39: 5221.7 | BZ39: 26724.35 | CA39: 39351.35 | CB39: 8589.59 | CC39: 5212.07 | CD39: 26526.69 | CE39: 40328.35 | CF39: 8921.37 | CG39: 4997 | CH39: 20238.54 | CI39: 34156.91 | CL39: 29398.213 | CM39: 44748.42 | CN39: 67404.326 | CO39: 91979.37 | CP39: 103541.72 | CQ39: 119403.4 | CR39: 120676.69 | CS39: 127236.43 | CT39: 126334.99 | DG39: 47 | DH39: 30 | DI39: 28 | DJ39: 44 | DK39: 19 | DL39: 21 | DO39: 1 | DQ39: 10075.95 | DR39: 10449.74 | DS39: 7449.88 | DT39: 18524.57 | DU39: 3098.79 | DV39: 8849.41 | DY39: 239.25 | EA39: 2882.69 | EB39: 2398.89 | EC39: 1447.2 | ED39: 1136.06 | EE39: 934.07 | EF39: 1176.55 | EG39: 1493.45
A40: 98920 | B40: RES | C40: =A40&B40 -> 98920RES | E40: 1 | G40: 1 | H40: 1 | I40: 1 | M40: 1 | O40: 104.22 | P40: 0 | Q40: 0 | R40: 104.22 | W40: 109.1 | X40: 0 | Y40: 0 | Z40: 109.1 | AA40: 11.73 | AB40: 0 | AC40: 0 | AD40: 11.73 | AE40: 101.13 | AF40: 11.73 | AG40: 0 | AH40: 112.86 | AU40: 39.25 | AV40: 0 | AW40: 0 | AX40: 39.25 | CL40: 2.5054817 | CN40: 3.5739083 | CO40: 0.42334499 | CP40: 3.5938033 | CT40: 0.94079764
A41: 98921 | B41: RES | C41: =A41&B41 -> 98921RES | E41: 87 | F41: 88 | G41: 85 | H41: 89 | I41: 85 | J41: 84 | K41: 85 | L41: 74 | M41: 76 | O41: 12756.49 | P41: 3236.3 | Q41: 2495.07 | R41: 18487.86 | S41: 13815.63 | T41: 6037.08 | U41: 2844.39 | V41: 22697.1 | W41: 10690.97 | X41: 7259.9 | Y41: 5171.68 | Z41: 23122.55 | AA41: 10443.22 | AB41: 7247.15 | AC41: 9083.09 | AD41: 26773.46 | AE41: 7307 | AF41: 7092.66 | AG41: 11711.38 | AH41: 26111.04 | AI41: 5378.38 | AJ41: 5313.97 | AK41: 14838.57 | AL41: 25530.92 | AM41: 5393.9 | AN41: 3522.83 | AO41: 16914.68 | AP41: 25831.41 | AQ41: 5242.93 | AR41: 3369.01 | AS41: 17692.01 | AT41: 26303.95 | AU41: 6870.39 | AV41: 3681.09 | AW41: 18027.86 | AX41: 28579.34 | AZ41: 2882.61 | BA41: 849.16 | BB41: 900.12 | BC41: 4631.89 | BD41: 2416.88 | BE41: 1750.54 | BF41: 976.97 | BG41: 5144.39 | BH41: 2035.99 | BI41: 1106.4 | BJ41: 1405.99 | BK41: 4548.38 | BL41: 2331 | BM41: 1641.87 | BN41: 2238.15 | BO41: 6211.02 | BP41: 1839.72 | BQ41: 1972.58 | BR41: 3445.71 | BS41: 7258.01 | BT41: 1396.54 | BU41: 1437.96 | BV41: 3707.93 | BW41: 6542.43 | BX41: 1367.93 | BY41: 1071.26 | BZ41: 4304.36 | CA41: 6743.55 | CB41: 1440.97 | CC41: 1021.32 | CD41: 4930.99 | CE41: 7393.28 | CF41: 1727.49 | CG41: 1208.57 | CH41: 4690.83 | CI41: 7626.89 | CL41: 1073.2999 | CM41: 1586.409 | CN41: 2366.2697 | CO41: 3556.9912 | CP41: 4007.4023 | CQ41: 4923.8442 | CR41: 5415.8718 | CS41: 6053.3215 | CT41: 6149.747 | DG41: 5 | DH41: 1 | DI41: 2 | DJ41: 1 | DL41: 1 | DQ41: 886.18 | DR41: 448.52 | DS41: 820.43 | DT41: 360.39 | DV41: 598.8 | EA41: 466.46 | EC41: 41.56
A42: 98923 | B42: RES | C42: =A42&B42 -> 98923RES | E42: 106 | F42: 136 | G42: 130 | H42: 143 | I42: 123 | J42: 127 | K42: 109 | L42: 114 | M42: 102 | O42: 19897.85 | P42: 2541.44 | Q42: 980.11 | R42: 23419.4 | S42: 23780.39 | T42: 6906.65 | U42: 1246.11 | V42: 31933.15 | W42: 21373.35 | X42: 9758.59 | Y42: 3386.71 | Z42: 34518.65 | AA42: 22461.25 | AB42: 12435.64 | AC42: 7512.19 | AD42: 42409.08 | AE42: 16138.2 | AF42: 13775.51 | AG42: 11386.79 | AH42: 41300.5 | AI42: 10997.46 | AJ42: 10788 | AK42: 16462.07 | AL42: 38247.53 | AM42: 8875.15 | AN42: 6099.25 | AO42: 17004.41 | AP42: 31978.81 | AQ42: 10041.35 | AR42: 5730.64 | AS42: 16265.51 | AT42: 32037.5 | AU42: 9092.72 | AV42: 5511.26 | AW42: 16659.29 | AX42: 31263.27 | AZ42: 808.04 | BA42: 79.52 | BB42: 19.15 | BC42: 906.71 | BD42: 1275.55 | BE42: 346.07 | BF42: 98.67 | BG42: 1720.29 | BH42: 1142.55 | BI42: 940.67 | BJ42: 50.7 | BK42: 2133.92 | BL42: 1103.72 | BM42: 1081.44 | BN42: 297.83 | BO42: 2482.99 | BP42: 856.8 | BQ42: 1059.59 | BR42: 794.53 | BS42: 2710.92 | BT42: 656.55 | BU42: 705.54 | BV42: 822.14 | BW42: 2184.23 | BX42: 559.13 | BY42: 436.5 | BZ42: 292.53 | CA42: 1288.16 | CB42: 542.44 | CC42: 326.57 | CD42: 166.46 | CE42: 1035.47 | CF42: 501.17 | CG42: 334.05 | CH42: 144.38 | CI42: 979.6 | CL42: 846.69781 | CM42: 1572.3277 | CN42: 2472.981 | CO42: 3972.1871 | CP42: 4575.2228 | CQ42: 5988.8642 | CR42: 5742.1792 | CS42: 5912.3975 | CT42: 5896.2144 | DG42: 3 | DH42: 1 | DI42: 3 | DQ42: 230.84 | DR42: 405.04 | DS42: 780.25 | EA42: 122.73 | EC42: 241.51
A43: 98930 | B43: RES | C43: =A43&B43 -> 98930RES | E43: 668 | F43: 753 | G43: 918 | H43: 942 | I43: 924 | J43: 833 | K43: 727 | L43: 683 | M43: 761 | O43: 87553.86 | P43: 8405.55 | Q43: 17914.18 | R43: 113873.59 | S43: 103623.11 | T43: 27085.84 | U43: 11801.79 | V43: 142510.74 | W43: 130320.63 | X43: 44537.58 | Y43: 18084.32 | Z43: 192942.53 | AA43: 114106.44 | AB43: 68575.95 | AC43: 41844.14 | AD43: 224526.53 | AE43: 101468.93 | AF43: 63900.12 | AG43: 72169.82 | AH43: 237538.87 | AI43: 59219.13 | AJ43: 59824.4 | AK43: 93953.51 | AL43: 212997.04 | AM43: 48916.43 | AN43: 32210.88 | AO43: 110876.69 | AP43: 192004 | AQ43: 49275.73 | AR43: 32198.93 | AS43: 112273.18 | AT43: 193747.84 | AU43: 69397.45 | AV43: 29282.87 | AW43: 113654.62 | AX43: 212334.94 | AZ43: 14314.01 | BA43: 898.44 | BB43: 4278.46 | BC43: 19490.91 | BD43: 15583.86 | BE43: 6264.21 | BF43: 2816.44 | BG43: 24664.51 | BH43: 15306.12 | BI43: 8129.05 | BJ43: 4034.52 | BK43: 27469.69 | BL43: 13000.28 | BM43: 10840.98 | BN43: 8394.86 | BO43: 32236.12 | BP43: 13169.52 | BQ43: 9490.47 | BR43: 13070.39 | BS43: 35730.38 | BT43: 7179.86 | BU43: 9156.1 | BV43: 15417.93 | BW43: 31753.89 | BX43: 6577.45 | BY43: 5208.92 | BZ43: 18187.94 | CA43: 29974.31 | CB43: 6001.9 | CC43: 5250.97 | CD43: 17373.99 | CE43: 28626.86 | CF43: 7968.86 | CG43: 3936.16 | CH43: 15771.9 | CI43: 27676.92 | CL43: 6824.4519 | CM43: 8174.8665 | CN43: 13050.846 | CO43: 21671.368 | CP43: 27538.182 | CQ43: 33941.636 | CR43: 36600.552 | CS43: 39687.208 | CT43: 39820.561 | DG43: 18 | DH43: 10 | DI43: 10 | DJ43: 16 | DK43: 5 | DL43: 10 | DQ43: 9598.92 | DR43: 3606.48 | DS43: 2665.49 | DT43: 6046.86 | DU43: 416.1 | DV43: 1740.46 | EA43: 1549.86 | EB43: 1648.21 | EC43: 113.23 | ED43: 110.47 | EE43: 303.71 | EF43: 143.39 | EG43: 1226.27
A44: 98932 | B44: RES | C44: =A44&B44 -> 98932RES | E44: 521 | F44: 547 | G44: 528 | H44: 517 | I44: 482 | J44: 469 | K44: 439 | L44: 455 | M44: 458 | O44: 84227.48 | P44: 16710.31 | Q44: 12157.66 | R44: 113095.45 | S44: 88716.45 | T44: 31053.22 | U44: 14427.03 | V44: 134196.7 | W44: 70336.77 | X44: 44143.38 | Y44: 26565.46 | Z44: 141045.61 | AA44: 61586.56 | AB44: 40017.84 | AC44: 44094.63 | AD44: 145699.03 | AE44: 44448.11 | AF44: 36544.01 | AG44: 59653.69 | AH44: 140645.81 | AI44: 30962.23 | AJ44: 28375.98 | AK44: 71097.16 | AL44: 130435.37 | AM44: 30922.22 | AN44: 17265.45 | AO44: 73155.1 | AP44: 121342.77 | AQ44: 41773.39 | AR44: 18218.01 | AS44: 69051.3 | AT44: 129042.7 | AU44: 42912.85 | AV44: 23719.23 | AW44: 71176.01 | AX44: 137808.09 | AZ44: 11937.73 | BA44: 3160.13 | BB44: 2438.84 | BC44: 17536.7 | BD44: 11078.33 | BE44: 6068.97 | BF44: 3447.7 | BG44: 20595 | BH44: 7722.84 | BI44: 6648.52 | BJ44: 4231.22 | BK44: 18602.58 | BL44: 7659.59 | BM44: 5417.86 | BN44: 6665 | BO44: 19742.45 | BP44: 5719.41 | BQ44: 5568.22 | BR44: 8601.08 | BS44: 19888.71 | BT44: 3912.93 | BU44: 4133.22 | BV44: 9777.99 | BW44: 17824.14 | BX44: 4150.4 | BY44: 2446.1 | BZ44: 9618.42 | CA44: 16214.92 | CB44: 5822.6 | CC44: 3007.7 | CD44: 8977.53 | CE44: 17807.83 | CF44: 6322.53 | CG44: 4656.17 | CH44: 9739.11 | CI44: 20717.81 | CL44: 5810.1709 | CM44: 8657.8896 | CN44: 13279.641 | CO44: 18059.668 | CP44: 20643.301 | CQ44: 23969.027 | CR44: 23808.253 | CS44: 24611.212 | CT44: 25300.792 | DG44: 8 | DH44: 6 | DI44: 7 | DJ44: 10 | DK44: 5 | DL44: 8 | DQ44: 2243.08 | DR44: 2378.04 | DS44: 4287.18 | DT44: 1345.67 | DU44: 1946.87 | DV44: 5438.67 | EA44: 54.33 | EB44: 1013.78 | EC44: 680.06 | ED44: 509.74 | EE44: 1800.21 | EF44: 45.06 | EG44: 127.51
A45: 98933 | B45: RES | C45: =A45&B45 -> 98933RES | E45: 76 | F45: 77 | G45: 88 | H45: 85 | I45: 78 | J45: 71 | K45: 51 | L45: 50 | M45: 56 | O45: 12246.39 | P45: 3249.95 | Q45: 3097.29 | R45: 18593.63 | S45: 13925.15 | T45: 3103.72 | U45: 1998.17 | V45: 19027.04 | W45: 13556.14 | X45: 6335.58 | Y45: 2846.39 | Z45: 22738.11 | AA45: 10777.73 | AB45: 5924.31 | AC45: 5684.84 | AD45: 22386.88 | AE45: 9460.75 | AF45: 5850.67 | AG45: 8776.12 | AH45: 24087.54 | AI45: 5200.94 | AJ45: 5156.8 | AK45: 11593.66 | AL45: 21951.4 | AM45: 3660.93 | AN45: 2529.21 | AO45: 13770.81 | AP45: 19960.95 | AQ45: 4023.64 | AR45: 2318.93 | AS45: 15205.09 | AT45: 21547.66 | AU45: 5550.61 | AV45: 2666.85 | AW45: 16521.57 | AX45: 24739.03 | AZ45: 3334.56 | BA45: 1173.05 | BB45: 1768.22 | BC45: 6275.83 | BD45: 2778.98 | BE45: 749.05 | BF45: 323.87 | BG45: 3851.9 | BH45: 3065.47 | BI45: 1497.79 | BJ45: 263.73 | BK45: 4826.99 | BL45: 2043.41 | BM45: 1317.4 | BN45: 796.62 | BO45: 4157.43 | BP45: 1754.18 | BQ45: 1145.31 | BR45: 1529.12 | BS45: 4428.61 | BT45: 873.42 | BU45: 1012.45 | BV45: 2104.65 | BW45: 3990.52 | BX45: 731.98 | BY45: 647.31 | BZ45: 2306.77 | CA45: 3686.06 | CB45: 620.12 | CC45: 473.66 | CD45: 2757.69 | CE45: 3851.47 | CF45: 1028.48 | CG45: 503.56 | CH45: 3078.46 | CI45: 4610.5 | CL45: 1205.4687 | CM45: 1157.9438 | CN45: 1765.2908 | CO45: 2493.852 | CP45: 3149.1381 | CQ45: 3954.1914 | CR45: 4361.4529 | CS45: 5145.025 | CT45: 5568.6134 | DG45: 1 | DH45: 2 | DI45: 5 | DJ45: 1 | DQ45: 34.19 | DR45: 1385.06 | DS45: 3281.45 | DT45: 296.33 | EB45: 88.06 | EC45: 152.79
A46: 98935 | B46: RES | C46: =A46&B46 -> 98935RES | E46: 156 | F46: 189 | G46: 229 | H46: 232 | I46: 304 | J46: 215 | K46: 190 | L46: 180 | M46: 170 | O46: 8444.06 | P46: 18310.15 | Q46: 8667.24 | R46: 35421.45 | S46: 33708.55 | T46: 9734.06 | U46: 6787.23 | V46: 50229.84 | W46: 41315.9 | X46: 15953.73 | Y46: 9005.35 | Z46: 66274.98 | AA46: 35757.98 | AB46: 25071.44 | AC46: 17161.64 | AD46: 77991.06 | AE46: 48841.27 | AF46: 22491.9 | AG46: 28734.87 | AH46: 100068.04 | AI46: 18100.7 | AJ46: 18309 | AK46: 36491.54 | AL46: 72901.24 | AM46: 15209.76 | AN46: 2723.68 | AO46: 50545.81 | AP46: 68479.25 | AQ46: 4198.7 | AR46: 21141.87 | AS46: 42852.56 | AT46: 68193.13 | AU46: 17222.36 | AV46: 2865.48 | AW46: 50175.95 | AX46: 70263.79 | AZ46: 766.08 | BA46: 3698.73 | BB46: 1753.15 | BC46: 6217.96 | BD46: 4964.58 | BE46: 1423.32 | BF46: 1553.66 | BG46: 7941.56 | BH46: 5577.07 | BI46: 2466.31 | BJ46: 645.25 | BK46: 8688.63 | BL46: 4345.66 | BM46: 4174.39 | BN46: 2200.45 | BO46: 10720.5 | BP46: 6750.87 | BQ46: 3042.97 | BR46: 3916.88 | BS46: 13710.72 | BT46: 2452.98 | BU46: 2158.29 | BV46: 5168.17 | BW46: 9779.44 | BX46: 1984.15 | BZ46: 7752.7 | CA46: 9736.85 | CB46: 95.81 | CC46: 4011.38 | CD46: 7199.16 | CE46: 11306.35 | CF46: 2801.5 | CH46: 8693.11 | CI46: 11494.61 | CL46: 3240.0272 | CM46: 3449.5333 | CN46: 5163.5071 | CO46: 8237.7284 | CP46: 11023.327 | CQ46: 12657.751 | CR46: 15571.252 | CS46: 15409.286 | CT46: 16554.554 | DG46: 3 | DH46: 7 | DI46: 6 | DJ46: 4 | DK46: 3 | DL46: 1 | DQ46: 1307.37 | DR46: 3262.51 | DS46: 3279.8 | DT46: 2134.56 | DU46: 1215.43 | DV46: 558.33 | EA46: 56.58 | EB46: 177.03 | ED46: 1729.27
A47: 98936 | B47: RES | C47: =A47&B47 -> 98936RES | E47: 273 | F47: 332 | G47: 426 | H47: 409 | I47: 399 | J47: 384 | K47: 324 | L47: 316 | M47: 376 | O47: 36462.71 | P47: 524.41 | Q47: 19595.47 | R47: 56582.59 | S47: 45403.91 | T47: 15427.35 | U47: 11935.79 | V47: 72767.05 | W47: 61719.5 | X47: 22626.79 | Y47: 16625.76 | Z47: 100972.05 | AA47: 50783.54 | AB47: 32524.1 | AC47: 28034.73 | AD47: 111342.37 | AE47: 45390.89 | AF47: 29473.96 | AG47: 46058.95 | AH47: 120923.8 | AI47: 33213.55 | AJ47: 26830.98 | AK47: 56697.3 | AL47: 116741.83 | AM47: 23823.08 | AN47: 18540.84 | AO47: 66354.91 | AP47: 108718.83 | AQ47: 25165.56 | AR47: 14841.58 | AS47: 70905.61 | AT47: 110912.75 | AU47: 41859.68 | AV47: 16306.09 | AW47: 77731.59 | AX47: 135897.36 | AZ47: 1287.64 | BB47: 1422.08 | BC47: 2709.72 | BD47: 1375.03 | BE47: 835.84 | BF47: 1178.63 | BG47: 3389.5 | BH47: 989.24 | BI47: 760.14 | BJ47: 1067.55 | BK47: 2816.93 | BL47: 1087.16 | BM47: 545.9 | BN47: 1401.94 | BO47: 3035 | BP47: 873.76 | BQ47: 859.88 | BR47: 1678.99 | BS47: 3412.63 | BT47: 685.67 | BU47: 465.73 | BV47: 1833.77 | BW47: 2985.17 | BX47: 718.03 | BY47: 322.5 | BZ47: 1988.65 | CA47: 3029.18 | CB47: 423.65 | CC47: 242.01 | CD47: 2050.37 | CE47: 2716.03 | CF47: 1117.67 | CG47: 299.95 | CH47: 2092.38 | CI47: 3510 | CL47: 5580.4465 | CM47: 5505.9717 | CN47: 8438.5575 | CO47: 12485.929 | CP47: 16330.674 | CQ47: 19687.954 | CR47: 21681.595 | CS47: 24479.091 | CT47: 26839.822 | DG47: 10 | DH47: 5 | DI47: 5 | DJ47: 13 | DK47: 3 | DL47: 2 | DQ47: 2038.11 | DR47: 3363.69 | DS47: 3411.85 | DT47: 7320.79 | DU47: 237.61 | DV47: 1264.86 | EA47: 387.96 | EB47: 502.58 | EC47: 1178.24 | ED47: 910.4 | EF47: 124.53 | EG47: 227.93
A48: 98937 | B48: RES | C48: =A48&B48 -> 98937RES | E48: 323 | F48: 360 | G48: 396 | H48: 414 | I48: 384 | J48: 367 | K48: 308 | L48: 298 | M48: 284 | O48: 51192.34 | P48: 7777.45 | Q48: 4235.06 | R48: 63204.85 | S48: 65112.42 | T48: 15486.73 | U48: 6276.14 | V48: 86875.29 | W48: 64581.85 | X48: 26255 | Y48: 10535.21 | Z48: 101372.06 | AA48: 55568.94 | AB48: 30024.32 | AC48: 20192.43 | AD48: 105785.69 | AE48: 49586.37 | AF48: 28742.89 | AG48: 32495.35 | AH48: 110824.61 | AI48: 31454.77 | AJ48: 28738.25 | AK48: 41048 | AL48: 101241.02 | AM48: 23749.55 | AN48: 16051.65 | AO48: 45968.76 | AP48: 85769.96 | AQ48: 24931.33 | AR48: 12451.27 | AS48: 44874.33 | AT48: 82256.93 | AU48: 28124.16 | AV48: 13870.76 | AW48: 41308.16 | AX48: 83303.08 | AZ48: 3225.79 | BA48: 889.45 | BB48: 213.33 | BC48: 4328.57 | BD48: 3103.1 | BE48: 1720.35 | BF48: 497.99 | BG48: 5321.44 | BH48: 2011.1 | BI48: 1604.98 | BJ48: 1099.85 | BK48: 4715.93 | BL48: 1517.21 | BM48: 1266.72 | BN48: 1743.7 | BO48: 4527.63 | BP48: 1478.27 | BQ48: 1128.22 | BR48: 2599.11 | BS48: 5205.6 | BT48: 1149.45 | BU48: 1099.04 | BV48: 3471.35 | BW48: 5719.84 | BX48: 804.49 | BY48: 711.17 | BZ48: 3064.07 | CA48: 4579.73 | CB48: 814.49 | CC48: 590.14 | CD48: 3492.07 | CE48: 4896.7 | CF48: 888.82 | CG48: 441.75 | CH48: 2021.04 | CI48: 3351.61 | CL48: 2652.7887 | CM48: 4740.9025 | CN48: 7259.464 | CO48: 10222.942 | CP48: 12508.427 | CQ48: 15192.903 | CR48: 15482.893 | CS48: 15978.187 | CT48: 14768.223 | DG48: 4 | DH48: 5 | DI48: 10 | DJ48: 8 | DK48: 3 | DL48: 3 | DQ48: 285.64 | DR48: 1559.35 | DS48: 3964.68 | DT48: 3868.2 | DU48: 914.06 | DV48: 1775.52 | EA48: 104.54 | EC48: 83.99 | ED48: 280.77 | EE48: 124.18 | EF48: 442.89 | EG48: 487.86
A49: 98938 | B49: RES | C49: =A49&B49 -> 98938RES | E49: 176 | F49: 194 | G49: 186 | H49: 178 | I49: 172 | J49: 171 | K49: 158 | L49: 152 | M49: 168 | O49: 39686.2 | P49: 7941.4 | Q49: 5329.72 | R49: 52957.32 | S49: 41787.73 | T49: 12759.09 | U49: 3567.73 | V49: 58114.55 | W49: 33990.06 | X49: 20012.4 | Y49: 7557.05 | Z49: 61559.51 | AA49: 30575.56 | AB49: 19872.68 | AC49: 16635.78 | AD49: 67084.02 | AE49: 23128.54 | AF49: 19994.95 | AG49: 25208.47 | AH49: 68331.96 | AI49: 15244.9 | AJ49: 15437.92 | AK49: 33079.18 | AL49: 63762 | AM49: 14124.33 | AN49: 9572.88 | AO49: 34515.73 | AP49: 58212.94 | AQ49: 17516.92 | AR49: 8656.33 | AS49: 35718.18 | AT49: 61891.43 | AU49: 21414.77 | AV49: 10823.91 | AW49: 35407.74 | AX49: 67646.42 | AZ49: 5193.35 | BA49: 1350.92 | BB49: 414.35 | BC49: 6958.62 | BD49: 3319.3 | BE49: 1988.63 | BF49: 322.34 | BG49: 5630.27 | BH49: 3033.76 | BI49: 2091 | BJ49: 600.95 | BK49: 5725.71 | BL49: 2299.66 | BM49: 2186.9 | BN49: 2176.76 | BO49: 6663.32 | BP49: 2115.08 | BQ49: 1796 | BR49: 3619.56 | BS49: 7530.64 | BT49: 1442.77 | BU49: 1494.06 | BV49: 4316.38 | BW49: 7253.21 | BX49: 1316.46 | BY49: 936.73 | BZ49: 3032.37 | CA49: 5285.56 | CB49: 1172.5 | CC49: 790.35 | CD49: 3128.17 | CE49: 5091.02 | CF49: 1958.95 | CG49: 1030.98 | CH49: 3505.67 | CI49: 6495.6 | CL49: 2646.0736 | CM49: 3147.0109 | CN49: 4909.8891 | CO49: 7472.3054 | CP49: 9126.2968 | CQ49: 11350.264 | CR49: 11325.816 | CS49: 12557.129 | CT49: 12519.687 | DH49: 5 | DI49: 3 | DJ49: 8 | DL49: 1 | DR49: 1733.54 | DS49: 1209.95 | DT49: 8710.42 | DV49: 1260.28 | EB49: 50 | EC49: 363.01 | ED49: 44.62
A50: 98939 | B50: RES | C50: =A50&B50 -> 98939RES | E50: 21 | F50: 23 | G50: 26 | H50: 25 | I50: 23 | J50: 23 | K50: 20 | L50: 19 | M50: 20 | O50: 3242.24 | P50: 766.63 | Q50: 960.16 | R50: 4969.03 | S50: 3601.84 | T50: 1636.48 | U50: 1023.45 | V50: 6261.77 | W50: 4087.23 | X50: 1837.31 | Y50: 1787.49 | Z50: 7712.03 | AA50: 2906.01 | AB50: 3006 | AC50: 3264.39 | AD50: 9176.4 | AE50: 2987.71 | AF50: 2038.36 | AG50: 5777.52 | AH50: 10803.59 | AI50: 1842.29 | AJ50: 2176.94 | AK50: 6419.69 | AL50: 10438.92 | AM50: 1481.4 | AN50: 1306.99 | AO50: 7908.63 | AP50: 10697.02 | AQ50: 1594.25 | AR50: 965.61 | AS50: 7559.96 | AT50: 10119.82 | AU50: 2163.61 | AV50: 1365.33 | AW50: 8230.15 | AX50: 11759.09 | AZ50: 260 | BA50: 82.81 | BC50: 342.81 | BD50: 260.93 | BE50: 1.74 | BG50: 262.67 | BH50: 651.94 | BI50: 62.67 | BK50: 714.61 | BL50: 434.99 | BM50: 651.94 | BN50: 62.67 | BO50: 1149.6 | BP50: 452.24 | BQ50: 220.1 | BR50: 485.29 | BS50: 1157.63 | BT50: 298.33 | BU50: 452.24 | BV50: 399.61 | BW50: 1150.18 | BX50: 106.92 | BY50: 116.75 | BZ50: 604.06 | CA50: 827.73 | CB50: 134.72 | CC50: 106.92 | CD50: 720.81 | CE50: 962.45 | CF50: 161.31 | CG50: 134.72 | CH50: 827.73 | CI50: 1123.76 | CL50: 347.63064 | CM50: 487.17796 | CN50: 769.92901 | CO50: 1280.8957 | CP50: 1869.7853 | CQ50: 2106.7118 | CR50: 2474.852 | CS50: 2532.4223 | CT50: 2762.1433 | DG50: 2 | DI50: 2 | DJ50: 1 | DQ50: 122.07 | DS50: 195.26 | DT50: 2230.98 | EA50: 73.54
