Workbook

Sheet 1. General 2023_Q3
A1: Count of aggreements by ZIP and CLASS.
A2: WA_TERM_COVID_COUNTS
A3: General 2023
A4: 45108 | D4: 45139 | G4: 45170 | K4: Retail Sales (kWh) | L4: July | M4: August | N4: September | O4: 45108 | P4: 45139 | Q4: 45170 | R4: July | S4: August | T4: September | U4: October | V4: November | W4: December | X4: Totals Q3
A5: Zip | B5: Class | C5: Count | D5: Zip | E5: Class | F5: Count | G5: Zip | H5: Class | I5: Count | K5: Residential | L5: 149454803 | M5: 144341255 | N5: 106642496 | O5: 127826646 | P5: 133081832 | Q5: 111734624 | X5: =SUM(O5:Q5) -> 372643102
A6: 98901 | B6: COM | C6: 2140 | D6: 98901 | E6: COM | F6: 2151 | G6: 98901 | H6: COM | I6: 2156 | K6: Commercial | L6: 140404042 | M6: 148198213 | N6: 131511808 | O6: 128676067 | P6: 138229616 | Q6: 135834307 | X6: =SUM(O6:Q6) -> 402739990
A7: 98902 | B7: COM | C7: 2571 | D7: 98902 | E7: COM | F7: 2574 | G7: 98902 | H7: COM | I7: 2570 | K7: Industrial | L7: 72533895 | M7: 71622459 | N7: 72818621 | O7: 33667523 | P7: 23039927 | Q7: 30185750 | X7: =SUM(O7:Q7) -> 86893200
A8: 98903 | B8: COM | C8: 1649 | D8: 98903 | E8: COM | F8: 1646 | G8: 98903 | H8: COM | I8: 1645 | K8: Irrigation | L8: 36860793 | M8: 39164393 | N8: 25760901 | O8: 32157540 | P8: 35430267 | Q8: 29459076 | X8: =SUM(O8:Q8) -> 97046883
A9: 98904 | B9: COM | C9: 2 | D9: 98904 | E9: COM | F9: 2 | G9: 98904 | H9: COM | I9: 2 | K9: Totals | L9: =SUM(L5:L8) -> 399253533 | M9: =SUM(M5:M8) -> 403326320 | N9: =SUM(N5:N8) -> 336733826 | O9: =SUM(O5:O8) -> 322327776 | P9: =SUM(P5:P8) -> 329781642 | Q9: =SUM(Q5:Q8) -> 307213757 | R9: =SUM(R5:R8) -> 0 | S9: =SUM(S5:S8) -> 0 | ... X9: =SUM(X5:X8) -> 959323175
A10: 98907 | B10: COM | C10: 2 | D10: 98907 | E10: COM | F10: 2 | G10: 98907 | H10: COM | I10: 2
A11: 98908 | B11: COM | C11: 1571 | D11: 98908 | E11: COM | F11: 1581 | G11: 98908 | H11: COM | I11: 1583
A12: 98920 | B12: COM | C12: 3 | D12: 98920 | E12: COM | F12: 3 | G12: 98920 | H12: COM | I12: 3
A13: 98921 | B13: COM | C13: 26 | D13: 98921 | E13: COM | F13: 26 | G13: 98921 | H13: COM | I13: 26
A14: 98923 | B14: COM | C14: 107 | D14: 98923 | E14: COM | F14: 107 | G14: 98923 | H14: COM | I14: 108
A15: 98930 | B15: COM | C15: 637 | D15: 98930 | E15: COM | F15: 640 | G15: 98930 | H15: COM | I15: 649
A16: 98932 | B16: COM | C16: 231 | D16: 98932 | E16: COM | F16: 231 | G16: 98932 | H16: COM | I16: 230
A17: 98933 | B17: COM | C17: 73 | D17: 98933 | E17: COM | F17: 71 | G17: 98933 | H17: COM | I17: 71
A18: 98935 | B18: COM | C18: 137 | D18: 98935 | E18: COM | F18: 137 | G18: 98935 | H18: COM | I18: 137
A19: 98936 | B19: COM | C19: 346 | D19: 98936 | E19: COM | F19: 345 | G19: 98936 | H19: COM | I19: 344
A20: 98937 | B20: COM | C20: 398 | D20: 98937 | E20: COM | F20: 399 | G20: 98937 | H20: COM | I20: 395
A21: 98938 | B21: COM | C21: 153 | D21: 98938 | E21: COM | F21: 154 | G21: 98938 | H21: COM | I21: 153
... A40: 99363 | B40: COM | C40: 73 | D40: 99363 | E40: COM | F40: 73 | G40: 99363 | H40: COM | I40: 73
B41: COM | C41: 4 | E41: COM | F41: 4 | H41: COM | I41: 4
A42: 98901 | B42: IND | C42: 48 | D42: 98901 | E42: IND | F42: 48 | G42: 98901 | H42: IND | I42: 48
A43: 98902 | B43: IND | C43: 85 | D43: 98902 | E43: IND | F43: 85 | G43: 98902 | H43: IND | I43: 85
A44: 98903 | B44: IND | C44: 64 | D44: 98903 | E44: IND | F44: 64 | G44: 98903 | H44: IND | I44: 64
A45: 98908 | B45: IND | C45: 17 | D45: 98908 | E45: IND | F45: 17 | G45: 98908 | H45: IND | I45: 17
A46: 98921 | B46: IND | C46: 1 | D46: 98921 | E46: IND | F46: 1 | G46: 98921 | H46: IND | I46: 1
A47: 98923 | B47: IND | C47: 4 | D47: 98923 | E47: IND | F47: 4 | G47: 98923 | H47: IND | I47: 4
A48: 98930 | B48: IND | C48: 26 | D48: 98930 | E48: IND | F48: 26 | G48: 98930 | H48: IND | I48: 26
A49: 98932 | B49: IND | C49: 12 | D49: 98932 | E49: IND | F49: 12 | G49: 98932 | H49: IND | I49: 12
A50: 98933 | B50: IND | C50: 1 | D50: 98933 | E50: IND | F50: 1 | G50: 98933 | H50: IND | I50: 1
A51: 98935 | B51: IND | C51: 3 | D51: 98935 | E51: IND | F51: 3 | G51: 98935 | H51: IND | I51: 3
A52: 98936 | B52: IND | C52: 18 | D52: 98936 | E52: IND | F52: 18 | G52: 98936 | H52: IND | I52: 18
A53: 98937 | B53: IND | C53: 11 | D53: 98937 | E53: IND | F53: 11 | G53: 98937 | H53: IND | I53: 11
... A143: 99363 | B143: RES | C143: 72 | D143: 99363 | E143: RES | F143: 74 | G143: 99363 | H143: RES | I143: 74

Sheet 2. Disconnections 2023_Q3
A1: General 2023 | D1: Item a) Number of Disconnections by Customer Class per Month | H1: Item b) Avg. Duration of Disconnection by Customer Class (in Hours for recon 10 days or less) | R1: Item c) Number of Customers by Customer Class Receiving Disconnection Notices | W1: Item d) Number of Customers by Customer Class Who Absent the Disconnection Moratorium Would Have Been Disconnected
A2: Zip Code | B2: Customer Class | D2: 45108 | E2: 45139 | F2: 45170 | H2: ZIP | I2: REV | J2: 45108 | K2: ZIP | L2: REV | M2: 45139 | N2: ZIP | O2: REV | P2: 45170 | R2: Category | S2: 45108 | T2: 45139 | U2: 45170 | W2: Category | X2: 45108 | Y2: 45139 | Z2: 45170
A3: 98901 | B3: COM | E3: 2 | F3: 3 | H3: 99324 | I3: RES | J3: 0.60019841 | K3: 98901 | L3: RES | M3: 0.70300926 | N3: 98901 | O3: RES | P3: 2.85625 | R3: FFN | S3: 6363 | T3: 6695 | U3: 6599
A4: 98901 | B4: RES | E4: 20 | F4: 26 | H4: 99328 | I4: RES | J4: 1.0013889 | K4: 98902 | L4: COM | M4: 4.9416667 | N4: 98902 | O4: RES | P4: 0.031944444 | R4: FNL | S4: 9767 | T4: 10303 | U4: 10076
A5: 98902 | B5: COM | E5: 1 | H5: 99362 | I5: RES | J5: 0.57282197 | K5: 98936 | L5: RES | M5: 1.0166667 | N5: 98903 | O5: COM | P5: 1.0409722 | R5: PDN | S5: 11304 | T5: 13006 | U5: 12145
A6: 98902 | B6: RES | D6: 2 | E6: 3 | F6: 6 | K6: 98942 | L6: COM | M6: 0.85972222 | N6: 98932 | O6: RES | P6: 0.1375
A7: 98903 | B7: COM | D7: 1 | F7: 1 | K7: 98951 | L7: RES | M7: 1.2358796 | N7: 98933 | O7: RES | P7: 0.98541667
A8: 98903 | B8: RES | D8: 1 | E8: 1 | F8: 1 | K8: 99324 | L8: RES | M8: 0.80185185 | N8: 98937 | O8: COM | P8: 0.26527778
A9: 98908 | B9: RES | D9: 1 | F9: 13 | K9: 99347 | L9: RES | M9: 1.9104167 | N9: 98937 | O9: RES | P9: 0.67847222
A10: 98932 | B10: RES | F10: 1 | K10: 99362 | L10: RES | M10: 0.84229167 | N10: 98938 | O10: IRG | P10: 0.98194444
A11: 98933 | B11: RES | F11: 1 | N11: 98938 | O11: RES | P11: 0.10138889
A12: 98936 | B12: RES | E12: 4 | N12: 98942 | O12: RES | P12: 1.0229167
A13: 98937 | B13: COM | F13: 2 | N13: 99323 | O13: RES | P13: 0.066319444
A14: 98937 | B14: RES | F14: 5 | N14: 99324 | O14: RES | P14: 0.14305556
A15: 98938 | B15: IRG | F15: 1 | N15: 99328 | O15: RES | P15: 0.05
A16: 98938 | B16: RES | F16: 2 | N16: 99361 | O16: RES | P16: 0.31388889
A17: 98942 | B17: COM | E17: 1 | N17: 99362 | O17: RES | P17: 1.1102705
A18: 98942 | B18: IRG | E18: 4
A19: 98942 | B19: RES | E19: 5 | F19: 1
A20: 98944 | B20: RES | F20: 10
A21: 98948 | B21: RES | E21: 1
A22: 98951 | B22: COM | E22: 1
A23: 98951 | B23: IRG | E23: 1
A24: 98951 | B24: RES | E24: 14 | F24: 1
A25: 98952 | B25: RES | F25: 1
A26: 98953 | B26: RES | E26: 1 | F26: 1
A27: 99301 | B27: RES | F27: 1
A28: 99323 | B28: RES | D28: 2 | E28: 1 | F28: 2
A29: 99324 | B29: RES | D29: 15 | E29: 5 | F29: 3
A30: 99328 | B30: RES | D30: 5 | F30: 2
A31: 99329 | B31: RES | D31: 1
A32: 99347 | B32: RES | E32: 12
A33: 99348 | B33: RES | D33: 2
A34: 99360 | B34: RES | D34: 2 | F34: 1
A35: 99361 | B35: RES | D35: 6 | F35: 2
A36: 99362 | B36: COM | F36: 1
A37: 99362 | B37: RES | D37: 60 | E37: 42 | F37: 34
A38: 99363 | B38: RES | F38: 1
A39: TOTAL | D39: =SUMIF($B$3:$B$38,$B$4,D3:D38) -> 97 | E39: =SUMIF($B$3:$B$38,$B$4,E3:E38) -> 109 | F39: =SUMIF($B$3:$B$38,$B$4,F3:F38) -> 115

Sheet 3. Fees 2023_Q3
A1: General 2023 | D1: Item a) Number of Customers by Customer Class Assessed Late Payment Fees | H1: Item a) Aggregate amount of Charged Late Payment Fees | L1: Item a) Number of Customers by Customer Class Assessed Disconnection Fees | P1: Item a) Aggregate amount of Charged Disconnection Fees | T1: Item a) Number of Customers by Customer Class Assessed Reconnection Fees | X1: Item a) Aggregate amount of Charged Reconnection Fees
A2: Zip Code | B2: Customer Class | D2: 45017 | E2: 45047 | F2: 45078 | H2: 45017 | I2: 45047 | J2: 45078 | L2: 45017 | M2: 45047 | N2: 45078 | P2: 45017 | Q2: 45047 | R2: 45078 | T2: 45017 | U2: 45047 | V2: 45078 | X2: 45017 | Y2: 45047 | Z2: 45078
A3: None

Sheet 4. Payment Arrangements 2023_Q3
A1: General 2023 | D1: Item a) Number of Customers by Customer Class Taking Service at the Beginning of Each Month with Existing Long Term Payment Agreements | H1: Item b) Number of Customers By Customer Class Completing Long-term Payment Agreements | L1: Item c) Number of Customers by Customer Class Enrolling in New Long-term Payment Agreements | P1: Item d) Number of Customers By Customer Class Renegotiating Long-term Payment Agreements
A2: Zip Code | B2: Customer Class | D2: 45108 | E2: 45139 | F2: 45170 | H2: 45108 | I2: 45139 | J2: 45170 | L2: 45108 | M2: 45139 | N2: 45170 | P2: 45108 | Q2: 45139 | R2: 45170
A3: NA | B3: COM | D3: 164 | E3: 157 | F3: 150 | H3: 17 | I3: 20 | J3: 14 | L3: 40 | M3: 46 | N3: 36 | P3: 1 | Q3: 0 | R3: 0
A4: NA | B4: RES | D4: 5473 | E4: 5298 | F4: 5044 | H4: 175 | I4: 256 | J4: 147 | L4: 866 | M4: 1027 | N4: 778 | P4: 144 | Q4: 147 | R4: 67

Sheet 5. Medical Certificates 2023_Q3
A1: General 2023 | D1: Item a) Number of Customers Taking Service at the Beginning of Each Month Under Existing Medical Payment Arrangements | H1: Item b) Number of Customers Completing Medical Payment Arrangements Each Month | L1: Item c) Number of Customers Enrolling in New Medical Payment Arrangements Each Month | P1: Item d) Number of Customers Renegotiating Medical Payment Arrangements Each Month
A2: Zip Code | B2: Customer Class | D2: 45108 | E2: 45139 | F2: 45170 | H2: 45108 | I2: 45139 | J2: 45170 | L2: 45108 | M2: 45139 | N2: 45170 | P2: 44197 | Q2: 44228 | R2: 44256 | S2: 44287 | T2: 44317 | U2: 44348 | V2: 44378 | W2: 44409 | X2: 44440 | Y2: 45108 | Z2: 45139 | AA2: 45170
A3: NA | B3: RES | D3: 14 | E3: 13 | F3: 17 | H3: 0 | I3: 0 | J3: 0 | L3: 2 | M3: 9 | N3: 5 | P3: 0 | Q3: 0 | R3: 0 | S3: 0 | T3: 0 | U3: 0 | V3: 0 | W3: 0 | X3: 0 | Y3: 0 | Z3: 0 | AA3: 0

Sheet 6. Deposits 2023_Q3
A1: General 2023 | D1: Item a) Number of Customers by Customer Class with Required Deposits at the Beginning of Each Month | N1: Item b) Number of Customers by Customer Class Required to Submit New or Increased Deposits Each Month | AH1: Item c) Number of Customers by Customer Class Whose Deposits Were Reduced In Part or Foregone Each Month | AR1: Item d) Number of Customers by Customer Class whose Deposits were Returned in Full Each Month
D2: 45108 | G2: 45139 | J2: 45170 | N2: Zip Code | O2: Customer Class | P2: 44197 | Q2: 44228 | R2: 44256 | S2: Zip Code | T2: Customer Class | U2: 44287 | V2: 44317 | W2: 44348 | X2: 45108 | AA2: 45139 | AD2: 45170 | AH2: 44197 | AI2: 44228 | AJ2: 44256 | AK2: 44287 | AL2: 44317 | AM2: 44348 | AN2: 45108 | AO2: 45139 | AP2: 45170 | AR2: 45108 | AU2: 45139 | AX2: 45170
D3: ZIP | E3: CLASS | F3: Concat Agreement Number | G3: ZIP | H3: CLASS | I3: Concat Agreement Number | J3: ZIP | K3: CLASS | L3: Concat Agreement Number | N3: 98901 | O3: COM | P3: 4 | Q3: 1 | R3: 2 | S3: 98901 | T3: COM | U3: 1 | V3: 6 | X3: ZIP | Y3: CLASS | Z3: Concat Agreement Number | AA3: ZIP | AB3: CLASS | AC3: Concat Agreement Number | AD3: ZIP | AE3: CLASS | AF3: Concat Agreement Number | AR3: ZIP | AS3: CLASS | AT3: Concat Agreement Number | AU3: ZIP | AV3: CLASS | AW3: Concat Agreement Number | AX3: ZIP | AY3: CLASS | AZ3: Concat Agreement Number
D4: 98901 | E4: COM | F4: 8 | G4: 98901 | H4: COM | I4: 71 | J4: 98901 | K4: COM | L4: 64 | N4: 98901 | O4: RES | P4: 71 | Q4: 53 | R4: 58 | S4: 98901 | T4: RES | U4: 19 | V4: 17 | W4: 19 | X4: 98901 | Y4: COM | Z4: 5 | AA4: 98901 | AB4: COM | AC4: 1 | AD4: 98901 | AE4: COM | AF4: 4 | AR4: 98901 | AS4: COM | AT4: 2 | AU4: 98901 | AV4: COM | AW4: 8 | AX4: ZIP | AY4: CLASS | AZ4: Concat Agreement Number
D5: 98901 | E5: RES | F5: 44 | G5: 98901 | H5: RES | I5: 11 | J5: 98901 | K5: RES | L5: 4 | N5: 98902 | O5: COM | Q5: 6 | R5: 3 | S5: 98902 | T5: COM | U5: 4 | V5: 12 | W5: 5 | X5: 98901 | Y5: RES | Z5: 19 | AA5: 98902 | AB5: COM | AC5: 10 | AD5: 98902 | AE5: COM | AF5: 4 | AR5: 98901 | AS5: RES | AT5: 56 | AU5: 98902 | AV5: COM | AW5: 6 | AX5: 98901 | AY5: COM | AZ5: 3
D6: 98902 | E6: COM | F6: 8 | G6: 98902 | H6: COM | I6: 71 | J6: 98902 | K6: COM | L6: 73 | N6: 98902 | O6: RES | P6: 103 | Q6: 75 | R6: 32 | S6: 98902 | T6: RES | U6: 48 | V6: 22 | W6: 19 | X6: 98902 | Y6: COM | Z6: 4 | AA6: 98903 | AB6: COM | AC6: 2 | AD6: 98903 | AE6: COM | AF6: 8 | AR6: 98902 | AS6: COM | AT6: 5 | AU6: 98902 | AV6: RES | AW6: 13 | AX6: 98902 | AY6: COM | AZ6: 3
D7: 98902 | E7: RES | F7: 48 | G7: 98902 | H7: RES | I7: 15 | J7: 98902 | K7: RES | L7: 2 | N7: 98903 | O7: COM | P7: 6 | R7: 1 | S7: 98903 | T7: COM | U7: 2 | V7: 3 | W7: 3 | X7: 98902 | Y7: RES | Z7: 18 | AA7: 98908 | AB7: COM | AC7: 2 | AD7: 98908 | AE7: COM | AF7: 3 | AR7: 98902 | AS7: RES | AT7: 66 | AU7: 98903 | AV7: COM | AW7: 4 | AX7: 98903 | AY7: COM | AZ7: 4
D8: 98903 | E8: COM | F8: 3 | G8: 98903 | H8: COM | I8: 34 | J8: 98903 | K8: COM | L8: 32 | N8: 98903 | O8: RES | P8: 17 | Q8: 16 | R8: 22 | S8: 98903 | T8: RES | U8: 5 | V8: 1 | W8: 6 | X8: 98903 | Y8: COM | Z8: 1 | AA8: 98930 | AB8: COM | AC8: 1 | AD8: 98937 | AE8: COM | AF8: 1 | AR8: 98903 | AS8: RES | AT8: 20 | AU8: 98903 | AV8: RES | AW8: 5 | AX8: 98908 | AY8: RES | AZ8: 1
D9: 98903 | E9: RES | F9: 24 | G9: 98903 | H9: RES | I9: 9 | J9: 98903 | K9: RES | L9: 4 | N9: 98908 | O9: COM | P9: 4 | Q9: 1 | R9: 2 | S9: 98908 | T9: COM | V9: 4 | W9: 2 | X9: 98903 | Y9: RES | Z9: 4 | AA9: 98937 | AB9: COM | AC9: 1 | AD9: 98944 | AE9: COM | AF9: 11 | AR9: 98908 | AS9: COM | AT9: 2 | AU9: 98908 | AV9: COM | AW9: 2 | AX9: 98930 | AY9: COM | AZ9: 1
D10: 98908 | E10: COM | F10: 6 | G10: 98908 | H10: COM | I10: 30 | J10: 98908 | K10: COM | L10: 30 | N10: 98908 | O10: RES | P10: 37 | Q10: 59 | R10: 47 | S10: 98908 | T10: RES | U10: 31 | V10: 18 | W10: 14 | X10: 98908 | Y10: COM | Z10: 3 | AA10: 98944 | AB10: COM | AC10: 1 | AD10: 98948 | AE10: COM | AF10: 1 | AR10: 98908 | AS10: RES | AT10: 60 | AU10: 98908 | AV10: RES | AW10: 14 | AX10: 98936 | AY10: COM | AZ10: 1
D11: 98908 | E11: RES | F11: 50 | G11: 98908 | H11: RES | I11: 29 | J11: 98908 | K11: RES | L11: 15 | N11: 98921 | O11: RES | P11: 2 | Q11: 1 | S11: 98921 | T11: RES | U11: 2 | X11: 98908 | Y11: RES | Z11: 10 | AA11: 98948 | AB11: COM | AC11: 1 | AD11: 98951 | AE11: COM | AF11: 1 | AR11: 98923 | AS11: RES | AT11: 1 | AU11: 98921 | AV11: RES | AW11: 1 | AX11: 98937 | AY11: COM | AZ11: 2
D12: 98921 | E12: RES | F12: 2 | G12: 98921 | H12: RES | I12: 2 | J12: 98921 | K12: RES | L12: 1 | N12: 98923 | O12: RES | P12: 3 | Q12: 1 | S12: 98923 | T12: RES | U12: 1 | X12: 98932 | Y12: RES | Z12: 1 | AA12: 98951 | AB12: COM | AC12: 2 | AD12: 98953 | AE12: COM | AF12: 2 | AR12: 98930 | AS12: COM | AT12: 1 | AU12: 98923 | AV12: RES | AW12: 1 | AX12: 98938 | AY12: COM | AZ12: 1
D13: 98923 | E13: RES | F13: 1 | G13: 98923 | H13: COM | I13: 1 | J13: 98923 | K13: COM | L13: 1 | N13: 98930 | O13: COM | P13: 2 | Q13: 2 | R13: 1 | S13: 98930 | T13: COM | V13: 2 | X13: 98935 | Y13: COM | Z13: 1 | AA13: 98953 | AB13: COM | AC13: 1 | AD13: 99324 | AE13: COM | AF13: 1 | AR13: 98930 | AS13: RES | AT13: 23 | AU13: 98930 | AV13: RES | AW13: 5 | AX13: 98938 | AY13: RES | AZ13: 1
D14: 98930 | E14: COM | F14: 5 | G14: 98923 | H14: RES | I14: 1 | J14: 98930 | K14: COM | L14: 10 | N14: 98930 | O14: RES | P14: 11 | Q14: 23 | R14: 21 | S14: 98930 | T14: RES | U14: 3 | V14: 2 | W14: 1 | X14: 98937 | Y14: COM | Z14: 1 | AA14: 99328 | AB14: COM | AC14: 1 | AD14: 99328 | AE14: COM | AF14: 1 | AR14: 98932 | AS14: COM | AT14: 1 | AU14: 98932 | AV14: RES | AW14: 1 | AX14: 98944 | AY14: COM | AZ14: 3
D15: 98930 | E15: RES | F15: 25 | G15: 98930 | H15: COM | I15: 9 | J15: 98930 | K15: RES | L15: 2 | N15: 98932 | O15: RES | P15: 5 | Q15: 4 | R15: 6 | S15: 98932 | T15: RES | V15: 3 | X15: 98937 | Y15: RES | Z15: 2 | AA15: 99362 | AB15: COM | AC15: 6 | AD15: 99329 | AE15: COM | AF15: 1 | AR15: 98932 | AS15: RES | AT15: 4 | AU15: 98935 | AV15: COM | AW15: 1 | AX15: 98951 | AY15: COM | AZ15: 1
D16: 98932 | E16: COM | F16: 3 | G16: 98930 | H16: RES | I16: 7 | J16: 98932 | K16: COM | L16: 2 | N16: 98933 | O16: RES | Q16: 1 | S16: 98933 | T16: RES | X16: 98938 | Y16: COM | Z16: 2 | AD16: 99347 | AE16: COM | AF16: 1 | AR16: 98933 | AS16: RES | AT16: 2 | AU16: 98936 | AV16: RES | AW16: 2 | AX16: 98953 | AY16: COM | AZ16: 1
D17: 98932 | E17: RES | F17: 5 | G17: 98932 | H17: COM | I17: 2 | J17: 98933 | K17: COM | L17: 1 | N17: 98935 | O17: COM | Q17: 4 | S17: 98935 | T17: COM | X17: 98942 | Y17: COM | Z17: 1 | AD17: 99362 | AE17: COM | AF17: 2 | AR17: 98935 | AS17: RES | AT17: 4 | AU17: 98937 | AV17: COM | AW17: 1 | AX17: 99329 | AY17: COM | AZ17: 1
D18: 98933 | E18: COM | F18: 1 | G18: 98932 | H18: RES | I18: 1 | J18: 98933 | K18: RES | L18: 1 | N18: 98935 | O18: RES | P18: 6 | Q18: 9 | R18: 1 | S18: 98935 | T18: RES | U18: 2 | V18: 1 | X18: 98942 | Y18: RES | Z18: 3 | AR18: 98936 | AS18: COM | AT18: 3 | AU18: 98942 | AV18: COM | AW18: 5 | AX18: 99362 | AY18: COM | AZ18: 8
D19: 98933 | E19: RES | F19: 1 | G19: 98933 | H19: COM | I19: 1 | J19: 98935 | K19: COM | L19: 7 | N19: 98936 | O19: RES | P19: 2 | Q19: 6 | R19: 5 | S19: 98936 | T19: RES | X19: 98944 | Y19: COM | Z19: 2 | AR19: 98936 | AS19: RES | AT19: 8 | AU19: 98942 | AV19: RES | AW19: 6
D20: 98935 | E20: RES | F20: 4 | G20: 98933 | H20: RES | I20: 1 | J20: 98936 | K20: COM | L20: 13 | N20: 98937 | O20: RES | P20: 5 | Q20: 2 | R20: 2 | S20: 98937 | T20: COM | U20: 1 | W20: 2 | X20: 98944 | Y20: RES | Z20: 1 | AR20: 98937 | AS20: RES | AT20: 1 | AU20: 98944 | AV20: COM | AW20: 3
D21: 98936 | E21: COM | F21: 7 | G21: 98935 | H21: COM | I21: 8 | J21: 98937 | K21: COM | L21: 10 | N21: 98938 | O21: COM | P21: 1 | S21: 98937 | T21: RES | V21: 2 | X21: 98947 | Y21: RES | Z21: 1 | AR21: 98938 | AS21: COM | AT21: 1 | AU21: 98944 | AV21: RES | AW21: 7
D22: 98936 | E22: RES | F22: 9 | G22: 98936 | H22: COM | I22: 13 | J22: 98938 | K22: COM | L22: 1 | N22: 98938 | O22: RES | P22: 7 | Q22: 2 | R22: 1 | S22: 98938 | T22: COM | X22: 98948 | Y22: RES | Z22: 1 | AR22: 98938 | AS22: RES | AT22: 5 | AU22: 98947 | AV22: RES | AW22: 1
D23: 98937 | E23: RES | F23: 1 | G23: 98936 | H23: RES | I23: 2 | J23: 98938 | K23: RES | L23: 1 | N23: 98939 | O23: RES | P23: 1 | S23: 98938 | T23: RES | X23: 98951 | Y23: RES | Z23: 3 | AR23: 98939 | AS23: RES | AT23: 1 | AU23: 98948 | AV23: COM | AW23: 2
D24: 98938 | E24: RES | F24: 6 | G24: 98937 | H24: COM | I24: 10 | J24: 98942 | K24: COM | L24: 11 | N24: 98942 | O24: COM | P24: 2 | Q24: 2 | S24: 98939 | T24: RES | X24: 99324 | Y24: RES | Z24: 2 | AR24: 98942 | AS24: COM | AT24: 1 | AU24: 98948 | AV24: RES | AW24: 3
D25: 98939 | E25: RES | F25: 1 | G25: 98938 | H25: COM | I25: 1 | J25: 98942 | K25: RES | L25: 1 | N25: 98942 | O25: RES | P25: 14 | Q25: 25 | R25: 25 | S25: 98942 | T25: COM | W25: 2 | X25: 99328 | Y25: COM | Z25: 2 | AR25: 98942 | AS25: RES | AT25: 24 | AU25: 98951 | AV25: RES | AW25: 2
D26: 98942 | E26: COM | F26: 12 | G26: 98938 | H26: RES | I26: 1 | J26: 98944 | K26: COM | L26: 19 | N26: 98944 | O26: COM | P26: 4 | Q26: 1 | R26: 9 | S26: 98942 | T26: RES | U26: 7 | V26: 8 | W26: 6 | X26: 99328 | Y26: RES | Z26: 1 | AR26: 98944 | AS26: COM | AT26: 3 | AU26: 99324 | AV26: RES | AW26: 4
D27: 98942 | E27: RES | F27: 23 | G27: 98942 | H27: COM | I27: 15 | J27: 98944 | K27: RES | L27: 4 | N27: 98944 | O27: RES | P27: 36 | Q27: 21 | R27: 7 | S27: 98944 | T27: COM | U27: 2 | V27: 3 | W27: 1 | X27: 99347 | Y27: COM | Z27: 3 | AR27: 98947 | AS27: RES | AT27: 5 | AU27: 99347 | AV27: COM | AW27: 3
D28: 98944 | E28: COM | F28: 7 | G28: 98942 | H28: RES | I28: 7 | J28: 98947 | K28: COM | L28: 4 | N28: 98947 | O28: RES | P28: 3 | Q28: 5 | S28: 98944 | T28: RES | U28: 13 | V28: 7 | W28: 2 | X28: 99361 | Y28: RES | Z28: 2 | AR28: 98948 | AS28: COM | AT28: 1 | AU28: 99361 | AV28: RES | AW28: 1
D29: 98944 | E29: RES | F29: 30 | G29: 98944 | H29: COM | I29: 21 | J29: 98947 | K29: RES | L29: 1 | N29: 98948 | O29: RES | P29: 20 | Q29: 16 | R29: 20 | S29: 98947 | T29: RES | U29: 4 | V29: 2 | X29: 99362 | Y29: COM | Z29: 3 | AR29: 98948 | AS29: RES | AT29: 11 | AU29: 99362 | AV29: COM | AW29: 8
D30: 98947 | E30: RES | F30: 4 | G30: 98944 | H30: RES | I30: 11 | J30: 98948 | K30: COM | L30: 13 | N30: 98951 | O30: COM | R30: 1 | S30: 98948 | T30: COM | U30: 2 | V30: 5 | X30: 99362 | Y30: RES | Z30: 14 | AR30: 98951 | AS30: RES | AT30: 19 | AU30: 99362 | AV30: RES | AW30: 16
D31: 98948 | E31: COM | F31: 5 | G31: 98947 | H31: COM | I31: 4 | J31: 98948 | K31: RES | L31: 3 | N31: 98951 | O31: RES | P31: 18 | Q31: 24 | R31: 13 | S31: 98948 | T31: RES | U31: 4 | V31: 3 | W31: 1 | AR31: 98952 | AS31: RES | AT31: 3
D32: 98948 | E32: RES | F32: 16 | G32: 98947 | H32: RES | I32: 2 | J32: 98951 | K32: COM | L32: 36 | N32: 98952 | O32: RES | Q32: 1 | R32: 2 | S32: 98951 | T32: COM | U32: 1 | V32: 8 | W32: 6 | AR32: 98953 | AS32: COM | AT32: 1
D33: 98951 | E33: COM | F33: 11 | G33: 98948 | H33: COM | I33: 14 | J33: 98951 | K33: RES | L33: 2 | N33: 98953 | O33: COM | R33: 1 | S33: 98951 | T33: RES | U33: 9 | V33: 2 | AR33: 98953 | AS33: RES | AT33: 10
D34: 98951 | E34: RES | F34: 20 | G34: 98948 | H34: RES | I34: 6 | J34: 98952 | K34: COM | L34: 1 | N34: 98953 | O34: RES | P34: 7 | Q34: 6 | R34: 9 | S34: 98952 | T34: RES | V34: 2 | AR34: 99323 | AS34: RES | AT34: 3
D35: 98952 | E35: RES | F35: 2 | G35: 98951 | H35: COM | I35: 34 | J35: 98953 | K35: COM | L35: 13 | N35: 99323 | O35: RES | Q35: 2 | R35: 3 | S35: 98953 | T35: COM | U35: 2 | AR35: 99324 | AS35: RES | AT35: 5
D36: 98953 | E36: COM | F36: 1 | G36: 98951 | H36: RES | I36: 4 | J36: 98953 | K36: RES | L36: 3 | N36: 99324 | O36: RES | P36: 14 | Q36: 8 | R36: 10 | S36: 98953 | T36: RES | U36: 5 | V36: 3 | AR36: 99328 | AS36: COM | AT36: 3
D37: 98953 | E37: RES | F37: 9 | G37: 98952 | H37: COM | I37: 1 | J37: 99323 | K37: COM | L37: 2 | N37: 99328 | O37: COM | R37: 1 | S37: 99323 | T37: COM | U37: 1 | AR37: 99328 | AS37: RES | AT37: 10
D38: 99323 | E38: COM | F38: 2 | G38: 98953 | H38: COM | I38: 12 | J38: 99324 | K38: COM | L38: 1 | N38: 99328 | O38: RES | P38: 7 | Q38: 9 | R38: 4 | S38: 99323 | T38: RES | U38: 2 | AR38: 99347 | AS38: RES | AT38: 2
D39: 99323 | E39: RES | F39: 2 | G39: 98953 | H39: RES | I39: 3 | J39: 99328 | K39: COM | L39: 6 | N39: 99347 | O39: RES | P39: 2 | Q39: 4 | R39: 4 | S39: 99324 | T39: RES | U39: 8 | W39: 7 | AR39: 99361 | AS39: RES | AT39: 1
D40: 99324 | E40: RES | F40: 5 | G40: 99323 | H40: COM | I40: 2 | J40: 99347 | K40: COM | L40: 2 | N40: 99360 | O40: COM | R40: 1 | S40: 99328 | T40: COM | U40: 1 | V40: 2 | AR40: 99362 | AS40: COM | AT40: 4
D41: 99328 | E41: RES | F41: 3 | G41: 99324 | H41: COM | I41: 1 | J41: 99360 | K41: COM | L41: 5 | N41: 99360 | O41: RES | P41: 1 | Q41: 2 | S41: 99328 | T41: RES | U41: 1 | V41: 7 | AR41: 99362 | AS41: RES | AT41: 38
D42: 99347 | E42: RES | F42: 2 | G42: 99324 | H42: RES | I42: 4 | J42: 99361 | K42: COM | L42: 1 | N42: 99361 | O42: RES | Q42: 4 | R42: 1 | S42: 99347 | T42: COM | U42: 2
D43: 99360 | E43: COM | F43: 3 | G43: 99328 | H43: COM | I43: 5 | J43: 99362 | K43: COM | L43: 75 | N43: 99362 | O43: COM | P43: 4 | Q43: 2 | R43: 1 | S43: 99347 | T43: RES | V43: 2
D44: 99361 | E44: RES | F44: 1 | G44: 99347 | H44: COM | I44: 5 | J44: 99362 | K44: RES | L44: 2 | N44: 99362 | O44: RES | P44: 69 | Q44: 47 | R44: 44 | S44: 99360 | T44: COM
D45: 99362 | E45: COM | F45: 12 | G45: 99360 | H45: COM | I45: 5 | N45: 99363 | O45: RES | P45: 1 | S45: 99360 | T45: RES
D46: 99362 | E46: RES | F46: 24 | G46: 99361 | H46: COM | I46: 1 | S46: 99361 | T46: RES | U46: 3
G47: 99361 | H47: RES | I47: 1 | S47: 99362 | T47: COM | U47: 3 | V47: 2 | W47: 8
G48: 99362 | H48: COM | I48: 75 | S48: 99362 | T48: RES | U48: 21 | V48: 14 | W48: 29
G49: 99362 | H49: RES | I49: 18 | S49: 99363 | T49: RES

Sheet DEP_WKSHT
A1: Zip Code | B1: CLASS | C1: CountOfConcat Agreement Number | D1: MO | G1: Zip Code | H1: CLASS | I1: CountOfConcat Agreement Number | J1: YRMO | K1: Expr1 | Q1: Sum of CountOfConcat Agreement Number | S1: YRMO | X1: Zip Code | Y1: CLASS | Z1: CountOfConcat Agreement Number | AA1: SumOfAmount | AB1: YRMO | AD1: Sum of CountOfConcat Agreement Number | AF1: YRMO
A2: 98901 | B2: NDEP | C2: 78 | D2: 1 | E2: =VLOOKUP(A2,'6. Deposits 2023_Q3'!$A$3:$A$34,1,FALSE) -> #N/A | G2: 98901 | H2: NDEP | I2: 4 | J2: 202010 | K2: 0 | Q2: CLASS | R2: Zip Code | S2: 202010 | T2: 202011 | U2: 202012 | V2: 20209 | X2: 98901 | Y2: NDEP | Z2: 30 | AA2: 0 | AB2: 10 | AD2: CLASS | AE2: Zip Code | AF2: 10 | AG2: 11 | AH2: 12 | AI2: Grand Total
A3: 98902 | B3: NDEP | C3: 97 | D3: 1 | E3: =VLOOKUP(A3,'6. Deposits 2023_Q3'!$A$3:$A$34,1,FALSE) -> #N/A | G3: 98901 | H3: NDEP | I3: 9 | J3: 202011 | K3: 0 | Q3: NDEP | R3: 98901 | S3: 4 | T3: 9 | U3: 2 | V3: 6 | X3: 98901 | Y3: NDEP | Z3: 16 | AA3: 0 | AB3: 11 | AD3: NDEP | AE3: 98901 | AF3: 30 | AG3: 16 | AH3: 20 | AI3: 66
A4: 98903 | B4: NDEP | C4: 47 | D4: 1 | E4: =VLOOKUP(A4,'6. Deposits 2023_Q3'!$A$3:$A$34,1,FALSE) -> #N/A | G4: 98901 | H4: NDEP | I4: 2 | J4: 202012 | K4: 0 | Q4: NDEP | R4: 98902 | S4: 8 | T4: 2 | U4: 2 | V4: 5 | X4: 98901 | Y4: NDEP | Z4: 20 | AA4: 0 | AB4: 12 | AD4: NDEP | AE4: 98902 | AF4: 24 | AG4: 22 | AH4: 32 | AI4: 78
A5: 98908 | B5: NDEP | C5: 35 | D5: 1 | E5: =VLOOKUP(A5,'6. Deposits 2023_Q3'!$A$3:$A$34,1,FALSE) -> #N/A | G5: 98901 | H5: NDEP | I5: 6 | J5: 20209 | K5: 0 | Q5: NDEP | R5: 98903 | S5: 2 | T5: 2 | V5: 4 | X5: 98901 | Y5: RDEP | Z5: 344 | AA5: 0 | AB5: 10 | AD5: NDEP | AE5: 98903 | AF5: 12 | AG5: 6 | AH5: 8 | AI5: 26
A6: 98920 | B6: NDEP | C6: 2 | D6: 1 | E6: =VLOOKUP(A6,'6. Deposits 2023_Q3'!$A$3:$A$34,1,FALSE) -> #N/A | G6: 98901 | H6: RDEP | I6: 99 | J6: 202010 | K6: 0 | Q6: NDEP | R6: 98908 | T6: 5 | X6: 98901 | Y6: RDEP | Z6: 358 | AA6: 0 | AB6: 11 | AD6: NDEP | AE6: 98908 | AF6: 8 | AG6: 18 | AH6: 12 | AI6: 38
A7: 98921 | B7: NDEP | C7: 2 | D7: 1 | E7: =VLOOKUP(A7,'6. Deposits 2023_Q3'!$A$3:$A$34,1,FALSE) -> #N/A | G7: 98901 | H7: RDEP | I7: 70 | J7: 202011 | K7: 0 | Q7: NDEP | R7: 98930 | S7: 3 | X7: 98901 | Y7: RDEP | Z7: 398 | AA7: 0 | AB7: 12 | AD7: NDEP | AE7: 98920 | AH7: 2 | AI7: 2
A8: 98930 | B8: NDEP | C8: 24 | D8: 1 | E8: =VLOOKUP(A8,'6. Deposits 2023_Q3'!$A$3:$A$34,1,FALSE) -> #N/A | G8: 98901 | H8: RDEP | I8: 26 | J8: 202012 | K8: 0 | Q8: NDEP | R8: 98937 | T8: 3 | U8: 2 | X8: 98902 | Y8: NDEP | Z8: 24 | AA8: 0 | AB8: 10 | AD8: NDEP | AE8: 98930 | AF8: 8 | AG8: 8 | AH8: 4 | AI8: 20
A9: 98932 | B9: NDEP | C9: 7 | D9: 1 | E9: =VLOOKUP(A9,'6. Deposits 2023_Q3'!$A$3:$A$34,1,FALSE) -> #N/A | G9: 98901 | H9: RDEP | I9: 109 | J9: 20209 | K9: 0 | Q9: NDEP | R9: 98942 | S9: 2 | V9: 1 | X9: 98902 | Y9: NDEP | Z9: 22 | AA9: 0 | AB9: 11 | AD9: NDEP | AE9: 98932 | AF9: 2 | AI9: 2
A10: 98933 | B10: NDEP | C10: 3 | D10: 1 | E10: =VLOOKUP(A10,'6. Deposits 2023_Q3'!$A$3:$A$34,1,FALSE) -> #N/A | G10: 98902 | H10: NDEP | I10: 8 | J10: 202010 | K10: 0 | Q10: NDEP | R10: 98944 | S10: 17 | U10: 6 | V10: 2 | X10: 98902 | Y10: NDEP | Z10: 32 | AA10: 0 | AB10: 12 | AD10: NDEP | AE10: 98933 | AF10: 2 | AG10: 4 | AH10: 2 | AI10: 8
A11: 98935 | B11: NDEP | C11: 4 | D11: 1 | E11: =VLOOKUP(A11,'6. Deposits 2023_Q3'!$A$3:$A$34,1,FALSE) -> #N/A | G11: 98902 | H11: NDEP | I11: 2 | J11: 202011 | K11: 0 | Q11: NDEP | R11: 98948 | S11: 2 | X11: 98902 | Y11: RDEP | Z11: 502 | AA11: 0 | AB11: 10 | AD11: NDEP | AE11: 98935 | AF11: 4 | AI11: 4
A12: 98936 | B12: NDEP | C12: 21 | D12: 1 | E12: =VLOOKUP(A12,'6. Deposits 2023_Q3'!$A$3:$A$34,1,FALSE) -> #N/A | G12: 98902 | H12: NDEP | I12: 2 | J12: 202012 | K12: 0 | Q12: NDEP | R12: 98951 | S12: 2 | T12: 2 | U12: 2 | X12: 98902 | Y12: RDEP | Z12: 510 | AA12: 0 | AB12: 11 | AD12: NDEP | AE12: 98936 | AF12: 4 | AG12: 2 | AH12: 24 | AI12: 30
A13: 98937 | B13: NDEP | C13: 10 | D13: 1 | E13: =VLOOKUP(A13,'6. Deposits 2023_Q3'!$A$3:$A$34,1,FALSE) -> #N/A | G13: 98902 | H13: NDEP | I13: 5 | J13: 20209 | K13: 0 | Q13: NDEP | R13: 99324 | T13: 2 | X13: 98902 | Y13: RDEP | Z13: 784 | AA13: 0 | AB13: 12 | AD13: NDEP | AE13: 98937 | AG13: 6 | AH13: 2 | AI13: 8
A14: 98938 | B14: NDEP | C14: 1 | D14: 1 | E14: =VLOOKUP(A14,'6. Deposits 2023_Q3'!$A$3:$A$34,1,FALSE) -> #N/A | G14: 98902 | H14: RDEP | I14: 163 | J14: 202010 | K14: 0 | Q14: NDEP | R14: 99328 | V14: 1 | X14: 98903 | Y14: NDEP | Z14: 12 | AA14: 0 | AB14: 10 | AD14: NDEP | AE14: 98942 | AF14: 8 | AG14: 14 | AH14: 4 | AI14: 26
A15: 98942 | B15: NDEP | C15: 18 | D15: 1 | E15: =VLOOKUP(A15,'6. Deposits 2023_Q3'!$A$3:$A$34,1,FALSE) -> #N/A | G15: 98902 | H15: RDEP | I15: 98 | J15: 202011 | K15: 0 | Q15: NDEP | R15: 99347 | S15: 2 | T15: 2 | X15: 98903 | Y15: NDEP | Z15: 6 | AA15: 0 | AB15: 11 | AD15: NDEP | AE15: 98944 | AF15: 12 | AG15: 26 | AH15: 18 | AI15: 56
A16: 98944 | B16: NDEP | C16: 61 | D16: 1 | E16: =VLOOKUP(A16,'6. Deposits 2023_Q3'!$A$3:$A$34,1,FALSE) -> #N/A | G16: 98902 | H16: RDEP | I16: 53 | J16: 202012 | K16: 0 | Q16: NDEP | R16: 99360 | T16: 2 | X16: 98903 | Y16: NDEP | Z16: 8 | AA16: 0 | AB16: 12 | AD16: NDEP | AE16: 98948 | AF16: 6 | AG16: 2 | AH16: 10 | AI16: 18
A17: 98947 | B17: NDEP | C17: 1 | D17: 1 | E17: =VLOOKUP(A17,'6. Deposits 2023_Q3'!$A$3:$A$34,1,FALSE) -> #N/A | G17: 98902 | H17: RDEP | I17: 127 | J17: 20209 | K17: 0 | Q17: NDEP | R17: 99361 | S17: 2 | V17: 1 | X17: 98903 | Y17: RDEP | Z17: 130 | AA17: 0 | AB17: 10 | AD17: NDEP | AE17: 98951 | AF17: 2 | AG17: 4 | AH17: 16 | AI17: 22
A18: 98948 | B18: NDEP | C18: 29 | D18: 1 | E18: =VLOOKUP(A18,'6. Deposits 2023_Q3'!$A$3:$A$34,1,FALSE) -> #N/A | G18: 98903 | H18: NDEP | I18: 2 | J18: 202010 | K18: 0 | Q18: NDEP | R18: 99362 | S18: 4 | T18: 8 | U18: 3 | V18: 8 | X18: 98903 | Y18: RDEP | Z18: 84 | AA18: 0 | AB18: 11 | AD18: NDEP | AE18: 98952 | AH18: 4 | AI18: 4
A19: 98951 | B19: NDEP | C19: 36 | D19: 1 | E19: =VLOOKUP(A19,'6. Deposits 2023_Q3'!$A$3:$A$34,1,FALSE) -> #N/A | G19: 98903 | H19: NDEP | I19: 2 | J19: 202011 | K19: 0 | Q19: NDEP | R19: 99363 | S19: 1 | X19: 98903 | Y19: RDEP | Z19: 130 | AA19: 0 | AB19: 12 | AD19: NDEP | AE19: 98953 | AF19: 2 | AG19: 2 | AH19: 4 | AI19: 8
A20: 98952 | B20: NDEP | C20: 1 | D20: 1 | E20: =VLOOKUP(A20,'6. Deposits 2023_Q3'!$A$3:$A$34,1,FALSE) -> #N/A | G20: 98903 | H20: NDEP | I20: 4 | J20: 20209 | K20: 0 | Q20: RDEP | R20: 98901 | S20: 99 | T20: 70 | U20: 26 | V20: 109 | X20: 98908 | Y20: NDEP | Z20: 8 | AA20: 0 | AB20: 10 | AD20: NDEP | AE20: 99323 | AH20: 2 | AI20: 2
A21: 98953 | B21: NDEP | C21: 10 | D21: 1 | E21: =VLOOKUP(A21,'6. Deposits 2023_Q3'!$A$3:$A$34,1,FALSE) -> #N/A | G21: 98903 | H21: RDEP | I21: 27 | J21: 202010 | K21: 0 | Q21: RDEP | R21: 98902 | S21: 163 | T21: 98 | U21: 53 | V21: 127 | X21: 98908 | Y21: NDEP | Z21: 18 | AA21: 0 | AB21: 11 | AD21: NDEP | AE21: 99324 | AG21: 4 | AH21: 2 | AI21: 6
A22: 99323 | B22: NDEP | C22: 1 | D22: 1 | E22: =VLOOKUP(A22,'6. Deposits 2023_Q3'!$A$3:$A$34,1,FALSE) -> #N/A | G22: 98903 | H22: RDEP | I22: 5 | J22: 202011 | K22: 0 | Q22: RDEP | R22: 98903 | S22: 27 | T22: 5 | U22: 12 | V22: 26 | X22: 98908 | Y22: NDEP | Z22: 12 | AA22: 0 | AB22: 12 | AD22: NDEP | AE22: 99328 | AF22: 2 | AH22: 2 | AI22: 4
A23: 99324 | B23: NDEP | C23: 4 | D23: 1 | E23: =VLOOKUP(A23,'6. Deposits 2023_Q3'!$A$3:$A$34,1,FALSE) -> #N/A | G23: 98903 | H23: RDEP | I23: 12 | J23: 202012 | K23: 0 | Q23: RDEP | R23: 98908 | S23: 136 | T23: 107 | U23: 32 | V23: 123 | X23: 98908 | Y23: RDEP | Z23: 320 | AA23: 0 | AB23: 10 | AD23: NDEP | AE23: 99347 | AG23: 4 | AI23: 4
A24: 99328 | B24: NDEP | C24: 5 | D24: 1 | E24: =VLOOKUP(A24,'6. Deposits 2023_Q3'!$A$3:$A$34,1,FALSE) -> #N/A | G24: 98903 | H24: RDEP | I24: 26 | J24: 20209 | K24: 0 | Q24: RDEP | R24: 98921 | S24: 7 | T24: 4 | V24: 4 | X24: 98908 | Y24: RDEP | Z24: 450 | AA24: 0 | AB24: 11 | AD24: NDEP | AE24: 99360 | AG24: 4 | AH24: 2 | AI24: 6
A25: 99329 | B25: NDEP | C25: 1 | D25: 1 | E25: =VLOOKUP(A25,'6. Deposits 2023_Q3'!$A$3:$A$34,1,FALSE) -> #N/A | G25: 98908 | H25: NDEP | I25: 5 | J25: 202011 | K25: 0 | Q25: RDEP | R25: 98923 | S25: 3 | T25: 2 | U25: 1 | V25: 2 | X25: 98908 | Y25: RDEP | Z25: 350 | AA25: 0 | AB25: 12 | AD25: NDEP | AE25: 99361 | AH25: 6 | AI25: 6
A26: 99347 | B26: NDEP | C26: 3 | D26: 1 | E26: =VLOOKUP(A26,'6. Deposits 2023_Q3'!$A$3:$A$34,1,FALSE) -> #N/A | G26: 98908 | H26: RDEP | I26: 136 | J26: 202010 | K26: 0 | Q26: RDEP | R26: 98930 | S26: 29 | T26: 10 | U26: 18 | V26: 15 | X26: 98920 | Y26: NDEP | Z26: 2 | AA26: 0 | AB26: 12 | AD26: NDEP | AE26: 99362 | AF26: 18 | AG26: 20 | AH26: 16 | AI26: 54
A27: 99360 | B27: NDEP | C27: 3 | D27: 1 | E27: =VLOOKUP(A27,'6. Deposits 2023_Q3'!$A$3:$A$34,1,FALSE) -> #N/A | G27: 98908 | H27: RDEP | I27: 107 | J27: 202011 | K27: 0 | Q27: RDEP | R27: 98932 | S27: 7 | T27: 17 | U27: 8 | V27: 7 | X27: 98921 | Y27: RDEP | Z27: 6 | AA27: 0 | AB27: 10 | AD27: RDEP | AE27: 98901 | AF27: 344 | AG27: 358 | AH27: 398 | AI27: 1100
A28: 99361 | B28: NDEP | C28: 6 | D28: 1 | E28: =VLOOKUP(A28,'6. Deposits 2023_Q3'!$A$3:$A$34,1,FALSE) -> #N/A | G28: 98908 | H28: RDEP | I28: 32 | J28: 202012 | K28: 0 | Q28: RDEP | R28: 98933 | S28: 3 | T28: 3 | U28: 3 | V28: 1 | X28: 98921 | Y28: RDEP | Z28: 18 | AA28: 0 | AB28: 11 | AD28: RDEP | AE28: 98902 | AF28: 502 | AG28: 510 | AH28: 784 | AI28: 1796
A29: 99362 | B29: NDEP | C29: 62 | D29: 1 | E29: =VLOOKUP(A29,'6. Deposits 2023_Q3'!$A$3:$A$34,1,FALSE) -> #N/A | G29: 98908 | H29: RDEP | I29: 123 | J29: 20209 | K29: 0 | Q29: RDEP | R29: 98935 | S29: 5 | T29: 6 | U29: 2 | V29: 4 | X29: 98921 | Y29: RDEP | Z29: 14 | AA29: 0 | AB29: 12 | AD29: RDEP | AE29: 98903 | AF29: 130 | AG29: 84 | AH29: 130 | AI29: 344
A30: 99363 | B30: NDEP | C30: 1 | D30: 1 | E30: =VLOOKUP(A30,'6. Deposits 2023_Q3'!$A$3:$A$34,1,FALSE) -> #N/A | G30: 98921 | H30: RDEP | I30: 7 | J30: 202010 | K30: 0 | Q30: RDEP | R30: 98936 | S30: 6 | T30: 10 | U30: 6 | V30: 5 | X30: 98923 | Y30: RDEP | Z30: 4 | AA30: 0 | AB30: 10 | AD30: RDEP | AE30: 98908 | AF30: 320 | AG30: 450 | AH30: 350 | AI30: 1120
A31: 98901 | B31: RDEP | C31: 1427 | D31: 1 | E31: =VLOOKUP(A31,'6. Deposits 2023_Q3'!$A$35:$A$61,1,FALSE) -> #N/A | G31: 98921 | H31: RDEP | I31: 4 | J31: 202011 | K31: 0 | Q31: RDEP | R31: 98937 | S31: 9 | T31: 2 | U31: 3 | V31: 7 | X31: 98923 | Y31: RDEP | Z31: 4 | AA31: 0 | AB31: 11 | AD31: RDEP | AE31: 98921 | AF31: 6 | AG31: 18 | AH31: 14 | AI31: 38
A32: 98902 | B32: RDEP | C32: 1838 | D32: 1 | E32: =VLOOKUP(A32,'6. Deposits 2023_Q3'!$A$35:$A$61,1,FALSE) -> #N/A | G32: 98921 | H32: RDEP | I32: 4 | J32: 20209 | K32: 0 | Q32: RDEP | R32: 98938 | S32: 1 | U32: 4 | X32: 98923 | Y32: RDEP | Z32: 16 | AA32: 0 | AB32: 12 | AD32: RDEP | AE32: 98923 | AF32: 4 | AG32: 4 | AH32: 16 | AI32: 24
A33: 98903 | B33: RDEP | C33: 403 | D33: 1 | E33: =VLOOKUP(A33,'6. Deposits 2023_Q3'!$A$35:$A$61,1,FALSE) -> #N/A | G33: 98923 | H33: RDEP | I33: 3 | J33: 202010 | K33: 0 | Q33: RDEP | R33: 98939 | U33: 1 | X33: 98930 | Y33: NDEP | Z33: 8 | AA33: 0 | AB33: 10 | AD33: RDEP | AE33: 98930 | AF33: 90 | AG33: 74 | AH33: 120 | AI33: 284
A34: 98908 | B34: RDEP | C34: 1026 | D34: 1 | E34: =VLOOKUP(A34,'6. Deposits 2023_Q3'!$A$35:$A$61,1,FALSE) -> #N/A | G34: 98923 | H34: RDEP | I34: 2 | J34: 202011 | K34: 0 | Q34: RDEP | R34: 98942 | S34: 42 | T34: 27 | U34: 12 | V34: 36 | X34: 98930 | Y34: NDEP | Z34: 8 | AA34: 0 | AB34: 11 | AD34: RDEP | AE34: 98932 | AF34: 30 | AG34: 72 | AH34: 62 | AI34: 164
A35: 98921 | B35: RDEP | C35: 31 | D35: 1 | E35: =VLOOKUP(A35,'6. Deposits 2023_Q3'!$A$35:$A$61,1,FALSE) -> #N/A | G35: 98923 | H35: RDEP | I35: 1 | J35: 202012 | K35: 0 | Q35: RDEP | R35: 98944 | S35: 23 | T35: 30 | U35: 15 | V35: 31 | X35: 98930 | Y35: NDEP | Z35: 4 | AA35: 0 | AB35: 12 | AD35: RDEP | AE35: 98933 | AF35: 4 | AG35: 4 | AH35: 14 | AI35: 22
A36: 98923 | B36: RDEP | C36: 30 | D36: 1 | E36: =VLOOKUP(A36,'6. Deposits 2023_Q3'!$A$35:$A$61,1,FALSE) -> #N/A | G36: 98923 | H36: RDEP | I36: 2 | J36: 20209 | K36: 0 | Q36: RDEP | R36: 98947 | S36: 4 | T36: 2 | U36: 3 | V36: 1 | X36: 98930 | Y36: RDEP | Z36: 90 | AA36: 0 | AB36: 10 | AD36: RDEP | AE36: 98935 | AF36: 30 | AG36: 16 | AH36: 36 | AI36: 82
A37: 98930 | B37: RDEP | C37: 336 | D37: 1 | E37: =VLOOKUP(A37,'6. Deposits 2023_Q3'!$A$35:$A$61,1,FALSE) -> #N/A | G37: 98930 | H37: NDEP | I37: 3 | J37: 202010 | K37: 0 | Q37: RDEP | R37: 98948 | S37: 24 | T37: 4 | U37: 4 | V37: 10 | X37: 98930 | Y37: RDEP | Z37: 74 | AA37: 0 | AB37: 11 | AD37: RDEP | AE37: 98936 | AF37: 38 | AG37: 26 | AH37: 80 | AI37: 144
A38: 98932 | B38: RDEP | C38: 165 | D38: 1 | E38: =VLOOKUP(A38,'6. Deposits 2023_Q3'!$A$35:$A$61,1,FALSE) -> #N/A | G38: 98930 | H38: RDEP | I38: 29 | J38: 202010 | K38: 0 | Q38: RDEP | R38: 98951 | S38: 16 | T38: 12 | U38: 8 | V38: 10 | X38: 98930 | Y38: RDEP | Z38: 120 | AA38: 0 | AB38: 12 | AD38: RDEP | AE38: 98937 | AF38: 20 | AG38: 30 | AH38: 38 | AI38: 88
A39: 98933 | B39: RDEP | C39: 24 | D39: 1 | E39: =VLOOKUP(A39,'6. Deposits 2023_Q3'!$A$35:$A$61,1,FALSE) -> #N/A | G39: 98930 | H39: RDEP | I39: 10 | J39: 202011 | K39: 0 | Q39: RDEP | R39: 98952 | S39: 1 | U39: 1 | X39: 98932 | Y39: NDEP | Z39: 2 | AA39: 0 | AB39: 10 | AD39: RDEP | AE39: 98938 | AF39: 24 | AG39: 14 | AH39: 40 | AI39: 78
A40: 98935 | B40: RDEP | C40: 85 | D40: 1 | E40: =VLOOKUP(A40,'6. Deposits 2023_Q3'!$A$35:$A$61,1,FALSE) -> #N/A | G40: 98930 | H40: RDEP | I40: 18 | J40: 202012 | K40: 0 | Q40: RDEP | R40: 98953 | S40: 7 | T40: 9 | V40: 10 | X40: 98932 | Y40: RDEP | Z40: 30 | AA40: 0 | AB40: 10 | AD40: RDEP | AE40: 98939 | AF40: 4 | AG40: 4 | AH40: 2 | AI40: 10
A41: 98936 | B41: RDEP | C41: 130 | D41: 1 | E41: =VLOOKUP(A41,'6. Deposits 2023_Q3'!$A$35:$A$61,1,FALSE) -> #N/A | G41: 98930 | H41: RDEP | I41: 15 | J41: 20209 | K41: 0 | Q41: RDEP | R41: 99323 | U41: 2 | V41: 2 | X41: 98932 | Y41: RDEP | Z41: 72 | AA41: 0 | AB41: 11 | AD41: RDEP | AE41: 98942 | AF41: 114 | AG41: 190 | AH41: 106 | AI41: 410
A42: 98937 | B42: RDEP | C42: 85 | D42: 1 | E42: =VLOOKUP(A42,'6. Deposits 2023_Q3'!$A$35:$A$61,1,FALSE) -> #N/A | G42: 98932 | H42: RDEP | I42: 7 | J42: 202010 | K42: 0 | Q42: RDEP | R42: 99324 | S42: 29 | T42: 17 | U42: 4 | V42: 67 | X42: 98932 | Y42: RDEP | Z42: 62 | AA42: 0 | AB42: 12 | AD42: RDEP | AE42: 98944 | AF42: 100 | AG42: 182 | AH42: 230 | AI42: 512
A43: 98938 | B43: RDEP | C43: 51 | D43: 1 | E43: =VLOOKUP(A43,'6. Deposits 2023_Q3'!$A$35:$A$61,1,FALSE) -> #N/A | G43: 98932 | H43: RDEP | I43: 17 | J43: 202011 | K43: 0 | Q43: RDEP | R43: 99328 | S43: 11 | T43: 6 | U43: 7 | V43: 8 | X43: 98933 | Y43: NDEP | Z43: 2 | AA43: 0 | AB43: 10 | AD43: RDEP | AE43: 98947 | AF43: 22 | AG43: 26 | AH43: 28 | AI43: 76
A44: 98939 | B44: RDEP | C44: 8 | D44: 1 | E44: =VLOOKUP(A44,'6. Deposits 2023_Q3'!$A$35:$A$61,1,FALSE) -> #N/A | G44: 98932 | H44: RDEP | I44: 8 | J44: 202012 | K44: 0 | Q44: RDEP | R44: 99329 | U44: 1 | X44: 98933 | Y44: NDEP | Z44: 4 | AA44: 0 | AB44: 11 | AD44: RDEP | AE44: 98948 | AF44: 60 | AG44: 84 | AH44: 162 | AI44: 306
A45: 98942 | B45: RDEP | C45: 446 | D45: 1 | E45: =VLOOKUP(A45,'6. Deposits 2023_Q3'!$A$35:$A$61,1,FALSE) -> #N/A | G45: 98932 | H45: RDEP | I45: 7 | J45: 20209 | K45: 0 | Q45: RDEP | R45: 99347 | S45: 4 | V45: 6 | X45: 98933 | Y45: NDEP | Z45: 2 | AA45: 0 | AB45: 12 | AD45: RDEP | AE45: 98951 | AF45: 86 | AG45: 82 | AH45: 154 | AI45: 322
A46: 98944 | B46: RDEP | C46: 535 | D46: 1 | E46: =VLOOKUP(A46,'6. Deposits 2023_Q3'!$A$35:$A$61,1,FALSE) -> #N/A | G46: 98933 | H46: RDEP | I46: 3 | J46: 202010 | K46: 0 | Q46: RDEP | R46: 99348 | S46: 2 | V46: 1 | X46: 98933 | Y46: RDEP | Z46: 4 | AA46: 0 | AB46: 10 | AD46: RDEP | AE46: 98952 | AF46: 6 | AG46: 2 | AH46: 22 | AI46: 30
A47: 98947 | B47: RDEP | C47: 69 | D47: 1 | E47: =VLOOKUP(A47,'6. Deposits 2023_Q3'!$A$35:$A$61,1,FALSE) -> #N/A | G47: 98933 | H47: RDEP | I47: 3 | J47: 202011 | K47: 0 | Q47: RDEP | R47: 99360 | T47: 2 | X47: 98933 | Y47: RDEP | Z47: 4 | AA47: 0 | AB47: 11 | AD47: RDEP | AE47: 98953 | AF47: 62 | AG47: 58 | AH47: 62 | AI47: 182
A48: 98948 | B48: RDEP | C48: 308 | D48: 1 | E48: =VLOOKUP(A48,'6. Deposits 2023_Q3'!$A$35:$A$61,1,FALSE) -> #N/A | G48: 98933 | H48: RDEP | I48: 3 | J48: 202012 | K48: 0 | Q48: RDEP | R48: 99361 | S48: 3 | U48: 2 | V48: 1 | X48: 98933 | Y48: RDEP | Z48: 14 | AA48: 0 | AB48: 12 | AD48: RDEP | AE48: 99323 | AF48: 6 | AG48: 18 | AH48: 6 | AI48: 30
A49: 98951 | B49: RDEP | C49: 351 | D49: 1 | E49: =VLOOKUP(A49,'6. Deposits 2023_Q3'!$A$35:$A$61,1,FALSE) -> #N/A | G49: 98933 | H49: RDEP | I49: 1 | J49: 20209 | K49: 0 | Q49: RDEP | R49: 99362 | S49: 85 | T49: 56 | U49: 23 | V49: 112 | X49: 98935 | Y49: NDEP | Z49: 4 | AA49: 0 | AB49: 10 | AD49: RDEP | AE49: 99324 | AF49: 64 | AG49: 102 | AH49: 64 | AI49: 230
A50: 98952 | B50: RDEP | C50: 33 | D50: 1 | E50: =VLOOKUP(A50,'6. Deposits 2023_Q3'!$A$35:$A$61,1,FALSE) -> #N/A | G50: 98935 | H50: RDEP | I50: 5 | J50: 202010 | K50: 0 | Q50: Grand Total | S50: 795 | T50: 536 | U50: 268 | V50: 753 | X50: 98935 | Y50: RDEP | Z50: 30 | AA50: 0 | AB50: 10 | AD50: RDEP | AE50: 99328 | AF50: 20 | AG50: 36 | AH50: 34 | AI50: 90
A51: 98953 | B51: RDEP | C51: 127 | D51: 1 | E51: =VLOOKUP(A51,'6. Deposits 2023_Q3'!$A$35:$A$61,1,FALSE) -> #N/A | G51: 98935 | H51: RDEP | I51: 6 | J51: 202011 | K51: 0 | X51: 98935 | Y51: RDEP | Z51: 16 | AA51: 0 | AB51: 11 | AD51: RDEP | AE51: 99329 | AF51: 2 | AH51: 2 | AI51: 4
A52: 99323 | B52: RDEP | C52: 26 | D52: 1 | E52: =VLOOKUP(A52,'6. Deposits 2023_Q3'!$A$35:$A$61,1,FALSE) -> #N/A | G52: 98935 | H52: RDEP | I52: 2 | J52: 202012 | K52: 0 | X52: 98935 | Y52: RDEP | Z52: 36 | AA52: 0 | AB52: 12 | AD52: RDEP | AE52: 99347 | AF52: 6 | AG52: 10 | AH52: 6 | AI52: 22
A53: 99324 | B53: RDEP | C53: 336 | D53: 1 | E53: =VLOOKUP(A53,'6. Deposits 2023_Q3'!$A$35:$A$61,1,FALSE) -> #N/A | G53: 98935 | H53: RDEP | I53: 4 | J53: 20209 | K53: 0 | X53: 98936 | Y53: NDEP | Z53: 4 | AA53: 0 | AB53: 10 | AD53: RDEP | AE53: 99348 | AG53: 4 | AH53: 2 | AI53: 6
A54: 99328 | B54: RDEP | C54: 97 | D54: 1 | E54: =VLOOKUP(A54,'6. Deposits 2023_Q3'!$A$35:$A$61,1,FALSE) -> #N/A | G54: 98936 | H54: RDEP | I54: 6 | J54: 202010 | K54: 0 | X54: 98936 | Y54: NDEP | Z54: 2 | AA54: 0 | AB54: 11 | AD54: RDEP | AE54: 99360 | AF54: 2 | AG54: 2 | AH54: 6 | AI54: 10
A55: 99329 | B55: RDEP | C55: 2 | D55: 1 | E55: =VLOOKUP(A55,'6. Deposits 2023_Q3'!$A$35:$A$61,1,FALSE) -> #N/A | G55: 98936 | H55: RDEP | I55: 10 | J55: 202011 | K55: 0 | X55: 98936 | Y55: NDEP | Z55: 24 | AA55: 0 | AB55: 12 | AD55: RDEP | AE55: 99361 | AF55: 6 | AH55: 24 | AI55: 30
A56: 99347 | B56: RDEP | C56: 45 | D56: 1 | E56: =VLOOKUP(A56,'6. Deposits 2023_Q3'!$A$35:$A$61,1,FALSE) -> #N/A | G56: 98936 | H56: RDEP | I56: 6 | J56: 202012 | K56: 0 | X56: 98936 | Y56: RDEP | Z56: 38 | AA56: 0 | AB56: 10 | AD56: RDEP | AE56: 99362 | AF56: 394 | AG56: 308 | AH56: 342 | AI56: 1044
A57: 99348 | B57: RDEP | C57: 12 | D57: 1 | E57: =VLOOKUP(A57,'6. Deposits 2023_Q3'!$A$35:$A$61,1,FALSE) -> #N/A | G57: 98936 | H57: RDEP | I57: 5 | J57: 20209 | K57: 0 | X57: 98936 | Y57: RDEP | Z57: 26 | AA57: 0 | AB57: 11 | AD57: RDEP | AE57: 99363 | AF57: 4 | AH57: 2 | AI57: 6
A58: 99350 | B58: RDEP | C58: 3 | D58: 1 | E58: =VLOOKUP(A58,'6. Deposits 2023_Q3'!$A$35:$A$61,1,FALSE) -> #N/A | G58: 98937 | H58: NDEP | I58: 3 | J58: 202011 | K58: 0 | X58: 98936 | Y58: RDEP | Z58: 80 | AA58: 0 | AB58: 12 | AD58: Grand Total | AF58: 2644 | AG58: 2930 | AH58: 3528 | AI58: 9102
A59: 99360 | B59: RDEP | C59: 11 | D59: 1 | E59: =VLOOKUP(A59,'6. Deposits 2023_Q3'!$A$35:$A$61,1,FALSE) -> #N/A | G59: 98937 | H59: NDEP | I59: 2 | J59: 202012 | K59: 0 | X59: 98937 | Y59: NDEP | Z59: 6 | AA59: 0 | AB59: 11
A60: 99361 | B60: RDEP | C60: 31 | D60: 1 | E60: =VLOOKUP(A60,'6. Deposits 2023_Q3'!$A$35:$A$61,1,FALSE) -> #N/A | G60: 98937 | H60: RDEP | I60: 9 | J60: 202010 | K60: 0 | X60: 98937 | Y60: NDEP | Z60: 2 | AA60: 0 | AB60: 12
A61: 99362 | B61: RDEP | C61: 1179 | D61: 1 | E61: =VLOOKUP(A61,'6. Deposits 2023_Q3'!$A$35:$A$61,1,FALSE) -> #N/A | G61: 98937 | H61: RDEP | I61: 2 | J61: 202011 | K61: 0 | X61: 98937 | Y61: RDEP | Z61: 20 | AA61: 0 | AB61: 10
A62: 99363 | B62: RDEP | C62: 3 | D62: 1 | E62: =VLOOKUP(A62,'6. Deposits 2023_Q3'!$A$35:$A$61,1,FALSE) -> #N/A | G62: 98937 | H62: RDEP | I62: 3 | J62: 202012 | K62: 0 | X62: 98937 | Y62: RDEP | Z62: 30 | AA62: 0 | AB62: 11
G63: 98937 | H63: RDEP | I63: 7 | J63: 20209 | K63: 0 | X63: 98937 | Y63: RDEP | Z63: 38 | AA63: 0 | AB63: 12
G64: 98938 | H64: RDEP | I64: 1 | J64: 202010 | K64: 0 | X64: 98938 | Y64: RDEP | Z64: 24 | AA64: 0 | AB64: 10
G65: 98938 | H65: RDEP | I65: 4 | J65: 202012 | K65: 0 | X65: 98938 | Y65: RDEP | Z65: 14 | AA65: 0 | AB65: 11
G66: 98939 | H66: RDEP | I66: 1 | J66: 202012 | K66: 0 | X66: 98938 | Y66: RDEP | Z66: 40 | AA66: 0 | AB66: 12
G67: 98942 | H67: NDEP | I67: 2 | J67: 202010 | K67: 0 | X67: 98939 | Y67: RDEP | Z67: 4 | AA67: 0 | AB67: 10
G68: 98942 | H68: NDEP | I68: 1 | J68: 20209 | K68: 0 | X68: 98939 | Y68: RDEP | Z68: 4 | AA68: 0 | AB68: 11
G69: 98942 | H69: RDEP | I69: 42 | J69: 202010 | K69: 0 | X69: 98939 | Y69: RDEP | Z69: 2 | AA69: 0 | AB69: 12
G70: 98942 | H70: RDEP | I70: 27 | J70: 202011 | K70: 0 | X70: 98942 | Y70: NDEP | Z70: 8 | AA70: 0 | AB70: 10
G71: 98942 | H71: RDEP | I71: 12 | J71: 202012 | K71: 0 | X71: 98942 | Y71: NDEP | Z71: 14 | AA71: 0 | AB71: 11
G72: 98942 | H72: RDEP | I72: 36 | J72: 20209 | K72: 0 | X72: 98942 | Y72: NDEP | Z72: 4 | AA72: 0 | AB72: 12
G73: 98944 | H73: NDEP | I73: 17 | J73: 202010 | K73: 0 | X73: 98942 | Y73: RDEP | Z73: 114 | AA73: 0 | AB73: 10
G74: 98944 | H74: NDEP | I74: 6 | J74: 202012 | K74: 0 | X74: 98942 | Y74: RDEP | Z74: 190 | AA74: 0 | AB74: 11
... G135: 99363 | H135: NDEP | I135: 1 | J135: 202010 | K135: 0 | X135: 99361 | Y135: RDEP | Z135: 6 | AA135: 0 | AB135: 10
X136: 99361 | Y136: RDEP | Z136: 24 | AA136: 0 | AB136: 12
X137: 99362 | Y137: NDEP | Z137: 18 | AA137: 0 | AB137: 10
X138: 99362 | Y138: NDEP | Z138: 20 | AA138: 0 | AB138: 11
X139: 99362 | Y139: NDEP | Z139: 16 | AA139: 0 | AB139: 12
X140: 99362 | Y140: RDEP | Z140: 394 | AA140: 0 | AB140: 10
X141: 99362 | Y141: RDEP | Z141: 308 | AA141: 0 | AB141: 11
X142: 99362 | Y142: RDEP | Z142: 342 | AA142: 0 | AB142: 12
X143: 99363 | Y143: RDEP | Z143: 4 | AA143: 0 | AB143: 10
X144: 99363 | Y144: RDEP | Z144: 2 | AA144: 0 | AB144: 12

Sheet 7. Bill Assistance 2023_Q3
A1: Item a) Number of Premises Receiving Bill Assistance or Enrolled in Any Other Assistance Program
A2: 44197 | B2: 44228 | C2: 44256 | D2: ZIP ** | E2: 44287 | F2: 44317 | G2: 44348 | H2: 44378 | I2: 44409 | J2: 44440 | K2: 44470 | L2: 44501 | M2: 44531 | N2: Zip Code | O2: 45108 | P2: Zip Code | Q2: 45139 | R2: Zip Code | S2: 45170
N3: 98901 | O3: 1212 | P3: 98901 | Q3: 1208 | R3: 98901 | S3: 1178
N4: 98902 | O4: 1708 | P4: 98902 | Q4: 1696 | R4: 98902 | S4: 1669
N5: 98903 | O5: 563 | P5: 98903 | Q5: 563 | R5: 98903 | S5: 557
N6: 98908 | O6: 562 | P6: 98908 | Q6: 562 | R6: 98908 | S6: 548
N7: 98921 | O7: 53 | P7: 98921 | Q7: 54 | R7: 98921 | S7: 53
N8: 98923 | O8: 29 | P8: 98923 | Q8: 28 | R8: 98923 | S8: 28
N9: 98930 | O9: 452 | P9: 98930 | Q9: 452 | R9: 98930 | S9: 446
N10: 98932 | O10: 214 | P10: 98932 | Q10: 212 | R10: 98932 | S10: 210
N11: 98933 | O11: 19 | P11: 98933 | Q11: 19 | R11: 98933 | S11: 19
N12: 98935 | O12: 138 | P12: 98935 | Q12: 137 | R12: 98935 | S12: 137
N13: 98936 | O13: 100 | P13: 98936 | Q13: 98 | R13: 98936 | S13: 97
N14: 98937 | O14: 47 | P14: 98937 | Q14: 48 | R14: 98937 | S14: 45
... N34: 99363 | O34: 4 | P34: 99363 | Q34: 4 | R34: 99363 | S34: 5
N35: TOTAL | O35: =SUM(O3:O34) -> 8355 | Q35: =SUM(Q3:Q34) -> 8328 | S35: =SUM(S3:S34) -> 8181

Sheet BA_WRKSHT
A1: FLAG | B1: SumOfJAN20 | C1: SumOfFEB20 | D1: SumOfMAR20 | E1: SumOfAPR20 | F1: SumOfMAY20 | G1: SumOfJUN20 | H1: SumOfJUL20 | I1: SumOfAUG20 | J1: SumOfSEP20 | K1: SumOfOCT20 | L1: SumOfNOV20 | M1: SumOfDEC20 | N1: SumOfJAN19 | O1: SumOfFEB19 | P1: SumOfMAR19 | Q1: SumOfAPR19 | R1: SumOfMAY19 | S1: SumOfJUN19 | T1: SumOfJUL19 | U1: SumOfAUG19 | V1: SumOfSEP19 | W1: SumOfOCT19 | X1: SumOfNOV19 | Y1: SumOfDEC19
A2: 98901RES | B2: 37 | C2: 35 | D2: 33 | E2: 31 | F2: 31 | G2: 31 | H2: 30 | I2: 27 | J2: 27 | K2: 27 | L2: 24 | M2: 24 | N2: 23 | O2: 28 | P2: 28 | Q2: 30 | R2: 32 | S2: 33 | T2: 33 | U2: 35 | V2: 36 | W2: 37 | X2: 38 | Y2: 39
A3: 98902RES | B3: 54 | C3: 51 | D3: 48 | E3: 46 | F3: 43 | G3: 41 | H3: 38 | I3: 34 | J3: 33 | K3: 29 | L3: 27 | M3: 24 | N3: 24 | O3: 31 | P3: 34 | Q3: 38 | R3: 39 | S3: 43 | T3: 45 | U3: 47 | V3: 48 | W3: 50 | X3: 51 | Y3: 53
A4: 98903RES | B4: 26 | C4: 26 | D4: 24 | E4: 24 | F4: 23 | G4: 21 | H4: 22 | I4: 23 | J4: 23 | K4: 22 | L4: 22 | M4: 21 | N4: 22 | O4: 23 | P4: 24 | Q4: 26 | R4: 26 | S4: 27 | T4: 26 | U4: 26 | V4: 25 | W4: 26 | X4: 26 | Y4: 26
A5: 98908RES | B5: 29 | C5: 29 | D5: 27 | E5: 27 | F5: 27 | G5: 26 | H5: 26 | I5: 25 | J5: 26 | K5: 26 | L5: 26 | M5: 23 | N5: 23 | O5: 26 | P5: 26 | Q5: 26 | R5: 25 | S5: 25 | T5: 25 | U5: 26 | V5: 27 | W5: 27 | X5: 26 | Y5: 28
A6: 98921RES | B6: 10 | C6: 10 | D6: 9 | E6: 9 | F6: 9 | G6: 10 | H6: 9 | I6: 9 | J6: 7 | K6: 7 | L6: 7 | M6: 7 | N6: 12 | O6: 13 | P6: 12 | Q6: 12 | R6: 12 | S6: 11 | T6: 11 | U6: 10 | V6: 10 | W6: 10 | X6: 10 | Y6: 10
A7: 98923RES | B7: 3 | C7: 4 | D7: 3 | E7: 4 | F7: 3 | G7: 3 | H7: 4 | I7: 3 | J7: 4 | K7: 3 | L7: 4 | M7: 4 | N7: 4 | O7: 4 | P7: 5 | Q7: 4 | R7: 4 | S7: 5 | T7: 4 | U7: 4 | V7: 5 | W7: 5 | X7: 4 | Y7: 4
A8: 98930RES | B8: 33 | C8: 32 | D8: 32 | E8: 32 | F8: 30 | G8: 29 | H8: 28 | I8: 28 | J8: 28 | K8: 24 | L8: 21 | M8: 20 | N8: 21 | O8: 22 | P8: 25 | Q8: 25 | R8: 26 | S8: 27 | T8: 28 | U8: 28 | V8: 32 | W8: 31 | X8: 32 | Y8: 32
A9: 98932RES | B9: 21 | C9: 20 | D9: 21 | E9: 22 | F9: 21 | G9: 18 | H9: 18 | I9: 18 | J9: 17 | K9: 16 | L9: 15 | M9: 14 | N9: 16 | O9: 17 | P9: 17 | Q9: 17 | R9: 17 | S9: 19 | T9: 19 | U9: 20 | V9: 19 | W9: 20 | X9: 21 | Y9: 21
A10: 98933RES | B10: 4 | C10: 4 | D10: 4 | E10: 4 | F10: 4 | G10: 4 | H10: 4 | I10: 3 | J10: 2 | K10: 2 | L10: 2 | M10: 3 | N10: 2 | O10: 3 | P10: 3 | Q10: 3 | R10: 2 | S10: 3 | T10: 1 | U10: 1 | V10: 1 | W10: 2 | X10: 3 | Y10: 3
A11: 98935RES | B11: 12 | C11: 12 | D11: 12 | E11: 12 | F11: 12 | G11: 11 | H11: 10 | I11: 10 | J11: 10 | K11: 10 | L11: 10 | M11: 8 | N11: 9 | O11: 10 | P11: 10 | Q11: 9 | R11: 10 | S11: 11 | T11: 11 | U11: 10 | V11: 10 | W11: 12 | X11: 12 | Y11: 12
A12: 98936RES | B12: 8 | C12: 8 | D12: 7 | E12: 8 | F12: 7 | G12: 8 | H12: 8 | I12: 8 | J12: 8 | K12: 10 | L12: 10 | M12: 9 | N12: 7 | O12: 7 | P12: 7 | Q12: 7 | R12: 6 | S12: 6 | T12: 6 | U12: 5 | V12: 5 | W12: 7 | X12: 6 | Y12: 8
A13: 98937RES | B13: 9 | C13: 10 | D13: 9 | E13: 9 | F13: 8 | G13: 10 | H13: 10 | I13: 9 | J13: 10 | K13: 9 | L13: 9 | M13: 9 | N13: 7 | O13: 7 | P13: 7 | Q13: 7 | R13: 8 | S13: 8 | T13: 7 | U13: 7 | V13: 7 | W13: 9 | X13: 8 | Y13: 9
... A33: 99363RES | B33: 3 | C33: 2 | D33: 2 | E33: 2 | F33: 2 | G33: 2 | H33: 2 | I33: 1 | J33: 2 | K33: 1 | L33: 1 | M33: 1 | N33: 2 | O33: 2 | P33: 2 | Q33: 3 | R33: 2 | S33: 2 | T33: 2 | U33: 2 | V33: 2 | W33: 2 | X33: 2 | Y33: 3

Sheet 8.ARREARS NEW 2023_Q3
A1: Item a) Number of Customers by Customer Class With Past-due balances (arrearages) | R1: Item c) Amount of Past-due Balances for Known Low-income Households and Number of Days Past-due | AR1: Section D. Bad Debt | AW1: Item e) The Amount of Past-due Balances Written-off and Classified as Bad Debt, if different than item d | BJ1: Item f) Number of Customer Accounts Referred to Collection Agencies | BS1: Item f) Total Amount of Bad Debt Referred for Collection | BY1: Item f) Total Revenue to the Company from the Collection Process
A3: 202307 | H3: 202308 | O3: 202309 | R3: 202307 | Y3: 202308 | AD3: 202309 | AR3: 202307 | AU3: 202308 | AV3: 202309 | AW3: Class | AX3: 202101 | AY3: 202102 | AZ3: 202103 | BA3: 202104 | BB3: 202105 | BC3: 202106 | BD3: 202107 | BE3: 202108 | BF3: 202109 | BG3: 202307 | BH3: 202308 | BI3: 202309 | BJ3: 202307 | BM3: 202308 | BP3: 202309 | BS3: 202307 | BU3: 202308 | BW3: 202309 | BY3: 202307 | CA3: 202308 | CC3: 202309
A4: CLASS | B4: ZIP | C4: COUNT | D4: DAYS 31 60 | E4: DAYS 61 90 | F4: DAYS 91+ | G4: ARREARS | H4: COUNT | I4: DAYS 31 60 | J4: DAYS 61 90 | K4: DAYS 91+ | L4: ARREARS | M4: COUNT | N4: DAYS 31 60 | O4: DAYS 61 90 | P4: DAYS 91+ | Q4: ARREARS | R4: CLASS | S4: ZIP | T4: COUNT | U4: DAYS 31 60 | V4: DAYS 61 90 | W4: DAYS 91+ | X4: ARREARS | Y4: COUNT | Z4: DAYS 31 60 | AA4: DAYS 61 90 | AB4: DAYS 91+ | AC4: ARREARS | AD4: COUNT | AE4: DAYS 31 60 | AF4: DAYS 61 90 | AG4: DAYS 91+ | AH4: ARREARS | AR4: CLASS | AS4: ZIP | AT4: BAD DEBT | AU4: BAD DEBT | AV4: BAD DEBT | AW4: RES | AX4: 78547.88 | AY4: 83507.78 | AZ4: 74673.15 | BA4: 63441.04 | BB4: 64476.9 | BC4: 57542.34 | BD4: 83815.89 | BE4: 81559.71 | BF4: 121882.53 | BG4: 235999.64 | BH4: 280875.02 | BI4: 334506.88 | BJ4: ZIP | BK4: CLASS | BL4: Count | BM4: ZIP | BN4: CLASS | BO4: Count | BP4: Zip Code | BQ4: CLASS | BR4: Count | BS4: ZIP/CLASS | BT4: Amount | BU4: ZIP/CLASS | BV4: Amount | BW4: ZIP/CLASS | BX4: Amount | BY4: ZIP/CLASS | BZ4: Amount | CA4: ZIP/CLASS | CB4: Amount | CC4: ZIP/CLASS | CD4: Amount
A5: COM | B5: 98901 | C5: 121 | D5: 45844.45 | E5: 22882.89 | F5: 183422.03 | G5: 252149.37 | H5: 130 | I5: 47977.92 | J5: 20050.96 | K5: 166925.16 | L5: 234954.04 | M5: 155 | N5: 65368.24 | O5: 22713.44 | P5: 120555.73 | Q5: 208637.41 | R5: COM | S5: 98901 | T5: 6 | U5: 225.34 | V5: 297.41 | W5: 1136.97 | X5: 1659.72 | Y5: 5 | Z5: 262.55 | AA5: 231.46 | AB5: 1412.06 | AC5: 1906.07 | AD5: 5 | AE5: 233.48 | AF5: 244.55 | AG5: 836.2 | AH5: 1314.23 | AR5: COM | AS5: 98901 | AT5: =D5*1.6%+E5*6.3%+F5*28.9% -> 55184.1 | AU5: =I5*1.6%+J5*6.3%+K5*28.9% -> 50272.228 | AV5: =N5*1.6%+O5*6.3%+P5*28.9% -> 37317.445 | AW5: COM | AX5: 35411.49 | AY5: 19861.99 | AZ5: 1614.2 | BA5: 209.93 | BB5: 2347.21 | BC5: 3702.39 | BD5: 16587.84 | BE5: 21717.76 | BF5: 41593.57 | BG5: 57754.15 | BH5: 41500.39 | BI5: 23065.75 | BJ5: 98901 | BK5: COM | BL5: 2 | BM5: 98901 | BN5: COM | BO5: 5 | BP5: 98901 | BQ5: COM | BR5: 3 | BS5: 98901COM | BT5: 1021.93 | BU5: 98901COM | BV5: 55987.33 | BW5: 98901COM | BX5: 26605.29 | BY5: 98901COM | BZ5: 87.97 | CA5: 98901COM | CB5: 230.16 | CC5: 98901RES | CD5: 819.1
A6: COM | B6: 98902 | C6: 209 | D6: 70788.9 | E6: 27409.63 | F6: 107286.42 | G6: 205484.95 | H6: 197 | I6: 60951.68 | J6: 26441.63 | K6: 108496.66 | L6: 195889.97 | M6: 231 | N6: 87758.69 | O6: 32081.85 | P6: 117775.9 | Q6: 237616.44 | R6: COM | S6: 98902 | T6: 4 | U6: 273.34 | V6: 239.01 | W6: 948.15 | X6: 1460.5 | Y6: 4 | Z6: 1497.65 | AA6: 86.13 | AB6: 222.72 | AC6: 1806.5 | AD6: 4 | AE6: 306.53 | AF6: 88.46 | AG6: 308.85 | AH6: 703.84 | AR6: COM | AS6: 98902 | AT6: =D6*1.6%+E6*6.3%+F6*28.9% -> 33865.204 | AU6: =I6*1.6%+J6*6.3%+K6*28.9% -> 33996.584 | AV6: =N6*1.6%+O6*6.3%+P6*28.9% -> 37462.531 | BJ6: 98902 | BK6: COM | BL6: 1 | BM6: 98902 | BN6: COM | BO6: 4 | BP6: 98902 | BQ6: COM | BR6: 1 | BS6: 98901RES | BT6: 40734.43 | BU6: 98901RES | BV6: 81570.47 | BW6: 98901RES | BX6: 41667.14 | BY6: 98901RES | BZ6: 1301.41 | CA6: 98901RES | CB6: 1645.55 | CC6: 98902RES | CD6: 1936.48
A7: COM | B7: 98903 | C7: 139 | D7: 14933.74 | E7: 22284.73 | F7: 155348.95 | G7: 192567.42 | H7: 100 | I7: 30267.37 | J7: 11192.05 | K7: 150206.92 | L7: 191666.34 | M7: 193 | N7: 117396.53 | O7: 9537.04 | P7: 126497.38 | Q7: 253430.95 | R7: COM | S7: 98903 | T7: 5 | U7: 308.48 | V7: 252.27 | W7: 1715.53 | X7: 2276.28 | Y7: 5 | Z7: 323.21 | AA7: 279.04 | AB7: 884.84 | AC7: 1487.09 | AD7: 5 | AE7: 316.25 | AF7: 215.73 | AG7: 1170.82 | AH7: 1702.8 | AR7: COM | AS7: 98903 | AT7: =D7*1.6%+E7*6.3%+F7*28.9% -> 46538.724 | AU7: =I7*1.6%+J7*6.3%+K7*28.9% -> 44599.177 | AV7: =N7*1.6%+O7*6.3%+P7*28.9% -> 39036.921 | BJ7: 98903 | BK7: COM | BL7: 2 | BM7: 98903 | BN7: COM | BO7: 1 | BP7: 98951 | BQ7: COM | BR7: 1 | BS7: 98902COM | BT7: 16571.43 | BU7: 98902COM | BV7: 43337.6 | BW7: 98902COM | BX7: 109.28 | BY7: 98902RES | BZ7: 4070.94 | CA7: 98902RES | CB7: 747.66 | CC7: 98903RES | CD7: 104.49
A8: COM | B8: 98904 | D8: 0 | E8: 0 | F8: 0 | G8: 0 | I8: 0 | J8: 0 | K8: 0 | L8: 0 | N8: 0 | O8: 0 | P8: 0 | Q8: 0 | R8: COM | S8: 98908 | T8: 6 | U8: 356.95 | V8: 309.87 | W8: 1737.83 | X8: 2404.65 | Y8: 7 | Z8: 460.79 | AA8: 409.61 | AB8: 1838.73 | AC8: 2709.13 | AD8: 7 | AE8: 509.45 | AF8: 308.3 | AG8: 2225.35 | AH8: 3043.1 | AR8: COM | AS8: 98904 | AT8: =D8*1.6%+E8*6.3%+F8*28.9% -> 0 | AU8: =I8*1.6%+J8*6.3%+K8*28.9% -> 0 | AV8: =N8*1.6%+O8*6.3%+P8*28.9% -> 0 | BJ8: 98936 | BK8: COM | BL8: 1 | BM8: 98908 | BN8: COM | BO8: 1 | BP8: 99328 | BQ8: COM | BR8: 1 | BS8: 98902RES | BT8: 97412.08 | BU8: 98902RES | BV8: 102992.75 | BW8: 98902RES | BX8: 71143.46 | BY8: 98903RES | BZ8: 1284.52 | CA8: 98903RES | CB8: 519.1 | CC8: 98908RES | CD8: 123.99
A9: COM | B9: 98907 | D9: 0 | E9: 0 | F9: 0 | G9: 0 | I9: 0 | J9: 0 | K9: 0 | L9: 0 | N9: 0 | O9: 0 | P9: 0 | Q9: 0 | R9: COM | S9: 98930 | U9: 0 | V9: 0 | W9: 0 | X9: 0 | Y9: 1 | Z9: 11.71 | AA9: 0 | AB9: 0 | AC9: 11.71 | AR9: COM | AS9: 98907 | AT9: =D9*1.6%+E9*6.3%+F9*28.9% -> 0 | AU9: =I9*1.6%+J9*6.3%+K9*28.9% -> 0 | AV9: =N9*1.6%+O9*6.3%+P9*28.9% -> 0 | BJ9: 98937 | BK9: COM | BL9: 1 | BM9: 98942 | BN9: COM | BO9: 1 | BP9: 99347 | BQ9: COM | BR9: 1 | BS9: 98903COM | BT9: 5802.3 | BU9: 98903COM | BV9: 3495.99 | BW9: 98903RES | BX9: 23058.6 | BY9: 98908RES | BZ9: 2014.83 | CA9: 98908RES | CB9: 1010.08 | CC9: 98930RES | CD9: 150.9
A10: COM | B10: 98908 | C10: 116 | D10: 37953.29 | E10: 9065.54 | F10: 27735.11 | G10: 74753.94 | H10: 137 | I10: 89937.53 | J10: 8484.55 | K10: 25456.59 | L10: 123878.67 | M10: 133 | N10: 50929.41 | O10: 13003.59 | P10: 24520.22 | Q10: 88453.22 | R10: COM | S10: 98932 | T10: 1 | U10: 14.74 | V10: 15.13 | W10: 143.46 | X10: 173.33 | Y10: 1 | Z10: 16.94 | AA10: 14.74 | AB10: 132.46 | AC10: 164.14 | AD10: 1 | AE10: 15.13 | AF10: 16.94 | AG10: 18.73 | AH10: 50.8 | AR10: COM | AS10: 98908 | AT10: =D10*1.6%+E10*6.3%+F10*28.9% -> 9193.8285 | AU10: =I10*1.6%+J10*6.3%+K10*28.9% -> 9330.4816 | AV10: =N10*1.6%+O10*6.3%+P10*28.9% -> 8720.4403 | BJ10: 98942 | BK10: COM | BL10: 1 | BM10: 98944 | BN10: COM | BO10: 1 | BP10: 99362 | BQ10: COM | BR10: 3 | BS10: 98903RES | BT10: 31989.74 | BU10: 98903RES | BV10: 120967.55 | BW10: 98908RES | BX10: 50024.74 | BY10: 98930RES | BZ10: 797.03 | CA10: 98930RES | CB10: 56.14 | CC10: 98935RES | CD10: 62.69
A11: COM | B11: 98920 | D11: 0 | E11: 0 | F11: 0 | G11: 0 | I11: 0 | J11: 0 | K11: 0 | L11: 0 | N11: 0 | O11: 0 | P11: 0 | Q11: 0 | R11: COM | S11: 98933 | U11: 0 | V11: 0 | W11: 0 | X11: 0 | Z11: 0 | AA11: 0 | AB11: 0 | AC11: 0 | AE11: 0 | AF11: 0 | AG11: 0 | AH11: 0 | AR11: COM | AS11: 98920 | AT11: =D11*1.6%+E11*6.3%+F11*28.9% -> 0 | AU11: =I11*1.6%+J11*6.3%+K11*28.9% -> 0 | AV11: =N11*1.6%+O11*6.3%+P11*28.9% -> 0 | BJ11: 98944 | BK11: COM | BL11: 1 | BM11: 98947 | BN11: COM | BO11: 1 | BP11: 98901 | BQ11: RES | BR11: 65 | BS11: 98908RES | BT11: 66317.97 | BU11: 98908COM | BV11: 1058.53 | BW11: 98930RES | BX11: 8543.94 | BY11: 98932RES | BZ11: 483.86 | CA11: 98932RES | CB11: 221.53 | CC11: 98942RES | CD11: 36.72
A12: COM | B12: 98921 | C12: 1 | D12: 13.7 | E12: 13.7 | F12: 95.9 | G12: 123.3 | H12: 2 | I12: 15417.72 | J12: 13.7 | K12: 109.6 | L12: 15541.02 | M12: 1 | N12: 13.7 | O12: 13.7 | P12: 123.3 | Q12: 150.7 | R12: COM | S12: 98936 | T12: 1 | U12: 37.76 | V12: 107.8 | W12: 0 | X12: 145.56 | Y12: 1 | Z12: 35.03 | AA12: 37.76 | AB12: 107.8 | AC12: 180.59 | AD12: 1 | AE12: 35.98 | AF12: 35.03 | AG12: 145.56 | AH12: 216.57 | AR12: COM | AS12: 98921 | AT12: =D12*1.6%+E12*6.3%+F12*28.9% -> 28.7974 | AU12: =I12*1.6%+J12*6.3%+K12*28.9% -> 279.22102 | AV12: =N12*1.6%+O12*6.3%+P12*28.9% -> 36.716 | BJ12: 98948 | BK12: COM | BL12: 2 | BM12: 98948 | BN12: COM | BO12: 3 | BP12: 98902 | BQ12: RES | BR12: 84 | BS12: 98921RES | BT12: 686.37 | BU12: 98908RES | BV12: 32146.85 | BW12: 98932RES | BX12: 2372.6 | BY12: 98933RES | BZ12: 165.2 | CA12: 98936RES | CB12: 439.98 | CC12: 98944RES | CD12: 551.43
A13: COM | B13: 98923 | C13: 8 | D13: 15294.03 | E13: 2332.86 | F13: 13466.93 | G13: 31093.82 | H13: 9 | I13: 14841.39 | J13: 2664.88 | K13: 12522.31 | L13: 30028.58 | M13: 7 | N13: 12941.62 | O13: 1596.24 | P13: 13632.73 | Q13: 28170.59 | R13: COM | S13: 98937 | T13: 1 | U13: 28.85 | V13: 24.87 | W13: 268.81 | X13: 322.53 | Y13: 1 | Z13: 36.4 | AA13: 28.85 | AB13: 293.68 | AC13: 358.93 | AD13: 1 | AE13: 43.14 | AF13: 36.4 | AG13: 322.53 | AH13: 402.07 | AR13: COM | AS13: 98923 | AT13: =D13*1.6%+E13*6.3%+F13*28.9% -> 4283.6174 | AU13: =I13*1.6%+J13*6.3%+K13*28.9% -> 4024.2973 | AV13: =N13*1.6%+O13*6.3%+P13*28.9% -> 4247.488 | BJ13: 98951 | BK13: COM | BL13: 3 | BM13: 99328 | BN13: COM | BO13: 1 | BP13: 98903 | BQ13: RES | BR13: 17 | BS13: 98923RES | BT13: 3597.58 | BU13: 98923RES | BV13: 1402.38 | BW13: 98933RES | BX13: 7983.59 | BY13: 98935RES | BZ13: 889.86 | CA13: 98937RES | CB13: 335.33 | CC13: 98948RES | CD13: 237.99
A14: COM | B14: 98930 | C14: 33 | D14: 6078.2 | E14: 4826.14 | F14: 30904.02 | G14: 41808.36 | H14: 33 | I14: 7600.99 | J14: 5123.68 | K14: 30835.44 | L14: 43560.11 | M14: 41 | N14: 19763.75 | O14: 2728.02 | P14: 29183.44 | Q14: 51675.21 | R14: COM | S14: 98938 | T14: 1 | U14: 85.86 | V14: 87.29 | W14: 971 | X14: 1144.15 | Y14: 2 | Z14: 156.5 | AA14: 85.86 | AB14: 1058.29 | AC14: 1300.65 | AD14: 1 | AE14: 87.04 | AF14: 66.17 | AG14: 1144.15 | AH14: 1297.36 | AR14: COM | AS14: 98930 | AT14: =D14*1.6%+E14*6.3%+F14*28.9% -> 9332.5598 | AU14: =I14*1.6%+J14*6.3%+K14*28.9% -> 9355.8498 | AV14: =N14*1.6%+O14*6.3%+P14*28.9% -> 8922.0994 | BJ14: 99328 | BK14: COM | BL14: 5 | BM14: 99362 | BN14: COM | BO14: 1 | BP14: 98908 | BQ14: RES | BR14: 37 | BS14: 98930RES | BT14: 10757.62 | BU14: 98930RES | BV14: 11499.35 | BW14: 98935RES | BX14: 752.65 | BY14: 98942RES | BZ14: 1394.99 | CA14: 98942RES | CB14: 1056.17 | CC14: 98951RES | CD14: 33.13
A15: COM | B15: 98932 | C15: 24 | D15: 8434.25 | E15: 2545.33 | F15: 16552.01 | G15: 27531.59 | H15: 26 | I15: 12078.76 | J15: 2582.38 | K15: 15803.65 | L15: 30464.79 | M15: 21 | N15: 34101.08 | O15: 14590.73 | P15: 15777.9 | Q15: 64469.71 | R15: COM | S15: 98939 | T15: 1 | U15: 509.46 | V15: 21.85 | W15: 119.35 | X15: 650.66 | Y15: 1 | Z15: 22 | AA15: 8.9 | AB15: 0 | AC15: 30.9 | AD15: 1 | AE15: 76.72 | AF15: 22 | AG15: 8.9 | AH15: 107.62 | AR15: COM | AS15: 98932 | AT15: =D15*1.6%+E15*6.3%+F15*28.9% -> 5078.8347 | AU15: =I15*1.6%+J15*6.3%+K15*28.9% -> 4923.2049 | AV15: =N15*1.6%+O15*6.3%+P15*28.9% -> 6024.6464 | BJ15: 99362 | BK15: COM | BL15: 1 | BM15: 98901 | BN15: RES | BO15: 54 | BP15: 98930 | BQ15: RES | BR15: 19 | BS15: 98932RES | BT15: 4828.32 | BU15: 98932RES | BV15: 1730.38 | BW15: 98936RES | BX15: 2995.38 | BY15: 98944RES | BZ15: 250.22 | CA15: 98944RES | CB15: 667.56 | CC15: 99324RES | CD15: 97.61
A16: COM | B16: 98933 | C16: 10 | D16: 2494.33 | E16: 1012.59 | F16: 2136.02 | G16: 5642.94 | H16: 11 | I16: 2946.1 | J16: 850.36 | K16: 1154.1 | L16: 4950.56 | M16: 12 | N16: 2797.21 | O16: 983.08 | P16: 1153.78 | Q16: 4934.07 | R16: COM | S16: 98942 | U16: 0 | V16: 0 | W16: 0 | X16: 0 | Z16: 0 | AA16: 0 | AB16: 0 | AC16: 0 | AE16: 0 | AF16: 0 | AG16: 0 | AH16: 0 | AR16: COM | AS16: 98933 | AT16: =D16*1.6%+E16*6.3%+F16*28.9% -> 721.01223 | AU16: =I16*1.6%+J16*6.3%+K16*28.9% -> 434.24518 | AV16: =N16*1.6%+O16*6.3%+P16*28.9% -> 440.13182 | BJ16: 98901 | BK16: RES | BL16: 43 | BM16: 98902 | BN16: RES | BO16: 63 | BP16: 98932 | BQ16: RES | BR16: 3 | BS16: 98933RES | BT16: 650.34 | BU16: 98933RES | BV16: 3128.92 | BW16: 98937RES | BX16: 1656.58 | BY16: 98948RES | BZ16: 152.65 | CA16: 98948RES | CB16: 405.27 | CC16: 99347RES | CD16: 326.42
A17: COM | B17: 98935 | C17: 7 | D17: 0 | E17: 480.9 | F17: 587.44 | G17: 1068.34 | H17: 8 | I17: 3904.55 | J17: 278.07 | K17: 71.9 | L17: 4254.52 | M17: 13 | N17: 7221.07 | O17: 0 | P17: 676.63 | Q17: 7897.7 | R17: COM | S17: 98944 | T17: 3 | U17: 650.6 | V17: 547.67 | W17: 22219.64 | X17: 23417.91 | Y17: 3 | Z17: 619.47 | AA17: 609.73 | AB17: 22767.31 | AC17: 23996.51 | AD17: 3 | AE17: 859.76 | AF17: 619.47 | AG17: 22875.54 | AH17: 24354.77 | AR17: COM | AS17: 98935 | AT17: =D17*1.6%+E17*6.3%+F17*28.9% -> 200.06686 | AU17: =I17*1.6%+J17*6.3%+K17*28.9% -> 100.77031 | AV17: =N17*1.6%+O17*6.3%+P17*28.9% -> 311.08319 | BJ17: 98902 | BK17: RES | BL17: 85 | BM17: 98903 | BN17: RES | BO17: 24 | BP17: 98933 | BQ17: RES | BR17: 3 | BS17: 98935RES | BT17: 1756.35 | BU17: 98936RES | BV17: 2847.11 | BW17: 98942RES | BX17: 36069.66 | BY17: 98951RES | BZ17: 153.5 | CA17: 98951RES | CB17: 131.65 | CC17: 99362COM | CD17: 3178.49
A18: COM | B18: 98936 | C18: 22 | D18: 4994.39 | E18: 1760.09 | F18: 17304.8 | G18: 24059.28 | H18: 21 | I18: 3447.19 | J18: 4084.09 | K18: 13849.47 | L18: 21380.75 | M18: 22 | N18: 9728.19 | O18: 1754.15 | P18: 15667.34 | Q18: 27149.68 | R18: COM | S18: 98947 | T18: 1 | U18: 42.33 | V18: 55.21 | W18: 0 | X18: 97.54 | Z18: 0 | AA18: 0 | AB18: 0 | AC18: 0 | AE18: 0 | AF18: 0 | AG18: 0 | AH18: 0 | AR18: COM | AS18: 98936 | AT18: =D18*1.6%+E18*6.3%+F18*28.9% -> 5191.8831 | AU18: =I18*1.6%+J18*6.3%+K18*28.9% -> 4314.9495 | AV18: =N18*1.6%+O18*6.3%+P18*28.9% -> 4794.0237 | BJ18: 98903 | BK18: RES | BL18: 18 | BM18: 98908 | BN18: RES | BO18: 44 | BP18: 98935 | BQ18: RES | BR18: 4 | BS18: 98936COM | BT18: 1445.29 | BU18: 98937RES | BV18: 4202.65 | BW18: 98944RES | BX18: 6514.1 | BY18: 99324RES | BZ18: 294.59 | CA18: 98953RES | CB18: 34.25 | CC18: 99362RES | CD18: 3871.47
A19: COM | B19: 98937 | C19: 25 | D19: 7287.07 | E19: 4856.71 | F19: 29434.02 | G19: 41577.8 | H19: 31 | I19: 22944.58 | J19: 4708.27 | K19: 31296.25 | L19: 58949.1 | M19: 28 | N19: 23480.04 | O19: 2860.44 | P19: 17955.52 | Q19: 44296 | R19: COM | S19: 98948 | T19: 9 | U19: 3976.71 | V19: 2494.41 | W19: 10820.2 | X19: 17291.32 | Y19: 8 | Z19: 0 | AA19: 3911.46 | AB19: 12242.74 | AC19: 16154.2 | AD19: 10 | AE19: 4452.82 | AF19: 4889.21 | AG19: 16154.2 | AH19: 25496.23 | AR19: COM | AS19: 98937 | AT19: =D19*1.6%+E19*6.3%+F19*28.9% -> 8928.9976 | AU19: =I19*1.6%+J19*6.3%+K19*28.9% -> 9708.3505 | AV19: =N19*1.6%+O19*6.3%+P19*28.9% -> 5745.0336 | BJ19: 98908 | BK19: RES | BL19: 46 | BM19: 98923 | BN19: RES | BO19: 2 | BP19: 98936 | BQ19: RES | BR19: 5 | BS19: 98936RES | BT19: 2145.05 | BU19: 98938RES | BV19: 18311.32 | BW19: 98947RES | BX19: 124.49 | BY19: 99328RES | BZ19: 357.05 | CA19: 99323RES | CB19: 79.64
A20: COM | B20: 98938 | C20: 19 | D20: 61067.37 | E20: 4221.54 | F20: 8501.43 | G20: 73790.34 | H20: 17 | I20: 39439.16 | J20: 30837.41 | K20: 11667.66 | L20: 81944.23 | M20: 19 | N20: 67634.04 | O20: 1486.44 | P20: 8229.13 | Q20: 77349.61 | R20: COM | S20: 98951 | T20: 2 | U20: 76.64 | V20: 51.41 | W20: 124.2 | X20: 252.25 | Y20: 3 | Z20: 178.19 | AA20: 76.64 | AB20: 175.61 | AC20: 430.44 | AD20: 3 | AE20: 141.28 | AF20: 83.71 | AG20: 190.7 | AH20: 415.69 | AR20: COM | AS20: 98938 | AT20: =D20*1.6%+E20*6.3%+F20*28.9% -> 3699.9482 | AU20: =I20*1.6%+J20*6.3%+K20*28.9% -> 5945.7371 | AV20: =N20*1.6%+O20*6.3%+P20*28.9% -> 3554.0089 | BJ20: 98921 | BK20: RES | BL20: 1 | BM20: 98930 | BN20: RES | BO20: 11 | BP20: 98937 | BQ20: RES | BR20: 3 | BS20: 98937COM | BT20: 17.42 | BU20: 98942COM | BV20: 18961.88 | BW20: 98948RES | BX20: 8551.77 | BY20: 99362COM | BZ20: 2352.5 | CA20: 99324RES | CB20: 316.18
A21: COM | B21: 98939 | C21: 2 | D21: 717.5 | E21: 176.72 | F21: 119.35 | G21: 1013.57 | H21: 2 | I21: 224.21 | J21: 216.94 | K21: 154.87 | L21: 596.02 | M21: 2 | N21: 268.62 | O21: 224.21 | P21: 371.81 | Q21: 864.64 | R21: COM | S21: 98952 | T21: 1 | U21: 89.54 | V21: 66.05 | W21: 0 | X21: 155.59 | Y21: 1 | Z21: 95.14 | AA21: 89.54 | AB21: 66.05 | AC21: 250.73 | AD21: 1 | AE21: 104.6 | AF21: 95.14 | AG21: 48.09 | AH21: 247.83 | AR21: COM | AS21: 98939 | AT21: =D21*1.6%+E21*6.3%+F21*28.9% -> 57.10551 | AU21: =I21*1.6%+J21*6.3%+K21*28.9% -> 62.01201 | AV21: =N21*1.6%+O21*6.3%+P21*28.9% -> 125.87624 | BJ21: 98923 | BK21: RES | BL21: 1 | BM21: 98932 | BN21: RES | BO21: 3 | BP21: 98942 | BQ21: RES | BR21: 17 | BS21: 98937RES | BT21: 1779.39 | BU21: 98942RES | BV21: 56427.81 | BW21: 98951COM | BX21: 430.9 | BY21: 99362RES | BZ21: 1693.87 | CA21: 99361RES | CB21: 84.98
A22: COM | B22: 98942 | C22: 59 | D22: 98891.39 | E22: 4903.02 | F22: 24819.88 | G22: 128614.29 | H22: 59 | I22: 70082.12 | J22: 4993.32 | K22: 20664.58 | L22: 95740.02 | M22: 70 | N22: 72079.13 | O22: 4833.23 | P22: 20619.88 | Q22: 97532.24 | R22: COM | S22: 98953 | T22: 4 | U22: 74.33 | V22: 130.2 | W22: 2609.18 | X22: 2813.71 | Y22: 3 | Z22: 88.64 | AA22: 74.16 | AB22: 2739.38 | AC22: 2902.18 | AD22: 3 | AE22: 74.18 | AF22: 88.64 | AG22: 2813.54 | AH22: 2976.36 | AR22: COM | AS22: 98942 | AT22: =D22*1.6%+E22*6.3%+F22*28.9% -> 9064.0978 | AU22: =I22*1.6%+J22*6.3%+K22*28.9% -> 7407.9567 | AV22: =N22*1.6%+O22*6.3%+P22*28.9% -> 7416.9049 | BJ22: 98930 | BK22: RES | BL22: 11 | BM22: 98933 | BN22: RES | BO22: 2 | BP22: 98944 | BQ22: RES | BR22: 18 | BS22: 98938RES | BT22: 21472.21 | BU22: 98944COM | BV22: 12921.82 | BW22: 98951RES | BX22: 20150.09 | CA22: 99362RES | CB22: 2300.95
A23: COM | B23: 98944 | C23: 116 | D23: 36806.73 | E23: 16252.42 | F23: 139272.14 | G23: 192331.29 | H23: 119 | I23: 45879.74 | J23: 23090.24 | K23: 141342.78 | L23: 210312.76 | M23: 116 | N23: 37749.44 | O23: 13716.32 | P23: 103373.55 | Q23: 154839.31 | R23: COM | S23: 99323 | T23: 1 | U23: 53.48 | V23: 41.17 | W23: 146.14 | X23: 240.79 | Y23: 1 | Z23: 59.95 | AA23: 53.48 | AB23: 110.32 | AC23: 223.75 | AD23: 1 | AE23: 56.33 | AF23: 59.95 | AG23: 163.8 | AH23: 280.08 | AR23: COM | AS23: 98944 | AT23: =D23*1.6%+E23*6.3%+F23*28.9% -> 41862.459 | AU23: =I23*1.6%+J23*6.3%+K23*28.9% -> 43036.824 | AV23: =N23*1.6%+O23*6.3%+P23*28.9% -> 31343.075 | BJ23: 98932 | BK23: RES | BL23: 8 | BM23: 98936 | BN23: RES | BO23: 6 | BP23: 98947 | BQ23: RES | BR23: 3 | BS23: 98942COM | BT23: 18961.88 | BU23: 98944RES | BV23: 18413.48 | BW23: 98952RES | BX23: 3353.01
A24: COM | B24: 98947 | C24: 14 | D24: 5116.8 | E24: 882.94 | F24: 3090.06 | G24: 9089.8 | H24: 12 | I24: 5781.98 | J24: 640.65 | K24: 3056.21 | L24: 9478.84 | M24: 14 | N24: 59471.36 | O24: 330.29 | P24: 2983.8 | Q24: 62785.45 | R24: COM | S24: 99324 | T24: 1 | U24: 14.09 | V24: 14.09 | W24: 296.24 | X24: 324.42 | Z24: 0 | AA24: 0 | AB24: 0 | AC24: 0 | AD24: 1 | AE24: 12.22 | AF24: 0 | AG24: 0 | AH24: 12.22 | AR24: COM | AS24: 98947 | AT24: =D24*1.6%+E24*6.3%+F24*28.9% -> 1030.5214 | AU24: =I24*1.6%+J24*6.3%+K24*28.9% -> 1016.1173 | AV24: =N24*1.6%+O24*6.3%+P24*28.9% -> 1834.6682 | BJ24: 98933 | BK24: RES | BL24: 2 | BM24: 98937 | BN24: RES | BO24: 5 | BP24: 98948 | BQ24: RES | BR24: 15 | BS24: 98942RES | BT24: 25870.05 | BU24: 98947COM | BV24: 52.51 | BW24: 98953RES | BX24: 1130.03
A25: COM | B25: 98948 | C25: 102 | D25: 57881.36 | E25: 20431.84 | F25: 182326.84 | G25: 260640.04 | H25: 68 | I25: 8066.65 | J25: 22154.11 | K25: 189645.38 | L25: 219866.14 | M25: 96 | N25: 69698.57 | O25: 25036.55 | P25: 203313.77 | Q25: 298048.89 | R25: COM | S25: 99328 | U25: 0 | V25: 0 | W25: 0 | X25: 0 | Z25: 0 | AA25: 0 | AB25: 0 | AC25: 0 | AE25: 0 | AF25: 0 | AG25: 0 | AH25: 0 | AR25: COM | AS25: 98948 | AT25: =D25*1.6%+E25*6.3%+F25*28.9% -> 54905.764 | AU25: =I25*1.6%+J25*6.3%+K25*28.9% -> 56332.29 | AV25: =N25*1.6%+O25*6.3%+P25*28.9% -> 61450.159 | BJ25: 98935 | BK25: RES | BL25: 3 | BM25: 98938 | BN25: RES | BO25: 1 | BP25: 98951 | BQ25: RES | BR25: 13 | BS25: 98944COM | BT25: 202.28 | BU25: 98947RES | BV25: 2286.04 | BW25: 99323RES | BX25: 2591.97
A26: COM | B26: 98951 | C26: 78 | D26: 40110.06 | E26: 29204.68 | F26: 45865.98 | G26: 115180.72 | H26: 75 | I26: 40785 | J26: 9904.36 | K26: 37181.46 | L26: 87870.82 | M26: 80 | N26: 68919.71 | O26: 9878.69 | P26: 42371.24 | Q26: 121169.64 | R26: COM | S26: 99347 | T26: 3 | U26: 252.16 | V26: 241.06 | W26: 1880.45 | X26: 2373.67 | Y26: 1 | Z26: 101.03 | AA26: 0 | AB26: 0 | AC26: 101.03 | AD26: 1 | AE26: 43.3 | AF26: 0 | AG26: 0 | AH26: 43.3 | AR26: COM | AS26: 98951 | AT26: =D26*1.6%+E26*6.3%+F26*28.9% -> 15736.924 | AU26: =I26*1.6%+J26*6.3%+K26*28.9% -> 12021.977 | AV26: =N26*1.6%+O26*6.3%+P26*28.9% -> 13970.361 | BJ26: 98936 | BK26: RES | BL26: 2 | BM26: 98942 | BN26: RES | BO26: 27 | BP26: 98952 | BQ26: RES | BR26: 1 | BS26: 98944RES | BT26: 12698.47 | BU26: 98948COM | BV26: 99798.3 | BW26: 99324RES | BX26: 7670.27
A27: COM | B27: 98952 | C27: 3 | D27: 262.7 | E27: 245.52 | F27: 2957.9 | G27: 3466.12 | H27: 3 | I27: 263.25 | J27: 172.27 | K27: 2777.72 | L27: 3213.24 | M27: 6 | N27: 501.58 | O27: 174.25 | P27: 2842.49 | Q27: 3518.32 | R27: COM | S27: 99361 | Z27: 0 | AA27: 0 | AB27: 0 | AC27: 0 | AR27: COM | AS27: 98952 | AT27: =D27*1.6%+E27*6.3%+F27*28.9% -> 874.50406 | AU27: =I27*1.6%+J27*6.3%+K27*28.9% -> 817.82609 | AV27: =N27*1.6%+O27*6.3%+P27*28.9% -> 840.48264 | BJ27: 98937 | BK27: RES | BL27: 3 | BM27: 98944 | BN27: RES | BO27: 24 | BP27: 98953 | BQ27: RES | BR27: 3 | BS27: 98947RES | BT27: 2154.36 | BU27: 98948RES | BV27: 38070.58 | BW27: 99328COM | BX27: 36.49
A28: COM | B28: 98953 | C28: 50 | D28: 13050.16 | E28: 3614.09 | F28: 32151.25 | G28: 48815.5 | H28: 41 | I28: 8789.58 | J28: 4853.82 | K28: 33352.61 | L28: 46996.01 | M28: 57 | N28: 12603.62 | O28: 3657.67 | P28: 32836.75 | Q28: 49098.04 | R28: COM | S28: 99362 | U28: 0 | V28: 0 | W28: 0 | X28: 0 | Z28: 0 | AA28: 0 | AB28: 0 | AC28: 0 | AD28: 2 | AE28: 1279.48 | AF28: 0 | AG28: 0 | AH28: 1279.48 | AR28: COM | AS28: 98953 | AT28: =D28*1.6%+E28*6.3%+F28*28.9% -> 9728.2015 | AU28: =I28*1.6%+J28*6.3%+K28*28.9% -> 10085.328 | AV28: =N28*1.6%+O28*6.3%+P28*28.9% -> 9921.9119 | BJ28: 98938 | BK28: RES | BL28: 2 | BM28: 98947 | BN28: RES | BO28: 4 | BP28: 99323 | BQ28: RES | BR28: 3 | BS28: 98948COM | BT28: 4798.94 | BU28: 98951RES | BV28: 53675.04 | BW28: 99328RES | BX28: 2000.13
A29: COM | B29: 99301 | C29: 1 | D29: 20.35 | E29: 0 | F29: 0 | G29: 20.35 | H29: 1 | I29: 18.8 | J29: 0 | K29: 0 | L29: 18.8 | N29: 0 | O29: 0 | P29: 0 | Q29: 0 | R29: RES | S29: 98901 | T29: 589 | U29: 38253.11 | V29: 44977.29 | W29: 238476.84 | X29: 321707.24 | Y29: 498 | Z29: 40435.75 | AA29: 28924.97 | AB29: 179635.17 | AC29: 248995.89 | AD29: 522 | AE29: 57521.5 | AF29: 22647.33 | AG29: 149178.89 | AH29: 229347.72 | AR29: COM | AS29: 99301 | AT29: =D29*1.6%+E29*6.3%+F29*28.9% -> 0.3256 | AU29: =I29*1.6%+J29*6.3%+K29*28.9% -> 0.3008 | AV29: =N29*1.6%+O29*6.3%+P29*28.9% -> 0 | BJ29: 98942 | BK29: RES | BL29: 12 | BM29: 98948 | BN29: RES | BO29: 10 | BP29: 99324 | BQ29: RES | BR29: 18 | BS29: 98948RES | BT29: 10706.23 | BU29: 98952RES | BV29: 13076.06 | BW29: 99329RES | BX29: 1742.6
A30: COM | B30: 99323 | C30: 12 | D30: 3301.51 | E30: 2005.66 | F30: 13285.8 | G30: 18592.97 | H30: 13 | I30: 5364.72 | J30: 2983.8 | K30: 11826.47 | L30: 20174.99 | M30: 14 | N30: 5314.29 | O30: 2854.31 | P30: 13670.54 | Q30: 21839.14 | R30: RES | S30: 98902 | T30: 1008 | U30: 81855.85 | V30: 60638.51 | W30: 330033 | X30: 472527.36 | Y30: 858 | Z30: 64276.02 | AA30: 53391.06 | AB30: 252124.57 | AC30: 369791.65 | AD30: 907 | AE30: 92435.72 | AF30: 65324.62 | AG30: 205855.08 | AH30: 363615.42 | AR30: COM | AS30: 99323 | AT30: =D30*1.6%+E30*6.3%+F30*28.9% -> 4018.7769 | AU30: =I30*1.6%+J30*6.3%+K30*28.9% -> 3691.6647 | AV30: =N30*1.6%+O30*6.3%+P30*28.9% -> 4215.6362 | BJ30: 98944 | BK30: RES | BL30: 19 | BM30: 98951 | BN30: RES | BO30: 14 | BP30: 99328 | BQ30: RES | BR30: 5 | BS30: 98951COM | BT30: 2415.68 | BU30: 98953RES | BV30: 8175.12 | BW30: 99347COM | BX30: 48.8
A31: COM | B31: 99324 | C31: 9 | D31: 4186.32 | E31: 1962.71 | F31: 578.35 | G31: 6727.38 | H31: 12 | I31: 5551.96 | J31: 3528.3 | K31: 2105.84 | L31: 11186.1 | M31: 10 | N31: 5199.03 | O31: 4586.96 | P31: 302.19 | Q31: 10088.18 | R31: RES | S31: 98903 | T31: 294 | U31: 17434.78 | V31: 18813.07 | W31: 163147.59 | X31: 199395.44 | Y31: 242 | Z31: 17096.3 | AA31: 16027.23 | AB31: 117716.78 | AC31: 150840.31 | AD31: 301 | AE31: 40086.81 | AF31: 13260.21 | AG31: 102038.85 | AH31: 155385.87 | AR31: COM | AS31: 99324 | AT31: =D31*1.6%+E31*6.3%+F31*28.9% -> 357.775 | AU31: =I31*1.6%+J31*6.3%+K31*28.9% -> 919.70202 | AV31: =N31*1.6%+O31*6.3%+P31*28.9% -> 459.49587 | BJ31: 98947 | BK31: RES | BL31: 3 | BM31: 98952 | BN31: RES | BO31: 1 | BP31: 99329 | BQ31: RES | BR31: 1 | BS31: 98951RES | BT31: 16154.85 | BU31: 99323RES | BV31: 79.64 | BW31: 99347RES | BX31: 15464.26
A32: COM | B32: 99328 | C32: 19 | D32: 3342.68 | E32: 1741.95 | F32: 3649.65 | G32: 8734.28 | H32: 26 | I32: 7346.3 | J32: 1772.62 | K32: 2758.75 | L32: 11877.67 | M32: 27 | N32: 7153.16 | O32: 3646.71 | P32: 2190.25 | Q32: 12990.12 | R32: RES | S32: 98908 | T32: 395 | U32: 35363.61 | V32: 30261.57 | W32: 178966.39 | X32: 244591.57 | Y32: 345 | Z32: 38787.21 | AA32: 22567.48 | AB32: 121526.59 | AC32: 182881.28 | AD32: 351 | AE32: 38289.49 | AF32: 26422.27 | AG32: 96096.74 | AH32: 160808.5 | AR32: COM | AS32: 99328 | AT32: =D32*1.6%+E32*6.3%+F32*28.9% -> 1217.9746 | AU32: =I32*1.6%+J32*6.3%+K32*28.9% -> 1026.4946 | AV32: =N32*1.6%+O32*6.3%+P32*28.9% -> 977.17554 | BJ32: 98948 | BK32: RES | BL32: 6 | BM32: 98953 | BN32: RES | BO32: 12 | BP32: 99347 | BQ32: RES | BR32: 11 | BS32: 98952RES | BT32: 2756.47 | BU32: 99324RES | BV32: 21103.75 | BW32: 99360RES | BX32: 5036.73
A33: COM | B33: 99329 | C33: 2 | D33: 69.94 | E33: 106.74 | F33: 3117.39 | G33: 3294.07 | H33: 3 | I33: 95.76 | J33: 69.94 | K33: 3224.13 | L33: 3389.83 | M33: 2 | N33: 28.71 | O33: 13.7 | P33: 82.33 | Q33: 124.74 | R33: RES | S33: 98921 | T33: 41 | U33: 3022.86 | V33: 2527.28 | W33: 17893.13 | X33: 23443.27 | Y33: 44 | Z33: 3879.02 | AA33: 2457.61 | AB33: 17813.13 | AC33: 24149.76 | AD33: 41 | AE33: 3456.35 | AF33: 2698.38 | AG33: 16110.39 | AH33: 22265.12 | AR33: COM | AS33: 99329 | AT33: =D33*1.6%+E33*6.3%+F33*28.9% -> 908.76937 | AU33: =I33*1.6%+J33*6.3%+K33*28.9% -> 937.71195 | AV33: =N33*1.6%+O33*6.3%+P33*28.9% -> 25.11583 | BJ33: 98951 | BK33: RES | BL33: 14 | BM33: 99323 | BN33: RES | BO33: 1 | BP33: 99360 | BQ33: RES | BR33: 2 | BS33: 99323RES | BT33: 1182.93 | BU33: 99328COM | BV33: 5515.53 | BW33: 99361RES | BX33: 18964.11
A34: COM | B34: 99347 | C34: 14 | D34: 3874.1 | E34: 3163.9 | F34: 9004.18 | G34: 16042.18 | H34: 7 | I34: 2194.95 | J34: 1949.38 | K34: 7556.75 | L34: 11701.08 | M34: 9 | N34: 2898.46 | O34: 2057.15 | P34: 9375.45 | Q34: 14331.06 | R34: RES | S34: 98923 | T34: 13 | U34: 1347.46 | V34: 1359.94 | W34: 4851.08 | X34: 7558.48 | Y34: 11 | Z34: 1372.75 | AA34: 1195.89 | AB34: 4860.43 | AC34: 7429.07 | AD34: 10 | AE34: 1251.85 | AF34: 982.13 | AG34: 2254.65 | AH34: 4488.63 | AR34: COM | AS34: 99347 | AT34: =D34*1.6%+E34*6.3%+F34*28.9% -> 2863.5193 | AU34: =I34*1.6%+J34*6.3%+K34*28.9% -> 2341.8309 | AV34: =N34*1.6%+O34*6.3%+P34*28.9% -> 2885.4809 | BJ34: 98952 | BK34: RES | BL34: 2 | BM34: 99324 | BN34: RES | BO34: 22 | BP34: 99361 | BQ34: RES | BR34: 6 | BS34: 99324RES | BT34: 7622.93 | BU34: 99328RES | BV34: 87704.41 | BW34: 99362COM | BX34: 3304.54
A35: COM | B35: 99348 | C35: 3 | D35: 142.89 | E35: 156.57 | F35: 343.41 | G35: 642.87 | H35: 4 | I35: 221.3 | J35: 222.47 | K35: 908.77 | L35: 1352.54 | M35: 2 | N35: 81.51 | O35: 82.07 | P35: 175.51 | Q35: 339.09 | R35: RES | S35: 98930 | T35: 227 | U35: 16058.46 | V35: 13148.72 | W35: 63681.49 | X35: 92888.67 | Y35: 200 | Z35: 15309.08 | AA35: 11447.31 | AB35: 62716.9 | AC35: 89473.29 | AD35: 200 | AE35: 18303.96 | AF35: 10563.99 | AG35: 63637.53 | AH35: 92505.48 | AR35: COM | AS35: 99348 | AT35: =D35*1.6%+E35*6.3%+F35*28.9% -> 111.39564 | AU35: =I35*1.6%+J35*6.3%+K35*28.9% -> 280.19094 | AV35: =N35*1.6%+O35*6.3%+P35*28.9% -> 57.19696 | BJ35: 99323 | BK35: RES | BL35: 4 | BM35: 99328 | BN35: RES | BO35: 24 | BP35: 99362 | BQ35: RES | BR35: 88 | BS35: 99328COM | BT35: 10077.52 | BU35: 99329RES | BV35: 1642.63 | BW35: 99362RES | BX35: 85165.72
A36: COM | B36: 99360 | C36: 14 | D36: 9125.62 | E36: 73.46 | F36: 96.79 | G36: 9295.87 | H36: 4 | I36: 535.54 | J36: 0 | K36: 44.64 | L36: 580.18 | M36: 14 | N36: 1552.65 | O36: 345.69 | P36: 0 | Q36: 1898.34 | R36: RES | S36: 98932 | T36: 150 | U36: 12167.36 | V36: 9181.57 | W36: 60531.79 | X36: 81880.72 | Y36: 141 | Z36: 14292.59 | AA36: 8563.88 | AB36: 54583.43 | AC36: 77439.9 | AD36: 146 | AE36: 14464.26 | AF36: 9494.74 | AG36: 51085.15 | AH36: 75044.15 | AR36: COM | AS36: 99360 | AT36: =D36*1.6%+E36*6.3%+F36*28.9% -> 178.61021 | AU36: =I36*1.6%+J36*6.3%+K36*28.9% -> 21.4696 | AV36: =N36*1.6%+O36*6.3%+P36*28.9% -> 46.62087 | BJ36: 99324 | BK36: RES | BL36: 11 | BM36: 99329 | BN36: RES | BO36: 2 | BP36: 99363 | BQ36: RES | BR36: 1 | BS36: 99328RES | BT36: 11449.86 | BU36: 99347RES | BV36: 21990 | BW36: 99363RES | BX36: 23.73
A37: COM | B37: 99361 | C37: 13 | D37: 1148.25 | E37: 938.11 | F37: 1135.62 | G37: 3221.98 | H37: 9 | I37: 673.35 | J37: 467.98 | K37: 907.93 | L37: 2049.26 | M37: 11 | N37: 846.5 | O37: 285.14 | P37: 326.13 | Q37: 1457.77 | R37: RES | S37: 98933 | T37: 16 | U37: 1988.35 | V37: 1587.49 | W37: 13720.03 | X37: 17295.87 | Y37: 18 | Z37: 2129.29 | AA37: 1669.52 | AB37: 14185.12 | AC37: 17983.93 | AD37: 18 | AE37: 2120.73 | AF37: 1644.03 | AG37: 13393.26 | AH37: 17158.02 | AR37: COM | AS37: 99361 | AT37: =D37*1.6%+E37*6.3%+F37*28.9% -> 405.66711 | AU37: =I37*1.6%+J37*6.3%+K37*28.9% -> 302.64811 | AV37: =N37*1.6%+O37*6.3%+P37*28.9% -> 125.75939 | BJ37: 99328 | BK37: RES | BL37: 8 | BM37: 99347 | BN37: RES | BO37: 3 | BS37: 99347RES | BT37: 4383.05 | BU37: 99348RES | BV37: 3545.56
A38: COM | B38: 99362 | C38: 104 | D38: 90352.96 | E38: 9990.63 | F38: 20830.18 | G38: 121173.77 | H38: 109 | I38: 125195.17 | J38: 8058.01 | K38: 15888.25 | L38: 149141.43 | M38: 151 | N38: 123314.84 | O38: 21733.6 | P38: 12375.92 | Q38: 157424.36 | R38: RES | S38: 98935 | T38: 68 | U38: 1371.65 | V38: 6268.25 | W38: 42765.93 | X38: 50405.83 | Y38: 63 | Z38: 5937 | AA38: 4713.9 | AB38: 37545.03 | AC38: 48195.93 | AD38: 87 | AE38: 15162.96 | AF38: 1119.97 | AG38: 41570.65 | AH38: 57853.58 | AR38: COM | AS38: 99362 | AT38: =D38*1.6%+E38*6.3%+F38*28.9% -> 8094.9791 | AU38: =I38*1.6%+J38*6.3%+K38*28.9% -> 7102.4816 | AV38: =N38*1.6%+O38*6.3%+P38*28.9% -> 6918.8951 | BJ38: 99347 | BK38: RES | BL38: 3 | BM38: 99348 | BN38: RES | BO38: 3 | BS38: 99361RES | BT38: 1026.27 | BU38: 99361RES | BV38: 27746.54
A39: COM | B39: 99363 | C39: 4 | D39: 400.19 | E39: 80.22 | F39: 180.36 | G39: 660.77 | H39: 1 | I39: 0 | J39: 94.34 | K39: 101.58 | L39: 195.92 | M39: 2 | N39: 19001.44 | O39: 119.6 | P39: 15.92 | Q39: 19136.96 | R39: RES | S39: 98936 | T39: 57 | U39: 6168.56 | V39: 6604.11 | W39: 45444.86 | X39: 58217.53 | Y39: 48 | Z39: 5092.57 | AA39: 4463.2 | AB39: 34324.14 | AC39: 43879.91 | AD39: 42 | AE39: 5127.28 | AF39: 3183.16 | AG39: 22124.15 | AH39: 30434.59 | AR39: COM | AS39: 99363 | AT39: =D39*1.6%+E39*6.3%+F39*28.9% -> 63.58094 | AU39: =I39*1.6%+J39*6.3%+K39*28.9% -> 35.30004 | AV39: =N39*1.6%+O39*6.3%+P39*28.9% -> 316.15872 | BJ39: 99361 | BK39: RES | BL39: 1 | BM39: 99361 | BN39: RES | BO39: 3 | BS39: 99362COM | BT39: 2352.5 | BU39: 99362COM | BV39: 1503.01
A40: COM | B40: WA | D40: 0 | E40: 0 | F40: 0 | G40: 0 | H40: 1 | I40: 25.88 | J40: 0 | K40: 0 | L40: 25.88 | N40: 0 | O40: 0 | P40: 0 | Q40: 0 | R40: RES | S40: 98937 | T40: 32 | U40: 2902.67 | V40: 2841.02 | W40: 12332.03 | X40: 18075.72 | Y40: 28 | Z40: 2438.11 | AA40: 1720.52 | AB40: 8245.01 | AC40: 12403.64 | AD40: 29 | AE40: 2774.87 | AF40: 1543.12 | AG40: 6968.35 | AH40: 11286.34 | AR40: COM | AS40: WA | AT40: =D40*1.6%+E40*6.3%+F40*28.9% -> 0 | AU40: =I40*1.6%+J40*6.3%+K40*28.9% -> 0.41408 | AV40: =N40*1.6%+O40*6.3%+P40*28.9% -> 0 | BJ40: 99362 | BK40: RES | BL40: 51 | BM40: 99362 | BN40: RES | BO40: 76 | BS40: 99362RES | BT40: 23877.17 | BU40: 99362RES | BV40: 93400.7
A41: RES | B41: 98603 | C41: 1 | D41: 252.68 | E41: 283.87 | F41: 177.01 | G41: 713.56 | H41: 1 | I41: 76.99 | J41: 252.68 | K41: 205.88 | L41: 535.55 | M41: 1 | N41: 185.54 | O41: 76.99 | P41: 203.56 | Q41: 466.09 | R41: RES | S41: 98938 | T41: 33 | U41: 4312.54 | V41: 2931.17 | W41: 25920.79 | X41: 33164.5 | Y41: 33 | Z41: 4553.28 | AA41: 2709.88 | AB41: 21850.22 | AC41: 29113.38 | AD41: 30 | AE41: 4481.36 | AF41: 2581.43 | AG41: 13744.52 | AH41: 20807.31 | AR41: RES | AS41: 98603 | AT41: =D41*1.6%+E41*6.3%+F41*28.9% -> 73.08258 | AU41: =I41*1.6%+J41*6.3%+K41*28.9% -> 76.65 | AV41: =N41*1.6%+O41*6.3%+P41*28.9% -> 66.64785 | BG41: TOTAL | BL41: =SUM(BL5:BL40) -> 379 | BO41: =SUM(BO5:BO40) -> 460 | BR41: =SUM(BR5:BR40) -> 455 | BT41: =SUM(BT5:BT40) -> 467677.26 | BV41: =SUM(BV5:BV40) -> 1070769.6 | BX41: =SUM(BX5:BX40) -> 455286.65 | BZ41: =SUM(BZ5:BZ40) -> 17744.99 | CB41: =SUM(CB5:CB40) -> 10282.18 | CD41: =SUM(CD5:CD40) -> 11530.91
A42: RES | B42: 98901 | C42: 2601 | D42: 204461.89 | E42: 187582.02 | F42: 1145755.5 | G42: 1537799.4 | H42: 2511 | I42: 238391.86 | J42: 135887.27 | K42: 1005090.4 | L42: 1379369.5 | M42: 2683 | N42: 324799.11 | O42: 124985.88 | P42: 902111.59 | Q42: 1351896.6 | R42: RES | S42: 98939 | T42: 10 | U42: 849.66 | V42: 750.01 | W42: 6410.95 | X42: 8010.62 | Y42: 11 | Z42: 979.13 | AA42: 799.32 | AB42: 7060.37 | AC42: 8838.82 | AD42: 12 | AE42: 1138.37 | AF42: 846.97 | AG42: 5725.89 | AH42: 7711.23 | AR42: RES | AS42: 98901 | AT42: =D42*1.6%+E42*6.3%+F42*28.9% -> 346212.41 | AU42: =I42*1.6%+J42*6.3%+K42*28.9% -> 302846.28 | AV42: =N42*1.6%+O42*6.3%+P42*28.9% -> 273781.15
A43: RES | B43: 98902 | C43: 5035 | D43: 433804.72 | E43: 261648.42 | F43: 1297628.2 | G43: 1993081.3 | H43: 4368 | I43: 366523.26 | J43: 250473.87 | K43: 1104556.6 | L43: 1721553.7 | M43: 5167 | N43: 567506.67 | O43: 317833.17 | P43: 951442.95 | Q43: 1836782.8 | R43: RES | S43: 98942 | T43: 135 | U43: 12693.98 | V43: 11913.39 | W43: 65784.35 | X43: 90391.72 | Y43: 119 | Z43: 13287.98 | AA43: 8108.16 | AB43: 54119.76 | AC43: 75515.9 | AD43: 112 | AE43: 12941.1 | AF43: 8977.79 | AG43: 38571.26 | AH43: 60490.15 | AR43: RES | AS43: 98902 | AT43: =D43*1.6%+E43*6.3%+F43*28.9% -> 398439.27 | AU43: =I43*1.6%+J43*6.3%+K43*28.9% -> 340861.07 | AV43: =N43*1.6%+O43*6.3%+P43*28.9% -> 304070.61
A44: RES | B44: 98903 | C44: 2069 | D44: 191275.29 | E44: 140024.7 | F44: 889077.21 | G44: 1220377.2 | H44: 1851 | I44: 214187.5 | J44: 124338.69 | K44: 765526.59 | L44: 1104052.8 | M44: 2226 | N44: 322026.1 | O44: 122500.91 | P44: 729022.75 | Q44: 1173549.8 | R44: RES | S44: 98944 | T44: 474 | U44: 43197.54 | V44: 30544.22 | W44: 198276.19 | X44: 272017.95 | Y44: 473 | Z44: 47268.08 | AA44: 31843.13 | AB44: 192946.35 | AC44: 272057.56 | AD44: 461 | AE44: 47832.69 | AF44: 33442.61 | AG44: 188876.58 | AH44: 270151.88 | AR44: RES | AS44: 98903 | AT44: =D44*1.6%+E44*6.3%+F44*28.9% -> 268825.27 | AU44: =I44*1.6%+J44*6.3%+K44*28.9% -> 232497.52 | AV44: =N44*1.6%+O44*6.3%+P44*28.9% -> 223557.55
A45: RES | B45: 98904 | I45: 0 | J45: 0 | K45: 0 | L45: 0 | N45: 0 | O45: 0 | P45: 0 | Q45: 0 | R45: RES | S45: 98947 | T45: 66 | U45: 11014.83 | V45: 8771.84 | W45: 42373.68 | X45: 62160.35 | Y45: 54 | Z45: 5023.19 | AA45: 5658.84 | AB45: 35554.29 | AC45: 46236.32 | AD45: 42 | AE45: 3824.56 | AF45: 2329.09 | AG45: 25981.93 | AH45: 32135.58 | AR45: RES | AS45: 98904 | AT45: =D45*1.6%+E45*6.3%+F45*28.9% -> 0 | AU45: =I45*1.6%+J45*6.3%+K45*28.9% -> 0 | AV45: =N45*1.6%+O45*6.3%+P45*28.9% -> 0
A46: RES | B46: 98908 | C46: 3908 | D46: 403172.43 | E46: 228934.95 | F46: 1038748.1 | G46: 1670855.5 | H46: 3997 | I46: 522167.16 | J46: 218467.24 | K46: 868033.31 | L46: 1608667.7 | M46: 4069 | N46: 514554.7 | O46: 274709.43 | P46: 709870.98 | Q46: 1499135.1 | R46: RES | S46: 98948 | T46: 392 | U46: 39037.82 | V46: 29016.15 | W46: 209092.1 | X46: 277146.07 | Y46: 325 | Z46: 16680.6 | AA46: 28377.67 | AB46: 206395.84 | AC46: 251454.11 | AD46: 399 | AE46: 43290.43 | AF46: 38976.86 | AG46: 205320.34 | AH46: 287587.63 | AR46: RES | AS46: 98908 | AT46: =D46*1.6%+E46*6.3%+F46*28.9% -> 321071.87 | AU46: =I46*1.6%+J46*6.3%+K46*28.9% -> 272979.74 | AV46: =N46*1.6%+O46*6.3%+P46*28.9% -> 230692.28
A47: RES | B47: 98920 | D47: 0 | E47: 0 | F47: 0 | G47: 0 | H47: 1 | I47: 90.35 | J47: 0 | K47: 0 | L47: 90.35 | M47: 1 | N47: 72.33 | O47: 90.35 | P47: 0 | Q47: 162.68 | R47: RES | S47: 98951 | T47: 320 | U47: 33654.08 | V47: 26873.52 | W47: 223604.93 | X47: 284132.53 | Y47: 330 | Z47: 38260.32 | AA47: 25900.73 | AB47: 205138.29 | AC47: 269299.34 | AD47: 336 | AE47: 43793.29 | AF47: 28830.61 | AG47: 204127.06 | AH47: 276750.96 | AR47: RES | AS47: 98920 | AT47: =D47*1.6%+E47*6.3%+F47*28.9% -> 0 | AU47: =I47*1.6%+J47*6.3%+K47*28.9% -> 1.4456 | AV47: =N47*1.6%+O47*6.3%+P47*28.9% -> 6.84933
A48: RES | B48: 98921 | C48: 96 | D48: 8569.13 | E48: 6193.99 | F48: 60851.98 | G48: 75615.1 | H48: 96 | I48: 9765.45 | J48: 6034.62 | K48: 59547.13 | L48: 75347.2 | M48: 90 | N48: 8795.42 | O48: 6633.89 | P48: 56702.21 | Q48: 72131.52 | R48: RES | S48: 98952 | T48: 34 | U48: 3703.9 | V48: 3652.37 | W48: 27252.64 | X48: 34608.91 | Y48: 37 | Z48: 4098.7 | AA48: 3252.54 | AB48: 28425.09 | AC48: 35776.33 | AD48: 34 | AE48: 3695.76 | AF48: 2990.92 | AG48: 20102.03 | AH48: 26788.71 | AR48: RES | AS48: 98921 | AT48: =D48*1.6%+E48*6.3%+F48*28.9% -> 18113.55 | AU48: =I48*1.6%+J48*6.3%+K48*28.9% -> 17745.549 | AV48: =N48*1.6%+O48*6.3%+P48*28.9% -> 16945.6
A49: RES | B49: 98923 | C49: 119 | D49: 12551.14 | E49: 10688.04 | F49: 54747.45 | G49: 77986.63 | H49: 117 | I49: 13781.3 | J49: 8564.78 | K49: 44460.43 | L49: 66806.51 | M49: 111 | N49: 14751.21 | O49: 6929.32 | P49: 37919.98 | Q49: 59600.51 | R49: RES | S49: 98953 | T49: 75 | U49: 7958.43 | V49: 5442.62 | W49: 31599.67 | X49: 45000.72 | Y49: 76 | Z49: 10183.7 | AA49: 5658.24 | AB49: 29704.66 | AC49: 45546.6 | AD49: 83 | AE49: 9747.01 | AF49: 7364.65 | AG49: 30237.33 | AH49: 47348.99 | AR49: RES | AS49: 98923 | AT49: =D49*1.6%+E49*6.3%+F49*28.9% -> 16696.178 | AU49: =I49*1.6%+J49*6.3%+K49*28.9% -> 13609.146 | AV49: =N49*1.6%+O49*6.3%+P49*28.9% -> 11631.441
A50: RES | B50: 98930 | C50: 1040 | D50: 93489.53 | E50: 73455.74 | F50: 382061.82 | G50: 549007.09 | H50: 1004 | I50: 98661.26 | J50: 62330.9 | K50: 370712.74 | L50: 531704.9 | M50: 1022 | N50: 125341.22 | O50: 54440.86 | P50: 340103.8 | Q50: 519885.88 | R50: RES | S50: 99323 | T50: 15 | U50: 1605.01 | V50: 852.84 | W50: 1522.66 | X50: 3980.51 | Y50: 19 | Z50: 2339.69 | AA50: 1085.91 | AB50: 1458.38 | AC50: 4883.98 | AD50: 26 | AE50: 5770.49 | AF50: 1412.75 | AG50: 1247.32 | AH50: 8430.56 | AR50: RES | AS50: 98930 | AT50: =D50*1.6%+E50*6.3%+F50*28.9% -> 116539.41 | AU50: =I50*1.6%+J50*6.3%+K50*28.9% -> 112641.41 | AV50: =N50*1.6%+O50*6.3%+P50*28.9% -> 103725.23
A51: RES | B51: 98932 | C51: 545 | D51: 56078.69 | E51: 37032.12 | F51: 241590.48 | G51: 334701.29 | H51: 548 | I51: 70534.91 | J51: 37285.81 | K51: 222151.71 | L51: 329972.43 | M51: 559 | N51: 69739.73 | O51: 42073.12 | P51: 207109.75 | Q51: 318922.6 | R51: RES | S51: 99324 | T51: 76 | U51: 4713.1 | V51: 2806.7 | W51: 7030.75 | X51: 14550.55 | Y51: 86 | Z51: 6931.83 | AA51: 3055.73 | AB51: 7957.49 | AC51: 17945.05 | AD51: 93 | AE51: 8095.32 | AF51: 3649.19 | AG51: 7279.02 | AH51: 19023.53 | AR51: RES | AS51: 98932 | AT51: =D51*1.6%+E51*6.3%+F51*28.9% -> 73049.931 | AU51: =I51*1.6%+J51*6.3%+K51*28.9% -> 67679.409 | AV51: =N51*1.6%+O51*6.3%+P51*28.9% -> 63621.16
A52: RES | B52: 98933 | C52: 92 | D52: 11557.96 | E52: 5996.07 | F52: 38925.07 | G52: 56479.1 | H52: 96 | I52: 11772.76 | J52: 6272.96 | K52: 38448.65 | L52: 56494.37 | M52: 94 | N52: 11026.52 | O52: 4945.54 | P52: 23102.01 | Q52: 39074.07 | R52: RES | S52: 99328 | T52: 54 | U52: 3488.3 | V52: 1915.84 | W52: 4736.98 | X52: 10141.12 | Y52: 49 | Z52: 4067.09 | AA52: 2027.87 | AB52: 3742.09 | AC52: 9837.05 | AD52: 46 | AE52: 3295.65 | AF52: 2142.43 | AG52: 3054.41 | AH52: 8492.49 | AR52: RES | AS52: 98933 | AT52: =D52*1.6%+E52*6.3%+F52*28.9% -> 11812.025 | AU52: =I52*1.6%+J52*6.3%+K52*28.9% -> 11695.22 | AV52: =N52*1.6%+O52*6.3%+P52*28.9% -> 7164.4742
A53: RES | B53: 98935 | C53: 269 | D53: 8328.67 | E53: 26854.94 | F53: 168798.59 | G53: 203982.2 | H53: 242 | I53: 25595.98 | J53: 15878.97 | K53: 145379.91 | L53: 186854.86 | M53: 343 | N53: 59923.94 | O53: 4593.63 | P53: 153427 | Q53: 217944.57 | R53: RES | S53: 99329 | U53: 0 | V53: 0 | W53: 0 | X53: 0 | Z53: 0 | AA53: 0 | AB53: 0 | AC53: 0 | AE53: 0 | AF53: 0 | AG53: 0 | AH53: 0 | AR53: RES | AS53: 98935 | AT53: =D53*1.6%+E53*6.3%+F53*28.9% -> 50607.912 | AU53: =I53*1.6%+J53*6.3%+K53*28.9% -> 43424.705 | AV53: =N53*1.6%+O53*6.3%+P53*28.9% -> 45588.585
A54: RES | B54: 98936 | C54: 500 | D54: 55738.05 | E54: 41148.47 | F54: 255412.73 | G54: 352299.25 | H54: 491 | I54: 54204.52 | J54: 33299.03 | K54: 196948.24 | L54: 284451.79 | M54: 510 | N54: 66805.59 | O54: 27914.24 | P54: 164910.37 | Q54: 259630.2 | R54: RES | S54: 99347 | T54: 31 | U54: 2124.04 | V54: 2343.04 | W54: 17056.56 | X54: 21523.64 | Y54: 19 | Z54: 1620.74 | AA54: 1009.17 | AB54: 10174.19 | AC54: 12804.1 | AD54: 19 | AE54: 1614.16 | AF54: 1281.24 | AG54: 7711.38 | AH54: 10606.78 | AR54: RES | AS54: 98936 | AT54: =D54*1.6%+E54*6.3%+F54*28.9% -> 77298.441 | AU54: =I54*1.6%+J54*6.3%+K54*28.9% -> 59883.153 | AV54: =N54*1.6%+O54*6.3%+P54*28.9% -> 50486.583
A55: RES | B55: 98937 | C55: 426 | D55: 46904.41 | E55: 34453.05 | F55: 170952.69 | G55: 252310.15 | H55: 420 | I55: 47535.89 | J55: 30212.61 | K55: 155243.1 | L55: 232991.6 | M55: 415 | N55: 55331.67 | O55: 24115.75 | P55: 113575.59 | Q55: 193023.01 | R55: RES | S55: 99348 | T55: 8 | U55: 667.42 | V55: 453.94 | W55: 1302.35 | X55: 2423.71 | Y55: 7 | Z55: 770.76 | AA55: 392.44 | AB55: 863.06 | AC55: 2026.26 | AD55: 7 | AE55: 632.56 | AF55: 387.96 | AG55: 578.1 | AH55: 1598.62 | AR55: RES | AS55: 98937 | AT55: =D55*1.6%+E55*6.3%+F55*28.9% -> 52326.34 | AU55: =I55*1.6%+J55*6.3%+K55*28.9% -> 47529.225 | AV55: =N55*1.6%+O55*6.3%+P55*28.9% -> 35227.944
A56: RES | B56: 98938 | C56: 192 | D56: 27450.38 | E56: 15981.03 | F56: 119675.78 | G56: 163107.19 | H56: 188 | I56: 31328.43 | J56: 17181.46 | K56: 110707.16 | L56: 159217.05 | M56: 180 | N56: 29123.36 | O56: 17014.69 | P56: 91843.31 | Q56: 137981.36 | R56: RES | S56: 99350 | T56: 2 | U56: 0 | V56: 236.94 | W56: 1497.13 | X56: 1734.07 | Y56: 2 | Z56: 247.88 | AA56: 236.94 | AB56: 1195.14 | AC56: 1679.96 | AD56: 2 | AE56: 536.46 | AF56: 0 | AG56: 1336.9 | AH56: 1873.36 | AR56: RES | AS56: 98938 | AT56: =D56*1.6%+E56*6.3%+F56*28.9% -> 36032.311 | AU56: =I56*1.6%+J56*6.3%+K56*28.9% -> 33578.056 | AV56: =N56*1.6%+O56*6.3%+P56*28.9% -> 28080.616
A57: RES | B57: 98939 | C57: 32 | D57: 2984.31 | E57: 2742.61 | F57: 29973.6 | G57: 35700.52 | H57: 28 | I57: 2576.59 | J57: 1952.73 | K57: 19199.11 | L57: 23728.43 | M57: 32 | N57: 3487.55 | O57: 2028.84 | P57: 17729.95 | Q57: 23246.34 | R57: RES | S57: 99360 | T57: 2 | U57: 159.29 | V57: 136.19 | W57: 973.03 | X57: 1268.51 | Y57: 2 | Z57: 257.62 | AA57: 132.31 | AB57: 851.23 | AC57: 1241.16 | AD57: 2 | AE57: 213.55 | AF57: 283.84 | AG57: 983.54 | AH57: 1480.93 | AR57: RES | AS57: 98939 | AT57: =D57*1.6%+E57*6.3%+F57*28.9% -> 8882.9038 | AU57: =I57*1.6%+J57*6.3%+K57*28.9% -> 5712.7902 | AV57: =N57*1.6%+O57*6.3%+P57*28.9% -> 5307.5733
A58: RES | B58: 98942 | C58: 1751 | D58: 193937.54 | E58: 132145.78 | F58: 650312.12 | G58: 976395.44 | H58: 1736 | I58: 226971.18 | J58: 110148.3 | K58: 586126.66 | L58: 923246.14 | M58: 1700 | N58: 227903.54 | O58: 117198.73 | P58: 522234.11 | Q58: 867336.38 | R58: RES | S58: 99361 | T58: 11 | U58: 902.95 | V58: 1285.46 | W58: 5436.19 | X58: 7624.6 | Y58: 14 | Z58: 1030.93 | AA58: 883.35 | AB58: 5641.75 | AC58: 7556.03 | AD58: 10 | AE58: 852.33 | AF58: 588.48 | AG58: 2716.19 | AH58: 4157 | AR58: RES | AS58: 98942 | AT58: =D58*1.6%+E58*6.3%+F58*28.9% -> 199368.39 | AU58: =I58*1.6%+J58*6.3%+K58*28.9% -> 179961.49 | AV58: =N58*1.6%+O58*6.3%+P58*28.9% -> 161955.63
A59: RES | B59: 98944 | C59: 1887 | D59: 194405.41 | E59: 118173.39 | F59: 678485.29 | G59: 991064.09 | H59: 1990 | I59: 233071.31 | J59: 122824.21 | K59: 643283.47 | L59: 999178.99 | M59: 1959 | N59: 237363.63 | O59: 134055.71 | P59: 597726.16 | Q59: 969145.5 | R59: RES | S59: 99362 | T59: 426 | U59: 18532.26 | V59: 21651.65 | W59: 73696.87 | X59: 113880.78 | Y59: 429 | Z59: 32131.88 | AA59: 16884.34 | AB59: 48463.87 | AC59: 97480.09 | AD59: 533 | AE59: 60846.31 | AF59: 12414.23 | AG59: 30368.57 | AH59: 103629.11 | AR59: RES | AS59: 98944 | AT59: =D59*1.6%+E59*6.3%+F59*28.9% -> 206637.66 | AU59: =I59*1.6%+J59*6.3%+K59*28.9% -> 197375.99 | AV59: =N59*1.6%+O59*6.3%+P59*28.9% -> 184986.19
A60: RES | B60: 98947 | C60: 358 | D60: 36914.74 | E60: 33495.09 | F60: 146256.47 | G60: 216666.3 | H60: 353 | I60: 33949.47 | J60: 22426.52 | K60: 132339.52 | L60: 188715.51 | M60: 333 | N60: 36350.22 | O60: 18573.53 | P60: 112441.19 | Q60: 167364.94 | R60: RES | S60: 99363 | T60: 4 | U60: 391.53 | V60: 333.8 | W60: 405.65 | X60: 1130.98 | Y60: 3 | Z60: 0 | AA60: 286.56 | AB60: 734.61 | AC60: 1021.17 | AD60: 4 | AE60: 330.21 | AF60: 279.93 | AG60: 416.45 | AH60: 1026.59 | AR60: RES | AS60: 98947 | AT60: =D60*1.6%+E60*6.3%+F60*28.9% -> 44968.946 | AU60: =I60*1.6%+J60*6.3%+K60*28.9% -> 40202.184 | AV60: =N60*1.6%+O60*6.3%+P60*28.9% -> 34247.24
A61: RES | B61: 98948 | C61: 1238 | D61: 131967.61 | E61: 85749.94 | F61: 571484.81 | G61: 789202.36 | H61: 968 | I61: 58475.91 | J61: 81163.82 | K61: 540916.69 | L61: 680556.42 | M61: 1262 | N61: 156122.79 | O61: 115042.28 | P61: 529640.63 | Q61: 800805.7 | R61: TOTAL | T61: =SUM(T5:T60) -> 5109 | U61: =SUM(U5:U60) -> 414012.06 | V61: =SUM(V5:V60) -> 355117.28 | W61: =SUM(W5:W60) -> 2160954.8 | X61: =SUM(X5:X60) -> 2930084.1 | Y61: =SUM(Y5:Y60) -> 4632 | Z61: =SUM(Z5:Z60) -> 404744.29 | AA61: =SUM(AA5:AA60) -> 301443.06 | ... AH61: =SUM(AH5:AH60) -> 2474229.2 | AR61: RES | AS61: 98948 | AT61: =D61*1.6%+E61*6.3%+F61*28.9% -> 172672.84 | AU61: =I61*1.6%+J61*6.3%+K61*28.9% -> 162373.86 | AV61: =N61*1.6%+O61*6.3%+P61*28.9% -> 162811.77
A62: RES | B62: 98951 | C62: 1095 | D62: 123730.64 | E62: 90667.04 | F62: 678563 | G62: 892960.68 | H62: 1085 | I62: 133546.55 | J62: 79525.89 | K62: 577543.14 | L62: 790615.58 | M62: 1098 | N62: 156619.98 | O62: 88297.26 | P62: 550692.33 | Q62: 795609.57 | AR62: RES | AS62: 98951 | AT62: =D62*1.6%+E62*6.3%+F62*28.9% -> 203796.42 | AU62: =I62*1.6%+J62*6.3%+K62*28.9% -> 174056.84 | AV62: =N62*1.6%+O62*6.3%+P62*28.9% -> 167218.73
A63: RES | B63: 98952 | C63: 90 | D63: 9767.02 | E63: 7706.43 | F63: 74433.18 | G63: 91906.63 | H63: 91 | I63: 10000.88 | J63: 7990.11 | K63: 75234.07 | L63: 93225.06 | M63: 85 | N63: 9685.58 | O63: 7157.59 | P63: 60892.44 | Q63: 77735.61 | AR63: RES | AS63: 98952 | AT63: =D63*1.6%+E63*6.3%+F63*28.9% -> 22152.966 | AU63: =I63*1.6%+J63*6.3%+K63*28.9% -> 22406.037 | AV63: =N63*1.6%+O63*6.3%+P63*28.9% -> 18203.813
A64: RES | B64: 98953 | C64: 698 | D64: 85722.78 | E64: 45525.81 | F64: 222234.75 | G64: 353483.34 | H64: 749 | I64: 119858.61 | J64: 48415.41 | K64: 203989.32 | L64: 372263.34 | M64: 719 | N64: 100874.43 | O64: 60522.53 | P64: 172552.57 | Q64: 333949.53 | AR64: RES | AS64: 98953 | AT64: =D64*1.6%+E64*6.3%+F64*28.9% -> 68465.533 | AU64: =I64*1.6%+J64*6.3%+K64*28.9% -> 63920.822 | AV64: =N64*1.6%+O64*6.3%+P64*28.9% -> 55294.603
A65: RES | B65: 99301 | C65: 1 | D65: 157.44 | E65: 101.89 | F65: 0 | G65: 259.33 | H65: 1 | I65: 243.05 | J65: 157.44 | K65: 101.89 | L65: 502.38 | N65: 0 | O65: 0 | P65: 0 | Q65: 0 | AR65: RES | AS65: 99301 | AT65: =D65*1.6%+E65*6.3%+F65*28.9% -> 8.93811 | AU65: =I65*1.6%+J65*6.3%+K65*28.9% -> 43.25373 | AV65: =N65*1.6%+O65*6.3%+P65*28.9% -> 0
A66: RES | B66: 99323 | C66: 250 | D66: 32919.22 | E66: 13477.09 | F66: 33549.37 | G66: 79945.68 | H66: 255 | I66: 41251.26 | J66: 15768.37 | K66: 21676.31 | L66: 78695.94 | M66: 261 | N66: 43829.19 | O66: 18509.16 | P66: 16287.02 | Q66: 78625.37 | AR66: RES | AS66: 99323 | AT66: =D66*1.6%+E66*6.3%+F66*28.9% -> 11071.532 | AU66: =I66*1.6%+J66*6.3%+K66*28.9% -> 7917.8811 | AV66: =N66*1.6%+O66*6.3%+P66*28.9% -> 6574.2929
A67: RES | B67: 99324 | C67: 554 | D67: 43797.91 | E67: 21888.81 | F67: 39318.5 | G67: 105005.22 | H67: 569 | I67: 52384.56 | J67: 21512.73 | K67: 31104.17 | L67: 105001.46 | M67: 595 | N67: 58447.59 | O67: 22764.66 | P67: 22777.34 | Q67: 103989.59 | AR67: RES | AS67: 99324 | AT67: =D67*1.6%+E67*6.3%+F67*28.9% -> 13442.808 | AU67: =I67*1.6%+J67*6.3%+K67*28.9% -> 11182.56 | AV67: =N67*1.6%+O67*6.3%+P67*28.9% -> 8951.9863
A68: RES | B68: 99328 | C68: 373 | D68: 33097.33 | E68: 21090.56 | F68: 55428.31 | G68: 109616.2 | H68: 369 | I68: 45811.31 | J68: 19033.69 | K68: 42392.41 | L68: 107237.41 | M68: 372 | N68: 38620.28 | O68: 21915.41 | P68: 26300.21 | Q68: 86835.9 | AR68: RES | AS68: 99328 | AT68: =D68*1.6%+E68*6.3%+F68*28.9% -> 17877.044 | AU68: =I68*1.6%+J68*6.3%+K68*28.9% -> 14183.51 | AV68: =N68*1.6%+O68*6.3%+P68*28.9% -> 9599.356
A69: RES | B69: 99329 | C69: 26 | D69: 3069.37 | E69: 2137.05 | F69: 1689.54 | G69: 6895.96 | H69: 22 | I69: 2553.98 | J69: 1255.8 | K69: 1195.57 | L69: 5005.35 | M69: 22 | N69: 2164.15 | O69: 1086.21 | P69: 362.47 | Q69: 3612.83 | AR69: RES | AS69: 99329 | AT69: =D69*1.6%+E69*6.3%+F69*28.9% -> 672.02113 | AU69: =I69*1.6%+J69*6.3%+K69*28.9% -> 465.49881 | AV69: =N69*1.6%+O69*6.3%+P69*28.9% -> 207.81146
A70: RES | B70: 99347 | C70: 202 | D70: 18287.53 | E70: 18508.87 | F70: 68053.76 | G70: 104850.16 | H70: 180 | I70: 19535.64 | J70: 10227.44 | K70: 36104.35 | L70: 65867.43 | M70: 173 | N70: 20153.24 | O70: 10505.25 | P70: 27978.75 | Q70: 58637.24 | AR70: RES | AS70: 99347 | AT70: =D70*1.6%+E70*6.3%+F70*28.9% -> 21126.196 | AU70: =I70*1.6%+J70*6.3%+K70*28.9% -> 11391.056 | AV70: =N70*1.6%+O70*6.3%+P70*28.9% -> 9070.1413
A71: RES | B71: 99348 | C71: 47 | D71: 4317.11 | E71: 3382.57 | F71: 7846.67 | G71: 15546.35 | H71: 48 | I71: 5052.51 | J71: 2747.21 | K71: 7139.15 | L71: 14938.87 | M71: 43 | N71: 4735.18 | O71: 2565.55 | P71: 5241.1 | Q71: 12541.83 | AR71: RES | AS71: 99348 | AT71: =D71*1.6%+E71*6.3%+F71*28.9% -> 2549.8633 | AU71: =I71*1.6%+J71*6.3%+K71*28.9% -> 2317.1287 | AV71: =N71*1.6%+O71*6.3%+P71*28.9% -> 1752.0704
A72: RES | B72: 99350 | C72: 8 | D72: 0 | E72: 948.58 | F72: 1728.89 | G72: 2677.47 | H72: 6 | I72: 895.4 | J72: 261.96 | K72: 1195.14 | L72: 2352.5 | M72: 11 | N72: 2603.41 | O72: 0 | P72: 1336.9 | Q72: 3940.31 | AR72: RES | AS72: 99350 | AT72: =D72*1.6%+E72*6.3%+F72*28.9% -> 559.40975 | AU72: =I72*1.6%+J72*6.3%+K72*28.9% -> 376.22534 | AV72: =N72*1.6%+O72*6.3%+P72*28.9% -> 428.01866
A73: RES | B73: 99360 | C73: 88 | D73: 11295.93 | E73: 5621.82 | F73: 12082.1 | G73: 28999.85 | H73: 48 | I73: 2842.08 | J73: 4685.16 | K73: 6318.41 | L73: 13845.65 | M73: 92 | N73: 13314 | O73: 8046.91 | P73: 4592.49 | Q73: 25953.4 | AR73: RES | AS73: 99360 | AT73: =D73*1.6%+E73*6.3%+F73*28.9% -> 4026.6364 | AU73: =I73*1.6%+J73*6.3%+K73*28.9% -> 2166.6588 | AV73: =N73*1.6%+O73*6.3%+P73*28.9% -> 2047.2089
A74: RES | B74: 99361 | C74: 131 | D74: 15202.03 | E74: 11398.52 | F74: 23006.08 | G74: 49606.63 | H74: 138 | I74: 15814.05 | J74: 9196.6 | K74: 19425.26 | L74: 44435.91 | M74: 126 | N74: 15219.45 | O74: 7327.48 | P74: 12031.14 | Q74: 34578.07 | AR74: RES | AS74: 99361 | AT74: =D74*1.6%+E74*6.3%+F74*28.9% -> 7610.0964 | AU74: =I74*1.6%+J74*6.3%+K74*28.9% -> 6446.3107 | AV74: =N74*1.6%+O74*6.3%+P74*28.9% -> 4182.1419
A75: RES | B75: 99362 | C75: 2322 | D75: 156381.86 | E75: 127891.45 | F75: 345961.15 | G75: 630234.46 | H75: 2379 | I75: 215488.03 | J75: 91923.92 | K75: 231762.88 | L75: 539174.83 | M75: 3143 | N75: 392212.75 | O75: 76377.97 | P75: 163677.88 | Q75: 632268.6 | AR75: RES | AS75: 99362 | AT75: =D75*1.6%+E75*6.3%+F75*28.9% -> 110542.04 | AU75: =I75*1.6%+J75*6.3%+K75*28.9% -> 76218.488 | AV75: =N75*1.6%+O75*6.3%+P75*28.9% -> 58390.123
A76: RES | B76: 99363 | C76: 19 | D76: 1908.08 | E76: 1111.34 | F76: 1181.03 | G76: 4200.45 | H76: 11 | I76: 0 | J76: 882.1 | K76: 1226.87 | L76: 2108.97 | M76: 23 | N76: 2377.46 | O76: 1255.96 | P76: 798.27 | Q76: 4431.69 | AR76: RES | AS76: 99363 | AT76: =D76*1.6%+E76*6.3%+F76*28.9% -> 441.86137 | AU76: =I76*1.6%+J76*6.3%+K76*28.9% -> 410.13773 | AV76: =N76*1.6%+O76*6.3%+P76*28.9% -> 347.86487
A77: TOTAL | C77: =SUM(C5:C76) -> 29416 | D77: =SUM(D5:D76) -> 3297484.1 | E77: =SUM(E5:E76) -> 2013665.9 | F77: =SUM(F5:F76) -> 10581591 | G77: =SUM(G5:G76) -> 15892741 | H77: =SUM(H5:H76) -> 28248 | I77: =SUM(I5:I76) -> 3603791.2 | J77: =SUM(J5:J76) -> 1801064.9 | ... Q77: =SUM(Q5:Q76) -> 14882513 | AR77: TOTAL | AT77: =SUM(AT41:AT76) -> 2903972.1 | AU77: =SUM(AU41:AU76) -> 2536177.3 | AV77: =SUM(AV41:AV76) -> 2286223.3

Sheet 8. Past Due Balances 2020 OLD
A1: General 2020 | E1: Item a) Number of Customers by Customer Class With Past-due balances (arrearages) | O1: Item b) Past-due Balances by Customer Class and Number of Days Past-due | AZ1: Item c) Amount of Past-due Balances for Known Low-income Households and Number of Days Past-due | CL1: Item d) Amount of Past Due Balances Classified as Uncollectible | CV1: Item e) The Amount of Past-due Balances Written-off and Classified as Bad Debt, if different than item d | DG1: Item f) Number of Customer Accounts Referred to Collection Agencies | DQ1: Item f) Total Amount of Bad Debt Referred for Collection | EA1: Item f) Total Revenue to the Company from the Collection Process
O2: 43831 | S2: 43862 | W2: 43891 | AA2: 43922 | AE2: 43952 | AI2: 43983 | AM2: 44013 | AQ2: 44044 | AU2: 44075 | AZ2: 43831 | BD2: 43862 | BH2: 43891 | BL2: 43922 | BP2: 43952 | BT2: 43983 | BX2: 44013 | CB2: 44044 | CF2: 44075
A3: Zip Code | B3: Customer Class | C3: x | D3: x | E3: 43831 | F3: 43862 | G3: 43891 | H3: 43922 | I3: 43952 | J3: 43983 | K3: 44013 | L3: 44044 | M3: 44075 | N3: x | O3: 30 Days | P3: 60 Days | Q3: 90 Days + | R3: Total Arrearages | S3: 30 Days | T3: 60 Days | U3: 90 Days + | V3: Total Arrearages | W3: 30 Days | X3: 60 Days | Y3: 90 Days + | Z3: Total Arrearages | AA3: 30 Days | AB3: 60 Days | AC3: 90 Days + | AD3: Total Arrearages | AE3: 30 Days | AF3: 60 Days | AG3: 90 Days + | AH3: Total Arrearages | AI3: 30 Days | AJ3: 60 Days | AK3: 90 Days + | AL3: Total Arrearages | AM3: 30 Days | AN3: 60 Days | AO3: 90 Days + | AP3: Total Arrearages | AQ3: 30 Days | AR3: 60 Days | AS3: 90 Days + | AT3: Total Arrearages | AU3: 30 Days | AV3: 60 Days | AW3: 90 Days + | AX3: Total Arrearages | AZ3: 30 Days | BA3: 60 Days | BB3: 90 Days + | BC3: Total Arrearages | BD3: 30 Days | BE3: 60 Days | BF3: 90 Days + | BG3: Total Arrearages | BH3: 30 Days | BI3: 60 Days | BJ3: 90 Days + | BK3: Total Arrearages | BL3: 30 Days | BM3: 60 Days | BN3: 90 Days + | BO3: Total Arrearages | BP3: 30 Days | BQ3: 60 Days | BR3: 90 Days + | BS3: Total Arrearages | BT3: 30 Days | BU3: 60 Days | BV3: 90 Days + | BW3: Total Arrearages | BX3: 30 Days | BY3: 60 Days | BZ3: 90 Days + | CA3: Total Arrearages | CB3: 30 Days | CC3: 60 Days | CD3: 90 Days + | CE3: Total Arrearages | CF3: 30 Days | CG3: 60 Days | CH3: 90 Days + | CI3: Total Arrearages | CL3: 43831 | CM3: 43862 | CN3: 43891 | CO3: 43922 | CP3: 43952 | CQ3: 43983 | CR3: 44013 | CS3: 44044 | CT3: 44075 | CV3: CLASS | CW3: 43831 | CX3: 43862 | CY3: 43891 | CZ3: 43922 | DA3: 43952 | DB3: 43983 | DC3: 44013 | DD3: 44044 | DE3: 44075 | DG3: 43831 | DH3: 43862 | DI3: 43891 | DJ3: 43922 | DK3: 43952 | DL3: 43983 | DM3: 44013 | DN3: 44044 | DO3: 44075 | DQ3: 43831 | DR3: 43862 | DS3: 43891 | DT3: 43922 | DU3: 43952 | DV3: 43983 | DW3: 44013 | DX3: 44044 | DY3: 44075 | EA3: 43831 | EB3: 43862 | EC3: 43891 | ED3: 43922 | EE3: 43952 | EF3: 43983 | EG3: 44013 | EH3: 44044 | EI3: 44075
A4: 98901 | B4: COM | C4: =A4&B4 -> 98901COM | E4: 131 | F4: 132 | G4: 145 | H4: 173 | I4: 221 | J4: 160 | K4: 137 | L4: 152 | M4: 156 | O4: 19871.38 | P4: 7897.63 | Q4: 24242.65 | R4: 52011.66 | S4: 53580.83 | T4: 9976.46 | U4: 27438.96 | V4: 90996.25 | W4: 48277.95 | X4: 17941.85 | Y4: 22854.02 | Z4: 89073.82 | AA4: 71009.6 | AB4: 29051.57 | AC4: 36760.09 | AD4: 136821.26 | AE4: 86883.42 | AF4: 34985.09 | AG4: 49645.24 | AH4: 171513.75 | AI4: 39740.66 | AJ4: 29311.53 | AK4: 66630.47 | AL4: 135682.66 | AM4: 38006.67 | AN4: 14078.08 | AO4: 65366.26 | AP4: 117451.01 | AQ4: 29853.1 | AR4: 15834.18 | AS4: 62985.51 | AT4: 108672.79 | AU4: 41939.18 | AV4: 15055.03 | AW4: 60553.4 | AX4: 117547.61 | AZ4: 42.71 | BA4: 41.08 | BC4: 83.79 | BD4: 48.96 | BE4: 42.71 | BF4: 41.08 | BG4: 132.75 | BH4: 56.74 | BI4: 48.96 | BJ4: 83.79 | BK4: 189.49 | BL4: 50.42 | BM4: 56.74 | BN4: 132.75 | BO4: 239.91 | BP4: 44.7 | BQ4: 50.42 | BR4: 189.49 | BS4: 284.61 | BT4: 24.09 | BU4: 44.7 | BV4: 189.91 | BW4: 258.7 | BX4: 23.42 | BY4: 24.09 | BZ4: 234.61 | CA4: 282.12 | CB4: 29.16 | CC4: 23.42 | CD4: 184.25 | CE4: 236.83 | CF4: 33.34 | CG4: 29.16 | CH4: 207.67 | CI4: 270.17 | CJ4: =VLOOKUP($C4,#REF!,#REF!,FALSE) -> #REF! | CL4: 6680.653 | CM4: 9123.4953 | CN4: 9211.7238 | CO4: 15409.934 | CP4: 18878.318 | CQ4: 22984.908 | CR4: 21490.276 | CS4: 22157.377 | CT4: 21296.568 | CV4: RES | CW4: 155378.03 | CX4: 91404.44 | CY4: 77084.33 | CZ4: 161847.29 | DA4: 69802.26 | DB4: 66491.04 | DC4: 72376.07 | DD4: 109624.03 | DE4: 76241.97 | DG4: 2 | DH4: 2 | DI4: 3 | DJ4: 3 | DK4: 1 | DQ4: 3400.92 | DR4: 1528.25 | DS4: 1009.25 | DT4: 25469.44 | DU4: 361.46 | EC4: 215.93 | EE4: 361.46
A5: 98902 | B5: COM | C5: =A5&B5 -> 98902COM | E5: 197 | F5: 198 | G5: 189 | H5: 218 | I5: 275 | J5: 206 | K5: 187 | L5: 219 | M5: 208 | O5: 56081.52 | P5: 11010.14 | Q5: 15451.95 | R5: 82543.61 | S5: 126371.49 | T5: 13179.05 | U5: 17580.15 | V5: 157130.69 | W5: 34416.43 | X5: 16097.77 | Y5: 20292.23 | Z5: 70806.43 | AA5: 67882.3 | AB5: 22425.07 | AC5: 28833.05 | AD5: 119140.42 | AE5: 82008.83 | AF5: 27881.35 | AG5: 44079.42 | AH5: 153969.6 | AI5: 39115.86 | AJ5: 22652.96 | AK5: 55917.07 | AL5: 117685.89 | AM5: 37473.1 | AN5: 19881.82 | AO5: 51286.11 | AP5: 108641.03 | AQ5: 60464.87 | AR5: 21310.31 | AS5: 56987.72 | AT5: 138762.9 | AU5: 44660.96 | AV5: 22729.12 | AW5: 61819.4 | AX5: 129209.48 | AZ5: 40.74 | BC5: 40.74 | BD5: 29.81 | BE5: 40.74 | BG5: 70.55 | BH5: 33.2 | BI5: 29.81 | BJ5: 40.74 | BK5: 103.75 | BL5: 122.34 | BM5: 33.2 | BN5: 70.55 | BO5: 226.09 | BP5: 110.62 | BQ5: 122.34 | BR5: 103.75 | BS5: 336.71 | BT5: 55.19 | BU5: 110.62 | BV5: 226.09 | BW5: 391.9 | BX5: 69.27 | BY5: 55.19 | BZ5: 336.71 | CA5: 461.17 | CB5: 87.53 | CC5: 69.27 | CD5: 391.9 | CE5: 548.7 | CF5: 80.19 | CG5: 87.53 | CH5: 461.17 | CI5: 628.89 | CJ5: 0.24399667 | CL5: 5618.0792 | CM5: 9221.8192 | CN5: 7917.4582 | CO5: 12496.834 | CP5: 16704.887 | CQ5: 19304.53 | CR5: 17758.213 | CS5: 21520.255 | CT5: 22300.768 | CV5: COM | CW5: 2753.02 | CX5: 9149.27 | CY5: 12487.38 | CZ5: 14610.42 | DA5: 12690.61 | DB5: 6158.09 | DC5: 7360.64 | DD5: 6977.57 | DE5: 14974.03 | DG5: 4 | DH5: 4 | DI5: 17 | DJ5: 5 | DK5: 1 | DL5: 4 | DQ5: 227.95 | DR5: 12847.79 | DS5: 12855.73 | DT5: 693.93 | DU5: 260.59 | DV5: 210.46 | EA5: 204.97 | EC5: 366.14 | ED5: 262.16 | EF5: 155.42 | EG5: 83.93
A6: 98903 | B6: COM | C6: =A6&B6 -> 98903COM | E6: 123 | F6: 109 | G6: 105 | H6: 119 | I6: 188 | J6: 112 | K6: 117 | L6: 134 | M6: 124 | O6: 22768.85 | P6: 7604.5 | Q6: 7617.7 | R6: 37991.05 | S6: 62967.03 | T6: 4976.34 | U6: 6658.94 | V6: 74602.31 | W6: 14427.86 | X6: 9455.36 | Y6: 6303.98 | Z6: 30187.2 | AA6: 34080.48 | AB6: 10589.12 | AC6: 11180.85 | AD6: 55850.45 | AE6: 57986.56 | AF6: 15693.43 | AG6: 19537.11 | AH6: 93217.1 | AI6: 18745.46 | AJ6: 12483.44 | AK6: 22869.82 | AL6: 54098.72 | AM6: 17601.8 | AN6: 3910.46 | AO6: 33199.92 | AP6: 54712.18 | AQ6: 19669.93 | AR6: 18272.7 | AS6: 34813.48 | AT6: 72756.11 | AU6: 23168.57 | AV6: 4663.56 | AW6: 42563.61 | AX6: 70395.74 | CJ6: 0.26286604 | CL6: 2767.5383 | CM6: 3960.1853 | CN6: 2984.8866 | CO6: 5282.1529 | CP6: 8223.6545 | CQ6: 8225.4179 | CR6: 10619.978 | CS6: 13059.721 | CT6: 14404.337 | DG6: 5 | DH6: 1 | DI6: 1 | DJ6: 4 | DK6: 1 | DL6: 2 | DQ6: 817.64 | DR6: 142.22 | DS6: 154.34 | DT6: 976.96 | DU6: 385.63 | DV6: 533.4 | EA6: 746.69 | EC6: 154.34 | ED6: 478.24 | EE6: 385.63 | EF6: 101.99
A7: 98908 | B7: COM | C7: =A7&B7 -> 98908COM | E7: 100 | F7: 117 | G7: 126 | H7: 144 | I7: 142 | J7: 104 | K7: 89 | L7: 123 | M7: 117 | O7: 24914.74 | P7: 1417.66 | Q7: 1482.68 | R7: 27815.08 | S7: 13416.06 | T7: 2358.05 | U7: 2511.35 | V7: 18285.46 | W7: 19122.52 | X7: 5305.24 | Y7: 2841.91 | Z7: 27269.67 | AA7: 21192.33 | AB7: 7382.52 | AC7: 5830.49 | AD7: 34405.34 | AE7: 42531.53 | AF7: 11285.05 | AG7: 9525.78 | AH7: 63342.36 | AI7: 16892.88 | AJ7: 5857.23 | AK7: 13310.88 | AL7: 36060.99 | AM7: 9242.42 | AN7: 4737.16 | AO7: 13686.29 | AP7: 27665.87 | AQ7: 22069.54 | AR7: 6286.33 | AS7: 16209.75 | AT7: 44565.62 | AU7: 17866.4 | AV7: 6732.99 | AW7: 15270.36 | AX7: 39869.75 | AZ7: 82.16 | BA7: 29.84 | BC7: 112 | BD7: 74.84 | BE7: 82.16 | BF7: 29.84 | BG7: 186.84 | BH7: 73.81 | BK7: 73.81 | BL7: 67.88 | BM7: 73.81 | BO7: 141.69 | BP7: 42.04 | BQ7: 67.88 | BR7: 73.81 | BS7: 183.73 | BT7: 24.13 | BU7: 42.04 | BV7: 141.69 | BW7: 207.86 | BX7: 45.72 | BY7: 24.13 | BZ7: 183.73 | CA7: 253.58 | CB7: 50.87 | CC7: 45.72 | CD7: 207.86 | CE7: 304.45 | CF7: 50.18 | CG7: 50.87 | CH7: 253.58 | CI7: 354.63 | CJ7: 0.2842874 | CL7: 1027.7791 | CM7: 1210.0733 | CN7: 1853.2718 | CO7: 3031.4297 | CP7: 4637.8175 | CQ7: 4850.8456 | CR7: 4673.1373 | CS7: 6275.5162 | CT7: 5750.6895 | DH7: 1 | DI7: 2 | DJ7: 3 | DL7: 2 | DR7: 258.25 | DS7: 584.7 | DT7: 866.82 | DV7: 740.9 | EB7: 258.25 | EC7: 209.33 | ED7: 240.28 | EF7: 740.9
A8: 98920 | B8: COM | C8: =A8&B8 -> 98920COM | E8: 1 | J8: 2 | O8: 35.7 | P8: 0 | Q8: 0 | R8: 35.7 | AI8: 53.06 | AJ8: 0 | AK8: 0 | AL8: 53.06 | CJ8: 0.28728463 | CL8: 0.85823928 | CQ8: 1.534743
A9: 98921 | B9: COM | C9: =A9&B9 -> 98921COM | E9: 1 | F9: 2 | G9: 2 | H9: 5 | I9: 4 | J9: 2 | K9: 4 | L9: 3 | M9: 3 | O9: 11.8 | P9: 11.68 | Q9: 13.15 | R9: 36.63 | S9: 161.8 | T9: 11.8 | U9: 24.83 | V9: 198.43 | W9: 146.79 | X9: 161.8 | Y9: 36.63 | Z9: 345.22 | AA9: 918.22 | AB9: 12.04 | AC9: 48.55 | AD9: 978.81 | AE9: 519.37 | AF9: 136.16 | AG9: 60.59 | AH9: 716.12 | AI9: 73.2 | AJ9: 113.5 | AK9: 196.75 | AL9: 383.45 | AM9: 292.13 | AN9: 29.87 | AO9: 83.69 | AP9: 405.69 | AQ9: 217.55 | AR9: 186.1 | AS9: 95.24 | AT9: 498.89 | AU9: 216.72 | AV9: 104.19 | AW9: 124.89 | AX9: 445.8 | CJ9: 0.29347129 | CL9: 4.0396567 | CM9: 11.983693 | CN9: 29.070748 | CO9: 47.934722 | CP9: 40.521968 | CQ9: 68.691376 | CR9: 35.864705 | CS9: 50.683103 | CT9: 52.160528 | DL9: 2 | DV9: 323.73 | EF9: 323.73
A10: 98923 | B10: COM | C10: =A10&B10 -> 98923COM | E10: 16 | F10: 9 | G10: 18 | H10: 6 | I10: 5 | J10: 18 | K10: 15 | L10: 16 | M10: 16 | O10: 17959.08 | P10: 31.33 | Q10: 255.2 | R10: 18245.61 | S10: 537.76 | T10: 47.2 | U10: 286.53 | V10: 871.49 | W10: 16599.05 | X10: 66.75 | Y10: 183.73 | Z10: 16849.53 | AA10: 91.78 | AB10: 110.2 | AC10: 250.48 | AD10: 452.46 | AE10: 70.62 | AF10: 77.75 | AG10: 318.49 | AH10: 466.86 | AI10: 7533.87 | AJ10: 70.62 | AK10: 396.24 | AL10: 8000.73 | AM10: 6002.33 | AN10: 42.71 | AO10: 377.8 | AP10: 6422.84 | AQ10: 7712.15 | AR10: 45.18 | AS10: 319.02 | AT10: 8076.35 | AU10: 8746.24 | AV10: 71.71 | AW10: 364.2 | AX10: 9182.15 | CJ10: 0.29479967 | CL10: 494.29869 | CM10: 90.21886 | CN10: 598.08661 | CO10: 83.612057 | CP10: 98.275407 | CQ10: 339.69606 | CR10: 298.54343 | CS10: 322.46673 | CT10: 330.36683 | DG10: 1 | DQ10: 106.87
A11: 98930 | B11: COM | C11: =A11&B11 -> 98930COM | E11: 27 | F11: 27 | G11: 37 | H11: 47 | I11: 41 | J11: 35 | K11: 40 | L11: 30 | M11: 44 | O11: 3937.2 | P11: 207.64 | Q11: 1005.96 | R11: 5150.8 | S11: 3368.57 | T11: 872.13 | U11: 845.24 | V11: 5085.94 | W11: 6174.01 | X11: 634.42 | Y11: 718.11 | Z11: 7526.54 | AA11: 10506.12 | AB11: 5266.98 | AC11: 1232.67 | AD11: 17005.77 | AE11: 18016.66 | AF11: 5883.63 | AG11: 5651.82 | AH11: 29552.11 | AI11: 6772.97 | AJ11: 4121.62 | AK11: 8529.95 | AL11: 19424.54 | AM11: 3828.79 | AN11: 3397.63 | AO11: 10724.7 | AP11: 17951.12 | AQ11: 4004.54 | AR11: 2298.98 | AS11: 11177.95 | AT11: 17481.47 | AU11: 7780.57 | AV11: 3529.16 | AW11: 13198.62 | AX11: 24508.35 | CJ11: 0.31933271 | CL11: 345.69247 | CM11: 377.73042 | CN11: 448.39332 | CO11: 1164.1248 | CP11: 2496.745 | CQ11: 3019.9837 | CR11: 3533.7121 | CS11: 3856.9734 | CT11: 4626.6464 | DI11: 1 | DK11: 1 | DL11: 1 | DS11: 128.23 | DU11: 116.78 | DV11: 87.06 | EC11: 128.23 | EE11: 116.78 | EF11: 87.06
A12: 98932 | B12: COM | C12: =A12&B12 -> 98932COM | E12: 29 | F12: 21 | G12: 22 | H12: 27 | I12: 20 | J12: 39 | K12: 19 | L12: 44 | M12: 26 | O12: 34084.29 | P12: 473.24 | Q12: 1162.68 | R12: 35720.21 | S12: 6747.19 | T12: 1739.15 | U12: 925.66 | V12: 9412 | W12: 4186.74 | X12: 950 | Y12: 1372.21 | Z12: 6508.95 | AA12: 7151.55 | AB12: 799.06 | AC12: 2041.27 | AD12: 9991.88 | AE12: 5209.73 | AF12: 2122.8 | AG12: 2780.96 | AH12: 10113.49 | AI12: 25617.11 | AJ12: 1969.69 | AK12: 4809.93 | AL12: 32396.73 | AM12: 11868.98 | AN12: 640.97 | AO12: 3789.83 | AP12: 16299.78 | AQ12: 28353.4 | AR12: 1284.5 | AS12: 4409.18 | AT12: 34047.08 | AU12: 23595.91 | AV12: 1355.28 | AW12: 5243.27 | AX12: 30194.46 | CJ12: 0.31770853 | CL12: 1121.8888 | CM12: 568.76641 | CN12: 583.77628 | CO12: 904.3337 | CP12: 1077.2483 | CQ12: 2305.8422 | CR12: 1529.0687 | CS12: 2303.9982 | CT12: 2326.2018 | DG12: 3 | DK12: 1 | DQ12: 4434.07 | DU12: 132.18 | EE12: 132.18
A13: 98933 | B13: COM | C13: =A13&B13 -> 98933COM | E13: 6 | F13: 6 | G13: 5 | H13: 6 | I13: 5 | J13: 4 | K13: 7 | L13: 8 | M13: 5 | O13: 3864.65 | P13: 273.81 | Q13: 49.14 | R13: 4187.6 | S13: 3224.29 | T13: 3476.65 | U13: 0 | V13: 6700.94 | W13: 696.79 | X13: 340.58 | Y13: 255.24 | Z13: 1292.61 | AA13: 1601.96 | AB13: 323.68 | AC13: 581.51 | AD13: 2507.15 | AE13: 2340.63 | AF13: 565.86 | AG13: 892.39 | AH13: 3798.88 | AI13: 898.59 | AJ13: 238.19 | AK13: 1203.87 | AL13: 2340.65 | AM13: 1433.43 | AN13: 862.59 | AO13: 1442.06 | AP13: 3738.08 | AQ13: 3542.54 | AR13: 421.55 | AS13: 1814.66 | AT13: 5778.75 | AU13: 2355.16 | AV13: 673.07 | AW13: 2195.97 | AX13: 5224.2 | CL13: 119.12037 | CM13: 367.14007 | CN13: 120.72194 | CO13: 249.83509 | CP13: 357.61206 | CQ13: 397.83084 | CR13: 533.72174 | CS13: 711.2703 | CT13: 801.20603
A14: 98935 | B14: COM | C14: =A14&B14 -> 98935COM | E14: 4 | F14: 6 | G14: 6 | H14: 5 | I14: 13 | J14: 5 | K14: 5 | L14: 5 | M14: 4 | O14: 149.96 | P14: 671.54 | Q14: 581.23 | R14: 1402.73 | S14: 754.6 | T14: 654.15 | U14: 311.23 | V14: 1719.98 | W14: 954.7 | X14: 546.48 | Y14: 365.42 | Z14: 1866.6 | AA14: 502.21 | AB14: 695.09 | AC14: 911.9 | AD14: 2109.2 | AE14: 1843.16 | AF14: 225.76 | AG14: 670.41 | AH14: 2739.33 | AI14: 253.45 | AJ14: 202.26 | AK14: 896.17 | AL14: 1351.88 | AM14: 289.37 | AN14: 0 | AO14: 1276.4 | AP14: 1565.77 | AQ14: 90.52 | AR14: 321.67 | AS14: 1192.57 | AT14: 1604.76 | AU14: 158.39 | AV14: 0 | AW14: 1513.61 | AX14: 1672 | CL14: 177.83509 | CM14: 149.60689 | CN14: 176.75503 | CO14: 334.71073 | CP14: 258.83263 | CQ14: 286.07286 | CR14: 385.15124 | CS14: 407.8232 | CT14: 484.68332
A15: 98936 | B15: COM | C15: =A15&B15 -> 98936COM | E15: 13 | F15: 17 | G15: 22 | H15: 21 | I15: 20 | J15: 21 | K15: 18 | L15: 21 | M15: 27 | O15: 1104.69 | P15: 78.91 | Q15: 1520.2 | R15: 2703.8 | S15: 3151.94 | T15: 633.25 | U15: 1433.68 | V15: 5218.87 | W15: 2444.51 | X15: 1857.26 | Y15: 1627.91 | Z15: 5929.68 | AA15: 3530.94 | AB15: 3133.97 | AC15: 2022.93 | AD15: 8687.84 | AE15: 1453.39 | AF15: 2537.97 | AG15: 5901.48 | AH15: 9892.84 | AI15: 2778.91 | AJ15: 1259.65 | AK15: 8299.19 | AL15: 12337.75 | AM15: 3827.82 | AN15: 2571.81 | AO15: 9163.91 | AP15: 15563.54 | AQ15: 2117.52 | AR15: 1482.42 | AS15: 6712.12 | AT15: 10312.06 | AU15: 12683.62 | AV15: 1442.45 | AW15: 8194.54 | AX15: 22320.61 | CL15: 393.50193 | CM15: 496.234 | CN15: 675.97277 | CO15: 961.0758 | CP15: 1892.4527 | CQ15: 2613.9906 | CR15: 3011.6491 | CS15: 2315.6924 | CT15: 3008.3816 | DJ15: 2 | DT15: 103.59 | ED15: 62.32
A16: 98937 | B16: COM | C16: =A16&B16 -> 98937COM | E16: 28 | F16: 22 | G16: 34 | H16: 35 | I16: 28 | J16: 37 | K16: 32 | L16: 36 | M16: 22 | O16: 2201.03 | P16: 805.92 | Q16: 721.38 | R16: 3728.33 | S16: 3729.78 | T16: 628.91 | U16: 315.98 | V16: 4674.67 | W16: 4471.17 | X16: 2079.24 | Y16: 157.9 | Z16: 6708.31 | AA16: 5410.5 | AB16: 2269.38 | AC16: 494.42 | AD16: 8174.3 | AE16: 4693.5 | AF16: 2128.39 | AG16: 1020.84 | AH16: 7842.73 | AI16: 3333.54 | AJ16: 2347.39 | AK16: 2460.92 | AL16: 8141.85 | AM16: 6046.68 | AN16: 1430.96 | AO16: 3620.15 | AP16: 11097.79 | AQ16: 5032.12 | AR16: 1881.12 | AS16: 3254.81 | AT16: 10168.05 | AU16: 2961.69 | AV16: 1481.18 | AW16: 2739.54 | AX16: 7182.41 | CL16: 267.69756 | CM16: 241.10847 | CN16: 376.02276 | CO16: 523.04709 | CP16: 557.26531 | CQ16: 1001.3264 | CR16: 1359.8255 | CS16: 1324.032 | CT16: 1044.9619 | DG16: 1 | DJ16: 2 | DQ16: 8.59 | DT16: 320.49 | EG16: 6.44
A17: 98938 | B17: COM | C17: =A17&B17 -> 98938COM | E17: 19 | F17: 9 | G17: 4 | H17: 10 | I17: 10 | J17: 31 | K17: 18 | L17: 21 | M17: 31 | O17: 28703.41 | P17: 7.92 | Q17: 0 | R17: 28711.33 | S17: 1460.29 | T17: 525.87 | U17: 7.92 | V17: 1994.08 | W17: 653.6 | X17: 28.9 | Y17: 0 | Z17: 682.5 | AA17: 2235.35 | AB17: 413.02 | AC17: 11.51 | AD17: 2659.88 | AE17: 8154.4 | AF17: 531.61 | AG17: 407.47 | AH17: 9093.48 | AI17: 44246.12 | AJ17: 389.25 | AK17: 904.91 | AL17: 45540.28 | AM17: 27696.04 | AN17: 189.79 | AO17: 914.92 | AP17: 28800.75 | AQ17: 27749.76 | AR17: 321.03 | AS17: 723.93 | AT17: 28794.72 | AU17: 28169.52 | AV17: 5734.07 | AW17: 53.25 | AX17: 33956.84 | CL17: 690.45807 | CM17: 87.632328 | CN17: 24.024445 | CO17: 118.02124 | CP17: 381.41988 | CQ17: 1575.6645 | CR17: 1132.806 | CS17: 1036.9539 | CT17: 1093.1765
A18: 98942 | B18: COM | C18: =A18&B18 -> 98942COM | E18: 61 | F18: 64 | G18: 61 | H18: 73 | I18: 70 | J18: 58 | K18: 46 | L18: 56 | M18: 63 | O18: 12032.12 | P18: 1888.13 | Q18: 1227.37 | R18: 15147.62 | S18: 50682.28 | T18: 3561.83 | U18: 2431.76 | V18: 56675.87 | W18: 9946.74 | X18: 2883.43 | Y18: 3116.66 | Z18: 15946.83 | AA18: 11559.45 | AB18: 5429.91 | AC18: 5479.66 | AD18: 22469.02 | AE18: 50847.74 | AF18: 6926.61 | AG18: 9794.77 | AH18: 67569.12 | AI18: 43936.06 | AJ18: 5152.35 | AK18: 14754.35 | AL18: 63842.76 | AM18: 7176.09 | AN18: 4418.02 | AO18: 12609.04 | AP18: 24203.15 | AQ18: 9350.26 | AR18: 5557.96 | AS18: 16123.68 | AT18: 31031.9 | AU18: 13554.32 | AV18: 5995.18 | AW18: 19525.29 | AX18: 39074.79 | CL18: 682.04274 | CM18: 2439.0431 | CN18: 1405.8815 | CO18: 2422.9475 | CP18: 4683.9702 | CQ18: 6001.8174 | CR18: 4268.3068 | CS18: 5834.5226 | CT18: 6947.5552 | DI18: 1 | DJ18: 3 | DS18: 83.67 | DT18: 189.48 | EC18: 83.67 | EG18: 118.91
A19: 98944 | B19: COM | C19: =A19&B19 -> 98944COM | E19: 102 | F19: 109 | G19: 116 | H19: 141 | I19: 139 | J19: 121 | K19: 115 | L19: 122 | M19: 148 | O19: 28613.88 | P19: 7264.59 | Q19: 16028.35 | R19: 51906.82 | S19: 29333.66 | T19: 8231.58 | U19: 15798.7 | V19: 53363.94 | W19: 28365.22 | X19: 13838.46 | Y19: 18015.38 | Z19: 60219.06 | AA19: 38176.02 | AB19: 14581.69 | AC19: 27376.56 | AD19: 80134.27 | AE19: 25168.18 | AF19: 15323.14 | AG19: 37689.21 | AH19: 78180.53 | AI19: 24913.62 | AJ19: 12061.23 | AK19: 45457.88 | AL19: 82432.73 | AM19: 29855.38 | AN19: 8886 | AO19: 48374.44 | AP19: 87115.82 | AQ19: 31184.6 | AR19: 9916.15 | AS19: 50435.11 | AT19: 91535.86 | AU19: 44021.59 | AV19: 13597.29 | AW19: 51075.36 | AX19: 108694.24 | CL19: 4897.1298 | CM19: 5397.1605 | CN19: 6916.3906 | CO19: 10363.582 | CP19: 12483.096 | CQ19: 14999.917 | CR19: 15842.006 | CS19: 17737.331 | CT19: 18233.27 | DG19: 1 | DH19: 3 | DI19: 1 | DJ19: 4 | DN19: 1 | DQ19: 74.38 | DR19: 412.46 | DS19: 198.41 | DT19: 2420.24 | DX19: 1155.9 | EB19: 224.58 | ED19: 16.75
A20: 98947 | B20: COM | C20: =A20&B20 -> 98947COM | E20: 24 | F20: 16 | G20: 12 | H20: 12 | I20: 14 | J20: 14 | K20: 18 | L20: 23 | M20: 21 | O20: 11460.87 | P20: 733.36 | Q20: 277.69 | R20: 12471.92 | S20: 4006.02 | T20: 1486.4 | U20: 154.83 | V20: 5647.25 | W20: 8745.89 | X20: 1847.37 | Y20: 663.19 | Z20: 11256.45 | AA20: 2453.94 | AB20: 2936.83 | AC20: 1541.56 | AD20: 6932.33 | AE20: 2095.96 | AF20: 2044.01 | AG20: 2638.66 | AH20: 6778.63 | AI20: 4199.68 | AJ20: 1991.46 | AK20: 3094.63 | AL20: 9285.77 | AM20: 3360.31 | AN20: 1627.78 | AO20: 4321.87 | AP20: 9309.96 | AQ20: 4113.45 | AR20: 1531.68 | AS20: 4242.07 | AT20: 9887.2 | AU20: 4822.47 | AV20: 1338.62 | AW20: 3321.27 | AX20: 9482.36 | CL20: 380.589 | CM20: 276.24261 | CN20: 627.9074 | CO20: 769.09484 | CP20: 943.04341 | CQ20: 1184.6531 | CR20: 1499.1133 | CS20: 1586.8701 | CT20: 1264.4133
A21: 98948 | B21: COM | C21: =A21&B21 -> 98948COM | E21: 82 | F21: 82 | G21: 61 | H21: 83 | I21: 115 | J21: 94 | K21: 123 | L21: 106 | M21: 95 | O21: 23670.59 | P21: 9817.95 | Q21: 9527.94 | R21: 43016.48 | S21: 45406.29 | T21: 10392.76 | U21: 15955.05 | V21: 71754.1 | W21: 11196.65 | X21: 4388.62 | Y21: 8562.34 | Z21: 24147.61 | AA21: 18721.49 | AB21: 8485.51 | AC21: 11791.56 | AD21: 38998.56 | AE21: 19917.3 | AF21: 18314.64 | AG21: 16273.44 | AH21: 54505.38 | AI21: 10461.57 | AJ21: 19008.72 | AK21: 22432.55 | AL21: 51902.84 | AM21: 29948.2 | AN21: 4265.13 | AO21: 34840.47 | AP21: 69053.8 | AQ21: 21391.13 | AR21: 7718.58 | AS21: 26566.07 | AT21: 55675.78 | AU21: 36008.3 | AV21: 11610.49 | AW21: 31064.86 | AX21: 78683.65 | AZ21: 4263.35 | BA21: 1046.4 | BC21: 5309.75 | BD21: 5183.12 | BE21: 3204.41 | BF21: 1046.4 | BG21: 9433.93 | BH21: 2706.94 | BI21: 3.75 | BK21: 2710.69 | BL21: 6015.17 | BM21: 2364.95 | BO21: 8380.12 | BP21: 5908.2 | BQ21: 5951.28 | BS21: 11859.48 | BT21: 2964.8 | BU21: 7647.2 | BV21: 3918.47 | BW21: 14530.47 | BX21: 7976.19 | BY21: 2914.57 | BZ21: 11044.5 | CA21: 21935.26 | CB21: 2300.29 | CC21: 1696.12 | CD21: 2847.77 | CE21: 6844.18 | CF21: 4100.83 | CG21: 2113.24 | CH21: 4316.18 | CI21: 10530.25 | CL21: 3362.1703 | CM21: 6099.8945 | CN21: 3014.4419 | CO21: 4727.9073 | CP21: 6365.0271 | CQ21: 8365.3402 | CR21: 11508.608 | CS21: 9672.3797 | CT21: 11544.729 | DG21: 1 | DH21: 1 | DI21: 7 | DJ21: 2 | DQ21: 0.32 | DR21: 244.27 | DS21: 2508.01 | DT21: 975.37 | EA21: 0.32
A22: 98951 | B22: COM | C22: =A22&B22 -> 98951COM | E22: 88 | F22: 114 | G22: 85 | H22: 88 | I22: 86 | J22: 109 | K22: 81 | L22: 75 | M22: 88 | O22: 64362.45 | P22: 1922.59 | Q22: 1690.43 | R22: 67975.47 | S22: 76535.55 | T22: 21184.04 | U22: 3957.03 | V22: 101676.62 | W22: 37253.46 | X22: 30018.66 | Y22: 20585.01 | Z22: 87857.13 | AA22: 43359.49 | AB22: 18643.46 | AC22: 8806.75 | AD22: 70809.7 | AE22: 38671.96 | AF22: 12576.05 | AG22: 9223.65 | AH22: 60471.66 | AI22: 26262.47 | AJ22: 8482.65 | AK22: 16803.69 | AL22: 51548.81 | AM22: 23891.44 | AN22: 17779.52 | AO22: 19019.06 | AP22: 60690.02 | AQ22: 30546.7 | AR22: 10574.39 | AS22: 22148.74 | AT22: 63269.83 | AU22: 25371.59 | AV22: 6949.61 | AW22: 23036.6 | AX22: 55357.8 | AZ22: 296.75 | BA22: 106.13 | BB22: 61.51 | BC22: 464.39 | BD22: 138.28 | BE22: 284.01 | BF22: 167.64 | BG22: 589.93 | BH22: 198.38 | BI22: 28.57 | BJ22: 207.35 | BK22: 434.3 | BL22: 187.22 | BM22: 198.38 | BN22: 235.92 | BO22: 621.52 | BP22: 170.1 | BQ22: 187.22 | BR22: 434.3 | BS22: 791.62 | BT22: 108.53 | BU22: 128.36 | BV22: 105.51 | BW22: 342.4 | BX22: 113.23 | BY22: 108.53 | BZ22: 233.87 | CA22: 455.63 | CB22: 116.95 | CC22: 113.23 | CD22: 342.4 | CE22: 572.58 | CF22: 30.46 | CG22: 116.95 | CH22: 455.63 | CI22: 603.04 | CL22: 2052.405 | CM22: 4967.1194 | CN22: 9346.3794 | CO22: 5606.5842 | CP22: 4520.5597 | CQ22: 6351.2317 | CR22: 7672.0194 | CS22: 8736.6338 | CT22: 8413.1357 | DG22: 3 | DJ22: 6 | DL22: 1 | DQ22: 455.93 | DT22: 14372.61 | DV22: 33.87 | EA22: 276.65 | ED22: 48.04 | EF22: 33.87 | EG22: 55.91
A23: 98952 | B23: COM | C23: =A23&B23 -> 98952COM | E23: 3 | F23: 1 | G23: 1 | H23: 4 | I23: 5 | J23: 5 | K23: 4 | L23: 2 | M23: 3 | O23: 1480.77 | P23: 245.28 | Q23: 0 | R23: 1726.05 | S23: 0.87 | T23: 0 | U23: 0 | V23: 0.87 | W23: 91.52 | X23: 0 | Y23: 0 | Z23: 91.52 | AA23: 1334.53 | AB23: 91.52 | AC23: 0 | AD23: 1426.05 | AE23: 1296.7 | AF23: 125.93 | AG23: 91.52 | AH23: 1514.15 | AI23: 177.28 | AJ23: 78.62 | AK23: 178.48 | AL23: 434.38 | AM23: 1433.71 | AN23: 55.32 | AO23: 257.1 | AP23: 1746.13 | AQ23: 65.25 | AR23: 38.34 | AS23: 312.42 | AT23: 416.01 | AU23: 175.81 | AV23: 36.48 | AW23: 350.76 | AX23: 563.05 | BH23: 91.52 | BK23: 91.52 | BL23: 86.96 | BM23: 91.52 | BO23: 178.48 | BP23: 78.62 | BQ23: 86.96 | BR23: 91.52 | BS23: 257.1 | BT23: 55.32 | BU23: 78.62 | BV23: 178.48 | BW23: 312.42 | BX23: 38.34 | BY23: 55.32 | BZ23: 257.1 | CA23: 350.76 | CB23: 36.48 | CC23: 38.34 | CD23: 312.42 | CE23: 387.24 | CF23: 16.34 | CG23: 36.48 | CH23: 350.76 | CI23: 403.58 | CL23: 48.575268 | CM23: 0.026985017 | CN23: 2.9980209 | CO23: 55.714509 | CP23: 70.870601 | CQ23: 63.625453 | CR23: 123.88235 | CS23: 104.51717 | CT23: 118.20499 | DJ23: 1 | DT23: 114.67 | ED23: 114.67
A24: 98953 | B24: COM | C24: =A24&B24 -> 98953COM | E24: 50 | F24: 45 | G24: 58 | H24: 66 | I24: 57 | J24: 46 | K24: 40 | L24: 59 | M24: 48 | O24: 10780.74 | P24: 3413.24 | Q24: 3220.65 | R24: 17414.63 | S24: 9165.6 | T24: 5173.53 | U24: 2982.85 | V24: 17321.98 | W24: 10821.9 | X24: 4981.04 | Y24: 4281.27 | Z24: 20084.21 | AA24: 10872.19 | AB24: 6630.19 | AC24: 6730.21 | AD24: 24232.59 | AE24: 7229.48 | AF24: 5613.28 | AG24: 9852.49 | AH24: 22695.25 | AI24: 4365.09 | AJ24: 4561.92 | AK24: 11590.42 | AL24: 20517.43 | AM24: 4784.8 | AN24: 3438.34 | AO24: 10939.72 | AP24: 19162.86 | AQ24: 94285.34 | AR24: 3716.02 | AS24: 13213.97 | AT24: 111215.33 | AU24: 7082.65 | AV24: 4838.43 | AW24: 12767.19 | AX24: 24688.27 | CL24: 1208.311 | CM24: 1409.6099 | CN24: 1930.3971 | CO24: 2852.6807 | CP24: 3380.3852 | CQ24: 3882.7649 | CR24: 3629.4529 | CS24: 7156.9747 | CT24: 4564.4218 | DI24: 3 | DL24: 1 | DS24: 3182.72 | DV24: 26.57 | EF24: 26.57
A25: 99323 | B25: COM | C25: =A25&B25 -> 99323COM | E25: 14 | F25: 9 | G25: 10 | H25: 10 | I25: 19 | J25: 13 | K25: 9 | L25: 14 | M25: 14 | O25: 4953.42 | P25: 355.81 | Q25: 493.61 | R25: 5802.84 | S25: 3706.74 | T25: 233.52 | U25: 167.96 | V25: 4108.22 | W25: 2421.11 | X25: 223.05 | Y25: 401.48 | Z25: 3045.64 | AA25: 1278.02 | AB25: 68.47 | AC25: 624.53 | AD25: 1971.02 | AE25: 3525.42 | AF25: 406.22 | AG25: 693 | AH25: 4624.64 | AI25: 2767.63 | AJ25: 414.25 | AK25: 1002.23 | AL25: 4184.11 | AM25: 2045.43 | AN25: 250.54 | AO25: 1331.02 | AP25: 3626.99 | AQ25: 4715.33 | AR25: 245.63 | AS25: 1581.56 | AT25: 6542.52 | AU25: 2192.39 | AV25: 1038.92 | AW25: 1827.19 | AX25: 5058.5 | CL25: 255.69836 | CM25: 173.89731 | CN25: 205.01934 | CO25: 229.31944 | CP25: 324.20409 | CQ25: 406.41926 | CR25: 473.85821 | CS25: 656.48702 | CT25: 705.72831 | DJ25: 1 | DT25: 94.92
A26: 99324 | B26: COM | C26: =A26&B26 -> 99324COM | E26: 7 | F26: 7 | G26: 10 | H26: 5 | I26: 4 | J26: 6 | K26: 2 | L26: 4 | M26: 9 | O26: 2004.59 | P26: 111.42 | Q26: 0 | R26: 2116.01 | S26: 673.98 | T26: 184.1 | U26: 0 | V26: 858.08 | W26: 1486.09 | X26: 253.59 | Y26: 110.43 | Z26: 1850.11 | AA26: 512.35 | AB26: 599.51 | AC26: 304.98 | AD26: 1416.84 | AE26: 341.18 | AF26: 127.73 | AG26: 572.43 | AH26: 1041.34 | AI26: 146.85 | AJ26: 140.32 | AK26: 700.16 | AL26: 987.33 | AM26: 107.79 | AN26: 56.42 | AO26: 776.37 | AP26: 940.58 | AQ26: 338.91 | AR26: 107.79 | AS26: 832.79 | AT26: 1279.49 | AU26: 1459.81 | AV26: 262.05 | AW26: 940.58 | AX26: 2662.44 | CL26: 54.085902 | CM26: 35.050497 | CN26: 100.64479 | CO26: 154.65177 | CP26: 181.98449 | CQ26: 220.64544 | CR26: 236.40718 | CS26: 283.67245 | CT26: 352.14934 | DG26: 1 | DQ26: 31.15
A27: 99328 | B27: COM | C27: =A27&B27 -> 99328COM | E27: 36 | F27: 24 | G27: 43 | H27: 39 | I27: 32 | J27: 31 | K27: 31 | L27: 30 | M27: 33 | O27: 12481.18 | P27: 2787.41 | Q27: 11033.61 | R27: 26302.2 | S27: 8186.04 | T27: 4960.69 | U27: 12322.69 | V27: 25469.42 | W27: 12221.81 | X27: 5905.06 | Y27: 11055.34 | Z27: 29182.21 | AA27: 20059.52 | AB27: 8336.8 | AC27: 13916.77 | AD27: 42313.09 | AE27: 6113.59 | AF27: 5915.32 | AG27: 16649.93 | AH27: 28678.84 | AI27: 5275.13 | AJ27: 3927.99 | AK27: 13776.41 | AL27: 22979.53 | AM27: 6285.47 | AN27: 3036.72 | AO27: 13367.7 | AP27: 22689.89 | AQ27: 5163.33 | AR27: 2461 | AS27: 8875.38 | AT27: 16499.71 | AU27: 5800.57 | AV27: 1885.46 | AW27: 9392.3 | AX27: 17078.33 | CL27: 3080.5094 | CM27: 3641.7627 | CN27: 3840.498 | CO27: 5368.0999 | CP27: 5320.0081 | CQ27: 4501.2745 | CR27: 4361.1048 | CS27: 3166.6308 | CT27: 3254.9229 | DI27: 1 | DS27: 81.48 | EC27: 81.48
A28: 99329 | B28: COM | C28: =A28&B28 -> 99329COM | E28: 2 | F28: 2 | G28: 4 | H28: 6 | I28: 3 | J28: 3 | K28: 3 | L28: 3 | M28: 1 | O28: 140.56 | P28: 103.03 | Q28: 183.18 | R28: 426.77 | S28: 171.79 | T28: 140.56 | U28: 286.21 | V28: 598.56 | W28: 476.32 | X28: 171.79 | Y28: 426.77 | Z28: 1074.88 | AA28: 677.03 | AB28: 476.32 | AC28: 598.56 | AD28: 1751.91 | AE28: 424.3 | AF28: 223.97 | AG28: 770.12 | AH28: 1418.39 | AI28: 295.82 | AJ28: 424.3 | AK28: 694.09 | AL28: 1414.21 | AM28: 287.89 | AN28: 89.64 | AO28: 824.57 | AP28: 1202.1 | AQ28: 239.25 | AR28: 63.39 | AS28: 906.46 | AT28: 1209.1 | AU28: 70.34 | AV28: 35.58 | AW28: 851.55 | AX28: 957.47 | CL28: 52.542938 | CM28: 85.962791 | CN28: 143.32359 | CO28: 233.89331 | CP28: 247.04581 | CQ28: 245.27491 | CR28: 258.62697 | CS28: 301.01695 | CT28: 274.71924
A29: 99347 | B29: COM | C29: =A29&B29 -> 99347COM | E29: 12 | F29: 12 | G29: 19 | H29: 18 | I29: 25 | J29: 18 | K29: 21 | L29: 13 | M29: 18 | O29: 3711.67 | P29: 476.78 | Q29: 508.46 | R29: 4696.91 | S29: 1522.3 | T29: 396.5 | U29: 943.61 | V29: 2862.41 | W29: 4951.82 | X29: 572.27 | Y29: 1320.82 | Z29: 6844.91 | AA29: 2597.36 | AB29: 2037.51 | AC29: 1650.41 | AD29: 6285.28 | AE29: 6447.62 | AF29: 2163.63 | AG29: 3241.57 | AH29: 11852.82 | AI29: 2051.87 | AJ29: 1284.68 | AK29: 2248.14 | AL29: 5584.69 | AM29: 2393.35 | AN29: 982.05 | AO29: 2756.99 | AP29: 6132.39 | AQ29: 2359.56 | AR29: 1365.18 | AS29: 3482.97 | AT29: 7207.71 | AU29: 3278.63 | AV29: 848.87 | AW29: 3962.5 | AX29: 8090 | AZ29: 266.65 | BA29: 25.71 | BC29: 292.36 | BD29: 226.98 | BG29: 226.98 | BH29: 252.84 | BI29: 226.98 | BK29: 479.82 | BL29: 360.09 | BM29: 189.36 | BO29: 549.45 | BP29: 227.36 | BQ29: 124.39 | BS29: 351.75 | BT29: 63.84 | BW29: 63.84 | BX29: 209.92 | BY29: 1.84 | CA29: 211.76 | CB29: 151.71 | CE29: 151.71 | CF29: 151.28 | CI29: 151.28 | CL29: 235.79018 | CM29: 307.92069 | CN29: 561.16776 | CO29: 731.02309 | CP29: 1247.2592 | CQ29: 819.09982 | CR29: 959.73946 | CS29: 1282.424 | CT29: 1396.8785 | DI29: 1 | DJ29: 1 | DK29: 2 | DS29: 277.4 | DT29: 3.48 | DU29: 79.25 | EE29: 26.79
A30: 99348 | B30: COM | C30: =A30&B30 -> 99348COM | E30: 1 | G30: 1 | H30: 2 | I30: 4 | J30: 5 | K30: 4 | L30: 4 | M30: 4 | O30: 135.07 | P30: 0 | Q30: 0 | R30: 135.07 | W30: 229.72 | X30: 0 | Y30: 0 | Z30: 229.72 | AA30: 6.78 | AB30: 0 | AC30: 0 | AD30: 6.78 | AE30: 242.24 | AF30: 6.68 | AG30: 0 | AH30: 248.92 | AI30: 976.08 | AJ30: 1.88 | AK30: 0 | AL30: 977.96 | AM30: 938.89 | AN30: 60.5 | AO30: 1.88 | AP30: 1001.27 | AQ30: 1025.57 | AR30: 30.41 | AS30: 0 | AT30: 1055.98 | AU30: 1046.51 | AV30: 22.74 | AW30: 0 | AX30: 1069.25 | CL30: 3.2471255 | CN30: 7.5251898 | CO30: 0.24469557 | CP30: 7.2940653 | CQ30: 28.37911 | CR30: 33.866137 | CS30: 31.189329 | CT30: 26.674665
A31: 99360 | B31: COM | C31: =A31&B31 -> 99360COM | E31: 13 | F31: 12 | G31: 3 | H31: 4 | I31: 16 | J31: 16 | K31: 7 | L31: 10 | M31: 12 | O31: 4475.98 | P31: 972.7 | Q31: 965.09 | R31: 6413.77 | S31: 3478.13 | T31: 182.5 | U31: 1313.8 | V31: 4974.43 | W31: 775.15 | X31: 505.96 | Y31: 1352.19 | Z31: 2633.3 | AA31: 1698.72 | AB31: 610.25 | AC31: 1357.05 | AD31: 3666.02 | AE31: 7703.62 | AF31: 1356.19 | AG31: 2378.24 | AH31: 11438.05 | AI31: 2562.11 | AJ31: 1430.59 | AK31: 3545.52 | AL31: 7538.22 | AM31: 2247.42 | AN31: 1626.44 | AO31: 4532.06 | AP31: 8405.92 | AQ31: 2062.93 | AR31: 2173.48 | AS31: 6125.79 | AT31: 10362.2 | AU31: 1786.31 | AV31: 1922.97 | AW31: 8299.27 | AX31: 12008.55 | CL31: 389.3692 | CM31: 442.46743 | CN31: 426.59695 | CO31: 497.44508 | CP31: 985.38234 | CQ31: 1225.9582 | CR31: 1526.8677 | CS31: 2179.4432 | CT31: 2814.0622
A32: 99361 | B32: COM | C32: =A32&B32 -> 99361COM | E32: 10 | F32: 11 | G32: 15 | H32: 17 | I32: 10 | J32: 11 | K32: 9 | L32: 28 | M32: 27 | O32: 938.62 | P32: 23.84 | Q32: 0 | R32: 962.46 | S32: 1151.25 | T32: 23.56 | U32: 11.55 | V32: 1186.36 | W32: 1905.07 | X32: 204.08 | Y32: 23.22 | Z32: 2132.37 | AA32: 1528.38 | AB32: 1303.22 | AC32: 50.12 | AD32: 2881.72 | AE32: 1134.76 | AF32: 488.89 | AG32: 761.04 | AH32: 2384.69 | AI32: 1292.8 | AJ32: 594.98 | AK32: 1198.9 | AL32: 3086.68 | AM32: 1079.26 | AN32: 731.53 | AO32: 1500.16 | AP32: 3310.95 | AQ32: 4574.44 | AR32: 628.32 | AS32: 2159.5 | AT32: 7362.26 | AU32: 2778.12 | AV32: 1214.25 | AW32: 2681.12 | AX32: 6673.49 | CL32: 23.82603 | CM32: 40.337036 | CN32: 86.967478 | CO32: 176.92265 | CP32: 280.88465 | CQ32: 435.54336 | CR32: 530.16886 | CS32: 866.16036 | CT32: 1003.3317 | DG32: 1 | DQ32: 389.95
A33: 99362 | B33: COM | C33: =A33&B33 -> 99362COM | E33: 70 | F33: 62 | G33: 98 | H33: 135 | I33: 150 | J33: 92 | K33: 97 | L33: 104 | M33: 126 | O33: 12678.68 | P33: 1557.65 | Q33: 3775.19 | R33: 18011.52 | S33: 9103.82 | T33: 1819.28 | U33: 3423.84 | V33: 14346.94 | W33: 19252.04 | X33: 2807.61 | Y33: 4184.42 | Z33: 26244.07 | AA33: 28713.23 | AB33: 14258.59 | AC33: 6223.88 | AD33: 49195.7 | AE33: 45283.34 | AF33: 14418.44 | AG33: 11726.35 | AH33: 71428.13 | AI33: 25210.76 | AJ33: 12626.28 | AK33: 17246.72 | AL33: 55083.76 | AM33: 17292.34 | AN33: 8965.93 | AO33: 27355.14 | AP33: 53613.41 | AQ33: 25047.3 | AR33: 14016.27 | AS33: 29128.22 | AT33: 68191.79 | AU33: 27589.99 | AV33: 10002.36 | AW33: 35529.39 | AX33: 73121.74 | CL33: 1288.0955 | CM33: 1257.5671 | CN33: 1984.526 | CO33: 3981.9664 | CP33: 5540.4935 | CQ33: 6773.3233 | CR33: 9266.4694 | CS33: 11072.149 | CT33: 12648.891 | DG33: 1 | DH33: 1 | DI33: 2 | DJ33: 11 | DK33: 1 | DL33: 1 | DQ33: 3.02 | DR33: 15.02 | DS33: 477.9 | DT33: 974.43 | DU33: 20.86 | DV33: 235.32 | EC33: 237.12 | ED33: 387.67 | EG33: 340.63
A34: 99363 | B34: COM | C34: =A34&B34 -> 99363COM | E34: 1 | F34: 1 | H34: 2 | I34: 5 | J34: 8 | K34: 3 | L34: 2 | M34: 5 | O34: 23.71 | P34: 21.48 | Q34: 0 | R34: 45.19 | S34: 294.05 | T34: 0 | U34: 0 | V34: 294.05 | AA34: 134.3 | AB34: 0 | AC34: 0 | AD34: 134.3 | AE34: 438.87 | AF34: 0 | AG34: 0 | AH34: 438.87 | AI34: 1768.02 | AJ34: 27.93 | AK34: 42.89 | AL34: 1838.84 | AM34: 189.73 | AN34: 50.31 | AO34: 70.82 | AP34: 310.86 | AQ34: 56.26 | AR34: 38.76 | AS34: 9.58 | AT34: 104.6 | AU34: 427.54 | AV34: 44.71 | AW34: 48.34 | AX34: 520.59 | CL34: 1.7064435 | CM34: 9.1206254 | CO34: 4.8469933 | CP34: 12.472106 | CQ34: 65.900147 | CR34: 30.464579 | CS34: 7.5892381 | CT34: 28.733005
A35: 98603 | B35: RES | C35: =A35&B35 -> 98603RES | E35: 2 | F35: 1 | G35: 2 | H35: 1 | J35: 2 | K35: 3 | L35: 3 | M35: 2 | O35: 193.12 | P35: 71.94 | Q35: 0 | R35: 265.06 | S35: 134.22 | T35: 0 | U35: 0 | V35: 134.22 | W35: 314.3 | X35: 134.22 | Y35: 0 | Z35: 448.52 | AA35: 73.95 | AB35: 99.78 | AC35: 0 | AD35: 173.73 | AI35: 137.09 | AJ35: 0 | AK35: 0 | AL35: 137.09 | AM35: 240.84 | AN35: 88.96 | AO35: 0 | AP35: 329.8 | AQ35: 230.75 | AR35: 147.87 | AS35: 0 | AT35: 378.62 | AU35: 227.73 | AV35: 86.75 | AW35: 87.56 | AX35: 402.04 | CL35: 8.4488131 | CM35: 4.1631367 | CN35: 22.434902 | CO35: 10.900616 | CQ35: 3.9652829 | CR35: 14.050987 | CS35: 17.735968 | CT35: 39.344581
A36: 98901 | B36: RES | C36: =A36&B36 -> 98901RES | E36: 1791 | F36: 2003 | G36: 2437 | H36: 2457 | I36: 2589 | J36: 2271 | K36: 2081 | L36: 2064 | M36: 2182 | O36: 211556.16 | P36: 49355.3 | Q36: 106478.27 | R36: 367389.73 | S36: 266940.28 | T36: 90735.95 | U36: 86472.57 | V36: 444148.8 | W36: 331306.28 | X36: 139007.9 | Y36: 118095.2 | Z36: 588409.38 | AA36: 285711.64 | AB36: 187431.68 | AC36: 192742.46 | AD36: 665885.78 | AE36: 283319.02 | AF36: 178061.7 | AG36: 295396.06 | AH36: 756776.78 | AI36: 157353.87 | AJ36: 172107.96 | AK36: 370224.93 | AL36: 699686.76 | AM36: 136305.7 | AN36: 91769.7 | AO36: 440880.57 | AP36: 668955.97 | AQ36: 126994.15 | AR36: 102469.1 | AS36: 443670.38 | AT36: 673133.63 | AU36: 188410.44 | AV36: 83261.09 | AW36: 462572.34 | AX36: 734243.87 | AZ36: 26441.46 | BA36: 8076.58 | BB36: 25567.34 | BC36: 60085.38 | BD36: 26927.63 | BE36: 14721.25 | BF36: 22024.94 | BG36: 63673.82 | BH36: 28524.05 | BI36: 17745.99 | BJ36: 27203 | BK36: 73473.04 | BL36: 26085.85 | BM36: 19410.97 | BN36: 36126.33 | BO36: 81623.15 | BP36: 27302.66 | BQ36: 19653.85 | BR36: 49293.7 | BS36: 96250.21 | BT36: 17354.58 | BU36: 19189.3 | BV36: 60975.14 | BW36: 97519.02 | BX36: 15339.28 | BY36: 10625.55 | BZ36: 67991.79 | CA36: 93956.62 | CB36: 13706.7 | CC36: 14767.51 | CD36: 71559.49 | CE36: 100033.7 | CF36: 19009.31 | CG36: 9828.92 | CH36: 70795.22 | CI36: 99633.45 | CL36: 33106.362 | CM36: 36350.551 | CN36: 54468.237 | CO36: 80568.647 | CP36: 103841.22 | CQ36: 126596.82 | CR36: 141029.2 | CS36: 153042.28 | CT36: 157302.71 | DG36: 79 | DH36: 35 | DI36: 60 | DJ36: 92 | DK36: 37 | DL36: 30 | DQ36: 24291.68 | DR36: 11494.23 | DS36: 16501.22 | DT36: 36800.86 | DU36: 10519.58 | DV36: 7519.44 | EA36: 3171.7 | EB36: 730.68 | EC36: 3314.41 | ED36: 2358.25 | EE36: 3086.46 | EF36: 1502.08 | EG36: 1931.95
A37: 98902 | B37: RES | C37: =A37&B37 -> 98902RES | E37: 4693 | F37: 4490 | G37: 4191 | H37: 4086 | I37: 4485 | J37: 4132 | K37: 4125 | L37: 4351 | M37: 4311 | O37: 635243.51 | P37: 142831.08 | Q37: 109970.09 | R37: 888044.68 | S37: 589300.06 | T37: 183914.74 | U37: 108026.7 | V37: 881241.5 | W37: 408410.38 | X37: 309914.48 | Y37: 150061.96 | Z37: 868386.82 | AA37: 426143.77 | AB37: 262940.95 | AC37: 269245.44 | AD37: 958330.16 | AE37: 354380.16 | AF37: 330641.52 | AG37: 407762.84 | AH37: 1092784.5 | AI37: 223156.79 | AJ37: 254252.39 | AK37: 503311.56 | AL37: 980720.74 | AM37: 289886.51 | AN37: 129102.32 | AO37: 555740.97 | AP37: 974729.8 | AQ37: 346119.51 | AR37: 156930.52 | AS37: 566480.19 | AT37: 1069530.2 | AU37: 344831.92 | AV37: 193881.03 | AW37: 581904.12 | AX37: 1120617.1 | AZ37: 53146.56 | BA37: 18696.43 | BB37: 25522.09 | BC37: 97365.08 | BD37: 46528.26 | BE37: 21774.33 | BF37: 23673.88 | BG37: 91976.47 | BH37: 36211.16 | BI37: 31191.41 | BJ37: 30909.39 | BK37: 98311.96 | BL37: 38995.5 | BM37: 26847.56 | BN37: 45527.91 | BO37: 111370.97 | BP37: 33424.16 | BQ37: 34721.6 | BR37: 65125.42 | BS37: 133271.18 | BT37: 24320.8 | BU37: 27325.06 | BV37: 77475.69 | BW37: 129121.55 | BX37: 27788.61 | BY37: 14155.25 | BZ37: 73453.91 | CA37: 115397.77 | CB37: 31822.6 | CC37: 17786.05 | CD37: 79590.6 | CE37: 129199.25 | CF37: 29417.13 | CG37: 20227.47 | CH37: 79114.34 | CI37: 128758.94 | CL37: 49070.749 | CM37: 58767.877 | CN37: 80854.011 | CO37: 113615.19 | CP37: 147505.13 | CQ37: 173950.49 | CR37: 182396 | CS37: 202568.83 | CT37: 206701.75 | DG37: 93 | DH37: 56 | DI37: 112 | DJ37: 125 | DK37: 43 | DL37: 46 | DQ37: 23031.17 | DR37: 11938.61 | DS37: 43588.68 | DT37: 46863.11 | DU37: 9870.55 | DV37: 14516.59 | EA37: 3102.07 | EB37: 2046.57 | EC37: 4601.78 | ED37: 6786.44 | EE37: 2660.06 | EF37: 1845.63 | EG37: 1727
A38: 98903 | B38: RES | C38: =A38&B38 -> 98903RES | E38: 1638 | F38: 1579 | G38: 1685 | H38: 1709 | I38: 1958 | J38: 1536 | K38: 1537 | L38: 1589 | M38: 1327 | O38: 275061.31 | P38: 87636.11 | Q38: 67222.86 | R38: 429920.28 | S38: 265584.44 | T38: 82201.84 | U38: 68401.98 | V38: 416188.26 | W38: 255838.06 | X38: 130359.84 | Y38: 93306.24 | Z38: 479504.14 | AA38: 236917.35 | AB38: 140904.84 | AC38: 152132.17 | AD38: 529954.36 | AE38: 226442.07 | AF38: 181354.85 | AG38: 211300.72 | AH38: 619097.64 | AI38: 103719.78 | AJ38: 139611.71 | AK38: 261811.37 | AL38: 505142.86 | AM38: 140825.51 | AN38: 43066.62 | AO38: 310614.76 | AP38: 494506.89 | AQ38: 138506.14 | AR38: 87443.69 | AS38: 296706.58 | AT38: 522656.41 | AU38: 109224.85 | AV38: 67052.49 | AW38: 306032.03 | AX38: 482309.37 | AZ38: 19086.36 | BA38: 11792.61 | BB38: 17447.02 | BC38: 48325.99 | BD38: 16634.29 | BE38: 8822.29 | BF38: 13278.41 | BG38: 38734.99 | BH38: 18786.04 | BI38: 12404.55 | BJ38: 14222.76 | BK38: 45413.35 | BL38: 16787.35 | BM38: 13027.91 | BN38: 20741.02 | BO38: 50556.28 | BP38: 18054.16 | BQ38: 16600.38 | BR38: 28705.41 | BS38: 63359.95 | BT38: 7659.03 | BU38: 14639.98 | BV38: 34249.49 | BW38: 56548.5 | BX38: 11094.65 | BY38: 3485.71 | BZ38: 39506.26 | CA38: 54086.62 | CB38: 8480.4 | CC38: 9379.93 | CD38: 37259.98 | CE38: 55120.31 | CF38: 6876.8 | CG38: 6487.43 | CH38: 34015.71 | CI38: 47379.94 | CL38: 27290.741 | CM38: 31243.607 | CN38: 44697.724 | CO38: 63424.234 | CP38: 78267.639 | CQ38: 90700.048 | CR38: 99114.071 | CS38: 105294.12 | CT38: 104536.83 | DG38: 20 | DH38: 29 | DI38: 18 | DJ38: 40 | DK38: 16 | DL38: 13 | DN38: 2 | DQ38: 5116.5 | DR38: 10964.56 | DS38: 13323.17 | DT38: 18140.77 | DU38: 3338.55 | DV38: 3231.23 | DX38: 2164.79 | EA38: 1413.53 | EB38: 1752.54 | EC38: 1180 | ED38: 3327.94 | EE38: 131.84 | EF38: 352.84 | EG38: 70.57
A39: 98908 | B39: RES | C39: =A39&B39 -> 98908RES | E39: 2982 | F39: 3347 | G39: 3428 | H39: 3270 | I39: 3083 | J39: 2920 | K39: 2619 | L39: 2887 | M39: 2982 | O39: 457284.55 | P39: 75247.62 | Q39: 60443.45 | R39: 592975.62 | S39: 519437.76 | T39: 147581.21 | U39: 70891.76 | V39: 737910.73 | W39: 436145.99 | X39: 240383.96 | Y39: 119362.6 | Z39: 795892.55 | AA39: 383361.37 | AB39: 236620.23 | AC39: 206209.41 | AD39: 826191.01 | AE39: 290907.9 | AF39: 221299.71 | AG39: 284366.9 | AH39: 796574.51 | AI39: 203244.25 | AJ39: 169197.36 | AK39: 341962.34 | AL39: 714403.95 | AM39: 200426.21 | AN39: 109483.88 | AO39: 360670.83 | AP39: 670580.92 | AQ39: 260112.03 | AR39: 105371.71 | AS39: 350429.68 | AT39: 715913.42 | AU39: 306548.73 | AV39: 128285.6 | AW39: 346275.4 | AX39: 781109.73 | AZ39: 20194.44 | BA39: 5809.53 | BB39: 6529.74 | BC39: 32533.71 | BD39: 19676.18 | BE39: 10778.62 | BF39: 7320.91 | BG39: 37775.71 | BH39: 15722.93 | BI39: 12723.1 | BJ39: 12522.72 | BK39: 40968.75 | BL39: 14343.46 | BM39: 11498.54 | BN39: 19195.09 | BO39: 45037.09 | BP39: 10731.94 | BQ39: 11055.81 | BR39: 23572.11 | BS39: 45359.86 | BT39: 7904.69 | BU39: 8699.06 | BV39: 28912.6 | BW39: 45516.35 | BX39: 7405.3 | BY39: 5221.7 | BZ39: 26724.35 | CA39: 39351.35 | CB39: 8589.59 | CC39: 5212.07 | CD39: 26526.69 | CE39: 40328.35 | CF39: 8921.37 | CG39: 4997 | CH39: 20238.54 | CI39: 34156.91 | CL39: 29398.213 | CM39: 44748.42 | CN39: 67404.326 | CO39: 91979.37 | CP39: 103541.72 | CQ39: 119403.4 | CR39: 120676.69 | CS39: 127236.43 | CT39: 126334.99 | DG39: 47 | DH39: 30 | DI39: 28 | DJ39: 44 | DK39: 19 | DL39: 21 | DO39: 1 | DQ39: 10075.95 | DR39: 10449.74 | DS39: 7449.88 | DT39: 18524.57 | DU39: 3098.79 | DV39: 8849.41 | DY39: 239.25 | EA39: 2882.69 | EB39: 2398.89 | EC39: 1447.2 | ED39: 1136.06 | EE39: 934.07 | EF39: 1176.55 | EG39: 1493.45
A40: 98920 | B40: RES | C40: =A40&B40 -> 98920RES | E40: 1 | G40: 1 | H40: 1 | I40: 1 | M40: 1 | O40: 104.22 | P40: 0 | Q40: 0 | R40: 104.22 | W40: 109.1 | X40: 0 | Y40: 0 | Z40: 109.1 | AA40: 11.73 | AB40: 0 | AC40: 0 | AD40: 11.73 | AE40: 101.13 | AF40: 11.73 | AG40: 0 | AH40: 112.86 | AU40: 39.25 | AV40: 0 | AW40: 0 | AX40: 39.25 | CL40: 2.5054817 | CN40: 3.5739083 | CO40: 0.42334499 | CP40: 3.5938033 | CT40: 0.94079764
A41: 98921 | B41: RES | C41: =A41&B41 -> 98921RES | E41: 87 | F41: 88 | G41: 85 | H41: 89 | I41: 85 | J41: 84 | K41: 85 | L41: 74 | M41: 76 | O41: 12756.49 | P41: 3236.3 | Q41: 2495.07 | R41: 18487.86 | S41: 13815.63 | T41: 6037.08 | U41: 2844.39 | V41: 22697.1 | W41: 10690.97 | X41: 7259.9 | Y41: 5171.68 | Z41: 23122.55 | AA41: 10443.22 | AB41: 7247.15 | AC41: 9083.09 | AD41: 26773.46 | AE41: 7307 | AF41: 7092.66 | AG41: 11711.38 | AH41: 26111.04 | AI41: 5378.38 | AJ41: 5313.97 | AK41: 14838.57 | AL41: 25530.92 | AM41: 5393.9 | AN41: 3522.83 | AO41: 16914.68 | AP41: 25831.41 | AQ41: 5242.93 | AR41: 3369.01 | AS41: 17692.01 | AT41: 26303.95 | AU41: 6870.39 | AV41: 3681.09 | AW41: 18027.86 | AX41: 28579.34 | AZ41: 2882.61 | BA41: 849.16 | BB41: 900.12 | BC41: 4631.89 | BD41: 2416.88 | BE41: 1750.54 | BF41: 976.97 | BG41: 5144.39 | BH41: 2035.99 | BI41: 1106.4 | BJ41: 1405.99 | BK41: 4548.38 | BL41: 2331 | BM41: 1641.87 | BN41: 2238.15 | BO41: 6211.02 | BP41: 1839.72 | BQ41: 1972.58 | BR41: 3445.71 | BS41: 7258.01 | BT41: 1396.54 | BU41: 1437.96 | BV41: 3707.93 | BW41: 6542.43 | BX41: 1367.93 | BY41: 1071.26 | BZ41: 4304.36 | CA41: 6743.55 | CB41: 1440.97 | CC41: 1021.32 | CD41: 4930.99 | CE41: 7393.28 | CF41: 1727.49 | CG41: 1208.57 | CH41: 4690.83 | CI41: 7626.89 | CL41: 1073.2999 | CM41: 1586.409 | CN41: 2366.2697 | CO41: 3556.9912 | CP41: 4007.4023 | CQ41: 4923.8442 | CR41: 5415.8718 | CS41: 6053.3215 | CT41: 6149.747 | DG41: 5 | DH41: 1 | DI41: 2 | DJ41: 1 | DL41: 1 | DQ41: 886.18 | DR41: 448.52 | DS41: 820.43 | DT41: 360.39 | DV41: 598.8 | EA41: 466.46 | EC41: 41.56
A42: 98923 | B42: RES | C42: =A42&B42 -> 98923RES | E42: 106 | F42: 136 | G42: 130 | H42: 143 | I42: 123 | J42: 127 | K42: 109 | L42: 114 | M42: 102 | O42: 19897.85 | P42: 2541.44 | Q42: 980.11 | R42: 23419.4 | S42: 23780.39 | T42: 6906.65 | U42: 1246.11 | V42: 31933.15 | W42: 21373.35 | X42: 9758.59 | Y42: 3386.71 | Z42: 34518.65 | AA42: 22461.25 | AB42: 12435.64 | AC42: 7512.19 | AD42: 42409.08 | AE42: 16138.2 | AF42: 13775.51 | AG42: 11386.79 | AH42: 41300.5 | AI42: 10997.46 | AJ42: 10788 | AK42: 16462.07 | AL42: 38247.53 | AM42: 8875.15 | AN42: 6099.25 | AO42: 17004.41 | AP42: 31978.81 | AQ42: 10041.35 | AR42: 5730.64 | AS42: 16265.51 | AT42: 32037.5 | AU42: 9092.72 | AV42: 5511.26 | AW42: 16659.29 | AX42: 31263.27 | AZ42: 808.04 | BA42: 79.52 | BB42: 19.15 | BC42: 906.71 | BD42: 1275.55 | BE42: 346.07 | BF42: 98.67 | BG42: 1720.29 | BH42: 1142.55 | BI42: 940.67 | BJ42: 50.7 | BK42: 2133.92 | BL42: 1103.72 | BM42: 1081.44 | BN42: 297.83 | BO42: 2482.99 | BP42: 856.8 | BQ42: 1059.59 | BR42: 794.53 | BS42: 2710.92 | BT42: 656.55 | BU42: 705.54 | BV42: 822.14 | BW42: 2184.23 | BX42: 559.13 | BY42: 436.5 | BZ42: 292.53 | CA42: 1288.16 | CB42: 542.44 | CC42: 326.57 | CD42: 166.46 | CE42: 1035.47 | CF42: 501.17 | CG42: 334.05 | CH42: 144.38 | CI42: 979.6 | CL42: 846.69781 | CM42: 1572.3277 | CN42: 2472.981 | CO42: 3972.1871 | CP42: 4575.2228 | CQ42: 5988.8642 | CR42: 5742.1792 | CS42: 5912.3975 | CT42: 5896.2144 | DG42: 3 | DH42: 1 | DI42: 3 | DQ42: 230.84 | DR42: 405.04 | DS42: 780.25 | EA42: 122.73 | EC42: 241.51
A43: 98930 | B43: RES | C43: =A43&B43 -> 98930RES | E43: 668 | F43: 753 | G43: 918 | H43: 942 | I43: 924 | J43: 833 | K43: 727 | L43: 683 | M43: 761 | O43: 87553.86 | P43: 8405.55 | Q43: 17914.18 | R43: 113873.59 | S43: 103623.11 | T43: 27085.84 | U43: 11801.79 | V43: 142510.74 | W43: 130320.63 | X43: 44537.58 | Y43: 18084.32 | Z43: 192942.53 | AA43: 114106.44 | AB43: 68575.95 | AC43: 41844.14 | AD43: 224526.53 | AE43: 101468.93 | AF43: 63900.12 | AG43: 72169.82 | AH43: 237538.87 | AI43: 59219.13 | AJ43: 59824.4 | AK43: 93953.51 | AL43: 212997.04 | AM43: 48916.43 | AN43: 32210.88 | AO43: 110876.69 | AP43: 192004 | AQ43: 49275.73 | AR43: 32198.93 | AS43: 112273.18 | AT43: 193747.84 | AU43: 69397.45 | AV43: 29282.87 | AW43: 113654.62 | AX43: 212334.94 | AZ43: 14314.01 | BA43: 898.44 | BB43: 4278.46 | BC43: 19490.91 | BD43: 15583.86 | BE43: 6264.21 | BF43: 2816.44 | BG43: 24664.51 | BH43: 15306.12 | BI43: 8129.05 | BJ43: 4034.52 | BK43: 27469.69 | BL43: 13000.28 | BM43: 10840.98 | BN43: 8394.86 | BO43: 32236.12 | BP43: 13169.52 | BQ43: 9490.47 | BR43: 13070.39 | BS43: 35730.38 | BT43: 7179.86 | BU43: 9156.1 | BV43: 15417.93 | BW43: 31753.89 | BX43: 6577.45 | BY43: 5208.92 | BZ43: 18187.94 | CA43: 29974.31 | CB43: 6001.9 | CC43: 5250.97 | CD43: 17373.99 | CE43: 28626.86 | CF43: 7968.86 | CG43: 3936.16 | CH43: 15771.9 | CI43: 27676.92 | CL43: 6824.4519 | CM43: 8174.8665 | CN43: 13050.846 | CO43: 21671.368 | CP43: 27538.182 | CQ43: 33941.636 | CR43: 36600.552 | CS43: 39687.208 | CT43: 39820.561 | DG43: 18 | DH43: 10 | DI43: 10 | DJ43: 16 | DK43: 5 | DL43: 10 | DQ43: 9598.92 | DR43: 3606.48 | DS43: 2665.49 | DT43: 6046.86 | DU43: 416.1 | DV43: 1740.46 | EA43: 1549.86 | EB43: 1648.21 | EC43: 113.23 | ED43: 110.47 | EE43: 303.71 | EF43: 143.39 | EG43: 1226.27
A44: 98932 | B44: RES | C44: =A44&B44 -> 98932RES | E44: 521 | F44: 547 | G44: 528 | H44: 517 | I44: 482 | J44: 469 | K44: 439 | L44: 455 | M44: 458 | O44: 84227.48 | P44: 16710.31 | Q44: 12157.66 | R44: 113095.45 | S44: 88716.45 | T44: 31053.22 | U44: 14427.03 | V44: 134196.7 | W44: 70336.77 | X44: 44143.38 | Y44: 26565.46 | Z44: 141045.61 | AA44: 61586.56 | AB44: 40017.84 | AC44: 44094.63 | AD44: 145699.03 | AE44: 44448.11 | AF44: 36544.01 | AG44: 59653.69 | AH44: 140645.81 | AI44: 30962.23 | AJ44: 28375.98 | AK44: 71097.16 | AL44: 130435.37 | AM44: 30922.22 | AN44: 17265.45 | AO44: 73155.1 | AP44: 121342.77 | AQ44: 41773.39 | AR44: 18218.01 | AS44: 69051.3 | AT44: 129042.7 | AU44: 42912.85 | AV44: 23719.23 | AW44: 71176.01 | AX44: 137808.09 | AZ44: 11937.73 | BA44: 3160.13 | BB44: 2438.84 | BC44: 17536.7 | BD44: 11078.33 | BE44: 6068.97 | BF44: 3447.7 | BG44: 20595 | BH44: 7722.84 | BI44: 6648.52 | BJ44: 4231.22 | BK44: 18602.58 | BL44: 7659.59 | BM44: 5417.86 | BN44: 6665 | BO44: 19742.45 | BP44: 5719.41 | BQ44: 5568.22 | BR44: 8601.08 | BS44: 19888.71 | BT44: 3912.93 | BU44: 4133.22 | BV44: 9777.99 | BW44: 17824.14 | BX44: 4150.4 | BY44: 2446.1 | BZ44: 9618.42 | CA44: 16214.92 | CB44: 5822.6 | CC44: 3007.7 | CD44: 8977.53 | CE44: 17807.83 | CF44: 6322.53 | CG44: 4656.17 | CH44: 9739.11 | CI44: 20717.81 | CL44: 5810.1709 | CM44: 8657.8896 | CN44: 13279.641 | CO44: 18059.668 | CP44: 20643.301 | CQ44: 23969.027 | CR44: 23808.253 | CS44: 24611.212 | CT44: 25300.792 | DG44: 8 | DH44: 6 | DI44: 7 | DJ44: 10 | DK44: 5 | DL44: 8 | DQ44: 2243.08 | DR44: 2378.04 | DS44: 4287.18 | DT44: 1345.67 | DU44: 1946.87 | DV44: 5438.67 | EA44: 54.33 | EB44: 1013.78 | EC44: 680.06 | ED44: 509.74 | EE44: 1800.21 | EF44: 45.06 | EG44: 127.51
A45: 98933 | B45: RES | C45: =A45&B45 -> 98933RES | E45: 76 | F45: 77 | G45: 88 | H45: 85 | I45: 78 | J45: 71 | K45: 51 | L45: 50 | M45: 56 | O45: 12246.39 | P45: 3249.95 | Q45: 3097.29 | R45: 18593.63 | S45: 13925.15 | T45: 3103.72 | U45: 1998.17 | V45: 19027.04 | W45: 13556.14 | X45: 6335.58 | Y45: 2846.39 | Z45: 22738.11 | AA45: 10777.73 | AB45: 5924.31 | AC45: 5684.84 | AD45: 22386.88 | AE45: 9460.75 | AF45: 5850.67 | AG45: 8776.12 | AH45: 24087.54 | AI45: 5200.94 | AJ45: 5156.8 | AK45: 11593.66 | AL45: 21951.4 | AM45: 3660.93 | AN45: 2529.21 | AO45: 13770.81 | AP45: 19960.95 | AQ45: 4023.64 | AR45: 2318.93 | AS45: 15205.09 | AT45: 21547.66 | AU45: 5550.61 | AV45: 2666.85 | AW45: 16521.57 | AX45: 24739.03 | AZ45: 3334.56 | BA45: 1173.05 | BB45: 1768.22 | BC45: 6275.83 | BD45: 2778.98 | BE45: 749.05 | BF45: 323.87 | BG45: 3851.9 | BH45: 3065.47 | BI45: 1497.79 | BJ45: 263.73 | BK45: 4826.99 | BL45: 2043.41 | BM45: 1317.4 | BN45: 796.62 | BO45: 4157.43 | BP45: 1754.18 | BQ45: 1145.31 | BR45: 1529.12 | BS45: 4428.61 | BT45: 873.42 | BU45: 1012.45 | BV45: 2104.65 | BW45: 3990.52 | BX45: 731.98 | BY45: 647.31 | BZ45: 2306.77 | CA45: 3686.06 | CB45: 620.12 | CC45: 473.66 | CD45: 2757.69 | CE45: 3851.47 | CF45: 1028.48 | CG45: 503.56 | CH45: 3078.46 | CI45: 4610.5 | CL45: 1205.4687 | CM45: 1157.9438 | CN45: 1765.2908 | CO45: 2493.852 | CP45: 3149.1381 | CQ45: 3954.1914 | CR45: 4361.4529 | CS45: 5145.025 | CT45: 5568.6134 | DG45: 1 | DH45: 2 | DI45: 5 | DJ45: 1 | DQ45: 34.19 | DR45: 1385.06 | DS45: 3281.45 | DT45: 296.33 | EB45: 88.06 | EC45: 152.79
A46: 98935 | B46: RES | C46: =A46&B46 -> 98935RES | E46: 156 | F46: 189 | G46: 229 | H46: 232 | I46: 304 | J46: 215 | K46: 190 | L46: 180 | M46: 170 | O46: 8444.06 | P46: 18310.15 | Q46: 8667.24 | R46: 35421.45 | S46: 33708.55 | T46: 9734.06 | U46: 6787.23 | V46: 50229.84 | W46: 41315.9 | X46: 15953.73 | Y46: 9005.35 | Z46: 66274.98 | AA46: 35757.98 | AB46: 25071.44 | AC46: 17161.64 | AD46: 77991.06 | AE46: 48841.27 | AF46: 22491.9 | AG46: 28734.87 | AH46: 100068.04 | AI46: 18100.7 | AJ46: 18309 | AK46: 36491.54 | AL46: 72901.24 | AM46: 15209.76 | AN46: 2723.68 | AO46: 50545.81 | AP46: 68479.25 | AQ46: 4198.7 | AR46: 21141.87 | AS46: 42852.56 | AT46: 68193.13 | AU46: 17222.36 | AV46: 2865.48 | AW46: 50175.95 | AX46: 70263.79 | AZ46: 766.08 | BA46: 3698.73 | BB46: 1753.15 | BC46: 6217.96 | BD46: 4964.58 | BE46: 1423.32 | BF46: 1553.66 | BG46: 7941.56 | BH46: 5577.07 | BI46: 2466.31 | BJ46: 645.25 | BK46: 8688.63 | BL46: 4345.66 | BM46: 4174.39 | BN46: 2200.45 | BO46: 10720.5 | BP46: 6750.87 | BQ46: 3042.97 | BR46: 3916.88 | BS46: 13710.72 | BT46: 2452.98 | BU46: 2158.29 | BV46: 5168.17 | BW46: 9779.44 | BX46: 1984.15 | BZ46: 7752.7 | CA46: 9736.85 | CB46: 95.81 | CC46: 4011.38 | CD46: 7199.16 | CE46: 11306.35 | CF46: 2801.5 | CH46: 8693.11 | CI46: 11494.61 | CL46: 3240.0272 | CM46: 3449.5333 | CN46: 5163.5071 | CO46: 8237.7284 | CP46: 11023.327 | CQ46: 12657.751 | CR46: 15571.252 | CS46: 15409.286 | CT46: 16554.554 | DG46: 3 | DH46: 7 | DI46: 6 | DJ46: 4 | DK46: 3 | DL46: 1 | DQ46: 1307.37 | DR46: 3262.51 | DS46: 3279.8 | DT46: 2134.56 | DU46: 1215.43 | DV46: 558.33 | EA46: 56.58 | EB46: 177.03 | ED46: 1729.27
A47: 98936 | B47: RES | C47: =A47&B47 -> 98936RES | E47: 273 | F47: 332 | G47: 426 | H47: 409 | I47: 399 | J47: 384 | K47: 324 | L47: 316 | M47: 376 | O47: 36462.71 | P47: 524.41 | Q47: 19595.47 | R47: 56582.59 | S47: 45403.91 | T47: 15427.35 | U47: 11935.79 | V47: 72767.05 | W47: 61719.5 | X47: 22626.79 | Y47: 16625.76 | Z47: 100972.05 | AA47: 50783.54 | AB47: 32524.1 | AC47: 28034.73 | AD47: 111342.37 | AE47: 45390.89 | AF47: 29473.96 | AG47: 46058.95 | AH47: 120923.8 | AI47: 33213.55 | AJ47: 26830.98 | AK47: 56697.3 | AL47: 116741.83 | AM47: 23823.08 | AN47: 18540.84 | AO47: 66354.91 | AP47: 108718.83 | AQ47: 25165.56 | AR47: 14841.58 | AS47: 70905.61 | AT47: 110912.75 | AU47: 41859.68 | AV47: 16306.09 | AW47: 77731.59 | AX47: 135897.36 | AZ47: 1287.64 | BB47: 1422.08 | BC47: 2709.72 | BD47: 1375.03 | BE47: 835.84 | BF47: 1178.63 | BG47: 3389.5 | BH47: 989.24 | BI47: 760.14 | BJ47: 1067.55 | BK47: 2816.93 | BL47: 1087.16 | BM47: 545.9 | BN47: 1401.94 | BO47: 3035 | BP47: 873.76 | BQ47: 859.88 | BR47: 1678.99 | BS47: 3412.63 | BT47: 685.67 | BU47: 465.73 | BV47: 1833.77 | BW47: 2985.17 | BX47: 718.03 | BY47: 322.5 | BZ47: 1988.65 | CA47: 3029.18 | CB47: 423.65 | CC47: 242.01 | CD47: 2050.37 | CE47: 2716.03 | CF47: 1117.67 | CG47: 299.95 | CH47: 2092.38 | CI47: 3510 | CL47: 5580.4465 | CM47: 5505.9717 | CN47: 8438.5575 | CO47: 12485.929 | CP47: 16330.674 | CQ47: 19687.954 | CR47: 21681.595 | CS47: 24479.091 | CT47: 26839.822 | DG47: 10 | DH47: 5 | DI47: 5 | DJ47: 13 | DK47: 3 | DL47: 2 | DQ47: 2038.11 | DR47: 3363.69 | DS47: 3411.85 | DT47: 7320.79 | DU47: 237.61 | DV47: 1264.86 | EA47: 387.96 | EB47: 502.58 | EC47: 1178.24 | ED47: 910.4 | EF47: 124.53 | EG47: 227.93
A48: 98937 | B48: RES | C48: =A48&B48 -> 98937RES | E48: 323 | F48: 360 | G48: 396 | H48: 414 | I48: 384 | J48: 367 | K48: 308 | L48: 298 | M48: 284 | O48: 51192.34 | P48: 7777.45 | Q48: 4235.06 | R48: 63204.85 | S48: 65112.42 | T48: 15486.73 | U48: 6276.14 | V48: 86875.29 | W48: 64581.85 | X48: 26255 | Y48: 10535.21 | Z48: 101372.06 | AA48: 55568.94 | AB48: 30024.32 | AC48: 20192.43 | AD48: 105785.69 | AE48: 49586.37 | AF48: 28742.89 | AG48: 32495.35 | AH48: 110824.61 | AI48: 31454.77 | AJ48: 28738.25 | AK48: 41048 | AL48: 101241.02 | AM48: 23749.55 | AN48: 16051.65 | AO48: 45968.76 | AP48: 85769.96 | AQ48: 24931.33 | AR48: 12451.27 | AS48: 44874.33 | AT48: 82256.93 | AU48: 28124.16 | AV48: 13870.76 | AW48: 41308.16 | AX48: 83303.08 | AZ48: 3225.79 | BA48: 889.45 | BB48: 213.33 | BC48: 4328.57 | BD48: 3103.1 | BE48: 1720.35 | BF48: 497.99 | BG48: 5321.44 | BH48: 2011.1 | BI48: 1604.98 | BJ48: 1099.85 | BK48: 4715.93 | BL48: 1517.21 | BM48: 1266.72 | BN48: 1743.7 | BO48: 4527.63 | BP48: 1478.27 | BQ48: 1128.22 | BR48: 2599.11 | BS48: 5205.6 | BT48: 1149.45 | BU48: 1099.04 | BV48: 3471.35 | BW48: 5719.84 | BX48: 804.49 | BY48: 711.17 | BZ48: 3064.07 | CA48: 4579.73 | CB48: 814.49 | CC48: 590.14 | CD48: 3492.07 | CE48: 4896.7 | CF48: 888.82 | CG48: 441.75 | CH48: 2021.04 | CI48: 3351.61 | CL48: 2652.7887 | CM48: 4740.9025 | CN48: 7259.464 | CO48: 10222.942 | CP48: 12508.427 | CQ48: 15192.903 | CR48: 15482.893 | CS48: 15978.187 | CT48: 14768.223 | DG48: 4 | DH48: 5 | DI48: 10 | DJ48: 8 | DK48: 3 | DL48: 3 | DQ48: 285.64 | DR48: 1559.35 | DS48: 3964.68 | DT48: 3868.2 | DU48: 914.06 | DV48: 1775.52 | EA48: 104.54 | EC48: 83.99 | ED48: 280.77 | EE48: 124.18 | EF48: 442.89 | EG48: 487.86
A49: 98938 | B49: RES | C49: =A49&B49 -> 98938RES | E49: 176 | F49: 194 | G49: 186 | H49: 178 | I49: 172 | J49: 171 | K49: 158 | L49: 152 | M49: 168 | O49: 39686.2 | P49: 7941.4 | Q49: 5329.72 | R49: 52957.32 | S49: 41787.73 | T49: 12759.09 | U49: 3567.73 | V49: 58114.55 | W49: 33990.06 | X49: 20012.4 | Y49: 7557.05 | Z49: 61559.51 | AA49: 30575.56 | AB49: 19872.68 | AC49: 16635.78 | AD49: 67084.02 | AE49: 23128.54 | AF49: 19994.95 | AG49: 25208.47 | AH49: 68331.96 | AI49: 15244.9 | AJ49: 15437.92 | AK49: 33079.18 | AL49: 63762 | AM49: 14124.33 | AN49: 9572.88 | AO49: 34515.73 | AP49: 58212.94 | AQ49: 17516.92 | AR49: 8656.33 | AS49: 35718.18 | AT49: 61891.43 | AU49: 21414.77 | AV49: 10823.91 | AW49: 35407.74 | AX49: 67646.42 | AZ49: 5193.35 | BA49: 1350.92 | BB49: 414.35 | BC49: 6958.62 | BD49: 3319.3 | BE49: 1988.63 | BF49: 322.34 | BG49: 5630.27 | BH49: 3033.76 | BI49: 2091 | BJ49: 600.95 | BK49: 5725.71 | BL49: 2299.66 | BM49: 2186.9 | BN49: 2176.76 | BO49: 6663.32 | BP49: 2115.08 | BQ49: 1796 | BR49: 3619.56 | BS49: 7530.64 | BT49: 1442.77 | BU49: 1494.06 | BV49: 4316.38 | BW49: 7253.21 | BX49: 1316.46 | BY49: 936.73 | BZ49: 3032.37 | CA49: 5285.56 | CB49: 1172.5 | CC49: 790.35 | CD49: 3128.17 | CE49: 5091.02 | CF49: 1958.95 | CG49: 1030.98 | CH49: 3505.67 | CI49: 6495.6 | CL49: 2646.0736 | CM49: 3147.0109 | CN49: 4909.8891 | CO49: 7472.3054 | CP49: 9126.2968 | CQ49: 11350.264 | CR49: 11325.816 | CS49: 12557.129 | CT49: 12519.687 | DH49: 5 | DI49: 3 | DJ49: 8 | DL49: 1 | DR49: 1733.54 | DS49: 1209.95 | DT49: 8710.42 | DV49: 1260.28 | EB49: 50 | EC49: 363.01 | ED49: 44.62
A50: 98939 | B50: RES | C50: =A50&B50 -> 98939RES | E50: 21 | F50: 23 | G50: 26 | H50: 25 | I50: 23 | J50: 23 | K50: 20 | L50: 19 | M50: 20 | O50: 3242.24 | P50: 766.63 | Q50: 960.16 | R50: 4969.03 | S50: 3601.84 | T50: 1636.48 | U50: 1023.45 | V50: 6261.77 | W50: 4087.23 | X50: 1837.31 | Y50: 1787.49 | Z50: 7712.03 | AA50: 2906.01 | AB50: 3006 | AC50: 3264.39 | AD50: 9176.4 | AE50: 2987.71 | AF50: 2038.36 | AG50: 5777.52 | AH50: 10803.59 | AI50: 1842.29 | AJ50: 2176.94 | AK50: 6419.69 | AL50: 10438.92 | AM50: 1481.4 | AN50: 1306.99 | AO50: 7908.63 | AP50: 10697.02 | AQ50: 1594.25 | AR50: 965.61 | AS50: 7559.96 | AT50: 10119.82 | AU50: 2163.61 | AV50: 1365.33 | AW50: 8230.15 | AX50: 11759.09 | AZ50: 260 | BA50: 82.81 | BC50: 342.81 | BD50: 260.93 | BE50: 1.74 | BG50: 262.67 | BH50: 651.94 | BI50: 62.67 | BK50: 714.61 | BL50: 434.99 | BM50: 651.94 | BN50: 62.67 | BO50: 1149.6 | BP50: 452.24 | BQ50: 220.1 | BR50: 485.29 | BS50: 1157.63 | BT50: 298.33 | BU50: 452.24 | BV50: 399.61 | BW50: 1150.18 | BX50: 106.92 | BY50: 116.75 | BZ50: 604.06 | CA50: 827.73 | CB50: 134.72 | CC50: 106.92 | CD50: 720.81 | CE50: 962.45 | CF50: 161.31 | CG50: 134.72 | CH50: 827.73 | CI50: 1123.76 | CL50: 347.63064 | CM50: 487.17796 | CN50: 769.92901 | CO50: 1280.8957 | CP50: 1869.7853 | CQ50: 2106.7118 | CR50: 2474.852 | CS50: 2532.4223 | CT50: 2762.1433 | DG50: 2 | DI50: 2 | DJ50: 1 | DQ50: 122.07 | DS50: 195.26 | DT50: 2230.98 | EA50: 73.54
A51: 98942 | B51: RES | C51: =A51&B51 -> 98942RES | E51: 1138 | F51: 1333 | G51: 1528 | H51: 1537 | I51: 1457 | J51: 1384 | K51: 1193 | L51: 1167 | M51: 1282 | O51: 172931.12 | P51: 28287.35 | Q51: 34145.81 | R51: 235364.28 | S51: 223154.81 | T51: 61229.01 | U51: 38475.72 | V51: 322859.54 | W51: 250398.32 | X51: 94787.68 | Y51: 57402.07 | Z51: 402588.07 | AA51: 212697.97 | AB51: 125745.48 | AC51: 96193.13 | AD51: 434636.58 | AE51: 181607.59 | AF51: 119773.48 | AG51: 144791.25 | AH51: 446172.32 | AI51: 113050.53 | AJ51: 106348.53 | AK51: 183631.98 | AL51: 403031.04 | AM51: 98822.83 | AN51: 63487.52 | AO51: 206979.07 | AP51: 369289.42 | AQ51: 102189.28 | AR51: 55081.24 | AS51: 208136.33 | AT51: 365406.85 | AU51: 139850.5 | AV51: 56035.3 | AW51: 216020.64 | AX51: 411906.44 | AZ51: 4097.94 | BA51: 930.08 | BB51: 4245.76 | BC51: 9273.78 | BD51: 5865.56 | BE51: 2894.3 | BF51: 4645.07 | BG51: 13404.93 | BH51: 5904.43 | BI51: 4071.5 | BJ51: 6139.35 | BK51: 16115.28 | BL51: 4630.8 | BM51: 3835.14 | BN51: 7800.43 | BO51: 16266.37 | BP51: 3951.52 | BQ51: 3393 | BR51: 10545.42 | BS51: 17889.94 | BT51: 2962.64 | BU51: 3237.7 | BV51: 11480.19 | BW51: 17680.53 | BX51: 2051.49 | BY51: 1801.75 | BZ51: 10500.7 | CA51: 14353.94 | CB51: 2305.06 | CC51: 1646.81 | CD51: 10362.9 | CE51: 14314.77 | CF51: 3875.52 | CG51: 1962.55 | CH51: 9772.15 | CI51: 15610.22 | CL51: 13802.243 | CM51: 21014.182 | CN51: 31864.349 | CO51: 45396.748 | CP51: 54107.357 | CQ51: 65437.684 | CR51: 68805.942 | CS51: 73528.504 | CT51: 75902.955 | DG51: 21 | DH51: 16 | DI51: 15 | DJ51: 32 | DK51: 14 | DL51: 8 | DQ51: 4811.27 | DR51: 4825.89 | DS51: 8162.36 | DT51: 15137.35 | DU51: 6955.46 | DV51: 1412.65 | EA51: 1857.55 | EB51: 872.99 | EC51: 356.17 | ED51: 990.09 | EE51: 115.53 | EF51: 84.56 | EG51: 505.15
A52: 98944 | B52: RES | C52: =A52&B52 -> 98944RES | E52: 1536 | F52: 1674 | G52: 1710 | H52: 1657 | I52: 1583 | J52: 1458 | K52: 1410 | L52: 1433 | M52: 1554 | O52: 221458.67 | P52: 36987.16 | Q52: 30125.95 | R52: 288571.78 | S52: 246077.66 | T52: 70423.08 | U52: 31050.74 | V52: 347551.48 | W52: 221336.6 | X52: 102857.52 | Y52: 48797.66 | Z52: 372991.78 | AA52: 193724.3 | AB52: 118439.89 | AC52: 95598.19 | AD52: 407762.38 | AE52: 149642.11 | AF52: 110381.54 | AG52: 142366.38 | AH52: 402390.03 | AI52: 95390.28 | AJ52: 89469.31 | AK52: 178123.49 | AL52: 362983.08 | AM52: 95619.07 | AN52: 55095.3 | AO52: 192572.53 | AP52: 343286.9 | AQ52: 110754.45 | AR52: 54901.48 | AS52: 190877.94 | AT52: 356533.87 | AU52: 146848.48 | AV52: 67137.17 | AW52: 198537.64 | AX52: 412523.29 | AZ52: 29821.43 | BA52: 7306.22 | BB52: 8224.9 | BC52: 45352.55 | BD52: 30360.82 | BE52: 12996.55 | BF52: 7988.38 | BG52: 51345.75 | BH52: 23904.83 | BI52: 15267.92 | BJ52: 9830.07 | BK52: 49002.82 | BL52: 21764.3 | BM52: 17008.66 | BN52: 18785.35 | BO52: 57558.31 | BP52: 17152.74 | BQ52: 15465.17 | BR52: 28276.89 | BS52: 60894.8 | BT52: 11113.45 | BU52: 12083.54 | BV52: 33847.86 | BW52: 57044.85 | BX52: 10727.87 | BY52: 7680.53 | BZ52: 35589.37 | CA52: 53997.77 | CB52: 13599.13 | CC52: 7828.68 | CD52: 35497.89 | CE52: 56925.7 | CF52: 15308.29 | CG52: 9615.86 | CH52: 36128.53 | CI52: 61052.68 | CL52: 14469.872 | CM52: 20619.951 | CN52: 29380.382 | CO52: 43940.139 | CP52: 51925.967 | CQ52: 61996.587 | CR52: 63831.53 | CS52: 68244.852 | CT52: 71292.682 | DG52: 24 | DH52: 21 | DI52: 25 | DJ52: 59 | DK52: 14 | DL52: 14 | DQ52: 6060.87 | DR52: 5021.5 | DS52: 11780.26 | DT52: 44855.09 | DU52: 4852.92 | DV52: 1827.77 | EA52: 1448.67 | EB52: 1114.08 | EC52: 2389.6 | ED52: 1555.89 | EE52: 613.33 | EF52: 58.6 | EG52: 162.32
A53: 98947 | B53: RES | C53: =A53&B53 -> 98947RES | E53: 261 | F53: 327 | G53: 320 | H53: 329 | I53: 296 | J53: 284 | K53: 270 | L53: 255 | M53: 259 | O53: 43294.12 | P53: 6709.52 | Q53: 4009.19 | R53: 54012.83 | S53: 59802.26 | T53: 15089.15 | U53: 5755.41 | V53: 80646.82 | W53: 52395.29 | X53: 22929.54 | Y53: 10480.98 | Z53: 85805.81 | AA53: 49878.15 | AB53: 28640.87 | AC53: 20818.3 | AD53: 99337.32 | AE53: 36582.27 | AF53: 29649.91 | AG53: 32178.65 | AH53: 98410.83 | AI53: 24418.26 | AJ53: 24254.19 | AK53: 45369.6 | AL53: 94042.05 | AM53: 20340.82 | AN53: 15201.86 | AO53: 51543.47 | AP53: 87086.15 | AQ53: 21756.51 | AR53: 12400.91 | AS53: 51086.69 | AT53: 85244.11 | AU53: 23655.99 | AV53: 13251.09 | AW53: 51513.01 | AX53: 88420.09 | AZ53: 3631.19 | BA53: 664.25 | BB53: 1792.01 | BC53: 6087.45 | BD53: 3279.97 | BE53: 1426.65 | BF53: 1781.84 | BG53: 6488.46 | BH53: 2757.28 | BI53: 1504.28 | BJ53: 2244.97 | BK53: 6506.53 | BL53: 2723.08 | BM53: 2158.97 | BN53: 3077.64 | BO53: 7959.69 | BP53: 2151.33 | BQ53: 2096.32 | BR53: 4728.38 | BS53: 8976.03 | BT53: 1386.38 | BU53: 1601.17 | BV53: 6123.75 | BW53: 9111.3 | BX53: 980.7 | BY53: 1004.28 | BZ53: 5959.95 | CA53: 7944.93 | CB53: 1146.1 | CC53: 717.59 | CD53: 5889.57 | CE53: 7753.26 | CF53: 1265.19 | CG53: 895.79 | CH53: 5535.83 | CI53: 7696.81 | CL53: 2352.5117 | CM53: 4418.5911 | CN53: 6545.2413 | CO53: 10081.352 | CP53: 12103.545 | CQ53: 15908.649 | CR53: 16958.131 | CS53: 17868.773 | CT53: 17859.951 | DH53: 3 | DI53: 2 | DJ53: 1 | DK53: 2 | DL53: 3 | DO53: 1 | DR53: 937.94 | DS53: 587.29 | DT53: 93.81 | DU53: 1066.59 | DV53: 1407.51 | DY53: 829.07 | EE53: 150.96 | EG53: 93.81
A54: 98948 | B54: RES | C54: =A54&B54 -> 98948RES | E54: 1118 | F54: 925 | G54: 822 | H54: 807 | I54: 975 | J54: 822 | K54: 957 | L54: 992 | M54: 833 | O54: 190188.17 | P54: 52149.41 | Q54: 26916.97 | R54: 269254.55 | S54: 140172.33 | T54: 47653.38 | U54: 33147.76 | V54: 220973.47 | W54: 90759.45 | X54: 78717.38 | Y54: 34180.63 | Z54: 203657.46 | AA54: 105915.71 | AB54: 63668.89 | AC54: 61828 | AD54: 231412.6 | AE54: 87118.5 | AF54: 99990.24 | AG54: 107098.45 | AH54: 294207.19 | AI54: 42575.46 | AJ54: 74721.17 | AK54: 135243.64 | AL54: 252540.27 | AM54: 92355 | AN54: 24424.32 | AO54: 160883.81 | AP54: 277663.13 | AQ54: 97741.13 | AR54: 43055.76 | AS54: 160977.93 | AT54: 301774.82 | AU54: 59748.18 | AV54: 54578.7 | AW54: 161505.24 | AX54: 275832.12 | AZ54: 47476.16 | BA54: 18817.5 | BB54: 10283.02 | BC54: 76576.68 | BD54: 34143.51 | BE54: 13421.1 | BF54: 14822.39 | BG54: 62387 | BH54: 22326.85 | BI54: 20432.67 | BJ54: 11971.01 | BK54: 54730.53 | BL54: 26578.41 | BM54: 19021.05 | BN54: 21453.82 | BO54: 67053.28 | BP54: 21093.24 | BQ54: 29375.15 | BR54: 38072.84 | BS54: 88541.23 | BT54: 8900.33 | BU54: 21988.86 | BV54: 45263.47 | BW54: 76152.66 | BX54: 22714.65 | BY54: 6261.32 | BZ54: 55871.99 | CA54: 84847.96 | CB54: 21560.38 | CC54: 12622.51 | CD54: 56766.4 | CE54: 90949.29 | CF54: 11489.55 | CG54: 15893.99 | CH54: 58140.69 | CI54: 85524.23 | CL54: 13754.543 | CM54: 16097.193 | CN54: 19077.337 | CO54: 26652.092 | CP54: 39379.523 | CQ54: 46737.095 | CR54: 52090.218 | CS54: 57430.067 | CT54: 56561.068 | DG54: 22 | DH54: 12 | DI54: 18 | DJ54: 14 | DK54: 4 | DL54: 8 | DQ54: 7211.52 | DR54: 4935.08 | DS54: 11488.83 | DT54: 4495.31 | DU54: 1020.36 | DV54: 2377.48 | EA54: 393.7 | EB54: 328.13 | EC54: 130.5 | ED54: 857.54 | EE54: 61.49 | EF54: 520.17
A55: 98951 | B55: RES | C55: =A55&B55 -> 98951RES | E55: 991 | F55: 1027 | G55: 1070 | H55: 1099 | I55: 1047 | J55: 997 | K55: 949 | L55: 913 | M55: 966 | O55: 175199.34 | P55: 28513.6 | Q55: 62973.55 | R55: 266686.49 | S55: 183044.55 | T55: 66401.13 | U55: 61612.41 | V55: 311058.09 | W55: 160465.65 | X55: 91115.59 | Y55: 80604.5 | Z55: 332185.74 | AA55: 154119.11 | AB55: 98495.07 | AC55: 125684.36 | AD55: 378298.54 | AE55: 121919.72 | AF55: 98012.44 | AG55: 172831.28 | AH55: 392763.44 | AI55: 81533.9 | AJ55: 81402.13 | AK55: 214432.46 | AL55: 377368.49 | AM55: 74936.65 | AN55: 52616.52 | AO55: 229740.41 | AP55: 357293.58 | AQ55: 88689.45 | AR55: 47155.77 | AS55: 234732.52 | AT55: 370577.74 | AU55: 108902.97 | AV55: 54409.78 | AW55: 241267.51 | AX55: 404580.26 | AZ55: 45952.69 | BA55: 9473.84 | BB55: 38401.44 | BC55: 93827.97 | BD55: 50046.62 | BE55: 25046.96 | BF55: 37875.88 | BG55: 112969.46 | BH55: 42538.15 | BI55: 29381.74 | BJ55: 46346.9 | BK55: 118266.79 | BL55: 38017.94 | BM55: 33369.46 | BN55: 64652.12 | BO55: 136039.52 | BP55: 32467.34 | BQ55: 28834.57 | BR55: 80566.49 | BS55: 141868.4 | BT55: 20450.12 | BU55: 24900.53 | BV55: 96367.76 | BW55: 141718.41 | BX55: 19712.46 | BY55: 16813.53 | BZ55: 107987.28 | CA55: 144513.27 | CB55: 22733.91 | CC55: 15816.87 | CD55: 113302.87 | CE55: 151853.65 | CF55: 27506 | CG55: 17708.77 | CH55: 115784.19 | CI55: 160998.96 | CL55: 20747.992 | CM55: 25812.752 | CN55: 34685.348 | CO55: 49418.457 | CP55: 59131.19 | CQ55: 71623.574 | CR55: 73968.873 | CS55: 81039.052 | CT55: 83068.616 | DG55: 17 | DH55: 15 | DI55: 18 | DJ55: 22 | DK55: 5 | DL55: 6 | DQ55: 9376.06 | DR55: 4243.97 | DS55: 10524.78 | DT55: 12165.26 | DU55: 1940.11 | DV55: 1672.67 | EA55: 980.36 | EB55: 953.11 | EC55: 935.12 | ED55: 1342.96 | EE55: 464.88 | EF55: 16.76 | EG55: 602.92
A56: 98952 | B56: RES | C56: =A56&B56 -> 98952RES | E56: 73 | F56: 72 | G56: 66 | H56: 75 | I56: 74 | J56: 73 | K56: 61 | L56: 62 | M56: 71 | O56: 12523.51 | P56: 4046.92 | Q56: 3559.39 | R56: 20129.82 | S56: 15002.24 | T56: 5685.26 | U56: 3827.27 | V56: 24514.77 | W56: 12212.25 | X56: 8318.84 | Y56: 5746.49 | Z56: 26277.58 | AA56: 11027.75 | AB56: 8915.9 | AC56: 10879.01 | AD56: 30822.66 | AE56: 9759.39 | AF56: 8078.67 | AG56: 16341.87 | AH56: 34179.93 | AI56: 6958.54 | AJ56: 7122.95 | AK56: 20299.19 | AL56: 34380.68 | AM56: 4464.53 | AN56: 4697.57 | AO56: 23929.87 | AP56: 33091.97 | AQ56: 5587.8 | AR56: 3767.4 | AS56: 25615.41 | AT56: 34970.61 | AU56: 7575.15 | AV56: 4178.91 | AW56: 26383.58 | AX56: 38137.64 | AZ56: 7246.96 | BA56: 2925.09 | BB56: 2173.57 | BC56: 12345.62 | BD56: 6937.27 | BE56: 3845.08 | BF56: 1758.27 | BG56: 12540.62 | BH56: 5863.12 | BI56: 5103.71 | BJ56: 2755.53 | BK56: 13722.36 | BL56: 5438.13 | BM56: 4801.32 | BN56: 5913.38 | BO56: 16152.83 | BP56: 4429.22 | BQ56: 4374.62 | BR56: 8838.14 | BS56: 17641.98 | BT56: 3005.67 | BU56: 3455 | BV56: 10278.03 | BW56: 16738.7 | BX56: 2050.58 | BY56: 2335.28 | BZ56: 12237.15 | CA56: 16623.01 | CB56: 2675.68 | CC56: 1872.67 | CD56: 12899.49 | CE56: 17447.84 | CF56: 3596.07 | CG56: 2081.77 | CH56: 13245.57 | CI56: 18923.41 | CL56: 1364.5685 | CM56: 1836.0014 | CN56: 2662.9739 | CO56: 4226.3142 | CP56: 5467.8719 | CQ56: 6712.8764 | CR56: 7543.5351 | CS56: 8623.5118 | CT56: 8856.1418 | DI56: 3 | DJ56: 2 | DK56: 1 | DL56: 1 | DS56: 2545.95 | DT56: 524.9 | DU56: 238.37 | DV56: 44.91 | ED56: 195.68
A57: 98953 | B57: RES | C57: =A57&B57 -> 98953RES | E57: 606 | F57: 657 | G57: 656 | H57: 623 | I57: 581 | J57: 570 | K57: 539 | L57: 554 | M57: 548 | O57: 105504 | P57: 17396.96 | Q57: 13605.77 | R57: 136506.73 | S57: 112600.84 | T57: 33318.24 | U57: 12224.44 | V57: 158143.52 | W57: 92153.55 | X57: 51119.11 | Y57: 24413.25 | Z57: 167685.91 | AA57: 79361.07 | AB57: 49414.18 | AC57: 45630.06 | AD57: 174405.31 | AE57: 57292.25 | AF57: 44765.82 | AG57: 62624.74 | AH57: 164682.81 | AI57: 45510.37 | AJ57: 34218.8 | AK57: 74078.09 | AL57: 153807.26 | AM57: 46252.72 | AN57: 25528.1 | AO57: 77807.07 | AP57: 149587.89 | AQ57: 60452.74 | AR57: 25169.51 | AS57: 75071.78 | AT57: 160694.03 | AU57: 64044.63 | AV57: 30216.9 | AW57: 79929.49 | AX57: 174191.02 | AZ57: 8229.28 | BA57: 1723.75 | BB57: 1659.37 | BC57: 11612.4 | BD57: 7982.17 | BE57: 3668.66 | BF57: 1686.3 | BG57: 13337.13 | BH57: 5812.75 | BI57: 3884.11 | BJ57: 2432.04 | BK57: 12128.9 | BL57: 5241.77 | BM57: 4387.66 | BN57: 4182.1 | BO57: 13811.53 | BP57: 3380.6 | BQ57: 2677.82 | BR57: 4698.19 | BS57: 10756.61 | BT57: 2409.42 | BU57: 2170.6 | BV57: 5238.1 | BW57: 9818.12 | BX57: 2595.91 | BY57: 1925.51 | BZ57: 6439.12 | CA57: 10960.54 | CB57: 3432.25 | CC57: 1970.83 | CD57: 5706.23 | CE57: 11109.31 | CF57: 3523.34 | CG57: 2457.38 | CH57: 6721.08 | CI57: 12701.8 | CL57: 6703.5608 | CM57: 9035.3281 | CN57: 14059.468 | CO57: 19912.851 | CP57: 22366.391 | CQ57: 25719.387 | CR57: 26268.981 | CS57: 27588.054 | CT57: 29042.824 | DG57: 5 | DH57: 7 | DI57: 4 | DJ57: 11 | DK57: 5 | DL57: 3 | DQ57: 2008.97 | DR57: 2463.56 | DS57: 837.9 | DT57: 3698.73 | DU57: 961.22 | DV57: 552.73 | EA57: 11.07 | EB57: 1173.1 | ED57: 246.23 | EE57: 692.95 | EF57: 170.06 | EG57: 168.22
A58: 99301 | B58: RES | C58: =A58&B58 -> 99301RES | E58: 1 | F58: 1 | G58: 1 | H58: 1 | I58: 1 | J58: 1 | K58: 1 | L58: 1 | M58: 1 | O58: 291.45 | P58: 0 | Q58: 0 | R58: 291.45 | S58: 262.79 | T58: 0 | U58: 0 | V58: 262.79 | W58: 215.32 | X58: 262.79 | Y58: 0 | Z58: 478.11 | AA58: 166.73 | AB58: 215.32 | AC58: 262.79 | AD58: 644.84 | AE58: 135.93 | AF58: 166.73 | AG58: 478.11 | AH58: 780.77 | AI58: 70.3 | AJ58: 135.93 | AK58: 244.84 | AL58: 451.07 | AM58: 80.01 | AN58: 70.3 | AO58: 380.77 | AP58: 531.08 | AQ58: 148.35 | AR58: 80.01 | AS58: 451.07 | AT58: 679.43 | AU58: 185.01 | AV58: 148.35 | AW58: 531.08 | AX58: 864.44 | CL58: 7.0065501 | CM58: 8.1510259 | CN58: 30.820545 | CO58: 98.488883 | CP58: 151.44814 | CQ58: 84.466237 | CR58: 119.9736 | CS58: 154.29962 | CT58: 183.53913
A59: 99323 | B59: RES | C59: =A59&B59 -> 99323RES | E59: 253 | F59: 249 | G59: 255 | H59: 239 | I59: 228 | J59: 206 | K59: 210 | L59: 222 | M59: 209 | O59: 49653.58 | P59: 6979.08 | Q59: 3880.96 | R59: 60513.62 | S59: 39998.18 | T59: 12839.76 | U59: 2416.31 | V59: 55254.25 | W59: 37063.18 | X59: 16801.55 | Y59: 4273.16 | Z59: 58137.89 | AA59: 31119.73 | AB59: 17987.5 | AC59: 9642.23 | AD59: 58749.46 | AE59: 22918.13 | AF59: 15282.3 | AG59: 16311.04 | AH59: 54511.47 | AI59: 15920.62 | AJ59: 11598.56 | AK59: 20553.73 | AL59: 48072.91 | AM59: 19360.84 | AN59: 7649.63 | AO59: 19447.51 | AP59: 46457.98 | AQ59: 28922.09 | AR59: 8751.41 | AS59: 21564.24 | AT59: 59237.74 | AU59: 25287.19 | AV59: 11378.59 | AW59: 20718.96 | AX59: 57384.74 | AZ59: 1368.64 | BA59: 619.25 | BB59: 389.2 | BC59: 2377.09 | BD59: 1488.12 | BE59: 1020.78 | BF59: 737.72 | BG59: 3246.62 | BH59: 1304.88 | BI59: 1349.06 | BJ59: 510.34 | BK59: 3164.28 | BL59: 800.27 | BM59: 767.15 | BN59: 944.52 | BO59: 2511.94 | BP59: 392.04 | BQ59: 556.08 | BR59: 1234.53 | BS59: 2182.65 | BT59: 457.24 | BU59: 302.17 | BV59: 1060.97 | BW59: 1820.38 | BX59: 312.35 | BY59: 389.45 | BZ59: 1196.14 | CA59: 1897.94 | CB59: 612.08 | CC59: 180.87 | CD59: 1483.46 | CE59: 2276.41 | CF59: 334.74 | CG59: 247.64 | CH59: 1564.33 | CI59: 2146.71 | CL59: 2489.0569 | CM59: 2816.7597 | CN59: 3856.9421 | CO59: 5348.2422 | CP59: 6275.0263 | CQ59: 7395.1349 | CR59: 6900.0155 | CS59: 8365.6869 | CT59: 7984.5509 | DH59: 2 | DJ59: 7 | DK59: 2 | DL59: 1 | DR59: 1427.21 | DT59: 4931.56 | DU59: 439.51 | DV59: 100 | ED59: 579.8 | EE59: 77.8 | EF59: 100
A60: 99324 | B60: RES | C60: =A60&B60 -> 99324RES | E60: 452 | F60: 503 | G60: 558 | H60: 521 | I60: 486 | J60: 479 | K60: 427 | L60: 422 | M60: 473 | O60: 48027.14 | P60: 7935.89 | Q60: 7100.46 | R60: 63063.49 | S60: 52953.2 | T60: 13230.16 | U60: 5203.26 | V60: 71386.62 | W60: 53872.52 | X60: 22026.15 | Y60: 7881.7 | Z60: 83780.37 | AA60: 44797.59 | AB60: 26170.74 | AC60: 16157.51 | AD60: 87125.84 | AE60: 38931.97 | AF60: 24030.75 | AG60: 24694.91 | AH60: 87657.63 | AI60: 25619.91 | AJ60: 23022.33 | AK60: 33515.41 | AL60: 82157.65 | AM60: 23743.53 | AN60: 14017.28 | AO60: 36847.7 | AP60: 74608.51 | AQ60: 26966.49 | AR60: 13129.44 | AS60: 36840.63 | AT60: 76936.56 | AU60: 38934.92 | AV60: 15205.91 | AW60: 39428 | AX60: 93568.83 | AZ60: 5906.33 | BA60: 1231.55 | BB60: 947.54 | BC60: 8085.42 | BD60: 4944.26 | BE60: 2164.36 | BF60: 325.26 | BG60: 7433.88 | BH60: 5398.86 | BI60: 2900.9 | BJ60: 1047.97 | BK60: 9347.73 | BL60: 3861.27 | BM60: 3111.16 | BN60: 2236.16 | BO60: 9208.59 | BP60: 3502.8 | BQ60: 2625.84 | BR60: 4226.18 | BS60: 10354.82 | BT60: 2823.32 | BU60: 2712.87 | BV60: 5796.97 | BW60: 11333.16 | BX60: 2344.39 | BY60: 1928.73 | BZ60: 6062.59 | CA60: 10335.71 | CB60: 2813.17 | CC60: 1809.76 | CD60: 7109.07 | CE60: 11732 | CF60: 3445.03 | CG60: 2359.11 | CH60: 8257.49 | CI60: 14061.63 | CL60: 3268.858 | CM60: 3928.5921 | CN60: 5828.6663 | CO60: 8369.2042 | CP60: 9675.5321 | CQ60: 12368.667 | CR60: 12641.303 | CS60: 13521.613 | CT60: 14523.391 | DG60: 14 | DH60: 8 | DI60: 16 | DJ60: 10 | DK60: 8 | DL60: 8 | DQ60: 1199.66 | DR60: 1804.86 | DS60: 4440.67 | DT60: 2483.58 | DU60: 989.21 | DV60: 858.89 | EA60: 467.19 | EB60: 20.51 | EC60: 182.07 | ED60: 804.93 | EE60: 281.67 | EF60: 439.01 | EG60: 152.96
A61: 99328 | B61: RES | C61: =A61&B61 -> 99328RES | E61: 351 | F61: 369 | G61: 401 | H61: 410 | I61: 395 | J61: 381 | K61: 343 | L61: 338 | M61: 347 | O61: 54273.04 | P61: 11262.17 | Q61: 7504.5 | R61: 73039.71 | S61: 60785.48 | T61: 14920.28 | U61: 8619.28 | V61: 84325.04 | W61: 61776.89 | X61: 27481.52 | Y61: 13107.08 | Z61: 102365.49 | AA61: 54798.1 | AB61: 32127.58 | AC61: 24616.02 | AD61: 111541.7 | AE61: 41953.53 | AF61: 32473.7 | AG61: 37361.73 | AH61: 111788.96 | AI61: 27886.25 | AJ61: 25826.45 | AK61: 48477.2 | AL61: 102189.9 | AM61: 25425.7 | AN61: 15962.48 | AO61: 54208.21 | AP61: 95596.39 | AQ61: 24504.7 | AR61: 14512 | AS61: 51754.49 | AT61: 90771.19 | AU61: 32908.2 | AV61: 14136.2 | AW61: 53816.71 | AX61: 100861.11 | AZ61: 5479.61 | BA61: 1893.46 | BB61: 885.35 | BC61: 8258.42 | BD61: 6104.95 | BE61: 2398.81 | BF61: 975.38 | BG61: 9479.14 | BH61: 5820.57 | BI61: 3868.95 | BJ61: 1762.32 | BK61: 11451.84 | BL61: 5450.51 | BM61: 3934.6 | BN61: 4733.63 | BO61: 14118.74 | BP61: 3919.94 | BQ61: 3872.48 | BR61: 7383.35 | BS61: 15175.77 | BT61: 2932.81 | BU61: 2732.02 | BV61: 8871.54 | BW61: 14536.37 | BX61: 2863.69 | BY61: 2195.85 | BZ61: 10126.2 | CA61: 15185.74 | CB61: 2967.38 | CC61: 2377.4 | CD61: 10233.67 | CE61: 15578.45 | CF61: 3507.91 | CG61: 2228.51 | CH61: 11082.11 | CI61: 16818.53 | CL61: 3691.413 | CM61: 5134.8873 | CN61: 7954.5642 | CO61: 11626.209 | CP61: 13918.493 | CQ61: 17043.319 | CR61: 17956.567 | CS61: 18319.855 | CT61: 18875.532 | DG61: 11 | DH61: 5 | DI61: 7 | DJ61: 8 | DK61: 5 | DL61: 1 | DQ61: 2555.89 | DR61: 2811.14 | DS61: 5010.7 | DT61: 3173.66 | DU61: 1861.88 | DV61: 130.73 | EA61: 204.99 | EB61: 411.4 | ED61: 40.21 | EF61: 130.73 | EG61: 18.45
A62: 99329 | B62: RES | C62: =A62&B62 -> 99329RES | E62: 15 | F62: 18 | G62: 19 | H62: 17 | I62: 21 | J62: 20 | K62: 16 | L62: 18 | M62: 17 | O62: 2318 | P62: 117.99 | Q62: 75.13 | R62: 2511.12 | S62: 3146.66 | T62: 459.53 | U62: 0 | V62: 3606.19 | W62: 2903.31 | X62: 736.02 | Y62: 0 | Z62: 3639.33 | AA62: 2163.68 | AB62: 925.27 | AC62: 231.33 | AD62: 3320.28 | AE62: 2496.5 | AF62: 1353.03 | AG62: 658.42 | AH62: 4507.95 | AI62: 1641.89 | AJ62: 1482.53 | AK62: 1494.13 | AL62: 4618.55 | AM62: 1577.37 | AN62: 989.2 | AO62: 1318.38 | AP62: 3884.95 | AQ62: 1443.36 | AR62: 423.87 | AS62: 1519.05 | AT62: 3386.28 | AU62: 1695.98 | AV62: 658.44 | AW62: 1452.12 | AX62: 3806.54 | CL62: 79.896478 | CM62: 132.90916 | CN62: 161.67352 | CO62: 220.18653 | CP62: 343.1311 | CQ62: 601.3595 | CR62: 511.16468 | CS62: 557.93978 | CT62: 548.05516 | DJ62: 1 | DL62: 1 | DT62: 808.32 | DV62: 254.13
A63: 99347 | B63: RES | C63: =A63&B63 -> 99347RES | E63: 122 | F63: 127 | G63: 187 | H63: 185 | I63: 190 | J63: 172 | K63: 155 | L63: 136 | M63: 129 | O63: 16321.16 | P63: 2312.63 | Q63: 2336.31 | R63: 20970.1 | S63: 19534.87 | T63: 5070.92 | U63: 2379.73 | V63: 26985.52 | W63: 29590.86 | X63: 8807.25 | Y63: 4270.82 | Z63: 42668.93 | AA63: 27417.9 | AB63: 16299.55 | AC63: 7823.13 | AD63: 51540.58 | AE63: 25463.38 | AF63: 16218.38 | AG63: 15295.84 | AH63: 56977.6 | AI63: 15002.01 | AJ63: 15248.75 | AK63: 21501.28 | AL63: 51752.04 | AM63: 10925.3 | AN63: 8995.31 | AO63: 26383.12 | AP63: 46303.73 | AQ63: 9540.54 | AR63: 6726.38 | AS63: 27941.69 | AT63: 44208.61 | AU63: 10740.58 | AV63: 6105.15 | AW63: 29429.41 | AX63: 46275.14 | AZ63: 1828.85 | BA63: 389.21 | BB63: 348.45 | BC63: 2566.51 | BD63: 2312.75 | BE63: 845.94 | BF63: 146.72 | BG63: 3305.41 | BH63: 3304.89 | BI63: 1821.3 | BJ63: 257.04 | BK63: 5383.23 | BL63: 2263.15 | BM63: 1843 | BN63: 974.31 | BO63: 5080.46 | BP63: 1727.85 | BQ63: 1151.99 | BR63: 1611.39 | BS63: 4491.23 | BT63: 1224.97 | BU63: 1137.49 | BV63: 2311.82 | BW63: 4674.28 | BX63: 784.47 | BY63: 746.77 | BZ63: 2376.84 | CA63: 3908.08 | CB63: 752.94 | CC63: 767.5 | CD63: 3053.55 | CE63: 4573.99 | CF63: 1033.19 | CG63: 723.74 | CH63: 3655.3 | CI63: 5412.23 | CL63: 1072.2415 | CM63: 1576.1929 | CN63: 2888.533 | CO63: 4558.2397 | CP63: 6113.151 | CQ63: 7930.7345 | CR63: 8786.9768 | CS63: 9702.5605 | CT63: 10034.427 | DG63: 3 | DH63: 6 | DI63: 3 | DJ63: 8 | DK63: 7 | DL63: 1 | DQ63: 674.16 | DR63: 2137.22 | DS63: 1069.02 | DT63: 3205.07 | DU63: 643.62 | DV63: 186.47 | EB63: 1516.36 | EC63: 728.46 | ED63: 291.91 | EE63: 144.9
A64: 99348 | B64: RES | C64: =A64&B64 -> 99348RES | E64: 41 | F64: 46 | G64: 51 | H64: 54 | I64: 50 | J64: 49 | K64: 44 | L64: 44 | M64: 42 | O64: 5916.59 | P64: 1154.67 | Q64: 1719.04 | R64: 8790.3 | S64: 7131.21 | T64: 1550.02 | U64: 1298.92 | V64: 9980.15 | W64: 9173.09 | X64: 2362.36 | Y64: 1300.35 | Z64: 12835.8 | AA64: 8374.65 | AB64: 4531.26 | AC64: 2736.74 | AD64: 15642.65 | AE64: 6810.97 | AF64: 5080.74 | AG64: 3694.05 | AH64: 15585.76 | AI64: 3942.34 | AJ64: 4031.57 | AK64: 5730.46 | AL64: 13704.37 | AM64: 3239.31 | AN64: 2519.16 | AO64: 6068.19 | AP64: 11826.66 | AQ64: 3540.21 | AR64: 1820.57 | AS64: 7163.12 | AT64: 12523.9 | AU64: 4180.45 | AV64: 1557.77 | AW64: 5536.07 | AX64: 11274.29 | AZ64: 752.36 | BA64: 340.09 | BB64: 517.96 | BC64: 1610.41 | BD64: 756.15 | BE64: 316.82 | BF64: 465.85 | BG64: 1538.82 | BH64: 1304.97 | BI64: 403.21 | BJ64: 423.67 | BK64: 2131.85 | BL64: 580.18 | BM64: 385.48 | BN64: 826.88 | BO64: 1792.54 | BP64: 343.6 | BQ64: 227.41 | BR64: 388.48 | BS64: 959.49 | BT64: 214.08 | BU64: 236.6 | BV64: 461.89 | BW64: 912.57 | BX64: 230.98 | BY64: 137.14 | BZ64: 541.3 | CA64: 909.42 | CB64: 338.62 | CC64: 141.88 | CD64: 572.3 | CE64: 1052.8 | CF64: 555.81 | CG64: 215.22 | CH64: 714.18 | CI64: 1485.21 | CL64: 613.54682 | CM64: 657.21988 | CN64: 855.96575 | CO64: 1454.0907 | CP64: 1566.5868 | CQ64: 2109.5302 | CR64: 2077.0473 | CS64: 2525.4719 | CT64: 1968.0131 | DG64: 1 | DI64: 2 | DJ64: 2 | DQ64: 314.45 | DS64: 1332.54 | DT64: 903.67 | EC64: 514.16
A65: 99350 | B65: RES | C65: =A65&B65 -> 99350RES | E65: 3 | F65: 6 | G65: 8 | H65: 6 | I65: 12 | J65: 6 | K65: 5 | L65: 4 | M65: 5 | O65: 0 | P65: 266.06 | Q65: 0 | R65: 266.06 | S65: 766.25 | T65: 0 | U65: 0 | V65: 766.25 | W65: 1397.15 | X65: 388.39 | Y65: 0 | Z65: 1785.54 | AA65: 790.76 | AB65: 636.98 | AC65: 154.03 | AD65: 1581.77 | AE65: 1882.92 | AF65: 626.18 | AG65: 791.01 | AH65: 3300.11 | AI65: 364.41 | AJ65: 277.98 | AK65: 1088.1 | AL65: 1730.49 | AM65: 219.44 | AN65: 0 | AO65: 1570.23 | AP65: 1789.67 | AQ65: 0 | AR65: 439.22 | AS65: 1020.5 | AT65: 1459.72 | AU65: 657.47 | AV65: 0 | AW65: 1037.53 | AX65: 1695 | BA65: 123.17 | BC65: 123.17 | BD65: 498.09 | BG65: 498.09 | BH65: 679.89 | BI65: 262.09 | BK65: 941.98 | BL65: 327.3 | BM65: 198.69 | BN65: 27.73 | BO65: 553.72 | BP65: 471.9 | BQ65: 327.3 | BR65: 226.42 | BS65: 1025.62 | BT65: 63.65 | BU65: 72.87 | BV65: 229.97 | BW65: 366.49 | BX65: 80.81 | BZ65: 366.49 | CA65: 447.3 | CC65: 32.4 | CE65: 32.4 | CF65: 85.99 | CH65: 32.4 | CI65: 118.39 | CL65: 14.076502 | CM65: 23.766976 | CN65: 80.894475 | CO65: 124.87785 | CP65: 319.18122 | CQ65: 351.50151 | CR65: 469.62893 | CS65: 359.26084 | CT65: 345.39127 | DH65: 1 | DL65: 1 | DR65: 71.39 | DV65: 297.22 | EB65: 71.39 | EF65: 297.22
A66: 99360 | B66: RES | C66: =A66&B66 -> 99360RES | E66: 93 | F66: 97 | G66: 64 | H66: 60 | I66: 90 | J66: 84 | K66: 79 | L66: 78 | M66: 92 | O66: 18000.75 | P66: 2870.59 | Q66: 368.29 | R66: 21239.63 | S66: 16851.49 | T66: 6570.56 | U66: 1138.86 | V66: 24560.91 | W66: 2059.72 | X66: 11075.55 | Y66: 1427.14 | Z66: 14562.41 | AA66: 7616.63 | AB66: 3683.2 | AC66: 2713.86 | AD66: 14013.69 | AE66: 9379.09 | AF66: 7015.81 | AG66: 6326.92 | AH66: 22721.82 | AI66: 7620.45 | AJ66: 5820.09 | AK66: 8101.92 | AL66: 21542.46 | AM66: 7765.03 | AN66: 4184.29 | AO66: 9818.84 | AP66: 21768.16 | AQ66: 10612.85 | AR66: 3855.41 | AS66: 10025.2 | AT66: 24493.46 | AU66: 11542.66 | AV66: 5559.89 | AW66: 8158.19 | AX66: 25260.74 | AZ66: 717.14 | BA66: 368.95 | BC66: 1086.09 | BD66: 738.2 | BE66: 450.51 | BF66: 25.78 | BG66: 1214.49 | BH66: 323.76 | BI66: 593.44 | BJ66: 223.29 | BK66: 1140.49 | BL66: 126.93 | BM66: 49.58 | BO66: 176.51 | BP66: 363.53 | BQ66: 94.79 | BR66: 123.84 | BS66: 582.16 | BT66: 275.29 | BU66: 219.3 | BW66: 494.59 | BX66: 162.19 | BY66: 72.24 | BZ66: 18.93 | CA66: 253.36 | CB66: 66.92 | CE66: 66.92 | CF66: 65 | CI66: 65 | CL66: 672.50489 | CM66: 1305.4198 | CN66: 1444.3064 | CO66: 1350.2649 | CP66: 2514.6998 | CQ66: 3051.0728 | CR66: 3446.2841 | CS66: 3793.2326 | CT66: 3257.4673 | DG66: 1 | DH66: 2 | DJ66: 2 | DQ66: 256.11 | DR66: 272.68 | DT66: 26.08 | EB66: 272.68 | ED66: 10.83
A67: 99361 | B67: RES | C67: =A67&B67 -> 99361RES | E67: 111 | F67: 111 | G67: 149 | H67: 148 | I67: 134 | J67: 132 | K67: 126 | L67: 110 | M67: 115 | O67: 21350.45 | P67: 3160.55 | Q67: 1625.1 | R67: 26136.1 | S67: 21337.07 | T67: 6630.56 | U67: 2170.89 | V67: 30138.52 | W67: 22916.77 | X67: 9394.96 | Y67: 4703.32 | Z67: 37015.05 | AA67: 20507.1 | AB67: 12022.6 | AC67: 7989.9 | AD67: 40519.6 | AE67: 17230.15 | AF67: 10926.96 | AG67: 11502.25 | AH67: 39659.36 | AI67: 11645.85 | AJ67: 11105.01 | AK67: 14395.54 | AL67: 37146.4 | AM67: 8691.19 | AN67: 6558.06 | AO67: 17827.81 | AP67: 33077.06 | AQ67: 7876.06 | AR67: 5150.31 | AS67: 18067.68 | AT67: 31094.05 | AU67: 10013.16 | AV67: 3836.57 | AW67: 18537.53 | AX67: 32387.26 | AZ67: 1416.17 | BA67: 476.62 | BB67: 654.93 | BC67: 2547.72 | BD67: 1656.08 | BE67: 445.5 | BF67: 845.88 | BG67: 2947.46 | BH67: 1474.37 | BI67: 744.79 | BJ67: 363.65 | BK67: 2582.81 | BL67: 1338.85 | BM67: 732.19 | BN67: 579.46 | BO67: 2650.5 | BP67: 915.4 | BQ67: 578.47 | BR67: 661.11 | BS67: 2154.98 | BT67: 510.33 | BU67: 594.51 | BV67: 968.74 | BW67: 2073.58 | BX67: 466.57 | BY67: 309.89 | BZ67: 1439.76 | CA67: 2216.22 | CB67: 367.6 | CC67: 280.63 | CD67: 1746.02 | CE67: 2394.25 | CF67: 669.65 | CG67: 330.06 | CH67: 2026.65 | CI67: 3026.36 | CL67: 1068.2901 | CM67: 1700.9722 | CN67: 2836.7453 | CO67: 4003.392 | CP67: 4464.6206 | CQ67: 5425.824 | CR67: 6013.6767 | CS67: 6382.8123 | CT67: 6397.8783 | DG67: 3 | DH67: 2 | DI67: 2 | DJ67: 3 | DK67: 3 | DL67: 2 | DQ67: 1346.53 | DR67: 470.26 | DS67: 637.35 | DT67: 3011.76 | DU67: 285.58 | DV67: 1127.55 | EA67: 156.99 | EC67: 26.97 | EE67: 232.78
A68: 99362 | B68: RES | C68: =A68&B68 -> 99362RES | E68: 1739 | F68: 1960 | G68: 2257 | H68: 2274 | I68: 2626 | J68: 2083 | K68: 1949 | L68: 1854 | M68: 2126 | O68: 147850.33 | P68: 57254.51 | Q68: 40270.71 | R68: 245375.55 | S68: 217596.32 | T68: 61515.33 | U68: 31236.48 | V68: 310348.13 | W68: 241235.07 | X68: 93533.24 | Y68: 44619.17 | Z68: 379387.48 | AA68: 219788.51 | AB68: 126179.33 | AC68: 89556 | AD68: 435523.84 | AE68: 257395.15 | AF68: 121973.22 | AG68: 138166.99 | AH68: 517535.36 | AI68: 134084.22 | AJ68: 119584.82 | AK68: 184405.85 | AL68: 438074.89 | AM68: 118141.81 | AN68: 58144.31 | AO68: 235780.79 | AP68: 412066.91 | AQ68: 93396.4 | AR68: 96775.2 | AS68: 228787.63 | AT68: 418959.23 | AU68: 177317.76 | AV68: 54190.39 | AW68: 261983.14 | AX68: 493491.29 | AZ68: 19264 | BA68: 11568.08 | BB68: 7488.53 | BC68: 38320.61 | BD68: 28994.93 | BE68: 13120.89 | BF68: 4158.74 | BG68: 46274.56 | BH68: 28184.22 | BI68: 15997.12 | BJ68: 9530.08 | BK68: 53711.42 | BL68: 22994.3 | BM68: 18941.58 | BN68: 17821.31 | BO68: 59757.19 | BP68: 27534.06 | BQ68: 16054.53 | BR68: 25181.3 | BS68: 68769.89 | BT68: 14026.26 | BU68: 14206.02 | BV68: 32750.37 | BW68: 60982.65 | BX68: 13188.15 | BY68: 5787.3 | BZ68: 42306.94 | CA68: 61282.39 | CB68: 6633.07 | CC68: 14807.15 | CD68: 39713.57 | CE68: 61153.79 | CF68: 17657.77 | CG68: 5385.63 | CH68: 47447.97 | CI68: 70491.37 | CL68: 16193.469 | CM68: 19097.423 | CN68: 28090.535 | CO68: 43801.591 | CP68: 54493.08 | CQ68: 67303.355 | CR68: 77488.201 | CS68: 83044.394 | CT68: 91274.663 | DG68: 52 | DH68: 54 | DI68: 43 | DJ68: 88 | DK68: 36 | DL68: 33 | DO68: 1 | DQ68: 12870.32 | DR68: 12088.88 | DS68: 10202.07 | DT68: 27325.88 | DU68: 8337.7 | DV68: 5974.77 | DY68: 182.85 | EA68: 1585.75 | EB68: 1985.92 | EC68: 1645.1 | ED68: 2086.43 | EE68: 485.1 | EF68: 1323.93 | EG68: 2433.6
A69: 99363 | B69: RES | C69: =A69&B69 -> 99363RES | E69: 20 | F69: 22 | H69: 18 | I69: 23 | J69: 24 | K69: 21 | L69: 22 | M69: 20 | O69: 3074.42 | P69: 269.01 | Q69: 191.4 | R69: 3534.83 | S69: 3465.67 | T69: 1139.47 | U69: 241.3 | V69: 4846.44 | W69: 240.1 | X69: 1747.14 | Y69: 117.18 | Z69: 2104.42 | AA69: 1955.49 | AB69: 640.4 | AC69: 270.4 | AD69: 2866.29 | AE69: 2197.56 | AF69: 2337.29 | AG69: 999.37 | AH69: 5534.22 | AI69: 1695.11 | AJ69: 1419.95 | AK69: 1289.77 | AL69: 4404.83 | AM69: 1605.12 | AN69: 791.54 | AO69: 1392.03 | AP69: 3788.69 | AQ69: 2351.09 | AR69: 602.93 | AS69: 1246.86 | AT69: 4200.88 | AU69: 1937.09 | AV69: 871.34 | AW69: 1418.66 | AX69: 4227.09 | AZ69: 46.42 | BA69: 41.87 | BC69: 88.29 | BD69: 36.99 | BE69: 46.42 | BF69: 41.87 | BG69: 125.28 | BL69: 36.38 | BO69: 36.38 | BP69: 121.1 | BQ69: 131.17 | BR69: 36.38 | BS69: 288.65 | BT69: 89.85 | BU69: 121.1 | BV69: 167.55 | BW69: 378.5 | BX69: 66.6 | BY69: 89.85 | BZ69: 288.65 | CA69: 445.1 | CB69: 48.06 | CC69: 37.6 | CD69: 234.98 | CE69: 320.64 | CF69: 45.47 | CG69: 48.06 | CH69: 272.58 | CI69: 366.11 | CL69: 133.81697 | CM69: 253.92415 | CN69: 196.68149 | CO69: 200.27854 | CP69: 492.98532 | CQ69: 538.05452 | CR69: 518.90835 | CS69: 510.18957 | CT69: 558.09456 | DL69: 1 | DV69: 28.34 | EF69: 28.34
A70: 98939 | B70: COM | C70: 98939COM | E70: 0 | F70: 3 | G70: 2 | H70: 2 | I70: 3 | J70: 3 | K70: 3 | L70: 3 | M70: 5 | O70: 0 | P70: 0 | Q70: 0 | R70: 0 | S70: 469.55 | T70: 0 | U70: 0 | V70: 469.55 | W70: 156.67 | X70: 0 | Y70: 0 | Z70: 156.67 | AA70: 134.39 | AB70: 0 | AC70: 0 | AD70: 134.39 | AE70: 208.18 | AF70: 21.71 | AG70: 0 | AH70: 229.89 | AI70: 335.62 | AJ70: 103.91 | AK70: 0 | AL70: 439.53 | AM70: 187.11 | AN70: 105.01 | AO70: 26.13 | AP70: 318.25 | AQ70: 229.02 | AR70: 100.74 | AS70: 131.14 | AT70: 460.9 | AU70: 360.6 | AV70: 201.17 | AW70: 17.99 | AX70: 579.76 | CL70: 0 | CM70: 14.564155 | CN70: 5.1322109 | CO70: 4.8502415 | CP70: 7.2484548 | CQ70: 17.794929 | CR70: 21.310617 | CS70: 55.982548 | CT70: 28.429185
C71: 99301COM | H71: 1 | I71: 1 | AA71: 116.35 | AB71: 0 | AC71: 0 | AD71: 116.35 | AE71: 107.54 | AF71: 0 | AG71: 0 | AH71: 230.89 | CL71: 0 | CM71: 0 | CN71: 0 | CO71: 4.1991636 | CP71: 3.0561449 | CT71: 0

Sheet 8. Past Due Balances 2020
F1: 5 | G1: 5 | H1: 5 | I1: 5 | J1: 5 | K1: 5 | L1: 5 | V1: 5 | AF1: 6 | AG1: 7 | AH1: 8 | AI1: 9 | BU1: 2 | BV1: 3 | BW1: 4 | BX1: 5 | BY1: 2 | BZ1: 3 | CA1: 4 | CB1: 5 | CC1: 2 | CD1: 3 | CE1: 4 | CF1: 5 | CG1: 2 | CH1: 3 | CI1: 4 | CJ1: 5 | CK1: 2 | CL1: 3 | CM1: 4 | CN1: 5 | CO1: 2 | CP1: 3 | CQ1: 4 | CR1: 5 | CS1: 2 | CT1: 3 | CU1: 4 | CV1: 5 | CW1: 2 | CX1: 3 | CY1: 4 | CZ1: 5 | DA1: 2 | DB1: 3 | DC1: 4 | DD1: 5 | DF1: 2 | DG1: 3 | DH1: 4 | DI1: 5 | DJ1: 2 | DK1: 3 | DL1: 4 | DM1: 5 | DN1: 2 | DO1: 3 | DP1: 4 | DQ1: 5 | DT1: ACCOUTING - ESTIMATE | EG1: BD WRITE OFF -- WOF | EU1: 14 | EV1: 15 | EW1: 16 | EX1: 17 | EY1: 18 | EZ1: 19 | FB1: 20 | FF1: 21 | FH1: 14 | FI1: 15 | FJ1: 16 | FK1: 17 | FL1: 18 | FM1: 19 | FO1: 20 | FS1: 21 | FU1: 2 | FV1: 3 | FW1: 4 | FX1: 5 | FY1: 6 | FZ1: 7 | GA1: 8
A2: General 2020 | E2: Item a) Number of Customers by Customer Class With Past-due balances (arrearages) | X2: Item b) Past-due Balances by Customer Class and Number of Days Past-due | BU2: Item c) Amount of Past-due Balances for Known Low-income Households and Number of Days Past-due | DT2: Item d) Amount of Past Due Balances Classified as Uncollectible | EG2: Item e) The Amount of Past-due Balances Written-off and Classified as Bad Debt, if different than item d | EU2: Item f) Number of Customer Accounts Referred to Collection Agencies | FH2: Item f) Total Amount of Bad Debt Referred for Collection | FU2: Item f) Total Revenue to the Company from the Collection Process
X3: 43831 | AB3: 43862 | AF3: 43891 | AJ3: 43922 | AN3: 43952 | AR3: 43983 | AV3: 44013 | AZ3: 44044 | BD3: 44075 | BH3: 44105 | BL3: 44136 | BP3: 44166 | BU3: 43831 | BY3: 43862 | CC3: 43891 | CG3: 43922 | CK3: 43952 | CO3: 43983 | CS3: 44013 | CW3: 44044 | DA3: 44075 | DF3: 44105 | DJ3: 44136 | DN3: 44166
A4: Zip Code | B4: Customer Class | C4: x | D4: x | E4: 43831 | F4: 43862 | G4: 43891 | H4: 43922 | I4: 43952 | J4: 43983 | K4: 44013 | L4: 44044 | M4: 44075 | P4: 44105 | S4: 44136 | V4: 44166 | W4: x | X4: 30 Days | Y4: 60 Days | Z4: 90 Days + | AA4: Total Arrearages | AB4: 30 Days | AC4: 60 Days | AD4: 90 Days + | AE4: Total Arrearages | AF4: 30 Days | AG4: 60 Days | AH4: 90 Days + | AI4: Total Arrearages | AJ4: 30 Days | AK4: 60 Days | AL4: 90 Days + | AM4: Total Arrearages | AN4: 30 Days | AO4: 60 Days | AP4: 90 Days + | AQ4: Total Arrearages | AR4: 30 Days | AS4: 60 Days | AT4: 90 Days + | AU4: Total Arrearages | AV4: 30 Days | AW4: 60 Days | AX4: 90 Days + | AY4: Total Arrearages | AZ4: 30 Days | BA4: 60 Days | BB4: 90 Days + | BC4: Total Arrearages | BD4: 30 Days | BE4: 60 Days | BF4: 90 Days + | BG4: Total Arrearages | BH4: 30 Days | BI4: 60 Days | BJ4: 90 Days + | BK4: Total Arrearages | BL4: 30 Days | BM4: 60 Days | BN4: 90 Days + | BO4: Total Arrearages | BP4: 30 Days | BQ4: 60 Days | BR4: 90 Days + | BS4: Total Arrearages | BU4: 30 Days | BV4: 60 Days | BW4: 90 Days + | BX4: Total Arrearages | BY4: 30 Days | BZ4: 60 Days | CA4: 90 Days + | CB4: Total Arrearages | CC4: 30 Days | CD4: 60 Days | CE4: 90 Days + | CF4: Total Arrearages | CG4: 30 Days | CH4: 60 Days | CI4: 90 Days + | CJ4: Total Arrearages | CK4: 30 Days | CL4: 60 Days | CM4: 90 Days + | CN4: Total Arrearages | CO4: 30 Days | CP4: 60 Days | CQ4: 90 Days + | CR4: Total Arrearages | CS4: 30 Days | CT4: 60 Days | CU4: 90 Days + | CV4: Total Arrearages | CW4: 30 Days | CX4: 60 Days | CY4: 90 Days + | CZ4: Total Arrearages | DA4: 30 Days | DB4: 60 Days | DC4: 90 Days + | DD4: Total Arrearages | DF4: 30 Days | DG4: 60 Days | DH4: 90 Days + | DI4: Total Arrearages | DJ4: 30 Days | DK4: 60 Days | DL4: 90 Days + | DM4: Total Arrearages | DN4: 30 Days | DO4: 60 Days | DP4: 90 Days + | DQ4: Total Arrearages | DT4: 43831 | DU4: 43862 | DV4: 43891 | DW4: 43922 | DX4: 43952 | DY4: 43983 | DZ4: 44013 | EA4: 44044 | EB4: 44075 | EC4: 44105 | ED4: 44136 | EE4: 44166 | EG4: CLASS | EH4: 43831 | EI4: 43862 | EJ4: 43891 | EK4: 43922 | EL4: 43952 | EM4: 43983 | EN4: 44013 | EO4: 44044 | EP4: 44075 | EQ4: 44105 | ER4: 44136 | ES4: 44166 | EU4: 43831 | EV4: 43862 | EW4: 43891 | EX4: 43922 | EY4: 43952 | EZ4: 43983 | FA4: 44013 | FB4: 44044 | FC4: 44075 | FD4: 44105 | FE4: 44136 | FF4: 44166 | FH4: 43831 | FI4: 43862 | FJ4: 43891 | FK4: 43922 | FL4: 43952 | FM4: 43983 | FN4: 44013 | FO4: 44044 | FP4: 44075 | FQ4: 44105 | FR4: 44136 | FS4: 44166 | FU4: 43831 | FV4: 43862 | FW4: 43891 | FX4: 43922 | FY4: 43952 | FZ4: 43983 | GA4: 44013 | GB4: 44044 | GC4: 44075 | GD4: 44105 | GE4: 44136 | GF4: 44166
