Workbook

Sheet 1. General 2024_Q1
A1: Count of aggreements by ZIP and CLASS.
A2: WA_TERM_COVID_COUNTS
A3: General 2024
A4: 45292 | D4: 45323 | G4: 45352 | K4: Retail Sales (kWh) | L4: July | M4: August | N4: September | O4: 45292 | P4: 45324 | Q4: 45354 | R4: July | S4: August | T4: September | U4: October | V4: November | W4: December | X4: Totals Q1
A5: Zip | B5: Class | C5: Count | D5: Zip | E5: Class | F5: Count | G5: Zip | H5: Class | I5: Count | K5: Residential | L5: 149454803 | M5: 144341255 | N5: 106642496 | O5: 210372218 | P5: 185759262 | Q5: 145770248 | X5: =SUM(O5:Q5) -> 541901728
A6: 98901 | B6: COM | C6: 2148 | D6: 98901 | E6: COM | F6: 2155 | G6: 98901 | H6: COM | I6: 2149 | K6: Commercial | L6: 140404042 | M6: 148198213 | N6: 131511808 | O6: 136370618 | P6: 125657389 | Q6: 120323998 | X6: =SUM(O6:Q6) -> 382352005
A7: 98902 | B7: COM | C7: 2583 | D7: 98902 | E7: COM | F7: 2579 | G7: 98902 | H7: COM | I7: 2586 | K7: Industrial | L7: 72533895 | M7: 71622459 | N7: 72818621 | O7: 97571126 | P7: 24268044 | Q7: 61864249 | X7: =SUM(O7:Q7) -> 183703419
A8: 98903 | B8: COM | C8: 1671 | D8: 98903 | E8: COM | F8: 1668 | G8: 98903 | H8: COM | I8: 1660 | K8: Irrigation | L8: 36860793 | M8: 39164393 | N8: 25760901 | O8: 503639 | P8: 634240 | Q8: 1931983 | X8: =SUM(O8:Q8) -> 3069862
A9: 98904 | B9: COM | C9: 2 | D9: 98904 | E9: COM | F9: 2 | G9: 98904 | H9: COM | I9: 2 | K9: Totals | L9: =SUM(L5:L8) -> 399253533 | M9: =SUM(M5:M8) -> 403326320 | N9: =SUM(N5:N8) -> 336733826 | O9: =SUM(O5:O8) -> 444817601 | P9: =SUM(P5:P8) -> 336318935 | Q9: =SUM(Q5:Q8) -> 329890478 | R9: =SUM(R5:R8) -> 0 | S9: =SUM(S5:S8) -> 0 | ... X9: =SUM(X5:X8) -> 1111027014
A10: 98907 | B10: COM | C10: 2 | D10: 98907 | E10: COM | F10: 2 | G10: 98907 | H10: COM | I10: 2
A11: 98908 | B11: COM | C11: 1607 | D11: 98908 | E11: COM | F11: 1601 | G11: 98908 | H11: COM | I11: 1615
A12: 98920 | B12: COM | C12: 4 | D12: 98920 | E12: COM | F12: 4 | G12: 98920 | H12: COM | I12: 4
A13: 98921 | B13: COM | C13: 27 | D13: 98921 | E13: COM | F13: 26 | G13: 98921 | H13: COM | I13: 26
A14: 98923 | B14: COM | C14: 105 | D14: 98923 | E14: COM | F14: 106 | G14: 98923 | H14: COM | I14: 106
A15: 98930 | B15: COM | C15: 663 | D15: 98930 | E15: COM | F15: 660 | G15: 98930 | H15: COM | I15: 664
A16: 98932 | B16: COM | C16: 233 | D16: 98932 | E16: COM | F16: 230 | G16: 98932 | H16: COM | I16: 230
A17: 98933 | B17: COM | C17: 71 | D17: 98933 | E17: COM | F17: 72 | G17: 98933 | H17: COM | I17: 72
A18: 98935 | B18: COM | C18: 139 | D18: 98935 | E18: COM | F18: 142 | G18: 98935 | H18: COM | I18: 140
A19: 98936 | B19: COM | C19: 344 | D19: 98936 | E19: COM | F19: 345 | G19: 98936 | H19: COM | I19: 345
A20: 98937 | B20: COM | C20: 400 | D20: 98937 | E20: COM | F20: 399 | G20: 98937 | H20: COM | I20: 403
A21: 98938 | B21: COM | C21: 158 | D21: 98938 | E21: COM | F21: 159 | G21: 98938 | H21: COM | I21: 158
... A41: 99363 | B41: COM | C41: 73 | D41: 99363 | E41: COM | F41: 73 | G41: 99363 | H41: COM | I41: 73
B42: COM | C42: 4 | E42: COM | F42: 4 | H42: COM | I42: 4
A43: 98901 | B43: IND | C43: 48 | D43: 98901 | E43: IND | F43: 48 | G43: 98901 | H43: IND | I43: 48
A44: 98902 | B44: IND | C44: 85 | D44: 98902 | E44: IND | F44: 85 | G44: 98902 | H44: IND | I44: 85
A45: 98903 | B45: IND | C45: 64 | D45: 98903 | E45: IND | F45: 64 | G45: 98903 | H45: IND | I45: 64
A46: 98908 | B46: IND | C46: 17 | D46: 98908 | E46: IND | F46: 17 | G46: 98908 | H46: IND | I46: 17
A47: 98921 | B47: IND | C47: 1 | D47: 98921 | E47: IND | F47: 1 | G47: 98921 | H47: IND | I47: 1
A48: 98923 | B48: IND | C48: 4 | D48: 98923 | E48: IND | F48: 4 | G48: 98923 | H48: IND | I48: 4
A49: 98930 | B49: IND | C49: 26 | D49: 98930 | E49: IND | F49: 26 | G49: 98930 | H49: IND | I49: 26
A50: 98932 | B50: IND | C50: 12 | D50: 98932 | E50: IND | F50: 12 | G50: 98932 | H50: IND | I50: 12
A51: 98933 | B51: IND | C51: 1 | D51: 98933 | E51: IND | F51: 1 | G51: 98933 | H51: IND | I51: 1
A52: 98935 | B52: IND | C52: 3 | D52: 98935 | E52: IND | F52: 3 | G52: 98935 | H52: IND | I52: 4
A53: 98936 | B53: IND | C53: 18 | D53: 98936 | E53: IND | F53: 18 | G53: 98936 | H53: IND | I53: 18
A54: 98937 | B54: IND | C54: 11 | D54: 98937 | E54: IND | F54: 11 | G54: 98937 | H54: IND | I54: 11
... A144: 99363 | B144: RES | C144: 72 | D144: 99363 | E144: RES | F144: 74 | G144: 99363 | H144: RES | I144: 72

Sheet 2. Disconnections 2024_Q1
A1: General 2024 | D1: Item a) Number of Disconnections by Customer Class per Month | N1: Item b) Avg. Duration of Disconnection by Customer Class (in Hours for recon 10 days or less) | X1: Item c) Number of Customers by Customer Class Receiving Disconnection Notices | AC1: Item d) Number of Customers by Customer Class Who Absent the Disconnection Moratorium Would Have Been Disconnected
D2: Zip Code | E2: Customer Class | F2: 45292 | G2: Zip Code | H2: Customer Class | I2: 45323 | J2: Zip Code | K2: Customer Class | L2: 45352 | N2: ZIP | O2: REV | P2: 45292 | Q2: ZIP | R2: REV | S2: 45323 | T2: ZIP | U2: REV | V2: 45352 | X2: Category | Y2: 45292 | Z2: 45323 | AA2: 45352 | AC2: Category | AD2: 45292 | AE2: 45323 | AF2: 45352
D3: 98901 | E3: RES | F3: 3 | G3: 98901 | H3: RES | I3: 1 | J3: 98901 | K3: RES | L3: 7 | N3: RES | O3: 98903 | P3: 1.3854167 | Q3: RES | R3: 98908 | S3: 0.24791667 | T3: RES | U3: 98901 | V3: 0.86493056 | X3: FFN | Y3: 7051 | Z3: 7345 | AA3: 7751
D4: 98902 | E4: RES | F4: 3 | G4: 98908 | H4: RES | I4: 2 | J4: 98902 | K4: RES | L4: 32 | N4: RES | O4: 99328 | P4: 2.1284722 | Q4: RES | R4: 99323 | S4: 0.51909722 | T4: RES | U4: 98902 | V4: 0.59502315 | X4: FNL | Y4: 11288 | Z4: 11763 | AA4: 11866
D5: 98903 | E5: COM | F5: 1 | G5: 98932 | H5: RES | I5: 2 | J5: 98903 | K5: RES | L5: 14 | N5: RES | O5: 99362 | P5: 0.73414352 | Q5: RES | R5: 99324 | S5: 1.4166667 | T5: RES | U5: 98903 | V5: 0.50677083 | X5: PDN | Y5: 13846 | Z5: 14638 | AA5: 14591
D6: 98903 | E6: RES | F6: 10 | G6: 98951 | H6: COM | I6: 1 | J6: 98908 | K6: COM | L6: 1 | Q6: RES | R6: 99328 | S6: 0.62222222 | T6: RES | U6: 98908 | V6: 2.0520833
D7: 98948 | E7: RES | F7: 2 | G7: 98951 | H7: IRG | I7: 1 | J7: 98908 | K7: RES | L7: 4 | Q7: RES | R7: 99360 | S7: 0.86388889 | T7: RES | U7: 98921 | V7: 0.099305556
D8: 99328 | E8: RES | F8: 2 | G8: 98951 | H8: RES | I8: 4 | J8: 98921 | K8: RES | L8: 2 | Q8: RES | R8: 99362 | S8: 1.0440972 | T8: RES | U8: 98944 | V8: 1.1159722
D9: 99362 | E9: RES | F9: 17 | G9: 99323 | H9: RES | I9: 3 | J9: 98930 | K9: RES | L9: 1 | T9: RES | U9: 98948 | V9: 0.35972222
G10: 99324 | H10: RES | I10: 2 | J10: 98942 | K10: RES | L10: 1 | T10: RES | U10: 98951 | V10: 0.13333333
G11: 99328 | H11: RES | I11: 4 | J11: 98944 | K11: RES | L11: 3 | T11: RES | U11: 99324 | V11: 1.1138889
G12: 99360 | H12: RES | I12: 2 | J12: 98948 | K12: RES | L12: 3 | T12: RES | U12: 99362 | V12: 0.74583333
G13: 99362 | H13: RES | I13: 5 | J13: 98951 | K13: RES | L13: 1
G14: 99363 | H14: RES | I14: 1 | J14: 99324 | K14: RES | L14: 5
J15: 99328 | K15: RES | L15: 3
J16: 99362 | K16: RES | L16: 4
D17: TOTAL | F17: =SUM(F3:F9) -> 38 | I17: =SUM(I3:I9) -> 14 | L17: =SUM(L3:L9) -> 61

Sheet 3. Fees 2024_Q1
A1: General 2024 | D1: Item a) Number of Customers by Customer Class Assessed Late Payment Fees | H1: Item a) Aggregate amount of Charged Late Payment Fees | L1: Item a) Number of Customers by Customer Class Assessed Disconnection Fees | P1: Item a) Aggregate amount of Charged Disconnection Fees | T1: Item a) Number of Customers by Customer Class Assessed Reconnection Fees | X1: Item a) Aggregate amount of Charged Reconnection Fees
A2: Zip Code | B2: Customer Class | D2: 45292 | E2: 45323 | F2: 45352 | H2: 45292 | I2: 45323 | J2: 45352 | L2: 45292 | M2: 45323 | N2: 45352 | P2: 45292 | Q2: 45323 | R2: 45352 | T2: 45292 | U2: 45323 | V2: 45352 | X2: 45292 | Y2: 45323 | Z2: 45352
A3: None
A4: Asked JH question

Sheet 4. Payment Arrangements 2024_Q1
A1: General 2024 | D1: Item a) Number of Customers by Customer Class Taking Service at the Beginning of Each Month with Existing Long Term Payment Agreements | H1: Item b) Number of Customers By Customer Class Completing Long-term Payment Agreements | L1: Item c) Number of Customers by Customer Class Enrolling in New Long-term Payment Agreements | P1: Item d) Number of Customers By Customer Class Renegotiating Long-term Payment Agreements
A2: Zip Code | B2: Customer Class | D2: 45292 | E2: 45323 | F2: 45352 | H2: 45292 | I2: 45323 | J2: 45352 | L2: 45292 | M2: 45323 | N2: 45352 | P2: 45292 | Q2: 45323 | R2: 45352
A3: NA | B3: COM | D3: 142 | E3: 170 | F3: 172 | H3: 19 | I3: 20 | J3: 33 | L3: 62 | M3: 54 | N3: 62 | P3: 0 | Q3: 0 | R3: 1
A4: NA | B4: RES | D4: 4276 | E4: 4296 | F4: 4442 | H4: 250 | I4: 209 | J4: 169 | L4: 991 | M4: 1144 | N4: 1187 | P4: 27 | Q4: 28 | R4: 33

Sheet 5. Medical Certificates 2024_Q1
A1: General 2023 | D1: Item a) Number of Customers Taking Service at the Beginning of Each Month Under Existing Medical Payment Arrangements | H1: Item b) Number of Customers Completing Medical Payment Arrangements Each Month | L1: Item c) Number of Customers Enrolling in New Medical Payment Arrangements Each Month | P1: Item d) Number of Customers Renegotiating Medical Payment Arrangements Each Month
A2: Zip Code | B2: Customer Class | D2: 45292 | E2: 45323 | F2: 45352 | H2: 45292 | I2: 45323 | J2: 45352 | L2: 45292 | M2: 45323 | N2: 45352 | P2: 44197 | Q2: 44228 | R2: 44256 | S2: 44287 | T2: 44317 | U2: 44348 | V2: 44378 | W2: 44409 | X2: 44440 | Y2: 45292 | Z2: 45323 | AA2: 45352
A3: NA | B3: RES | D3: 19 | E3: 16 | F3: 14 | H3: 0 | I3: 0 | J3: 0 | L3: 4 | M3: 5 | N3: 11 | P3: 0 | Q3: 0 | R3: 0 | S3: 0 | T3: 0 | U3: 0 | V3: 0 | W3: 0 | X3: 0 | Y3: 0 | Z3: 0 | AA3: 0

Sheet 6. Deposits 2024_Q1
A1: General 2024 | D1: Item a) Number of Customers by Customer Class with Required Deposits at the Beginning of Each Month | N1: Item b) Number of Customers by Customer Class Required to Submit New or Increased Deposits Each Month | AH1: Item c) Number of Customers by Customer Class Whose Deposits Were Reduced In Part or Foregone Each Month | AR1: Item d) Number of Customers by Customer Class whose Deposits were Returned in Full Each Month
D2: 45292 | G2: 45323 | J2: 45352 | N2: Zip Code | O2: Customer Class | P2: 44197 | Q2: 44228 | R2: 44256 | S2: Zip Code | T2: Customer Class | U2: 44287 | V2: 44317 | W2: 44348 | X2: 45292 | AA2: 45323 | AD2: 45352 | AH2: 44197 | AI2: 44228 | AJ2: 44256 | AK2: 44287 | AL2: 44317 | AM2: 44348 | AN2: 45292 | AO2: 45323 | AP2: 45352 | AR2: 45292 | AU2: 45323 | AX2: 45352
D3: ZIP | E3: CLASS | F3: Concat Agreement Number | G3: ZIP | H3: CLASS | I3: Concat Agreement Number | J3: ZIP | K3: CLASS | L3: Concat Agreement Number | N3: 98901 | O3: COM | P3: 4 | Q3: 1 | R3: 2 | S3: 98901 | T3: COM | U3: 1 | V3: 6 | X3: ZIP | Y3: CLASS | Z3: Concat Agreement Number | AA3: ZIP | AB3: CLASS | AC3: Concat Agreement Number | AD3: ZIP | AE3: CLASS | AF3: Concat Agreement Number | AR3: ZIP | AS3: CLASS | AT3: Concat Agreement Number | AU3: ZIP | AV3: CLASS | AW3: Concat Agreement Number | AX3: ZIP | AY3: CLASS | AZ3: Concat Agreement Number
D4: 98901 | E4: COM | F4: 64 | G4: 98901 | H4: COM | I4: 62 | J4: 98901 | K4: COM | L4: 61 | N4: 98901 | O4: RES | P4: 71 | Q4: 53 | R4: 58 | S4: 98901 | T4: RES | U4: 19 | V4: 17 | W4: 19 | X4: 98901 | Y4: COM | Z4: 7 | AA4: 98901 | AB4: COM | AC4: 2 | AD4: 98901 | AE4: COM | AF4: 9 | AR4: 98901 | AS4: COM | AT4: 8 | AU4: 98901 | AV4: COM | AW4: 3 | AX4: 98901 | AY4: COM | AZ4: 3
D5: 98901 | E5: RES | F5: 4 | G5: 98901 | H5: RES | I5: 4 | J5: 98901 | K5: RES | L5: 4 | N5: 98902 | O5: COM | Q5: 6 | R5: 3 | S5: 98902 | T5: COM | U5: 4 | V5: 12 | W5: 5 | X5: 98902 | Y5: COM | Z5: 14 | AA5: 98902 | AB5: COM | AC5: 11 | AD5: 98902 | AE5: COM | AF5: 10 | AR5: 98902 | AS5: COM | AT5: 4 | AU5: 98902 | AV5: COM | AW5: 2 | AX5: 98902 | AY5: COM | AZ5: 1
D6: 98902 | E6: COM | F6: 90 | G6: 98902 | H6: COM | I6: 101 | J6: 98902 | K6: COM | L6: 110 | N6: 98902 | O6: RES | P6: 103 | Q6: 75 | R6: 32 | S6: 98902 | T6: RES | U6: 48 | V6: 22 | W6: 19 | X6: 98903 | Y6: COM | Z6: 8 | AA6: 98903 | AB6: COM | AC6: 5 | AD6: 98903 | AE6: COM | AF6: 2 | AR6: 98902 | AS6: RES | AT6: 1 | AU6: 98903 | AV6: COM | AW6: 2 | AX6: 98903 | AY6: COM | AZ6: 3
D7: 98902 | E7: RES | F7: 1 | G7: 98903 | H7: COM | I7: 48 | J7: 98903 | K7: COM | L7: 50 | N7: 98903 | O7: COM | P7: 6 | R7: 1 | S7: 98903 | T7: COM | U7: 2 | V7: 3 | W7: 3 | X7: 98908 | Y7: COM | Z7: 6 | AA7: 98908 | AB7: COM | AC7: 5 | AD7: 98908 | AE7: COM | AF7: 6 | AR7: 98903 | AS7: COM | AT7: 4 | AU7: 98903 | AV7: RES | AW7: 1 | AX7: 98903 | AY7: RES | AZ7: 1
D8: 98903 | E8: COM | F8: 42 | G8: 98903 | H8: RES | I8: 4 | J8: 98903 | K8: RES | L8: 3 | N8: 98903 | O8: RES | P8: 17 | Q8: 16 | R8: 22 | S8: 98903 | T8: RES | U8: 5 | V8: 1 | W8: 6 | X8: 98930 | Y8: COM | Z8: 2 | AA8: 98923 | AB8: COM | AC8: 1 | AD8: 98921 | AE8: COM | AF8: 1 | AR8: 98908 | AS8: COM | AT8: 3 | AU8: 98908 | AV8: COM | AW8: 2 | AX8: 98908 | AY8: COM | AZ8: 3
D9: 98903 | E9: RES | F9: 4 | G9: 98908 | H9: COM | I9: 37 | J9: 98908 | K9: COM | L9: 40 | N9: 98908 | O9: COM | P9: 4 | Q9: 1 | R9: 2 | S9: 98908 | T9: COM | V9: 4 | W9: 2 | X9: 98932 | Y9: COM | Z9: 2 | AA9: 98930 | AB9: COM | AC9: 1 | AD9: 98923 | AE9: COM | AF9: 2 | AR9: 98908 | AS9: RES | AT9: 2 | AU9: 98930 | AV9: COM | AW9: 1 | AX9: 98933 | AY9: RES | AZ9: 1
D10: 98908 | E10: COM | F10: 34 | G10: 98908 | H10: RES | I10: 10 | J10: 98908 | K10: RES | L10: 10 | N10: 98908 | O10: RES | P10: 37 | Q10: 59 | R10: 47 | S10: 98908 | T10: RES | U10: 31 | V10: 18 | W10: 14 | X10: 98944 | Y10: COM | Z10: 3 | AA10: 98938 | AB10: COM | AC10: 1 | AD10: 98930 | AE10: COM | AF10: 2 | AR10: 98932 | AS10: COM | AT10: 1 | AU10: 98942 | AV10: COM | AW10: 1 | AX10: 98947 | AY10: COM | AZ10: 2
D11: 98908 | E11: RES | F11: 12 | G11: 98921 | H11: RES | I11: 1 | J11: 98921 | K11: RES | L11: 1 | N11: 98921 | O11: RES | P11: 2 | Q11: 1 | S11: 98921 | T11: RES | U11: 2 | X11: 98947 | Y11: COM | Z11: 1 | AA11: 98944 | AB11: COM | AC11: 8 | AD11: 98937 | AE11: COM | AF11: 1 | AR11: 98936 | AS11: COM | AT11: 4 | AU11: 98944 | AV11: COM | AW11: 2 | AX11: 98948 | AY11: COM | AZ11: 3
D12: 98921 | E12: RES | F12: 1 | G12: 98923 | H12: COM | I12: 1 | J12: 98923 | K12: COM | L12: 2 | N12: 98923 | O12: RES | P12: 3 | Q12: 1 | S12: 98923 | T12: RES | U12: 1 | X12: 98948 | Y12: COM | Z12: 4 | AA12: 98948 | AB12: COM | AC12: 2 | AD12: 98942 | AE12: COM | AF12: 2 | AR12: 98937 | AS12: COM | AT12: 2 | AU12: 98948 | AV12: COM | AW12: 2 | AX12: 98948 | AY12: RES | AZ12: 1
D13: 98923 | E13: COM | F13: 1 | G13: 98930 | H13: COM | I13: 16 | J13: 98930 | K13: COM | L13: 16 | N13: 98930 | O13: COM | P13: 2 | Q13: 2 | R13: 1 | S13: 98930 | T13: COM | V13: 2 | X13: 98951 | Y13: COM | Z13: 1 | AA13: 98951 | AB13: COM | AC13: 2 | AD13: 98944 | AE13: COM | AF13: 4 | AR13: 98942 | AS13: RES | AT13: 1 | AU13: 98951 | AV13: COM | AW13: 13 | AX13: 98951 | AY13: COM | AZ13: 2
D14: 98930 | E14: COM | F14: 14 | G14: 98930 | H14: RES | I14: 1 | J14: 98930 | K14: RES | L14: 1 | N14: 98930 | O14: RES | P14: 11 | Q14: 23 | R14: 21 | S14: 98930 | T14: RES | U14: 3 | V14: 2 | W14: 1 | X14: 98953 | Y14: COM | Z14: 4 | AA14: 98953 | AB14: COM | AC14: 1 | AD14: 98948 | AE14: COM | AF14: 4 | AR14: 98944 | AS14: COM | AT14: 1 | AU14: 98953 | AV14: COM | AW14: 1 | AX14: 98953 | AY14: COM | AZ14: 5
D15: 98930 | E15: RES | F15: 1 | G15: 98932 | H15: COM | I15: 4 | J15: 98932 | K15: COM | L15: 4 | N15: 98932 | O15: RES | P15: 5 | Q15: 4 | R15: 6 | S15: 98932 | T15: RES | V15: 3 | X15: 99324 | Y15: COM | Z15: 1 | AA15: 99328 | AB15: COM | AC15: 1 | AD15: 98951 | AE15: COM | AF15: 5 | AR15: 98948 | AS15: COM | AT15: 1 | AU15: 99347 | AV15: COM | AW15: 1 | AX15: 99360 | AY15: COM | AZ15: 1
D16: 98932 | E16: COM | F16: 2 | G16: 98933 | H16: COM | I16: 2 | J16: 98933 | K16: COM | L16: 2 | N16: 98933 | O16: RES | Q16: 1 | S16: 98933 | T16: RES | X16: 99328 | Y16: COM | Z16: 1 | AA16: 99329 | AB16: COM | AC16: 1 | AD16: 98953 | AE16: COM | AF16: 5 | AR16: 99347 | AS16: COM | AT16: 1 | AU16: 99360 | AV16: COM | AW16: 1 | AX16: 99362 | AY16: COM | AZ16: 9
D17: 98933 | E17: COM | F17: 2 | G17: 98933 | H17: RES | I17: 1 | J17: 98933 | K17: RES | L17: 1 | N17: 98935 | O17: COM | Q17: 4 | S17: 98935 | T17: COM | X17: 99362 | Y17: COM | Z17: 7 | AA17: 99360 | AB17: COM | AC17: 1 | AD17: 99347 | AE17: COM | AF17: 1 | AR17: 99362 | AS17: COM | AT17: 8 | AU17: 99362 | AV17: COM | AW17: 5
D18: 98933 | E18: RES | F18: 1 | G18: 98935 | H18: COM | I18: 10 | J18: 98935 | K18: COM | L18: 10 | N18: 98935 | O18: RES | P18: 6 | Q18: 9 | R18: 1 | S18: 98935 | T18: RES | U18: 2 | V18: 1 | AA18: 99362 | AB18: COM | AC18: 7 | AD18: 99360 | AE18: COM | AF18: 1
D19: 98935 | E19: COM | F19: 10 | G19: 98936 | H19: COM | I19: 8 | J19: 98936 | K19: COM | L19: 8 | N19: 98936 | O19: RES | P19: 2 | Q19: 6 | R19: 5 | S19: 98936 | T19: RES | AD19: 99361 | AE19: COM | AF19: 1
D20: 98936 | E20: COM | F20: 12 | G20: 98937 | H20: COM | I20: 9 | J20: 98937 | K20: COM | L20: 9 | N20: 98937 | O20: RES | P20: 5 | Q20: 2 | R20: 2 | S20: 98937 | T20: COM | U20: 1 | W20: 2 | AD20: 99362 | AE20: COM | AF20: 11
D21: 98937 | E21: COM | F21: 11 | G21: 98938 | H21: COM | I21: 1 | J21: 98938 | K21: COM | L21: 2 | N21: 98938 | O21: COM | P21: 1 | S21: 98937 | T21: RES | V21: 2
D22: 98938 | E22: COM | F22: 1 | G22: 98942 | H22: COM | I22: 14 | J22: 98942 | K22: COM | L22: 13 | N22: 98938 | O22: RES | P22: 7 | Q22: 2 | R22: 1 | S22: 98938 | T22: COM
D23: 98942 | E23: COM | F23: 14 | G23: 98944 | H23: COM | I23: 39 | J23: 98944 | K23: COM | L23: 45 | N23: 98939 | O23: RES | P23: 1 | S23: 98938 | T23: RES
D24: 98942 | E24: RES | F24: 1 | G24: 98944 | H24: RES | I24: 4 | J24: 98944 | K24: RES | L24: 4 | N24: 98942 | O24: COM | P24: 2 | Q24: 2 | S24: 98939 | T24: RES
D25: 98944 | E25: COM | F25: 37 | G25: 98947 | H25: COM | I25: 7 | J25: 98947 | K25: COM | L25: 7 | N25: 98942 | O25: RES | P25: 14 | Q25: 25 | R25: 25 | S25: 98942 | T25: COM | W25: 2
D26: 98944 | E26: RES | F26: 4 | G26: 98947 | H26: RES | I26: 1 | J26: 98947 | K26: RES | L26: 1 | N26: 98944 | O26: COM | P26: 4 | Q26: 1 | R26: 9 | S26: 98942 | T26: RES | U26: 7 | V26: 8 | W26: 6
D27: 98947 | E27: COM | F27: 6 | G27: 98948 | H27: COM | I27: 21 | J27: 98948 | K27: COM | L27: 21 | N27: 98944 | O27: RES | P27: 36 | Q27: 21 | R27: 7 | S27: 98944 | T27: COM | U27: 2 | V27: 3 | W27: 1
D28: 98947 | E28: RES | F28: 1 | G28: 98948 | H28: RES | I28: 3 | J28: 98948 | K28: RES | L28: 3 | N28: 98947 | O28: RES | P28: 3 | Q28: 5 | S28: 98944 | T28: RES | U28: 13 | V28: 7 | W28: 2
D29: 98948 | E29: COM | F29: 18 | G29: 98951 | H29: COM | I29: 43 | J29: 98951 | K29: COM | L29: 32 | N29: 98948 | O29: RES | P29: 20 | Q29: 16 | R29: 20 | S29: 98947 | T29: RES | U29: 4 | V29: 2
D30: 98948 | E30: RES | F30: 3 | G30: 98951 | H30: RES | I30: 2 | J30: 98951 | K30: RES | L30: 2 | N30: 98951 | O30: COM | R30: 1 | S30: 98948 | T30: COM | U30: 2 | V30: 5
D31: 98951 | E31: COM | F31: 42 | G31: 98952 | H31: COM | I31: 1 | J31: 98952 | K31: COM | L31: 1 | N31: 98951 | O31: RES | P31: 18 | Q31: 24 | R31: 13 | S31: 98948 | T31: RES | U31: 4 | V31: 3 | W31: 1
D32: 98951 | E32: RES | F32: 2 | G32: 98953 | H32: COM | I32: 18 | J32: 98953 | K32: COM | L32: 18 | N32: 98952 | O32: RES | Q32: 1 | R32: 2 | S32: 98951 | T32: COM | U32: 1 | V32: 8 | W32: 6
D33: 98952 | E33: COM | F33: 1 | G33: 98953 | H33: RES | I33: 2 | J33: 98953 | K33: RES | L33: 2 | N33: 98953 | O33: COM | R33: 1 | S33: 98951 | T33: RES | U33: 9 | V33: 2
D34: 98953 | E34: COM | F34: 14 | G34: 99323 | H34: COM | I34: 3 | J34: 99323 | K34: COM | L34: 3 | N34: 98953 | O34: RES | P34: 7 | Q34: 6 | R34: 9 | S34: 98952 | T34: RES | V34: 2
D35: 98953 | E35: RES | F35: 2 | G35: 99324 | H35: COM | I35: 3 | J35: 99324 | K35: COM | L35: 3 | N35: 99323 | O35: RES | Q35: 2 | R35: 3 | S35: 98953 | T35: COM | U35: 2
D36: 99323 | E36: COM | F36: 3 | G36: 99328 | H36: COM | I36: 9 | J36: 99328 | K36: COM | L36: 10 | N36: 99324 | O36: RES | P36: 14 | Q36: 8 | R36: 10 | S36: 98953 | T36: RES | U36: 5 | V36: 3
D37: 99324 | E37: COM | F37: 2 | G37: 99347 | H37: COM | I37: 2 | J37: 99329 | K37: COM | L37: 1 | N37: 99328 | O37: COM | R37: 1 | S37: 99323 | T37: COM | U37: 1
D38: 99328 | E38: COM | F38: 8 | G38: 99360 | H38: COM | I38: 8 | J38: 99347 | K38: COM | L38: 1 | N38: 99328 | O38: RES | P38: 7 | Q38: 9 | R38: 4 | S38: 99323 | T38: RES | U38: 2
D39: 99347 | E39: COM | F39: 3 | G39: 99361 | H39: COM | I39: 1 | J39: 99360 | K39: COM | L39: 8 | N39: 99347 | O39: RES | P39: 2 | Q39: 4 | R39: 4 | S39: 99324 | T39: RES | U39: 8 | W39: 7
D40: 99360 | E40: COM | F40: 8 | G40: 99362 | H40: COM | I40: 80 | J40: 99361 | K40: COM | L40: 1 | N40: 99360 | O40: COM | R40: 1 | S40: 99328 | T40: COM | U40: 1 | V40: 2
D41: 99361 | E41: COM | F41: 1 | G41: 99362 | H41: RES | I41: 2 | J41: 99362 | K41: COM | L41: 82 | N41: 99360 | O41: RES | P41: 1 | Q41: 2 | S41: 99328 | T41: RES | U41: 1 | V41: 7
D42: 99362 | E42: COM | F42: 81 | J42: 99362 | K42: RES | L42: 2 | N42: 99361 | O42: RES | Q42: 4 | R42: 1 | S42: 99347 | T42: COM | U42: 2
D43: 99362 | E43: RES | F43: 2 | N43: 99362 | O43: COM | P43: 4 | Q43: 2 | R43: 1 | S43: 99347 | T43: RES | V43: 2
N44: 99362 | O44: RES | P44: 69 | Q44: 47 | R44: 44 | S44: 99360 | T44: COM
N45: 99363 | O45: RES | P45: 1 | S45: 99360 | T45: RES
S46: 99361 | T46: RES | U46: 3
S47: 99362 | T47: COM | U47: 3 | V47: 2 | W47: 8
S48: 99362 | T48: RES | U48: 21 | V48: 14 | W48: 29
S49: 99363 | T49: RES

Sheet DEP_WKSHT
A1: Zip Code | B1: CLASS | C1: CountOfConcat Agreement Number | D1: MO | G1: Zip Code | H1: CLASS | I1: CountOfConcat Agreement Number | J1: YRMO | K1: Expr1 | Q1: Sum of CountOfConcat Agreement Number | S1: YRMO | X1: Zip Code | Y1: CLASS | Z1: CountOfConcat Agreement Number | AA1: SumOfAmount | AB1: YRMO | AD1: Sum of CountOfConcat Agreement Number | AF1: YRMO
A2: 98901 | B2: NDEP | C2: 78 | D2: 1 | E2: =VLOOKUP(A2,'6. Deposits 2024_Q1'!$A$3:$A$34,1,FALSE) -> #N/A | G2: 98901 | H2: NDEP | I2: 4 | J2: 202010 | K2: 0 | Q2: CLASS | R2: Zip Code | S2: 202010 | T2: 202011 | U2: 202012 | V2: 20209 | X2: 98901 | Y2: NDEP | Z2: 30 | AA2: 0 | AB2: 10 | AD2: CLASS | AE2: Zip Code | AF2: 10 | AG2: 11 | AH2: 12 | AI2: Grand Total
A3: 98902 | B3: NDEP | C3: 97 | D3: 1 | E3: =VLOOKUP(A3,'6. Deposits 2024_Q1'!$A$3:$A$34,1,FALSE) -> #N/A | G3: 98901 | H3: NDEP | I3: 9 | J3: 202011 | K3: 0 | Q3: NDEP | R3: 98901 | S3: 4 | T3: 9 | U3: 2 | V3: 6 | X3: 98901 | Y3: NDEP | Z3: 16 | AA3: 0 | AB3: 11 | AD3: NDEP | AE3: 98901 | AF3: 30 | AG3: 16 | AH3: 20 | AI3: 66
A4: 98903 | B4: NDEP | C4: 47 | D4: 1 | E4: =VLOOKUP(A4,'6. Deposits 2024_Q1'!$A$3:$A$34,1,FALSE) -> #N/A | G4: 98901 | H4: NDEP | I4: 2 | J4: 202012 | K4: 0 | Q4: NDEP | R4: 98902 | S4: 8 | T4: 2 | U4: 2 | V4: 5 | X4: 98901 | Y4: NDEP | Z4: 20 | AA4: 0 | AB4: 12 | AD4: NDEP | AE4: 98902 | AF4: 24 | AG4: 22 | AH4: 32 | AI4: 78
A5: 98908 | B5: NDEP | C5: 35 | D5: 1 | E5: =VLOOKUP(A5,'6. Deposits 2024_Q1'!$A$3:$A$34,1,FALSE) -> #N/A | G5: 98901 | H5: NDEP | I5: 6 | J5: 20209 | K5: 0 | Q5: NDEP | R5: 98903 | S5: 2 | T5: 2 | V5: 4 | X5: 98901 | Y5: RDEP | Z5: 344 | AA5: 0 | AB5: 10 | AD5: NDEP | AE5: 98903 | AF5: 12 | AG5: 6 | AH5: 8 | AI5: 26
A6: 98920 | B6: NDEP | C6: 2 | D6: 1 | E6: =VLOOKUP(A6,'6. Deposits 2024_Q1'!$A$3:$A$34,1,FALSE) -> #N/A | G6: 98901 | H6: RDEP | I6: 99 | J6: 202010 | K6: 0 | Q6: NDEP | R6: 98908 | T6: 5 | X6: 98901 | Y6: RDEP | Z6: 358 | AA6: 0 | AB6: 11 | AD6: NDEP | AE6: 98908 | AF6: 8 | AG6: 18 | AH6: 12 | AI6: 38
A7: 98921 | B7: NDEP | C7: 2 | D7: 1 | E7: =VLOOKUP(A7,'6. Deposits 2024_Q1'!$A$3:$A$34,1,FALSE) -> #N/A | G7: 98901 | H7: RDEP | I7: 70 | J7: 202011 | K7: 0 | Q7: NDEP | R7: 98930 | S7: 3 | X7: 98901 | Y7: RDEP | Z7: 398 | AA7: 0 | AB7: 12 | AD7: NDEP | AE7: 98920 | AH7: 2 | AI7: 2
A8: 98930 | B8: NDEP | C8: 24 | D8: 1 | E8: =VLOOKUP(A8,'6. Deposits 2024_Q1'!$A$3:$A$34,1,FALSE) -> #N/A | G8: 98901 | H8: RDEP | I8: 26 | J8: 202012 | K8: 0 | Q8: NDEP | R8: 98937 | T8: 3 | U8: 2 | X8: 98902 | Y8: NDEP | Z8: 24 | AA8: 0 | AB8: 10 | AD8: NDEP | AE8: 98930 | AF8: 8 | AG8: 8 | AH8: 4 | AI8: 20
A9: 98932 | B9: NDEP | C9: 7 | D9: 1 | E9: =VLOOKUP(A9,'6. Deposits 2024_Q1'!$A$3:$A$34,1,FALSE) -> #N/A | G9: 98901 | H9: RDEP | I9: 109 | J9: 20209 | K9: 0 | Q9: NDEP | R9: 98942 | S9: 2 | V9: 1 | X9: 98902 | Y9: NDEP | Z9: 22 | AA9: 0 | AB9: 11 | AD9: NDEP | AE9: 98932 | AF9: 2 | AI9: 2
A10: 98933 | B10: NDEP | C10: 3 | D10: 1 | E10: =VLOOKUP(A10,'6. Deposits 2024_Q1'!$A$3:$A$34,1,FALSE) -> #N/A | G10: 98902 | H10: NDEP | I10: 8 | J10: 202010 | K10: 0 | Q10: NDEP | R10: 98944 | S10: 17 | U10: 6 | V10: 2 | X10: 98902 | Y10: NDEP | Z10: 32 | AA10: 0 | AB10: 12 | AD10: NDEP | AE10: 98933 | AF10: 2 | AG10: 4 | AH10: 2 | AI10: 8
A11: 98935 | B11: NDEP | C11: 4 | D11: 1 | E11: =VLOOKUP(A11,'6. Deposits 2024_Q1'!$A$3:$A$34,1,FALSE) -> #N/A | G11: 98902 | H11: NDEP | I11: 2 | J11: 202011 | K11: 0 | Q11: NDEP | R11: 98948 | S11: 2 | X11: 98902 | Y11: RDEP | Z11: 502 | AA11: 0 | AB11: 10 | AD11: NDEP | AE11: 98935 | AF11: 4 | AI11: 4
A12: 98936 | B12: NDEP | C12: 21 | D12: 1 | E12: =VLOOKUP(A12,'6. Deposits 2024_Q1'!$A$3:$A$34,1,FALSE) -> #N/A | G12: 98902 | H12: NDEP | I12: 2 | J12: 202012 | K12: 0 | Q12: NDEP | R12: 98951 | S12: 2 | T12: 2 | U12: 2 | X12: 98902 | Y12: RDEP | Z12: 510 | AA12: 0 | AB12: 11 | AD12: NDEP | AE12: 98936 | AF12: 4 | AG12: 2 | AH12: 24 | AI12: 30
A13: 98937 | B13: NDEP | C13: 10 | D13: 1 | E13: =VLOOKUP(A13,'6. Deposits 2024_Q1'!$A$3:$A$34,1,FALSE) -> #N/A | G13: 98902 | H13: NDEP | I13: 5 | J13: 20209 | K13: 0 | Q13: NDEP | R13: 99324 | T13: 2 | X13: 98902 | Y13: RDEP | Z13: 784 | AA13: 0 | AB13: 12 | AD13: NDEP | AE13: 98937 | AG13: 6 | AH13: 2 | AI13: 8
A14: 98938 | B14: NDEP | C14: 1 | D14: 1 | E14: =VLOOKUP(A14,'6. Deposits 2024_Q1'!$A$3:$A$34,1,FALSE) -> #N/A | G14: 98902 | H14: RDEP | I14: 163 | J14: 202010 | K14: 0 | Q14: NDEP | R14: 99328 | V14: 1 | X14: 98903 | Y14: NDEP | Z14: 12 | AA14: 0 | AB14: 10 | AD14: NDEP | AE14: 98942 | AF14: 8 | AG14: 14 | AH14: 4 | AI14: 26
A15: 98942 | B15: NDEP | C15: 18 | D15: 1 | E15: =VLOOKUP(A15,'6. Deposits 2024_Q1'!$A$3:$A$34,1,FALSE) -> #N/A | G15: 98902 | H15: RDEP | I15: 98 | J15: 202011 | K15: 0 | Q15: NDEP | R15: 99347 | S15: 2 | T15: 2 | X15: 98903 | Y15: NDEP | Z15: 6 | AA15: 0 | AB15: 11 | AD15: NDEP | AE15: 98944 | AF15: 12 | AG15: 26 | AH15: 18 | AI15: 56
A16: 98944 | B16: NDEP | C16: 61 | D16: 1 | E16: =VLOOKUP(A16,'6. Deposits 2024_Q1'!$A$3:$A$34,1,FALSE) -> #N/A | G16: 98902 | H16: RDEP | I16: 53 | J16: 202012 | K16: 0 | Q16: NDEP | R16: 99360 | T16: 2 | X16: 98903 | Y16: NDEP | Z16: 8 | AA16: 0 | AB16: 12 | AD16: NDEP | AE16: 98948 | AF16: 6 | AG16: 2 | AH16: 10 | AI16: 18
A17: 98947 | B17: NDEP | C17: 1 | D17: 1 | E17: =VLOOKUP(A17,'6. Deposits 2024_Q1'!$A$3:$A$34,1,FALSE) -> #N/A | G17: 98902 | H17: RDEP | I17: 127 | J17: 20209 | K17: 0 | Q17: NDEP | R17: 99361 | S17: 2 | V17: 1 | X17: 98903 | Y17: RDEP | Z17: 130 | AA17: 0 | AB17: 10 | AD17: NDEP | AE17: 98951 | AF17: 2 | AG17: 4 | AH17: 16 | AI17: 22
A18: 98948 | B18: NDEP | C18: 29 | D18: 1 | E18: =VLOOKUP(A18,'6. Deposits 2024_Q1'!$A$3:$A$34,1,FALSE) -> #N/A | G18: 98903 | H18: NDEP | I18: 2 | J18: 202010 | K18: 0 | Q18: NDEP | R18: 99362 | S18: 4 | T18: 8 | U18: 3 | V18: 8 | X18: 98903 | Y18: RDEP | Z18: 84 | AA18: 0 | AB18: 11 | AD18: NDEP | AE18: 98952 | AH18: 4 | AI18: 4
A19: 98951 | B19: NDEP | C19: 36 | D19: 1 | E19: =VLOOKUP(A19,'6. Deposits 2024_Q1'!$A$3:$A$34,1,FALSE) -> #N/A | G19: 98903 | H19: NDEP | I19: 2 | J19: 202011 | K19: 0 | Q19: NDEP | R19: 99363 | S19: 1 | X19: 98903 | Y19: RDEP | Z19: 130 | AA19: 0 | AB19: 12 | AD19: NDEP | AE19: 98953 | AF19: 2 | AG19: 2 | AH19: 4 | AI19: 8
A20: 98952 | B20: NDEP | C20: 1 | D20: 1 | E20: =VLOOKUP(A20,'6. Deposits 2024_Q1'!$A$3:$A$34,1,FALSE) -> #N/A | G20: 98903 | H20: NDEP | I20: 4 | J20: 20209 | K20: 0 | Q20: RDEP | R20: 98901 | S20: 99 | T20: 70 | U20: 26 | V20: 109 | X20: 98908 | Y20: NDEP | Z20: 8 | AA20: 0 | AB20: 10 | AD20: NDEP | AE20: 99323 | AH20: 2 | AI20: 2
A21: 98953 | B21: NDEP | C21: 10 | D21: 1 | E21: =VLOOKUP(A21,'6. Deposits 2024_Q1'!$A$3:$A$34,1,FALSE) -> #N/A | G21: 98903 | H21: RDEP | I21: 27 | J21: 202010 | K21: 0 | Q21: RDEP | R21: 98902 | S21: 163 | T21: 98 | U21: 53 | V21: 127 | X21: 98908 | Y21: NDEP | Z21: 18 | AA21: 0 | AB21: 11 | AD21: NDEP | AE21: 99324 | AG21: 4 | AH21: 2 | AI21: 6
A22: 99323 | B22: NDEP | C22: 1 | D22: 1 | E22: =VLOOKUP(A22,'6. Deposits 2024_Q1'!$A$3:$A$34,1,FALSE) -> #N/A | G22: 98903 | H22: RDEP | I22: 5 | J22: 202011 | K22: 0 | Q22: RDEP | R22: 98903 | S22: 27 | T22: 5 | U22: 12 | V22: 26 | X22: 98908 | Y22: NDEP | Z22: 12 | AA22: 0 | AB22: 12 | AD22: NDEP | AE22: 99328 | AF22: 2 | AH22: 2 | AI22: 4
A23: 99324 | B23: NDEP | C23: 4 | D23: 1 | E23: =VLOOKUP(A23,'6. Deposits 2024_Q1'!$A$3:$A$34,1,FALSE) -> #N/A | G23: 98903 | H23: RDEP | I23: 12 | J23: 202012 | K23: 0 | Q23: RDEP | R23: 98908 | S23: 136 | T23: 107 | U23: 32 | V23: 123 | X23: 98908 | Y23: RDEP | Z23: 320 | AA23: 0 | AB23: 10 | AD23: NDEP | AE23: 99347 | AG23: 4 | AI23: 4
A24: 99328 | B24: NDEP | C24: 5 | D24: 1 | E24: =VLOOKUP(A24,'6. Deposits 2024_Q1'!$A$3:$A$34,1,FALSE) -> #N/A | G24: 98903 | H24: RDEP | I24: 26 | J24: 20209 | K24: 0 | Q24: RDEP | R24: 98921 | S24: 7 | T24: 4 | V24: 4 | X24: 98908 | Y24: RDEP | Z24: 450 | AA24: 0 | AB24: 11 | AD24: NDEP | AE24: 99360 | AG24: 4 | AH24: 2 | AI24: 6
A25: 99329 | B25: NDEP | C25: 1 | D25: 1 | E25: =VLOOKUP(A25,'6. Deposits 2024_Q1'!$A$3:$A$34,1,FALSE) -> #N/A | G25: 98908 | H25: NDEP | I25: 5 | J25: 202011 | K25: 0 | Q25: RDEP | R25: 98923 | S25: 3 | T25: 2 | U25: 1 | V25: 2 | X25: 98908 | Y25: RDEP | Z25: 350 | AA25: 0 | AB25: 12 | AD25: NDEP | AE25: 99361 | AH25: 6 | AI25: 6
A26: 99347 | B26: NDEP | C26: 3 | D26: 1 | E26: =VLOOKUP(A26,'6. Deposits 2024_Q1'!$A$3:$A$34,1,FALSE) -> #N/A | G26: 98908 | H26: RDEP | I26: 136 | J26: 202010 | K26: 0 | Q26: RDEP | R26: 98930 | S26: 29 | T26: 10 | U26: 18 | V26: 15 | X26: 98920 | Y26: NDEP | Z26: 2 | AA26: 0 | AB26: 12 | AD26: NDEP | AE26: 99362 | AF26: 18 | AG26: 20 | AH26: 16 | AI26: 54
A27: 99360 | B27: NDEP | C27: 3 | D27: 1 | E27: =VLOOKUP(A27,'6. Deposits 2024_Q1'!$A$3:$A$34,1,FALSE) -> #N/A | G27: 98908 | H27: RDEP | I27: 107 | J27: 202011 | K27: 0 | Q27: RDEP | R27: 98932 | S27: 7 | T27: 17 | U27: 8 | V27: 7 | X27: 98921 | Y27: RDEP | Z27: 6 | AA27: 0 | AB27: 10 | AD27: RDEP | AE27: 98901 | AF27: 344 | AG27: 358 | AH27: 398 | AI27: 1100
A28: 99361 | B28: NDEP | C28: 6 | D28: 1 | E28: =VLOOKUP(A28,'6. Deposits 2024_Q1'!$A$3:$A$34,1,FALSE) -> #N/A | G28: 98908 | H28: RDEP | I28: 32 | J28: 202012 | K28: 0 | Q28: RDEP | R28: 98933 | S28: 3 | T28: 3 | U28: 3 | V28: 1 | X28: 98921 | Y28: RDEP | Z28: 18 | AA28: 0 | AB28: 11 | AD28: RDEP | AE28: 98902 | AF28: 502 | AG28: 510 | AH28: 784 | AI28: 1796
A29: 99362 | B29: NDEP | C29: 62 | D29: 1 | E29: =VLOOKUP(A29,'6. Deposits 2024_Q1'!$A$3:$A$34,1,FALSE) -> #N/A | G29: 98908 | H29: RDEP | I29: 123 | J29: 20209 | K29: 0 | Q29: RDEP | R29: 98935 | S29: 5 | T29: 6 | U29: 2 | V29: 4 | X29: 98921 | Y29: RDEP | Z29: 14 | AA29: 0 | AB29: 12 | AD29: RDEP | AE29: 98903 | AF29: 130 | AG29: 84 | AH29: 130 | AI29: 344
A30: 99363 | B30: NDEP | C30: 1 | D30: 1 | E30: =VLOOKUP(A30,'6. Deposits 2024_Q1'!$A$3:$A$34,1,FALSE) -> #N/A | G30: 98921 | H30: RDEP | I30: 7 | J30: 202010 | K30: 0 | Q30: RDEP | R30: 98936 | S30: 6 | T30: 10 | U30: 6 | V30: 5 | X30: 98923 | Y30: RDEP | Z30: 4 | AA30: 0 | AB30: 10 | AD30: RDEP | AE30: 98908 | AF30: 320 | AG30: 450 | AH30: 350 | AI30: 1120
A31: 98901 | B31: RDEP | C31: 1427 | D31: 1 | E31: =VLOOKUP(A31,'6. Deposits 2024_Q1'!$A$35:$A$61,1,FALSE) -> #N/A | G31: 98921 | H31: RDEP | I31: 4 | J31: 202011 | K31: 0 | Q31: RDEP | R31: 98937 | S31: 9 | T31: 2 | U31: 3 | V31: 7 | X31: 98923 | Y31: RDEP | Z31: 4 | AA31: 0 | AB31: 11 | AD31: RDEP | AE31: 98921 | AF31: 6 | AG31: 18 | AH31: 14 | AI31: 38
A32: 98902 | B32: RDEP | C32: 1838 | D32: 1 | E32: =VLOOKUP(A32,'6. Deposits 2024_Q1'!$A$35:$A$61,1,FALSE) -> #N/A | G32: 98921 | H32: RDEP | I32: 4 | J32: 20209 | K32: 0 | Q32: RDEP | R32: 98938 | S32: 1 | U32: 4 | X32: 98923 | Y32: RDEP | Z32: 16 | AA32: 0 | AB32: 12 | AD32: RDEP | AE32: 98923 | AF32: 4 | AG32: 4 | AH32: 16 | AI32: 24
A33: 98903 | B33: RDEP | C33: 403 | D33: 1 | E33: =VLOOKUP(A33,'6. Deposits 2024_Q1'!$A$35:$A$61,1,FALSE) -> #N/A | G33: 98923 | H33: RDEP | I33: 3 | J33: 202010 | K33: 0 | Q33: RDEP | R33: 98939 | U33: 1 | X33: 98930 | Y33: NDEP | Z33: 8 | AA33: 0 | AB33: 10 | AD33: RDEP | AE33: 98930 | AF33: 90 | AG33: 74 | AH33: 120 | AI33: 284
A34: 98908 | B34: RDEP | C34: 1026 | D34: 1 | E34: =VLOOKUP(A34,'6. Deposits 2024_Q1'!$A$35:$A$61,1,FALSE) -> #N/A | G34: 98923 | H34: RDEP | I34: 2 | J34: 202011 | K34: 0 | Q34: RDEP | R34: 98942 | S34: 42 | T34: 27 | U34: 12 | V34: 36 | X34: 98930 | Y34: NDEP | Z34: 8 | AA34: 0 | AB34: 11 | AD34: RDEP | AE34: 98932 | AF34: 30 | AG34: 72 | AH34: 62 | AI34: 164
A35: 98921 | B35: RDEP | C35: 31 | D35: 1 | E35: =VLOOKUP(A35,'6. Deposits 2024_Q1'!$A$35:$A$61,1,FALSE) -> #N/A | G35: 98923 | H35: RDEP | I35: 1 | J35: 202012 | K35: 0 | Q35: RDEP | R35: 98944 | S35: 23 | T35: 30 | U35: 15 | V35: 31 | X35: 98930 | Y35: NDEP | Z35: 4 | AA35: 0 | AB35: 12 | AD35: RDEP | AE35: 98933 | AF35: 4 | AG35: 4 | AH35: 14 | AI35: 22
A36: 98923 | B36: RDEP | C36: 30 | D36: 1 | E36: =VLOOKUP(A36,'6. Deposits 2024_Q1'!$A$35:$A$61,1,FALSE) -> #N/A | G36: 98923 | H36: RDEP | I36: 2 | J36: 20209 | K36: 0 | Q36: RDEP | R36: 98947 | S36: 4 | T36: 2 | U36: 3 | V36: 1 | X36: 98930 | Y36: RDEP | Z36: 90 | AA36: 0 | AB36: 10 | AD36: RDEP | AE36: 98935 | AF36: 30 | AG36: 16 | AH36: 36 | AI36: 82
A37: 98930 | B37: RDEP | C37: 336 | D37: 1 | E37: =VLOOKUP(A37,'6. Deposits 2024_Q1'!$A$35:$A$61,1,FALSE) -> #N/A | G37: 98930 | H37: NDEP | I37: 3 | J37: 202010 | K37: 0 | Q37: RDEP | R37: 98948 | S37: 24 | T37: 4 | U37: 4 | V37: 10 | X37: 98930 | Y37: RDEP | Z37: 74 | AA37: 0 | AB37: 11 | AD37: RDEP | AE37: 98936 | AF37: 38 | AG37: 26 | AH37: 80 | AI37: 144
A38: 98932 | B38: RDEP | C38: 165 | D38: 1 | E38: =VLOOKUP(A38,'6. Deposits 2024_Q1'!$A$35:$A$61,1,FALSE) -> #N/A | G38: 98930 | H38: RDEP | I38: 29 | J38: 202010 | K38: 0 | Q38: RDEP | R38: 98951 | S38: 16 | T38: 12 | U38: 8 | V38: 10 | X38: 98930 | Y38: RDEP | Z38: 120 | AA38: 0 | AB38: 12 | AD38: RDEP | AE38: 98937 | AF38: 20 | AG38: 30 | AH38: 38 | AI38: 88
A39: 98933 | B39: RDEP | C39: 24 | D39: 1 | E39: =VLOOKUP(A39,'6. Deposits 2024_Q1'!$A$35:$A$61,1,FALSE) -> #N/A | G39: 98930 | H39: RDEP | I39: 10 | J39: 202011 | K39: 0 | Q39: RDEP | R39: 98952 | S39: 1 | U39: 1 | X39: 98932 | Y39: NDEP | Z39: 2 | AA39: 0 | AB39: 10 | AD39: RDEP | AE39: 98938 | AF39: 24 | AG39: 14 | AH39: 40 | AI39: 78
A40: 98935 | B40: RDEP | C40: 85 | D40: 1 | E40: =VLOOKUP(A40,'6. Deposits 2024_Q1'!$A$35:$A$61,1,FALSE) -> #N/A | G40: 98930 | H40: RDEP | I40: 18 | J40: 202012 | K40: 0 | Q40: RDEP | R40: 98953 | S40: 7 | T40: 9 | V40: 10 | X40: 98932 | Y40: RDEP | Z40: 30 | AA40: 0 | AB40: 10 | AD40: RDEP | AE40: 98939 | AF40: 4 | AG40: 4 | AH40: 2 | AI40: 10
A41: 98936 | B41: RDEP | C41: 130 | D41: 1 | E41: =VLOOKUP(A41,'6. Deposits 2024_Q1'!$A$35:$A$61,1,FALSE) -> #N/A | G41: 98930 | H41: RDEP | I41: 15 | J41: 20209 | K41: 0 | Q41: RDEP | R41: 99323 | U41: 2 | V41: 2 | X41: 98932 | Y41: RDEP | Z41: 72 | AA41: 0 | AB41: 11 | AD41: RDEP | AE41: 98942 | AF41: 114 | AG41: 190 | AH41: 106 | AI41: 410
A42: 98937 | B42: RDEP | C42: 85 | D42: 1 | E42: =VLOOKUP(A42,'6. Deposits 2024_Q1'!$A$35:$A$61,1,FALSE) -> #N/A | G42: 98932 | H42: RDEP | I42: 7 | J42: 202010 | K42: 0 | Q42: RDEP | R42: 99324 | S42: 29 | T42: 17 | U42: 4 | V42: 67 | X42: 98932 | Y42: RDEP | Z42: 62 | AA42: 0 | AB42: 12 | AD42: RDEP | AE42: 98944 | AF42: 100 | AG42: 182 | AH42: 230 | AI42: 512
A43: 98938 | B43: RDEP | C43: 51 | D43: 1 | E43: =VLOOKUP(A43,'6. Deposits 2024_Q1'!$A$35:$A$61,1,FALSE) -> #N/A | G43: 98932 | H43: RDEP | I43: 17 | J43: 202011 | K43: 0 | Q43: RDEP | R43: 99328 | S43: 11 | T43: 6 | U43: 7 | V43: 8 | X43: 98933 | Y43: NDEP | Z43: 2 | AA43: 0 | AB43: 10 | AD43: RDEP | AE43: 98947 | AF43: 22 | AG43: 26 | AH43: 28 | AI43: 76
A44: 98939 | B44: RDEP | C44: 8 | D44: 1 | E44: =VLOOKUP(A44,'6. Deposits 2024_Q1'!$A$35:$A$61,1,FALSE) -> #N/A | G44: 98932 | H44: RDEP | I44: 8 | J44: 202012 | K44: 0 | Q44: RDEP | R44: 99329 | U44: 1 | X44: 98933 | Y44: NDEP | Z44: 4 | AA44: 0 | AB44: 11 | AD44: RDEP | AE44: 98948 | AF44: 60 | AG44: 84 | AH44: 162 | AI44: 306
A45: 98942 | B45: RDEP | C45: 446 | D45: 1 | E45: =VLOOKUP(A45,'6. Deposits 2024_Q1'!$A$35:$A$61,1,FALSE) -> #N/A | G45: 98932 | H45: RDEP | I45: 7 | J45: 20209 | K45: 0 | Q45: RDEP | R45: 99347 | S45: 4 | V45: 6 | X45: 98933 | Y45: NDEP | Z45: 2 | AA45: 0 | AB45: 12 | AD45: RDEP | AE45: 98951 | AF45: 86 | AG45: 82 | AH45: 154 | AI45: 322
A46: 98944 | B46: RDEP | C46: 535 | D46: 1 | E46: =VLOOKUP(A46,'6. Deposits 2024_Q1'!$A$35:$A$61,1,FALSE) -> #N/A | G46: 98933 | H46: RDEP | I46: 3 | J46: 202010 | K46: 0 | Q46: RDEP | R46: 99348 | S46: 2 | V46: 1 | X46: 98933 | Y46: RDEP | Z46: 4 | AA46: 0 | AB46: 10 | AD46: RDEP | AE46: 98952 | AF46: 6 | AG46: 2 | AH46: 22 | AI46: 30
A47: 98947 | B47: RDEP | C47: 69 | D47: 1 | E47: =VLOOKUP(A47,'6. Deposits 2024_Q1'!$A$35:$A$61,1,FALSE) -> #N/A | G47: 98933 | H47: RDEP | I47: 3 | J47: 202011 | K47: 0 | Q47: RDEP | R47: 99360 | T47: 2 | X47: 98933 | Y47: RDEP | Z47: 4 | AA47: 0 | AB47: 11 | AD47: RDEP | AE47: 98953 | AF47: 62 | AG47: 58 | AH47: 62 | AI47: 182
A48: 98948 | B48: RDEP | C48: 308 | D48: 1 | E48: =VLOOKUP(A48,'6. Deposits 2024_Q1'!$A$35:$A$61,1,FALSE) -> #N/A | G48: 98933 | H48: RDEP | I48: 3 | J48: 202012 | K48: 0 | Q48: RDEP | R48: 99361 | S48: 3 | U48: 2 | V48: 1 | X48: 98933 | Y48: RDEP | Z48: 14 | AA48: 0 | AB48: 12 | AD48: RDEP | AE48: 99323 | AF48: 6 | AG48: 18 | AH48: 6 | AI48: 30
A49: 98951 | B49: RDEP | C49: 351 | D49: 1 | E49: =VLOOKUP(A49,'6. Deposits 2024_Q1'!$A$35:$A$61,1,FALSE) -> #N/A | G49: 98933 | H49: RDEP | I49: 1 | J49: 20209 | K49: 0 | Q49: RDEP | R49: 99362 | S49: 85 | T49: 56 | U49: 23 | V49: 112 | X49: 98935 | Y49: NDEP | Z49: 4 | AA49: 0 | AB49: 10 | AD49: RDEP | AE49: 99324 | AF49: 64 | AG49: 102 | AH49: 64 | AI49: 230
A50: 98952 | B50: RDEP | C50: 33 | D50: 1 | E50: =VLOOKUP(A50,'6. Deposits 2024_Q1'!$A$35:$A$61,1,FALSE) -> #N/A | G50: 98935 | H50: RDEP | I50: 5 | J50: 202010 | K50: 0 | Q50: Grand Total | S50: 795 | T50: 536 | U50: 268 | V50: 753 | X50: 98935 | Y50: RDEP | Z50: 30 | AA50: 0 | AB50: 10 | AD50: RDEP | AE50: 99328 | AF50: 20 | AG50: 36 | AH50: 34 | AI50: 90
A51: 98953 | B51: RDEP | C51: 127 | D51: 1 | E51: =VLOOKUP(A51,'6. Deposits 2024_Q1'!$A$35:$A$61,1,FALSE) -> #N/A | G51: 98935 | H51: RDEP | I51: 6 | J51: 202011 | K51: 0 | X51: 98935 | Y51: RDEP | Z51: 16 | AA51: 0 | AB51: 11 | AD51: RDEP | AE51: 99329 | AF51: 2 | AH51: 2 | AI51: 4
A52: 99323 | B52: RDEP | C52: 26 | D52: 1 | E52: =VLOOKUP(A52,'6. Deposits 2024_Q1'!$A$35:$A$61,1,FALSE) -> #N/A | G52: 98935 | H52: RDEP | I52: 2 | J52: 202012 | K52: 0 | X52: 98935 | Y52: RDEP | Z52: 36 | AA52: 0 | AB52: 12 | AD52: RDEP | AE52: 99347 | AF52: 6 | AG52: 10 | AH52: 6 | AI52: 22
A53: 99324 | B53: RDEP | C53: 336 | D53: 1 | E53: =VLOOKUP(A53,'6. Deposits 2024_Q1'!$A$35:$A$61,1,FALSE) -> #N/A | G53: 98935 | H53: RDEP | I53: 4 | J53: 20209 | K53: 0 | X53: 98936 | Y53: NDEP | Z53: 4 | AA53: 0 | AB53: 10 | AD53: RDEP | AE53: 99348 | AG53: 4 | AH53: 2 | AI53: 6
A54: 99328 | B54: RDEP | C54: 97 | D54: 1 | E54: =VLOOKUP(A54,'6. Deposits 2024_Q1'!$A$35:$A$61,1,FALSE) -> #N/A | G54: 98936 | H54: RDEP | I54: 6 | J54: 202010 | K54: 0 | X54: 98936 | Y54: NDEP | Z54: 2 | AA54: 0 | AB54: 11 | AD54: RDEP | AE54: 99360 | AF54: 2 | AG54: 2 | AH54: 6 | AI54: 10
A55: 99329 | B55: RDEP | C55: 2 | D55: 1 | E55: =VLOOKUP(A55,'6. Deposits 2024_Q1'!$A$35:$A$61,1,FALSE) -> #N/A | G55: 98936 | H55: RDEP | I55: 10 | J55: 202011 | K55: 0 | X55: 98936 | Y55: NDEP | Z55: 24 | AA55: 0 | AB55: 12 | AD55: RDEP | AE55: 99361 | AF55: 6 | AH55: 24 | AI55: 30
A56: 99347 | B56: RDEP | C56: 45 | D56: 1 | E56: =VLOOKUP(A56,'6. Deposits 2024_Q1'!$A$35:$A$61,1,FALSE) -> #N/A | G56: 98936 | H56: RDEP | I56: 6 | J56: 202012 | K56: 0 | X56: 98936 | Y56: RDEP | Z56: 38 | AA56: 0 | AB56: 10 | AD56: RDEP | AE56: 99362 | AF56: 394 | AG56: 308 | AH56: 342 | AI56: 1044
A57: 99348 | B57: RDEP | C57: 12 | D57: 1 | E57: =VLOOKUP(A57,'6. Deposits 2024_Q1'!$A$35:$A$61,1,FALSE) -> #N/A | G57: 98936 | H57: RDEP | I57: 5 | J57: 20209 | K57: 0 | X57: 98936 | Y57: RDEP | Z57: 26 | AA57: 0 | AB57: 11 | AD57: RDEP | AE57: 99363 | AF57: 4 | AH57: 2 | AI57: 6
A58: 99350 | B58: RDEP | C58: 3 | D58: 1 | E58: =VLOOKUP(A58,'6. Deposits 2024_Q1'!$A$35:$A$61,1,FALSE) -> #N/A | G58: 98937 | H58: NDEP | I58: 3 | J58: 202011 | K58: 0 | X58: 98936 | Y58: RDEP | Z58: 80 | AA58: 0 | AB58: 12 | AD58: Grand Total | AF58: 2644 | AG58: 2930 | AH58: 3528 | AI58: 9102
A59: 99360 | B59: RDEP | C59: 11 | D59: 1 | E59: =VLOOKUP(A59,'6. Deposits 2024_Q1'!$A$35:$A$61,1,FALSE) -> #N/A | G59: 98937 | H59: NDEP | I59: 2 | J59: 202012 | K59: 0 | X59: 98937 | Y59: NDEP | Z59: 6 | AA59: 0 | AB59: 11
A60: 99361 | B60: RDEP | C60: 31 | D60: 1 | E60: =VLOOKUP(A60,'6. Deposits 2024_Q1'!$A$35:$A$61,1,FALSE) -> #N/A | G60: 98937 | H60: RDEP | I60: 9 | J60: 202010 | K60: 0 | X60: 98937 | Y60: NDEP | Z60: 2 | AA60: 0 | AB60: 12
A61: 99362 | B61: RDEP | C61: 1179 | D61: 1 | E61: =VLOOKUP(A61,'6. Deposits 2024_Q1'!$A$35:$A$61,1,FALSE) -> #N/A | G61: 98937 | H61: RDEP | I61: 2 | J61: 202011 | K61: 0 | X61: 98937 | Y61: RDEP | Z61: 20 | AA61: 0 | AB61: 10
A62: 99363 | B62: RDEP | C62: 3 | D62: 1 | E62: =VLOOKUP(A62,'6. Deposits 2024_Q1'!$A$35:$A$61,1,FALSE) -> #N/A | G62: 98937 | H62: RDEP | I62: 3 | J62: 202012 | K62: 0 | X62: 98937 | Y62: RDEP | Z62: 30 | AA62: 0 | AB62: 11
G63: 98937 | H63: RDEP | I63: 7 | J63: 20209 | K63: 0 | X63: 98937 | Y63: RDEP | Z63: 38 | AA63: 0 | AB63: 12
G64: 98938 | H64: RDEP | I64: 1 | J64: 202010 | K64: 0 | X64: 98938 | Y64: RDEP | Z64: 24 | AA64: 0 | AB64: 10
G65: 98938 | H65: RDEP | I65: 4 | J65: 202012 | K65: 0 | X65: 98938 | Y65: RDEP | Z65: 14 | AA65: 0 | AB65: 11
G66: 98939 | H66: RDEP | I66: 1 | J66: 202012 | K66: 0 | X66: 98938 | Y66: RDEP | Z66: 40 | AA66: 0 | AB66: 12
G67: 98942 | H67: NDEP | I67: 2 | J67: 202010 | K67: 0 | X67: 98939 | Y67: RDEP | Z67: 4 | AA67: 0 | AB67: 10
G68: 98942 | H68: NDEP | I68: 1 | J68: 20209 | K68: 0 | X68: 98939 | Y68: RDEP | Z68: 4 | AA68: 0 | AB68: 11
G69: 98942 | H69: RDEP | I69: 42 | J69: 202010 | K69: 0 | X69: 98939 | Y69: RDEP | Z69: 2 | AA69: 0 | AB69: 12
G70: 98942 | H70: RDEP | I70: 27 | J70: 202011 | K70: 0 | X70: 98942 | Y70: NDEP | Z70: 8 | AA70: 0 | AB70: 10
G71: 98942 | H71: RDEP | I71: 12 | J71: 202012 | K71: 0 | X71: 98942 | Y71: NDEP | Z71: 14 | AA71: 0 | AB71: 11
G72: 98942 | H72: RDEP | I72: 36 | J72: 20209 | K72: 0 | X72: 98942 | Y72: NDEP | Z72: 4 | AA72: 0 | AB72: 12
G73: 98944 | H73: NDEP | I73: 17 | J73: 202010 | K73: 0 | X73: 98942 | Y73: RDEP | Z73: 114 | AA73: 0 | AB73: 10
G74: 98944 | H74: NDEP | I74: 6 | J74: 202012 | K74: 0 | X74: 98942 | Y74: RDEP | Z74: 190 | AA74: 0 | AB74: 11
... G135: 99363 | H135: NDEP | I135: 1 | J135: 202010 | K135: 0 | X135: 99361 | Y135: RDEP | Z135: 6 | AA135: 0 | AB135: 10
X136: 99361 | Y136: RDEP | Z136: 24 | AA136: 0 | AB136: 12
X137: 99362 | Y137: NDEP | Z137: 18 | AA137: 0 | AB137: 10
X138: 99362 | Y138: NDEP | Z138: 20 | AA138: 0 | AB138: 11
X139: 99362 | Y139: NDEP | Z139: 16 | AA139: 0 | AB139: 12
X140: 99362 | Y140: RDEP | Z140: 394 | AA140: 0 | AB140: 10
X141: 99362 | Y141: RDEP | Z141: 308 | AA141: 0 | AB141: 11
X142: 99362 | Y142: RDEP | Z142: 342 | AA142: 0 | AB142: 12
X143: 99363 | Y143: RDEP | Z143: 4 | AA143: 0 | AB143: 10
X144: 99363 | Y144: RDEP | Z144: 2 | AA144: 0 | AB144: 12

Sheet 7. Bill Assistance 2024_Q1
A1: Item a) Number of Premises Receiving Bill Assistance or Enrolled in Any Other Assistance Program
A2: 44197 | B2: 44228 | C2: 44256 | D2: ZIP ** | E2: 44287 | F2: 44317 | G2: 44348 | H2: 44378 | I2: 44409 | J2: 44440 | K2: 44470 | L2: 44501 | M2: 44531 | N2: Zip Code | O2: 45292 | P2: Zip Code | Q2: 45323 | R2: Zip Code | S2: 45352
N3: 98901 | O3: 1263 | P3: 98901 | Q3: 1258 | R3: 98901 | S3: 1225
N4: 98902 | O4: 1762 | P4: 98902 | Q4: 1747 | R4: 98902 | S4: 1680
N5: 98903 | O5: 570 | P5: 98903 | Q5: 567 | R5: 98903 | S5: 547
N6: 98908 | O6: 607 | P6: 98908 | Q6: 604 | R6: 98908 | S6: 559
N7: 98921 | O7: 60 | P7: 98921 | Q7: 59 | R7: 98921 | S7: 59
N8: 98923 | O8: 35 | P8: 98923 | Q8: 35 | R8: 98923 | S8: 36
N9: 98930 | O9: 453 | P9: 98930 | Q9: 453 | R9: 98930 | S9: 463
N10: 98932 | O10: 228 | P10: 98932 | Q10: 226 | R10: 98932 | S10: 230
N11: 98933 | O11: 20 | P11: 98933 | Q11: 20 | R11: 98933 | S11: 22
N12: 98935 | O12: 135 | P12: 98935 | Q12: 133 | R12: 98935 | S12: 141
N13: 98936 | O13: 109 | P13: 98936 | Q13: 106 | R13: 98936 | S13: 96
N14: 98937 | O14: 46 | P14: 98937 | Q14: 46 | R14: 98937 | S14: 51
... N34: 99363 | O34: 3 | P34: 99363 | Q34: 4 | R34: 99363 | S34: 3
N35: TOTAL | O35: =SUM(O3:O34) -> 8701 | Q35: =SUM(Q3:Q34) -> 8655 | S35: =SUM(S3:S34) -> 8513

Sheet BA_WRKSHT
A1: FLAG | B1: SumOfJAN20 | C1: SumOfFEB20 | D1: SumOfMAR20 | E1: SumOfAPR20 | F1: SumOfMAY20 | G1: SumOfJUN20 | H1: SumOfJUL20 | I1: SumOfAUG20 | J1: SumOfSEP20 | K1: SumOfOCT20 | L1: SumOfNOV20 | M1: SumOfDEC20 | N1: SumOfJAN19 | O1: SumOfFEB19 | P1: SumOfMAR19 | Q1: SumOfAPR19 | R1: SumOfMAY19 | S1: SumOfJUN19 | T1: SumOfJUL19 | U1: SumOfAUG19 | V1: SumOfSEP19 | W1: SumOfOCT19 | X1: SumOfNOV19 | Y1: SumOfDEC19
A2: 98901RES | B2: 37 | C2: 35 | D2: 33 | E2: 31 | F2: 31 | G2: 31 | H2: 30 | I2: 27 | J2: 27 | K2: 27 | L2: 24 | M2: 24 | N2: 23 | O2: 28 | P2: 28 | Q2: 30 | R2: 32 | S2: 33 | T2: 33 | U2: 35 | V2: 36 | W2: 37 | X2: 38 | Y2: 39
A3: 98902RES | B3: 54 | C3: 51 | D3: 48 | E3: 46 | F3: 43 | G3: 41 | H3: 38 | I3: 34 | J3: 33 | K3: 29 | L3: 27 | M3: 24 | N3: 24 | O3: 31 | P3: 34 | Q3: 38 | R3: 39 | S3: 43 | T3: 45 | U3: 47 | V3: 48 | W3: 50 | X3: 51 | Y3: 53
A4: 98903RES | B4: 26 | C4: 26 | D4: 24 | E4: 24 | F4: 23 | G4: 21 | H4: 22 | I4: 23 | J4: 23 | K4: 22 | L4: 22 | M4: 21 | N4: 22 | O4: 23 | P4: 24 | Q4: 26 | R4: 26 | S4: 27 | T4: 26 | U4: 26 | V4: 25 | W4: 26 | X4: 26 | Y4: 26
A5: 98908RES | B5: 29 | C5: 29 | D5: 27 | E5: 27 | F5: 27 | G5: 26 | H5: 26 | I5: 25 | J5: 26 | K5: 26 | L5: 26 | M5: 23 | N5: 23 | O5: 26 | P5: 26 | Q5: 26 | R5: 25 | S5: 25 | T5: 25 | U5: 26 | V5: 27 | W5: 27 | X5: 26 | Y5: 28
A6: 98921RES | B6: 10 | C6: 10 | D6: 9 | E6: 9 | F6: 9 | G6: 10 | H6: 9 | I6: 9 | J6: 7 | K6: 7 | L6: 7 | M6: 7 | N6: 12 | O6: 13 | P6: 12 | Q6: 12 | R6: 12 | S6: 11 | T6: 11 | U6: 10 | V6: 10 | W6: 10 | X6: 10 | Y6: 10
A7: 98923RES | B7: 3 | C7: 4 | D7: 3 | E7: 4 | F7: 3 | G7: 3 | H7: 4 | I7: 3 | J7: 4 | K7: 3 | L7: 4 | M7: 4 | N7: 4 | O7: 4 | P7: 5 | Q7: 4 | R7: 4 | S7: 5 | T7: 4 | U7: 4 | V7: 5 | W7: 5 | X7: 4 | Y7: 4
A8: 98930RES | B8: 33 | C8: 32 | D8: 32 | E8: 32 | F8: 30 | G8: 29 | H8: 28 | I8: 28 | J8: 28 | K8: 24 | L8: 21 | M8: 20 | N8: 21 | O8: 22 | P8: 25 | Q8: 25 | R8: 26 | S8: 27 | T8: 28 | U8: 28 | V8: 32 | W8: 31 | X8: 32 | Y8: 32
A9: 98932RES | B9: 21 | C9: 20 | D9: 21 | E9: 22 | F9: 21 | G9: 18 | H9: 18 | I9: 18 | J9: 17 | K9: 16 | L9: 15 | M9: 14 | N9: 16 | O9: 17 | P9: 17 | Q9: 17 | R9: 17 | S9: 19 | T9: 19 | U9: 20 | V9: 19 | W9: 20 | X9: 21 | Y9: 21
A10: 98933RES | B10: 4 | C10: 4 | D10: 4 | E10: 4 | F10: 4 | G10: 4 | H10: 4 | I10: 3 | J10: 2 | K10: 2 | L10: 2 | M10: 3 | N10: 2 | O10: 3 | P10: 3 | Q10: 3 | R10: 2 | S10: 3 | T10: 1 | U10: 1 | V10: 1 | W10: 2 | X10: 3 | Y10: 3
A11: 98935RES | B11: 12 | C11: 12 | D11: 12 | E11: 12 | F11: 12 | G11: 11 | H11: 10 | I11: 10 | J11: 10 | K11: 10 | L11: 10 | M11: 8 | N11: 9 | O11: 10 | P11: 10 | Q11: 9 | R11: 10 | S11: 11 | T11: 11 | U11: 10 | V11: 10 | W11: 12 | X11: 12 | Y11: 12
A12: 98936RES | B12: 8 | C12: 8 | D12: 7 | E12: 8 | F12: 7 | G12: 8 | H12: 8 | I12: 8 | J12: 8 | K12: 10 | L12: 10 | M12: 9 | N12: 7 | O12: 7 | P12: 7 | Q12: 7 | R12: 6 | S12: 6 | T12: 6 | U12: 5 | V12: 5 | W12: 7 | X12: 6 | Y12: 8
A13: 98937RES | B13: 9 | C13: 10 | D13: 9 | E13: 9 | F13: 8 | G13: 10 | H13: 10 | I13: 9 | J13: 10 | K13: 9 | L13: 9 | M13: 9 | N13: 7 | O13: 7 | P13: 7 | Q13: 7 | R13: 8 | S13: 8 | T13: 7 | U13: 7 | V13: 7 | W13: 9 | X13: 8 | Y13: 9
... A33: 99363RES | B33: 3 | C33: 2 | D33: 2 | E33: 2 | F33: 2 | G33: 2 | H33: 2 | I33: 1 | J33: 2 | K33: 1 | L33: 1 | M33: 1 | N33: 2 | O33: 2 | P33: 2 | Q33: 3 | R33: 2 | S33: 2 | T33: 2 | U33: 2 | V33: 2 | W33: 2 | X33: 2 | Y33: 3

Sheet 8.ARREARS NEW 2024_Q1
A1: Item a) Number of Customers by Customer Class With Past-due balances (arrearages) | R1: Item c) Amount of Past-due Balances for Known Low-income Households and Number of Days Past-due | AR1: Section D. Bad Debt | AW1: Item e) The Amount of Past-due Balances Written-off and Classified as Bad Debt, if different than item d | BJ1: Item f) Number of Customer Accounts Referred to Collection Agencies | BS1: Item f) Total Amount of Bad Debt Referred for Collection | BY1: Item f) Total Revenue to the Company from the Collection Process
A3: 202401 | H3: 202402 | O3: 202403 | R3: 202401 | Y3: 202402 | AD3: 202403 | AR3: 202401 | AU3: 202402 | AV3: 202403 | AW3: Class | AX3: 202101 | AY3: 202102 | AZ3: 202103 | BA3: 202104 | BB3: 202105 | BC3: 202106 | BD3: 202107 | BE3: 202108 | BF3: 202109 | BG3: 202401 | BH3: 202402 | BI3: 202403 | BJ3: 202401 | BM3: 202402 | BP3: 202403 | BS3: 202401 | BU3: 202402 | BW3: 202403 | BY3: 202401 | CA3: 202402 | CC3: 202403
A4: CLASS | B4: ZIP | C4: COUNT | D4: DAYS 31 60 | E4: DAYS 61 90 | F4: DAYS 91+ | G4: ARREARS | H4: COUNT | I4: DAYS 31 60 | J4: DAYS 61 90 | K4: DAYS 91+ | L4: ARREARS | M4: COUNT | N4: DAYS 31 60 | O4: DAYS 61 90 | P4: DAYS 91+ | Q4: ARREARS | R4: CLASS | S4: ZIP | T4: COUNT | U4: DAYS 31 60 | V4: DAYS 61 90 | W4: DAYS 91+ | X4: ARREARS | Y4: COUNT | Z4: DAYS 31 60 | AA4: DAYS 61 90 | AB4: DAYS 91+ | AC4: ARREARS | AD4: COUNT | AE4: DAYS 31 60 | AF4: DAYS 61 90 | AG4: DAYS 91+ | AH4: ARREARS | AR4: CLASS | AS4: ZIP | AT4: BAD DEBT | AU4: BAD DEBT | AV4: BAD DEBT | AW4: RES | AX4: 78547.88 | AY4: 83507.78 | AZ4: 74673.15 | BA4: 63441.04 | BB4: 64476.9 | BC4: 57542.34 | BD4: 83815.89 | BE4: 81559.71 | BF4: 121882.53 | BG4: 332931.22 | BH4: 521109.71 | BI4: 529713.15 | BJ4: ZIP | BK4: CLASS | BL4: Count | BM4: ZIP | BN4: CLASS | BO4: Count | BP4: ZIP | BQ4: CLASS | BR4: Count | BS4: FLAG | BT4: SumOfSumOfAccount Collection Amount | BU4: FLAG | BV4: SumOfSumOfAccount Collection Amount | BW4: FLAG | BX4: SumOfSumOfAccount Collection Amount | BY4: FLAG | BZ4: SumOfPaid Amount | CA4: FLAG | CB4: SumOfPaid Amount | CC4: FLAG | CD4: SumOfPaid Amount
A5: COM | B5: 98901 | C5: 131 | D5: 69568.04 | E5: 16310.36 | F5: 119403.81 | G5: 205282.21 | H5: 123 | I5: 34900.54 | J5: 21242.23 | K5: 85977.31 | L5: 142120.08 | M5: 142 | N5: 81373.57 | O5: 19757.51 | P5: 77773.65 | Q5: 178904.73 | R5: COM | S5: 98901 | T5: 5 | U5: 406.89 | V5: 224.2 | W5: 775.07 | X5: 1406.16 | Y5: 4 | Z5: 413.36 | AA5: 383.61 | AB5: 924.2 | AC5: 1721.17 | AD5: 4 | AE5: 390.84 | AF5: 395.42 | AG5: 1270.05 | AH5: 2056.31 | AR5: =A5 -> COM | AS5: =B5 -> 98901 | AT5: =D5*1.6%+E5*6.3%+F5*28.9% -> 36648.342 | AU5: =I5*1.6%+J5*6.3%+K5*28.9% -> 26744.112 | AV5: =N5*1.6%+O5*6.3%+P5*28.9% -> 25023.285 | AW5: COM | AX5: 35411.49 | AY5: 19861.99 | AZ5: 1614.2 | BA5: 209.93 | BB5: 2347.21 | BC5: 3702.39 | BD5: 16587.84 | BE5: 21717.76 | BF5: 41593.57 | BG5: 42414.62 | BH5: 14589.08 | BI5: 20749.08 | BJ5: 98901 | BK5: COM | BL5: 8 | BM5: 98901 | BN5: COM | BO5: 1 | BP5: 98901 | BQ5: RES | BR5: 65 | BS5: 98901COM | BT5: 27265.99 | BU5: 98901COM | BV5: 2903.22 | BW5: 98901RES | BX5: 48324.46 | BY5: 98901COM | BZ5: 2181.68 | CA5: 98901RES | CB5: 737.56 | CC5: 98901RES | CD5: 491.89
A6: COM | B6: 98902 | C6: 188 | D6: 55317.06 | E6: 20010.3 | F6: 104595.96 | G6: 179923.32 | H6: 227 | I6: 113297.04 | J6: 27278.76 | K6: 107772.19 | L6: 248347.99 | M6: 203 | N6: 68594.01 | O6: 37551.17 | P6: 99427.64 | Q6: 205572.82 | R6: COM | S6: 98902 | T6: 4 | U6: 307.69 | V6: 113.12 | W6: 377.64 | X6: 798.45 | Y6: 4 | Z6: 386.22 | AA6: 299.69 | AB6: 132.14 | AC6: 818.05 | AD6: 5 | AE6: 283.7 | AF6: 350.79 | AG6: 210.93 | AH6: 845.42 | AR6: =A6 -> COM | AS6: =B6 -> 98902 | AT6: =D6*1.6%+E6*6.3%+F6*28.9% -> 32373.954 | AU6: =I6*1.6%+J6*6.3%+K6*28.9% -> 34677.477 | AV6: =N6*1.6%+O6*6.3%+P6*28.9% -> 32197.816 | BJ6: 98901 | BK6: RES | BL6: 85 | BM6: 98901 | BN6: RES | BO6: 64 | BP6: 98902 | BQ6: COM | BR6: 6 | BS6: 98901RES | BT6: 63382.49 | BU6: 98901RES | BV6: 94219.05 | BW6: 98902COM | BX6: 6680.46 | BY6: 98901RES | BZ6: 2158.21 | CA6: 98902COM | CB6: 250.08 | CC6: 98902COM | CD6: 117.45
A7: COM | B7: 98903 | C7: 101 | D7: 24198.88 | E7: 4458.14 | F7: 156033.01 | G7: 184690.03 | H7: 133 | I7: 58387.8 | J7: 8750.71 | K7: 55105.97 | L7: 122244.48 | M7: 121 | N7: 30300.13 | O7: 12520.28 | P7: 55606.16 | Q7: 98426.57 | R7: COM | S7: 98903 | T7: 2 | U7: 353.36 | V7: 242.74 | W7: 72.28 | X7: 668.38 | Y7: 2 | Z7: 401.97 | AA7: 338.8 | AB7: 329.58 | AC7: 1070.35 | AD7: 3 | AE7: 302.08 | AF7: 387.68 | AG7: 668.38 | AH7: 1358.14 | AR7: =A7 -> COM | AS7: =B7 -> 98903 | AT7: =D7*1.6%+E7*6.3%+F7*28.9% -> 45761.585 | AU7: =I7*1.6%+J7*6.3%+K7*28.9% -> 17411.125 | AV7: =N7*1.6%+O7*6.3%+P7*28.9% -> 17343.76 | BJ7: 98902 | BK7: COM | BL7: 6 | BM7: 98902 | BN7: COM | BO7: 7 | BP7: 98902 | BQ7: RES | BR7: 85 | BS7: 98902COM | BT7: 1825.24 | BU7: 98902COM | BV7: 10207.93 | BW7: 98902RES | BX7: 63250.47 | BY7: 98902COM | BZ7: 169.26 | CA7: 98902RES | CB7: 2986.94 | CC7: 98902RES | CD7: 2475.53
A8: COM | B8: 98904 | D8: 0 | E8: 0 | F8: 0 | G8: 0 | I8: 0 | J8: 0 | K8: 0 | L8: 0 | N8: 0 | O8: 0 | P8: 0 | Q8: 0 | R8: COM | S8: 98908 | T8: 4 | U8: 664.49 | V8: 507.45 | W8: 2804.53 | X8: 3976.47 | Y8: 5 | Z8: 1128.12 | AA8: 626.93 | AB8: 3311.98 | AC8: 5067.03 | AD8: 6 | AE8: 982.22 | AF8: 766.41 | AG8: 3938.91 | AH8: 5687.54 | AR8: =A8 -> COM | AS8: =B8 -> 98904 | AT8: =D8*1.6%+E8*6.3%+F8*28.9% -> 0 | AU8: =I8*1.6%+J8*6.3%+K8*28.9% -> 0 | AV8: =N8*1.6%+O8*6.3%+P8*28.9% -> 0 | BJ8: 98902 | BK8: RES | BL8: 110 | BM8: 98902 | BN8: RES | BO8: 74 | BP8: 98903 | BQ8: RES | BR8: 23 | BS8: 98902RES | BT8: 86277.4 | BU8: 98902RES | BV8: 46488.75 | BW8: 98903RES | BX8: 60814.18 | BY8: 98902RES | BZ8: 908.07 | CA8: 98903RES | CB8: 1759.29 | CC8: 98903RES | CD8: 339.94
A9: COM | B9: 98907 | D9: 0 | E9: 0 | F9: 0 | G9: 0 | I9: 0 | J9: 0 | K9: 0 | L9: 0 | N9: 0 | O9: 0 | P9: 0 | Q9: 0 | R9: COM | S9: 98930 | U9: 0 | V9: 0 | W9: 0 | X9: 0 | Y9: 1 | Z9: 21.22 | AA9: 0 | AB9: 0 | AC9: 21.22 | AR9: =A9 -> COM | AS9: =B9 -> 98907 | AT9: =D9*1.6%+E9*6.3%+F9*28.9% -> 0 | AU9: =I9*1.6%+J9*6.3%+K9*28.9% -> 0 | AV9: =N9*1.6%+O9*6.3%+P9*28.9% -> 0 | BJ9: 98903 | BK9: COM | BL9: 2 | BM9: 98903 | BN9: COM | BO9: 2 | BP9: 98908 | BQ9: RES | BR9: 44 | BS9: 98903COM | BT9: 1797.35 | BU9: 98903COM | BV9: 2127.82 | BW9: 98908RES | BX9: 25083.52 | BY9: 98903COM | BZ9: 1703.32 | CA9: 98908RES | CB9: 895.95 | CC9: 98908RES | CD9: 1187.01
A10: COM | B10: 98908 | C10: 128 | D10: 37174.41 | E10: 9264.09 | F10: 35610.03 | G10: 82048.53 | H10: 133 | I10: 49700.56 | J10: 11002.22 | K10: 38652.13 | L10: 99354.91 | M10: 131 | N10: 40502.57 | O10: 20698.55 | P10: 41216.81 | Q10: 102417.93 | R10: COM | S10: 98932 | T10: 1 | U10: 14.21 | V10: 0 | W10: 0 | X10: 14.21 | Y10: 1 | Z10: 14.46 | AA10: 0 | AB10: 0 | AC10: 14.46 | AD10: 1 | AE10: 14.85 | AF10: 0 | AG10: 0 | AH10: 14.85 | AR10: =A10 -> COM | AS10: =B10 -> 98908 | AT10: =D10*1.6%+E10*6.3%+F10*28.9% -> 11469.727 | AU10: =I10*1.6%+J10*6.3%+K10*28.9% -> 12658.814 | AV10: =N10*1.6%+O10*6.3%+P10*28.9% -> 13863.708 | BJ10: 98903 | BK10: RES | BL10: 26 | BM10: 98903 | BN10: RES | BO10: 23 | BP10: 98921 | BQ10: RES | BR10: 1 | BS10: 98903RES | BT10: 41341.98 | BU10: 98903RES | BV10: 28063.01 | BW10: 98921RES | BX10: 87.64 | BY10: 98903RES | BZ10: 321.66 | CA10: 98923RES | CB10: 111.55 | CC10: 98930RES | CD10: 10.01
A11: COM | B11: 98920 | D11: 0 | E11: 0 | F11: 0 | G11: 0 | I11: 0 | J11: 0 | K11: 0 | L11: 0 | N11: 0 | O11: 0 | P11: 0 | Q11: 0 | R11: COM | S11: 98933 | U11: 0 | V11: 0 | W11: 0 | X11: 0 | Z11: 0 | AA11: 0 | AB11: 0 | AC11: 0 | AE11: 0 | AF11: 0 | AG11: 0 | AH11: 0 | AR11: =A11 -> COM | AS11: =B11 -> 98920 | AT11: =D11*1.6%+E11*6.3%+F11*28.9% -> 0 | AU11: =I11*1.6%+J11*6.3%+K11*28.9% -> 0 | AV11: =N11*1.6%+O11*6.3%+P11*28.9% -> 0 | BJ11: 98908 | BK11: COM | BL11: 2 | BM11: 98908 | BN11: RES | BO11: 31 | BP11: 98930 | BQ11: RES | BR11: 10 | BS11: 98908COM | BT11: 305.37 | BU11: 98908RES | BV11: 25328.58 | BW11: 98930RES | BX11: 5497.77 | BY11: 98908COM | BZ11: 12.78 | CA11: 98930COM | CB11: 254.21 | CC11: 98932RES | CD11: 46.57
A12: COM | B12: 98921 | C12: 2 | D12: 163.44 | E12: 0 | F12: 0 | G12: 163.44 | I12: 0 | J12: 0 | K12: 0 | L12: 0 | M12: 1 | N12: 13.7 | O12: 0 | P12: 0 | Q12: 13.7 | R12: COM | S12: 98936 | T12: 1 | U12: 0 | V12: 35.22 | W12: 141.41 | X12: 176.63 | Y12: 1 | Z12: 38.08 | AA12: 38.93 | AB12: 176.63 | AC12: 253.64 | AD12: 1 | AE12: 35.22 | AF12: 77.01 | AG12: 166.82 | AH12: 279.05 | AR12: =A12 -> COM | AS12: =B12 -> 98921 | AT12: =D12*1.6%+E12*6.3%+F12*28.9% -> 2.61504 | AU12: =I12*1.6%+J12*6.3%+K12*28.9% -> 0 | AV12: =N12*1.6%+O12*6.3%+P12*28.9% -> 0.2192 | BJ12: 98908 | BK12: RES | BL12: 71 | BM12: 98921 | BN12: RES | BO12: 1 | BP12: 98932 | BQ12: RES | BR12: 6 | BS12: 98908RES | BT12: 40035.65 | BU12: 98921RES | BV12: 154.3 | BW12: 98932RES | BX12: 11140.44 | BY12: 98908RES | BZ12: 1340.08 | CA12: 98933COM | CB12: 191.91 | CC12: 98936RES | CD12: 141.43
A13: COM | B13: 98923 | C13: 5 | D13: 16940.32 | E13: 2535.15 | F13: 14050.68 | G13: 33526.15 | H13: 10 | I13: 3386.05 | J13: 2551.33 | K13: 10388.06 | L13: 16325.44 | M13: 7 | N13: 3222.68 | O13: 2634.86 | P13: 10181.55 | Q13: 16039.09 | R13: COM | S13: 98937 | T13: 1 | U13: 27.4 | V13: 24.16 | W13: 369.88 | X13: 421.44 | Y13: 1 | Z13: 47.29 | AA13: 27.4 | AB13: 236.23 | AC13: 310.92 | AD13: 1 | AE13: 20.65 | AF13: 47.29 | AG13: 263.63 | AH13: 331.57 | AR13: =A13 -> COM | AS13: =B13 -> 98923 | AT13: =D13*1.6%+E13*6.3%+F13*28.9% -> 4491.4061 | AU13: =I13*1.6%+J13*6.3%+K13*28.9% -> 3217.0599 | AV13: =N13*1.6%+O13*6.3%+P13*28.9% -> 3160.027 | BJ13: 98921 | BK13: RES | BL13: 3 | BM13: 98923 | BN13: COM | BO13: 1 | BP13: 98933 | BQ13: RES | BR13: 1 | BS13: 98921RES | BT13: 180.23 | BU13: 98923COM | BV13: 348.94 | BW13: 98933RES | BX13: 9828.91 | BY13: 98930RES | BZ13: 369.45 | CA13: 98935COM | CB13: 306.58 | CC13: 98951RES | CD13: 298.43
A14: COM | B14: 98930 | C14: 39 | D14: 11221.25 | E14: 1165.66 | F14: 29350.18 | G14: 41737.09 | H14: 39 | I14: 10592.47 | J14: 4565.52 | K14: 29031.34 | L14: 44189.33 | M14: 35 | N14: 8330.64 | O14: 5095.96 | P14: 30467.32 | Q14: 43893.92 | R14: COM | S14: 98938 | T14: 2 | U14: 443.13 | V14: 268.26 | W14: 1069.62 | X14: 1781.01 | Y14: 2 | Z14: 438.88 | AA14: 343.7 | AB14: 1337.88 | AC14: 2120.46 | AD14: 2 | AE14: 606.29 | AF14: 438.25 | AG14: 1681.58 | AH14: 2726.12 | AR14: =A14 -> COM | AS14: =B14 -> 98930 | AT14: =D14*1.6%+E14*6.3%+F14*28.9% -> 8735.1786 | AU14: =I14*1.6%+J14*6.3%+K14*28.9% -> 8847.1645 | AV14: =N14*1.6%+O14*6.3%+P14*28.9% -> 9259.3912 | BJ14: 98923 | BK14: RES | BL14: 8 | BM14: 98923 | BN14: RES | BO14: 1 | BP14: 98935 | BQ14: RES | BR14: 1 | BS14: 98923RES | BT14: 10431.85 | BU14: 98923RES | BV14: 111.55 | BW14: 98935RES | BX14: 75.62 | BY14: 98932RES | BZ14: 190.81 | CA14: 98936RES | CB14: 75.93 | CC14: 99328RES | CD14: 61.73
A15: COM | B15: 98932 | C15: 24 | D15: 12476 | E15: 1077.01 | F15: 17578.98 | G15: 31131.99 | H15: 24 | I15: 35023.44 | J15: 428.31 | K15: 5054.26 | L15: 40506.01 | M15: 19 | N15: 3818.37 | O15: 610.81 | P15: 4901.68 | Q15: 9330.86 | R15: COM | S15: 98939 | T15: 1 | U15: 426.38 | V15: 288.91 | W15: 224.28 | X15: 939.57 | Y15: 1 | Z15: 501.46 | AA15: 319.07 | AB15: 119.04 | AC15: 939.57 | AD15: 1 | AE15: 485.49 | AF15: 22.94 | AG15: 142.23 | AH15: 650.66 | AR15: =A15 -> COM | AS15: =B15 -> 98932 | AT15: =D15*1.6%+E15*6.3%+F15*28.9% -> 5347.7928 | AU15: =I15*1.6%+J15*6.3%+K15*28.9% -> 2048.0397 | AV15: =N15*1.6%+O15*6.3%+P15*28.9% -> 1516.1605 | BJ15: 98930 | BK15: RES | BL15: 25 | BM15: 98930 | BN15: COM | BO15: 2 | BP15: 98936 | BQ15: RES | BR15: 6 | BS15: 98930RES | BT15: 16314.13 | BU15: 98930COM | BV15: 422.71 | BW15: 98936RES | BX15: 2232.21 | BY15: 98935RES | BZ15: 59.78 | CA15: 98937RES | CB15: 57.15 | CC15: 99347RES | CD15: 113.3
A16: COM | B16: 98933 | C16: 10 | D16: 2093.94 | E16: 251.68 | F16: 186.3 | G16: 2531.92 | H16: 6 | I16: 830.84 | J16: 14 | K16: 14 | L16: 858.84 | M16: 8 | N16: 5840.85 | O16: 227.31 | P16: 0 | Q16: 6068.16 | R16: COM | S16: 98942 | U16: 0 | V16: 0 | W16: 0 | X16: 0 | Z16: 0 | AA16: 0 | AB16: 0 | AC16: 0 | AE16: 0 | AF16: 0 | AG16: 0 | AH16: 0 | AR16: =A16 -> COM | AS16: =B16 -> 98933 | AT16: =D16*1.6%+E16*6.3%+F16*28.9% -> 103.19958 | AU16: =I16*1.6%+J16*6.3%+K16*28.9% -> 18.22144 | AV16: =N16*1.6%+O16*6.3%+P16*28.9% -> 107.77413 | BJ16: 98932 | BK16: RES | BL16: 5 | BM16: 98930 | BN16: RES | BO16: 13 | BP16: 98937 | BQ16: RES | BR16: 4 | BS16: 98932RES | BT16: 4466.01 | BU16: 98930RES | BV16: 18389.11 | BW16: 98937RES | BX16: 546.98 | BY16: 98937COM | BZ16: 72.77 | CA16: 98942RES | CB16: 102.2 | CC16: 99362RES | CD16: 274.73
A17: COM | B17: 98935 | C17: 4 | D17: 1771.88 | E17: 0 | F17: 14.43 | G17: 1786.31 | H17: 3 | I17: 215.81 | J17: 0 | K17: 0 | L17: 215.81 | M17: 4 | N17: 599.25 | O17: 0 | P17: 0 | Q17: 599.25 | R17: COM | S17: 98944 | T17: 3 | U17: 954.98 | V17: 842.47 | W17: 23878.6 | X17: 25676.05 | Y17: 4 | Z17: 1288.61 | AA17: 954.98 | AB17: 24119.57 | AC17: 26363.16 | AD17: 4 | AE17: 1078.47 | AF17: 1288.61 | AG17: 25074.55 | AH17: 27441.63 | AR17: =A17 -> COM | AS17: =B17 -> 98935 | AT17: =D17*1.6%+E17*6.3%+F17*28.9% -> 32.52035 | AU17: =I17*1.6%+J17*6.3%+K17*28.9% -> 3.45296 | AV17: =N17*1.6%+O17*6.3%+P17*28.9% -> 9.588 | BJ17: 98933 | BK17: RES | BL17: 2 | BM17: 98932 | BN17: RES | BO17: 5 | BP17: 98938 | BQ17: RES | BR17: 2 | BS17: 98933RES | BT17: 16041.77 | BU17: 98932RES | BV17: 1895.13 | BW17: 98938RES | BX17: 7675.91 | BY17: 98939RES | BZ17: 14.55 | CA17: 98944RES | CB17: 392.99
A18: COM | B18: 98936 | C18: 21 | D18: 10345.76 | E18: 11502.12 | F18: 20556.05 | G18: 42403.93 | H18: 23 | I18: 70712.08 | J18: 1272.27 | K18: 11967.12 | L18: 83951.47 | M18: 23 | N18: 10495.06 | O18: 4387.49 | P18: 12853.96 | Q18: 27736.51 | R18: COM | S18: 98947 | U18: 0 | V18: 0 | W18: 0 | X18: 0 | Y18: 1 | Z18: 106.22 | AA18: 0 | AB18: 0 | AC18: 106.22 | AD18: 1 | AE18: 192.69 | AF18: 0 | AG18: 0 | AH18: 192.69 | AR18: =A18 -> COM | AS18: =B18 -> 98936 | AT18: =D18*1.6%+E18*6.3%+F18*28.9% -> 6830.8642 | AU18: =I18*1.6%+J18*6.3%+K18*28.9% -> 4670.044 | AV18: =N18*1.6%+O18*6.3%+P18*28.9% -> 4159.1273 | BJ18: 98935 | BK18: RES | BL18: 7 | BM18: 98933 | BN18: COM | BO18: 1 | BP18: 98942 | BQ18: RES | BR18: 15 | BS18: 98935RES | BT18: 3537.91 | BU18: 98933COM | BV18: 191.91 | BW18: 98942RES | BX18: 19480.52 | BY18: 98942RES | BZ18: 409.94 | CA18: 98947RES | CB18: 51.03
A19: COM | B19: 98937 | C19: 32 | D19: 17982.09 | E19: 2282.56 | F19: 13405.99 | G19: 33670.64 | H19: 31 | I19: 17962.2 | J19: 4560.46 | K19: 13749.17 | L19: 36271.83 | M19: 35 | N19: 15720.03 | O19: 2783.88 | P19: 11855.76 | Q19: 30359.67 | R19: COM | S19: 98948 | T19: 10 | U19: 5681.94 | V19: 2330.85 | W19: 17490.85 | X19: 25503.64 | Y19: 11 | Z19: 10728.07 | AA19: 1992.58 | AB19: 10765.52 | AC19: 23486.17 | AD19: 7 | AE19: 3065.2 | AF19: 4025.67 | AG19: 10138.46 | AH19: 17229.33 | AR19: =A19 -> COM | AS19: =B19 -> 98937 | AT19: =D19*1.6%+E19*6.3%+F19*28.9% -> 4305.8458 | AU19: =I19*1.6%+J19*6.3%+K19*28.9% -> 4548.2143 | AV19: =N19*1.6%+O19*6.3%+P19*28.9% -> 3853.2196 | BJ19: 98936 | BK19: RES | BL19: 7 | BM19: 98933 | BN19: RES | BO19: 2 | BP19: 98944 | BQ19: COM | BR19: 2 | BS19: 98936RES | BT19: 6875.3 | BU19: 98933RES | BV19: 6473.16 | BW19: 98944COM | BX19: 9292.87 | BY19: 98944COM | BZ19: 218.5 | CA19: 98948RES | CB19: 343
A20: COM | B20: 98938 | C20: 17 | D20: 32394.94 | E20: 903.05 | F20: 8737.46 | G20: 42035.45 | H20: 20 | I20: 35328.69 | J20: 30552.5 | K20: 8057.87 | L20: 73939.06 | M20: 16 | N20: 30621.42 | O20: 1795.27 | P20: 8996.35 | Q20: 41413.04 | R20: COM | S20: 98951 | T20: 4 | U20: 818.43 | V20: 121.76 | W20: 258.15 | X20: 1198.34 | Y20: 4 | Z20: 425.16 | AA20: 109.03 | AB20: 258.15 | AC20: 792.34 | AD20: 2 | AE20: 173.03 | AF20: 57.38 | AG20: 367.18 | AH20: 597.59 | AR20: =A20 -> COM | AS20: =B20 -> 98938 | AT20: =D20*1.6%+E20*6.3%+F20*28.9% -> 3100.3371 | AU20: =I20*1.6%+J20*6.3%+K20*28.9% -> 4818.791 | AV20: =N20*1.6%+O20*6.3%+P20*28.9% -> 3202.9899 | BJ20: 98937 | BK20: COM | BL20: 1 | BM20: 98935 | BN20: COM | BO20: 2 | BP20: 98944 | BQ20: RES | BR20: 38 | BS20: 98937COM | BT20: 72.77 | BU20: 98935COM | BV20: 310.56 | BW20: 98944RES | BX20: 17438.56 | BY20: 98944RES | BZ20: 495.95 | CA20: 98951RES | CB20: 557.73
A21: COM | B21: 98939 | C21: 2 | D21: 426.95 | E21: 288.91 | F21: 224.28 | G21: 940.14 | H21: 3 | I21: 672.33 | J21: 319.07 | K21: 119.04 | L21: 1110.44 | M21: 2 | N21: 509.3 | O21: 22.94 | P21: 142.23 | Q21: 674.47 | R21: COM | S21: 98952 | T21: 1 | U21: 142.92 | V21: 116.89 | W21: 245.31 | X21: 505.12 | Y21: 1 | Z21: 136.61 | AA21: 142.92 | AB21: 362.2 | AC21: 641.73 | AD21: 1 | AE21: 144.1 | AF21: 136.61 | AG21: 505.12 | AH21: 785.83 | AR21: =A21 -> COM | AS21: =B21 -> 98939 | AT21: =D21*1.6%+E21*6.3%+F21*28.9% -> 89.84945 | AU21: =I21*1.6%+J21*6.3%+K21*28.9% -> 65.26125 | AV21: =N21*1.6%+O21*6.3%+P21*28.9% -> 50.69849 | BJ21: 98937 | BK21: RES | BL21: 3 | BM21: 98935 | BN21: RES | BO21: 7 | BP21: 98947 | BQ21: RES | BR21: 2 | BS21: 98937RES | BT21: 488.48 | BU21: 98935RES | BV21: 3392.22 | BW21: 98947RES | BX21: 262.39 | BY21: 98947RES | BZ21: 103.91 | CA21: 99324RES | CB21: 254.97
A22: COM | B22: 98942 | C22: 56 | D22: 11099.93 | E22: 1960.7 | F22: 15454.52 | G22: 28515.15 | H22: 64 | I22: 177344.82 | J22: 3721.04 | K22: 14805.36 | L22: 195871.22 | M22: 63 | N22: 27922.76 | O22: 3816.14 | P22: 13035.01 | Q22: 44773.91 | R22: COM | S22: 98953 | T22: 4 | U22: 187.6 | V22: 483.68 | W22: 3350.72 | X22: 4022 | Y22: 4 | Z22: 193.8 | AA22: 187.6 | AB22: 3440.86 | AC22: 3822.26 | AD22: 5 | AE22: 296.43 | AF22: 193.8 | AG22: 3225.46 | AH22: 3715.69 | AR22: =A22 -> COM | AS22: =B22 -> 98942 | AT22: =D22*1.6%+E22*6.3%+F22*28.9% -> 4767.4793 | AU22: =I22*1.6%+J22*6.3%+K22*28.9% -> 7350.6917 | AV22: =N22*1.6%+O22*6.3%+P22*28.9% -> 4454.2989 | BJ22: 98938 | BK22: RES | BL22: 1 | BM22: 98936 | BN22: COM | BO22: 1 | BP22: 98948 | BQ22: COM | BR22: 1 | BS22: 98938RES | BT22: 323.75 | BU22: 98936COM | BV22: 1665.44 | BW22: 98948COM | BX22: 438.2 | BY22: 98951RES | BZ22: 142.72 | CA22: 99328RES | CB22: 491.91
A23: COM | B23: 98944 | C23: 99 | D23: 34942.88 | E23: 10216.64 | F23: 123485.32 | G23: 168644.84 | H23: 115 | I23: 45148.69 | J23: 18573.74 | K23: 127183.5 | L23: 190905.93 | M23: 116 | N23: 41395.79 | O23: 20822.17 | P23: 135741.57 | Q23: 197959.53 | R23: COM | S23: 99323 | T23: 1 | U23: 83.36 | V23: 103.27 | W23: 234.44 | X23: 421.07 | Y23: 1 | Z23: 52.88 | AA23: 83.36 | AB23: 337.71 | AC23: 473.95 | AE23: 0 | AF23: 0 | AG23: 0 | AH23: 0 | AR23: =A23 -> COM | AS23: =B23 -> 98944 | AT23: =D23*1.6%+E23*6.3%+F23*28.9% -> 36889.992 | AU23: =I23*1.6%+J23*6.3%+K23*28.9% -> 38648.556 | AV23: =N23*1.6%+O23*6.3%+P23*28.9% -> 41203.443 | BJ23: 98939 | BK23: RES | BL23: 4 | BM23: 98936 | BN23: RES | BO23: 7 | BP23: 98948 | BQ23: RES | BR23: 11 | BS23: 98939RES | BT23: 3036.33 | BU23: 98936RES | BV23: 15808.6 | BW23: 98948RES | BX23: 9395.19 | BY23: 98953RES | BZ23: 567.41 | CA23: 99347RES | CB23: 1899.16
A24: COM | B24: 98947 | C24: 12 | D24: 10344.96 | E24: 1058.9 | F24: 2565.77 | G24: 13969.63 | H24: 14 | I24: 5035.8 | J24: 235.96 | K24: 2397.72 | L24: 7669.48 | M24: 11 | N24: 3251.54 | O24: 1964.61 | P24: 2633.68 | Q24: 7849.83 | R24: COM | S24: 99324 | T24: 1 | U24: 12.22 | V24: 0 | W24: 0 | X24: 12.22 | Y24: 1 | Z24: 14.08 | AA24: 12.22 | AB24: 0 | AC24: 26.3 | AD24: 1 | AE24: 14.21 | AF24: 14.08 | AG24: 12.22 | AH24: 40.51 | AR24: =A24 -> COM | AS24: =B24 -> 98947 | AT24: =D24*1.6%+E24*6.3%+F24*28.9% -> 973.73759 | AU24: =I24*1.6%+J24*6.3%+K24*28.9% -> 788.37936 | AV24: =N24*1.6%+O24*6.3%+P24*28.9% -> 936.92859 | BJ24: 98942 | BK24: RES | BL24: 26 | BM24: 98937 | BN24: RES | BO24: 1 | BP24: 98951 | BQ24: RES | BR24: 15 | BS24: 98942RES | BT24: 17938.25 | BU24: 98937RES | BV24: 57.15 | BW24: 98951RES | BX24: 26543.17 | BY24: 99324RES | BZ24: 147.61 | CA24: 99362COM | CB24: 183.69
A25: COM | B25: 98948 | C25: 69 | D25: 18997.32 | E25: 18784.67 | F25: 194697.92 | G25: 232479.91 | H25: 110 | I25: 108221.94 | J25: 12330.23 | K25: 183058.95 | L25: 303611.12 | M25: 69 | N25: 47615.8 | O25: 28899.92 | P25: 169413.37 | Q25: 245929.09 | R25: COM | S25: 99328 | U25: 0 | V25: 0 | W25: 0 | X25: 0 | Z25: 0 | AA25: 0 | AB25: 0 | AC25: 0 | AE25: 0 | AF25: 0 | AG25: 0 | AH25: 0 | AR25: =A25 -> COM | AS25: =B25 -> 98948 | AT25: =D25*1.6%+E25*6.3%+F25*28.9% -> 57755.09 | AU25: =I25*1.6%+J25*6.3%+K25*28.9% -> 55412.392 | AV25: =N25*1.6%+O25*6.3%+P25*28.9% -> 51543.012 | BJ25: 98944 | BK25: COM | BL25: 1 | BM25: 98938 | BN25: RES | BO25: 2 | BP25: 98953 | BQ25: RES | BR25: 8 | BS25: 98944COM | BT25: 218.5 | BU25: 98938RES | BV25: 28200.44 | BW25: 98953RES | BX25: 13090.66 | BY25: 99328RES | BZ25: 61.73 | CA25: 99362RES | CB25: 1303.11
A26: COM | B26: 98951 | C26: 72 | D26: 80377.66 | E26: 7701.07 | F26: 36406.18 | G26: 124484.91 | H26: 81 | I26: 38031 | J26: 5700.8 | K26: 35175.14 | L26: 78906.94 | M26: 77 | N26: 41143.22 | O26: 9319.89 | P26: 33936.09 | Q26: 84399.2 | R26: COM | S26: 99347 | T26: 1 | U26: 109.95 | V26: 0 | W26: 0 | X26: 109.95 | Y26: 1 | Z26: 142.06 | AA26: 0 | AB26: 0 | AC26: 142.06 | AD26: 2 | AE26: 281.21 | AF26: 0 | AG26: 0 | AH26: 281.21 | AR26: =A26 -> COM | AS26: =B26 -> 98951 | AT26: =D26*1.6%+E26*6.3%+F26*28.9% -> 12292.596 | AU26: =I26*1.6%+J26*6.3%+K26*28.9% -> 11133.262 | AV26: =N26*1.6%+O26*6.3%+P26*28.9% -> 11052.975 | BJ26: 98944 | BK26: RES | BL26: 30 | BM26: 98942 | BN26: RES | BO26: 19 | BP26: 99323 | BQ26: RES | BR26: 3 | BS26: 98944RES | BT26: 14193.61 | BU26: 98942RES | BV26: 11952.92 | BW26: 99323RES | BX26: 1012.54 | BY26: 99347RES | BZ26: 36.69
A27: COM | B27: 98952 | C27: 11 | D27: 6879.33 | E27: 333.68 | F27: 3372.24 | G27: 10585.25 | H27: 8 | I27: 2034.42 | J27: 397.32 | K27: 3642.45 | L27: 6074.19 | M27: 7 | N27: 1624.24 | O27: 528.78 | P27: 4039.77 | Q27: 6192.79 | R27: COM | S27: 99362 | T27: 1 | U27: 20.71 | V27: 0 | W27: 0 | X27: 20.71 | Z27: 0 | AA27: 0 | AB27: 0 | AC27: 0 | AD27: 1 | AE27: 20.32 | AF27: 0 | AG27: 0 | AH27: 20.32 | AR27: =A27 -> COM | AS27: =B27 -> 98952 | AT27: =D27*1.6%+E27*6.3%+F27*28.9% -> 1105.6685 | AU27: =I27*1.6%+J27*6.3%+K27*28.9% -> 1110.2499 | AV27: =N27*1.6%+O27*6.3%+P27*28.9% -> 1226.7945 | BJ27: 98947 | BK27: COM | BL27: 1 | BM27: 98944 | BN27: COM | BO27: 4 | BP27: 99324 | BQ27: RES | BR27: 11 | BS27: 98947COM | BT27: 120.68 | BU27: 98944COM | BV27: 427.86 | BW27: 99324RES | BX27: 2894.78 | BY27: 99362COM | BZ27: 518.19
A28: COM | B28: 98953 | C28: 45 | D28: 9522.99 | E28: 5165.18 | F28: 38479.03 | G28: 53167.2 | H28: 53 | I28: 29527.62 | J28: 4496.1 | K28: 39123.4 | L28: 73147.12 | M28: 51 | N28: 10377.37 | O28: 4978.76 | P28: 37694.61 | Q28: 53050.74 | R28: RES | S28: 98901 | T28: 635 | U28: 98540.26 | V28: 19862.51 | W28: 199330.9 | X28: 317733.67 | Y28: 696 | Z28: 111265.69 | AA28: 75470.94 | AB28: 197958.33 | AC28: 384694.96 | AD28: 748 | AE28: 132079.94 | AF28: 78225.03 | AG28: 212515.65 | AH28: 422820.62 | AR28: =A28 -> COM | AS28: =B28 -> 98953 | AT28: =D28*1.6%+E28*6.3%+F28*28.9% -> 11598.214 | AU28: =I28*1.6%+J28*6.3%+K28*28.9% -> 12062.359 | AV28: =N28*1.6%+O28*6.3%+P28*28.9% -> 11373.442 | BJ28: 98947 | BK28: RES | BL28: 4 | BM28: 98944 | BN28: RES | BO28: 16 | BP28: 99328 | BQ28: RES | BR28: 4 | BS28: 98947RES | BT28: 896.7 | BU28: 98944RES | BV28: 12556.26 | BW28: 99328RES | BX28: 2687.17 | BY28: 99362RES | BZ28: 1349.33
A29: COM | B29: 99301 | C29: 1 | D29: 18.54 | E29: 18.79 | F29: 37.08 | G29: 74.41 | H29: 1 | I29: 18.54 | J29: 18.54 | K29: 55.87 | L29: 92.95 | M29: 1 | N29: 18.54 | O29: 18.54 | P29: 74.41 | Q29: 111.49 | R29: RES | S29: 98902 | T29: 959 | U29: 130619.55 | V29: 69276.01 | W29: 230718.48 | X29: 430614.04 | Y29: 1196 | Z29: 237711.52 | AA29: 101091.1 | AB29: 259936.37 | AC29: 598738.99 | AD29: 1095 | AE29: 160030.67 | AF29: 150399.94 | AG29: 239367.23 | AH29: 549797.84 | AR29: =A29 -> COM | AS29: =B29 -> 99301 | AT29: =D29*1.6%+E29*6.3%+F29*28.9% -> 12.19653 | AU29: =I29*1.6%+J29*6.3%+K29*28.9% -> 17.61109 | AV29: =N29*1.6%+O29*6.3%+P29*28.9% -> 22.96915 | BJ29: 98948 | BK29: RES | BL29: 13 | BM29: 98947 | BN29: RES | BO29: 1 | BP29: 99347 | BQ29: RES | BR29: 4 | BS29: 98948RES | BT29: 19918.27 | BU29: 98947RES | BV29: 51.03 | BW29: 99347RES | BX29: 1702.72
A30: COM | B30: 99323 | C30: 13 | D30: 4581.21 | E30: 2094.1 | F30: 4388.26 | G30: 11063.57 | H30: 11 | I30: 4495.18 | J30: 1897.27 | K30: 3720.11 | L30: 10112.56 | M30: 9 | N30: 3232.7 | O30: 2095.03 | P30: 2851.1 | Q30: 8178.83 | R30: RES | S30: 98903 | T30: 263 | U30: 47266.9 | V30: 10981.72 | W30: 102544.64 | X30: 160793.26 | Y30: 342 | Z30: 89347.25 | AA30: 26968.95 | AB30: 105098.65 | AC30: 221414.85 | AD30: 317 | AE30: 66207.47 | AF30: 45077.46 | AG30: 106444.56 | AH30: 217729.49 | AR30: =A30 -> COM | AS30: =B30 -> 99323 | AT30: =D30*1.6%+E30*6.3%+F30*28.9% -> 1473.4348 | AU30: =I30*1.6%+J30*6.3%+K30*28.9% -> 1266.5627 | AV30: =N30*1.6%+O30*6.3%+P30*28.9% -> 1007.678 | BJ30: 98951 | BK30: RES | BL30: 12 | BM30: 98948 | BN30: RES | BO30: 21 | BP30: 99348 | BQ30: RES | BR30: 1 | BS30: 98951RES | BT30: 26335.65 | BU30: 98948RES | BV30: 14855.49 | BW30: 99348RES | BX30: 125.31
A31: COM | B31: 99324 | C31: 13 | D31: 1834.2 | E31: 532.93 | F31: 10.09 | G31: 2377.22 | H31: 7 | I31: 662.5 | J31: 55.72 | K31: 0.76 | L31: 718.98 | M31: 13 | N31: 1460.12 | O31: 48.6 | P31: 12.22 | Q31: 1520.94 | R31: RES | S31: 98908 | T31: 405 | U31: 66317.22 | V31: 36888.77 | W31: 105620.71 | X31: 208826.7 | Y31: 458 | Z31: 92242.4 | AA31: 48473.78 | AB31: 117215.69 | AC31: 257931.87 | AD31: 432 | AE31: 68878.78 | AF31: 66412.81 | AG31: 117263.22 | AH31: 252554.81 | AR31: =A31 -> COM | AS31: =B31 -> 99324 | AT31: =D31*1.6%+E31*6.3%+F31*28.9% -> 65.8378 | AU31: =I31*1.6%+J31*6.3%+K31*28.9% -> 14.33 | AV31: =N31*1.6%+O31*6.3%+P31*28.9% -> 29.9553 | BJ31: 98952 | BK31: RES | BL31: 5 | BM31: 98951 | BN31: RES | BO31: 10 | BP31: 99361 | BQ31: RES | BR31: 3 | BS31: 98952RES | BT31: 9072.33 | BU31: 98951RES | BV31: 8353.74 | BW31: 99361RES | BX31: 810.21
A32: COM | B32: 99328 | C32: 26 | D32: 27010.18 | E32: 2653.73 | F32: 858.52 | G32: 30522.43 | H32: 20 | I32: 9931.13 | J32: 4301.62 | K32: 872.81 | L32: 15105.56 | M32: 21 | N32: 8530.84 | O32: 3724.21 | P32: 1728.14 | Q32: 13983.19 | R32: RES | S32: 98921 | T32: 40 | U32: 6779.96 | V32: 3460.18 | W32: 15021.91 | X32: 25262.05 | Y32: 43 | Z32: 8356.19 | AA32: 4705.48 | AB32: 15284.96 | AC32: 28346.63 | AD32: 40 | AE32: 7052.4 | AF32: 4924.6 | AG32: 12604.7 | AH32: 24581.7 | AR32: =A32 -> COM | AS32: =B32 -> 99328 | AT32: =D32*1.6%+E32*6.3%+F32*28.9% -> 847.46015 | AU32: =I32*1.6%+J32*6.3%+K32*28.9% -> 682.14223 | AV32: =N32*1.6%+O32*6.3%+P32*28.9% -> 870.55113 | BJ32: 98953 | BK32: RES | BL32: 11 | BM32: 98953 | BN32: COM | BO32: 1 | BP32: 99362 | BQ32: COM | BR32: 2 | BS32: 98953RES | BT32: 13028.52 | BU32: 98953COM | BV32: 65.22 | BW32: 99362COM | BX32: 3870.79
A33: COM | B33: 99329 | C33: 4 | D33: 163.38 | E33: 13.7 | F33: 137.13 | G33: 314.21 | H33: 2 | I33: 91.71 | J33: 37.54 | K33: 150.83 | L33: 280.08 | M33: 5 | N33: 377.91 | O33: 91.71 | P33: 188.37 | Q33: 657.99 | R33: RES | S33: 98923 | T33: 13 | U33: 3048.85 | V33: 1455.76 | W33: 5518.08 | X33: 10022.69 | Y33: 17 | Z33: 4334.74 | AA33: 1931.64 | AB33: 6254.94 | AC33: 12521.32 | AD33: 18 | AE33: 3293.26 | AF33: 2441.91 | AG33: 7271.92 | AH33: 13007.09 | AR33: =A33 -> COM | AS33: =B33 -> 99329 | AT33: =D33*1.6%+E33*6.3%+F33*28.9% -> 43.10775 | AU33: =I33*1.6%+J33*6.3%+K33*28.9% -> 47.42225 | AV33: =N33*1.6%+O33*6.3%+P33*28.9% -> 66.26322 | BJ33: 99324 | BK33: RES | BL33: 11 | BM33: 98953 | BN33: RES | BO33: 9 | BP33: 99362 | BQ33: RES | BR33: 58 | BS33: 99324RES | BT33: 768.1 | BU33: 98953RES | BV33: 24629.2 | BW33: 99362RES | BX33: 21683.21
A34: COM | B34: 99347 | C34: 9 | D34: 3801.04 | E34: 1869.66 | F34: 5913.8 | G34: 11584.5 | H34: 11 | I34: 5244.28 | J34: 2188.66 | K34: 7423.74 | L34: 14856.68 | M34: 13 | N34: 5734.26 | O34: 2390.21 | P34: 9612.4 | Q34: 17736.87 | R34: RES | S34: 98930 | T34: 204 | U34: 27674.95 | V34: 4663.36 | W34: 82944.23 | X34: 115282.54 | Y34: 203 | Z34: 30357.55 | AA34: 17513.81 | AB34: 76160.56 | AC34: 124031.92 | AD34: 220 | AE34: 33589.25 | AF34: 20101.33 | AG34: 68190.54 | AH34: 121881.12 | AR34: =A34 -> COM | AS34: =B34 -> 99347 | AT34: =D34*1.6%+E34*6.3%+F34*28.9% -> 1887.6934 | AU34: =I34*1.6%+J34*6.3%+K34*28.9% -> 2367.2549 | AV34: =N34*1.6%+O34*6.3%+P34*28.9% -> 3020.315 | BJ34: 99328 | BK34: COM | BL34: 4 | BM34: 99323 | BN34: COM | BO34: 1 | BS34: 99328COM | BT34: 4449.94 | BU34: 99323COM | BV34: 22.22
A35: COM | B35: 99348 | C35: 5 | D35: 1588.91 | E35: 127.84 | F35: 82.17 | G35: 1798.92 | H35: 2 | I35: 1248.32 | J35: 1071.65 | K35: 33.45 | L35: 2353.42 | M35: 2 | N35: 41517.35 | O35: 302.87 | P35: 170 | Q35: 41990.22 | R35: RES | S35: 98932 | T35: 154 | U35: 23624.87 | V35: 12957.8 | W35: 57887.83 | X35: 94470.5 | Y35: 152 | Z35: 31598.71 | AA35: 16170.23 | AB35: 59807.74 | AC35: 107576.68 | AD35: 149 | AE35: 21222.64 | AF35: 23017.72 | AG35: 57192.18 | AH35: 101432.54 | AR35: =A35 -> COM | AS35: =B35 -> 99348 | AT35: =D35*1.6%+E35*6.3%+F35*28.9% -> 57.22361 | AU35: =I35*1.6%+J35*6.3%+K35*28.9% -> 97.15412 | AV35: =N35*1.6%+O35*6.3%+P35*28.9% -> 732.48841 | BJ35: 99328 | BK35: RES | BL35: 9 | BM35: 99323 | BN35: RES | BO35: 5 | BS35: 99328RES | BT35: 6881.24 | BU35: 99323RES | BV35: 5123.43
A36: COM | B36: 99350 | D36: 0 | E36: 0 | F36: 0 | G36: 0 | H36: 1 | I36: 182.14 | J36: 0 | K36: 0 | L36: 182.14 | M36: 1 | N36: 28.11 | O36: 182.14 | P36: 0 | Q36: 210.25 | R36: RES | S36: 98933 | T36: 20 | U36: 4540.28 | V36: 1895.24 | W36: 16840.86 | X36: 23276.38 | Y36: 23 | Z36: 5246.35 | AA36: 3738.07 | AB36: 17922.53 | AC36: 26906.95 | AD36: 18 | AE36: 4057.17 | AF36: 3645.78 | AG36: 20494.69 | AH36: 28197.64 | AR36: =A36 -> COM | AS36: =B36 -> 99350 | AT36: =D36*1.6%+E36*6.3%+F36*28.9% -> 0 | AU36: =I36*1.6%+J36*6.3%+K36*28.9% -> 2.91424 | AV36: =N36*1.6%+O36*6.3%+P36*28.9% -> 11.92458 | BJ36: 99347 | BK36: RES | BL36: 3 | BM36: 99324 | BN36: RES | BO36: 14 | BS36: 99347RES | BT36: 2548.83 | BU36: 99324RES | BV36: 6758.89
A37: COM | B37: 99360 | C37: 12 | D37: 3921.24 | E37: 1233.38 | F37: 384.7 | G37: 5539.32 | H37: 12 | I37: 1594.74 | J37: 464.34 | K37: 281.84 | L37: 2340.92 | M37: 13 | N37: 2100.91 | O37: 447.53 | P37: 258.97 | Q37: 2807.41 | R37: RES | S37: 98935 | T37: 69 | U37: 12614.75 | V37: 498.66 | W37: 41627.95 | X37: 54741.36 | Y37: 74 | Z37: 13045.29 | AA37: 8451.31 | AB37: 38771.17 | AC37: 60267.77 | AD37: 72 | AE37: 15738.81 | AF37: 8746.83 | AG37: 41190.13 | AH37: 65675.77 | AR37: =A37 -> COM | AS37: =B37 -> 99360 | AT37: =D37*1.6%+E37*6.3%+F37*28.9% -> 251.62108 | AU37: =I37*1.6%+J37*6.3%+K37*28.9% -> 136.22102 | AV37: =N37*1.6%+O37*6.3%+P37*28.9% -> 136.65128 | BJ37: 99348 | BK37: RES | BL37: 3 | BM37: 99328 | BN37: RES | BO37: 5 | BS37: 99348RES | BT37: 2798.48 | BU37: 99328RES | BV37: 776.74
A38: COM | B38: 99361 | C38: 10 | D38: 1445.01 | E38: 49.71 | F38: 21.02 | G38: 1515.74 | H38: 11 | I38: 2928.52 | J38: 175.86 | K38: 62.17 | L38: 3166.55 | M38: 11 | N38: 6896.7 | O38: 776.87 | P38: 147.1 | Q38: 7820.67 | R38: RES | S38: 98936 | T38: 59 | U38: 9612.44 | V38: 117.35 | W38: 31661.34 | X38: 41391.13 | Y38: 65 | Z38: 11175.75 | AA38: 7920.67 | AB38: 29473.08 | AC38: 48569.5 | AD38: 67 | AE38: 12929.04 | AF38: 8438.04 | AG38: 32042.24 | AH38: 53409.32 | AR38: =A38 -> COM | AS38: =B38 -> 99361 | AT38: =D38*1.6%+E38*6.3%+F38*28.9% -> 32.32667 | AU38: =I38*1.6%+J38*6.3%+K38*28.9% -> 75.90263 | AV38: =N38*1.6%+O38*6.3%+P38*28.9% -> 201.80191 | BJ38: 99360 | BK38: RES | BL38: 1 | BM38: 99347 | BN38: RES | BO38: 4 | BS38: 99360RES | BT38: 36.44 | BU38: 99347RES | BV38: 6811.85
A39: COM | B39: 99362 | C39: 104 | D39: 85888.27 | E39: 38154.53 | F39: 47954.71 | G39: 171997.51 | H39: 106 | I39: 110597.98 | J39: 7251.26 | K39: 29131.98 | L39: 146981.22 | M39: 115 | N39: 112783.27 | O39: 5911.78 | P39: 25680.64 | Q39: 144375.69 | R39: RES | S39: 98937 | T39: 27 | U39: 5184.9 | V39: 2214.57 | W39: 7348.08 | X39: 14747.55 | Y39: 26 | Z39: 6823.63 | AA39: 2831.01 | AB39: 7756.75 | AC39: 17411.39 | AD39: 31 | AE39: 6460.7 | AF39: 4736.38 | AG39: 8186.42 | AH39: 19383.5 | AR39: =A39 -> COM | AS39: =B39 -> 99362 | AT39: =D39*1.6%+E39*6.3%+F39*28.9% -> 17636.859 | AU39: =I39*1.6%+J39*6.3%+K39*28.9% -> 10645.539 | AV39: =N39*1.6%+O39*6.3%+P39*28.9% -> 9598.6794 | BJ39: 99361 | BK39: RES | BL39: 3 | BM39: 99362 | BN39: COM | BO39: 2 | BS39: 99361RES | BT39: 1122.17 | BU39: 99362COM | BV39: 193.89
A40: COM | B40: 99363 | C40: 6 | D40: 2538.04 | E40: 121.51 | F40: 721.35 | G40: 3380.9 | H40: 5 | I40: 4153.24 | J40: 148.98 | K40: 49.75 | L40: 4351.97 | M40: 5 | N40: 2368.13 | O40: 333.98 | P40: 124.02 | Q40: 2826.13 | R40: RES | S40: 98938 | T40: 35 | U40: 8442.24 | V40: 3948.11 | W40: 17936.87 | X40: 30327.22 | Y40: 39 | Z40: 12929.4 | AA40: 6400.36 | AB40: 19605.57 | AC40: 38935.33 | AD40: 37 | AE40: 8322.93 | AF40: 8894.56 | AG40: 20257.97 | AH40: 37475.46 | AR40: =A40 -> COM | AS40: =B40 -> 99363 | AT40: =D40*1.6%+E40*6.3%+F40*28.9% -> 256.73392 | AU40: =I40*1.6%+J40*6.3%+K40*28.9% -> 90.21533 | AV40: =N40*1.6%+O40*6.3%+P40*28.9% -> 94.7726 | BJ40: 99362 | BK40: COM | BL40: 3 | BM40: 99362 | BN40: RES | BO40: 58 | BS40: 99362COM | BT40: 1172.23 | BU40: 99362RES | BV40: 17970.2
A41: COM | B41: WA | C41: 1 | D41: 5943.14 | E41: 0 | F41: 0 | G41: 5943.14 | I41: 0 | J41: 0 | K41: 0 | L41: 0 | M41: 2 | N41: 6543.26 | O41: 0 | P41: 0 | Q41: 6543.26 | R41: RES | S41: 98939 | T41: 10 | U41: 1952.3 | V41: 889.61 | W41: 7638.86 | X41: 10480.77 | Y41: 10 | Z41: 2103.74 | AA41: 1400.91 | AB41: 7592.97 | AC41: 11097.62 | AD41: 13 | AE41: 2517.92 | AF41: 1766.08 | AG41: 8942.75 | AH41: 13226.75 | AR41: =A41 -> COM | AS41: =B41 -> WA | AT41: =D41*1.6%+E41*6.3%+F41*28.9% -> 95.09024 | AU41: =I41*1.6%+J41*6.3%+K41*28.9% -> 0 | AV41: =N41*1.6%+O41*6.3%+P41*28.9% -> 104.69216 | BJ41: 99362 | BK41: RES | BL41: 72 | BS41: 99362RES | BT41: 24361.62
A42: RES | B42: 98603 | D42: 0 | E42: 0 | F42: 0 | G42: 0 | I42: 0 | J42: 0 | K42: 0 | L42: 0 | M42: 3 | N42: 362.02 | O42: 0 | P42: 0 | Q42: 362.02 | R42: RES | S42: 98942 | T42: 141 | U42: 27954.79 | V42: 12664.66 | W42: 49342.58 | X42: 89962.03 | Y42: 148 | Z42: 27276.57 | AA42: 21180.22 | AB42: 55380.12 | AC42: 103836.91 | AD42: 161 | AE42: 33592.37 | AF42: 20994.1 | AG42: 59227.84 | AH42: 113814.31 | AR42: =A42 -> RES | AS42: =B42 -> 98603 | AT42: =D42*1.6%+E42*6.3%+F42*28.9% -> 0 | AU42: =I42*1.6%+J42*6.3%+K42*28.9% -> 0 | AV42: =N42*1.6%+O42*6.3%+P42*28.9% -> 5.79232 | BJ42: TOTAL | BL42: =SUMIF($BK$5:$BK$41,$BK$6,$BL$5:BL41) -> 560 | BO42: =SUMIF(BN5:BN40,BN6,BO5:BO40) -> 393 | BR42: =SUMIF(BQ5:BQ33,BQ5,BR5:BR33) -> 421 | BT42: =SUM(BT6,BT8,BT10,BT12:BT19,BT21:BT24,BT26,BT28:BT33,BT35:BT39,BT41) -> 432633.49 | BV42: =SUM(BV6,BV8,BV10:BV12,BV14,BV16:BV17,BV19,BV21,BV23:BV26,BV28:BV31,BV33,BV35:BV38,BV40) -> 378420.8 | BX42: =SUM(BX5,BX7:BX18,BX20:BX21,BX23:BX31,BX33) -> 351684.54 | BZ42: =SUM(BZ6,BZ8,BZ10,BZ12:BZ15,BZ17:BZ18,BZ20:BZ25,BZ26,BZ28) -> 8677.9 | CB42: =SUM(CB5,CB7:CB10,CB14:CB23,CB25) -> 12020.47 | CD42: =SUM(CD5,CD7:CD16) -> 5440.57
A43: RES | B43: 98901 | C43: 2229 | D43: 322496 | E43: 65364.83 | F43: 781167.03 | G43: 1169027.9 | H43: 2389 | I43: 361710.38 | J43: 189903.23 | K43: 739544.32 | L43: 1291157.9 | M43: 2759 | N43: 492624.51 | O43: 213567.15 | P43: 780863.58 | Q43: 1487055.2 | R43: RES | S43: 98944 | T43: 477 | U43: 71358.71 | V43: 33753.18 | W43: 191938.15 | X43: 297050.04 | Y43: 504 | Z43: 89521.65 | AA43: 52295.33 | AB43: 189001.73 | AC43: 330818.71 | AD43: 502 | AE43: 74703.15 | AF43: 60652.38 | AG43: 193940.63 | AH43: 329296.16 | AR43: =A43 -> RES | AS43: =B43 -> 98901 | AT43: =D43*1.6%+E43*6.3%+F43*28.9% -> 235035.19 | AU43: =I43*1.6%+J43*6.3%+K43*28.9% -> 231479.58 | AV43: =N43*1.6%+O43*6.3%+P43*28.9% -> 247006.3
A44: RES | B44: 98902 | C44: 4091 | D44: 504695.33 | E44: 217180.35 | F44: 820832.9 | G44: 1542708.6 | H44: 5422 | I44: 993535.38 | J44: 296078.35 | K44: 868468.5 | L44: 2158082.2 | M44: 5030 | N44: 702390.79 | O44: 481305.55 | P44: 785007.34 | Q44: 1968703.7 | R44: RES | S44: 98947 | T44: 68 | U44: 13287.66 | V44: 7048.26 | W44: 25844.94 | X44: 46180.86 | Y44: 76 | Z44: 18317.45 | AA44: 9908.71 | AB44: 28992.32 | AC44: 57218.48 | AD44: 71 | AE44: 13759.99 | AF44: 12580.53 | AG44: 25633.35 | AH44: 51973.87 | AR44: =A44 -> RES | AS44: =B44 -> 98902 | AT44: =D44*1.6%+E44*6.3%+F44*28.9% -> 258978.2 | AU44: =I44*1.6%+J44*6.3%+K44*28.9% -> 285536.9 | AV44: =N44*1.6%+O44*6.3%+P44*28.9% -> 268427.62
A45: RES | B45: 98903 | C45: 1544 | D45: 276014.51 | E45: 73931.09 | F45: 580424.32 | G45: 930369.92 | H45: 2034 | I45: 513641.13 | J45: 116324.34 | K45: 582025.21 | L45: 1211990.7 | M45: 1893 | N45: 361509.16 | O45: 206355.53 | P45: 586511.83 | Q45: 1154376.5 | R45: RES | S45: 98948 | T45: 341 | U45: 43723.66 | V45: 30632.27 | W45: 202115.89 | X45: 276471.82 | Y45: 437 | Z45: 116177.51 | AA45: 35523.36 | AB45: 225784.96 | AC45: 377485.83 | AD45: 380 | AE45: 67553.55 | AF45: 71898.63 | AG45: 209430.55 | AH45: 348882.73 | AR45: =A45 -> RES | AS45: =B45 -> 98903 | AT45: =D45*1.6%+E45*6.3%+F45*28.9% -> 176816.52 | AU45: =I45*1.6%+J45*6.3%+K45*28.9% -> 183751.98 | AV45: =N45*1.6%+O45*6.3%+P45*28.9% -> 188286.46
A46: RES | B46: 98904 | D46: 0 | E46: 0 | F46: 0 | G46: 0 | H46: 1 | I46: 29.5 | J46: 0 | K46: 0 | L46: 29.5 | R46: RES | S46: 98951 | T46: 342 | U46: 64913.63 | V46: 23736.58 | W46: 245575.25 | X46: 334225.46 | Y46: 373 | Z46: 82632.8 | AA46: 48314.19 | AB46: 226270.63 | AC46: 357217.62 | AD46: 364 | AE46: 72714.32 | AF46: 58809.13 | AG46: 245139.22 | AH46: 376662.67 | AR46: =A46 -> RES | AS46: =B46 -> 98904 | AT46: =D46*1.6%+E46*6.3%+F46*28.9% -> 0 | AU46: =I46*1.6%+J46*6.3%+K46*28.9% -> 0.472 | AV46: =N46*1.6%+O46*6.3%+P46*28.9% -> 0
A47: RES | B47: 98908 | C47: 3501 | D47: 540012.1 | E47: 198384.79 | F47: 612366.7 | G47: 1350763.6 | H47: 3972 | I47: 771763.88 | J47: 251381.12 | K47: 636489.35 | L47: 1659634.4 | M47: 3921 | N47: 621413.58 | O47: 375647.42 | P47: 647348.7 | Q47: 1644409.7 | R47: RES | S47: 98952 | T47: 31 | U47: 7059.32 | V47: 3234.84 | W47: 19732.14 | X47: 30026.3 | Y47: 33 | Z47: 8295.3 | AA47: 5105.87 | AB47: 21100.98 | AC47: 34502.15 | AD47: 30 | AE47: 7484.96 | AF47: 6762.64 | AG47: 23203.05 | AH47: 37450.65 | AR47: =A47 -> RES | AS47: =B47 -> 98908 | AT47: =D47*1.6%+E47*6.3%+F47*28.9% -> 198112.41 | AU47: =I47*1.6%+J47*6.3%+K47*28.9% -> 212130.65 | AV47: =N47*1.6%+O47*6.3%+P47*28.9% -> 220692.18
A48: RES | B48: 98920 | D48: 0 | E48: 0 | F48: 0 | G48: 0 | H48: 1 | I48: 28.64 | J48: 0 | K48: 0 | L48: 28.64 | M48: 1 | N48: 31.11 | O48: 28.64 | P48: 0 | Q48: 59.75 | R48: RES | S48: 98953 | T48: 83 | U48: 15432.98 | V48: 9132.42 | W48: 44088.95 | X48: 68654.35 | Y48: 85 | Z48: 20707.91 | AA48: 10479.76 | AB48: 43008.72 | AC48: 74196.39 | AD48: 77 | AE48: 13370.38 | AF48: 12801.07 | AG48: 35406.19 | AH48: 61577.64 | AR48: =A48 -> RES | AS48: =B48 -> 98920 | AT48: =D48*1.6%+E48*6.3%+F48*28.9% -> 0 | AU48: =I48*1.6%+J48*6.3%+K48*28.9% -> 0.45824 | AV48: =N48*1.6%+O48*6.3%+P48*28.9% -> 2.30208
A49: RES | B49: 98921 | C49: 89 | D49: 16778.84 | E49: 7066.79 | F49: 55185.36 | G49: 79030.99 | H49: 95 | I49: 19539.55 | J49: 8917.09 | K49: 52358.29 | L49: 80814.93 | M49: 90 | N49: 16906.58 | O49: 12213.32 | P49: 52252.13 | Q49: 81372.03 | R49: RES | S49: 99323 | T49: 24 | U49: 4191.96 | V49: 1857.56 | W49: 481.49 | X49: 6531.01 | Y49: 24 | Z49: 5325.25 | AA49: 1435.53 | AB49: 864.17 | AC49: 7624.95 | AD49: 23 | AE49: 3538.89 | AF49: 2210.55 | AG49: 1702.12 | AH49: 7451.56 | AR49: =A49 -> RES | AS49: =B49 -> 98921 | AT49: =D49*1.6%+E49*6.3%+F49*28.9% -> 16662.238 | AU49: =I49*1.6%+J49*6.3%+K49*28.9% -> 16005.955 | AV49: =N49*1.6%+O49*6.3%+P49*28.9% -> 16140.81
A50: RES | B50: 98923 | C50: 107 | D50: 22705.43 | E50: 7342.24 | F50: 30557.67 | G50: 60605.34 | H50: 118 | I50: 29796.51 | J50: 10750.19 | K50: 32092.45 | L50: 72639.15 | M50: 125 | N50: 27953.45 | O50: 17139.85 | P50: 35673.92 | Q50: 80767.22 | R50: RES | S50: 99324 | T50: 96 | U50: 12086.71 | V50: 3779.56 | W50: 7959.71 | X50: 23825.98 | Y50: 92 | Z50: 11981.27 | AA50: 6382.14 | AB50: 7109.96 | AC50: 25473.37 | AD50: 106 | AE50: 15632.22 | AF50: 7424.08 | AG50: 6654.82 | AH50: 29711.12 | AR50: =A50 -> RES | AS50: =B50 -> 98923 | AT50: =D50*1.6%+E50*6.3%+F50*28.9% -> 9657.0146 | AU50: =I50*1.6%+J50*6.3%+K50*28.9% -> 10428.724 | AV50: =N50*1.6%+O50*6.3%+P50*28.9% -> 11836.829
A51: RES | B51: 98930 | C51: 897 | D51: 130918.4 | E51: 21878.89 | F51: 331079.71 | G51: 483877 | H51: 877 | I51: 148554.98 | J51: 65186.44 | K51: 313960.39 | L51: 527701.81 | M51: 1051 | N51: 193711.16 | O51: 81736.82 | P51: 313705.21 | Q51: 589153.19 | R51: RES | S51: 99328 | T51: 55 | U51: 8782.8 | V51: 2962.28 | W51: 1619.49 | X51: 13364.57 | Y51: 61 | Z51: 12168.64 | AA51: 5629.84 | AB51: 2870.8 | AC51: 20669.28 | AD51: 65 | AE51: 9730.36 | AF51: 8328.41 | AG51: 4046.8 | AH51: 22105.57 | AR51: =A51 -> RES | AS51: =B51 -> 98930 | AT51: =D51*1.6%+E51*6.3%+F51*28.9% -> 99155.101 | AU51: =I51*1.6%+J51*6.3%+K51*28.9% -> 97218.178 | AV51: =N51*1.6%+O51*6.3%+P51*28.9% -> 98909.604
A52: RES | B52: 98932 | C52: 547 | D52: 93689.17 | E52: 38104.55 | F52: 184041.91 | G52: 315835.63 | H52: 604 | I52: 139881.25 | J52: 50623.34 | K52: 184314.99 | L52: 374819.58 | M52: 594 | N52: 100838.81 | O52: 79506.55 | P52: 190840.01 | Q52: 371185.37 | R52: RES | S52: 99329 | T52: 2 | U52: 401.68 | V52: 123.24 | W52: 9.15 | X52: 534.07 | Y52: 2 | Z52: 188.94 | AA52: 0 | AB52: 0 | AC52: 188.94 | AD52: 3 | AE52: 301.75 | AF52: 92.38 | AG52: 0 | AH52: 394.13 | AR52: =A52 -> RES | AS52: =B52 -> 98932 | AT52: =D52*1.6%+E52*6.3%+F52*28.9% -> 57087.725 | AU52: =I52*1.6%+J52*6.3%+K52*28.9% -> 58694.403 | AV52: =N52*1.6%+O52*6.3%+P52*28.9% -> 61775.096
A53: RES | B53: 98933 | C53: 82 | D53: 14519.45 | E53: 3907.24 | F53: 23554.35 | G53: 41981.04 | H53: 94 | I53: 18016.3 | J53: 7833.6 | K53: 25476.49 | L53: 51326.39 | M53: 93 | N53: 17507.55 | O53: 9216.53 | P53: 29041.45 | Q53: 55765.53 | R53: RES | S53: 99347 | T53: 21 | U53: 2550.76 | V53: 892.64 | W53: 3348.8 | X53: 6792.2 | Y53: 22 | Z53: 3767.02 | AA53: 1601.21 | AB53: 1952.7 | AC53: 7320.93 | AD53: 26 | AE53: 4463.18 | AF53: 2184.75 | AG53: 2976.72 | AH53: 9624.65 | AR53: =A53 -> RES | AS53: =B53 -> 98933 | AT53: =D53*1.6%+E53*6.3%+F53*28.9% -> 7285.6745 | AU53: =I53*1.6%+J53*6.3%+K53*28.9% -> 8144.4832 | AV53: =N53*1.6%+O53*6.3%+P53*28.9% -> 9253.7412
A54: RES | B54: 98935 | C54: 217 | D54: 41540.33 | E54: 2812.37 | F54: 141031.86 | G54: 185384.56 | H54: 217 | I54: 40992.19 | J54: 22650.94 | K54: 129032.35 | L54: 192675.48 | M54: 255 | N54: 57796.73 | O54: 25479.65 | P54: 134416.5 | Q54: 217692.88 | R54: RES | S54: 99348 | T54: 11 | U54: 2433.84 | V54: 605.47 | W54: 653.41 | X54: 3692.72 | Y54: 14 | Z54: 3433.04 | AA54: 1148.52 | AB54: 328.35 | AC54: 4909.91 | AD54: 8 | AE54: 1924.39 | AF54: 1452.69 | AG54: 1018.87 | AH54: 4395.95 | AR54: =A54 -> RES | AS54: =B54 -> 98935 | AT54: =D54*1.6%+E54*6.3%+F54*28.9% -> 41600.032 | AU54: =I54*1.6%+J54*6.3%+K54*28.9% -> 39373.233 | AV54: =N54*1.6%+O54*6.3%+P54*28.9% -> 41376.334
A55: RES | B55: 98936 | C55: 419 | D55: 61303.25 | E55: 774.8 | F55: 157849.85 | G55: 219927.9 | H55: 445 | I55: 67429.93 | J55: 32691.1 | K55: 136788.19 | L55: 236909.22 | M55: 482 | N55: 86366.69 | O55: 35290.99 | P55: 145164.92 | Q55: 266822.6 | R55: RES | S55: 99350 | T55: 2 | U55: 483.82 | V55: 0 | W55: 1804.53 | X55: 2288.35 | Y55: 2 | Z55: 467.94 | AA55: 246.3 | AB55: 1804.53 | AC55: 2518.77 | AE55: 0 | AF55: 0 | AG55: 0 | AH55: 0 | AR55: =A55 -> RES | AS55: =B55 -> 98936 | AT55: =D55*1.6%+E55*6.3%+F55*28.9% -> 46648.271 | AU55: =I55*1.6%+J55*6.3%+K55*28.9% -> 42670.205 | AV55: =N55*1.6%+O55*6.3%+P55*28.9% -> 45557.861
A56: RES | B56: 98937 | C56: 363 | D56: 61777.89 | E56: 19292.38 | F56: 82374.94 | G56: 163445.21 | H56: 389 | I56: 86009.42 | J56: 25477.69 | K56: 84962.12 | L56: 196449.23 | M56: 415 | N56: 81618.91 | O56: 41737.13 | P56: 86941.1 | Q56: 210297.14 | R56: RES | S56: 99360 | T56: 2 | U56: 0 | V56: 404.62 | W56: 118.17 | X56: 522.79 | Y56: 4 | Z56: 1056.59 | AA56: 622.41 | AB56: 522.79 | AC56: 2201.79 | AD56: 4 | AE56: 761.04 | AF56: 984.29 | AG56: 456.86 | AH56: 2202.19 | AR56: =A56 -> RES | AS56: =B56 -> 98937 | AT56: =D56*1.6%+E56*6.3%+F56*28.9% -> 26010.224 | AU56: =I56*1.6%+J56*6.3%+K56*28.9% -> 27535.298 | AV56: =N56*1.6%+O56*6.3%+P56*28.9% -> 29061.32
A57: RES | B57: 98938 | C57: 167 | D57: 42705.27 | E57: 14151.21 | F57: 51460.77 | G57: 108317.25 | H57: 205 | I57: 66259.84 | J57: 22168.78 | K57: 53846.34 | L57: 142274.96 | M57: 202 | N57: 48957.53 | O57: 37169.29 | P57: 61754.79 | Q57: 147881.61 | R57: RES | S57: 99361 | T57: 8 | U57: 1918.5 | V57: 722.3 | W57: 674.56 | X57: 3315.36 | Y57: 9 | Z57: 2391.13 | AA57: 1312.23 | AB57: 757.43 | AC57: 4460.79 | AD57: 11 | AE57: 2205.86 | AF57: 1678.8 | AG57: 1245.16 | AH57: 5129.82 | AR57: =A57 -> RES | AS57: =B57 -> 98938 | AT57: =D57*1.6%+E57*6.3%+F57*28.9% -> 16446.973 | AU57: =I57*1.6%+J57*6.3%+K57*28.9% -> 18018.383 | AV57: =N57*1.6%+O57*6.3%+P57*28.9% -> 20972.12
A58: RES | B58: 98939 | C58: 28 | D58: 4575.73 | E58: 14182.21 | F58: 17851.02 | G58: 36608.96 | H58: 26 | I58: 5311.62 | J58: 2954.58 | K58: 30663.15 | L58: 38929.35 | M58: 33 | N58: 5881.82 | O58: 3377.21 | P58: 33260.96 | Q58: 42519.99 | R58: RES | S58: 99362 | T58: 478 | U58: 51917.8 | V58: 9904.51 | W58: 25144.58 | X58: 86966.89 | Y58: 469 | Z58: 56338.96 | AA58: 26150.54 | AB58: 18089.94 | AC58: 100579.44 | AD58: 487 | AE58: 67888.19 | AF58: 29634.86 | AG58: 23438.11 | AH58: 120961.16 | AR58: =A58 -> RES | AS58: =B58 -> 98939 | AT58: =D58*1.6%+E58*6.3%+F58*28.9% -> 6125.6357 | AU58: =I58*1.6%+J58*6.3%+K58*28.9% -> 9132.7748 | AV58: =N58*1.6%+O58*6.3%+P58*28.9% -> 9919.2908
A59: RES | B59: 98942 | C59: 1456 | D59: 250175.73 | E59: 71198.79 | F59: 477576.23 | G59: 798950.75 | H59: 1540 | I59: 284253.38 | J59: 116971.84 | K59: 480560.31 | L59: 881785.53 | M59: 1705 | N59: 349616.65 | O59: 138596.74 | P59: 516772.36 | Q59: 1004985.8 | R59: RES | S59: 99363 | T59: 4 | U59: 0 | V59: 746.16 | W59: 339.93 | X59: 1086.09 | Y59: 3 | Z59: 732.16 | AA59: 480.54 | AB59: 350.57 | AC59: 1563.27 | AD59: 3 | AE59: 545.72 | AF59: 857.18 | AG59: 247.11 | AH59: 1650.01 | AR59: =A59 -> RES | AS59: =B59 -> 98942 | AT59: =D59*1.6%+E59*6.3%+F59*28.9% -> 146507.87 | AU59: =I59*1.6%+J59*6.3%+K59*28.9% -> 150799.21 | AV59: =N59*1.6%+O59*6.3%+P59*28.9% -> 163672.67
A60: RES | B60: 98944 | C60: 1863 | D60: 298800.46 | E60: 98186.76 | F60: 559361.68 | G60: 956348.9 | H60: 1980 | I60: 383188.74 | J60: 157255.01 | K60: 556882.88 | L60: 1097326.6 | M60: 2046 | N60: 354148.53 | O60: 204733.99 | P60: 561678.17 | Q60: 1120560.7 | R60: TOTAL | T60: =SUM(T28:T59) -> 5079 | U60: =SUM(U28:U59) -> 774718.09 | V60: =SUM(V28:V59) -> 311310.2 | W60: =SUM(W28:W59) -> 1743432.5 | X60: =SUM(X28:X59) -> 2829460.7 | Y60: =SUM(Y28:Y59) -> 5702 | Z60: =SUM(Z28:Z59) -> 1117318.3 | AA60: =SUM(AA28:AA59) -> 550884.96 | ... AH60: =SUM(AH28:AH59) -> 3444457.8 | AR60: =A60 -> RES | AS60: =B60 -> 98944 | AT60: =D60*1.6%+E60*6.3%+F60*28.9% -> 172622.1 | AU60: =I60*1.6%+J60*6.3%+K60*28.9% -> 176977.24 | AV60: =N60*1.6%+O60*6.3%+P60*28.9% -> 180889.61
A61: RES | B61: 98947 | C61: 312 | D61: 56557.96 | E61: 20470.19 | F61: 90110.29 | G61: 167138.44 | H61: 366 | I61: 86333.64 | J61: 27567.39 | K61: 95384.77 | L61: 209285.8 | M61: 367 | N61: 70176.59 | O61: 49640.42 | P61: 98739.86 | Q61: 218556.87 | AR61: =A61 -> RES | AS61: =B61 -> 98947 | AT61: =D61*1.6%+E61*6.3%+F61*28.9% -> 28236.423 | AU61: =I61*1.6%+J61*6.3%+K61*28.9% -> 30684.282 | AV61: =N61*1.6%+O61*6.3%+P61*28.9% -> 32785.991
A62: RES | B62: 98948 | C62: 925 | D62: 121624.87 | E62: 70056.52 | F62: 520046.79 | G62: 711728.18 | H62: 1340 | I62: 349130.02 | J62: 80409.77 | K62: 559684.94 | L62: 989224.73 | M62: 1131 | N62: 199567.47 | O62: 169750.22 | P62: 523805.42 | Q62: 893123.11 | AR62: =A62 -> RES | AS62: =B62 -> 98948 | AT62: =D62*1.6%+E62*6.3%+F62*28.9% -> 156653.08 | AU62: =I62*1.6%+J62*6.3%+K62*28.9% -> 172400.84 | AV62: =N62*1.6%+O62*6.3%+P62*28.9% -> 165267.11
A63: RES | B63: 98951 | C63: 1000 | D63: 179522.39 | E63: 60896.61 | F63: 549661.97 | G63: 790080.97 | H63: 1126 | I63: 259702.27 | J63: 112358.87 | K63: 526379.55 | L63: 898440.69 | M63: 1156 | N63: 239727.1 | O63: 151564.87 | P63: 538652 | Q63: 929943.97 | AR63: =A63 -> RES | AS63: =B63 -> 98951 | AT63: =D63*1.6%+E63*6.3%+F63*28.9% -> 165561.15 | AU63: =I63*1.6%+J63*6.3%+K63*28.9% -> 163357.54 | AV63: =N63*1.6%+O63*6.3%+P63*28.9% -> 169054.65
A64: RES | B64: 98952 | C64: 88 | D64: 19451.42 | E64: 6964.49 | F64: 56485.1 | G64: 82901.01 | H64: 92 | I64: 21520.42 | J64: 12921.42 | K64: 60020.35 | L64: 94462.19 | M64: 92 | N64: 21380.86 | O64: 17028.05 | P64: 65874.34 | Q64: 104283.25 | AR64: =A64 -> RES | AS64: =B64 -> 98952 | AT64: =D64*1.6%+E64*6.3%+F64*28.9% -> 17074.179 | AU64: =I64*1.6%+J64*6.3%+K64*28.9% -> 18504.257 | AV64: =N64*1.6%+O64*6.3%+P64*28.9% -> 20452.545
A65: RES | B65: 98953 | C65: 638 | D65: 113002.93 | E65: 41988.3 | F65: 160442.13 | G65: 315433.36 | H65: 709 | I65: 163605.75 | J65: 50756.08 | K65: 156583.16 | L65: 370944.99 | M65: 705 | N65: 130785.23 | O65: 74436.6 | P65: 154353.2 | Q65: 359575.03 | AR65: =A65 -> RES | AS65: =B65 -> 98953 | AT65: =D65*1.6%+E65*6.3%+F65*28.9% -> 50821.085 | AU65: =I65*1.6%+J65*6.3%+K65*28.9% -> 51067.858 | AV65: =N65*1.6%+O65*6.3%+P65*28.9% -> 51390.144
A66: RES | B66: 99301 | D66: 0 | E66: 0 | F66: 0 | G66: 0 | I66: 0 | J66: 0 | K66: 0 | L66: 0 | N66: 0 | O66: 0 | P66: 0 | Q66: 0 | AR66: =A66 -> RES | AS66: =B66 -> 99301 | AT66: =D66*1.6%+E66*6.3%+F66*28.9% -> 0 | AU66: =I66*1.6%+J66*6.3%+K66*28.9% -> 0 | AV66: =N66*1.6%+O66*6.3%+P66*28.9% -> 0
A67: RES | B67: 99323 | C67: 236 | D67: 46545.98 | E67: 15682.55 | F67: 11424.79 | G67: 73653.32 | H67: 274 | I67: 73511.8 | J67: 15941.43 | K67: 10652.55 | L67: 100105.78 | M67: 268 | N67: 47512.82 | O67: 35324.95 | P67: 13539.74 | Q67: 96377.51 | AR67: =A67 -> RES | AS67: =B67 -> 99323 | AT67: =D67*1.6%+E67*6.3%+F67*28.9% -> 5034.5006 | AU67: =I67*1.6%+J67*6.3%+K67*28.9% -> 5259.0858 | AV67: =N67*1.6%+O67*6.3%+P67*28.9% -> 6898.6618
A68: RES | B68: 99324 | C68: 501 | D68: 57603.92 | E68: 16818.3 | F68: 16086.35 | G68: 90508.57 | H68: 548 | I68: 69138.39 | J68: 23164.8 | K68: 16924.21 | L68: 109227.4 | M68: 610 | N68: 83745.03 | O68: 30135.81 | P68: 16249.43 | Q68: 130130.27 | AR68: =A68 -> RES | AS68: =B68 -> 99324 | AT68: =D68*1.6%+E68*6.3%+F68*28.9% -> 6630.1708 | AU68: =I68*1.6%+J68*6.3%+K68*28.9% -> 7456.6933 | AV68: =N68*1.6%+O68*6.3%+P68*28.9% -> 7934.5618
A69: RES | B69: 99328 | C69: 338 | D69: 64868.4 | E69: 19494.67 | F69: 11124.42 | G69: 95487.49 | H69: 398 | I69: 96887.2 | J69: 28497.33 | K69: 11658.31 | L69: 137042.84 | M69: 406 | N69: 80504.02 | O69: 44183.67 | P69: 16191.57 | Q69: 140879.26 | AR69: =A69 -> RES | AS69: =B69 -> 99328 | AT69: =D69*1.6%+E69*6.3%+F69*28.9% -> 5481.016 | AU69: =I69*1.6%+J69*6.3%+K69*28.9% -> 6714.7786 | AV69: =N69*1.6%+O69*6.3%+P69*28.9% -> 8750.9993
A70: RES | B70: 99329 | C70: 18 | D70: 2274.36 | E70: 216.74 | F70: 9.15 | G70: 2500.25 | H70: 22 | I70: 3333.45 | J70: 600.01 | K70: 34.66 | L70: 3968.12 | M70: 25 | N70: 3718.29 | O70: 789.69 | P70: 267.63 | Q70: 4775.61 | AR70: =A70 -> RES | AS70: =B70 -> 99329 | AT70: =D70*1.6%+E70*6.3%+F70*28.9% -> 52.68873 | AU70: =I70*1.6%+J70*6.3%+K70*28.9% -> 101.15257 | AV70: =N70*1.6%+O70*6.3%+P70*28.9% -> 186.58818
A71: RES | B71: 99347 | C71: 134 | D71: 24172.06 | E71: 4982.61 | F71: 10068.7 | G71: 39223.37 | H71: 141 | I71: 28453.48 | J71: 8490.34 | K71: 6033.18 | L71: 42977 | M71: 183 | N71: 40092.3 | O71: 10195.01 | P71: 8557.71 | Q71: 58845.02 | AR71: =A71 -> RES | AS71: =B71 -> 99347 | AT71: =D71*1.6%+E71*6.3%+F71*28.9% -> 3610.5117 | AU71: =I71*1.6%+J71*6.3%+K71*28.9% -> 2733.7361 | AV71: =N71*1.6%+O71*6.3%+P71*28.9% -> 3756.9406
A72: RES | B72: 99348 | C72: 45 | D72: 7350.65 | E72: 1802.87 | F72: 1963.27 | G72: 11116.79 | H72: 49 | I72: 9929.61 | J72: 2839.35 | K72: 918.78 | L72: 13687.74 | M72: 45 | N72: 8901.25 | O72: 3955.74 | P72: 1752.18 | Q72: 14609.17 | AR72: =A72 -> RES | AS72: =B72 -> 99348 | AT72: =D72*1.6%+E72*6.3%+F72*28.9% -> 798.57624 | AU72: =I72*1.6%+J72*6.3%+K72*28.9% -> 603.28023 | AV72: =N72*1.6%+O72*6.3%+P72*28.9% -> 898.01164
A73: RES | B73: 99350 | C73: 4 | D73: 1016.25 | E73: 0 | F73: 1804.53 | G73: 2820.78 | H73: 6 | I73: 1054.96 | J73: 246.3 | K73: 1804.53 | L73: 3105.79 | M73: 5 | N73: 1367.87 | O73: 10.3 | P73: 0 | Q73: 1378.17 | AR73: =A73 -> RES | AS73: =B73 -> 99350 | AT73: =D73*1.6%+E73*6.3%+F73*28.9% -> 537.76917 | AU73: =I73*1.6%+J73*6.3%+K73*28.9% -> 553.90543 | AV73: =N73*1.6%+O73*6.3%+P73*28.9% -> 22.53482
A74: RES | B74: 99360 | C74: 40 | D74: 1926.19 | E74: 5113.18 | F74: 1724.59 | G74: 8763.96 | H74: 106 | I74: 26449.04 | J74: 6156.37 | K74: 888.66 | L74: 33494.07 | M74: 103 | N74: 18124.89 | O74: 9761.36 | P74: 725.26 | Q74: 28611.51 | AR74: =A74 -> RES | AS74: =B74 -> 99360 | AT74: =D74*1.6%+E74*6.3%+F74*28.9% -> 851.35589 | AU74: =I74*1.6%+J74*6.3%+K74*28.9% -> 1067.8587 | AV74: =N74*1.6%+O74*6.3%+P74*28.9% -> 1114.5641
A75: RES | B75: 99361 | C75: 99 | D75: 18801.22 | E75: 2749.01 | F75: 3850 | G75: 25400.23 | H75: 126 | I75: 30864.1 | J75: 7654.34 | K75: 2788.2 | L75: 41306.64 | M75: 146 | N75: 30553.49 | O75: 13723.53 | P75: 4761.54 | Q75: 49038.56 | AR75: =A75 -> RES | AS75: =B75 -> 99361 | AT75: =D75*1.6%+E75*6.3%+F75*28.9% -> 1586.6572 | AU75: =I75*1.6%+J75*6.3%+K75*28.9% -> 1781.8388 | AV75: =N75*1.6%+O75*6.3%+P75*28.9% -> 2729.5233
A76: RES | B76: 99362 | C76: 2152 | D76: 238971.25 | E76: 39648.82 | F76: 104010.66 | G76: 382630.73 | H76: 2289 | I76: 290441.06 | J76: 92151.42 | K76: 74798.87 | L76: 457391.35 | M76: 2465 | N76: 341908.54 | O76: 114933.73 | P76: 84846.8 | Q76: 541689.07 | AR76: =A76 -> RES | AS76: =B76 -> 99362 | AT76: =D76*1.6%+E76*6.3%+F76*28.9% -> 36380.496 | AU76: =I76*1.6%+J76*6.3%+K76*28.9% -> 32069.47 | AV76: =N76*1.6%+O76*6.3%+P76*28.9% -> 37232.087
A77: RES | B77: 99363 | C77: 8 | D77: 0 | E77: 1378.2 | F77: 339.93 | G77: 1718.13 | H77: 26 | I77: 6035.44 | J77: 1440.9 | K77: 522.72 | L77: 7999.06 | M77: 23 | N77: 4383.68 | O77: 2965.15 | P77: 247.11 | Q77: 7595.94 | AR77: =A77 -> RES | AS77: =B77 -> 99363 | AT77: =D77*1.6%+E77*6.3%+F77*28.9% -> 185.06637 | AU77: =I77*1.6%+J77*6.3%+K77*28.9% -> 338.40982 | AV77: =N77*1.6%+O77*6.3%+P77*28.9% -> 328.35812
A78: TOTAL | C78: =SUM(C42:C77) -> 24138 | D78: =SUM(D42:D77) -> 3636397.7 | E78: =SUM(E42:E77) -> 1162022.4 | F78: =SUM(F42:F77) -> 6445869 | G78: =SUM(G42:G77) -> 11244289 | H78: =SUM(H42:H77) -> 28027 | I78: =SUM(I42:I77) -> 5446333.2 | J78: =SUM(J42:J77) -> 1848363.8 | ... Q78: =SUM(Q42:Q77) -> 14023383 | AR78: =A78 -> TOTAL | AT78: =SUM(AT42:AT77) -> 1994245.9 | AU78: =SUM(AU42:AU77) -> 2062593.1 | AV78: =SUM(AV42:AV77) -> 2122589.2

Sheet 8. Past Due Balances 2020 OLD
A1: General 2020 | E1: Item a) Number of Customers by Customer Class With Past-due balances (arrearages) | O1: Item b) Past-due Balances by Customer Class and Number of Days Past-due | AZ1: Item c) Amount of Past-due Balances for Known Low-income Households and Number of Days Past-due | CL1: Item d) Amount of Past Due Balances Classified as Uncollectible | CV1: Item e) The Amount of Past-due Balances Written-off and Classified as Bad Debt, if different than item d | DG1: Item f) Number of Customer Accounts Referred to Collection Agencies | DQ1: Item f) Total Amount of Bad Debt Referred for Collection | EA1: Item f) Total Revenue to the Company from the Collection Process
O2: 43831 | S2: 43862 | W2: 43891 | AA2: 43922 | AE2: 43952 | AI2: 43983 | AM2: 44013 | AQ2: 44044 | AU2: 44075 | AZ2: 43831 | BD2: 43862 | BH2: 43891 | BL2: 43922 | BP2: 43952 | BT2: 43983 | BX2: 44013 | CB2: 44044 | CF2: 44075
A3: Zip Code | B3: Customer Class | C3: x | D3: x | E3: 43831 | F3: 43862 | G3: 43891 | H3: 43922 | I3: 43952 | J3: 43983 | K3: 44013 | L3: 44044 | M3: 44075 | N3: x | O3: 30 Days | P3: 60 Days | Q3: 90 Days + | R3: Total Arrearages | S3: 30 Days | T3: 60 Days | U3: 90 Days + | V3: Total Arrearages | W3: 30 Days | X3: 60 Days | Y3: 90 Days + | Z3: Total Arrearages | AA3: 30 Days | AB3: 60 Days | AC3: 90 Days + | AD3: Total Arrearages | AE3: 30 Days | AF3: 60 Days | AG3: 90 Days + | AH3: Total Arrearages | AI3: 30 Days | AJ3: 60 Days | AK3: 90 Days + | AL3: Total Arrearages | AM3: 30 Days | AN3: 60 Days | AO3: 90 Days + | AP3: Total Arrearages | AQ3: 30 Days | AR3: 60 Days | AS3: 90 Days + | AT3: Total Arrearages | AU3: 30 Days | AV3: 60 Days | AW3: 90 Days + | AX3: Total Arrearages | AZ3: 30 Days | BA3: 60 Days | BB3: 90 Days + | BC3: Total Arrearages | BD3: 30 Days | BE3: 60 Days | BF3: 90 Days + | BG3: Total Arrearages | BH3: 30 Days | BI3: 60 Days | BJ3: 90 Days + | BK3: Total Arrearages | BL3: 30 Days | BM3: 60 Days | BN3: 90 Days + | BO3: Total Arrearages | BP3: 30 Days | BQ3: 60 Days | BR3: 90 Days + | BS3: Total Arrearages | BT3: 30 Days | BU3: 60 Days | BV3: 90 Days + | BW3: Total Arrearages | BX3: 30 Days | BY3: 60 Days | BZ3: 90 Days + | CA3: Total Arrearages | CB3: 30 Days | CC3: 60 Days | CD3: 90 Days + | CE3: Total Arrearages | CF3: 30 Days | CG3: 60 Days | CH3: 90 Days + | CI3: Total Arrearages | CL3: 43831 | CM3: 43862 | CN3: 43891 | CO3: 43922 | CP3: 43952 | CQ3: 43983 | CR3: 44013 | CS3: 44044 | CT3: 44075 | CV3: CLASS | CW3: 43831 | CX3: 43862 | CY3: 43891 | CZ3: 43922 | DA3: 43952 | DB3: 43983 | DC3: 44013 | DD3: 44044 | DE3: 44075 | DG3: 43831 | DH3: 43862 | DI3: 43891 | DJ3: 43922 | DK3: 43952 | DL3: 43983 | DM3: 44013 | DN3: 44044 | DO3: 44075 | DQ3: 43831 | DR3: 43862 | DS3: 43891 | DT3: 43922 | DU3: 43952 | DV3: 43983 | DW3: 44013 | DX3: 44044 | DY3: 44075 | EA3: 43831 | EB3: 43862 | EC3: 43891 | ED3: 43922 | EE3: 43952 | EF3: 43983 | EG3: 44013 | EH3: 44044 | EI3: 44075
A4: 98901 | B4: COM | C4: =A4&B4 -> 98901COM | E4: 131 | F4: 132 | G4: 145 | H4: 173 | I4: 221 | J4: 160 | K4: 137 | L4: 152 | M4: 156 | O4: 19871.38 | P4: 7897.63 | Q4: 24242.65 | R4: 52011.66 | S4: 53580.83 | T4: 9976.46 | U4: 27438.96 | V4: 90996.25 | W4: 48277.95 | X4: 17941.85 | Y4: 22854.02 | Z4: 89073.82 | AA4: 71009.6 | AB4: 29051.57 | AC4: 36760.09 | AD4: 136821.26 | AE4: 86883.42 | AF4: 34985.09 | AG4: 49645.24 | AH4: 171513.75 | AI4: 39740.66 | AJ4: 29311.53 | AK4: 66630.47 | AL4: 135682.66 | AM4: 38006.67 | AN4: 14078.08 | AO4: 65366.26 | AP4: 117451.01 | AQ4: 29853.1 | AR4: 15834.18 | AS4: 62985.51 | AT4: 108672.79 | AU4: 41939.18 | AV4: 15055.03 | AW4: 60553.4 | AX4: 117547.61 | AZ4: 42.71 | BA4: 41.08 | BC4: 83.79 | BD4: 48.96 | BE4: 42.71 | BF4: 41.08 | BG4: 132.75 | BH4: 56.74 | BI4: 48.96 | BJ4: 83.79 | BK4: 189.49 | BL4: 50.42 | BM4: 56.74 | BN4: 132.75 | BO4: 239.91 | BP4: 44.7 | BQ4: 50.42 | BR4: 189.49 | BS4: 284.61 | BT4: 24.09 | BU4: 44.7 | BV4: 189.91 | BW4: 258.7 | BX4: 23.42 | BY4: 24.09 | BZ4: 234.61 | CA4: 282.12 | CB4: 29.16 | CC4: 23.42 | CD4: 184.25 | CE4: 236.83 | CF4: 33.34 | CG4: 29.16 | CH4: 207.67 | CI4: 270.17 | CJ4: =VLOOKUP($C4,#REF!,#REF!,FALSE) -> #REF! | CL4: 6680.653 | CM4: 9123.4953 | CN4: 9211.7238 | CO4: 15409.934 | CP4: 18878.318 | CQ4: 22984.908 | CR4: 21490.276 | CS4: 22157.377 | CT4: 21296.568 | CV4: RES | CW4: 155378.03 | CX4: 91404.44 | CY4: 77084.33 | CZ4: 161847.29 | DA4: 69802.26 | DB4: 66491.04 | DC4: 72376.07 | DD4: 109624.03 | DE4: 76241.97 | DG4: 2 | DH4: 2 | DI4: 3 | DJ4: 3 | DK4: 1 | DQ4: 3400.92 | DR4: 1528.25 | DS4: 1009.25 | DT4: 25469.44 | DU4: 361.46 | EC4: 215.93 | EE4: 361.46
A5: 98902 | B5: COM | C5: =A5&B5 -> 98902COM | E5: 197 | F5: 198 | G5: 189 | H5: 218 | I5: 275 | J5: 206 | K5: 187 | L5: 219 | M5: 208 | O5: 56081.52 | P5: 11010.14 | Q5: 15451.95 | R5: 82543.61 | S5: 126371.49 | T5: 13179.05 | U5: 17580.15 | V5: 157130.69 | W5: 34416.43 | X5: 16097.77 | Y5: 20292.23 | Z5: 70806.43 | AA5: 67882.3 | AB5: 22425.07 | AC5: 28833.05 | AD5: 119140.42 | AE5: 82008.83 | AF5: 27881.35 | AG5: 44079.42 | AH5: 153969.6 | AI5: 39115.86 | AJ5: 22652.96 | AK5: 55917.07 | AL5: 117685.89 | AM5: 37473.1 | AN5: 19881.82 | AO5: 51286.11 | AP5: 108641.03 | AQ5: 60464.87 | AR5: 21310.31 | AS5: 56987.72 | AT5: 138762.9 | AU5: 44660.96 | AV5: 22729.12 | AW5: 61819.4 | AX5: 129209.48 | AZ5: 40.74 | BC5: 40.74 | BD5: 29.81 | BE5: 40.74 | BG5: 70.55 | BH5: 33.2 | BI5: 29.81 | BJ5: 40.74 | BK5: 103.75 | BL5: 122.34 | BM5: 33.2 | BN5: 70.55 | BO5: 226.09 | BP5: 110.62 | BQ5: 122.34 | BR5: 103.75 | BS5: 336.71 | BT5: 55.19 | BU5: 110.62 | BV5: 226.09 | BW5: 391.9 | BX5: 69.27 | BY5: 55.19 | BZ5: 336.71 | CA5: 461.17 | CB5: 87.53 | CC5: 69.27 | CD5: 391.9 | CE5: 548.7 | CF5: 80.19 | CG5: 87.53 | CH5: 461.17 | CI5: 628.89 | CJ5: 0.24399667 | CL5: 5618.0792 | CM5: 9221.8192 | CN5: 7917.4582 | CO5: 12496.834 | CP5: 16704.887 | CQ5: 19304.53 | CR5: 17758.213 | CS5: 21520.255 | CT5: 22300.768 | CV5: COM | CW5: 2753.02 | CX5: 9149.27 | CY5: 12487.38 | CZ5: 14610.42 | DA5: 12690.61 | DB5: 6158.09 | DC5: 7360.64 | DD5: 6977.57 | DE5: 14974.03 | DG5: 4 | DH5: 4 | DI5: 17 | DJ5: 5 | DK5: 1 | DL5: 4 | DQ5: 227.95 | DR5: 12847.79 | DS5: 12855.73 | DT5: 693.93 | DU5: 260.59 | DV5: 210.46 | EA5: 204.97 | EC5: 366.14 | ED5: 262.16 | EF5: 155.42 | EG5: 83.93
A6: 98903 | B6: COM | C6: =A6&B6 -> 98903COM | E6: 123 | F6: 109 | G6: 105 | H6: 119 | I6: 188 | J6: 112 | K6: 117 | L6: 134 | M6: 124 | O6: 22768.85 | P6: 7604.5 | Q6: 7617.7 | R6: 37991.05 | S6: 62967.03 | T6: 4976.34 | U6: 6658.94 | V6: 74602.31 | W6: 14427.86 | X6: 9455.36 | Y6: 6303.98 | Z6: 30187.2 | AA6: 34080.48 | AB6: 10589.12 | AC6: 11180.85 | AD6: 55850.45 | AE6: 57986.56 | AF6: 15693.43 | AG6: 19537.11 | AH6: 93217.1 | AI6: 18745.46 | AJ6: 12483.44 | AK6: 22869.82 | AL6: 54098.72 | AM6: 17601.8 | AN6: 3910.46 | AO6: 33199.92 | AP6: 54712.18 | AQ6: 19669.93 | AR6: 18272.7 | AS6: 34813.48 | AT6: 72756.11 | AU6: 23168.57 | AV6: 4663.56 | AW6: 42563.61 | AX6: 70395.74 | CJ6: 0.26286604 | CL6: 2767.5383 | CM6: 3960.1853 | CN6: 2984.8866 | CO6: 5282.1529 | CP6: 8223.6545 | CQ6: 8225.4179 | CR6: 10619.978 | CS6: 13059.721 | CT6: 14404.337 | DG6: 5 | DH6: 1 | DI6: 1 | DJ6: 4 | DK6: 1 | DL6: 2 | DQ6: 817.64 | DR6: 142.22 | DS6: 154.34 | DT6: 976.96 | DU6: 385.63 | DV6: 533.4 | EA6: 746.69 | EC6: 154.34 | ED6: 478.24 | EE6: 385.63 | EF6: 101.99
A7: 98908 | B7: COM | C7: =A7&B7 -> 98908COM | E7: 100 | F7: 117 | G7: 126 | H7: 144 | I7: 142 | J7: 104 | K7: 89 | L7: 123 | M7: 117 | O7: 24914.74 | P7: 1417.66 | Q7: 1482.68 | R7: 27815.08 | S7: 13416.06 | T7: 2358.05 | U7: 2511.35 | V7: 18285.46 | W7: 19122.52 | X7: 5305.24 | Y7: 2841.91 | Z7: 27269.67 | AA7: 21192.33 | AB7: 7382.52 | AC7: 5830.49 | AD7: 34405.34 | AE7: 42531.53 | AF7: 11285.05 | AG7: 9525.78 | AH7: 63342.36 | AI7: 16892.88 | AJ7: 5857.23 | AK7: 13310.88 | AL7: 36060.99 | AM7: 9242.42 | AN7: 4737.16 | AO7: 13686.29 | AP7: 27665.87 | AQ7: 22069.54 | AR7: 6286.33 | AS7: 16209.75 | AT7: 44565.62 | AU7: 17866.4 | AV7: 6732.99 | AW7: 15270.36 | AX7: 39869.75 | AZ7: 82.16 | BA7: 29.84 | BC7: 112 | BD7: 74.84 | BE7: 82.16 | BF7: 29.84 | BG7: 186.84 | BH7: 73.81 | BK7: 73.81 | BL7: 67.88 | BM7: 73.81 | BO7: 141.69 | BP7: 42.04 | BQ7: 67.88 | BR7: 73.81 | BS7: 183.73 | BT7: 24.13 | BU7: 42.04 | BV7: 141.69 | BW7: 207.86 | BX7: 45.72 | BY7: 24.13 | BZ7: 183.73 | CA7: 253.58 | CB7: 50.87 | CC7: 45.72 | CD7: 207.86 | CE7: 304.45 | CF7: 50.18 | CG7: 50.87 | CH7: 253.58 | CI7: 354.63 | CJ7: 0.2842874 | CL7: 1027.7791 | CM7: 1210.0733 | CN7: 1853.2718 | CO7: 3031.4297 | CP7: 4637.8175 | CQ7: 4850.8456 | CR7: 4673.1373 | CS7: 6275.5162 | CT7: 5750.6895 | DH7: 1 | DI7: 2 | DJ7: 3 | DL7: 2 | DR7: 258.25 | DS7: 584.7 | DT7: 866.82 | DV7: 740.9 | EB7: 258.25 | EC7: 209.33 | ED7: 240.28 | EF7: 740.9
A8: 98920 | B8: COM | C8: =A8&B8 -> 98920COM | E8: 1 | J8: 2 | O8: 35.7 | P8: 0 | Q8: 0 | R8: 35.7 | AI8: 53.06 | AJ8: 0 | AK8: 0 | AL8: 53.06 | CJ8: 0.28728463 | CL8: 0.85823928 | CQ8: 1.534743
A9: 98921 | B9: COM | C9: =A9&B9 -> 98921COM | E9: 1 | F9: 2 | G9: 2 | H9: 5 | I9: 4 | J9: 2 | K9: 4 | L9: 3 | M9: 3 | O9: 11.8 | P9: 11.68 | Q9: 13.15 | R9: 36.63 | S9: 161.8 | T9: 11.8 | U9: 24.83 | V9: 198.43 | W9: 146.79 | X9: 161.8 | Y9: 36.63 | Z9: 345.22 | AA9: 918.22 | AB9: 12.04 | AC9: 48.55 | AD9: 978.81 | AE9: 519.37 | AF9: 136.16 | AG9: 60.59 | AH9: 716.12 | AI9: 73.2 | AJ9: 113.5 | AK9: 196.75 | AL9: 383.45 | AM9: 292.13 | AN9: 29.87 | AO9: 83.69 | AP9: 405.69 | AQ9: 217.55 | AR9: 186.1 | AS9: 95.24 | AT9: 498.89 | AU9: 216.72 | AV9: 104.19 | AW9: 124.89 | AX9: 445.8 | CJ9: 0.29347129 | CL9: 4.0396567 | CM9: 11.983693 | CN9: 29.070748 | CO9: 47.934722 | CP9: 40.521968 | CQ9: 68.691376 | CR9: 35.864705 | CS9: 50.683103 | CT9: 52.160528 | DL9: 2 | DV9: 323.73 | EF9: 323.73
A10: 98923 | B10: COM | C10: =A10&B10 -> 98923COM | E10: 16 | F10: 9 | G10: 18 | H10: 6 | I10: 5 | J10: 18 | K10: 15 | L10: 16 | M10: 16 | O10: 17959.08 | P10: 31.33 | Q10: 255.2 | R10: 18245.61 | S10: 537.76 | T10: 47.2 | U10: 286.53 | V10: 871.49 | W10: 16599.05 | X10: 66.75 | Y10: 183.73 | Z10: 16849.53 | AA10: 91.78 | AB10: 110.2 | AC10: 250.48 | AD10: 452.46 | AE10: 70.62 | AF10: 77.75 | AG10: 318.49 | AH10: 466.86 | AI10: 7533.87 | AJ10: 70.62 | AK10: 396.24 | AL10: 8000.73 | AM10: 6002.33 | AN10: 42.71 | AO10: 377.8 | AP10: 6422.84 | AQ10: 7712.15 | AR10: 45.18 | AS10: 319.02 | AT10: 8076.35 | AU10: 8746.24 | AV10: 71.71 | AW10: 364.2 | AX10: 9182.15 | CJ10: 0.29479967 | CL10: 494.29869 | CM10: 90.21886 | CN10: 598.08661 | CO10: 83.612057 | CP10: 98.275407 | CQ10: 339.69606 | CR10: 298.54343 | CS10: 322.46673 | CT10: 330.36683 | DG10: 1 | DQ10: 106.87
A11: 98930 | B11: COM | C11: =A11&B11 -> 98930COM | E11: 27 | F11: 27 | G11: 37 | H11: 47 | I11: 41 | J11: 35 | K11: 40 | L11: 30 | M11: 44 | O11: 3937.2 | P11: 207.64 | Q11: 1005.96 | R11: 5150.8 | S11: 3368.57 | T11: 872.13 | U11: 845.24 | V11: 5085.94 | W11: 6174.01 | X11: 634.42 | Y11: 718.11 | Z11: 7526.54 | AA11: 10506.12 | AB11: 5266.98 | AC11: 1232.67 | AD11: 17005.77 | AE11: 18016.66 | AF11: 5883.63 | AG11: 5651.82 | AH11: 29552.11 | AI11: 6772.97 | AJ11: 4121.62 | AK11: 8529.95 | AL11: 19424.54 | AM11: 3828.79 | AN11: 3397.63 | AO11: 10724.7 | AP11: 17951.12 | AQ11: 4004.54 | AR11: 2298.98 | AS11: 11177.95 | AT11: 17481.47 | AU11: 7780.57 | AV11: 3529.16 | AW11: 13198.62 | AX11: 24508.35 | CJ11: 0.31933271 | CL11: 345.69247 | CM11: 377.73042 | CN11: 448.39332 | CO11: 1164.1248 | CP11: 2496.745 | CQ11: 3019.9837 | CR11: 3533.7121 | CS11: 3856.9734 | CT11: 4626.6464 | DI11: 1 | DK11: 1 | DL11: 1 | DS11: 128.23 | DU11: 116.78 | DV11: 87.06 | EC11: 128.23 | EE11: 116.78 | EF11: 87.06
A12: 98932 | B12: COM | C12: =A12&B12 -> 98932COM | E12: 29 | F12: 21 | G12: 22 | H12: 27 | I12: 20 | J12: 39 | K12: 19 | L12: 44 | M12: 26 | O12: 34084.29 | P12: 473.24 | Q12: 1162.68 | R12: 35720.21 | S12: 6747.19 | T12: 1739.15 | U12: 925.66 | V12: 9412 | W12: 4186.74 | X12: 950 | Y12: 1372.21 | Z12: 6508.95 | AA12: 7151.55 | AB12: 799.06 | AC12: 2041.27 | AD12: 9991.88 | AE12: 5209.73 | AF12: 2122.8 | AG12: 2780.96 | AH12: 10113.49 | AI12: 25617.11 | AJ12: 1969.69 | AK12: 4809.93 | AL12: 32396.73 | AM12: 11868.98 | AN12: 640.97 | AO12: 3789.83 | AP12: 16299.78 | AQ12: 28353.4 | AR12: 1284.5 | AS12: 4409.18 | AT12: 34047.08 | AU12: 23595.91 | AV12: 1355.28 | AW12: 5243.27 | AX12: 30194.46 | CJ12: 0.31770853 | CL12: 1121.8888 | CM12: 568.76641 | CN12: 583.77628 | CO12: 904.3337 | CP12: 1077.2483 | CQ12: 2305.8422 | CR12: 1529.0687 | CS12: 2303.9982 | CT12: 2326.2018 | DG12: 3 | DK12: 1 | DQ12: 4434.07 | DU12: 132.18 | EE12: 132.18
A13: 98933 | B13: COM | C13: =A13&B13 -> 98933COM | E13: 6 | F13: 6 | G13: 5 | H13: 6 | I13: 5 | J13: 4 | K13: 7 | L13: 8 | M13: 5 | O13: 3864.65 | P13: 273.81 | Q13: 49.14 | R13: 4187.6 | S13: 3224.29 | T13: 3476.65 | U13: 0 | V13: 6700.94 | W13: 696.79 | X13: 340.58 | Y13: 255.24 | Z13: 1292.61 | AA13: 1601.96 | AB13: 323.68 | AC13: 581.51 | AD13: 2507.15 | AE13: 2340.63 | AF13: 565.86 | AG13: 892.39 | AH13: 3798.88 | AI13: 898.59 | AJ13: 238.19 | AK13: 1203.87 | AL13: 2340.65 | AM13: 1433.43 | AN13: 862.59 | AO13: 1442.06 | AP13: 3738.08 | AQ13: 3542.54 | AR13: 421.55 | AS13: 1814.66 | AT13: 5778.75 | AU13: 2355.16 | AV13: 673.07 | AW13: 2195.97 | AX13: 5224.2 | CL13: 119.12037 | CM13: 367.14007 | CN13: 120.72194 | CO13: 249.83509 | CP13: 357.61206 | CQ13: 397.83084 | CR13: 533.72174 | CS13: 711.2703 | CT13: 801.20603
A14: 98935 | B14: COM | C14: =A14&B14 -> 98935COM | E14: 4 | F14: 6 | G14: 6 | H14: 5 | I14: 13 | J14: 5 | K14: 5 | L14: 5 | M14: 4 | O14: 149.96 | P14: 671.54 | Q14: 581.23 | R14: 1402.73 | S14: 754.6 | T14: 654.15 | U14: 311.23 | V14: 1719.98 | W14: 954.7 | X14: 546.48 | Y14: 365.42 | Z14: 1866.6 | AA14: 502.21 | AB14: 695.09 | AC14: 911.9 | AD14: 2109.2 | AE14: 1843.16 | AF14: 225.76 | AG14: 670.41 | AH14: 2739.33 | AI14: 253.45 | AJ14: 202.26 | AK14: 896.17 | AL14: 1351.88 | AM14: 289.37 | AN14: 0 | AO14: 1276.4 | AP14: 1565.77 | AQ14: 90.52 | AR14: 321.67 | AS14: 1192.57 | AT14: 1604.76 | AU14: 158.39 | AV14: 0 | AW14: 1513.61 | AX14: 1672 | CL14: 177.83509 | CM14: 149.60689 | CN14: 176.75503 | CO14: 334.71073 | CP14: 258.83263 | CQ14: 286.07286 | CR14: 385.15124 | CS14: 407.8232 | CT14: 484.68332
A15: 98936 | B15: COM | C15: =A15&B15 -> 98936COM | E15: 13 | F15: 17 | G15: 22 | H15: 21 | I15: 20 | J15: 21 | K15: 18 | L15: 21 | M15: 27 | O15: 1104.69 | P15: 78.91 | Q15: 1520.2 | R15: 2703.8 | S15: 3151.94 | T15: 633.25 | U15: 1433.68 | V15: 5218.87 | W15: 2444.51 | X15: 1857.26 | Y15: 1627.91 | Z15: 5929.68 | AA15: 3530.94 | AB15: 3133.97 | AC15: 2022.93 | AD15: 8687.84 | AE15: 1453.39 | AF15: 2537.97 | AG15: 5901.48 | AH15: 9892.84 | AI15: 2778.91 | AJ15: 1259.65 | AK15: 8299.19 | AL15: 12337.75 | AM15: 3827.82 | AN15: 2571.81 | AO15: 9163.91 | AP15: 15563.54 | AQ15: 2117.52 | AR15: 1482.42 | AS15: 6712.12 | AT15: 10312.06 | AU15: 12683.62 | AV15: 1442.45 | AW15: 8194.54 | AX15: 22320.61 | CL15: 393.50193 | CM15: 496.234 | CN15: 675.97277 | CO15: 961.0758 | CP15: 1892.4527 | CQ15: 2613.9906 | CR15: 3011.6491 | CS15: 2315.6924 | CT15: 3008.3816 | DJ15: 2 | DT15: 103.59 | ED15: 62.32
A16: 98937 | B16: COM | C16: =A16&B16 -> 98937COM | E16: 28 | F16: 22 | G16: 34 | H16: 35 | I16: 28 | J16: 37 | K16: 32 | L16: 36 | M16: 22 | O16: 2201.03 | P16: 805.92 | Q16: 721.38 | R16: 3728.33 | S16: 3729.78 | T16: 628.91 | U16: 315.98 | V16: 4674.67 | W16: 4471.17 | X16: 2079.24 | Y16: 157.9 | Z16: 6708.31 | AA16: 5410.5 | AB16: 2269.38 | AC16: 494.42 | AD16: 8174.3 | AE16: 4693.5 | AF16: 2128.39 | AG16: 1020.84 | AH16: 7842.73 | AI16: 3333.54 | AJ16: 2347.39 | AK16: 2460.92 | AL16: 8141.85 | AM16: 6046.68 | AN16: 1430.96 | AO16: 3620.15 | AP16: 11097.79 | AQ16: 5032.12 | AR16: 1881.12 | AS16: 3254.81 | AT16: 10168.05 | AU16: 2961.69 | AV16: 1481.18 | AW16: 2739.54 | AX16: 7182.41 | CL16: 267.69756 | CM16: 241.10847 | CN16: 376.02276 | CO16: 523.04709 | CP16: 557.26531 | CQ16: 1001.3264 | CR16: 1359.8255 | CS16: 1324.032 | CT16: 1044.9619 | DG16: 1 | DJ16: 2 | DQ16: 8.59 | DT16: 320.49 | EG16: 6.44
A17: 98938 | B17: COM | C17: =A17&B17 -> 98938COM | E17: 19 | F17: 9 | G17: 4 | H17: 10 | I17: 10 | J17: 31 | K17: 18 | L17: 21 | M17: 31 | O17: 28703.41 | P17: 7.92 | Q17: 0 | R17: 28711.33 | S17: 1460.29 | T17: 525.87 | U17: 7.92 | V17: 1994.08 | W17: 653.6 | X17: 28.9 | Y17: 0 | Z17: 682.5 | AA17: 2235.35 | AB17: 413.02 | AC17: 11.51 | AD17: 2659.88 | AE17: 8154.4 | AF17: 531.61 | AG17: 407.47 | AH17: 9093.48 | AI17: 44246.12 | AJ17: 389.25 | AK17: 904.91 | AL17: 45540.28 | AM17: 27696.04 | AN17: 189.79 | AO17: 914.92 | AP17: 28800.75 | AQ17: 27749.76 | AR17: 321.03 | AS17: 723.93 | AT17: 28794.72 | AU17: 28169.52 | AV17: 5734.07 | AW17: 53.25 | AX17: 33956.84 | CL17: 690.45807 | CM17: 87.632328 | CN17: 24.024445 | CO17: 118.02124 | CP17: 381.41988 | CQ17: 1575.6645 | CR17: 1132.806 | CS17: 1036.9539 | CT17: 1093.1765
A18: 98942 | B18: COM | C18: =A18&B18 -> 98942COM | E18: 61 | F18: 64 | G18: 61 | H18: 73 | I18: 70 | J18: 58 | K18: 46 | L18: 56 | M18: 63 | O18: 12032.12 | P18: 1888.13 | Q18: 1227.37 | R18: 15147.62 | S18: 50682.28 | T18: 3561.83 | U18: 2431.76 | V18: 56675.87 | W18: 9946.74 | X18: 2883.43 | Y18: 3116.66 | Z18: 15946.83 | AA18: 11559.45 | AB18: 5429.91 | AC18: 5479.66 | AD18: 22469.02 | AE18: 50847.74 | AF18: 6926.61 | AG18: 9794.77 | AH18: 67569.12 | AI18: 43936.06 | AJ18: 5152.35 | AK18: 14754.35 | AL18: 63842.76 | AM18: 7176.09 | AN18: 4418.02 | AO18: 12609.04 | AP18: 24203.15 | AQ18: 9350.26 | AR18: 5557.96 | AS18: 16123.68 | AT18: 31031.9 | AU18: 13554.32 | AV18: 5995.18 | AW18: 19525.29 | AX18: 39074.79 | CL18: 682.04274 | CM18: 2439.0431 | CN18: 1405.8815 | CO18: 2422.9475 | CP18: 4683.9702 | CQ18: 6001.8174 | CR18: 4268.3068 | CS18: 5834.5226 | CT18: 6947.5552 | DI18: 1 | DJ18: 3 | DS18: 83.67 | DT18: 189.48 | EC18: 83.67 | EG18: 118.91
A19: 98944 | B19: COM | C19: =A19&B19 -> 98944COM | E19: 102 | F19: 109 | G19: 116 | H19: 141 | I19: 139 | J19: 121 | K19: 115 | L19: 122 | M19: 148 | O19: 28613.88 | P19: 7264.59 | Q19: 16028.35 | R19: 51906.82 | S19: 29333.66 | T19: 8231.58 | U19: 15798.7 | V19: 53363.94 | W19: 28365.22 | X19: 13838.46 | Y19: 18015.38 | Z19: 60219.06 | AA19: 38176.02 | AB19: 14581.69 | AC19: 27376.56 | AD19: 80134.27 | AE19: 25168.18 | AF19: 15323.14 | AG19: 37689.21 | AH19: 78180.53 | AI19: 24913.62 | AJ19: 12061.23 | AK19: 45457.88 | AL19: 82432.73 | AM19: 29855.38 | AN19: 8886 | AO19: 48374.44 | AP19: 87115.82 | AQ19: 31184.6 | AR19: 9916.15 | AS19: 50435.11 | AT19: 91535.86 | AU19: 44021.59 | AV19: 13597.29 | AW19: 51075.36 | AX19: 108694.24 | CL19: 4897.1298 | CM19: 5397.1605 | CN19: 6916.3906 | CO19: 10363.582 | CP19: 12483.096 | CQ19: 14999.917 | CR19: 15842.006 | CS19: 17737.331 | CT19: 18233.27 | DG19: 1 | DH19: 3 | DI19: 1 | DJ19: 4 | DN19: 1 | DQ19: 74.38 | DR19: 412.46 | DS19: 198.41 | DT19: 2420.24 | DX19: 1155.9 | EB19: 224.58 | ED19: 16.75
A20: 98947 | B20: COM | C20: =A20&B20 -> 98947COM | E20: 24 | F20: 16 | G20: 12 | H20: 12 | I20: 14 | J20: 14 | K20: 18 | L20: 23 | M20: 21 | O20: 11460.87 | P20: 733.36 | Q20: 277.69 | R20: 12471.92 | S20: 4006.02 | T20: 1486.4 | U20: 154.83 | V20: 5647.25 | W20: 8745.89 | X20: 1847.37 | Y20: 663.19 | Z20: 11256.45 | AA20: 2453.94 | AB20: 2936.83 | AC20: 1541.56 | AD20: 6932.33 | AE20: 2095.96 | AF20: 2044.01 | AG20: 2638.66 | AH20: 6778.63 | AI20: 4199.68 | AJ20: 1991.46 | AK20: 3094.63 | AL20: 9285.77 | AM20: 3360.31 | AN20: 1627.78 | AO20: 4321.87 | AP20: 9309.96 | AQ20: 4113.45 | AR20: 1531.68 | AS20: 4242.07 | AT20: 9887.2 | AU20: 4822.47 | AV20: 1338.62 | AW20: 3321.27 | AX20: 9482.36 | CL20: 380.589 | CM20: 276.24261 | CN20: 627.9074 | CO20: 769.09484 | CP20: 943.04341 | CQ20: 1184.6531 | CR20: 1499.1133 | CS20: 1586.8701 | CT20: 1264.4133
A21: 98948 | B21: COM | C21: =A21&B21 -> 98948COM | E21: 82 | F21: 82 | G21: 61 | H21: 83 | I21: 115 | J21: 94 | K21: 123 | L21: 106 | M21: 95 | O21: 23670.59 | P21: 9817.95 | Q21: 9527.94 | R21: 43016.48 | S21: 45406.29 | T21: 10392.76 | U21: 15955.05 | V21: 71754.1 | W21: 11196.65 | X21: 4388.62 | Y21: 8562.34 | Z21: 24147.61 | AA21: 18721.49 | AB21: 8485.51 | AC21: 11791.56 | AD21: 38998.56 | AE21: 19917.3 | AF21: 18314.64 | AG21: 16273.44 | AH21: 54505.38 | AI21: 10461.57 | AJ21: 19008.72 | AK21: 22432.55 | AL21: 51902.84 | AM21: 29948.2 | AN21: 4265.13 | AO21: 34840.47 | AP21: 69053.8 | AQ21: 21391.13 | AR21: 7718.58 | AS21: 26566.07 | AT21: 55675.78 | AU21: 36008.3 | AV21: 11610.49 | AW21: 31064.86 | AX21: 78683.65 | AZ21: 4263.35 | BA21: 1046.4 | BC21: 5309.75 | BD21: 5183.12 | BE21: 3204.41 | BF21: 1046.4 | BG21: 9433.93 | BH21: 2706.94 | BI21: 3.75 | BK21: 2710.69 | BL21: 6015.17 | BM21: 2364.95 | BO21: 8380.12 | BP21: 5908.2 | BQ21: 5951.28 | BS21: 11859.48 | BT21: 2964.8 | BU21: 7647.2 | BV21: 3918.47 | BW21: 14530.47 | BX21: 7976.19 | BY21: 2914.57 | BZ21: 11044.5 | CA21: 21935.26 | CB21: 2300.29 | CC21: 1696.12 | CD21: 2847.77 | CE21: 6844.18 | CF21: 4100.83 | CG21: 2113.24 | CH21: 4316.18 | CI21: 10530.25 | CL21: 3362.1703 | CM21: 6099.8945 | CN21: 3014.4419 | CO21: 4727.9073 | CP21: 6365.0271 | CQ21: 8365.3402 | CR21: 11508.608 | CS21: 9672.3797 | CT21: 11544.729 | DG21: 1 | DH21: 1 | DI21: 7 | DJ21: 2 | DQ21: 0.32 | DR21: 244.27 | DS21: 2508.01 | DT21: 975.37 | EA21: 0.32
A22: 98951 | B22: COM | C22: =A22&B22 -> 98951COM | E22: 88 | F22: 114 | G22: 85 | H22: 88 | I22: 86 | J22: 109 | K22: 81 | L22: 75 | M22: 88 | O22: 64362.45 | P22: 1922.59 | Q22: 1690.43 | R22: 67975.47 | S22: 76535.55 | T22: 21184.04 | U22: 3957.03 | V22: 101676.62 | W22: 37253.46 | X22: 30018.66 | Y22: 20585.01 | Z22: 87857.13 | AA22: 43359.49 | AB22: 18643.46 | AC22: 8806.75 | AD22: 70809.7 | AE22: 38671.96 | AF22: 12576.05 | AG22: 9223.65 | AH22: 60471.66 | AI22: 26262.47 | AJ22: 8482.65 | AK22: 16803.69 | AL22: 51548.81 | AM22: 23891.44 | AN22: 17779.52 | AO22: 19019.06 | AP22: 60690.02 | AQ22: 30546.7 | AR22: 10574.39 | AS22: 22148.74 | AT22: 63269.83 | AU22: 25371.59 | AV22: 6949.61 | AW22: 23036.6 | AX22: 55357.8 | AZ22: 296.75 | BA22: 106.13 | BB22: 61.51 | BC22: 464.39 | BD22: 138.28 | BE22: 284.01 | BF22: 167.64 | BG22: 589.93 | BH22: 198.38 | BI22: 28.57 | BJ22: 207.35 | BK22: 434.3 | BL22: 187.22 | BM22: 198.38 | BN22: 235.92 | BO22: 621.52 | BP22: 170.1 | BQ22: 187.22 | BR22: 434.3 | BS22: 791.62 | BT22: 108.53 | BU22: 128.36 | BV22: 105.51 | BW22: 342.4 | BX22: 113.23 | BY22: 108.53 | BZ22: 233.87 | CA22: 455.63 | CB22: 116.95 | CC22: 113.23 | CD22: 342.4 | CE22: 572.58 | CF22: 30.46 | CG22: 116.95 | CH22: 455.63 | CI22: 603.04 | CL22: 2052.405 | CM22: 4967.1194 | CN22: 9346.3794 | CO22: 5606.5842 | CP22: 4520.5597 | CQ22: 6351.2317 | CR22: 7672.0194 | CS22: 8736.6338 | CT22: 8413.1357 | DG22: 3 | DJ22: 6 | DL22: 1 | DQ22: 455.93 | DT22: 14372.61 | DV22: 33.87 | EA22: 276.65 | ED22: 48.04 | EF22: 33.87 | EG22: 55.91
A23: 98952 | B23: COM | C23: =A23&B23 -> 98952COM | E23: 3 | F23: 1 | G23: 1 | H23: 4 | I23: 5 | J23: 5 | K23: 4 | L23: 2 | M23: 3 | O23: 1480.77 | P23: 245.28 | Q23: 0 | R23: 1726.05 | S23: 0.87 | T23: 0 | U23: 0 | V23: 0.87 | W23: 91.52 | X23: 0 | Y23: 0 | Z23: 91.52 | AA23: 1334.53 | AB23: 91.52 | AC23: 0 | AD23: 1426.05 | AE23: 1296.7 | AF23: 125.93 | AG23: 91.52 | AH23: 1514.15 | AI23: 177.28 | AJ23: 78.62 | AK23: 178.48 | AL23: 434.38 | AM23: 1433.71 | AN23: 55.32 | AO23: 257.1 | AP23: 1746.13 | AQ23: 65.25 | AR23: 38.34 | AS23: 312.42 | AT23: 416.01 | AU23: 175.81 | AV23: 36.48 | AW23: 350.76 | AX23: 563.05 | BH23: 91.52 | BK23: 91.52 | BL23: 86.96 | BM23: 91.52 | BO23: 178.48 | BP23: 78.62 | BQ23: 86.96 | BR23: 91.52 | BS23: 257.1 | BT23: 55.32 | BU23: 78.62 | BV23: 178.48 | BW23: 312.42 | BX23: 38.34 | BY23: 55.32 | BZ23: 257.1 | CA23: 350.76 | CB23: 36.48 | CC23: 38.34 | CD23: 312.42 | CE23: 387.24 | CF23: 16.34 | CG23: 36.48 | CH23: 350.76 | CI23: 403.58 | CL23: 48.575268 | CM23: 0.026985017 | CN23: 2.9980209 | CO23: 55.714509 | CP23: 70.870601 | CQ23: 63.625453 | CR23: 123.88235 | CS23: 104.51717 | CT23: 118.20499 | DJ23: 1 | DT23: 114.67 | ED23: 114.67
A24: 98953 | B24: COM | C24: =A24&B24 -> 98953COM | E24: 50 | F24: 45 | G24: 58 | H24: 66 | I24: 57 | J24: 46 | K24: 40 | L24: 59 | M24: 48 | O24: 10780.74 | P24: 3413.24 | Q24: 3220.65 | R24: 17414.63 | S24: 9165.6 | T24: 5173.53 | U24: 2982.85 | V24: 17321.98 | W24: 10821.9 | X24: 4981.04 | Y24: 4281.27 | Z24: 20084.21 | AA24: 10872.19 | AB24: 6630.19 | AC24: 6730.21 | AD24: 24232.59 | AE24: 7229.48 | AF24: 5613.28 | AG24: 9852.49 | AH24: 22695.25 | AI24: 4365.09 | AJ24: 4561.92 | AK24: 11590.42 | AL24: 20517.43 | AM24: 4784.8 | AN24: 3438.34 | AO24: 10939.72 | AP24: 19162.86 | AQ24: 94285.34 | AR24: 3716.02 | AS24: 13213.97 | AT24: 111215.33 | AU24: 7082.65 | AV24: 4838.43 | AW24: 12767.19 | AX24: 24688.27 | CL24: 1208.311 | CM24: 1409.6099 | CN24: 1930.3971 | CO24: 2852.6807 | CP24: 3380.3852 | CQ24: 3882.7649 | CR24: 3629.4529 | CS24: 7156.9747 | CT24: 4564.4218 | DI24: 3 | DL24: 1 | DS24: 3182.72 | DV24: 26.57 | EF24: 26.57
A25: 99323 | B25: COM | C25: =A25&B25 -> 99323COM | E25: 14 | F25: 9 | G25: 10 | H25: 10 | I25: 19 | J25: 13 | K25: 9 | L25: 14 | M25: 14 | O25: 4953.42 | P25: 355.81 | Q25: 493.61 | R25: 5802.84 | S25: 3706.74 | T25: 233.52 | U25: 167.96 | V25: 4108.22 | W25: 2421.11 | X25: 223.05 | Y25: 401.48 | Z25: 3045.64 | AA25: 1278.02 | AB25: 68.47 | AC25: 624.53 | AD25: 1971.02 | AE25: 3525.42 | AF25: 406.22 | AG25: 693 | AH25: 4624.64 | AI25: 2767.63 | AJ25: 414.25 | AK25: 1002.23 | AL25: 4184.11 | AM25: 2045.43 | AN25: 250.54 | AO25: 1331.02 | AP25: 3626.99 | AQ25: 4715.33 | AR25: 245.63 | AS25: 1581.56 | AT25: 6542.52 | AU25: 2192.39 | AV25: 1038.92 | AW25: 1827.19 | AX25: 5058.5 | CL25: 255.69836 | CM25: 173.89731 | CN25: 205.01934 | CO25: 229.31944 | CP25: 324.20409 | CQ25: 406.41926 | CR25: 473.85821 | CS25: 656.48702 | CT25: 705.72831 | DJ25: 1 | DT25: 94.92
A26: 99324 | B26: COM | C26: =A26&B26 -> 99324COM | E26: 7 | F26: 7 | G26: 10 | H26: 5 | I26: 4 | J26: 6 | K26: 2 | L26: 4 | M26: 9 | O26: 2004.59 | P26: 111.42 | Q26: 0 | R26: 2116.01 | S26: 673.98 | T26: 184.1 | U26: 0 | V26: 858.08 | W26: 1486.09 | X26: 253.59 | Y26: 110.43 | Z26: 1850.11 | AA26: 512.35 | AB26: 599.51 | AC26: 304.98 | AD26: 1416.84 | AE26: 341.18 | AF26: 127.73 | AG26: 572.43 | AH26: 1041.34 | AI26: 146.85 | AJ26: 140.32 | AK26: 700.16 | AL26: 987.33 | AM26: 107.79 | AN26: 56.42 | AO26: 776.37 | AP26: 940.58 | AQ26: 338.91 | AR26: 107.79 | AS26: 832.79 | AT26: 1279.49 | AU26: 1459.81 | AV26: 262.05 | AW26: 940.58 | AX26: 2662.44 | CL26: 54.085902 | CM26: 35.050497 | CN26: 100.64479 | CO26: 154.65177 | CP26: 181.98449 | CQ26: 220.64544 | CR26: 236.40718 | CS26: 283.67245 | CT26: 352.14934 | DG26: 1 | DQ26: 31.15
A27: 99328 | B27: COM | C27: =A27&B27 -> 99328COM | E27: 36 | F27: 24 | G27: 43 | H27: 39 | I27: 32 | J27: 31 | K27: 31 | L27: 30 | M27: 33 | O27: 12481.18 | P27: 2787.41 | Q27: 11033.61 | R27: 26302.2 | S27: 8186.04 | T27: 4960.69 | U27: 12322.69 | V27: 25469.42 | W27: 12221.81 | X27: 5905.06 | Y27: 11055.34 | Z27: 29182.21 | AA27: 20059.52 | AB27: 8336.8 | AC27: 13916.77 | AD27: 42313.09 | AE27: 6113.59 | AF27: 5915.32 | AG27: 16649.93 | AH27: 28678.84 | AI27: 5275.13 | AJ27: 3927.99 | AK27: 13776.41 | AL27: 22979.53 | AM27: 6285.47 | AN27: 3036.72 | AO27: 13367.7 | AP27: 22689.89 | AQ27: 5163.33 | AR27: 2461 | AS27: 8875.38 | AT27: 16499.71 | AU27: 5800.57 | AV27: 1885.46 | AW27: 9392.3 | AX27: 17078.33 | CL27: 3080.5094 | CM27: 3641.7627 | CN27: 3840.498 | CO27: 5368.0999 | CP27: 5320.0081 | CQ27: 4501.2745 | CR27: 4361.1048 | CS27: 3166.6308 | CT27: 3254.9229 | DI27: 1 | DS27: 81.48 | EC27: 81.48
A28: 99329 | B28: COM | C28: =A28&B28 -> 99329COM | E28: 2 | F28: 2 | G28: 4 | H28: 6 | I28: 3 | J28: 3 | K28: 3 | L28: 3 | M28: 1 | O28: 140.56 | P28: 103.03 | Q28: 183.18 | R28: 426.77 | S28: 171.79 | T28: 140.56 | U28: 286.21 | V28: 598.56 | W28: 476.32 | X28: 171.79 | Y28: 426.77 | Z28: 1074.88 | AA28: 677.03 | AB28: 476.32 | AC28: 598.56 | AD28: 1751.91 | AE28: 424.3 | AF28: 223.97 | AG28: 770.12 | AH28: 1418.39 | AI28: 295.82 | AJ28: 424.3 | AK28: 694.09 | AL28: 1414.21 | AM28: 287.89 | AN28: 89.64 | AO28: 824.57 | AP28: 1202.1 | AQ28: 239.25 | AR28: 63.39 | AS28: 906.46 | AT28: 1209.1 | AU28: 70.34 | AV28: 35.58 | AW28: 851.55 | AX28: 957.47 | CL28: 52.542938 | CM28: 85.962791 | CN28: 143.32359 | CO28: 233.89331 | CP28: 247.04581 | CQ28: 245.27491 | CR28: 258.62697 | CS28: 301.01695 | CT28: 274.71924
A29: 99347 | B29: COM | C29: =A29&B29 -> 99347COM | E29: 12 | F29: 12 | G29: 19 | H29: 18 | I29: 25 | J29: 18 | K29: 21 | L29: 13 | M29: 18 | O29: 3711.67 | P29: 476.78 | Q29: 508.46 | R29: 4696.91 | S29: 1522.3 | T29: 396.5 | U29: 943.61 | V29: 2862.41 | W29: 4951.82 | X29: 572.27 | Y29: 1320.82 | Z29: 6844.91 | AA29: 2597.36 | AB29: 2037.51 | AC29: 1650.41 | AD29: 6285.28 | AE29: 6447.62 | AF29: 2163.63 | AG29: 3241.57 | AH29: 11852.82 | AI29: 2051.87 | AJ29: 1284.68 | AK29: 2248.14 | AL29: 5584.69 | AM29: 2393.35 | AN29: 982.05 | AO29: 2756.99 | AP29: 6132.39 | AQ29: 2359.56 | AR29: 1365.18 | AS29: 3482.97 | AT29: 7207.71 | AU29: 3278.63 | AV29: 848.87 | AW29: 3962.5 | AX29: 8090 | AZ29: 266.65 | BA29: 25.71 | BC29: 292.36 | BD29: 226.98 | BG29: 226.98 | BH29: 252.84 | BI29: 226.98 | BK29: 479.82 | BL29: 360.09 | BM29: 189.36 | BO29: 549.45 | BP29: 227.36 | BQ29: 124.39 | BS29: 351.75 | BT29: 63.84 | BW29: 63.84 | BX29: 209.92 | BY29: 1.84 | CA29: 211.76 | CB29: 151.71 | CE29: 151.71 | CF29: 151.28 | CI29: 151.28 | CL29: 235.79018 | CM29: 307.92069 | CN29: 561.16776 | CO29: 731.02309 | CP29: 1247.2592 | CQ29: 819.09982 | CR29: 959.73946 | CS29: 1282.424 | CT29: 1396.8785 | DI29: 1 | DJ29: 1 | DK29: 2 | DS29: 277.4 | DT29: 3.48 | DU29: 79.25 | EE29: 26.79
A30: 99348 | B30: COM | C30: =A30&B30 -> 99348COM | E30: 1 | G30: 1 | H30: 2 | I30: 4 | J30: 5 | K30: 4 | L30: 4 | M30: 4 | O30: 135.07 | P30: 0 | Q30: 0 | R30: 135.07 | W30: 229.72 | X30: 0 | Y30: 0 | Z30: 229.72 | AA30: 6.78 | AB30: 0 | AC30: 0 | AD30: 6.78 | AE30: 242.24 | AF30: 6.68 | AG30: 0 | AH30: 248.92 | AI30: 976.08 | AJ30: 1.88 | AK30: 0 | AL30: 977.96 | AM30: 938.89 | AN30: 60.5 | AO30: 1.88 | AP30: 1001.27 | AQ30: 1025.57 | AR30: 30.41 | AS30: 0 | AT30: 1055.98 | AU30: 1046.51 | AV30: 22.74 | AW30: 0 | AX30: 1069.25 | CL30: 3.2471255 | CN30: 7.5251898 | CO30: 0.24469557 | CP30: 7.2940653 | CQ30: 28.37911 | CR30: 33.866137 | CS30: 31.189329 | CT30: 26.674665
A31: 99360 | B31: COM | C31: =A31&B31 -> 99360COM | E31: 13 | F31: 12 | G31: 3 | H31: 4 | I31: 16 | J31: 16 | K31: 7 | L31: 10 | M31: 12 | O31: 4475.98 | P31: 972.7 | Q31: 965.09 | R31: 6413.77 | S31: 3478.13 | T31: 182.5 | U31: 1313.8 | V31: 4974.43 | W31: 775.15 | X31: 505.96 | Y31: 1352.19 | Z31: 2633.3 | AA31: 1698.72 | AB31: 610.25 | AC31: 1357.05 | AD31: 3666.02 | AE31: 7703.62 | AF31: 1356.19 | AG31: 2378.24 | AH31: 11438.05 | AI31: 2562.11 | AJ31: 1430.59 | AK31: 3545.52 | AL31: 7538.22 | AM31: 2247.42 | AN31: 1626.44 | AO31: 4532.06 | AP31: 8405.92 | AQ31: 2062.93 | AR31: 2173.48 | AS31: 6125.79 | AT31: 10362.2 | AU31: 1786.31 | AV31: 1922.97 | AW31: 8299.27 | AX31: 12008.55 | CL31: 389.3692 | CM31: 442.46743 | CN31: 426.59695 | CO31: 497.44508 | CP31: 985.38234 | CQ31: 1225.9582 | CR31: 1526.8677 | CS31: 2179.4432 | CT31: 2814.0622
A32: 99361 | B32: COM | C32: =A32&B32 -> 99361COM | E32: 10 | F32: 11 | G32: 15 | H32: 17 | I32: 10 | J32: 11 | K32: 9 | L32: 28 | M32: 27 | O32: 938.62 | P32: 23.84 | Q32: 0 | R32: 962.46 | S32: 1151.25 | T32: 23.56 | U32: 11.55 | V32: 1186.36 | W32: 1905.07 | X32: 204.08 | Y32: 23.22 | Z32: 2132.37 | AA32: 1528.38 | AB32: 1303.22 | AC32: 50.12 | AD32: 2881.72 | AE32: 1134.76 | AF32: 488.89 | AG32: 761.04 | AH32: 2384.69 | AI32: 1292.8 | AJ32: 594.98 | AK32: 1198.9 | AL32: 3086.68 | AM32: 1079.26 | AN32: 731.53 | AO32: 1500.16 | AP32: 3310.95 | AQ32: 4574.44 | AR32: 628.32 | AS32: 2159.5 | AT32: 7362.26 | AU32: 2778.12 | AV32: 1214.25 | AW32: 2681.12 | AX32: 6673.49 | CL32: 23.82603 | CM32: 40.337036 | CN32: 86.967478 | CO32: 176.92265 | CP32: 280.88465 | CQ32: 435.54336 | CR32: 530.16886 | CS32: 866.16036 | CT32: 1003.3317 | DG32: 1 | DQ32: 389.95
A33: 99362 | B33: COM | C33: =A33&B33 -> 99362COM | E33: 70 | F33: 62 | G33: 98 | H33: 135 | I33: 150 | J33: 92 | K33: 97 | L33: 104 | M33: 126 | O33: 12678.68 | P33: 1557.65 | Q33: 3775.19 | R33: 18011.52 | S33: 9103.82 | T33: 1819.28 | U33: 3423.84 | V33: 14346.94 | W33: 19252.04 | X33: 2807.61 | Y33: 4184.42 | Z33: 26244.07 | AA33: 28713.23 | AB33: 14258.59 | AC33: 6223.88 | AD33: 49195.7 | AE33: 45283.34 | AF33: 14418.44 | AG33: 11726.35 | AH33: 71428.13 | AI33: 25210.76 | AJ33: 12626.28 | AK33: 17246.72 | AL33: 55083.76 | AM33: 17292.34 | AN33: 8965.93 | AO33: 27355.14 | AP33: 53613.41 | AQ33: 25047.3 | AR33: 14016.27 | AS33: 29128.22 | AT33: 68191.79 | AU33: 27589.99 | AV33: 10002.36 | AW33: 35529.39 | AX33: 73121.74 | CL33: 1288.0955 | CM33: 1257.5671 | CN33: 1984.526 | CO33: 3981.9664 | CP33: 5540.4935 | CQ33: 6773.3233 | CR33: 9266.4694 | CS33: 11072.149 | CT33: 12648.891 | DG33: 1 | DH33: 1 | DI33: 2 | DJ33: 11 | DK33: 1 | DL33: 1 | DQ33: 3.02 | DR33: 15.02 | DS33: 477.9 | DT33: 974.43 | DU33: 20.86 | DV33: 235.32 | EC33: 237.12 | ED33: 387.67 | EG33: 340.63
A34: 99363 | B34: COM | C34: =A34&B34 -> 99363COM | E34: 1 | F34: 1 | H34: 2 | I34: 5 | J34: 8 | K34: 3 | L34: 2 | M34: 5 | O34: 23.71 | P34: 21.48 | Q34: 0 | R34: 45.19 | S34: 294.05 | T34: 0 | U34: 0 | V34: 294.05 | AA34: 134.3 | AB34: 0 | AC34: 0 | AD34: 134.3 | AE34: 438.87 | AF34: 0 | AG34: 0 | AH34: 438.87 | AI34: 1768.02 | AJ34: 27.93 | AK34: 42.89 | AL34: 1838.84 | AM34: 189.73 | AN34: 50.31 | AO34: 70.82 | AP34: 310.86 | AQ34: 56.26 | AR34: 38.76 | AS34: 9.58 | AT34: 104.6 | AU34: 427.54 | AV34: 44.71 | AW34: 48.34 | AX34: 520.59 | CL34: 1.7064435 | CM34: 9.1206254 | CO34: 4.8469933 | CP34: 12.472106 | CQ34: 65.900147 | CR34: 30.464579 | CS34: 7.5892381 | CT34: 28.733005
A35: 98603 | B35: RES | C35: =A35&B35 -> 98603RES | E35: 2 | F35: 1 | G35: 2 | H35: 1 | J35: 2 | K35: 3 | L35: 3 | M35: 2 | O35: 193.12 | P35: 71.94 | Q35: 0 | R35: 265.06 | S35: 134.22 | T35: 0 | U35: 0 | V35: 134.22 | W35: 314.3 | X35: 134.22 | Y35: 0 | Z35: 448.52 | AA35: 73.95 | AB35: 99.78 | AC35: 0 | AD35: 173.73 | AI35: 137.09 | AJ35: 0 | AK35: 0 | AL35: 137.09 | AM35: 240.84 | AN35: 88.96 | AO35: 0 | AP35: 329.8 | AQ35: 230.75 | AR35: 147.87 | AS35: 0 | AT35: 378.62 | AU35: 227.73 | AV35: 86.75 | AW35: 87.56 | AX35: 402.04 | CL35: 8.4488131 | CM35: 4.1631367 | CN35: 22.434902 | CO35: 10.900616 | CQ35: 3.9652829 | CR35: 14.050987 | CS35: 17.735968 | CT35: 39.344581
A36: 98901 | B36: RES | C36: =A36&B36 -> 98901RES | E36: 1791 | F36: 2003 | G36: 2437 | H36: 2457 | I36: 2589 | J36: 2271 | K36: 2081 | L36: 2064 | M36: 2182 | O36: 211556.16 | P36: 49355.3 | Q36: 106478.27 | R36: 367389.73 | S36: 266940.28 | T36: 90735.95 | U36: 86472.57 | V36: 444148.8 | W36: 331306.28 | X36: 139007.9 | Y36: 118095.2 | Z36: 588409.38 | AA36: 285711.64 | AB36: 187431.68 | AC36: 192742.46 | AD36: 665885.78 | AE36: 283319.02 | AF36: 178061.7 | AG36: 295396.06 | AH36: 756776.78 | AI36: 157353.87 | AJ36: 172107.96 | AK36: 370224.93 | AL36: 699686.76 | AM36: 136305.7 | AN36: 91769.7 | AO36: 440880.57 | AP36: 668955.97 | AQ36: 126994.15 | AR36: 102469.1 | AS36: 443670.38 | AT36: 673133.63 | AU36: 188410.44 | AV36: 83261.09 | AW36: 462572.34 | AX36: 734243.87 | AZ36: 26441.46 | BA36: 8076.58 | BB36: 25567.34 | BC36: 60085.38 | BD36: 26927.63 | BE36: 14721.25 | BF36: 22024.94 | BG36: 63673.82 | BH36: 28524.05 | BI36: 17745.99 | BJ36: 27203 | BK36: 73473.04 | BL36: 26085.85 | BM36: 19410.97 | BN36: 36126.33 | BO36: 81623.15 | BP36: 27302.66 | BQ36: 19653.85 | BR36: 49293.7 | BS36: 96250.21 | BT36: 17354.58 | BU36: 19189.3 | BV36: 60975.14 | BW36: 97519.02 | BX36: 15339.28 | BY36: 10625.55 | BZ36: 67991.79 | CA36: 93956.62 | CB36: 13706.7 | CC36: 14767.51 | CD36: 71559.49 | CE36: 100033.7 | CF36: 19009.31 | CG36: 9828.92 | CH36: 70795.22 | CI36: 99633.45 | CL36: 33106.362 | CM36: 36350.551 | CN36: 54468.237 | CO36: 80568.647 | CP36: 103841.22 | CQ36: 126596.82 | CR36: 141029.2 | CS36: 153042.28 | CT36: 157302.71 | DG36: 79 | DH36: 35 | DI36: 60 | DJ36: 92 | DK36: 37 | DL36: 30 | DQ36: 24291.68 | DR36: 11494.23 | DS36: 16501.22 | DT36: 36800.86 | DU36: 10519.58 | DV36: 7519.44 | EA36: 3171.7 | EB36: 730.68 | EC36: 3314.41 | ED36: 2358.25 | EE36: 3086.46 | EF36: 1502.08 | EG36: 1931.95
A37: 98902 | B37: RES | C37: =A37&B37 -> 98902RES | E37: 4693 | F37: 4490 | G37: 4191 | H37: 4086 | I37: 4485 | J37: 4132 | K37: 4125 | L37: 4351 | M37: 4311 | O37: 635243.51 | P37: 142831.08 | Q37: 109970.09 | R37: 888044.68 | S37: 589300.06 | T37: 183914.74 | U37: 108026.7 | V37: 881241.5 | W37: 408410.38 | X37: 309914.48 | Y37: 150061.96 | Z37: 868386.82 | AA37: 426143.77 | AB37: 262940.95 | AC37: 269245.44 | AD37: 958330.16 | AE37: 354380.16 | AF37: 330641.52 | AG37: 407762.84 | AH37: 1092784.5 | AI37: 223156.79 | AJ37: 254252.39 | AK37: 503311.56 | AL37: 980720.74 | AM37: 289886.51 | AN37: 129102.32 | AO37: 555740.97 | AP37: 974729.8 | AQ37: 346119.51 | AR37: 156930.52 | AS37: 566480.19 | AT37: 1069530.2 | AU37: 344831.92 | AV37: 193881.03 | AW37: 581904.12 | AX37: 1120617.1 | AZ37: 53146.56 | BA37: 18696.43 | BB37: 25522.09 | BC37: 97365.08 | BD37: 46528.26 | BE37: 21774.33 | BF37: 23673.88 | BG37: 91976.47 | BH37: 36211.16 | BI37: 31191.41 | BJ37: 30909.39 | BK37: 98311.96 | BL37: 38995.5 | BM37: 26847.56 | BN37: 45527.91 | BO37: 111370.97 | BP37: 33424.16 | BQ37: 34721.6 | BR37: 65125.42 | BS37: 133271.18 | BT37: 24320.8 | BU37: 27325.06 | BV37: 77475.69 | BW37: 129121.55 | BX37: 27788.61 | BY37: 14155.25 | BZ37: 73453.91 | CA37: 115397.77 | CB37: 31822.6 | CC37: 17786.05 | CD37: 79590.6 | CE37: 129199.25 | CF37: 29417.13 | CG37: 20227.47 | CH37: 79114.34 | CI37: 128758.94 | CL37: 49070.749 | CM37: 58767.877 | CN37: 80854.011 | CO37: 113615.19 | CP37: 147505.13 | CQ37: 173950.49 | CR37: 182396 | CS37: 202568.83 | CT37: 206701.75 | DG37: 93 | DH37: 56 | DI37: 112 | DJ37: 125 | DK37: 43 | DL37: 46 | DQ37: 23031.17 | DR37: 11938.61 | DS37: 43588.68 | DT37: 46863.11 | DU37: 9870.55 | DV37: 14516.59 | EA37: 3102.07 | EB37: 2046.57 | EC37: 4601.78 | ED37: 6786.44 | EE37: 2660.06 | EF37: 1845.63 | EG37: 1727
A38: 98903 | B38: RES | C38: =A38&B38 -> 98903RES | E38: 1638 | F38: 1579 | G38: 1685 | H38: 1709 | I38: 1958 | J38: 1536 | K38: 1537 | L38: 1589 | M38: 1327 | O38: 275061.31 | P38: 87636.11 | Q38: 67222.86 | R38: 429920.28 | S38: 265584.44 | T38: 82201.84 | U38: 68401.98 | V38: 416188.26 | W38: 255838.06 | X38: 130359.84 | Y38: 93306.24 | Z38: 479504.14 | AA38: 236917.35 | AB38: 140904.84 | AC38: 152132.17 | AD38: 529954.36 | AE38: 226442.07 | AF38: 181354.85 | AG38: 211300.72 | AH38: 619097.64 | AI38: 103719.78 | AJ38: 139611.71 | AK38: 261811.37 | AL38: 505142.86 | AM38: 140825.51 | AN38: 43066.62 | AO38: 310614.76 | AP38: 494506.89 | AQ38: 138506.14 | AR38: 87443.69 | AS38: 296706.58 | AT38: 522656.41 | AU38: 109224.85 | AV38: 67052.49 | AW38: 306032.03 | AX38: 482309.37 | AZ38: 19086.36 | BA38: 11792.61 | BB38: 17447.02 | BC38: 48325.99 | BD38: 16634.29 | BE38: 8822.29 | BF38: 13278.41 | BG38: 38734.99 | BH38: 18786.04 | BI38: 12404.55 | BJ38: 14222.76 | BK38: 45413.35 | BL38: 16787.35 | BM38: 13027.91 | BN38: 20741.02 | BO38: 50556.28 | BP38: 18054.16 | BQ38: 16600.38 | BR38: 28705.41 | BS38: 63359.95 | BT38: 7659.03 | BU38: 14639.98 | BV38: 34249.49 | BW38: 56548.5 | BX38: 11094.65 | BY38: 3485.71 | BZ38: 39506.26 | CA38: 54086.62 | CB38: 8480.4 | CC38: 9379.93 | CD38: 37259.98 | CE38: 55120.31 | CF38: 6876.8 | CG38: 6487.43 | CH38: 34015.71 | CI38: 47379.94 | CL38: 27290.741 | CM38: 31243.607 | CN38: 44697.724 | CO38: 63424.234 | CP38: 78267.639 | CQ38: 90700.048 | CR38: 99114.071 | CS38: 105294.12 | CT38: 104536.83 | DG38: 20 | DH38: 29 | DI38: 18 | DJ38: 40 | DK38: 16 | DL38: 13 | DN38: 2 | DQ38: 5116.5 | DR38: 10964.56 | DS38: 13323.17 | DT38: 18140.77 | DU38: 3338.55 | DV38: 3231.23 | DX38: 2164.79 | EA38: 1413.53 | EB38: 1752.54 | EC38: 1180 | ED38: 3327.94 | EE38: 131.84 | EF38: 352.84 | EG38: 70.57
A39: 98908 | B39: RES | C39: =A39&B39 -> 98908RES | E39: 2982 | F39: 3347 | G39: 3428 | H39: 3270 | I39: 3083 | J39: 2920 | K39: 2619 | L39: 2887 | M39: 2982 | O39: 457284.55 | P39: 75247.62 | Q39: 60443.45 | R39: 592975.62 | S39: 519437.76 | T39: 147581.21 | U39: 70891.76 | V39: 737910.73 | W39: 436145.99 | X39: 240383.96 | Y39: 119362.6 | Z39: 795892.55 | AA39: 383361.37 | AB39: 236620.23 | AC39: 206209.41 | AD39: 826191.01 | AE39: 290907.9 | AF39: 221299.71 | AG39: 284366.9 | AH39: 796574.51 | AI39: 203244.25 | AJ39: 169197.36 | AK39: 341962.34 | AL39: 714403.95 | AM39: 200426.21 | AN39: 109483.88 | AO39: 360670.83 | AP39: 670580.92 | AQ39: 260112.03 | AR39: 105371.71 | AS39: 350429.68 | AT39: 715913.42 | AU39: 306548.73 | AV39: 128285.6 | AW39: 346275.4 | AX39: 781109.73 | AZ39: 20194.44 | BA39: 5809.53 | BB39: 6529.74 | BC39: 32533.71 | BD39: 19676.18 | BE39: 10778.62 | BF39: 7320.91 | BG39: 37775.71 | BH39: 15722.93 | BI39: 12723.1 | BJ39: 12522.72 | BK39: 40968.75 | BL39: 14343.46 | BM39: 11498.54 | BN39: 19195.09 | BO39: 45037.09 | BP39: 10731.94 | BQ39: 11055.81 | BR39: 23572.11 | BS39: 45359.86 | BT39: 7904.69 | BU39: 8699.06 | BV39: 28912.6 | BW39: 45516.35 | BX39: 7405.3 | BY39: 5221.7 | BZ39: 26724.35 | CA39: 39351.35 | CB39: 8589.59 | CC39: 5212.07 | CD39: 26526.69 | CE39: 40328.35 | CF39: 8921.37 | CG39: 4997 | CH39: 20238.54 | CI39: 34156.91 | CL39: 29398.213 | CM39: 44748.42 | CN39: 67404.326 | CO39: 91979.37 | CP39: 103541.72 | CQ39: 119403.4 | CR39: 120676.69 | CS39: 127236.43 | CT39: 126334.99 | DG39: 47 | DH39: 30 | DI39: 28 | DJ39: 44 | DK39: 19 | DL39: 21 | DO39: 1 | DQ39: 10075.95 | DR39: 10449.74 | DS39: 7449.88 | DT39: 18524.57 | DU39: 3098.79 | DV39: 8849.41 | DY39: 239.25 | EA39: 2882.69 | EB39: 2398.89 | EC39: 1447.2 | ED39: 1136.06 | EE39: 934.07 | EF39: 1176.55 | EG39: 1493.45
A40: 98920 | B40: RES | C40: =A40&B40 -> 98920RES | E40: 1 | G40: 1 | H40: 1 | I40: 1 | M40: 1 | O40: 104.22 | P40: 0 | Q40: 0 | R40: 104.22 | W40: 109.1 | X40: 0 | Y40: 0 | Z40: 109.1 | AA40: 11.73 | AB40: 0 | AC40: 0 | AD40: 11.73 | AE40: 101.13 | AF40: 11.73 | AG40: 0 | AH40: 112.86 | AU40: 39.25 | AV40: 0 | AW40: 0 | AX40: 39.25 | CL40: 2.5054817 | CN40: 3.5739083 | CO40: 0.42334499 | CP40: 3.5938033 | CT40: 0.94079764
A41: 98921 | B41: RES | C41: =A41&B41 -> 98921RES | E41: 87 | F41: 88 | G41: 85 | H41: 89 | I41: 85 | J41: 84 | K41: 85 | L41: 74 | M41: 76 | O41: 12756.49 | P41: 3236.3 | Q41: 2495.07 | R41: 18487.86 | S41: 13815.63 | T41: 6037.08 | U41: 2844.39 | V41: 22697.1 | W41: 10690.97 | X41: 7259.9 | Y41: 5171.68 | Z41: 23122.55 | AA41: 10443.22 | AB41: 7247.15 | AC41: 9083.09 | AD41: 26773.46 | AE41: 7307 | AF41: 7092.66 | AG41: 11711.38 | AH41: 26111.04 | AI41: 5378.38 | AJ41: 5313.97 | AK41: 14838.57 | AL41: 25530.92 | AM41: 5393.9 | AN41: 3522.83 | AO41: 16914.68 | AP41: 25831.41 | AQ41: 5242.93 | AR41: 3369.01 | AS41: 17692.01 | AT41: 26303.95 | AU41: 6870.39 | AV41: 3681.09 | AW41: 18027.86 | AX41: 28579.34 | AZ41: 2882.61 | BA41: 849.16 | BB41: 900.12 | BC41: 4631.89 | BD41: 2416.88 | BE41: 1750.54 | BF41: 976.97 | BG41: 5144.39 | BH41: 2035.99 | BI41: 1106.4 | BJ41: 1405.99 | BK41: 4548.38 | BL41: 2331 | BM41: 1641.87 | BN41: 2238.15 | BO41: 6211.02 | BP41: 1839.72 | BQ41: 1972.58 | BR41: 3445.71 | BS41: 7258.01 | BT41: 1396.54 | BU41: 1437.96 | BV41: 3707.93 | BW41: 6542.43 | BX41: 1367.93 | BY41: 1071.26 | BZ41: 4304.36 | CA41: 6743.55 | CB41: 1440.97 | CC41: 1021.32 | CD41: 4930.99 | CE41: 7393.28 | CF41: 1727.49 | CG41: 1208.57 | CH41: 4690.83 | CI41: 7626.89 | CL41: 1073.2999 | CM41: 1586.409 | CN41: 2366.2697 | CO41: 3556.9912 | CP41: 4007.4023 | CQ41: 4923.8442 | CR41: 5415.8718 | CS41: 6053.3215 | CT41: 6149.747 | DG41: 5 | DH41: 1 | DI41: 2 | DJ41: 1 | DL41: 1 | DQ41: 886.18 | DR41: 448.52 | DS41: 820.43 | DT41: 360.39 | DV41: 598.8 | EA41: 466.46 | EC41: 41.56
A42: 98923 | B42: RES | C42: =A42&B42 -> 98923RES | E42: 106 | F42: 136 | G42: 130 | H42: 143 | I42: 123 | J42: 127 | K42: 109 | L42: 114 | M42: 102 | O42: 19897.85 | P42: 2541.44 | Q42: 980.11 | R42: 23419.4 | S42: 23780.39 | T42: 6906.65 | U42: 1246.11 | V42: 31933.15 | W42: 21373.35 | X42: 9758.59 | Y42: 3386.71 | Z42: 34518.65 | AA42: 22461.25 | AB42: 12435.64 | AC42: 7512.19 | AD42: 42409.08 | AE42: 16138.2 | AF42: 13775.51 | AG42: 11386.79 | AH42: 41300.5 | AI42: 10997.46 | AJ42: 10788 | AK42: 16462.07 | AL42: 38247.53 | AM42: 8875.15 | AN42: 6099.25 | AO42: 17004.41 | AP42: 31978.81 | AQ42: 10041.35 | AR42: 5730.64 | AS42: 16265.51 | AT42: 32037.5 | AU42: 9092.72 | AV42: 5511.26 | AW42: 16659.29 | AX42: 31263.27 | AZ42: 808.04 | BA42: 79.52 | BB42: 19.15 | BC42: 906.71 | BD42: 1275.55 | BE42: 346.07 | BF42: 98.67 | BG42: 1720.29 | BH42: 1142.55 | BI42: 940.67 | BJ42: 50.7 | BK42: 2133.92 | BL42: 1103.72 | BM42: 1081.44 | BN42: 297.83 | BO42: 2482.99 | BP42: 856.8 | BQ42: 1059.59 | BR42: 794.53 | BS42: 2710.92 | BT42: 656.55 | BU42: 705.54 | BV42: 822.14 | BW42: 2184.23 | BX42: 559.13 | BY42: 436.5 | BZ42: 292.53 | CA42: 1288.16 | CB42: 542.44 | CC42: 326.57 | CD42: 166.46 | CE42: 1035.47 | CF42: 501.17 | CG42: 334.05 | CH42: 144.38 | CI42: 979.6 | CL42: 846.69781 | CM42: 1572.3277 | CN42: 2472.981 | CO42: 3972.1871 | CP42: 4575.2228 | CQ42: 5988.8642 | CR42: 5742.1792 | CS42: 5912.3975 | CT42: 5896.2144 | DG42: 3 | DH42: 1 | DI42: 3 | DQ42: 230.84 | DR42: 405.04 | DS42: 780.25 | EA42: 122.73 | EC42: 241.51
A43: 98930 | B43: RES | C43: =A43&B43 -> 98930RES | E43: 668 | F43: 753 | G43: 918 | H43: 942 | I43: 924 | J43: 833 | K43: 727 | L43: 683 | M43: 761 | O43: 87553.86 | P43: 8405.55 | Q43: 17914.18 | R43: 113873.59 | S43: 103623.11 | T43: 27085.84 | U43: 11801.79 | V43: 142510.74 | W43: 130320.63 | X43: 44537.58 | Y43: 18084.32 | Z43: 192942.53 | AA43: 114106.44 | AB43: 68575.95 | AC43: 41844.14 | AD43: 224526.53 | AE43: 101468.93 | AF43: 63900.12 | AG43: 72169.82 | AH43: 237538.87 | AI43: 59219.13 | AJ43: 59824.4 | AK43: 93953.51 | AL43: 212997.04 | AM43: 48916.43 | AN43: 32210.88 | AO43: 110876.69 | AP43: 192004 | AQ43: 49275.73 | AR43: 32198.93 | AS43: 112273.18 | AT43: 193747.84 | AU43: 69397.45 | AV43: 29282.87 | AW43: 113654.62 | AX43: 212334.94 | AZ43: 14314.01 | BA43: 898.44 | BB43: 4278.46 | BC43: 19490.91 | BD43: 15583.86 | BE43: 6264.21 | BF43: 2816.44 | BG43: 24664.51 | BH43: 15306.12 | BI43: 8129.05 | BJ43: 4034.52 | BK43: 27469.69 | BL43: 13000.28 | BM43: 10840.98 | BN43: 8394.86 | BO43: 32236.12 | BP43: 13169.52 | BQ43: 9490.47 | BR43: 13070.39 | BS43: 35730.38 | BT43: 7179.86 | BU43: 9156.1 | BV43: 15417.93 | BW43: 31753.89 | BX43: 6577.45 | BY43: 5208.92 | BZ43: 18187.94 | CA43: 29974.31 | CB43: 6001.9 | CC43: 5250.97 | CD43: 17373.99 | CE43: 28626.86 | CF43: 7968.86 | CG43: 3936.16 | CH43: 15771.9 | CI43: 27676.92 | CL43: 6824.4519 | CM43: 8174.8665 | CN43: 13050.846 | CO43: 21671.368 | CP43: 27538.182 | CQ43: 33941.636 | CR43: 36600.552 | CS43: 39687.208 | CT43: 39820.561 | DG43: 18 | DH43: 10 | DI43: 10 | DJ43: 16 | DK43: 5 | DL43: 10 | DQ43: 9598.92 | DR43: 3606.48 | DS43: 2665.49 | DT43: 6046.86 | DU43: 416.1 | DV43: 1740.46 | EA43: 1549.86 | EB43: 1648.21 | EC43: 113.23 | ED43: 110.47 | EE43: 303.71 | EF43: 143.39 | EG43: 1226.27
A44: 98932 | B44: RES | C44: =A44&B44 -> 98932RES | E44: 521 | F44: 547 | G44: 528 | H44: 517 | I44: 482 | J44: 469 | K44: 439 | L44: 455 | M44: 458 | O44: 84227.48 | P44: 16710.31 | Q44: 12157.66 | R44: 113095.45 | S44: 88716.45 | T44: 31053.22 | U44: 14427.03 | V44: 134196.7 | W44: 70336.77 | X44: 44143.38 | Y44: 26565.46 | Z44: 141045.61 | AA44: 61586.56 | AB44: 40017.84 | AC44: 44094.63 | AD44: 145699.03 | AE44: 44448.11 | AF44: 36544.01 | AG44: 59653.69 | AH44: 140645.81 | AI44: 30962.23 | AJ44: 28375.98 | AK44: 71097.16 | AL44: 130435.37 | AM44: 30922.22 | AN44: 17265.45 | AO44: 73155.1 | AP44: 121342.77 | AQ44: 41773.39 | AR44: 18218.01 | AS44: 69051.3 | AT44: 129042.7 | AU44: 42912.85 | AV44: 23719.23 | AW44: 71176.01 | AX44: 137808.09 | AZ44: 11937.73 | BA44: 3160.13 | BB44: 2438.84 | BC44: 17536.7 | BD44: 11078.33 | BE44: 6068.97 | BF44: 3447.7 | BG44: 20595 | BH44: 7722.84 | BI44: 6648.52 | BJ44: 4231.22 | BK44: 18602.58 | BL44: 7659.59 | BM44: 5417.86 | BN44: 6665 | BO44: 19742.45 | BP44: 5719.41 | BQ44: 5568.22 | BR44: 8601.08 | BS44: 19888.71 | BT44: 3912.93 | BU44: 4133.22 | BV44: 9777.99 | BW44: 17824.14 | BX44: 4150.4 | BY44: 2446.1 | BZ44: 9618.42 | CA44: 16214.92 | CB44: 5822.6 | CC44: 3007.7 | CD44: 8977.53 | CE44: 17807.83 | CF44: 6322.53 | CG44: 4656.17 | CH44: 9739.11 | CI44: 20717.81 | CL44: 5810.1709 | CM44: 8657.8896 | CN44: 13279.641 | CO44: 18059.668 | CP44: 20643.301 | CQ44: 23969.027 | CR44: 23808.253 | CS44: 24611.212 | CT44: 25300.792 | DG44: 8 | DH44: 6 | DI44: 7 | DJ44: 10 | DK44: 5 | DL44: 8 | DQ44: 2243.08 | DR44: 2378.04 | DS44: 4287.18 | DT44: 1345.67 | DU44: 1946.87 | DV44: 5438.67 | EA44: 54.33 | EB44: 1013.78 | EC44: 680.06 | ED44: 509.74 | EE44: 1800.21 | EF44: 45.06 | EG44: 127.51
A45: 98933 | B45: RES | C45: =A45&B45 -> 98933RES | E45: 76 | F45: 77 | G45: 88 | H45: 85 | I45: 78 | J45: 71 | K45: 51 | L45: 50 | M45: 56 | O45: 12246.39 | P45: 3249.95 | Q45: 3097.29 | R45: 18593.63 | S45: 13925.15 | T45: 3103.72 | U45: 1998.17 | V45: 19027.04 | W45: 13556.14 | X45: 6335.58 | Y45: 2846.39 | Z45: 22738.11 | AA45: 10777.73 | AB45: 5924.31 | AC45: 5684.84 | AD45: 22386.88 | AE45: 9460.75 | AF45: 5850.67 | AG45: 8776.12 | AH45: 24087.54 | AI45: 5200.94 | AJ45: 5156.8 | AK45: 11593.66 | AL45: 21951.4 | AM45: 3660.93 | AN45: 2529.21 | AO45: 13770.81 | AP45: 19960.95 | AQ45: 4023.64 | AR45: 2318.93 | AS45: 15205.09 | AT45: 21547.66 | AU45: 5550.61 | AV45: 2666.85 | AW45: 16521.57 | AX45: 24739.03 | AZ45: 3334.56 | BA45: 1173.05 | BB45: 1768.22 | BC45: 6275.83 | BD45: 2778.98 | BE45: 749.05 | BF45: 323.87 | BG45: 3851.9 | BH45: 3065.47 | BI45: 1497.79 | BJ45: 263.73 | BK45: 4826.99 | BL45: 2043.41 | BM45: 1317.4 | BN45: 796.62 | BO45: 4157.43 | BP45: 1754.18 | BQ45: 1145.31 | BR45: 1529.12 | BS45: 4428.61 | BT45: 873.42 | BU45: 1012.45 | BV45: 2104.65 | BW45: 3990.52 | BX45: 731.98 | BY45: 647.31 | BZ45: 2306.77 | CA45: 3686.06 | CB45: 620.12 | CC45: 473.66 | CD45: 2757.69 | CE45: 3851.47 | CF45: 1028.48 | CG45: 503.56 | CH45: 3078.46 | CI45: 4610.5 | CL45: 1205.4687 | CM45: 1157.9438 | CN45: 1765.2908 | CO45: 2493.852 | CP45: 3149.1381 | CQ45: 3954.1914 | CR45: 4361.4529 | CS45: 5145.025 | CT45: 5568.6134 | DG45: 1 | DH45: 2 | DI45: 5 | DJ45: 1 | DQ45: 34.19 | DR45: 1385.06 | DS45: 3281.45 | DT45: 296.33 | EB45: 88.06 | EC45: 152.79
A46: 98935 | B46: RES | C46: =A46&B46 -> 98935RES | E46: 156 | F46: 189 | G46: 229 | H46: 232 | I46: 304 | J46: 215 | K46: 190 | L46: 180 | M46: 170 | O46: 8444.06 | P46: 18310.15 | Q46: 8667.24 | R46: 35421.45 | S46: 33708.55 | T46: 9734.06 | U46: 6787.23 | V46: 50229.84 | W46: 41315.9 | X46: 15953.73 | Y46: 9005.35 | Z46: 66274.98 | AA46: 35757.98 | AB46: 25071.44 | AC46: 17161.64 | AD46: 77991.06 | AE46: 48841.27 | AF46: 22491.9 | AG46: 28734.87 | AH46: 100068.04 | AI46: 18100.7 | AJ46: 18309 | AK46: 36491.54 | AL46: 72901.24 | AM46: 15209.76 | AN46: 2723.68 | AO46: 50545.81 | AP46: 68479.25 | AQ46: 4198.7 | AR46: 21141.87 | AS46: 42852.56 | AT46: 68193.13 | AU46: 17222.36 | AV46: 2865.48 | AW46: 50175.95 | AX46: 70263.79 | AZ46: 766.08 | BA46: 3698.73 | BB46: 1753.15 | BC46: 6217.96 | BD46: 4964.58 | BE46: 1423.32 | BF46: 1553.66 | BG46: 7941.56 | BH46: 5577.07 | BI46: 2466.31 | BJ46: 645.25 | BK46: 8688.63 | BL46: 4345.66 | BM46: 4174.39 | BN46: 2200.45 | BO46: 10720.5 | BP46: 6750.87 | BQ46: 3042.97 | BR46: 3916.88 | BS46: 13710.72 | BT46: 2452.98 | BU46: 2158.29 | BV46: 5168.17 | BW46: 9779.44 | BX46: 1984.15 | BZ46: 7752.7 | CA46: 9736.85 | CB46: 95.81 | CC46: 4011.38 | CD46: 7199.16 | CE46: 11306.35 | CF46: 2801.5 | CH46: 8693.11 | CI46: 11494.61 | CL46: 3240.0272 | CM46: 3449.5333 | CN46: 5163.5071 | CO46: 8237.7284 | CP46: 11023.327 | CQ46: 12657.751 | CR46: 15571.252 | CS46: 15409.286 | CT46: 16554.554 | DG46: 3 | DH46: 7 | DI46: 6 | DJ46: 4 | DK46: 3 | DL46: 1 | DQ46: 1307.37 | DR46: 3262.51 | DS46: 3279.8 | DT46: 2134.56 | DU46: 1215.43 | DV46: 558.33 | EA46: 56.58 | EB46: 177.03 | ED46: 1729.27
A47: 98936 | B47: RES | C47: =A47&B47 -> 98936RES | E47: 273 | F47: 332 | G47: 426 | H47: 409 | I47: 399 | J47: 384 | K47: 324 | L47: 316 | M47: 376 | O47: 36462.71 | P47: 524.41 | Q47: 19595.47 | R47: 56582.59 | S47: 45403.91 | T47: 15427.35 | U47: 11935.79 | V47: 72767.05 | W47: 61719.5 | X47: 22626.79 | Y47: 16625.76 | Z47: 100972.05 | AA47: 50783.54 | AB47: 32524.1 | AC47: 28034.73 | AD47: 111342.37 | AE47: 45390.89 | AF47: 29473.96 | AG47: 46058.95 | AH47: 120923.8 | AI47: 33213.55 | AJ47: 26830.98 | AK47: 56697.3 | AL47: 116741.83 | AM47: 23823.08 | AN47: 18540.84 | AO47: 66354.91 | AP47: 108718.83 | AQ47: 25165.56 | AR47: 14841.58 | AS47: 70905.61 | AT47: 110912.75 | AU47: 41859.68 | AV47: 16306.09 | AW47: 77731.59 | AX47: 135897.36 | AZ47: 1287.64 | BB47: 1422.08 | BC47: 2709.72 | BD47: 1375.03 | BE47: 835.84 | BF47: 1178.63 | BG47: 3389.5 | BH47: 989.24 | BI47: 760.14 | BJ47: 1067.55 | BK47: 2816.93 | BL47: 1087.16 | BM47: 545.9 | BN47: 1401.94 | BO47: 3035 | BP47: 873.76 | BQ47: 859.88 | BR47: 1678.99 | BS47: 3412.63 | BT47: 685.67 | BU47: 465.73 | BV47: 1833.77 | BW47: 2985.17 | BX47: 718.03 | BY47: 322.5 | BZ47: 1988.65 | CA47: 3029.18 | CB47: 423.65 | CC47: 242.01 | CD47: 2050.37 | CE47: 2716.03 | CF47: 1117.67 | CG47: 299.95 | CH47: 2092.38 | CI47: 3510 | CL47: 5580.4465 | CM47: 5505.9717 | CN47: 8438.5575 | CO47: 12485.929 | CP47: 16330.674 | CQ47: 19687.954 | CR47: 21681.595 | CS47: 24479.091 | CT47: 26839.822 | DG47: 10 | DH47: 5 | DI47: 5 | DJ47: 13 | DK47: 3 | DL47: 2 | DQ47: 2038.11 | DR47: 3363.69 | DS47: 3411.85 | DT47: 7320.79 | DU47: 237.61 | DV47: 1264.86 | EA47: 387.96 | EB47: 502.58 | EC47: 1178.24 | ED47: 910.4 | EF47: 124.53 | EG47: 227.93
A48: 98937 | B48: RES | C48: =A48&B48 -> 98937RES | E48: 323 | F48: 360 | G48: 396 | H48: 414 | I48: 384 | J48: 367 | K48: 308 | L48: 298 | M48: 284 | O48: 51192.34 | P48: 7777.45 | Q48: 4235.06 | R48: 63204.85 | S48: 65112.42 | T48: 15486.73 | U48: 6276.14 | V48: 86875.29 | W48: 64581.85 | X48: 26255 | Y48: 10535.21 | Z48: 101372.06 | AA48: 55568.94 | AB48: 30024.32 | AC48: 20192.43 | AD48: 105785.69 | AE48: 49586.37 | AF48: 28742.89 | AG48: 32495.35 | AH48: 110824.61 | AI48: 31454.77 | AJ48: 28738.25 | AK48: 41048 | AL48: 101241.02 | AM48: 23749.55 | AN48: 16051.65 | AO48: 45968.76 | AP48: 85769.96 | AQ48: 24931.33 | AR48: 12451.27 | AS48: 44874.33 | AT48: 82256.93 | AU48: 28124.16 | AV48: 13870.76 | AW48: 41308.16 | AX48: 83303.08 | AZ48: 3225.79 | BA48: 889.45 | BB48: 213.33 | BC48: 4328.57 | BD48: 3103.1 | BE48: 1720.35 | BF48: 497.99 | BG48: 5321.44 | BH48: 2011.1 | BI48: 1604.98 | BJ48: 1099.85 | BK48: 4715.93 | BL48: 1517.21 | BM48: 1266.72 | BN48: 1743.7 | BO48: 4527.63 | BP48: 1478.27 | BQ48: 1128.22 | BR48: 2599.11 | BS48: 5205.6 | BT48: 1149.45 | BU48: 1099.04 | BV48: 3471.35 | BW48: 5719.84 | BX48: 804.49 | BY48: 711.17 | BZ48: 3064.07 | CA48: 4579.73 | CB48: 814.49 | CC48: 590.14 | CD48: 3492.07 | CE48: 4896.7 | CF48: 888.82 | CG48: 441.75 | CH48: 2021.04 | CI48: 3351.61 | CL48: 2652.7887 | CM48: 4740.9025 | CN48: 7259.464 | CO48: 10222.942 | CP48: 12508.427 | CQ48: 15192.903 | CR48: 15482.893 | CS48: 15978.187 | CT48: 14768.223 | DG48: 4 | DH48: 5 | DI48: 10 | DJ48: 8 | DK48: 3 | DL48: 3 | DQ48: 285.64 | DR48: 1559.35 | DS48: 3964.68 | DT48: 3868.2 | DU48: 914.06 | DV48: 1775.52 | EA48: 104.54 | EC48: 83.99 | ED48: 280.77 | EE48: 124.18 | EF48: 442.89 | EG48: 487.86
A49: 98938 | B49: RES | C49: =A49&B49 -> 98938RES | E49: 176 | F49: 194 | G49: 186 | H49: 178 | I49: 172 | J49: 171 | K49: 158 | L49: 152 | M49: 168 | O49: 39686.2 | P49: 7941.4 | Q49: 5329.72 | R49: 52957.32 | S49: 41787.73 | T49: 12759.09 | U49: 3567.73 | V49: 58114.55 | W49: 33990.06 | X49: 20012.4 | Y49: 7557.05 | Z49: 61559.51 | AA49: 30575.56 | AB49: 19872.68 | AC49: 16635.78 | AD49: 67084.02 | AE49: 23128.54 | AF49: 19994.95 | AG49: 25208.47 | AH49: 68331.96 | AI49: 15244.9 | AJ49: 15437.92 | AK49: 33079.18 | AL49: 63762 | AM49: 14124.33 | AN49: 9572.88 | AO49: 34515.73 | AP49: 58212.94 | AQ49: 17516.92 | AR49: 8656.33 | AS49: 35718.18 | AT49: 61891.43 | AU49: 21414.77 | AV49: 10823.91 | AW49: 35407.74 | AX49: 67646.42 | AZ49: 5193.35 | BA49: 1350.92 | BB49: 414.35 | BC49: 6958.62 | BD49: 3319.3 | BE49: 1988.63 | BF49: 322.34 | BG49: 5630.27 | BH49: 3033.76 | BI49: 2091 | BJ49: 600.95 | BK49: 5725.71 | BL49: 2299.66 | BM49: 2186.9 | BN49: 2176.76 | BO49: 6663.32 | BP49: 2115.08 | BQ49: 1796 | BR49: 3619.56 | BS49: 7530.64 | BT49: 1442.77 | BU49: 1494.06 | BV49: 4316.38 | BW49: 7253.21 | BX49: 1316.46 | BY49: 936.73 | BZ49: 3032.37 | CA49: 5285.56 | CB49: 1172.5 | CC49: 790.35 | CD49: 3128.17 | CE49: 5091.02 | CF49: 1958.95 | CG49: 1030.98 | CH49: 3505.67 | CI49: 6495.6 | CL49: 2646.0736 | CM49: 3147.0109 | CN49: 4909.8891 | CO49: 7472.3054 | CP49: 9126.2968 | CQ49: 11350.264 | CR49: 11325.816 | CS49: 12557.129 | CT49: 12519.687 | DH49: 5 | DI49: 3 | DJ49: 8 | DL49: 1 | DR49: 1733.54 | DS49: 1209.95 | DT49: 8710.42 | DV49: 1260.28 | EB49: 50 | EC49: 363.01 | ED49: 44.62
A50: 98939 | B50: RES | C50: =A50&B50 -> 98939RES | E50: 21 | F50: 23 | G50: 26 | H50: 25 | I50: 23 | J50: 23 | K50: 20 | L50: 19 | M50: 20 | O50: 3242.24 | P50: 766.63 | Q50: 960.16 | R50: 4969.03 | S50: 3601.84 | T50: 1636.48 | U50: 1023.45 | V50: 6261.77 | W50: 4087.23 | X50: 1837.31 | Y50: 1787.49 | Z50: 7712.03 | AA50: 2906.01 | AB50: 3006 | AC50: 3264.39 | AD50: 9176.4 | AE50: 2987.71 | AF50: 2038.36 | AG50: 5777.52 | AH50: 10803.59 | AI50: 1842.29 | AJ50: 2176.94 | AK50: 6419.69 | AL50: 10438.92 | AM50: 1481.4 | AN50: 1306.99 | AO50: 7908.63 | AP50: 10697.02 | AQ50: 1594.25 | AR50: 965.61 | AS50: 7559.96 | AT50: 10119.82 | AU50: 2163.61 | AV50: 1365.33 | AW50: 8230.15 | AX50: 11759.09 | AZ50: 260 | BA50: 82.81 | BC50: 342.81 | BD50: 260.93 | BE50: 1.74 | BG50: 262.67 | BH50: 651.94 | BI50: 62.67 | BK50: 714.61 | BL50: 434.99 | BM50: 651.94 | BN50: 62.67 | BO50: 1149.6 | BP50: 452.24 | BQ50: 220.1 | BR50: 485.29 | BS50: 1157.63 | BT50: 298.33 | BU50: 452.24 | BV50: 399.61 | BW50: 1150.18 | BX50: 106.92 | BY50: 116.75 | BZ50: 604.06 | CA50: 827.73 | CB50: 134.72 | CC50: 106.92 | CD50: 720.81 | CE50: 962.45 | CF50: 161.31 | CG50: 134.72 | CH50: 827.73 | CI50: 1123.76 | CL50: 347.63064 | CM50: 487.17796 | CN50: 769.92901 | CO50: 1280.8957 | CP50: 1869.7853 | CQ50: 2106.7118 | CR50: 2474.852 | CS50: 2532.4223 | CT50: 2762.1433 | DG50: 2 | DI50: 2 | DJ50: 1 | DQ50: 122.07 | DS50: 195.26 | DT50: 2230.98 | EA50: 73.54
A51: 98942 | B51: RES | C51: =A51&B51 -> 98942RES | E51: 1138 | F51: 1333 | G51: 1528 | H51: 1537 | I51: 1457 | J51: 1384 | K51: 1193 | L51: 1167 | M51: 1282 | O51: 172931.12 | P51: 28287.35 | Q51: 34145.81 | R51: 235364.28 | S51: 223154.81 | T51: 61229.01 | U51: 38475.72 | V51: 322859.54 | W51: 250398.32 | X51: 94787.68 | Y51: 57402.07 | Z51: 402588.07 | AA51: 212697.97 | AB51: 125745.48 | AC51: 96193.13 | AD51: 434636.58 | AE51: 181607.59 | AF51: 119773.48 | AG51: 144791.25 | AH51: 446172.32 | AI51: 113050.53 | AJ51: 106348.53 | AK51: 183631.98 | AL51: 403031.04 | AM51: 98822.83 | AN51: 63487.52 | AO51: 206979.07 | AP51: 369289.42 | AQ51: 102189.28 | AR51: 55081.24 | AS51: 208136.33 | AT51: 365406.85 | AU51: 139850.5 | AV51: 56035.3 | AW51: 216020.64 | AX51: 411906.44 | AZ51: 4097.94 | BA51: 930.08 | BB51: 4245.76 | BC51: 9273.78 | BD51: 5865.56 | BE51: 2894.3 | BF51: 4645.07 | BG51: 13404.93 | BH51: 5904.43 | BI51: 4071.5 | BJ51: 6139.35 | BK51: 16115.28 | BL51: 4630.8 | BM51: 3835.14 | BN51: 7800.43 | BO51: 16266.37 | BP51: 3951.52 | BQ51: 3393 | BR51: 10545.42 | BS51: 17889.94 | BT51: 2962.64 | BU51: 3237.7 | BV51: 11480.19 | BW51: 17680.53 | BX51: 2051.49 | BY51: 1801.75 | BZ51: 10500.7 | CA51: 14353.94 | CB51: 2305.06 | CC51: 1646.81 | CD51: 10362.9 | CE51: 14314.77 | CF51: 3875.52 | CG51: 1962.55 | CH51: 9772.15 | CI51: 15610.22 | CL51: 13802.243 | CM51: 21014.182 | CN51: 31864.349 | CO51: 45396.748 | CP51: 54107.357 | CQ51: 65437.684 | CR51: 68805.942 | CS51: 73528.504 | CT51: 75902.955 | DG51: 21 | DH51: 16 | DI51: 15 | DJ51: 32 | DK51: 14 | DL51: 8 | DQ51: 4811.27 | DR51: 4825.89 | DS51: 8162.36 | DT51: 15137.35 | DU51: 6955.46 | DV51: 1412.65 | EA51: 1857.55 | EB51: 872.99 | EC51: 356.17 | ED51: 990.09 | EE51: 115.53 | EF51: 84.56 | EG51: 505.15
A52: 98944 | B52: RES | C52: =A52&B52 -> 98944RES | E52: 1536 | F52: 1674 | G52: 1710 | H52: 1657 | I52: 1583 | J52: 1458 | K52: 1410 | L52: 1433 | M52: 1554 | O52: 221458.67 | P52: 36987.16 | Q52: 30125.95 | R52: 288571.78 | S52: 246077.66 | T52: 70423.08 | U52: 31050.74 | V52: 347551.48 | W52: 221336.6 | X52: 102857.52 | Y52: 48797.66 | Z52: 372991.78 | AA52: 193724.3 | AB52: 118439.89 | AC52: 95598.19 | AD52: 407762.38 | AE52: 149642.11 | AF52: 110381.54 | AG52: 142366.38 | AH52: 402390.03 | AI52: 95390.28 | AJ52: 89469.31 | AK52: 178123.49 | AL52: 362983.08 | AM52: 95619.07 | AN52: 55095.3 | AO52: 192572.53 | AP52: 343286.9 | AQ52: 110754.45 | AR52: 54901.48 | AS52: 190877.94 | AT52: 356533.87 | AU52: 146848.48 | AV52: 67137.17 | AW52: 198537.64 | AX52: 412523.29 | AZ52: 29821.43 | BA52: 7306.22 | BB52: 8224.9 | BC52: 45352.55 | BD52: 30360.82 | BE52: 12996.55 | BF52: 7988.38 | BG52: 51345.75 | BH52: 23904.83 | BI52: 15267.92 | BJ52: 9830.07 | BK52: 49002.82 | BL52: 21764.3 | BM52: 17008.66 | BN52: 18785.35 | BO52: 57558.31 | BP52: 17152.74 | BQ52: 15465.17 | BR52: 28276.89 | BS52: 60894.8 | BT52: 11113.45 | BU52: 12083.54 | BV52: 33847.86 | BW52: 57044.85 | BX52: 10727.87 | BY52: 7680.53 | BZ52: 35589.37 | CA52: 53997.77 | CB52: 13599.13 | CC52: 7828.68 | CD52: 35497.89 | CE52: 56925.7 | CF52: 15308.29 | CG52: 9615.86 | CH52: 36128.53 | CI52: 61052.68 | CL52: 14469.872 | CM52: 20619.951 | CN52: 29380.382 | CO52: 43940.139 | CP52: 51925.967 | CQ52: 61996.587 | CR52: 63831.53 | CS52: 68244.852 | CT52: 71292.682 | DG52: 24 | DH52: 21 | DI52: 25 | DJ52: 59 | DK52: 14 | DL52: 14 | DQ52: 6060.87 | DR52: 5021.5 | DS52: 11780.26 | DT52: 44855.09 | DU52: 4852.92 | DV52: 1827.77 | EA52: 1448.67 | EB52: 1114.08 | EC52: 2389.6 | ED52: 1555.89 | EE52: 613.33 | EF52: 58.6 | EG52: 162.32
A53: 98947 | B53: RES | C53: =A53&B53 -> 98947RES | E53: 261 | F53: 327 | G53: 320 | H53: 329 | I53: 296 | J53: 284 | K53: 270 | L53: 255 | M53: 259 | O53: 43294.12 | P53: 6709.52 | Q53: 4009.19 | R53: 54012.83 | S53: 59802.26 | T53: 15089.15 | U53: 5755.41 | V53: 80646.82 | W53: 52395.29 | X53: 22929.54 | Y53: 10480.98 | Z53: 85805.81 | AA53: 49878.15 | AB53: 28640.87 | AC53: 20818.3 | AD53: 99337.32 | AE53: 36582.27 | AF53: 29649.91 | AG53: 32178.65 | AH53: 98410.83 | AI53: 24418.26 | AJ53: 24254.19 | AK53: 45369.6 | AL53: 94042.05 | AM53: 20340.82 | AN53: 15201.86 | AO53: 51543.47 | AP53: 87086.15 | AQ53: 21756.51 | AR53: 12400.91 | AS53: 51086.69 | AT53: 85244.11 | AU53: 23655.99 | AV53: 13251.09 | AW53: 51513.01 | AX53: 88420.09 | AZ53: 3631.19 | BA53: 664.25 | BB53: 1792.01 | BC53: 6087.45 | BD53: 3279.97 | BE53: 1426.65 | BF53: 1781.84 | BG53: 6488.46 | BH53: 2757.28 | BI53: 1504.28 | BJ53: 2244.97 | BK53: 6506.53 | BL53: 2723.08 | BM53: 2158.97 | BN53: 3077.64 | BO53: 7959.69 | BP53: 2151.33 | BQ53: 2096.32 | BR53: 4728.38 | BS53: 8976.03 | BT53: 1386.38 | BU53: 1601.17 | BV53: 6123.75 | BW53: 9111.3 | BX53: 980.7 | BY53: 1004.28 | BZ53: 5959.95 | CA53: 7944.93 | CB53: 1146.1 | CC53: 717.59 | CD53: 5889.57 | CE53: 7753.26 | CF53: 1265.19 | CG53: 895.79 | CH53: 5535.83 | CI53: 7696.81 | CL53: 2352.5117 | CM53: 4418.5911 | CN53: 6545.2413 | CO53: 10081.352 | CP53: 12103.545 | CQ53: 15908.649 | CR53: 16958.131 | CS53: 17868.773 | CT53: 17859.951 | DH53: 3 | DI53: 2 | DJ53: 1 | DK53: 2 | DL53: 3 | DO53: 1 | DR53: 937.94 | DS53: 587.29 | DT53: 93.81 | DU53: 1066.59 | DV53: 1407.51 | DY53: 829.07 | EE53: 150.96 | EG53: 93.81
A54: 98948 | B54: RES | C54: =A54&B54 -> 98948RES | E54: 1118 | F54: 925 | G54: 822 | H54: 807 | I54: 975 | J54: 822 | K54: 957 | L54: 992 | M54: 833 | O54: 190188.17 | P54: 52149.41 | Q54: 26916.97 | R54: 269254.55 | S54: 140172.33 | T54: 47653.38 | U54: 33147.76 | V54: 220973.47 | W54: 90759.45 | X54: 78717.38 | Y54: 34180.63 | Z54: 203657.46 | AA54: 105915.71 | AB54: 63668.89 | AC54: 61828 | AD54: 231412.6 | AE54: 87118.5 | AF54: 99990.24 | AG54: 107098.45 | AH54: 294207.19 | AI54: 42575.46 | AJ54: 74721.17 | AK54: 135243.64 | AL54: 252540.27 | AM54: 92355 | AN54: 24424.32 | AO54: 160883.81 | AP54: 277663.13 | AQ54: 97741.13 | AR54: 43055.76 | AS54: 160977.93 | AT54: 301774.82 | AU54: 59748.18 | AV54: 54578.7 | AW54: 161505.24 | AX54: 275832.12 | AZ54: 47476.16 | BA54: 18817.5 | BB54: 10283.02 | BC54: 76576.68 | BD54: 34143.51 | BE54: 13421.1 | BF54: 14822.39 | BG54: 62387 | BH54: 22326.85 | BI54: 20432.67 | BJ54: 11971.01 | BK54: 54730.53 | BL54: 26578.41 | BM54: 19021.05 | BN54: 21453.82 | BO54: 67053.28 | BP54: 21093.24 | BQ54: 29375.15 | BR54: 38072.84 | BS54: 88541.23 | BT54: 8900.33 | BU54: 21988.86 | BV54: 45263.47 | BW54: 76152.66 | BX54: 22714.65 | BY54: 6261.32 | BZ54: 55871.99 | CA54: 84847.96 | CB54: 21560.38 | CC54: 12622.51 | CD54: 56766.4 | CE54: 90949.29 | CF54: 11489.55 | CG54: 15893.99 | CH54: 58140.69 | CI54: 85524.23 | CL54: 13754.543 | CM54: 16097.193 | CN54: 19077.337 | CO54: 26652.092 | CP54: 39379.523 | CQ54: 46737.095 | CR54: 52090.218 | CS54: 57430.067 | CT54: 56561.068 | DG54: 22 | DH54: 12 | DI54: 18 | DJ54: 14 | DK54: 4 | DL54: 8 | DQ54: 7211.52 | DR54: 4935.08 | DS54: 11488.83 | DT54: 4495.31 | DU54: 1020.36 | DV54: 2377.48 | EA54: 393.7 | EB54: 328.13 | EC54: 130.5 | ED54: 857.54 | EE54: 61.49 | EF54: 520.17
A55: 98951 | B55: RES | C55: =A55&B55 -> 98951RES | E55: 991 | F55: 1027 | G55: 1070 | H55: 1099 | I55: 1047 | J55: 997 | K55: 949 | L55: 913 | M55: 966 | O55: 175199.34 | P55: 28513.6 | Q55: 62973.55 | R55: 266686.49 | S55: 183044.55 | T55: 66401.13 | U55: 61612.41 | V55: 311058.09 | W55: 160465.65 | X55: 91115.59 | Y55: 80604.5 | Z55: 332185.74 | AA55: 154119.11 | AB55: 98495.07 | AC55: 125684.36 | AD55: 378298.54 | AE55: 121919.72 | AF55: 98012.44 | AG55: 172831.28 | AH55: 392763.44 | AI55: 81533.9 | AJ55: 81402.13 | AK55: 214432.46 | AL55: 377368.49 | AM55: 74936.65 | AN55: 52616.52 | AO55: 229740.41 | AP55: 357293.58 | AQ55: 88689.45 | AR55: 47155.77 | AS55: 234732.52 | AT55: 370577.74 | AU55: 108902.97 | AV55: 54409.78 | AW55: 241267.51 | AX55: 404580.26 | AZ55: 45952.69 | BA55: 9473.84 | BB55: 38401.44 | BC55: 93827.97 | BD55: 50046.62 | BE55: 25046.96 | BF55: 37875.88 | BG55: 112969.46 | BH55: 42538.15 | BI55: 29381.74 | BJ55: 46346.9 | BK55: 118266.79 | BL55: 38017.94 | BM55: 33369.46 | BN55: 64652.12 | BO55: 136039.52 | BP55: 32467.34 | BQ55: 28834.57 | BR55: 80566.49 | BS55: 141868.4 | BT55: 20450.12 | BU55: 24900.53 | BV55: 96367.76 | BW55: 141718.41 | BX55: 19712.46 | BY55: 16813.53 | BZ55: 107987.28 | CA55: 144513.27 | CB55: 22733.91 | CC55: 15816.87 | CD55: 113302.87 | CE55: 151853.65 | CF55: 27506 | CG55: 17708.77 | CH55: 115784.19 | CI55: 160998.96 | CL55: 20747.992 | CM55: 25812.752 | CN55: 34685.348 | CO55: 49418.457 | CP55: 59131.19 | CQ55: 71623.574 | CR55: 73968.873 | CS55: 81039.052 | CT55: 83068.616 | DG55: 17 | DH55: 15 | DI55: 18 | DJ55: 22 | DK55: 5 | DL55: 6 | DQ55: 9376.06 | DR55: 4243.97 | DS55: 10524.78 | DT55: 12165.26 | DU55: 1940.11 | DV55: 1672.67 | EA55: 980.36 | EB55: 953.11 | EC55: 935.12 | ED55: 1342.96 | EE55: 464.88 | EF55: 16.76 | EG55: 602.92
A56: 98952 | B56: RES | C56: =A56&B56 -> 98952RES | E56: 73 | F56: 72 | G56: 66 | H56: 75 | I56: 74 | J56: 73 | K56: 61 | L56: 62 | M56: 71 | O56: 12523.51 | P56: 4046.92 | Q56: 3559.39 | R56: 20129.82 | S56: 15002.24 | T56: 5685.26 | U56: 3827.27 | V56: 24514.77 | W56: 12212.25 | X56: 8318.84 | Y56: 5746.49 | Z56: 26277.58 | AA56: 11027.75 | AB56: 8915.9 | AC56: 10879.01 | AD56: 30822.66 | AE56: 9759.39 | AF56: 8078.67 | AG56: 16341.87 | AH56: 34179.93 | AI56: 6958.54 | AJ56: 7122.95 | AK56: 20299.19 | AL56: 34380.68 | AM56: 4464.53 | AN56: 4697.57 | AO56: 23929.87 | AP56: 33091.97 | AQ56: 5587.8 | AR56: 3767.4 | AS56: 25615.41 | AT56: 34970.61 | AU56: 7575.15 | AV56: 4178.91 | AW56: 26383.58 | AX56: 38137.64 | AZ56: 7246.96 | BA56: 2925.09 | BB56: 2173.57 | BC56: 12345.62 | BD56: 6937.27 | BE56: 3845.08 | BF56: 1758.27 | BG56: 12540.62 | BH56: 5863.12 | BI56: 5103.71 | BJ56: 2755.53 | BK56: 13722.36 | BL56: 5438.13 | BM56: 4801.32 | BN56: 5913.38 | BO56: 16152.83 | BP56: 4429.22 | BQ56: 4374.62 | BR56: 8838.14 | BS56: 17641.98 | BT56: 3005.67 | BU56: 3455 | BV56: 10278.03 | BW56: 16738.7 | BX56: 2050.58 | BY56: 2335.28 | BZ56: 12237.15 | CA56: 16623.01 | CB56: 2675.68 | CC56: 1872.67 | CD56: 12899.49 | CE56: 17447.84 | CF56: 3596.07 | CG56: 2081.77 | CH56: 13245.57 | CI56: 18923.41 | CL56: 1364.5685 | CM56: 1836.0014 | CN56: 2662.9739 | CO56: 4226.3142 | CP56: 5467.8719 | CQ56: 6712.8764 | CR56: 7543.5351 | CS56: 8623.5118 | CT56: 8856.1418 | DI56: 3 | DJ56: 2 | DK56: 1 | DL56: 1 | DS56: 2545.95 | DT56: 524.9 | DU56: 238.37 | DV56: 44.91 | ED56: 195.68
A57: 98953 | B57: RES | C57: =A57&B57 -> 98953RES | E57: 606 | F57: 657 | G57: 656 | H57: 623 | I57: 581 | J57: 570 | K57: 539 | L57: 554 | M57: 548 | O57: 105504 | P57: 17396.96 | Q57: 13605.77 | R57: 136506.73 | S57: 112600.84 | T57: 33318.24 | U57: 12224.44 | V57: 158143.52 | W57: 92153.55 | X57: 51119.11 | Y57: 24413.25 | Z57: 167685.91 | AA57: 79361.07 | AB57: 49414.18 | AC57: 45630.06 | AD57: 174405.31 | AE57: 57292.25 | AF57: 44765.82 | AG57: 62624.74 | AH57: 164682.81 | AI57: 45510.37 | AJ57: 34218.8 | AK57: 74078.09 | AL57: 153807.26 | AM57: 46252.72 | AN57: 25528.1 | AO57: 77807.07 | AP57: 149587.89 | AQ57: 60452.74 | AR57: 25169.51 | AS57: 75071.78 | AT57: 160694.03 | AU57: 64044.63 | AV57: 30216.9 | AW57: 79929.49 | AX57: 174191.02 | AZ57: 8229.28 | BA57: 1723.75 | BB57: 1659.37 | BC57: 11612.4 | BD57: 7982.17 | BE57: 3668.66 | BF57: 1686.3 | BG57: 13337.13 | BH57: 5812.75 | BI57: 3884.11 | BJ57: 2432.04 | BK57: 12128.9 | BL57: 5241.77 | BM57: 4387.66 | BN57: 4182.1 | BO57: 13811.53 | BP57: 3380.6 | BQ57: 2677.82 | BR57: 4698.19 | BS57: 10756.61 | BT57: 2409.42 | BU57: 2170.6 | BV57: 5238.1 | BW57: 9818.12 | BX57: 2595.91 | BY57: 1925.51 | BZ57: 6439.12 | CA57: 10960.54 | CB57: 3432.25 | CC57: 1970.83 | CD57: 5706.23 | CE57: 11109.31 | CF57: 3523.34 | CG57: 2457.38 | CH57: 6721.08 | CI57: 12701.8 | CL57: 6703.5608 | CM57: 9035.3281 | CN57: 14059.468 | CO57: 19912.851 | CP57: 22366.391 | CQ57: 25719.387 | CR57: 26268.981 | CS57: 27588.054 | CT57: 29042.824 | DG57: 5 | DH57: 7 | DI57: 4 | DJ57: 11 | DK57: 5 | DL57: 3 | DQ57: 2008.97 | DR57: 2463.56 | DS57: 837.9 | DT57: 3698.73 | DU57: 961.22 | DV57: 552.73 | EA57: 11.07 | EB57: 1173.1 | ED57: 246.23 | EE57: 692.95 | EF57: 170.06 | EG57: 168.22
A58: 99301 | B58: RES | C58: =A58&B58 -> 99301RES | E58: 1 | F58: 1 | G58: 1 | H58: 1 | I58: 1 | J58: 1 | K58: 1 | L58: 1 | M58: 1 | O58: 291.45 | P58: 0 | Q58: 0 | R58: 291.45 | S58: 262.79 | T58: 0 | U58: 0 | V58: 262.79 | W58: 215.32 | X58: 262.79 | Y58: 0 | Z58: 478.11 | AA58: 166.73 | AB58: 215.32 | AC58: 262.79 | AD58: 644.84 | AE58: 135.93 | AF58: 166.73 | AG58: 478.11 | AH58: 780.77 | AI58: 70.3 | AJ58: 135.93 | AK58: 244.84 | AL58: 451.07 | AM58: 80.01 | AN58: 70.3 | AO58: 380.77 | AP58: 531.08 | AQ58: 148.35 | AR58: 80.01 | AS58: 451.07 | AT58: 679.43 | AU58: 185.01 | AV58: 148.35 | AW58: 531.08 | AX58: 864.44 | CL58: 7.0065501 | CM58: 8.1510259 | CN58: 30.820545 | CO58: 98.488883 | CP58: 151.44814 | CQ58: 84.466237 | CR58: 119.9736 | CS58: 154.29962 | CT58: 183.53913
A59: 99323 | B59: RES | C59: =A59&B59 -> 99323RES | E59: 253 | F59: 249 | G59: 255 | H59: 239 | I59: 228 | J59: 206 | K59: 210 | L59: 222 | M59: 209 | O59: 49653.58 | P59: 6979.08 | Q59: 3880.96 | R59: 60513.62 | S59: 39998.18 | T59: 12839.76 | U59: 2416.31 | V59: 55254.25 | W59: 37063.18 | X59: 16801.55 | Y59: 4273.16 | Z59: 58137.89 | AA59: 31119.73 | AB59: 17987.5 | AC59: 9642.23 | AD59: 58749.46 | AE59: 22918.13 | AF59: 15282.3 | AG59: 16311.04 | AH59: 54511.47 | AI59: 15920.62 | AJ59: 11598.56 | AK59: 20553.73 | AL59: 48072.91 | AM59: 19360.84 | AN59: 7649.63 | AO59: 19447.51 | AP59: 46457.98 | AQ59: 28922.09 | AR59: 8751.41 | AS59: 21564.24 | AT59: 59237.74 | AU59: 25287.19 | AV59: 11378.59 | AW59: 20718.96 | AX59: 57384.74 | AZ59: 1368.64 | BA59: 619.25 | BB59: 389.2 | BC59: 2377.09 | BD59: 1488.12 | BE59: 1020.78 | BF59: 737.72 | BG59: 3246.62 | BH59: 1304.88 | BI59: 1349.06 | BJ59: 510.34 | BK59: 3164.28 | BL59: 800.27 | BM59: 767.15 | BN59: 944.52 | BO59: 2511.94 | BP59: 392.04 | BQ59: 556.08 | BR59: 1234.53 | BS59: 2182.65 | BT59: 457.24 | BU59: 302.17 | BV59: 1060.97 | BW59: 1820.38 | BX59: 312.35 | BY59: 389.45 | BZ59: 1196.14 | CA59: 1897.94 | CB59: 612.08 | CC59: 180.87 | CD59: 1483.46 | CE59: 2276.41 | CF59: 334.74 | CG59: 247.64 | CH59: 1564.33 | CI59: 2146.71 | CL59: 2489.0569 | CM59: 2816.7597 | CN59: 3856.9421 | CO59: 5348.2422 | CP59: 6275.0263 | CQ59: 7395.1349 | CR59: 6900.0155 | CS59: 8365.6869 | CT59: 7984.5509 | DH59: 2 | DJ59: 7 | DK59: 2 | DL59: 1 | DR59: 1427.21 | DT59: 4931.56 | DU59: 439.51 | DV59: 100 | ED59: 579.8 | EE59: 77.8 | EF59: 100
A60: 99324 | B60: RES | C60: =A60&B60 -> 99324RES | E60: 452 | F60: 503 | G60: 558 | H60: 521 | I60: 486 | J60: 479 | K60: 427 | L60: 422 | M60: 473 | O60: 48027.14 | P60: 7935.89 | Q60: 7100.46 | R60: 63063.49 | S60: 52953.2 | T60: 13230.16 | U60: 5203.26 | V60: 71386.62 | W60: 53872.52 | X60: 22026.15 | Y60: 7881.7 | Z60: 83780.37 | AA60: 44797.59 | AB60: 26170.74 | AC60: 16157.51 | AD60: 87125.84 | AE60: 38931.97 | AF60: 24030.75 | AG60: 24694.91 | AH60: 87657.63 | AI60: 25619.91 | AJ60: 23022.33 | AK60: 33515.41 | AL60: 82157.65 | AM60: 23743.53 | AN60: 14017.28 | AO60: 36847.7 | AP60: 74608.51 | AQ60: 26966.49 | AR60: 13129.44 | AS60: 36840.63 | AT60: 76936.56 | AU60: 38934.92 | AV60: 15205.91 | AW60: 39428 | AX60: 93568.83 | AZ60: 5906.33 | BA60: 1231.55 | BB60: 947.54 | BC60: 8085.42 | BD60: 4944.26 | BE60: 2164.36 | BF60: 325.26 | BG60: 7433.88 | BH60: 5398.86 | BI60: 2900.9 | BJ60: 1047.97 | BK60: 9347.73 | BL60: 3861.27 | BM60: 3111.16 | BN60: 2236.16 | BO60: 9208.59 | BP60: 3502.8 | BQ60: 2625.84 | BR60: 4226.18 | BS60: 10354.82 | BT60: 2823.32 | BU60: 2712.87 | BV60: 5796.97 | BW60: 11333.16 | BX60: 2344.39 | BY60: 1928.73 | BZ60: 6062.59 | CA60: 10335.71 | CB60: 2813.17 | CC60: 1809.76 | CD60: 7109.07 | CE60: 11732 | CF60: 3445.03 | CG60: 2359.11 | CH60: 8257.49 | CI60: 14061.63 | CL60: 3268.858 | CM60: 3928.5921 | CN60: 5828.6663 | CO60: 8369.2042 | CP60: 9675.5321 | CQ60: 12368.667 | CR60: 12641.303 | CS60: 13521.613 | CT60: 14523.391 | DG60: 14 | DH60: 8 | DI60: 16 | DJ60: 10 | DK60: 8 | DL60: 8 | DQ60: 1199.66 | DR60: 1804.86 | DS60: 4440.67 | DT60: 2483.58 | DU60: 989.21 | DV60: 858.89 | EA60: 467.19 | EB60: 20.51 | EC60: 182.07 | ED60: 804.93 | EE60: 281.67 | EF60: 439.01 | EG60: 152.96
A61: 99328 | B61: RES | C61: =A61&B61 -> 99328RES | E61: 351 | F61: 369 | G61: 401 | H61: 410 | I61: 395 | J61: 381 | K61: 343 | L61: 338 | M61: 347 | O61: 54273.04 | P61: 11262.17 | Q61: 7504.5 | R61: 73039.71 | S61: 60785.48 | T61: 14920.28 | U61: 8619.28 | V61: 84325.04 | W61: 61776.89 | X61: 27481.52 | Y61: 13107.08 | Z61: 102365.49 | AA61: 54798.1 | AB61: 32127.58 | AC61: 24616.02 | AD61: 111541.7 | AE61: 41953.53 | AF61: 32473.7 | AG61: 37361.73 | AH61: 111788.96 | AI61: 27886.25 | AJ61: 25826.45 | AK61: 48477.2 | AL61: 102189.9 | AM61: 25425.7 | AN61: 15962.48 | AO61: 54208.21 | AP61: 95596.39 | AQ61: 24504.7 | AR61: 14512 | AS61: 51754.49 | AT61: 90771.19 | AU61: 32908.2 | AV61: 14136.2 | AW61: 53816.71 | AX61: 100861.11 | AZ61: 5479.61 | BA61: 1893.46 | BB61: 885.35 | BC61: 8258.42 | BD61: 6104.95 | BE61: 2398.81 | BF61: 975.38 | BG61: 9479.14 | BH61: 5820.57 | BI61: 3868.95 | BJ61: 1762.32 | BK61: 11451.84 | BL61: 5450.51 | BM61: 3934.6 | BN61: 4733.63 | BO61: 14118.74 | BP61: 3919.94 | BQ61: 3872.48 | BR61: 7383.35 | BS61: 15175.77 | BT61: 2932.81 | BU61: 2732.02 | BV61: 8871.54 | BW61: 14536.37 | BX61: 2863.69 | BY61: 2195.85 | BZ61: 10126.2 | CA61: 15185.74 | CB61: 2967.38 | CC61: 2377.4 | CD61: 10233.67 | CE61: 15578.45 | CF61: 3507.91 | CG61: 2228.51 | CH61: 11082.11 | CI61: 16818.53 | CL61: 3691.413 | CM61: 5134.8873 | CN61: 7954.5642 | CO61: 11626.209 | CP61: 13918.493 | CQ61: 17043.319 | CR61: 17956.567 | CS61: 18319.855 | CT61: 18875.532 | DG61: 11 | DH61: 5 | DI61: 7 | DJ61: 8 | DK61: 5 | DL61: 1 | DQ61: 2555.89 | DR61: 2811.14 | DS61: 5010.7 | DT61: 3173.66 | DU61: 1861.88 | DV61: 130.73 | EA61: 204.99 | EB61: 411.4 | ED61: 40.21 | EF61: 130.73 | EG61: 18.45
A62: 99329 | B62: RES | C62: =A62&B62 -> 99329RES | E62: 15 | F62: 18 | G62: 19 | H62: 17 | I62: 21 | J62: 20 | K62: 16 | L62: 18 | M62: 17 | O62: 2318 | P62: 117.99 | Q62: 75.13 | R62: 2511.12 | S62: 3146.66 | T62: 459.53 | U62: 0 | V62: 3606.19 | W62: 2903.31 | X62: 736.02 | Y62: 0 | Z62: 3639.33 | AA62: 2163.68 | AB62: 925.27 | AC62: 231.33 | AD62: 3320.28 | AE62: 2496.5 | AF62: 1353.03 | AG62: 658.42 | AH62: 4507.95 | AI62: 1641.89 | AJ62: 1482.53 | AK62: 1494.13 | AL62: 4618.55 | AM62: 1577.37 | AN62: 989.2 | AO62: 1318.38 | AP62: 3884.95 | AQ62: 1443.36 | AR62: 423.87 | AS62: 1519.05 | AT62: 3386.28 | AU62: 1695.98 | AV62: 658.44 | AW62: 1452.12 | AX62: 3806.54 | CL62: 79.896478 | CM62: 132.90916 | CN62: 161.67352 | CO62: 220.18653 | CP62: 343.1311 | CQ62: 601.3595 | CR62: 511.16468 | CS62: 557.93978 | CT62: 548.05516 | DJ62: 1 | DL62: 1 | DT62: 808.32 | DV62: 254.13
A63: 99347 | B63: RES | C63: =A63&B63 -> 99347RES | E63: 122 | F63: 127 | G63: 187 | H63: 185 | I63: 190 | J63: 172 | K63: 155 | L63: 136 | M63: 129 | O63: 16321.16 | P63: 2312.63 | Q63: 2336.31 | R63: 20970.1 | S63: 19534.87 | T63: 5070.92 | U63: 2379.73 | V63: 26985.52 | W63: 29590.86 | X63: 8807.25 | Y63: 4270.82 | Z63: 42668.93 | AA63: 27417.9 | AB63: 16299.55 | AC63: 7823.13 | AD63: 51540.58 | AE63: 25463.38 | AF63: 16218.38 | AG63: 15295.84 | AH63: 56977.6 | AI63: 15002.01 | AJ63: 15248.75 | AK63: 21501.28 | AL63: 51752.04 | AM63: 10925.3 | AN63: 8995.31 | AO63: 26383.12 | AP63: 46303.73 | AQ63: 9540.54 | AR63: 6726.38 | AS63: 27941.69 | AT63: 44208.61 | AU63: 10740.58 | AV63: 6105.15 | AW63: 29429.41 | AX63: 46275.14 | AZ63: 1828.85 | BA63: 389.21 | BB63: 348.45 | BC63: 2566.51 | BD63: 2312.75 | BE63: 845.94 | BF63: 146.72 | BG63: 3305.41 | BH63: 3304.89 | BI63: 1821.3 | BJ63: 257.04 | BK63: 5383.23 | BL63: 2263.15 | BM63: 1843 | BN63: 974.31 | BO63: 5080.46 | BP63: 1727.85 | BQ63: 1151.99 | BR63: 1611.39 | BS63: 4491.23 | BT63: 1224.97 | BU63: 1137.49 | BV63: 2311.82 | BW63: 4674.28 | BX63: 784.47 | BY63: 746.77 | BZ63: 2376.84 | CA63: 3908.08 | CB63: 752.94 | CC63: 767.5 | CD63: 3053.55 | CE63: 4573.99 | CF63: 1033.19 | CG63: 723.74 | CH63: 3655.3 | CI63: 5412.23 | CL63: 1072.2415 | CM63: 1576.1929 | CN63: 2888.533 | CO63: 4558.2397 | CP63: 6113.151 | CQ63: 7930.7345 | CR63: 8786.9768 | CS63: 9702.5605 | CT63: 10034.427 | DG63: 3 | DH63: 6 | DI63: 3 | DJ63: 8 | DK63: 7 | DL63: 1 | DQ63: 674.16 | DR63: 2137.22 | DS63: 1069.02 | DT63: 3205.07 | DU63: 643.62 | DV63: 186.47 | EB63: 1516.36 | EC63: 728.46 | ED63: 291.91 | EE63: 144.9
A64: 99348 | B64: RES | C64: =A64&B64 -> 99348RES | E64: 41 | F64: 46 | G64: 51 | H64: 54 | I64: 50 | J64: 49 | K64: 44 | L64: 44 | M64: 42 | O64: 5916.59 | P64: 1154.67 | Q64: 1719.04 | R64: 8790.3 | S64: 7131.21 | T64: 1550.02 | U64: 1298.92 | V64: 9980.15 | W64: 9173.09 | X64: 2362.36 | Y64: 1300.35 | Z64: 12835.8 | AA64: 8374.65 | AB64: 4531.26 | AC64: 2736.74 | AD64: 15642.65 | AE64: 6810.97 | AF64: 5080.74 | AG64: 3694.05 | AH64: 15585.76 | AI64: 3942.34 | AJ64: 4031.57 | AK64: 5730.46 | AL64: 13704.37 | AM64: 3239.31 | AN64: 2519.16 | AO64: 6068.19 | AP64: 11826.66 | AQ64: 3540.21 | AR64: 1820.57 | AS64: 7163.12 | AT64: 12523.9 | AU64: 4180.45 | AV64: 1557.77 | AW64: 5536.07 | AX64: 11274.29 | AZ64: 752.36 | BA64: 340.09 | BB64: 517.96 | BC64: 1610.41 | BD64: 756.15 | BE64: 316.82 | BF64: 465.85 | BG64: 1538.82 | BH64: 1304.97 | BI64: 403.21 | BJ64: 423.67 | BK64: 2131.85 | BL64: 580.18 | BM64: 385.48 | BN64: 826.88 | BO64: 1792.54 | BP64: 343.6 | BQ64: 227.41 | BR64: 388.48 | BS64: 959.49 | BT64: 214.08 | BU64: 236.6 | BV64: 461.89 | BW64: 912.57 | BX64: 230.98 | BY64: 137.14 | BZ64: 541.3 | CA64: 909.42 | CB64: 338.62 | CC64: 141.88 | CD64: 572.3 | CE64: 1052.8 | CF64: 555.81 | CG64: 215.22 | CH64: 714.18 | CI64: 1485.21 | CL64: 613.54682 | CM64: 657.21988 | CN64: 855.96575 | CO64: 1454.0907 | CP64: 1566.5868 | CQ64: 2109.5302 | CR64: 2077.0473 | CS64: 2525.4719 | CT64: 1968.0131 | DG64: 1 | DI64: 2 | DJ64: 2 | DQ64: 314.45 | DS64: 1332.54 | DT64: 903.67 | EC64: 514.16
A65: 99350 | B65: RES | C65: =A65&B65 -> 99350RES | E65: 3 | F65: 6 | G65: 8 | H65: 6 | I65: 12 | J65: 6 | K65: 5 | L65: 4 | M65: 5 | O65: 0 | P65: 266.06 | Q65: 0 | R65: 266.06 | S65: 766.25 | T65: 0 | U65: 0 | V65: 766.25 | W65: 1397.15 | X65: 388.39 | Y65: 0 | Z65: 1785.54 | AA65: 790.76 | AB65: 636.98 | AC65: 154.03 | AD65: 1581.77 | AE65: 1882.92 | AF65: 626.18 | AG65: 791.01 | AH65: 3300.11 | AI65: 364.41 | AJ65: 277.98 | AK65: 1088.1 | AL65: 1730.49 | AM65: 219.44 | AN65: 0 | AO65: 1570.23 | AP65: 1789.67 | AQ65: 0 | AR65: 439.22 | AS65: 1020.5 | AT65: 1459.72 | AU65: 657.47 | AV65: 0 | AW65: 1037.53 | AX65: 1695 | BA65: 123.17 | BC65: 123.17 | BD65: 498.09 | BG65: 498.09 | BH65: 679.89 | BI65: 262.09 | BK65: 941.98 | BL65: 327.3 | BM65: 198.69 | BN65: 27.73 | BO65: 553.72 | BP65: 471.9 | BQ65: 327.3 | BR65: 226.42 | BS65: 1025.62 | BT65: 63.65 | BU65: 72.87 | BV65: 229.97 | BW65: 366.49 | BX65: 80.81 | BZ65: 366.49 | CA65: 447.3 | CC65: 32.4 | CE65: 32.4 | CF65: 85.99 | CH65: 32.4 | CI65: 118.39 | CL65: 14.076502 | CM65: 23.766976 | CN65: 80.894475 | CO65: 124.87785 | CP65: 319.18122 | CQ65: 351.50151 | CR65: 469.62893 | CS65: 359.26084 | CT65: 345.39127 | DH65: 1 | DL65: 1 | DR65: 71.39 | DV65: 297.22 | EB65: 71.39 | EF65: 297.22
A66: 99360 | B66: RES | C66: =A66&B66 -> 99360RES | E66: 93 | F66: 97 | G66: 64 | H66: 60 | I66: 90 | J66: 84 | K66: 79 | L66: 78 | M66: 92 | O66: 18000.75 | P66: 2870.59 | Q66: 368.29 | R66: 21239.63 | S66: 16851.49 | T66: 6570.56 | U66: 1138.86 | V66: 24560.91 | W66: 2059.72 | X66: 11075.55 | Y66: 1427.14 | Z66: 14562.41 | AA66: 7616.63 | AB66: 3683.2 | AC66: 2713.86 | AD66: 14013.69 | AE66: 9379.09 | AF66: 7015.81 | AG66: 6326.92 | AH66: 22721.82 | AI66: 7620.45 | AJ66: 5820.09 | AK66: 8101.92 | AL66: 21542.46 | AM66: 7765.03 | AN66: 4184.29 | AO66: 9818.84 | AP66: 21768.16 | AQ66: 10612.85 | AR66: 3855.41 | AS66: 10025.2 | AT66: 24493.46 | AU66: 11542.66 | AV66: 5559.89 | AW66: 8158.19 | AX66: 25260.74 | AZ66: 717.14 | BA66: 368.95 | BC66: 1086.09 | BD66: 738.2 | BE66: 450.51 | BF66: 25.78 | BG66: 1214.49 | BH66: 323.76 | BI66: 593.44 | BJ66: 223.29 | BK66: 1140.49 | BL66: 126.93 | BM66: 49.58 | BO66: 176.51 | BP66: 363.53 | BQ66: 94.79 | BR66: 123.84 | BS66: 582.16 | BT66: 275.29 | BU66: 219.3 | BW66: 494.59 | BX66: 162.19 | BY66: 72.24 | BZ66: 18.93 | CA66: 253.36 | CB66: 66.92 | CE66: 66.92 | CF66: 65 | CI66: 65 | CL66: 672.50489 | CM66: 1305.4198 | CN66: 1444.3064 | CO66: 1350.2649 | CP66: 2514.6998 | CQ66: 3051.0728 | CR66: 3446.2841 | CS66: 3793.2326 | CT66: 3257.4673 | DG66: 1 | DH66: 2 | DJ66: 2 | DQ66: 256.11 | DR66: 272.68 | DT66: 26.08 | EB66: 272.68 | ED66: 10.83
A67: 99361 | B67: RES | C67: =A67&B67 -> 99361RES | E67: 111 | F67: 111 | G67: 149 | H67: 148 | I67: 134 | J67: 132 | K67: 126 | L67: 110 | M67: 115 | O67: 21350.45 | P67: 3160.55 | Q67: 1625.1 | R67: 26136.1 | S67: 21337.07 | T67: 6630.56 | U67: 2170.89 | V67: 30138.52 | W67: 22916.77 | X67: 9394.96 | Y67: 4703.32 | Z67: 37015.05 | AA67: 20507.1 | AB67: 12022.6 | AC67: 7989.9 | AD67: 40519.6 | AE67: 17230.15 | AF67: 10926.96 | AG67: 11502.25 | AH67: 39659.36 | AI67: 11645.85 | AJ67: 11105.01 | AK67: 14395.54 | AL67: 37146.4 | AM67: 8691.19 | AN67: 6558.06 | AO67: 17827.81 | AP67: 33077.06 | AQ67: 7876.06 | AR67: 5150.31 | AS67: 18067.68 | AT67: 31094.05 | AU67: 10013.16 | AV67: 3836.57 | AW67: 18537.53 | AX67: 32387.26 | AZ67: 1416.17 | BA67: 476.62 | BB67: 654.93 | BC67: 2547.72 | BD67: 1656.08 | BE67: 445.5 | BF67: 845.88 | BG67: 2947.46 | BH67: 1474.37 | BI67: 744.79 | BJ67: 363.65 | BK67: 2582.81 | BL67: 1338.85 | BM67: 732.19 | BN67: 579.46 | BO67: 2650.5 | BP67: 915.4 | BQ67: 578.47 | BR67: 661.11 | BS67: 2154.98 | BT67: 510.33 | BU67: 594.51 | BV67: 968.74 | BW67: 2073.58 | BX67: 466.57 | BY67: 309.89 | BZ67: 1439.76 | CA67: 2216.22 | CB67: 367.6 | CC67: 280.63 | CD67: 1746.02 | CE67: 2394.25 | CF67: 669.65 | CG67: 330.06 | CH67: 2026.65 | CI67: 3026.36 | CL67: 1068.2901 | CM67: 1700.9722 | CN67: 2836.7453 | CO67: 4003.392 | CP67: 4464.6206 | CQ67: 5425.824 | CR67: 6013.6767 | CS67: 6382.8123 | CT67: 6397.8783 | DG67: 3 | DH67: 2 | DI67: 2 | DJ67: 3 | DK67: 3 | DL67: 2 | DQ67: 1346.53 | DR67: 470.26 | DS67: 637.35 | DT67: 3011.76 | DU67: 285.58 | DV67: 1127.55 | EA67: 156.99 | EC67: 26.97 | EE67: 232.78
A68: 99362 | B68: RES | C68: =A68&B68 -> 99362RES | E68: 1739 | F68: 1960 | G68: 2257 | H68: 2274 | I68: 2626 | J68: 2083 | K68: 1949 | L68: 1854 | M68: 2126 | O68: 147850.33 | P68: 57254.51 | Q68: 40270.71 | R68: 245375.55 | S68: 217596.32 | T68: 61515.33 | U68: 31236.48 | V68: 310348.13 | W68: 241235.07 | X68: 93533.24 | Y68: 44619.17 | Z68: 379387.48 | AA68: 219788.51 | AB68: 126179.33 | AC68: 89556 | AD68: 435523.84 | AE68: 257395.15 | AF68: 121973.22 | AG68: 138166.99 | AH68: 517535.36 | AI68: 134084.22 | AJ68: 119584.82 | AK68: 184405.85 | AL68: 438074.89 | AM68: 118141.81 | AN68: 58144.31 | AO68: 235780.79 | AP68: 412066.91 | AQ68: 93396.4 | AR68: 96775.2 | AS68: 228787.63 | AT68: 418959.23 | AU68: 177317.76 | AV68: 54190.39 | AW68: 261983.14 | AX68: 493491.29 | AZ68: 19264 | BA68: 11568.08 | BB68: 7488.53 | BC68: 38320.61 | BD68: 28994.93 | BE68: 13120.89 | BF68: 4158.74 | BG68: 46274.56 | BH68: 28184.22 | BI68: 15997.12 | BJ68: 9530.08 | BK68: 53711.42 | BL68: 22994.3 | BM68: 18941.58 | BN68: 17821.31 | BO68: 59757.19 | BP68: 27534.06 | BQ68: 16054.53 | BR68: 25181.3 | BS68: 68769.89 | BT68: 14026.26 | BU68: 14206.02 | BV68: 32750.37 | BW68: 60982.65 | BX68: 13188.15 | BY68: 5787.3 | BZ68: 42306.94 | CA68: 61282.39 | CB68: 6633.07 | CC68: 14807.15 | CD68: 39713.57 | CE68: 61153.79 | CF68: 17657.77 | CG68: 5385.63 | CH68: 47447.97 | CI68: 70491.37 | CL68: 16193.469 | CM68: 19097.423 | CN68: 28090.535 | CO68: 43801.591 | CP68: 54493.08 | CQ68: 67303.355 | CR68: 77488.201 | CS68: 83044.394 | CT68: 91274.663 | DG68: 52 | DH68: 54 | DI68: 43 | DJ68: 88 | DK68: 36 | DL68: 33 | DO68: 1 | DQ68: 12870.32 | DR68: 12088.88 | DS68: 10202.07 | DT68: 27325.88 | DU68: 8337.7 | DV68: 5974.77 | DY68: 182.85 | EA68: 1585.75 | EB68: 1985.92 | EC68: 1645.1 | ED68: 2086.43 | EE68: 485.1 | EF68: 1323.93 | EG68: 2433.6
A69: 99363 | B69: RES | C69: =A69&B69 -> 99363RES | E69: 20 | F69: 22 | H69: 18 | I69: 23 | J69: 24 | K69: 21 | L69: 22 | M69: 20 | O69: 3074.42 | P69: 269.01 | Q69: 191.4 | R69: 3534.83 | S69: 3465.67 | T69: 1139.47 | U69: 241.3 | V69: 4846.44 | W69: 240.1 | X69: 1747.14 | Y69: 117.18 | Z69: 2104.42 | AA69: 1955.49 | AB69: 640.4 | AC69: 270.4 | AD69: 2866.29 | AE69: 2197.56 | AF69: 2337.29 | AG69: 999.37 | AH69: 5534.22 | AI69: 1695.11 | AJ69: 1419.95 | AK69: 1289.77 | AL69: 4404.83 | AM69: 1605.12 | AN69: 791.54 | AO69: 1392.03 | AP69: 3788.69 | AQ69: 2351.09 | AR69: 602.93 | AS69: 1246.86 | AT69: 4200.88 | AU69: 1937.09 | AV69: 871.34 | AW69: 1418.66 | AX69: 4227.09 | AZ69: 46.42 | BA69: 41.87 | BC69: 88.29 | BD69: 36.99 | BE69: 46.42 | BF69: 41.87 | BG69: 125.28 | BL69: 36.38 | BO69: 36.38 | BP69: 121.1 | BQ69: 131.17 | BR69: 36.38 | BS69: 288.65 | BT69: 89.85 | BU69: 121.1 | BV69: 167.55 | BW69: 378.5 | BX69: 66.6 | BY69: 89.85 | BZ69: 288.65 | CA69: 445.1 | CB69: 48.06 | CC69: 37.6 | CD69: 234.98 | CE69: 320.64 | CF69: 45.47 | CG69: 48.06 | CH69: 272.58 | CI69: 366.11 | CL69: 133.81697 | CM69: 253.92415 | CN69: 196.68149 | CO69: 200.27854 | CP69: 492.98532 | CQ69: 538.05452 | CR69: 518.90835 | CS69: 510.18957 | CT69: 558.09456 | DL69: 1 | DV69: 28.34 | EF69: 28.34
A70: 98939 | B70: COM | C70: 98939COM | E70: 0 | F70: 3 | G70: 2 | H70: 2 | I70: 3 | J70: 3 | K70: 3 | L70: 3 | M70: 5 | O70: 0 | P70: 0 | Q70: 0 | R70: 0 | S70: 469.55 | T70: 0 | U70: 0 | V70: 469.55 | W70: 156.67 | X70: 0 | Y70: 0 | Z70: 156.67 | AA70: 134.39 | AB70: 0 | AC70: 0 | AD70: 134.39 | AE70: 208.18 | AF70: 21.71 | AG70: 0 | AH70: 229.89 | AI70: 335.62 | AJ70: 103.91 | AK70: 0 | AL70: 439.53 | AM70: 187.11 | AN70: 105.01 | AO70: 26.13 | AP70: 318.25 | AQ70: 229.02 | AR70: 100.74 | AS70: 131.14 | AT70: 460.9 | AU70: 360.6 | AV70: 201.17 | AW70: 17.99 | AX70: 579.76 | CL70: 0 | CM70: 14.564155 | CN70: 5.1322109 | CO70: 4.8502415 | CP70: 7.2484548 | CQ70: 17.794929 | CR70: 21.310617 | CS70: 55.982548 | CT70: 28.429185
C71: 99301COM | H71: 1 | I71: 1 | AA71: 116.35 | AB71: 0 | AC71: 0 | AD71: 116.35 | AE71: 107.54 | AF71: 0 | AG71: 0 | AH71: 230.89 | CL71: 0 | CM71: 0 | CN71: 0 | CO71: 4.1991636 | CP71: 3.0561449 | CT71: 0

Sheet 8. Past Due Balances 2020
F1: 5 | G1: 5 | H1: 5 | I1: 5 | J1: 5 | K1: 5 | L1: 5 | V1: 5 | AF1: 6 | AG1: 7 | AH1: 8 | AI1: 9 | BU1: 2 | BV1: 3 | BW1: 4 | BX1: 5 | BY1: 2 | BZ1: 3 | CA1: 4 | CB1: 5 | CC1: 2 | CD1: 3 | CE1: 4 | CF1: 5 | CG1: 2 | CH1: 3 | CI1: 4 | CJ1: 5 | CK1: 2 | CL1: 3 | CM1: 4 | CN1: 5 | CO1: 2 | CP1: 3 | CQ1: 4 | CR1: 5 | CS1: 2 | CT1: 3 | CU1: 4 | CV1: 5 | CW1: 2 | CX1: 3 | CY1: 4 | CZ1: 5 | DA1: 2 | DB1: 3 | DC1: 4 | DD1: 5 | DF1: 2 | DG1: 3 | DH1: 4 | DI1: 5 | DJ1: 2 | DK1: 3 | DL1: 4 | DM1: 5 | DN1: 2 | DO1: 3 | DP1: 4 | DQ1: 5 | DT1: ACCOUTING - ESTIMATE | EG1: BD WRITE OFF -- WOF | EU1: 14 | EV1: 15 | EW1: 16 | EX1: 17 | EY1: 18 | EZ1: 19 | FB1: 20 | FF1: 21 | FH1: 14 | FI1: 15 | FJ1: 16 | FK1: 17 | FL1: 18 | FM1: 19 | FO1: 20 | FS1: 21 | FU1: 2 | FV1: 3 | FW1: 4 | FX1: 5 | FY1: 6 | FZ1: 7 | GA1: 8
A2: General 2020 | E2: Item a) Number of Customers by Customer Class With Past-due balances (arrearages) | X2: Item b) Past-due Balances by Customer Class and Number of Days Past-due | BU2: Item c) Amount of Past-due Balances for Known Low-income Households and Number of Days Past-due | DT2: Item d) Amount of Past Due Balances Classified as Uncollectible | EG2: Item e) The Amount of Past-due Balances Written-off and Classified as Bad Debt, if different than item d | EU2: Item f) Number of Customer Accounts Referred to Collection Agencies | FH2: Item f) Total Amount of Bad Debt Referred for Collection | FU2: Item f) Total Revenue to the Company from the Collection Process
X3: 43831 | AB3: 43862 | AF3: 43891 | AJ3: 43922 | AN3: 43952 | AR3: 43983 | AV3: 44013 | AZ3: 44044 | BD3: 44075 | BH3: 44105 | BL3: 44136 | BP3: 44166 | BU3: 43831 | BY3: 43862 | CC3: 43891 | CG3: 43922 | CK3: 43952 | CO3: 43983 | CS3: 44013 | CW3: 44044 | DA3: 44075 | DF3: 44105 | DJ3: 44136 | DN3: 44166
A4: Zip Code | B4: Customer Class | C4: x | D4: x | E4: 43831 | F4: 43862 | G4: 43891 | H4: 43922 | I4: 43952 | J4: 43983 | K4: 44013 | L4: 44044 | M4: 44075 | P4: 44105 | S4: 44136 | V4: 44166 | W4: x | X4: 30 Days | Y4: 60 Days | Z4: 90 Days + | AA4: Total Arrearages | AB4: 30 Days | AC4: 60 Days | AD4: 90 Days + | AE4: Total Arrearages | AF4: 30 Days | AG4: 60 Days | AH4: 90 Days + | AI4: Total Arrearages | AJ4: 30 Days | AK4: 60 Days | AL4: 90 Days + | AM4: Total Arrearages | AN4: 30 Days | AO4: 60 Days | AP4: 90 Days + | AQ4: Total Arrearages | AR4: 30 Days | AS4: 60 Days | AT4: 90 Days + | AU4: Total Arrearages | AV4: 30 Days | AW4: 60 Days | AX4: 90 Days + | AY4: Total Arrearages | AZ4: 30 Days | BA4: 60 Days | BB4: 90 Days + | BC4: Total Arrearages | BD4: 30 Days | BE4: 60 Days | BF4: 90 Days + | BG4: Total Arrearages | BH4: 30 Days | BI4: 60 Days | BJ4: 90 Days + | BK4: Total Arrearages | BL4: 30 Days | BM4: 60 Days | BN4: 90 Days + | BO4: Total Arrearages | BP4: 30 Days | BQ4: 60 Days | BR4: 90 Days + | BS4: Total Arrearages | BU4: 30 Days | BV4: 60 Days | BW4: 90 Days + | BX4: Total Arrearages | BY4: 30 Days | BZ4: 60 Days | CA4: 90 Days + | CB4: Total Arrearages | CC4: 30 Days | CD4: 60 Days | CE4: 90 Days + | CF4: Total Arrearages | CG4: 30 Days | CH4: 60 Days | CI4: 90 Days + | CJ4: Total Arrearages | CK4: 30 Days | CL4: 60 Days | CM4: 90 Days + | CN4: Total Arrearages | CO4: 30 Days | CP4: 60 Days | CQ4: 90 Days + | CR4: Total Arrearages | CS4: 30 Days | CT4: 60 Days | CU4: 90 Days + | CV4: Total Arrearages | CW4: 30 Days | CX4: 60 Days | CY4: 90 Days + | CZ4: Total Arrearages | DA4: 30 Days | DB4: 60 Days | DC4: 90 Days + | DD4: Total Arrearages | DF4: 30 Days | DG4: 60 Days | DH4: 90 Days + | DI4: Total Arrearages | DJ4: 30 Days | DK4: 60 Days | DL4: 90 Days + | DM4: Total Arrearages | DN4: 30 Days | DO4: 60 Days | DP4: 90 Days + | DQ4: Total Arrearages | DT4: 43831 | DU4: 43862 | DV4: 43891 | DW4: 43922 | DX4: 43952 | DY4: 43983 | DZ4: 44013 | EA4: 44044 | EB4: 44075 | EC4: 44105 | ED4: 44136 | EE4: 44166 | EG4: CLASS | EH4: 43831 | EI4: 43862 | EJ4: 43891 | EK4: 43922 | EL4: 43952 | EM4: 43983 | EN4: 44013 | EO4: 44044 | EP4: 44075 | EQ4: 44105 | ER4: 44136 | ES4: 44166 | EU4: 43831 | EV4: 43862 | EW4: 43891 | EX4: 43922 | EY4: 43952 | EZ4: 43983 | FA4: 44013 | FB4: 44044 | FC4: 44075 | FD4: 44105 | FE4: 44136 | FF4: 44166 | FH4: 43831 | FI4: 43862 | FJ4: 43891 | FK4: 43922 | FL4: 43952 | FM4: 43983 | FN4: 44013 | FO4: 44044 | FP4: 44075 | FQ4: 44105 | FR4: 44136 | FS4: 44166 | FU4: 43831 | FV4: 43862 | FW4: 43891 | FX4: 43922 | FY4: 43952 | FZ4: 43983 | GA4: 44013 | GB4: 44044 | GC4: 44075 | GD4: 44105 | GE4: 44136 | GF4: 44166
A5: 98901 | B5: COM | C5: =A5&B5 -> 98901COM | E5: 131 | F5: 132 | G5: 145 | H5: 173 | I5: 221 | J5: 160 | K5: 137 | L5: 152 | M5: 156 | N5: 98901 | O5: COM | P5: 171 | X5: 19871.38 | Y5: 7897.63 | Z5: 24242.65 | AA5: 52011.66 | AB5: 53580.83 | AC5: 9976.46 | AD5: 27438.96 | AE5: 90996.25 | AF5: 48277.95 | AG5: 17941.85 | AH5: 22854.02 | AI5: 89073.82 | AJ5: 71009.6 | AK5: 29051.57 | AL5: 36760.09 | AM5: 136821.26 | AN5: 86883.42 | AO5: 34985.09 | AP5: 49645.24 | AQ5: 171513.75 | AR5: 39740.66 | AS5: 29311.53 | AT5: 66630.47 | AU5: 135682.66 | AV5: 38006.67 | AW5: 14078.08 | AX5: 65366.26 | AY5: 117451.01 | AZ5: 29853.1 | BA5: 15834.18 | BB5: 62985.51 | BC5: 108672.79 | BD5: 41939.18 | BE5: 15055.03 | BF5: 60553.4 | BG5: 117547.61 | BH5: 46328.75 | BI5: 19103.27 | BJ5: 63397.82 | BK5: 128829.84 | BU5: 42.71 | BV5: 41.08 | BW5: 0 | BX5: 83.79 | BY5: 48.96 | BZ5: 42.71 | CA5: 41.08 | CB5: 132.75 | CC5: =IFERROR(VLOOKUP($C5,Sheet10!$C$3:$G$65,CC$1,FALSE),"") | CD5: =IFERROR(VLOOKUP($C5,Sheet10!$C$3:$G$65,CD$1,FALSE),"") | CE5: =IFERROR(VLOOKUP($C5,Sheet10!$C$3:$G$65,CE$1,FALSE),"") | CF5: =IFERROR(VLOOKUP($C5,Sheet10!$C$3:$G$65,CF$1,FALSE),"") | CG5: =IFERROR(VLOOKUP($C5,Sheet10!$C$3:$G$65,CG$1,FALSE),"") | CH5: =IFERROR(VLOOKUP($C5,Sheet10!$C$3:$G$65,CH$1,FALSE),"") | CI5: =IFERROR(VLOOKUP($C5,Sheet10!$C$3:$G$65,CI$1,FALSE),"") | CJ5: =IFERROR(VLOOKUP($C5,Sheet10!$C$3:$G$65,CJ$1,FALSE),"") | ... DD5: =IFERROR(VLOOKUP($C5,Sheet10!$C$3:$G$65,DD$1,FALSE),"") | DE5: 98901COM | DF5: 17.56 | DG5: 33.34 | DH5: 236.83 | DI5: 287.73 | DR5: =VLOOKUP($C5,Sheet10!$C$3:$G$65,DR$1,FALSE) -> #N/A | DT5: 6680.653 | DU5: 9123.4953 | DV5: 9211.7238 | DW5: 15409.934 | DX5: 18878.318 | DY5: 22984.908 | DZ5: 21490.276 | EA5: 22157.377 | EB5: 21296.568 | EG5: RES | EH5: 155378.03 | EI5: 91404.44 | EJ5: 77084.33 | EK5: 161847.29 | EL5: 69802.26 | EM5: 66491.04 | EN5: 72376.07 | EO5: 109624.03 | EP5: 76241.97 | EU5: 2 | EV5: 2 | EW5: 3 | EX5: 3 | EY5: 1 | FH5: 3400.92 | FI5: 1528.25 | FJ5: 1009.25 | FK5: 25469.44 | FL5: 361.46 | FW5: 215.93 | FY5: 361.46
